Workbook

Sheet ルール
B3: 1 | C3: 文字は「游ゴシック」、数字は「Arial」を基本。備考欄などの細かい文章は「游ゴシック Medium」。
B4: 2 | C4: タイトル、合計欄は太字
B5: 3 | C5: 数字は円単位で入力、表示は千円単位に設定済み
B6: 4 | C6: 基本の背景は以下の通り。紺、水色、グレー、白、青。パレットの上部の色。
C8: 線は紺か白か青。
C10: 資産の部
C11: 科目 | D11: ='BS(借方)'!F10 -> 0 | E11: 調整額 | F11: 調整後
C12: 【流動資産】 | D12: =SUM(D13:D26) -> 5000000 | E12: =SUM(E13:E26) -> -500000 | F12: =SUM(F13:F26) -> 4500000
C13: 現金及び預金 | D13: 5000000 | E13: -500000 | F13: =D13+E13 -> 4500000
F14: =D14+E14 -> 0

Sheet 財務入力→

Sheet BS(借方)
C2: 1期目 | D2: 2期目 | E2: 3期目 | F2: （4期目） | G2: 進行期
B3: 資産の部
B4: 科目 | C4: 令和6年3月期 | D4: 令和7年3月期 | E4: 令和8年3月期 | F4: － | G4: 進行期 （試算表未受領）
B5: 【流動資産】 | C5: =SUM(C6:C19) -> 243651732 | D5: =SUM(D6:D19) -> 899318583 | E5: =SUM(E6:E19) -> 293198020 | F5: =SUM(F6:F19) -> 0 | G5: =SUM(G6:G19) -> 0
B6: 現金及び預金 | C6: 154741516 | D6: 31966530 | E6: 226057309
B7: 受取手形
B8: 売掛金 | C8: 2064629 | D8: 841410642 | E8: 28512083
B9: 原材料
B10: 仕掛品
B11: 貯蔵品
B12: 前渡金 | C12: 0 | D12: 0 | E12: 18507883
B13: 未収入金 | C13: 77752587 | D13: 16432051 | E13: 0
B14: 貸倒引当金
B15: 商品 | C15: 8732000 | D15: 8732000 | E15: 8532000
B16: 前払費用 | C16: 361000 | D16: 386500 | E16: 710345
B17: 立替金 | C17: 0 | D17: 390860 | E17: 0
B18: 未収還付法人税等 | C18: 0 | D18: 0 | E18: 10878400
B20: 【固定資産】 | C20: =C21+C35+C46 -> 1096640549 | D20: =D21+D35+D46 -> 509171536 | E20: =E21+E35+E46 -> 503310970 | F20: =F21+F35+F46 -> 0 | G20: =G21+G35+G46 -> 0
B21: ［有形固定資産］ | C21: =SUM(C22:C34) -> 1074867927 | D21: =SUM(D22:D34) -> 496979036 | E21: =SUM(E22:E34) -> 490145870 | F21: =SUM(F22:F34) -> 0 | G21: =SUM(G22:G34) -> 0
B22: 建物 | C22: 160070644 | D22: 125537878 | E22: 118721091
B23: 建物付属設備 | C23: 64040157 | D23: 22588959 | E23: 20091490
B24: 構築物 | C24: 2425672 | D24: 0 | E24: 0
B25: 機械装置 | C25: 1 | D25: 0 | E25: 0
B26: 車輛運搬具 | C26: 2205038 | D26: 2756526 | E26: 5394909
B27: 工具器具備品 | C27: 1222069 | D27: 766047 | E27: 908754
B28: 一括償却資産
B29: 土地 | C29: 807629626 | D29: 341829626 | E29: 345029626
B30: 建設仮戡定 | C30: 37274720 | D30: 3500000 | E30: 0
B35: ［無形固定資産］ | C35: =SUM(C36:C45) -> 78231 | D35: =SUM(D36:D45) -> 0 | E35: =SUM(E36:E45) -> 0 | F35: =SUM(F36:F45) -> 0 | G35: =SUM(G36:G45) -> 0
B36: ソフトウェア
B37: 電話加入権
B38: 施設利用権 | C38: 78231 | D38: 0 | E38: 0
B46: ［投資その他資産］ | C46: =SUM(C47:C55) -> 21694391 | D46: =SUM(D47:D55) -> 12192500 | E46: =SUM(E47:E55) -> 13165100 | F46: =SUM(F47:F55) -> 0 | G46: =SUM(G47:G55) -> 0
B47: 出資金 | C47: 5000 | D47: 5000 | E47: 5000
B48: リサイクル預託金
B49: 保険積立金
B50: 投資有価証券
B51: 敷金 | C51: 15707391 | D51: 12187500 | E51: 13160100
B52: 差入保証金 | C52: 5982000 | D52: 0 | E52: 0
B56: 【繰延資産】 | C56: =SUM(C57:C60) -> 0 | D56: =SUM(D57:D60) -> 0 | E56: =SUM(E57:E60) -> 0 | F56: =SUM(F57:F60) -> 0 | G56: =SUM(G57:G60) -> 0
B57: 開業費
B61: 資産合計 | C61: =C5+C20+C56 -> 1340292281 | D61: =D5+D20+D56 -> 1408490119 | E61: =E5+E20+E56 -> 796508990 | F61: =F5+F20+F56 -> 0 | G61: =G5+G20+G56 -> 0
B63: バランスチェック | C63: =EXACT(C61,'BS (貸方)'!C51) -> 1 | D63: =EXACT(D61,'BS (貸方)'!D51) -> 1 | E63: =EXACT(E61,'BS (貸方)'!E51) -> 1 | F63: =EXACT(F61,'BS (貸方)'!F51) -> 1 | G63: =EXACT(G61,'BS (貸方)'!G51) -> 1

Sheet BS (貸方)
E2: (単位：千円)
B3: 負債の部
B4: 科目 | C4: ='BS(借方)'!C4 -> 令和6年3月期 | D4: ='BS(借方)'!D4 -> 令和7年3月期 | E4: ='BS(借方)'!E4 -> 令和8年3月期 | F4: ='BS(借方)'!F4 -> － | G4: ='BS(借方)'!G4 -> 進行期 （試算表未受領）
B5: 【流動負債】 | C5: =SUM(C6:C17) -> 546936524 | D5: =SUM(D6:D17) -> 549868324 | E5: =SUM(E6:E17) -> 196854699 | F5: =SUM(F6:F17) -> 0 | G5: =SUM(G6:G17) -> 0
B6: 買掛金 | C6: 10530062 | D6: 106089259 | E6: 10296760
B7: 未払金 | C7: 6830374 | D7: 11297305 | E7: 7639437
B8: 未払費用
B9: 未払消費税 | C9: 4995000 | D9: 3049800 | E9: 4950000
B10: 預り金 | C10: 990436 | D10: 831047 | E10: 794225
B11: 未払法人税等 | C11: 194500 | D11: 21952200 | E11: 97300
B12: 短期借入金 | C12: 523396152 | D12: 406648713 | E12: 173076977
B18: 【固定負債】 | C18: =SUM(C19:C24) -> 526719849 | D18: =SUM(D19:D24) -> 483629529 | E18: =SUM(E19:E24) -> 272745529 | F18: =SUM(F19:F24) -> 0 | G18: =SUM(G19:G24) -> 0
B19: 長期借入金 | C19: 526321529 | D19: 483629529 | E19: 272745529
B20: 長期預り保証金 | C20: 398320 | D20: 0 | E20: 0
B25: 負債合計 | C25: =C5+C18 -> 1073656373 | D25: =D5+D18 -> 1033497853 | E25: =E5+E18 -> 469600228 | F25: =F5+F18 -> 0 | G25: =G5+G18 -> 0
B34: 純資産の部
B35: 【資本金】 | C35: =SUM(C36:C38) -> 500000 | D35: =SUM(D36:D38) -> 500000 | E35: =SUM(E36:E38) -> 500000 | F35: =SUM(F36:F38) -> 0 | G35: =SUM(G36:G38) -> 0
B36: 資本金 | C36: 500000 | D36: 500000 | E36: 500000
B39: 【資本剰余金】 | C39: =SUM(C40:C42) -> 5000000 | D39: =SUM(D40:D42) -> 5000000 | E39: =SUM(E40:E42) -> 5000000 | F39: =SUM(F40:F42) -> 0 | G39: =SUM(G40:G42) -> 0
B40: その他資本剰余金 | C40: 5000000 | D40: 5000000 | E40: 5000000
B43: 【利益剰余金】 | C43: =SUM(C44:C48) -> 261135908 | D43: =SUM(D44:D48) -> 369492266 | E43: =SUM(E44:E48) -> 321408762 | F43: =SUM(F44:F48) -> 0 | G43: =SUM(G44:G48) -> 0
B44: 利益準備金
B45: 別途積立金
B46: 繰越利益剰余金 | C46: 261135908 | D46: 369492266 | E46: 321408762
B49: 【自己株式】 | C49: 0 | D49: 0 | E49: 0 | F49: 0 | G49: 0
B50: 純資産合計 | C50: =C35+C39+C43+C49 -> 266635908 | D50: =D35+D39+D43+D49 -> 374992266 | E50: =E35+E39+E43+E49 -> 326908762 | F50: =F35+F39+F43+F49 -> 0 | G50: =G35+G39+G43+G49 -> 0
B51: 負債・純資産合計 | C51: =C25+C50 -> 1340292281 | D51: =D25+D50 -> 1408490119 | E51: =E25+E50 -> 796508990 | F51: =F25+F50 -> 0 | G51: =G25+G50 -> 0
B53: バランスチェック | C53: =EXACT(C51,'BS(借方)'!C61) -> 1 | D53: =EXACT(D51,'BS(借方)'!D61) -> 1 | E53: =EXACT(E51,'BS(借方)'!E61) -> 1 | F53: =EXACT(F51,'BS(借方)'!F61) -> 1 | G53: =EXACT(G51,'BS(借方)'!G61) -> 1

Sheet PL
H2: (単位：千円)
B3: 科目 | C3: ='BS(借方)'!C4 -> 令和6年3月期 | E3: ='BS(借方)'!D4 -> 令和7年3月期 | G3: ='BS(借方)'!E4 -> 令和8年3月期 | I3: ='BS(借方)'!F4 -> － | K3: ='BS(借方)'!G4 -> 進行期 （試算表未受領）
C4: 帳簿価額 | D4: 売上高比 | E4: 帳簿価額 | F4: 売上高比 | G4: 帳簿価額 | H4: 売上高比 | I4: 帳簿価額 | J4: 売上高比 | K4: 帳簿価額 | L4: 売上高比
B5: 店舗・EC等売上高 | C5: 366805605 | D5: =IF(C5=0,"",C5/C$11) -> 0.95661987 | E5: 344797561 | F5: =IF(E5=0,"",E5/E$11) -> 0.28013419 | G5: 303702978 | H5: =IF(G5=0,"",G5/G$11) -> 0.95103815 | J5: =IF(I5=0,"",I5/I$11) | L5: =IF(K5=0,"",K5/K$11)
B6: 不動産賃貸収入 | C6: 16633646 | D6: =IF(C6=0,"",C6/C$11) -> 0.043380134 | E6: 16832410 | F6: =IF(E6=0,"",E6/E$11) -> 0.013675658 | G6: 1635396 | H6: =IF(G6=0,"",G6/G$11) -> 0.005121201 | J6: =IF(I6=0,"",I6/I$11) | L6: =IF(K6=0,"",K6/K$11)
B7: 不動産売却収入 | C7: 0 | D7: =IF(C7=0,"",C7/C$11) | E7: 869200000 | F7: =IF(E7=0,"",E7/E$11) -> 0.70619015 | G7: 0 | H7: =IF(G7=0,"",G7/G$11) | J7: =IF(I7=0,"",I7/I$11) | L7: =IF(K7=0,"",K7/K$11)
B8: コンサル収入 | C8: 0 | D8: =IF(C8=0,"",C8/C$11) | E8: 0 | F8: =IF(E8=0,"",E8/E$11) | G8: 14000000 | H8: =IF(G8=0,"",G8/G$11) -> 0.043840644 | J8: =IF(I8=0,"",I8/I$11) | L8: =IF(K8=0,"",K8/K$11)
D9: =IF(C9=0,"",C9/C$11) | F9: =IF(E9=0,"",E9/E$11) | H9: =IF(G9=0,"",G9/G$11) | J9: =IF(I9=0,"",I9/I$11) | L9: =IF(K9=0,"",K9/K$11)
D10: =IF(C10=0,"",C10/C$11) | F10: =IF(E10=0,"",E10/E$11) | H10: =IF(G10=0,"",G10/G$11) | J10: =IF(I10=0,"",I10/I$11) | L10: =IF(K10=0,"",K10/K$11)
B11: 売上高 | C11: =SUM(C5:C10) -> 383439251 | D11: =IF(C11=0,"",C11/C$11) -> 1 | E11: =SUM(E5:E10) -> 1230829971 | F11: =IF(E11=0,"",E11/E$11) -> 1 | G11: =SUM(G5:G10) -> 319338374 | H11: =IF(G11=0,"",G11/G$11) -> 1 | I11: =SUM(I5:I10) -> 0 | J11: =IF(I11=0,"",I11/I$11) | K11: =SUM(K5:K10) -> 0 | L11: =IF(K11=0,"",K11/K$11)
B12: 期首商品棚卸高 | C12: 7732842 | D12: =IF(C12=0,"",C12/C$11) -> 0.020167059 | E12: 8732000 | F12: =IF(E12=0,"",E12/E$11) -> 0.0070943999 | G12: 8732000 | H12: =IF(G12=0,"",G12/G$11) -> 0.027344036 | J12: =IF(I12=0,"",I12/I$11) | L12: =IF(K12=0,"",K12/K$11)
B13: 当期商品仕入高 | C13: 105841625 | D13: =IF(C13=0,"",C13/C$11) -> 0.27603232 | E13: 100866136 | F13: =IF(E13=0,"",E13/E$11) -> 0.081949691 | G13: 96006124 | H13: =IF(G13=0,"",G13/G$11) -> 0.30064074 | J13: =IF(I13=0,"",I13/I$11) | L13: =IF(K13=0,"",K13/K$11)
B14: 不動産売却関連原価 | C14: 0 | D14: =IF(C14=0,"",C14/C$11) | E14: 636056000 | F14: =IF(E14=0,"",E14/E$11) -> 0.51677 | G14: 0 | H14: =IF(G14=0,"",G14/G$11) | J14: =IF(I14=0,"",I14/I$11) | L14: =IF(K14=0,"",K14/K$11)
B15: 期末商品棚卸高 | C15: -8732000 | D15: =IF(C15=0,"",C15/C$11) -> -0.022772838 | E15: -8732000 | F15: =IF(E15=0,"",E15/E$11) -> -0.0070943999 | G15: -8532000 | H15: =IF(G15=0,"",G15/G$11) -> -0.026717741 | J15: =IF(I15=0,"",I15/I$11) | L15: =IF(K15=0,"",K15/K$11)
B16: 売上原価 | C16: =SUM(C12:C15) -> 104842467 | D16: =IF(C16=0,"",C16/C$11) -> 0.27342654 | E16: =SUM(E12:E15) -> 736922136 | F16: =IF(E16=0,"",E16/E$11) -> 0.59871969 | G16: =SUM(G12:G15) -> 96206124 | H16: =IF(G16=0,"",G16/G$11) -> 0.30126703 | I16: =SUM(I12:I15) -> 0 | J16: =IF(I16=0,"",I16/I$11) | K16: =SUM(K12:K15) -> 0 | L16: =IF(K16=0,"",K16/K$11)
B17: 売上総利益 | C17: =C11-C16 -> 278596784 | D17: =IF(C17=0,"",C17/C$11) -> 0.72657346 | E17: =E11-E16 -> 493907835 | F17: =IF(E17=0,"",E17/E$11) -> 0.40128031 | G17: =G11-G16 -> 223132250 | H17: =IF(G17=0,"",G17/G$11) -> 0.69873297 | I17: =I11-I16 -> 0 | J17: =IF(I17=0,"",I17/I$11) | K17: =K11-K16 -> 0 | L17: =IF(K17=0,"",K17/K$11)
B18: 販売費及び一般管理費 | C18: =SGA!C40 -> 283551728 | D18: =IF(C18=0,"",C18/C$11) -> 0.73949583 | E18: =SGA!E40 -> 273060341 | F18: =IF(E18=0,"",E18/E$11) -> 0.22185058 | G18: =SGA!G40 -> 222261444 | H18: =IF(G18=0,"",G18/G$11) -> 0.69600606 | I18: =SGA!I40 -> 0 | J18: =IF(I18=0,"",I18/I$11) | K18: =SGA!K40 -> 0 | L18: =IF(K18=0,"",K18/K$11)
B19: 営業利益 | C19: =C17- C18 -> -4954944 | D19: =IF(C19=0,"",C19/C$11) -> -0.01292237 | E19: =E17- E18 -> 220847494 | F19: =IF(E19=0,"",E19/E$11) -> 0.17942973 | G19: =G17- G18 -> 870806 | H19: =IF(G19=0,"",G19/G$11) -> 0.0027269069 | I19: =I17- I18 -> 0 | J19: =IF(I19=0,"",I19/I$11) | K19: =K17- K18 -> 0 | L19: =IF(K19=0,"",K19/K$11)
B20: 営業外収益 | C20: =SUM(C21:C27) -> 416337 | D20: =IF(C20=0,"",C20/C$11) -> 0.0010857965 | E20: =SUM(E21:E27) -> 2887886 | F20: =IF(E20=0,"",E20/E$11) -> 0.0023462916 | G20: =SUM(G21:G27) -> 2924950 | H20: =IF(G20=0,"",G20/G$11) -> 0.0091594066 | I20: =SUM(I21:I27) -> 0 | J20: =IF(I20=0,"",I20/I$11) | K20: =SUM(K21:K27) -> 0 | L20: =IF(K20=0,"",K20/K$11)
B21: 受取利息 | C21: 1507 | D21: =IF(C21=0,"",C21/C$11) -> 3.9302184e-06 | E21: 7617 | F21: =IF(E21=0,"",E21/E$11) -> 6.1885071e-06 | G21: 618278 | H21: =IF(G21=0,"",G21/G$11) -> 0.0019361218 | J21: =IF(I21=0,"",I21/I$11) | L21: =IF(K21=0,"",K21/K$11)
B22: 雑収入 | C22: 414830 | D22: =IF(C22=0,"",C22/C$11) -> 0.0010818663 | E22: 2880269 | F22: =IF(E22=0,"",E22/E$11) -> 0.0023401031 | G22: 2306672 | H22: =IF(G22=0,"",G22/G$11) -> 0.0072232847 | J22: =IF(I22=0,"",I22/I$11) | L22: =IF(K22=0,"",K22/K$11)
D25: =IF(C25=0,"",C25/C$11) | F25: =IF(E25=0,"",E25/E$11) | H25: =IF(G25=0,"",G25/G$11) | J25: =IF(I25=0,"",I25/I$11) | L25: =IF(K25=0,"",K25/K$11)
D26: =IF(C26=0,"",C26/C$11) | F26: =IF(E26=0,"",E26/E$11) | H26: =IF(G26=0,"",G26/G$11) | J26: =IF(I26=0,"",I26/I$11) | L26: =IF(K26=0,"",K26/K$11)
D27: =IF(C27=0,"",C27/C$11) | F27: =IF(E27=0,"",E27/E$11) | H27: =IF(G27=0,"",G27/G$11) | J27: =IF(I27=0,"",I27/I$11) | L27: =IF(K27=0,"",K27/K$11)
B28: 営業外費用 | C28: =SUM(C29:C35) -> 2751745 | D28: =IF(C28=0,"",C28/C$11) -> 0.0071764823 | E28: =SUM(E29:E35) -> 12167614 | F28: =IF(E28=0,"",E28/E$11) -> 0.0098856985 | G28: =SUM(G29:G35) -> 3215177 | H28: =IF(G28=0,"",G28/G$11) -> 0.010068245 | I28: =SUM(I29:I35) -> 0 | J28: =IF(I28=0,"",I28/I$11) | K28: =SUM(K29:K35) -> 0 | L28: =IF(K28=0,"",K28/K$11)
B29: 支払利息 | C29: 2647993 | D29: =IF(C29=0,"",C29/C$11) -> 0.0069058997 | E29: 3319038 | F29: =IF(E29=0,"",E29/E$11) -> 0.0026965853 | G29: 3189615 | H29: =IF(G29=0,"",G29/G$11) -> 0.0099881983 | J29: =IF(I29=0,"",I29/I$11) | L29: =IF(K29=0,"",K29/K$11)
B30: 雑損失 | C30: 103752 | E30: 8848576 | G30: 25562
D32: =IF(C32=0,"",C32/C$11) | F32: =IF(E32=0,"",E32/E$11) | H32: =IF(G32=0,"",G32/G$11) | J32: =IF(I32=0,"",I32/I$11) | L32: =IF(K32=0,"",K32/K$11)
D33: =IF(C33=0,"",C33/C$11) | F33: =IF(E33=0,"",E33/E$11) | H33: =IF(G33=0,"",G33/G$11) | J33: =IF(I33=0,"",I33/I$11) | L33: =IF(K33=0,"",K33/K$11)
D34: =IF(C34=0,"",C34/C$11) | F34: =IF(E34=0,"",E34/E$11) | H34: =IF(G34=0,"",G34/G$11) | J34: =IF(I34=0,"",I34/I$11) | L34: =IF(K34=0,"",K34/K$11)
D35: =IF(C35=0,"",C35/C$11) | F35: =IF(E35=0,"",E35/E$11) | H35: =IF(G35=0,"",G35/G$11) | J35: =IF(I35=0,"",I35/I$11) | L35: =IF(K35=0,"",K35/K$11)
B36: 経常利益 | C36: =C19+C20-C28 -> -7290352 | D36: =IF(C36=0,"",C36/C$11) -> -0.019013056 | E36: =E19+E20-E28 -> 211567766 | F36: =IF(E36=0,"",E36/E$11) -> 0.17189033 | G36: =G19+G20-G28 -> 580579 | H36: =IF(G36=0,"",G36/G$11) -> 0.0018180684 | I36: =I19+I20-I28 -> 0 | J36: =IF(I36=0,"",I36/I$11) | K36: =K19+K20-K28 -> 0 | L36: =IF(K36=0,"",K36/K$11)
B37: 特別利益 | C37: =SUM(C38:C43) -> 0 | D37: =IF(C37=0,"",C37/C$11) | E37: =SUM(E38:E43) -> 0 | F37: =IF(E37=0,"",E37/E$11) | G37: =SUM(G38:G43) -> 0 | H37: =IF(G37=0,"",G37/G$11) | I37: =SUM(I38:I43) -> 0 | J37: =IF(I37=0,"",I37/I$11) | K37: =SUM(K38:K43) -> 0 | L37: =IF(K37=0,"",K37/K$11)
B38: 貸倒引当金戻入額 | D38: =IF(C38=0,"",C38/C$11) | F38: =IF(E38=0,"",E38/E$11) | H38: =IF(G38=0,"",G38/G$11) | J38: =IF(I38=0,"",I38/I$11) | L38: =IF(K38=0,"",K38/K$11)
B39: 補助金収入 | D39: =IF(C39=0,"",C39/C$11) | F39: =IF(E39=0,"",E39/E$11) | H39: =IF(G39=0,"",G39/G$11) | J39: =IF(I39=0,"",I39/I$11) | L39: =IF(K39=0,"",K39/K$11)
D42: =IF(C42=0,"",C42/C$11) | F42: =IF(E42=0,"",E42/E$11) | H42: =IF(G42=0,"",G42/G$11) | J42: =IF(I42=0,"",I42/I$11) | L42: =IF(K42=0,"",K42/K$11)
D43: =IF(C43=0,"",C43/C$11) | F43: =IF(E43=0,"",E43/E$11) | H43: =IF(G43=0,"",G43/G$11) | J43: =IF(I43=0,"",I43/I$11) | L43: =IF(K43=0,"",K43/K$11)
B44: 特別損失 | C44: =SUM(C45:C50) -> 0 | D44: =IF(C44=0,"",C44/C$11) | E44: =SUM(E45:E50) -> 81258050 | F44: =IF(E44=0,"",E44/E$11) -> 0.066018907 | G44: =SUM(G45:G50) -> 0 | H44: =IF(G44=0,"",G44/G$11) | I44: =SUM(I45:I50) -> 0 | J44: =IF(I44=0,"",I44/I$11) | K44: =SUM(K45:K50) -> 0 | L44: =IF(K44=0,"",K44/K$11)
B45: 固定資産除却損 | C45: 0 | D45: =IF(C45=0,"",C45/C$11) | E45: 81258050 | F45: =IF(E45=0,"",E45/E$11) -> 0.066018907 | G45: 0 | H45: =IF(G45=0,"",G45/G$11) | J45: =IF(I45=0,"",I45/I$11) | L45: =IF(K45=0,"",K45/K$11)
B46: 役員死亡退職慰労金 | D46: =IF(C46=0,"",C46/C$11) | F46: =IF(E46=0,"",E46/E$11) | H46: =IF(G46=0,"",G46/G$11) | J46: =IF(I46=0,"",I46/I$11) | L46: =IF(K46=0,"",K46/K$11)
D49: =IF(C49=0,"",C49/C$11) | F49: =IF(E49=0,"",E49/E$11) | H49: =IF(G49=0,"",G49/G$11) | J49: =IF(I49=0,"",I49/I$11) | L49: =IF(K49=0,"",K49/K$11)
D50: =IF(C50=0,"",C50/C$11) | F50: =IF(E50=0,"",E50/E$11) | H50: =IF(G50=0,"",G50/G$11) | J50: =IF(I50=0,"",I50/I$11) | L50: =IF(K50=0,"",K50/K$11)
B51: 税引前当期純利益 | C51: =C36+C37-C44 -> -7290352 | D51: =IF(C51=0,"",C51/C$11) -> -0.019013056 | E51: =E36+E37-E44 -> 130309716 | F51: =IF(E51=0,"",E51/E$11) -> 0.10587142 | G51: =G36+G37-G44 -> 580579 | H51: =IF(G51=0,"",G51/G$11) -> 0.0018180684 | I51: =I36+I37-I44 -> 0 | J51: =IF(I51=0,"",I51/I$11) | K51: =K36+K37-K44 -> 0 | L51: =IF(K51=0,"",K51/K$11)
B52: 法人税等 | C52: =SUM(C53:C55) -> 194727 | D52: =IF(C52=0,"",C52/C$11) -> 0.00050784316 | E52: =SUM(E53:E55) -> 21953358 | F52: =IF(E52=0,"",E52/E$11) -> 0.017836223 | G52: =SUM(G53:G55) -> 48664083 | H52: =IF(G52=0,"",G52/G$11) -> 0.15239034 | I52: =SUM(I53:I55) -> 0 | J52: =IF(I52=0,"",I52/I$11) | K52: =SUM(K53:K55) -> 0 | L52: =IF(K52=0,"",K52/K$11)
B53: 法人税・住民税及び事業税（当期分） | C53: 194727 | D53: =IF(C53=0,"",C53/C$11) -> 0.00050784316 | E53: 21953358 | F53: =IF(E53=0,"",E53/E$11) -> 0.017836223 | G53: 289183 | H53: =IF(G53=0,"",G53/G$11) -> 0.00090556921 | J53: =IF(I53=0,"",I53/I$11) | L53: =IF(K53=0,"",K53/K$11)
B54: 過年度法人税等 | C54: 0 | E54: 0 | G54: 48374900
D55: =IF(C55=0,"",C55/C$11) | F55: =IF(E55=0,"",E55/E$11) | H55: =IF(G55=0,"",G55/G$11) | J55: =IF(I55=0,"",I55/I$11) | L55: =IF(K55=0,"",K55/K$11)
B56: 税引後当期純利益 | C56: =C51-C52 -> -7485079 | D56: =IF(C56=0,"",C56/C$11) -> -0.019520899 | E56: =E51-E52 -> 108356358 | F56: =IF(E56=0,"",E56/E$11) -> 0.088035196 | G56: =G51-G52 -> -48083504 | H56: =IF(G56=0,"",G56/G$11) -> -0.15057227 | I56: =I51-I52 -> 0 | J56: =IF(I56=0,"",I56/I$11) | K56: =K51-K52 -> 0 | L56: =IF(K56=0,"",K56/K$11)

Sheet CR
H4: (単位：千円)
B5: 科目 | C5: ='BS(借方)'!C4 -> 令和6年3月期 | E5: ='BS(借方)'!D4 -> 令和7年3月期 | G5: ='BS(借方)'!E4 -> 令和8年3月期 | I5: ='BS(借方)'!F4 -> － | K5: ='BS(借方)'!G4 -> 進行期 （試算表未受領）
C6: 帳簿価額 | D6: 売上高比 | E6: 帳簿価額 | F6: 売上高比 | G6: 帳簿価額 | H6: 売上高比 | I6: 帳簿価額 | J6: 売上高比 | K6: 帳簿価額 | L6: 売上高比
A7: IMに貼るときは非表示→ | B7: 売上 | C7: =PL!C11 -> 383439251 | D7: - | E7: =PL!E11 -> 1230829971 | F7: - | G7: =PL!G11 -> 319338374 | H7: - | I7: =PL!I11 -> 0 | J7: - | K7: =PL!K11 -> 0 | L7: -
B8: 期首原材料棚卸高 | D8: =IF(C8=0,"",C8/C$7) | F8: =IF(E8=0,"",E8/E$7) | H8: =IF(G8=0,"",G8/G$7) | J8: =IF(I8=0,"",I8/I$7) | L8: =IF(K8=0,"",K8/K$7)
B9: 原材料仕入高 | D9: =IF(C9=0,"",C9/C$7) | F9: =IF(E9=0,"",E9/E$7) | H9: =IF(G9=0,"",G9/G$7) | J9: =IF(I9=0,"",I9/I$7) | L9: =IF(K9=0,"",K9/K$7)
B10: 小計 | D10: =IF(C10=0,"",C10/C$7) | F10: =IF(E10=0,"",E10/E$7) | H10: =IF(G10=0,"",G10/G$7) | J10: =IF(I10=0,"",I10/I$7) | L10: =IF(K10=0,"",K10/K$7)
B11: 期末原材料棚卸高 | D11: =IF(C11=0,"",C11/C$7) | F11: =IF(E11=0,"",E11/E$7) | H11: =IF(G11=0,"",G11/G$7) | J11: =IF(I11=0,"",I11/I$7) | L11: =IF(K11=0,"",K11/K$7)
D12: =IF(C12=0,"",C12/C$7) | F12: =IF(E12=0,"",E12/E$7) | H12: =IF(G12=0,"",G12/G$7) | J12: =IF(I12=0,"",I12/I$7) | L12: =IF(K12=0,"",K12/K$7)
D13: =IF(C13=0,"",C13/C$7) | F13: =IF(E13=0,"",E13/E$7) | H13: =IF(G13=0,"",G13/G$7) | J13: =IF(I13=0,"",I13/I$7) | L13: =IF(K13=0,"",K13/K$7)
B14: 材料費 | C14: =SUM(C8:C13) -> 0 | D14: =IF(C14=0,"",C14/C$7) | E14: =SUM(E8:E13) -> 0 | F14: =IF(E14=0,"",E14/E$7) | G14: =SUM(G8:G13) -> 0 | H14: =IF(G14=0,"",G14/G$7) | I14: =SUM(I8:I13) -> 0 | J14: =IF(I14=0,"",I14/I$7) | K14: =SUM(K8:K13) -> 0 | L14: =IF(K14=0,"",K14/K$7)
D15: =IF(C15=0,"",C15/C$7) | F15: =IF(E15=0,"",E15/E$7) | H15: =IF(G15=0,"",G15/G$7) | J15: =IF(I15=0,"",I15/I$7) | L15: =IF(K15=0,"",K15/K$7)
D18: =IF(C18=0,"",C18/C$7) | F18: =IF(E18=0,"",E18/E$7) | H18: =IF(G18=0,"",G18/G$7) | J18: =IF(I18=0,"",I18/I$7) | L18: =IF(K18=0,"",K18/K$7)
D19: =IF(C19=0,"",C19/C$7) | F19: =IF(E19=0,"",E19/E$7) | H19: =IF(G19=0,"",G19/G$7) | J19: =IF(I19=0,"",I19/I$7) | L19: =IF(K19=0,"",K19/K$7)
D20: =IF(C20=0,"",C20/C$7) | F20: =IF(E20=0,"",E20/E$7) | H20: =IF(G20=0,"",G20/G$7) | J20: =IF(I20=0,"",I20/I$7) | L20: =IF(K20=0,"",K20/K$7)
D21: =IF(C21=0,"",C21/C$7) | F21: =IF(E21=0,"",E21/E$7) | H21: =IF(G21=0,"",G21/G$7) | J21: =IF(I21=0,"",I21/I$7) | L21: =IF(K21=0,"",K21/K$7)
D22: =IF(C22=0,"",C22/C$7) | F22: =IF(E22=0,"",E22/E$7) | H22: =IF(G22=0,"",G22/G$7) | J22: =IF(I22=0,"",I22/I$7) | L22: =IF(K22=0,"",K22/K$7)
B23: 労務費 | C23: =SUM(C15:C22) -> 0 | D23: =IF(C23=0,"",C23/C$7) | E23: =SUM(E15:E22) -> 0 | F23: =IF(E23=0,"",E23/E$7) | G23: =SUM(G15:G22) -> 0 | H23: =IF(G23=0,"",G23/G$7) | I23: =SUM(I15:I22) -> 0 | J23: =IF(I23=0,"",I23/I$7) | K23: =SUM(K15:K22) -> 0 | L23: =IF(K23=0,"",K23/K$7)
D24: =IF(C24=0,"",C24/C$7) | F24: =IF(E24=0,"",E24/E$7) | H24: =IF(G24=0,"",G24/G$7) | J24: =IF(I24=0,"",I24/I$7) | L24: =IF(K24=0,"",K24/K$7)
D28: =IF(C28=0,"",C28/C$7) | F28: =IF(E28=0,"",E28/E$7) | H28: =IF(G28=0,"",G28/G$7) | J28: =IF(I28=0,"",I28/I$7) | L28: =IF(K28=0,"",K28/K$7)
D29: =IF(C29=0,"",C29/C$7) | F29: =IF(E29=0,"",E29/E$7) | H29: =IF(G29=0,"",G29/G$7) | J29: =IF(I29=0,"",I29/I$7) | L29: =IF(K29=0,"",K29/K$7)
D30: =IF(C30=0,"",C30/C$7) | F30: =IF(E30=0,"",E30/E$7) | H30: =IF(G30=0,"",G30/G$7) | J30: =IF(I30=0,"",I30/I$7) | L30: =IF(K30=0,"",K30/K$7)
D31: =IF(C31=0,"",C31/C$7) | F31: =IF(E31=0,"",E31/E$7) | H31: =IF(G31=0,"",G31/G$7) | J31: =IF(I31=0,"",I31/I$7) | L31: =IF(K31=0,"",K31/K$7)
D32: =IF(C32=0,"",C32/C$7) | F32: =IF(E32=0,"",E32/E$7) | H32: =IF(G32=0,"",G32/G$7) | J32: =IF(I32=0,"",I32/I$7) | L32: =IF(K32=0,"",K32/K$7)
B33: 外注加工費 | C33: =SUM(C24:C32) -> 0 | D33: =IF(C33=0,"",C33/C$7) | E33: =SUM(E24:E32) -> 0 | F33: =IF(E33=0,"",E33/E$7) | G33: =SUM(G24:G32) -> 0 | H33: =IF(G33=0,"",G33/G$7) | I33: =SUM(I24:I32) -> 0 | J33: =IF(I33=0,"",I33/I$7) | K33: =SUM(K24:K32) -> 0 | L33: =IF(K33=0,"",K33/K$7)
D34: =IF(C34=0,"",C34/C$7) | F34: =IF(E34=0,"",E34/E$7) | H34: =IF(G34=0,"",G34/G$7) | J34: =IF(I34=0,"",I34/I$7) | L34: =IF(K34=0,"",K34/K$7)
D35: =IF(C35=0,"",C35/C$7) | F35: =IF(E35=0,"",E35/E$7) | H35: =IF(G35=0,"",G35/G$7) | J35: =IF(I35=0,"",I35/I$7) | L35: =IF(K35=0,"",K35/K$7)
D36: =IF(C36=0,"",C36/C$7) | F36: =IF(E36=0,"",E36/E$7) | H36: =IF(G36=0,"",G36/G$7) | J36: =IF(I36=0,"",I36/I$7) | L36: =IF(K36=0,"",K36/K$7)
D39: =IF(C39=0,"",C39/C$7) | F39: =IF(E39=0,"",E39/E$7) | H39: =IF(G39=0,"",G39/G$7) | J39: =IF(I39=0,"",I39/I$7) | L39: =IF(K39=0,"",K39/K$7)
D40: =IF(C40=0,"",C40/C$7) | F40: =IF(E40=0,"",E40/E$7) | H40: =IF(G40=0,"",G40/G$7) | J40: =IF(I40=0,"",I40/I$7) | L40: =IF(K40=0,"",K40/K$7)
D41: =IF(C41=0,"",C41/C$7) | F41: =IF(E41=0,"",E41/E$7) | H41: =IF(G41=0,"",G41/G$7) | J41: =IF(I41=0,"",I41/I$7) | L41: =IF(K41=0,"",K41/K$7)
D42: =IF(C42=0,"",C42/C$7) | F42: =IF(E42=0,"",E42/E$7) | H42: =IF(G42=0,"",G42/G$7) | J42: =IF(I42=0,"",I42/I$7) | L42: =IF(K42=0,"",K42/K$7)
D43: =IF(C43=0,"",C43/C$7) | F43: =IF(E43=0,"",E43/E$7) | H43: =IF(G43=0,"",G43/G$7) | J43: =IF(I43=0,"",I43/I$7) | L43: =IF(K43=0,"",K43/K$7)
D44: =IF(C44=0,"",C44/C$7) | F44: =IF(E44=0,"",E44/E$7) | H44: =IF(G44=0,"",G44/G$7) | J44: =IF(I44=0,"",I44/I$7) | L44: =IF(K44=0,"",K44/K$7)
D45: =IF(C45=0,"",C45/C$7) | F45: =IF(E45=0,"",E45/E$7) | H45: =IF(G45=0,"",G45/G$7) | J45: =IF(I45=0,"",I45/I$7) | L45: =IF(K45=0,"",K45/K$7)
B46: 経費 | C46: =SUM(C34:C45) -> 0 | D46: =IF(C46=0,"",C46/C$7) | E46: =SUM(E34:E45) -> 0 | F46: =IF(E46=0,"",E46/E$7) | G46: =SUM(G34:G45) -> 0 | H46: =IF(G46=0,"",G46/G$7) | I46: =SUM(I34:I45) -> 0 | J46: =IF(I46=0,"",I46/I$7) | K46: =SUM(K34:K45) -> 0 | L46: =IF(K46=0,"",K46/K$7)
B47: 当期製造費用 | C47: =C14+C23+C33+C46 -> 0 | D47: =IF(C47=0,"",C47/C$7) | E47: =E14+E23+E33+E46 -> 0 | F47: =IF(E47=0,"",E47/E$7) | G47: =G14+G23+G33+G46 -> 0 | H47: =IF(G47=0,"",G47/G$7) | I47: =I14+I23+I33+I46 -> 0 | J47: =IF(I47=0,"",I47/I$7) | K47: =K14+K23+K33+K46 -> 0 | L47: =IF(K47=0,"",K47/K$7)
B48: 期首仕掛品棚卸高 | D48: =IF(C48=0,"",C48/C$7) | E48: =SUM(E36:E47) -> 0 | F48: =IF(E48=0,"",E48/E$7) | G48: =SUM(G36:G47) -> 0 | H48: =IF(G48=0,"",G48/G$7) | I48: =SUM(I36:I47) -> 0 | J48: =IF(I48=0,"",I48/I$7) | K48: =SUM(K36:K47) -> 0 | L48: =IF(K48=0,"",K48/K$7)
B49: 合計 | C49: =SUM(C47:C48) -> 0 | D49: =IF(C49=0,"",C49/C$7) | E49: =SUM(E47:E48) -> 0 | F49: =IF(E49=0,"",E49/E$7) | G49: =SUM(G47:G48) -> 0 | H49: =IF(G49=0,"",G49/G$7) | I49: =SUM(I47:I48) -> 0 | J49: =IF(I49=0,"",I49/I$7) | K49: =SUM(K47:K48) -> 0 | L49: =IF(K49=0,"",K49/K$7)
B50: 期末仕掛品棚卸高 | D50: =IF(C50=0,"",C50/C$7) | E50: =SUM(E40:E49) -> 0 | F50: =IF(E50=0,"",E50/E$7) | G50: =SUM(G40:G49) -> 0 | H50: =IF(G50=0,"",G50/G$7) | I50: =SUM(I40:I49) -> 0 | J50: =IF(I50=0,"",I50/I$7) | K50: =SUM(K40:K49) -> 0 | L50: =IF(K50=0,"",K50/K$7)
B51: 当期製造原価 | C51: =C49-C50 -> 0 | D51: =IF(C51=0,"",C51/C$7) | E51: =E49-E50 -> 0 | F51: =IF(E51=0,"",E51/E$7) | G51: =G49-G50 -> 0 | H51: =IF(G51=0,"",G51/G$7) | I51: =I49-I50 -> 0 | J51: =IF(I51=0,"",I51/I$7) | K51: =K49-K50 -> 0 | L51: =IF(K51=0,"",K51/K$7)

Sheet SGA
H2: (単位：千円)
B3: 科目 | C3: ='BS(借方)'!C4 -> 令和6年3月期 | E3: ='BS(借方)'!D4 -> 令和7年3月期 | G3: ='BS(借方)'!E4 -> 令和8年3月期 | I3: ='BS(借方)'!F4 -> － | K3: ='BS(借方)'!G4 -> 進行期 （試算表未受領）
C4: 帳簿価額 | D4: 売上高比 | E4: 帳簿価額 | F4: 売上高比 | G4: 帳簿価額 | H4: 売上高比 | I4: 帳簿価額 | J4: 売上高比 | K4: 帳簿価額 | L4: 売上高比
B5: 売上 | C5: =PL!C11 -> 383439251 | D5: - | E5: =PL!E11 -> 1230829971 | F5: - | G5: =PL!G11 -> 319338374 | H5: - | I5: =PL!I11 -> 0 | J5: - | K5: =PL!K11 -> 0 | L5: - | M5: ←IMに貼るときは非表示
B6: 役員報酬 | C6: 1920000 | D6: =IFERROR(C6/$C$5,"") -> 0.0050073121 | E6: 1920000 | F6: =IFERROR(E6/$E$5,"") -> 0.001559923 | G6: 1920000 | H6: =IFERROR(G6/$G$5,"") -> 0.0060124312 | J6: =IFERROR(I6/$I$5,"") | L6: =IFERROR(K6/$K$5,"")
B7: 給料手当 | C7: 137394789 | D7: =IFERROR(C7/$C$5,"") -> 0.35832218 | E7: 111145074 | F7: =IFERROR(E7/$E$5,"") -> 0.090300916 | G7: 113155654 | H7: =IFERROR(G7/$G$5,"") -> 0.35434405 | J7: =IFERROR(I7/$I$5,"") | L7: =IFERROR(K7/$K$5,"")
B8: 法定福利費 | C8: 21065176 | D8: =IFERROR(C8/$C$5,"") -> 0.054937453 | E8: 14045855 | F8: =IFERROR(E8/$E$5,"") -> 0.011411694 | G8: 18258884 | H8: =IFERROR(G8/$G$5,"") -> 0.057177231 | J8: =IFERROR(I8/$I$5,"") | L8: =IFERROR(K8/$K$5,"")
B9: 荷造運賃 | C9: 893478 | D9: =IFERROR(C9/$C$5,"") -> 0.0023301683 | E9: 813145 | F9: =IFERROR(E9/$E$5,"") -> 0.00066064771 | G9: 654125 | H9: =IFERROR(G9/$G$5,"") -> 0.0020483758 | J9: =IFERROR(I9/$I$5,"") | L9: =IFERROR(K9/$K$5,"")
B10: 減価償却費 | C10: 4594828 | D10: =IFERROR(C10/$C$5,"") -> 0.011983197 | E10: 14219250 | F10: =IFERROR(E10/$E$5,"") -> 0.01155257 | G10: 11895803 | H10: =IFERROR(G10/$G$5,"") -> 0.037251405 | J10: =IFERROR(I10/$I$5,"") | L10: =IFERROR(K10/$K$5,"")
B11: 地代家賃 | C11: 14896364 | D11: =IFERROR(C11/$C$5,"") -> 0.038849346 | E11: 17605421 | F11: =IFERROR(E11/$E$5,"") -> 0.014303699 | G11: 21688139 | H11: =IFERROR(G11/$G$5,"") -> 0.067915856 | J11: =IFERROR(I11/$I$5,"") | L11: =IFERROR(K11/$K$5,"")
B12: 修繕費 | C12: 4820065 | D12: =IFERROR(C12/$C$5,"") -> 0.012570609 | E12: 12667849 | F12: =IFERROR(E12/$E$5,"") -> 0.010292119 | G12: 349720 | H12: =IFERROR(G12/$G$5,"") -> 0.0010951393 | J12: =IFERROR(I12/$I$5,"") | L12: =IFERROR(K12/$K$5,"")
B13: 事務用品費 | D13: =IFERROR(C13/$C$5,"") -> 0 | F13: =IFERROR(E13/$E$5,"") -> 0 | H13: =IFERROR(G13/$G$5,"") -> 0 | J13: =IFERROR(I13/$I$5,"") | L13: =IFERROR(K13/$K$5,"")
B14: 消耗品費 | C14: 8665567 | D14: =IFERROR(C14/$C$5,"") -> 0.022599583 | E14: 3622074 | F14: =IFERROR(E14/$E$5,"") -> 0.0029427899 | G14: 3114486 | H14: =IFERROR(G14/$G$5,"") -> 0.0097529337 | J14: =IFERROR(I14/$I$5,"") | L14: =IFERROR(K14/$K$5,"")
B15: 水道光熱費 | C15: 12094761 | D15: =IFERROR(C15/$C$5,"") -> 0.031542835 | E15: 7886267 | F15: =IFERROR(E15/$E$5,"") -> 0.0064072757 | G15: 8256277 | H15: =IFERROR(G15/$G$5,"") -> 0.025854322 | J15: =IFERROR(I15/$I$5,"") | L15: =IFERROR(K15/$K$5,"")
B16: 旅費交通費 | C16: 4459042 | D16: =IFERROR(C16/$C$5,"") -> 0.01162907 | E16: 13621116 | F16: =IFERROR(E16/$E$5,"") -> 0.011066611 | G16: 6127921 | H16: =IFERROR(G16/$G$5,"") -> 0.019189429 | J16: =IFERROR(I16/$I$5,"") | L16: =IFERROR(K16/$K$5,"")
B17: 支払手数料 | C17: 26496901 | D17: =IFERROR(C17/$C$5,"") -> 0.069103257 | E17: 25381508 | F17: =IFERROR(E17/$E$5,"") -> 0.020621458 | G17: 13893115 | H17: =IFERROR(G17/$G$5,"") -> 0.043505936 | J17: =IFERROR(I17/$I$5,"") | L17: =IFERROR(K17/$K$5,"")
B18: 租税公課 | C18: 6754902 | D18: =IFERROR(C18/$C$5,"") -> 0.017616616 | E18: 9642116 | F18: =IFERROR(E18/$E$5,"") -> 0.0078338326 | G18: 4553800 | H18: =IFERROR(G18/$G$5,"") -> 0.014260109 | J18: =IFERROR(I18/$I$5,"") | L18: =IFERROR(K18/$K$5,"")
B19: 交際接待費 | C19: 3417904 | D19: =IFERROR(C19/$C$5,"") -> 0.0089138084 | E19: 3153229 | F19: =IFERROR(E19/$E$5,"") -> 0.0025618721 | G19: 0 | H19: =IFERROR(G19/$G$5,"") -> 0 | J19: =IFERROR(I19/$I$5,"") | L19: =IFERROR(K19/$K$5,"")
B20: 保険料 | C20: 94180 | D20: =IFERROR(C20/$C$5,"") -> 0.00024561909 | E20: 219320 | F20: =IFERROR(E20/$E$5,"") -> 0.00017818871 | G20: 664014 | H20: =IFERROR(G20/$G$5,"") -> 0.002079343 | J20: =IFERROR(I20/$I$5,"") | L20: =IFERROR(K20/$K$5,"")
B21: 通信費 | C21: 1009720 | D21: =IFERROR(C21/$C$5,"") -> 0.0026333246 | E21: 953882 | F21: =IFERROR(E21/$E$5,"") -> 0.00077499088 | G21: 836193 | H21: =IFERROR(G21/$G$5,"") -> 0.0026185171 | J21: =IFERROR(I21/$I$5,"") | L21: =IFERROR(K21/$K$5,"")
B22: 諸会費 | C22: 28000 | D22: =IFERROR(C22/$C$5,"") -> 7.3023301e-05 | E22: 60000 | F22: =IFERROR(E22/$E$5,"") -> 4.8747594e-05 | G22: 60000 | H22: =IFERROR(G22/$G$5,"") -> 0.00018788847 | J22: =IFERROR(I22/$I$5,"") | L22: =IFERROR(K22/$K$5,"")
B23: 車輛費 | C23: 966665 | D23: =IFERROR(C23/$C$5,"") -> 0.0025210382 | E23: 159400 | F23: =IFERROR(E23/$E$5,"") -> 0.00012950611 | G23: 653731 | H23: =IFERROR(G23/$G$5,"") -> 0.002047142 | J23: =IFERROR(I23/$I$5,"") | L23: =IFERROR(K23/$K$5,"")
B24: 貸倒引当金繰入額 | D24: =IFERROR(C24/$C$5,"") -> 0 | F24: =IFERROR(E24/$E$5,"") -> 0 | H24: =IFERROR(G24/$G$5,"") -> 0 | J24: =IFERROR(I24/$I$5,"") | L24: =IFERROR(K24/$K$5,"")
B25: 研修費 | C25: 3456 | D25: =IFERROR(C25/$C$5,"") -> 9.0131618e-06 | E25: 0 | F25: =IFERROR(E25/$E$5,"") -> 0 | G25: 0 | H25: =IFERROR(G25/$G$5,"") -> 0 | J25: =IFERROR(I25/$I$5,"") | L25: =IFERROR(K25/$K$5,"")
B26: 雑費 | C26: 1181195 | D26: =IFERROR(C26/$C$5,"") -> 0.0030805271 | E26: 7140452 | F26: =IFERROR(E26/$E$5,"") -> 0.0058013309 | G26: 1368052 | H26: =IFERROR(G26/$G$5,"") -> 0.0042840201 | J26: =IFERROR(I26/$I$5,"") | L26: =IFERROR(K26/$K$5,"")
B27: 福利厚生費 | C27: 291880 | D27: =IFERROR(C27/$C$5,"") -> 0.00076121576 | E27: 380301 | F27: =IFERROR(E27/$E$5,"") -> 0.00030897931 | G27: 235205 | H27: =IFERROR(G27/$G$5,"") -> 0.00073653848 | J27: =IFERROR(I27/$I$5,"") | L27: =IFERROR(K27/$K$5,"")
B28: 外注費 | C28: 6144296 | D28: =IFERROR(C28/$C$5,"") -> 0.016024171 | E28: 3207403 | F28: =IFERROR(E28/$E$5,"") -> 0.0026058863 | G28: 2296521 | H28: =IFERROR(G28/$G$5,"") -> 0.0071914971 | J28: =IFERROR(I28/$I$5,"") | L28: =IFERROR(K28/$K$5,"")
B29: 広告宣伝費 | C29: 649000 | D29: =IFERROR(C29/$C$5,"") -> 0.0016925758 | E29: 292026 | F29: =IFERROR(E29/$E$5,"") -> 0.00023725942 | G29: 58411 | H29: =IFERROR(G29/$G$5,"") -> 0.00018291256 | J29: =IFERROR(I29/$I$5,"") | L29: =IFERROR(K29/$K$5,"")
B30: 会議費 | C30: 3050293 | D30: =IFERROR(C30/$C$5,"") -> 0.007955088 | E30: 5275153 | F30: =IFERROR(E30/$E$5,"") -> 0.0042858503 | G30: 27249 | H30: =IFERROR(G30/$G$5,"") -> 8.5329551e-05 | J30: =IFERROR(I30/$I$5,"") | L30: =IFERROR(K30/$K$5,"")
B31: 支払報酬料 | C31: 4469601 | D31: =IFERROR(C31/$C$5,"") -> 0.011656608 | E31: 6976250 | F31: =IFERROR(E31/$E$5,"") -> 0.0056679234 | G31: 1295640 | H31: =IFERROR(G31/$G$5,"") -> 0.0040572637 | J31: =IFERROR(I31/$I$5,"") | L31: =IFERROR(K31/$K$5,"")
B32: 採用教育費 | C32: 45273 | D32: =IFERROR(C32/$C$5,"") -> 0.00011807085 | E32: 0 | F32: =IFERROR(E32/$E$5,"") -> 0 | G32: 0 | H32: =IFERROR(G32/$G$5,"") -> 0 | J32: =IFERROR(I32/$I$5,"") | L32: =IFERROR(K32/$K$5,"")
B33: 不動産管理費 | C33: 4347132 | D33: =IFERROR(C33/$C$5,"") -> 0.011337212 | E33: 1928280 | F33: =IFERROR(E33/$E$5,"") -> 0.0015666502 | G33: 686448 | H33: =IFERROR(G33/$G$5,"") -> 0.0021495945 | J33: =IFERROR(I33/$I$5,"") | L33: =IFERROR(K33/$K$5,"")
B34: リース料 | C34: 13797260 | D34: =IFERROR(C34/$C$5,"") -> 0.03598291 | E34: 10744470 | F34: =IFERROR(E34/$E$5,"") -> 0.0087294511 | G34: 10212056 | H34: =IFERROR(G34/$G$5,"") -> 0.031978794 | J34: =IFERROR(I34/$I$5,"") | L34: =IFERROR(K34/$K$5,"")
B35: 寄付金 | C35: 0 | D35: =IFERROR(C35/$C$5,"") -> 0 | E35: 500 | F35: =IFERROR(E35/$E$5,"") -> 4.0622995e-07 | G35: 0 | H35: =IFERROR(G35/$G$5,"") -> 0 | J35: =IFERROR(I35/$I$5,"") | L35: =IFERROR(K35/$K$5,"")
D36: =IFERROR(C36/$C$5,"") -> 0 | F36: =IFERROR(E36/$E$5,"") -> 0 | H36: =IFERROR(G36/$G$5,"") -> 0 | J36: =IFERROR(I36/$I$5,"") | L36: =IFERROR(K36/$K$5,"")
D37: =IFERROR(C37/$C$5,"") -> 0 | F37: =IFERROR(E37/$E$5,"") -> 0 | H37: =IFERROR(G37/$G$5,"") -> 0 | J37: =IFERROR(I37/$I$5,"") | L37: =IFERROR(K37/$K$5,"")
D38: =IFERROR(C38/$C$5,"") -> 0 | F38: =IFERROR(E38/$E$5,"") -> 0 | H38: =IFERROR(G38/$G$5,"") -> 0 | J38: =IFERROR(I38/$I$5,"") | L38: =IFERROR(K38/$K$5,"")
D39: =IFERROR(C39/$C$5,"") -> 0 | F39: =IFERROR(E39/$E$5,"") -> 0 | H39: =IFERROR(G39/$G$5,"") -> 0 | J39: =IFERROR(I39/$I$5,"") | L39: =IFERROR(K39/$K$5,"")
B40: 販売費および一般管理費合計 | C40: =SUM(C6:C39) -> 283551728 | D40: =IFERROR(C40/C5,"") -> 0.73949583 | E40: =SUM(E6:E39) -> 273060341 | F40: =IFERROR(E40/E5,"") -> 0.22185058 | G40: =SUM(G6:G39) -> 222261444 | H40: =IFERROR(G40/G5,"") -> 0.69600606 | I40: =SUM(I6:I39) -> 0 | J40: =IFERROR(I40/I5,"") | K40: =SUM(K6:K39) -> 0 | L40: =IFERROR(K40/K5,"")

Sheet VR→ 

Sheet 株式価値 
A1: 作業不要（自動作成）
F2: (単位：千円)
C3: min | D3: 差（グラフ作成用） | E3: max
B4: インカム | C4: 0 | D4: 0 | E4: 0 | F4: 100 | I4: ｚ
B5: マーケット | C5: =IF(ISNUMBER('EV EBITDAマルチプル'!K7),MAX(0,'EV EBITDAマルチプル'!K7),0) -> 0 | D5: =E5-C5 -> 0 | E5: =IF(ISNUMBER('EV EBITDAマルチプル'!M7),MAX(0,'EV EBITDAマルチプル'!M7),0) -> 0 | F5: 0
B6: コスト | C6: ='年買法'!K6 -> 320002051 | D6: =E6-C6 -> 0 | E6: ='年買法'!M6 -> 320002051 | F6: 0

Sheet 修正BS(借方)
E2: (単位：千円)
B3: 資産の部
B4: 科目 | C4: ='BS(借方)'!E4 -> 令和8年3月期 | D4: 修正額 | E4: 修正後
B5: 【流動資産】 | C5: =SUM(C6:C19) -> 293198020 | D5: =SUM(D6:D19) -> 0 | E5: =C5+D5 -> 293198020
B6: 現金及び預金 | C6: ='BS(借方)'!E6 -> 226057309 | E6: =C6+D6 -> 226057309
B7: 受取手形 | C7: ='BS(借方)'!E7 -> 0 | E7: =C7+D7 -> 0
B8: 売掛金 | C8: ='BS(借方)'!E8 -> 28512083 | E8: =C8+D8 -> 28512083
B9: 原材料 | C9: ='BS(借方)'!E9 -> 0 | E9: =C9+D9 -> 0
B10: 仕掛品 | C10: ='BS(借方)'!E10 -> 0 | E10: =C10+D10 -> 0
B11: 貯蔵品 | C11: ='BS(借方)'!E11 -> 0 | E11: =C11+D11 -> 0
B12: 前渡金 | C12: ='BS(借方)'!E12 -> 18507883 | E12: =C12+D12 -> 18507883
B13: 未収入金 | C13: ='BS(借方)'!E13 -> 0 | E13: =C13+D13 -> 0
B14: 貸倒引当金 | C14: ='BS(借方)'!E14 -> 0 | E14: =C14+D14 -> 0
B15: 商品 | C15: ='BS(借方)'!E15 -> 8532000 | E15: =C15+D15 -> 8532000
B16: 前払費用 | C16: ='BS(借方)'!E16 -> 710345 | E16: =C16+D16 -> 710345
B17: 立替金 | C17: ='BS(借方)'!E17 -> 0 | E17: =C17+D17 -> 0
B18: 未収還付法人税等 | C18: ='BS(借方)'!E18 -> 10878400 | E18: =C18+D18 -> 10878400
C19: ='BS(借方)'!E19 -> 0 | E19: =C19+D19 -> 0
B20: 【固定資産】 | C20: =C21+C35+C46 -> 503310970 | D20: =D21+D35+D46 -> 0 | E20: =C20+D20 -> 503310970
B21: ［有形固定資産］ | C21: =SUM(C22:C34) -> 490145870 | D21: =SUM(D22:D34) -> 0 | E21: =C21+D21 -> 490145870
B22: 建物 | C22: ='BS(借方)'!E22 -> 118721091 | E22: =C22+D22 -> 118721091
B23: 建物付属設備 | C23: ='BS(借方)'!E23 -> 20091490 | E23: =C23+D23 -> 20091490
B24: 構築物 | C24: ='BS(借方)'!E24 -> 0 | E24: =C24+D24 -> 0
B25: 機械装置 | C25: ='BS(借方)'!E25 -> 0 | E25: =C25+D25 -> 0
B26: 車輛運搬具 | C26: ='BS(借方)'!E26 -> 5394909 | E26: =C26+D26 -> 5394909
B27: 工具器具備品 | C27: ='BS(借方)'!E27 -> 908754 | E27: =C27+D27 -> 908754
B28: 一括償却資産 | C28: ='BS(借方)'!E28 -> 0 | E28: =C28+D28 -> 0
B29: 土地 | C29: ='BS(借方)'!E29 -> 345029626 | E29: =C29+D29 -> 345029626
B30: 建設仮戡定 | C30: ='BS(借方)'!E30 -> 0 | E30: =C30+D30 -> 0
C31: ='BS(借方)'!E31 -> 0 | E31: =C31+D31 -> 0
C32: ='BS(借方)'!E32 -> 0 | E32: =C32+D32 -> 0
C33: ='BS(借方)'!E33 -> 0 | E33: =C33+D33 -> 0
C34: ='BS(借方)'!E34 -> 0 | E34: =C34+D34 -> 0
B35: ［無形固定資産］ | C35: =SUM(C36:C45) -> 0 | D35: =SUM(D36:D45) -> 0 | E35: =C35+D35 -> 0
B36: ソフトウェア | C36: ='BS(借方)'!E36 -> 0 | E36: =C36+D36 -> 0
B37: 電話加入権 | C37: ='BS(借方)'!E37 -> 0 | E37: =C37+D37 -> 0
B38: 施設利用権 | C38: ='BS(借方)'!E38 -> 0 | E38: =C38+D38 -> 0
C39: ='BS(借方)'!E39 -> 0 | E39: =C39+D39 -> 0
C40: ='BS(借方)'!E40 -> 0 | E40: =C40+D40 -> 0
C41: ='BS(借方)'!E41 -> 0 | E41: =C41+D41 -> 0
C42: ='BS(借方)'!E42 -> 0 | E42: =C42+D42 -> 0
C43: ='BS(借方)'!E43 -> 0 | E43: =C43+D43 -> 0
C44: ='BS(借方)'!E44 -> 0 | E44: =C44+D44 -> 0
C45: ='BS(借方)'!E45 -> 0 | E45: =C45+D45 -> 0
B46: ［投資その他資産］ | C46: =SUM(C47:C54) -> 13165100 | D46: =SUM(D47:D54) -> 0 | E46: =C46+D46 -> 13165100
B47: 出資金 | C47: ='BS(借方)'!E47 -> 5000 | E47: =C47+D47 -> 5000
B48: リサイクル預託金 | C48: ='BS(借方)'!E48 -> 0 | E48: =C48+D48 -> 0
B49: 保険積立金 | C49: ='BS(借方)'!E49 -> 0 | E49: =C49+D49 -> 0
B50: 投資有価証券 | C50: ='BS(借方)'!E50 -> 0 | E50: =C50+D50 -> 0
B51: 敷金 | C51: ='BS(借方)'!E51 -> 13160100 | E51: =C51+D51 -> 13160100
B52: 差入保証金 | C52: ='BS(借方)'!E52 -> 0 | E52: =C52+D52 -> 0
C53: ='BS(借方)'!E53 -> 0 | E53: =C53+D53 -> 0
C54: ='BS(借方)'!E54 -> 0 | E54: =C54+D54 -> 0
B55: 【繰延資産】 | C55: =SUM(C56:C59) -> 0 | D55: =SUM(D56:D59) -> 0 | E55: =C55+D55 -> 0
B56: 開業費 | C56: ='BS(借方)'!E57 -> 0 | E56: =C56+D56 -> 0
C57: ='BS(借方)'!E58 -> 0 | E57: =C57+D57 -> 0
C58: ='BS(借方)'!E59 -> 0 | E58: =C58+D58 -> 0
C59: ='BS(借方)'!E60 -> 0 | E59: =C59+D59 -> 0
B60: 【繰延税金資産】 | C60: 0 | D60: ='税効果'!E18 -> 3558003 | E60: =C60+D60 -> 3558003
B61: 資産合計 | C61: =C5+C20+C55+C60 -> 796508990 | D61: =D5+D20+D55+D60 -> 3558003 | E61: =C61+D61 -> 800066993

Sheet 売掛・棚卸
E2: (単位：千円)
A3: 売掛金 | B3: 相手先 | C3: 帳簿価額 | D3: 評価差額 | E3: 評価額 | F3: 調整事由
B4: コンサル料（相手先不明） | C4: 15400000 | D4: 0 | E4: =SUM(C4,D4) -> 15400000 | F4: 相手先・契約書・入金予定が未確認のため簿価評価。単発の売上計上であり、回収可能性・実在性は要確認
B5: 大船店（百貨店精算分等） | C5: 5988954 | D5: 0 | E5: =SUM(C5,D5) -> 5988954 | F5: 店舗売上に係る決済・百貨店精算の未収。年齢表未受領のため簿価評価
B6: 紀尾井町店 | C6: 3347303 | D6: 0 | E6: =SUM(C6,D6) -> 3347303 | F6: 同上
B7: その他（鎌倉山店・ミリュウショップ・リンベル㈱等） | C7: 3775826 | D7: 0 | E7: =SUM(C7,D7) -> 3775826 | F7: 鎌倉山店2,079千円、ミリュウショップ768千円、リンベル㈱644千円、㈱西武リアルティソリューションズ236千円ほか。年齢表未受領のため簿価評価
B8: 合計 | C8: =SUM(C4:C7) -> 28512083 | D8: =SUM(D4:D7) -> 0 | E8: =C8+D8 -> 28512083
E12: (単位：千円)
A13: 商品在庫 | B13: 相手先 | C13: 帳簿価額 | D13: 評価差額 | E13: 評価額 | F13: 調整事由
B14: 商品（ケーキ・菓子・食材等） | C14: 8532000 | D14: 0 | E14: =SUM(C14,D14) -> 8532000 | F14: 「明細別途保存」とされ棚卸明細は未受領のため簿価評価。滞留・陳腐化の有無は要確認
E15: =SUM(C15,D15) -> 0
E16: =SUM(C16,D16) -> 0
E17: =SUM(C17,D17) -> 0
B18: 合計 | C18: =SUM(C14:C17) -> 8532000 | D18: =SUM(D14:D17) -> 0 | E18: =C18+D18 -> 8532000

Sheet 減価償却
E2: (単位：千円)
B3: 資産 | C3: 帳簿価額 | D3: 評価差額 | E3: 評価額 | F3: 調整事由
B4: 建物 | C4: ='BS(借方)'!E22 -> 118721091 | D4: 0 | E4: =SUM(C4,D4) -> 118721091 | F4: 固定資産台帳上、普通償却限度額＝当期償却額で償却不足額なし。実態の劣化・耐用年数との乖離は未検討のため簿価評価（要確認）
B5: 建物付属設備 | C5: ='BS(借方)'!E23 -> 20091490 | D5: 0 | E5: =SUM(C5,D5) -> 20091490 | F5: 同上
B6: 車両運搬具 | C6: ='BS(借方)'!E26 -> 5394909 | D6: 0 | E6: =SUM(C6,D6) -> 5394909 | F6: 同上
B7: 工具器具備品 | C7: ='BS(借方)'!E27 -> 908754 | D7: 0 | E7: =SUM(C7,D7) -> 908754 | F7: 同上
B8: 合計 | C8: =SUM(C4:C7) -> 145116244 | D8: =SUM(D4:D7) -> 0 | E8: =C8+D8 -> 145116244

Sheet 土地
F2: (単位：千円)
B3: 内容・所在地 | C3: 地積(㎡) | D3: 帳簿価額 | E3: 評価差額 | F3: 時価評価額 | G3: 調整事由
B4: 鎌倉山店・本社敷地ほか／神奈川県鎌倉市鎌倉山三丁目2番31（地番・地目の詳細は要確認） | C4: 要確認 | D4: ='BS(借方)'!E29 -> 345029626 | E4: =F4-D4 -> 0 | F4: =D4 -> 345029626 | G4: 登記事項証明書・固定資産税評価証明書・路線価が未受領のため時価評価未実施（簿価評価）。うち約87,420千円は「鎌倉山三丁目計画」に係る建設仮勘定からの振替額（内容要確認）
E5: =F5-D5 -> 0
E6: =F6-D6 -> 0
E7: =F7-D7 -> 0
B8: 合計 | D8: =SUM(D4:D7) -> 345029626 | E8: =SUM(E4:E7) -> 0 | F8: =SUM(F4:F7) -> 345029626

Sheet 保険
E2: (単位：千円)
B3: 保険商品 | C3: 帳簿価額 | D3: 評価差額 | E3: 評価額 | F3: 調整事由
B4: 該当なし（BS上、保険積立金の計上なし） | C4: 0 | D4: =E4-C4 -> 0 | E4: 0 | F4: 保険契約の有無・解約返戻金は未確認（保険証券未受領）。支払保険料は年664千円のみ（損害保険料等と推察）
B8: 合計 | C8: =SUM(C4:C7) -> 0 | D8: =SUM(D4:D7) -> 0 | E8: =C8+D8 -> 0

Sheet 有価証券
F2: (単位：千円)
B3: 銘柄 | C3: 数量 | D3: 帳簿価額 | E3: 評価差額 | F3: 評価額 | G3: 調整事由
B4: 該当なし（BS上、投資有価証券の計上なし） | C4: 0 | D4: 0 | E4: =F4-D4 -> 0 | F4: 0 | G4: BSに計上なし（出資金5千円のみ）
E5: =F5-D5 -> 0
E7: =F7-D7 -> 0
E8: =F8-D8 -> 0
B9: 合計 | C9: - | D9: =SUM(D4:D8) -> 0 | E9: =SUM(E4:E8) -> 0 | F9: =D9+E9 -> 0

Sheet 敷金保証金
E2: (単位：千円)
B3: 内容 | C3: 帳簿価額 | D3: 評価差額 | E3: 評価額 | F3: 調整事由
B4: 敷金（店舗等の賃借物件） | C4: ='BS(借方)'!E51 -> 13160100 | D4: 0 | E4: =C4+D4 -> 13160100 | F4: 店舗別の賃貸借契約書・預託明細が未受領のため簿価評価。返還見込み・原状回復費用は要確認
B5: 差入保証金 | C5: ='BS(借方)'!E52 -> 0 | D5: 0 | E5: =C5+D5 -> 0 | F5: BSに計上なし
B8: 合計 | C8: =SUM(C4:C7) -> 13160100 | D8: =SUM(D4:D7) -> 0 | E8: =SUM(E4:E7) -> 13160100

Sheet 修正BS(貸方) 
E2: (単位：千円)
B3: 負債の部
B4: 科目 | C4: ='BS(借方)'!E4 -> 令和8年3月期 | D4: 修正額 | E4: 修正後
B5: 【流動負債】 | C5: =SUM(C6:C17) -> 196854699 | D5: =SUM(D6:D17) -> 10464714 | E5: =C5+D5 -> 207319413
B6: 買掛金 | C6: ='BS (貸方)'!E6 -> 10296760 | E6: =C6+D6 -> 10296760
B7: 未払金 | C7: ='BS (貸方)'!E7 -> 7639437 | E7: =C7+D7 -> 7639437
B8: 未払費用 | C8: ='BS (貸方)'!E8 -> 0 | D8: ='未払人件費・賞与'!F4 -> 10464714 | E8: =C8+D8 -> 10464714
B9: 未払消費税 | C9: ='BS (貸方)'!E9 -> 4950000 | E9: =C9+D9 -> 4950000
B10: 預り金 | C10: ='BS (貸方)'!E10 -> 794225 | E10: =C10+D10 -> 794225
B11: 未払法人税等 | C11: ='BS (貸方)'!E11 -> 97300 | E11: =C11+D11 -> 97300
B12: 短期借入金 | C12: ='BS (貸方)'!E12 -> 173076977 | E12: =C12+D12 -> 173076977
C13: ='BS (貸方)'!E13 -> 0 | E13: =C13+D13 -> 0
C14: ='BS (貸方)'!E14 -> 0 | E14: =C14+D14 -> 0
C15: ='BS (貸方)'!E15 -> 0 | E15: =C15+D15 -> 0
C16: ='BS (貸方)'!E16 -> 0 | E16: =C16+D16 -> 0
C17: ='BS (貸方)'!E17 -> 0 | E17: =C17+D17 -> 0
B18: 【固定負債】 | C18: =SUM(C19:C26) -> 272745529 | D18: =SUM(D19:D26) -> 0 | E18: =C18+D18 -> 272745529
B19: 長期借入金 | C19: ='BS (貸方)'!E19 -> 272745529 | E19: =C19+D19 -> 272745529
B20: 長期預り保証金 | C20: ='BS (貸方)'!E20 -> 0 | E20: =C20+D20 -> 0
C21: ='BS (貸方)'!E21 -> 0 | E21: =C21+D21 -> 0
C22: ='BS (貸方)'!E22 -> 0 | E22: =C22+D22 -> 0
C23: ='BS (貸方)'!E23 -> 0 | E23: =C23+D23 -> 0
C24: ='BS (貸方)'!E24 -> 0 | E24: =C24+D24 -> 0
E25: =C25+D25 -> 0
E26: =C26+D26 -> 0
B27: 【繰延税金負債】 | C27: 0 | D27: 0 | E27: =C27+D27 -> 0
B28: 負債合計 | C28: =C5+C18+C27 -> 469600228 | D28: =D5+D18+D27 -> 10464714 | E28: =C28+D28 -> 480064942
B34: 純資産の部
B35: 【資本金】 | C35: =SUM(C36:C38) -> 500000 | D35: =SUM(D36:D38) -> 0 | E35: =C35+D35 -> 500000
B36: 資本金 | C36: ='BS (貸方)'!E36 -> 500000 | E36: =C36+D36 -> 500000
C37: ='BS (貸方)'!E37 -> 0 | E37: =C37+D37 -> 0
C38: ='BS (貸方)'!E38 -> 0 | E38: =C38+D38 -> 0
B39: 【資本剰余金】 | C39: =SUM(C40:C42) -> 5000000 | D39: =SUM(D40:D42) -> 0 | E39: =C39+D39 -> 5000000
B40: その他資本剰余金 | C40: ='BS (貸方)'!E40 -> 5000000 | E40: =C40+D40 -> 5000000
C41: ='BS (貸方)'!E41 -> 0 | E41: =C41+D41 -> 0
C42: ='BS (貸方)'!E42 -> 0 | E42: =C42+D42 -> 0
B43: 【利益剰余金】 | C43: =SUM(C44:C47) -> 321408762 | D43: =SUM(D44:D47) -> 0 | E43: =C43+D43 -> 321408762
B44: 利益準備金 | C44: ='BS (貸方)'!E44 -> 0 | E44: =C44+D44 -> 0
B45: 別途積立金 | C45: ='BS (貸方)'!E45 -> 0 | E45: =C45+D45 -> 0
B46: 繰越利益剰余金 | C46: ='BS (貸方)'!E46 -> 321408762 | E46: =C46+D46 -> 321408762
E47: =C47+D47 -> 0
B48: 【自己株式】 | C48: 0 | D48: 0 | E48: =C48+D48 -> 0
B49: 【評価修正額】 | D49: =SUM(D50:D51) -> -6906711 | E49: =C49+D49 -> -6906711
B50: 修正額 | D50: ='修正BS(借方)'!D61-'修正BS(借方)'!D60-(D28-D27) -> -10464714 | E50: =C50+D50 -> -10464714
B51: 修正税効果 | D51: ='修正BS(借方)'!D60-D27 -> 3558003 | E51: =C51+D51 -> 3558003
B52: 純資産合計 | C52: =C35+C39+C43+C48 -> 326908762 | D52: =D35+D39+D43+D48+D49 -> -6906711 | E52: =C52+D52 -> 320002051
B53: 負債・純資産合計 | C53: =C28+C52 -> 796508990 | D53: =D28+D52 -> 3558003 | E53: =C53+D53 -> 800066993
B55: 検算：修正後 貸借一致 | C55: =EXACT(E53,'修正BS(借方)'!E61) -> 1

Sheet 未払人件費・賞与
F2: (単位：千円)
B3: 令和8年3月計上の給料手当 | C3: 未払日数 | D3: 未払給与引当額 | E3: 概算社会保険料 | F3: 未払給与引当額
B4: 9099751 | C4: 3月分給与は4月支給と推察（賃金規程未受領・要確認） | D4: =ROUND(B4*31/31,0) -> 9099751 | E4: =ROUND(D4*0.15,0) -> 1364963 | F4: =D4+E4 -> 10464714
E7: (単位：千円)
B8: 支払予定賞与 | C8: 支給対象月数 | D8: 経過月数 | E8: 引当額 | F8: 概算社会保険料 | G8: 社保考慮後引当不足
B9: 0 | C9: 賞与規程・支給実績未受領（給与台帳上、賞与の記載なし） | D9: － | E9: =B9*0 -> 0 | F9: =E9*0.15 -> 0 | G9: =E9+F9 -> 0

Sheet 退職金
J2: (単位：千円)
B3: № | C3: 氏名 | D3: 勤続年数(年) | E3: 基本給 | F3: 支給倍率 | G3: 退職理由率 | H3: 要支給額 | I3: 中退共積立額 | J3: 引当不足
C4: 退職金規程・中退共等の加入資料が未受領のため要支給額を算定できず、引当は未計上（簿外債務の可能性：要確認）
C10: 合計 | H10: 0 | I10: 0 | J10: =H10+I10 -> 0

Sheet 税効果
E2: (単位：千円)
B3: 修正科目 | C3: 適用判定 | D3: 修正額 | E3: 繰延税金資産/負債 | F3: 備考
B4: 売掛金 | C4: 〇 | D4: 0 | E4: =ROUND(-D4*0.34,0) -> 0 | F4: 修正なし
B5: 棚卸資産 | C5: 〇 | D5: 0 | E5: =ROUND(-D5*0.34,0) -> 0 | F5: 修正なし
B6: 建物 | C6: 〇 | E6: =ROUND(-D6*0.34,0) -> 0 | F6: 修正なし（償却不足なし）
B7: 土地 | C7: × | E7: － | F7: 時価評価未実施（簿価評価）のため修正なし
B8: 電話加入権 | C8: × | E8: － | F8: 流動性がないため、除外
B9: 保険積立金 | C9: 〇 | E9: =ROUND(-D9*0.34,0) -> 0 | F9: 該当なし
B10: 投資有価証券 | C10: 〇 | E10: =ROUND(-D10*0.34,0) -> 0 | F10: 該当なし
B11: 未払費用 | C11: 〇 | D11: =-'未払人件費・賞与'!F4 -> -10464714 | E11: =ROUND(-D11*0.34,0) -> 3558003 | F11: 3月分給与の未払計上に係る一時差異（実効税率34%）
B12: 賞与引当金 | C12: 〇 | E12: =ROUND(-D12*0.34,0) -> 0 | F12: 修正なし（賞与実績未確認）
B13: 退職給付引当 | C13: 〇 | E13: =ROUND(-D13*0.34,0) -> 0 | F13: 修正なし（退職金規程未受領・要確認）
E14: =ROUND(-D14*0.34,0) -> 0
E15: =ROUND(-D15*0.34,0) -> 0
E16: =ROUND(-D16*0.34,0) -> 0
E17: =ROUND(-D17*0.34,0) -> 0
B18: 合計 | C18: － | D18: =SUM(D4:D17) -> -10464714 | E18: =SUM(E4:E17) -> 3558003

Sheet ネットキャッシュ
F2: (単位：千円)
B3: キャッシュライクアイテム | C3: 金額 | E3: デットライクアイテム | F3: 金額
B4: 現金及び預金 | C4: ='修正BS(借方)'!E6 -> 226057309 | E4: 借入金（金融機関） | F4: 86156000
B5: 役員貸付金 | C5: 0 | E5: 未払配当金 | F5: 0
B6: 従業員貸付金 | C6: 0 | E6: 社債 | F6: 0
B7: 立替金 | C7: 0 | E7: 役員借入金 | F7: 359666506
B8: 保険積立金 | C8: 0 | E8: 未払法人税 | F8: ='修正BS(貸方) '!E11 -> 97300
B9: 投資有価証券 | C9: 0 | E9: 資産除去債務 | F9: 0
B10: 売却予定不動産 | C10: 0 | E10: 役員退職慰労金 | F10: 0
B11: 売却予定車両 | C11: 0 | E11: 営業循環外前受金 | F11: 0
B12: 未収還付法人税等 | C12: ='修正BS(借方)'!E18 -> 10878400 | E12: リース債務（未確認） | F12: 0
B13: 合計 | C13: =SUM(C4:C12) -> 236935709 | E13: 合計 | F13: =SUM(F4:F12) -> 445919806
B15: ネットキャッシュ | C15: =C13-F13 -> -208984097 | E15: ネットデット | F15: =F13-C13 -> 208984097
B19: ※借入金合計445,823千円（BS：短期173,077千円＋長期272,746千円）の内訳は勘定科目内訳明細書（令和8年3月期）による。
B20: ※未収還付法人税等は実現見込みを要確認のうえキャッシュライクに算入。リース債務・未払給与は評価書上、別途検討。

Sheet 修正PL
K2: (単位：千円)
B3: 科目 | C3: ='BS(借方)'!C4 -> 令和6年3月期 | F3: ='BS(借方)'!D4 -> 令和7年3月期 | I3: ='BS(借方)'!E4 -> 令和8年3月期 | L3: ='BS(借方)'!F4 -> － | O3: ='BS(借方)'!G4 -> 進行期 （試算表未受領）
C4: 帳簿価額 | D4: 修正額 | E4: 修正後 | F4: 帳簿価額 | G4: 修正額 | H4: 修正後 | I4: 帳簿価額 | J4: 修正額 | K4: 修正後 | L4: 帳簿価額 | M4: 修正額 | N4: 修正後 | O4: 帳簿価額 | P4: 修正額 | Q4: 修正後
B5: 店舗・EC等売上高 | C5: =PL!C5 -> 366805605 | E5: =C5+D5 -> 366805605 | F5: =PL!E5 -> 344797561 | H5: =F5+G5 -> 344797561 | I5: =PL!G5 -> 303702978 | K5: =I5+J5 -> 303702978 | N5: =L5+M5 -> 0 | Q5: =O5+P5 -> 0
B6: 不動産賃貸収入 | C6: =PL!C6 -> 16633646 | D6: -16633646 | E6: =C6+D6 -> 0 | F6: =PL!E6 -> 16832410 | G6: -16832410 | H6: =F6+G6 -> 0 | I6: =PL!G6 -> 1635396 | J6: -1635396 | K6: =I6+J6 -> 0 | N6: =L6+M6 -> 0 | Q6: =O6+P6 -> 0
B7: 不動産売却収入 | C7: =PL!C7 -> 0 | D7: 0 | E7: =C7+D7 -> 0 | F7: =PL!E7 -> 869200000 | G7: -869200000 | H7: =F7+G7 -> 0 | I7: =PL!G7 -> 0 | J7: 0 | K7: =I7+J7 -> 0 | N7: =L7+M7 -> 0 | Q7: =O7+P7 -> 0
B8: コンサル収入 | C8: =PL!C8 -> 0 | D8: 0 | E8: =C8+D8 -> 0 | F8: =PL!E8 -> 0 | G8: 0 | H8: =F8+G8 -> 0 | I8: =PL!G8 -> 14000000 | J8: -14000000 | K8: =I8+J8 -> 0 | N8: =L8+M8 -> 0 | Q8: =O8+P8 -> 0
B9: 売上高 | C9: =SUM(C5:C8) -> 383439251 | D9: =SUM(D5:D8) -> -16633646 | E9: =C9+D9 -> 366805605 | F9: =SUM(F5:F8) -> 1230829971 | G9: =SUM(G5:G8) -> -886032410 | H9: =F9+G9 -> 344797561 | I9: =SUM(I5:I8) -> 319338374 | J9: =SUM(J5:J8) -> -15635396 | K9: =I9+J9 -> 303702978 | L9: =SUM(L5:L8) -> 0 | M9: =SUM(M5:M8) -> 0 | N9: =L9+M9 -> 0 | O9: =SUM(O5:O8) -> 0 | P9: =SUM(P5:P8) -> 0 | Q9: =O9+P9 -> 0
B10: 期首商品棚卸高 | C10: =PL!C12 -> 7732842 | E10: =C10+D10 -> 7732842 | F10: =PL!E12 -> 8732000 | H10: =F10+G10 -> 8732000 | I10: =PL!G12 -> 8732000 | K10: =I10+J10 -> 8732000 | N10: =L10+M10 -> 0 | Q10: =O10+P10 -> 0
B11: 当期商品仕入高 | C11: =PL!C13 -> 105841625 | E11: =C11+D11 -> 105841625 | F11: =PL!E13 -> 100866136 | H11: =F11+G11 -> 100866136 | I11: =PL!G13 -> 96006124 | K11: =I11+J11 -> 96006124 | N11: =L11+M11 -> 0 | Q11: =O11+P11 -> 0
B12: 不動産売却関連原価 | C12: =PL!C14 -> 0 | D12: 0 | E12: =C12+D12 -> 0 | F12: =PL!E14 -> 636056000 | G12: -636056000 | H12: =F12+G12 -> 0 | I12: =PL!G14 -> 0 | J12: 0 | K12: =I12+J12 -> 0 | N12: =L12+M12 -> 0 | Q12: =O12+P12 -> 0
B13: 期末商品棚卸高 | C13: =PL!C15 -> -8732000 | E13: =C13+D13 -> -8732000 | F13: =PL!E15 -> -8732000 | H13: =F13+G13 -> -8732000 | I13: =PL!G15 -> -8532000 | K13: =I13+J13 -> -8532000 | N13: =L13+M13 -> 0 | Q13: =O13+P13 -> 0
B14: 売上原価 | C14: =SUM(C10:C13) -> 104842467 | D14: =SUM(D10:D13) -> 0 | E14: =C14+D14 -> 104842467 | F14: =SUM(F10:F13) -> 736922136 | G14: =SUM(G10:G13) -> -636056000 | H14: =F14+G14 -> 100866136 | I14: =SUM(I10:I13) -> 96206124 | J14: =SUM(J10:J13) -> 0 | K14: =I14+J14 -> 96206124 | L14: =SUM(L10:L13) -> 0 | M14: =SUM(M10:M13) -> 0 | N14: =L14+M14 -> 0 | O14: =SUM(O10:O13) -> 0 | P14: =SUM(P10:P13) -> 0 | Q14: =O14+P14 -> 0
B15: 売上総利益 | C15: =C9-C14 -> 278596784 | D15: =D9-D14 -> -16633646 | E15: =C15+D15 -> 261963138 | F15: =F9-F14 -> 493907835 | G15: =G9-G14 -> -249976410 | H15: =F15+G15 -> 243931425 | I15: =I9-I14 -> 223132250 | J15: =J9-J14 -> -15635396 | K15: =I15+J15 -> 207496854 | L15: =L9-L14 -> 0 | M15: =M9-M14 -> 0 | N15: =L15+M15 -> 0 | O15: =O9-O14 -> 0 | P15: =P9-P14 -> 0 | Q15: =O15+P15 -> 0
B16: 販売費及び一般管理費 | C16: =PL!C18 -> 283551728 | D16: ='修正SGA'!D39 -> -4347132 | E16: =C16+D16 -> 279204596 | F16: =PL!E18 -> 273060341 | G16: ='修正SGA'!G39 -> -1928280 | H16: =F16+G16 -> 271132061 | I16: =PL!G18 -> 222261444 | J16: ='修正SGA'!J39 -> -686448 | K16: =I16+J16 -> 221574996 | N16: =L16+M16 -> 0 | Q16: =O16+P16 -> 0
B17: 営業利益 | C17: =C15- C16 -> -4954944 | D17: =D15- D16 -> -12286514 | E17: =C17+D17 -> -17241458 | F17: =F15- F16 -> 220847494 | G17: =G15- G16 -> -248048130 | H17: =F17+G17 -> -27200636 | I17: =I15- I16 -> 870806 | J17: =J15- J16 -> -14948948 | K17: =I17+J17 -> -14078142 | L17: =L15- L16 -> 0 | M17: =M15- M16 -> 0 | N17: =L17+M17 -> 0 | O17: =O15- O16 -> 0 | P17: =P15- P16 -> 0 | Q17: =O17+P17 -> 0
B18: 営業外収益 | C18: =SUM(C19:C23) -> 416337 | D18: =SUM(D19:D23) -> 0 | E18: =C18+D18 -> 416337 | F18: =SUM(F19:F23) -> 2887886 | G18: =SUM(G19:G23) -> 0 | H18: =F18+G18 -> 2887886 | I18: =SUM(I19:I23) -> 2924950 | J18: =SUM(J19:J23) -> 0 | K18: =I18+J18 -> 2924950 | L18: =SUM(L19:L23) -> 0 | M18: =SUM(M19:M23) -> 0 | N18: =L18+M18 -> 0 | O18: =SUM(O19:O23) -> 0 | P18: =SUM(P19:P23) -> 0 | Q18: =O18+P18 -> 0
B19: 受取利息 | C19: =PL!C21 -> 1507 | E19: =C19+D19 -> 1507 | F19: =PL!E21 -> 7617 | H19: =F19+G19 -> 7617 | I19: =PL!G21 -> 618278 | K19: =I19+J19 -> 618278 | N19: =L19+M19 -> 0 | Q19: =O19+P19 -> 0
B20: 雑収入 | C20: =PL!C22 -> 414830 | E20: =C20+D20 -> 414830 | F20: =PL!E22 -> 2880269 | H20: =F20+G20 -> 2880269 | I20: =PL!G22 -> 2306672 | K20: =I20+J20 -> 2306672 | N20: =L20+M20 -> 0 | Q20: =O20+P20 -> 0
E21: =C21+D21 -> 0 | H21: =F21+G21 -> 0 | K21: =I21+J21 -> 0 | N21: =L21+M21 -> 0 | Q21: =O21+P21 -> 0
E22: =C22+D22 -> 0 | H22: =F22+G22 -> 0 | K22: =I22+J22 -> 0 | N22: =L22+M22 -> 0 | Q22: =O22+P22 -> 0
E23: =C23+D23 -> 0 | H23: =F23+G23 -> 0 | K23: =I23+J23 -> 0 | N23: =L23+M23 -> 0 | Q23: =O23+P23 -> 0
B24: 営業外費用 | C24: =SUM(C25:C29) -> 2751745 | D24: =SUM(D25:D29) -> 0 | E24: =C24+D24 -> 2751745 | F24: =SUM(F25:F29) -> 12167614 | G24: =SUM(G25:G29) -> 0 | H24: =F24+G24 -> 12167614 | I24: =SUM(I25:I29) -> 3215177 | J24: =SUM(J25:J29) -> 0 | K24: =I24+J24 -> 3215177 | L24: =SUM(L25:L29) -> 0 | M24: =SUM(M25:M29) -> 0 | N24: =L24+M24 -> 0 | O24: =SUM(O25:O29) -> 0 | P24: =SUM(P25:P29) -> 0 | Q24: =O24+P24 -> 0
B25: 支払利息 | C25: =PL!C29 -> 2647993 | E25: =C25+D25 -> 2647993 | F25: =PL!E29 -> 3319038 | H25: =F25+G25 -> 3319038 | I25: =PL!G29 -> 3189615 | K25: =I25+J25 -> 3189615 | N25: =L25+M25 -> 0 | Q25: =O25+P25 -> 0
B26: 雑損失 | C26: =PL!C30 -> 103752 | E26: =C26+D26 -> 103752 | F26: =PL!E30 -> 8848576 | H26: =F26+G26 -> 8848576 | I26: =PL!G30 -> 25562 | K26: =I26+J26 -> 25562 | N26: =L26+M26 -> 0 | Q26: =O26+P26 -> 0
E27: =C27+D27 -> 0 | H27: =F27+G27 -> 0 | K27: =I27+J27 -> 0 | N27: =L27+M27 -> 0 | Q27: =O27+P27 -> 0
E28: =C28+D28 -> 0 | H28: =F28+G28 -> 0 | K28: =I28+J28 -> 0 | N28: =L28+M28 -> 0 | Q28: =O28+P28 -> 0
E29: =C29+D29 -> 0 | H29: =F29+G29 -> 0 | K29: =I29+J29 -> 0 | N29: =L29+M29 -> 0 | Q29: =O29+P29 -> 0
B30: 経常利益 | C30: =C17+C18-C24 -> -7290352 | D30: =D17+D18-D24 -> -12286514 | E30: =C30+D30 -> -19576866 | F30: =F17+F18-F24 -> 211567766 | G30: =G17+G18-G24 -> -248048130 | H30: =F30+G30 -> -36480364 | I30: =I17+I18-I24 -> 580579 | J30: =J17+J18-J24 -> -14948948 | K30: =I30+J30 -> -14368369 | L30: =L17+L18-L24 -> 0 | M30: =M17+M18-M24 -> 0 | N30: =L30+M30 -> 0 | O30: =O17+O18-O24 -> 0 | P30: =P17+P18-P24 -> 0 | Q30: =O30+P30 -> 0
B31: 特別利益 | C31: =SUM(C32:C35) -> 0 | D31: =SUM(D32:D35) -> 0 | E31: =C31+D31 -> 0 | F31: =SUM(F32:F35) -> 0 | G31: =SUM(G32:G35) -> 0 | H31: =F31+G31 -> 0 | I31: =SUM(I32:I35) -> 0 | J31: =SUM(J32:J35) -> 0 | K31: =I31+J31 -> 0 | L31: =SUM(L32:L35) -> 0 | M31: =SUM(M32:M35) -> 0 | N31: =L31+M31 -> 0 | O31: =SUM(O32:O35) -> 0 | P31: =SUM(P32:P35) -> 0 | Q31: =O31+P31 -> 0
B32: 貸倒引当金戻入額 | E32: =C32+D32 -> 0 | H32: =F32+G32 -> 0 | K32: =I32+J32 -> 0 | N32: =L32+M32 -> 0 | Q32: =O32+P32 -> 0
B33: 補助金収入 | E33: =C33+D33 -> 0 | H33: =F33+G33 -> 0 | K33: =I33+J33 -> 0 | N33: =L33+M33 -> 0 | Q33: =O33+P33 -> 0
E34: =C34+D34 -> 0 | H34: =F34+G34 -> 0 | K34: =I34+J34 -> 0 | N34: =L34+M34 -> 0 | Q34: =O34+P34 -> 0
E35: =C35+D35 -> 0 | H35: =F35+G35 -> 0 | K35: =I35+J35 -> 0 | N35: =L35+M35 -> 0 | Q35: =O35+P35 -> 0
B36: 特別損失 | C36: =SUM(C37:C40) -> 0 | D36: =SUM(D37:D40) -> 0 | E36: =C36+D36 -> 0 | F36: =SUM(F37:F40) -> 81258050 | G36: =SUM(G37:G40) -> 0 | H36: =F36+G36 -> 81258050 | I36: =SUM(I37:I40) -> 0 | J36: =SUM(J37:J40) -> 0 | K36: =I36+J36 -> 0 | L36: =SUM(L37:L40) -> 0 | M36: =SUM(M37:M40) -> 0 | N36: =L36+M36 -> 0 | O36: =SUM(O37:O40) -> 0 | P36: =SUM(P37:P40) -> 0 | Q36: =O36+P36 -> 0
B37: 固定資産除却損 | C37: =PL!C45 -> 0 | E37: =C37+D37 -> 0 | F37: =PL!E45 -> 81258050 | H37: =F37+G37 -> 81258050 | I37: =PL!G45 -> 0 | K37: =I37+J37 -> 0 | N37: =L37+M37 -> 0 | Q37: =O37+P37 -> 0
B38: 役員死亡退職慰労金 | E38: =C38+D38 -> 0 | H38: =F38+G38 -> 0 | K38: =I38+J38 -> 0 | N38: =L38+M38 -> 0 | Q38: =O38+P38 -> 0
E39: =C39+D39 -> 0 | H39: =F39+G39 -> 0 | K39: =I39+J39 -> 0 | N39: =L39+M39 -> 0 | Q39: =O39+P39 -> 0
E40: =C40+D40 -> 0 | H40: =F40+G40 -> 0 | K40: =I40+J40 -> 0 | N40: =L40+M40 -> 0 | Q40: =O40+P40 -> 0
B41: 税引前当期純利益 | C41: =C30+C31-C36 -> -7290352 | D41: =D30+D31-D36 -> -12286514 | E41: =C41+D41 -> -19576866 | F41: =F30+F31-F36 -> 130309716 | G41: =G30+G31-G36 -> -248048130 | H41: =F41+G41 -> -117738414 | I41: =I30+I31-I36 -> 580579 | J41: =J30+J31-J36 -> -14948948 | K41: =I41+J41 -> -14368369 | L41: =L30+L31-L36 -> 0 | M41: =M30+M31-M36 -> 0 | N41: =L41+M41 -> 0 | O41: =O30+O31-O36 -> 0 | P41: =P30+P31-P36 -> 0 | Q41: =O41+P41 -> 0
B42: 法人税等 | C42: =SUM(C43:C44) -> 194727 | D42: =SUM(D43:D44) -> 0 | E42: =C42+D42 -> 194727 | F42: =SUM(F43:F44) -> 21953358 | G42: =SUM(G43:G44) -> 0 | H42: =F42+G42 -> 21953358 | I42: =SUM(I43:I44) -> 48664083 | J42: =SUM(J43:J44) -> 0 | K42: =I42+J42 -> 48664083 | L42: =SUM(L43:L44) -> 0 | M42: =SUM(M43:M44) -> 0 | N42: =L42+M42 -> 0 | O42: =SUM(O43:O44) -> 0 | P42: =SUM(P43:P44) -> 0 | Q42: =O42+P42 -> 0
B43: 法人税・住民税及び事業税（当期分） | C43: =PL!C53 -> 194727 | E43: =C43+D43 -> 194727 | F43: =PL!E53 -> 21953358 | H43: =F43+G43 -> 21953358 | I43: =PL!G53 -> 289183 | K43: =I43+J43 -> 289183 | N43: =L43+M43 -> 0 | Q43: =O43+P43 -> 0
B44: 過年度法人税等 | C44: =PL!C54 -> 0 | E44: =C44+D44 -> 0 | F44: =PL!E54 -> 0 | H44: =F44+G44 -> 0 | I44: =PL!G54 -> 48374900 | K44: =I44+J44 -> 48374900 | N44: =L44+M44 -> 0 | Q44: =O44+P44 -> 0
B45: 税引後当期純利益 | C45: =C41-C42 -> -7485079 | D45: =D41-D42 -> -12286514 | E45: =C45+D45 -> -19771593 | F45: =F41-F42 -> 108356358 | G45: =G41-G42 -> -248048130 | H45: =F45+G45 -> -139691772 | I45: =I41-I42 -> -48083504 | J45: =J41-J42 -> -14948948 | K45: =I45+J45 -> -63032452 | L45: =L41-L42 -> 0 | M45: =M41-M42 -> 0 | N45: =L45+M45 -> 0 | O45: =O41-O42 -> 0 | P45: =P41-P42 -> 0 | Q45: =O45+P45 -> 0
E46: =C46+D46 -> 0 | H46: =F46+G46 -> 0 | K46: =I46+J46 -> 0 | N46: =L46+M46 -> 0 | Q46: =O46+P46 -> 0
E47: =C47+D47 -> 0 | H47: =F47+G47 -> 0 | K47: =I47+J47 -> 0 | N47: =L47+M47 -> 0 | Q47: =O47+P47 -> 0
E48: =C48+D48 -> 0 | H48: =F48+G48 -> 0 | K48: =I48+J48 -> 0 | N48: =L48+M48 -> 0 | Q48: =O48+P48 -> 0
E49: =C49+D49 -> 0 | H49: =F49+G49 -> 0 | K49: =I49+J49 -> 0 | N49: =L49+M49 -> 0 | Q49: =O49+P49 -> 0
E50: =C50+D50 -> 0 | H50: =F50+G50 -> 0 | K50: =I50+J50 -> 0 | N50: =L50+M50 -> 0 | Q50: =O50+P50 -> 0
E51: =C51+D51 -> 0 | H51: =F51+G51 -> 0 | K51: =I51+J51 -> 0 | N51: =L51+M51 -> 0 | Q51: =O51+P51 -> 0
E52: =C52+D52 -> 0 | H52: =F52+G52 -> 0 | K52: =I52+J52 -> 0 | N52: =L52+M52 -> 0 | Q52: =O52+P52 -> 0
E53: =C53+D53 -> 0 | H53: =F53+G53 -> 0 | K53: =I53+J53 -> 0 | N53: =L53+M53 -> 0 | Q53: =O53+P53 -> 0
E54: =C54+D54 -> 0 | H54: =F54+G54 -> 0 | K54: =I54+J54 -> 0 | N54: =L54+M54 -> 0 | Q54: =O54+P54 -> 0
E55: =C55+D55 -> 0 | H55: =F55+G55 -> 0 | K55: =I55+J55 -> 0 | N55: =L55+M55 -> 0 | Q55: =O55+P55 -> 0
E56: =C56+D56 -> 0 | H56: =F56+G56 -> 0 | K56: =I56+J56 -> 0 | N56: =L56+M56 -> 0 | Q56: =O56+P56 -> 0
E57: =C57+D57 -> 0 | H57: =F57+G57 -> 0 | K57: =I57+J57 -> 0 | N57: =L57+M57 -> 0 | Q57: =O57+P57 -> 0
... E67: =C67+D67 -> 0 | H67: =F67+G67 -> 0 | K67: =I67+J67 -> 0 | N67: =L67+M67 -> 0 | Q67: =O67+P67 -> 0

Sheet 修正SGA
K2: (単位：千円)
B3: 科目 | C3: ='BS(借方)'!C4 -> 令和6年3月期 | F3: ='BS(借方)'!D4 -> 令和7年3月期 | I3: ='BS(借方)'!E4 -> 令和8年3月期 | L3: ='BS(借方)'!F4 -> － | O3: ='BS(借方)'!G4 -> 進行期 （試算表未受領）
C4: 帳簿価額 | D4: 修正額 | E4: 修正後 | F4: 帳簿価額 | G4: 修正額 | H4: 修正後 | I4: 帳簿価額 | J4: 修正額 | K4: 修正後 | L4: 帳簿価額 | M4: 修正額 | N4: 修正後 | O4: 帳簿価額 | P4: 修正額 | Q4: 修正後
B5: 役員報酬 | C5: =SGA!C6 -> 1920000 | E5: =C5+D5 -> 1920000 | F5: =SGA!E6 -> 1920000 | H5: =F5+G5 -> 1920000 | I5: =SGA!G6 -> 1920000 | K5: =I5+J5 -> 1920000 | N5: =L5+M5 -> 0 | Q5: =O5+P5 -> 0
B6: 給料手当 | C6: =SGA!C7 -> 137394789 | E6: =C6+D6 -> 137394789 | F6: =SGA!E7 -> 111145074 | H6: =F6+G6 -> 111145074 | I6: =SGA!G7 -> 113155654 | K6: =I6+J6 -> 113155654 | N6: =L6+M6 -> 0 | Q6: =O6+P6 -> 0
B7: 法定福利費 | C7: =SGA!C8 -> 21065176 | E7: =C7+D7 -> 21065176 | F7: =SGA!E8 -> 14045855 | H7: =F7+G7 -> 14045855 | I7: =SGA!G8 -> 18258884 | K7: =I7+J7 -> 18258884 | N7: =L7+M7 -> 0 | Q7: =O7+P7 -> 0
B8: 荷造運賃 | C8: =SGA!C9 -> 893478 | E8: =C8+D8 -> 893478 | F8: =SGA!E9 -> 813145 | H8: =F8+G8 -> 813145 | I8: =SGA!G9 -> 654125 | K8: =I8+J8 -> 654125 | N8: =L8+M8 -> 0 | Q8: =O8+P8 -> 0
B9: 減価償却費 | C9: =SGA!C10 -> 4594828 | E9: =C9+D9 -> 4594828 | F9: =SGA!E10 -> 14219250 | H9: =F9+G9 -> 14219250 | I9: =SGA!G10 -> 11895803 | K9: =I9+J9 -> 11895803 | N9: =L9+M9 -> 0 | Q9: =O9+P9 -> 0
B10: 地代家賃 | C10: =SGA!C11 -> 14896364 | E10: =C10+D10 -> 14896364 | F10: =SGA!E11 -> 17605421 | H10: =F10+G10 -> 17605421 | I10: =SGA!G11 -> 21688139 | K10: =I10+J10 -> 21688139 | N10: =L10+M10 -> 0 | Q10: =O10+P10 -> 0
B11: 修繕費 | C11: =SGA!C12 -> 4820065 | E11: =C11+D11 -> 4820065 | F11: =SGA!E12 -> 12667849 | H11: =F11+G11 -> 12667849 | I11: =SGA!G12 -> 349720 | K11: =I11+J11 -> 349720 | N11: =L11+M11 -> 0 | Q11: =O11+P11 -> 0
B12: 事務用品費 | C12: =SGA!C13 -> 0 | E12: =C12+D12 -> 0 | F12: =SGA!E13 -> 0 | H12: =F12+G12 -> 0 | I12: =SGA!G13 -> 0 | K12: =I12+J12 -> 0 | N12: =L12+M12 -> 0 | Q12: =O12+P12 -> 0
B13: 消耗品費 | C13: =SGA!C14 -> 8665567 | E13: =C13+D13 -> 8665567 | F13: =SGA!E14 -> 3622074 | H13: =F13+G13 -> 3622074 | I13: =SGA!G14 -> 3114486 | K13: =I13+J13 -> 3114486 | N13: =L13+M13 -> 0 | Q13: =O13+P13 -> 0
B14: 水道光熱費 | C14: =SGA!C15 -> 12094761 | E14: =C14+D14 -> 12094761 | F14: =SGA!E15 -> 7886267 | H14: =F14+G14 -> 7886267 | I14: =SGA!G15 -> 8256277 | K14: =I14+J14 -> 8256277 | N14: =L14+M14 -> 0 | Q14: =O14+P14 -> 0
B15: 旅費交通費 | C15: =SGA!C16 -> 4459042 | E15: =C15+D15 -> 4459042 | F15: =SGA!E16 -> 13621116 | H15: =F15+G15 -> 13621116 | I15: =SGA!G16 -> 6127921 | K15: =I15+J15 -> 6127921 | N15: =L15+M15 -> 0 | Q15: =O15+P15 -> 0
B16: 支払手数料 | C16: =SGA!C17 -> 26496901 | E16: =C16+D16 -> 26496901 | F16: =SGA!E17 -> 25381508 | H16: =F16+G16 -> 25381508 | I16: =SGA!G17 -> 13893115 | K16: =I16+J16 -> 13893115 | N16: =L16+M16 -> 0 | Q16: =O16+P16 -> 0
... B31: 採用教育費 | C31: =SGA!C32 -> 45273 | E31: =C31+D31 -> 45273 | F31: =SGA!E32 -> 0 | H31: =F31+G31 -> 0 | I31: =SGA!G32 -> 0 | K31: =I31+J31 -> 0 | N31: =L31+M31 -> 0 | Q31: =O31+P31 -> 0
B32: 不動産管理費 | C32: =SGA!C33 -> 4347132 | D32: -4347132 | E32: =C32+D32 -> 0 | F32: =SGA!E33 -> 1928280 | G32: -1928280 | H32: =F32+G32 -> 0 | I32: =SGA!G33 -> 686448 | J32: -686448 | K32: =I32+J32 -> 0 | N32: =L32+M32 -> 0 | Q32: =O32+P32 -> 0
B33: リース料 | C33: =SGA!C34 -> 13797260 | E33: =C33+D33 -> 13797260 | F33: =SGA!E34 -> 10744470 | H33: =F33+G33 -> 10744470 | I33: =SGA!G34 -> 10212056 | K33: =I33+J33 -> 10212056 | N33: =L33+M33 -> 0 | Q33: =O33+P33 -> 0
B34: 寄付金 | C34: =SGA!C35 -> 0 | E34: =C34+D34 -> 0 | F34: =SGA!E35 -> 500 | H34: =F34+G34 -> 500 | I34: =SGA!G35 -> 0 | K34: =I34+J34 -> 0 | N34: =L34+M34 -> 0 | Q34: =O34+P34 -> 0
E35: =C35+D35 -> 0 | H35: =F35+G35 -> 0 | K35: =I35+J35 -> 0 | N35: =L35+M35 -> 0 | Q35: =O35+P35 -> 0
E36: =C36+D36 -> 0 | H36: =F36+G36 -> 0 | K36: =I36+J36 -> 0 | N36: =L36+M36 -> 0 | Q36: =O36+P36 -> 0
E37: =C37+D37 -> 0 | H37: =F37+G37 -> 0 | K37: =I37+J37 -> 0 | N37: =L37+M37 -> 0 | Q37: =O37+P37 -> 0
E38: =C38+D38 -> 0 | H38: =F38+G38 -> 0 | K38: =I38+J38 -> 0 | N38: =L38+M38 -> 0 | Q38: =O38+P38 -> 0
B39: 販売費および一般管理費合計 | C39: =SUM(C5:C38) -> 283551728 | D39: =SUM(D5:D38) -> -4347132 | E39: =C39+D39 -> 279204596 | F39: =SUM(F5:F38) -> 273060341 | G39: =SUM(G5:G38) -> -1928280 | H39: =F39+G39 -> 271132061 | I39: =SUM(I5:I38) -> 222261444 | J39: =SUM(J5:J38) -> -686448 | K39: =I39+J39 -> 221574996 | L39: =SUM(L5:L38) -> 0 | M39: =SUM(M5:M38) -> 0 | N39: =L39+M39 -> 0 | O39: =SUM(O5:O38) -> 0 | P39: =SUM(P5:P38) -> 0 | Q39: =O39+P39 -> 0

Sheet 修正CR
K2: (単位：千円)
B3: 科目 | C3: ='BS(借方)'!C4 -> 令和6年3月期 | F3: ='BS(借方)'!D4 -> 令和7年3月期 | I3: ='BS(借方)'!E4 -> 令和8年3月期 | L3: ='BS(借方)'!F4 -> － | O3: ='BS(借方)'!G4 -> 進行期 （試算表未受領）
C4: 帳簿価額 | D4: 修正額 | E4: 修正後 | F4: 帳簿価額 | G4: 修正額 | H4: 修正後 | I4: 帳簿価額 | J4: 修正額 | K4: 修正後 | L4: 帳簿価額 | M4: 修正額 | N4: 修正後 | O4: 帳簿価額 | P4: 修正額 | Q4: 修正後
B5: 期首原材料棚卸高 | E5: =C5+D5 -> 0 | H5: =F5+G5 -> 0 | K5: =I5+J5 -> 0 | N5: =L5+M5 -> 0 | Q5: =O5+P5 -> 0
B6: 原材料仕入高 | E6: =C6+D6 -> 0 | H6: =F6+G6 -> 0 | K6: =I6+J6 -> 0 | N6: =L6+M6 -> 0 | Q6: =O6+P6 -> 0
B7: 小計 | E7: =C7+D7 -> 0 | H7: =F7+G7 -> 0 | K7: =I7+J7 -> 0 | N7: =L7+M7 -> 0 | Q7: =O7+P7 -> 0
B8: 期末原材料棚卸高 | E8: =C8+D8 -> 0 | H8: =F8+G8 -> 0 | K8: =I8+J8 -> 0 | N8: =L8+M8 -> 0 | Q8: =O8+P8 -> 0
E9: =C9+D9 -> 0 | H9: =F9+G9 -> 0 | K9: =I9+J9 -> 0 | N9: =L9+M9 -> 0 | Q9: =O9+P9 -> 0
E10: =C10+D10 -> 0 | H10: =F10+G10 -> 0 | K10: =I10+J10 -> 0 | N10: =L10+M10 -> 0 | Q10: =O10+P10 -> 0
B11: 材料費 | C11: =SUM(C5:C10) -> 0 | D11: =SUM(D5:D10) -> 0 | E11: =C11+D11 -> 0 | F11: =SUM(F5:F10) -> 0 | G11: =SUM(G5:G10) -> 0 | H11: =F11+G11 -> 0 | I11: =SUM(I5:I10) -> 0 | J11: =SUM(J5:J10) -> 0 | K11: =I11+J11 -> 0 | L11: =SUM(L5:L10) -> 0 | M11: =SUM(M5:M10) -> 0 | N11: =L11+M11 -> 0 | O11: =SUM(O5:O10) -> 0 | P11: =SUM(P5:P10) -> 0 | Q11: =O11+P11 -> 0
E12: =C12+D12 -> 0 | H12: =F12+G12 -> 0 | K12: =I12+J12 -> 0 | N12: =L12+M12 -> 0 | Q12: =O12+P12 -> 0
E13: =C13+D13 -> 0 | H13: =F13+G13 -> 0 | K13: =I13+J13 -> 0 | N13: =L13+M13 -> 0 | Q13: =O13+P13 -> 0
E14: =C14+D14 -> 0 | H14: =F14+G14 -> 0 | K14: =I14+J14 -> 0 | N14: =L14+M14 -> 0 | Q14: =O14+P14 -> 0
E15: =C15+D15 -> 0 | H15: =F15+G15 -> 0 | K15: =I15+J15 -> 0 | N15: =L15+M15 -> 0 | Q15: =O15+P15 -> 0
E16: =C16+D16 -> 0 | H16: =F16+G16 -> 0 | K16: =I16+J16 -> 0 | N16: =L16+M16 -> 0 | Q16: =O16+P16 -> 0
E17: =C17+D17 -> 0 | H17: =F17+G17 -> 0 | K17: =I17+J17 -> 0 | N17: =L17+M17 -> 0 | Q17: =O17+P17 -> 0
B18: 労務費 | C18: =SUM(C12:C17) -> 0 | D18: =SUM(D12:D17) -> 0 | E18: =C18+D18 -> 0 | F18: =SUM(F12:F17) -> 0 | G18: =SUM(G12:G17) -> 0 | H18: =F18+G18 -> 0 | I18: =SUM(I12:I17) -> 0 | J18: =SUM(J12:J17) -> 0 | K18: =I18+J18 -> 0 | L18: =SUM(L12:L17) -> 0 | M18: =SUM(M12:M17) -> 0 | N18: =L18+M18 -> 0 | O18: =SUM(O12:O17) -> 0 | P18: =SUM(P12:P17) -> 0 | Q18: =O18+P18 -> 0
E19: =C19+D19 -> 0 | H19: =F19+G19 -> 0 | K19: =I19+J19 -> 0 | N19: =L19+M19 -> 0 | Q19: =O19+P19 -> 0
E20: =C20+D20 -> 0 | H20: =F20+G20 -> 0 | K20: =I20+J20 -> 0 | N20: =L20+M20 -> 0 | Q20: =O20+P20 -> 0
E21: =C21+D21 -> 0 | H21: =F21+G21 -> 0 | K21: =I21+J21 -> 0 | N21: =L21+M21 -> 0 | Q21: =O21+P21 -> 0
E22: =C22+D22 -> 0 | H22: =F22+G22 -> 0 | K22: =I22+J22 -> 0 | N22: =L22+M22 -> 0 | Q22: =O22+P22 -> 0
E23: =C23+D23 -> 0 | H23: =F23+G23 -> 0 | K23: =I23+J23 -> 0 | N23: =L23+M23 -> 0 | Q23: =O23+P23 -> 0
E24: =C24+D24 -> 0 | H24: =F24+G24 -> 0 | K24: =I24+J24 -> 0 | N24: =L24+M24 -> 0 | Q24: =O24+P24 -> 0
B25: 外注加工費 | C25: =SUM(C19:C24) -> 0 | D25: =SUM(D19:D24) -> 0 | E25: =C25+D25 -> 0 | F25: =SUM(F19:F24) -> 0 | G25: =SUM(G19:G24) -> 0 | H25: =F25+G25 -> 0 | I25: =SUM(I19:I24) -> 0 | J25: =SUM(J19:J24) -> 0 | K25: =I25+J25 -> 0 | L25: =SUM(L19:L24) -> 0 | M25: =SUM(M19:M24) -> 0 | N25: =L25+M25 -> 0 | O25: =SUM(O19:O24) -> 0 | P25: =SUM(P19:P24) -> 0 | Q25: =O25+P25 -> 0
E26: =C26+D26 -> 0 | H26: =F26+G26 -> 0 | K26: =I26+J26 -> 0 | N26: =L26+M26 -> 0 | Q26: =O26+P26 -> 0
E27: =C27+D27 -> 0 | H27: =F27+G27 -> 0 | K27: =I27+J27 -> 0 | N27: =L27+M27 -> 0 | Q27: =O27+P27 -> 0
E28: =C28+D28 -> 0 | H28: =F28+G28 -> 0 | K28: =I28+J28 -> 0 | N28: =L28+M28 -> 0 | Q28: =O28+P28 -> 0
E29: =C29+D29 -> 0 | H29: =F29+G29 -> 0 | K29: =I29+J29 -> 0 | N29: =L29+M29 -> 0 | Q29: =O29+P29 -> 0
E30: =C30+D30 -> 0 | H30: =F30+G30 -> 0 | K30: =I30+J30 -> 0 | N30: =L30+M30 -> 0 | Q30: =O30+P30 -> 0
E31: =C31+D31 -> 0 | H31: =F31+G31 -> 0 | K31: =I31+J31 -> 0 | N31: =L31+M31 -> 0 | Q31: =O31+P31 -> 0
E32: =C32+D32 -> 0 | H32: =F32+G32 -> 0 | K32: =I32+J32 -> 0 | N32: =L32+M32 -> 0 | Q32: =O32+P32 -> 0
E33: =C33+D33 -> 0 | H33: =F33+G33 -> 0 | K33: =I33+J33 -> 0 | N33: =L33+M33 -> 0 | Q33: =O33+P33 -> 0
E34: =C34+D34 -> 0 | H34: =F34+G34 -> 0 | K34: =I34+J34 -> 0 | N34: =L34+M34 -> 0 | Q34: =O34+P34 -> 0
E35: =C35+D35 -> 0 | H35: =F35+G35 -> 0 | K35: =I35+J35 -> 0 | N35: =L35+M35 -> 0 | Q35: =O35+P35 -> 0
B36: 経費 | C36: =SUM(C26:C35) -> 0 | D36: =SUM(D26:D35) -> 0 | E36: =C36+D36 -> 0 | F36: =SUM(F26:F35) -> 0 | G36: =SUM(G26:G35) -> 0 | H36: =F36+G36 -> 0 | I36: =SUM(I26:I35) -> 0 | J36: =SUM(J26:J35) -> 0 | K36: =I36+J36 -> 0 | L36: =SUM(L26:L35) -> 0 | M36: =SUM(M26:M35) -> 0 | N36: =L36+M36 -> 0 | O36: =SUM(O26:O35) -> 0 | P36: =SUM(P26:P35) -> 0 | Q36: =O36+P36 -> 0
B37: 当期製造費用 | C37: =C11+C18+C25+C36 -> 0 | D37: =D11+D18+D25+D36 -> 0 | E37: =C37+D37 -> 0 | F37: =F11+F18+F25+F36 -> 0 | G37: =G11+G18+G25+G36 -> 0 | H37: =F37+G37 -> 0 | I37: =I11+I18+I25+I36 -> 0 | J37: =J11+J18+J25+J36 -> 0 | K37: =I37+J37 -> 0 | L37: =L11+L18+L25+L36 -> 0 | M37: =M11+M18+M25+M36 -> 0 | N37: =L37+M37 -> 0 | O37: =O11+O18+O25+O36 -> 0 | P37: =P11+P18+P25+P36 -> 0 | Q37: =O37+P37 -> 0
B38: 期首仕掛品棚卸高 | E38: =C38+D38 -> 0 | H38: =F38+G38 -> 0 | K38: =I38+J38 -> 0 | N38: =L38+M38 -> 0 | Q38: =O38+P38 -> 0
B39: 合計 | C39: =SUM(C37:C38) -> 0 | D39: =SUM(D37:D38) -> 0 | E39: =C39+D39 -> 0 | F39: =SUM(F37:F38) -> 0 | G39: =SUM(G37:G38) -> 0 | H39: =F39+G39 -> 0 | I39: =SUM(I37:I38) -> 0 | J39: =SUM(J37:J38) -> 0 | K39: =I39+J39 -> 0 | L39: =SUM(L37:L38) -> 0 | M39: =SUM(M37:M38) -> 0 | N39: =L39+M39 -> 0 | O39: =SUM(O37:O38) -> 0 | P39: =SUM(P37:P38) -> 0 | Q39: =O39+P39 -> 0
B40: 期末仕掛品棚卸高 | E40: =C40+D40 -> 0 | H40: =F40+G40 -> 0 | K40: =I40+J40 -> 0 | N40: =L40+M40 -> 0 | Q40: =O40+P40 -> 0
B41: 当期製造原価 | C41: =C39-C40 -> 0 | D41: =D39-D40 -> 0 | E41: =C41+D41 -> 0 | F41: =F39-F40 -> 0 | G41: =G39-G40 -> 0 | H41: =F41+G41 -> 0 | I41: =I39-I40 -> 0 | J41: =J39-J40 -> 0 | K41: =I41+J41 -> 0 | L41: =L39-L40 -> 0 | M41: =M39-M40 -> 0 | N41: =L41+M41 -> 0 | O41: =O39-O40 -> 0 | P41: =P39-P40 -> 0 | Q41: =O41+P41 -> 0

Sheet 年買法
C2: (単位：千円) | H2: (単位：千円) | M2: (単位：千円)
B3: ='BS(借方)'!E4 -> 令和8年3月期 | C3: 金額 | F3: ='BS(借方)'!C4 -> 令和6年3月期 | G3: ='BS(借方)'!D4 -> 令和7年3月期 | H3: ='BS(借方)'!E4 -> 令和8年3月期 | J3: 営業権倍率 | K3: x1 | L3: x2 | M3: x3
B4: 簿価純資産額 | C4: ='修正BS(貸方) '!C52 -> 326908762 | E4: 簿価営業利益 | F4: ='修正PL'!C17 -> -4954944 | G4: ='修正PL'!F17 -> 220847494 | H4: ='修正PL'!I17 -> 870806 | J4: 時価純資産 | K4: =C7 -> 320002051
B5: 修正額 | C5: ='修正BS(貸方) '!D50 -> -10464714 | E5: 修正額 | F5: ='修正PL'!D17 -> -12286514 | G5: ='修正PL'!G17 -> -248048130 | H5: ='修正PL'!J17 -> -14948948 | J5: 営業権 | K5: =MAX(0,H10*1) -> 0 | L5: =MAX(0,H10*2) -> 0 | M5: =MAX(0,H10*3) -> 0
B6: 税効果 | C6: ='修正BS(貸方) '!D51 -> 3558003 | E6: 修正後営業利益 | F6: =SUM(F4:F5) -> -17241458 | G6: =SUM(G4:G5) -> -27200636 | H6: =SUM(H4:H5) -> -14078142 | J6: 想定株式価値 | K6: =K4+K5 -> 320002051 | L6: =K4+L5 -> 320002051 | M6: =K4+M5 -> 320002051
B7: 時価純資産 | C7: =SUM(C4:C6) -> 320002051 | E7: 税考慮額 | F7: =-F6*0.34 -> 5862095.7 | G7: =-G6*0.34 -> 9248216.2 | H7: =-H6*0.34 -> 4786568.3
E8: 修正後税考慮後営業利益 | F8: =SUM(F6:F7) -> -11379362 | G8: =SUM(G6:G7) -> -17952420 | H8: =SUM(H6:H7) -> -9291573.7
G10: 基準営業利益 | H10: =(H8*0.5+G8*0.3+F8*0.2) -> -12307385
B12: ※基準営業利益がマイナスの場合、営業権は0（マイナスの営業権は計上しない）。
B13: ※修正後営業利益は修正PL（不動産売却・賃貸等の非継続損益、コンサル収入を除外）。新体制の役員報酬は未確認のため置換していない。

Sheet EV EBITDAマルチプル
C2: (単位：千円) | H2: (単位：千円) | M2: (単位：千円)
B3: ='BS(借方)'!E4 -> 令和8年3月期 | C3: 金額 | F3: ='BS(借方)'!C4 -> 令和6年3月期 | G3: ='BS(借方)'!D4 -> 令和7年3月期 | H3: ='BS(借方)'!E4 -> 令和8年3月期 | J3: マルチプル倍率 | K3: x3 | L3: x4 | M3: x5
B4: キャッシュライク | C4: ='ネットキャッシュ'!C13 -> 236935709 | E4: 簿価営業利益 | F4: ='修正PL'!C17 -> -4954944 | G4: ='修正PL'!F17 -> 220847494 | H4: ='修正PL'!I17 -> 870806 | J4: EV（EBITDA×倍率） | K4: =IF($H$10<=0,"算定不能",$H$10*3) -> 算定不能 | L4: =IF($H$10<=0,"算定不能",$H$10*4) -> 算定不能 | M4: =IF($H$10<=0,"算定不能",$H$10*5) -> 算定不能
B5: デットライク | C5: ='ネットキャッシュ'!F13 -> 445919806 | E5: 修正額 | F5: ='修正PL'!D17 -> -12286514 | G5: ='修正PL'!G17 -> -248048130 | H5: ='修正PL'!J17 -> -14948948 | J5: 非流動性ディスカウント | K5: =IF(ISNUMBER(K4),-K4*0.3,"－") -> － | L5: =IF(ISNUMBER(L4),-L4*0.3,"－") -> － | M5: =IF(ISNUMBER(M4),-M4*0.3,"－") -> －
B6: ネットキャッシュ | C6: =C4-C5 -> -208984097 | E6: 修正後営業利益 | F6: =SUM(F4:F5) -> -17241458 | G6: =SUM(G4:G5) -> -27200636 | H6: =SUM(H4:H5) -> -14078142 | J6: =B6 -> ネットキャッシュ | K6: =C6 -> -208984097
E7: 減価償却費 | F7: =SGA!C10 -> 4594828 | G7: =SGA!E10 -> 14219250 | H7: =SGA!G10 -> 11895803 | J7: 想定株式価値 | K7: =IF(ISNUMBER(K4),K4+K5+$K$6,"算定不能") -> 算定不能 | L7: =IF(ISNUMBER(L4),L4+L5+$K$6,"算定不能") -> 算定不能 | M7: =IF(ISNUMBER(M4),M4+M5+$K$6,"算定不能") -> 算定不能
E8: 修正後EBITDA | F8: =SUM(F6:F7) -> -12646630 | G8: =SUM(G6:G7) -> -12981386 | H8: =SUM(H6:H7) -> -2182339
G10: 基準EBITDA | H10: =(H8*0.5+G8*0.3+F8*0.2) -> -7514911.3
B12: ※基準EBITDAがマイナスのためEVは算定不能。ネットキャッシュのみの価値（参考）は評価結果に採用しない。

Sheet 参照企業
E2: (単位：千円)
B3: 企業名 | C3: 所在地 | D3: 事業内容 | E3: EV/EVIDA倍率
B4: （適用なし）正常EBITDAがマイナスのため、類似上場会社の倍率は適用していない。
D14: 平均値 | E14: =IFERROR(AVERAGE(E4:E13),"－") -> －
D15: 中央値 | E15: =IFERROR(MEDIAN(E4:E13),"－") -> －

Sheet IM→

Sheet 会社概要
B2: 項目 | C2: 内容
B3: 会社名 | C3: ウエスト・シークル株式会社
B4: 本社所在地 | C4: 神奈川県鎌倉市鎌倉山三丁目2番31号
B5: その他拠点 | C5: 紀尾井町店（東京都千代田区／賃借） 大船店（神奈川県鎌倉市／賃借） ※所在地の詳細は要確認。四谷店は令和6年3月期を最後に売上計上なし（閉店と推察・要確認）
B6: 設立/創業 | C6: 要確認（登記事項証明書未受領） ※鎌倉山店「ル・ミリュウ」は2010年開業（Web情報・要確認）
B7: 資本金 | C7: 500千円
B8: 代表者 | C8: 西丸 修（代表取締役）
B9: 株主 | C9: 西丸 修（100株/100％） ※法人税申告書 別表二（令和8年3月期）より。株主名簿は未受領・要確認
B10: 事業内容 | C10: フランス菓子・焼菓子・パン等の製造販売、併設カフェの運営（鎌倉山・紀尾井町・大船の3店舗）。Web情報では「ル・ミリュウ」「ラ・プレシューズ」を展開（要確認）
B11: 従業員数 | C11: 月給者6名・時給者約30名（2026年2月分給与台帳より推計）／役員1名（他の役員の有無は要確認）
B12: 許認可等 | C12: 要確認（営業許可証・菓子製造業許可等は未受領）
B13: 売上高 | C13: =TEXT(PL!G11/1000,"#,##0")&"千円（"&'BS(借方)'!E4&"）" -> 319,338千円（令和8年3月期）
B14: 調整後EBITDA | C14: =TEXT('PLハイライト'!E37/1000,"#,##0;△#,##0")&"千円（"&'BS(借方)'!E4&"）" -> △2,182千円（令和8年3月期）
B15: 譲渡理由 | C15: 要確認（オーナーヒアリング予定）

Sheet PLハイライト
E2: (単位：千円)
C3: ='BS(借方)'!C4 -> 令和6年3月期 | D3: ='BS(借方)'!D4 -> 令和7年3月期 | E3: ='BS(借方)'!E4 -> 令和8年3月期 | F3: ='BS(借方)'!F4 -> － | G3: ='BS(借方)'!G4 -> 進行期 （試算表未受領）
B4: 売上高 | C4: =PL!C11 -> 383439251 | D4: =PL!E11 -> 1230829971 | E4: =PL!G11 -> 319338374 | F4: =PL!I11 -> 0 | G4: =PL!K11 -> 0
B5: 前期比 | C5: - | D5: =IFERROR(D4/C4,"－") -> 3.2099739 | E5: =IFERROR(E4/D4,"－") -> 0.25944962 | F5: =IFERROR(F4/E4,"－") -> 0 | G5: -
B6: 売上総利益 | C6: =PL!C17 -> 278596784 | D6: =PL!E17 -> 493907835 | E6: =PL!G17 -> 223132250 | F6: =PL!I17 -> 0 | G6: =PL!K17 -> 0
B7: 利益率 | C7: =IFERROR(C6/C4,"－") -> 0.72657346 | D7: =IFERROR(D6/D4,"－") -> 0.40128031 | E7: =IFERROR(E6/E4,"－") -> 0.69873297 | F7: =IFERROR(F6/F4,"－") -> － | G7: =IFERROR(G6/G4,"－") -> －
B8: 営業利益 | C8: =PL!C19 -> -4954944 | D8: =PL!E19 -> 220847494 | E8: =PL!G19 -> 870806 | F8: =PL!I19 -> 0 | G8: =PL!K19 -> 0
B9: 利益率 | C9: =IFERROR(C8/C4,"－") -> -0.01292237 | D9: =IFERROR(D8/D4,"－") -> 0.17942973 | E9: =IFERROR(E8/E4,"－") -> 0.0027269069 | F9: =IFERROR(F8/F4,"－") -> － | G9: =IFERROR(G8/G4,"－") -> －
B10: 経常利益 | C10: =PL!C36 -> -7290352 | D10: =PL!E36 -> 211567766 | E10: =PL!G36 -> 580579 | F10: =PL!I36 -> 0 | G10: =PL!K36 -> 0
B11: 利益率 | C11: =IFERROR(C10/C4,"－") -> -0.019013056 | D11: =IFERROR(D10/D4,"－") -> 0.17189033 | E11: =IFERROR(E10/E4,"－") -> 0.0018180684 | F11: =IFERROR(F10/F4,"－") -> － | G11: =IFERROR(G10/G4,"－") -> －
B12: 税引後当期純利益 | C12: =PL!C56 -> -7485079 | D12: =PL!E56 -> 108356358 | E12: =PL!G56 -> -48083504 | F12: =PL!I56 -> 0 | G12: =PL!K56 -> 0
B13: 利益率 | C13: =IFERROR(C12/C4,"－") -> -0.019520899 | D13: =IFERROR(D12/D4,"－") -> 0.088035196 | E13: =IFERROR(E12/E4,"－") -> -0.15057227 | F13: =IFERROR(F12/F4,"－") -> － | G13: =IFERROR(G12/G4,"－") -> －
B15: 減価償却費 | C15: =SGA!C10 -> 4594828 | D15: =SGA!E10 -> 14219250 | E15: =SGA!G10 -> 11895803 | F15: 0 | G15: 0
B17: 調整項目 合計 | C17: =SUM(C18:C27) -> -12286514 | D17: =SUM(D18:D27) -> -248048130 | E17: =SUM(E18:E27) -> -14948948 | F17: =SUM(F18:F27) -> 0 | G17: =SUM(G18:G27) -> 0
B18: 不動産売却損益（非継続） | C18: ='修正PL'!D7-'修正PL'!D12 -> 0 | D18: ='修正PL'!G7-'修正PL'!G12 -> -233144000 | E18: ='修正PL'!J7-'修正PL'!J12 -> 0
B19: 不動産賃貸収入（非継続） | C19: ='修正PL'!D6 -> -16633646 | D19: ='修正PL'!G6 -> -16832410 | E19: ='修正PL'!J6 -> -1635396
B20: 不動産管理費（売却物件分） | C20: =-'修正SGA'!D32 -> 4347132 | D20: =-'修正SGA'!G32 -> 1928280 | E20: =-'修正SGA'!J32 -> 686448
B21: コンサル収入（単発） | C21: ='修正PL'!D8 -> 0 | D21: ='修正PL'!G8 -> 0 | E21: ='修正PL'!J8 -> -14000000
B37: 調整後EBITDA | C37: =C8+C15+C17 -> -12646630 | D37: =D8+D15+D17 -> -12981386 | E37: =E8+E15+E17 -> -2182339 | F37: =F8+F15+F17 -> 0 | G37: =G8+G15+G17 -> 0
B38: （検算）修正PLの営業利益＋減価償却費 | C38: ='修正PL'!E17+C15 -> -12646630 | D38: ='修正PL'!H17+D15 -> -12981386 | E38: ='修正PL'!K17+E15 -> -2182339
B39: （検算）調整後EBITDA一致 | C39: =EXACT(C37,C38) -> 1 | D39: =EXACT(D37,D38) -> 1 | E39: =EXACT(E37,E38) -> 1

Sheet BSハイライト
F2: (単位：千円)
B3: ='BS(借方)'!E4 -> 令和8年3月期
B4: 流動資産 | C4: =SUM(C5:C10) -> 293198020 | E4: 流動負債 | F4: =SUM(F5:F10) -> 196854699
B5: 現預金 | C5: ='BS(借方)'!E6 -> 226057309 | E5: 買掛金 | F5: ='BS (貸方)'!E6 -> 10296760
B6: 売掛金 | C6: ='BS(借方)'!E7+'BS(借方)'!E8+'BS(借方)'!E14 -> 28512083 | E6: 短期借入金 ※ | F6: ='BS (貸方)'!E12 -> 173076977
B7: 商品 | C7: ='BS(借方)'!E9+'BS(借方)'!E10+'BS(借方)'!E11+'BS(借方)'!E15 -> 8532000 | E7: 未払金 | F7: ='BS (貸方)'!E7+'BS (貸方)'!E8 -> 7639437
B8: 前渡金 | C8: ='BS(借方)'!E12 -> 18507883 | E8: 未払法人税等 | F8: ='BS (貸方)'!E11 -> 97300
B9: 未収還付法人税等 | C9: ='BS(借方)'!E18 -> 10878400 | E9: 預り金 | F9: ='BS (貸方)'!E10 -> 794225
B10: その他 | C10: ='BS(借方)'!E13+'BS(借方)'!E16+'BS(借方)'!E17+'BS(借方)'!E19 -> 710345 | E10: その他 | F10: ='BS (貸方)'!E9+'BS (貸方)'!E13+'BS (貸方)'!E14+'BS (貸方)'!E15+'BS (貸方)'!E16+'BS (貸方)'!E17 -> 4950000
B11: 固定資産 | C11: =SUM(C12:C20) -> 503310970 | E11: 固定負債 | F11: =SUM(F12:F14) -> 272745529
B12: 建物 | C12: ='BS(借方)'!E22 -> 118721091 | E12: 長期借入金 ※ | F12: ='BS (貸方)'!E19 -> 272745529
B13: 建物付属設備 | C13: ='BS(借方)'!E23 -> 20091490
B14: 車両・器具備品 | C14: ='BS(借方)'!E26+'BS(借方)'!E27 -> 6303663 | E14: その他 | F14: ='BS (貸方)'!E20+'BS (貸方)'!E21+'BS (貸方)'!E22+'BS (貸方)'!E23+'BS (貸方)'!E24 -> 0
B15: 土地 | C15: ='BS(借方)'!E29 -> 345029626 | E15: 負債合計 | F15: =F4+F11 -> 469600228
B16: 敷金・保証金 | C16: ='BS(借方)'!E51+'BS(借方)'!E52 -> 13160100
B17: 出資金 | C17: ='BS(借方)'!E47 -> 5000 | E17: 資本金 | F17: ='BS (貸方)'!E36 -> 500000
E18: 資本剰余金 | F18: ='BS (貸方)'!E39 -> 5000000
E19: 利益剰余金 | F19: ='BS (貸方)'!E43 -> 321408762
B20: その他 | C20: ='BS(借方)'!E24+'BS(借方)'!E25+'BS(借方)'!E28+'BS(借方)'!E30+'BS(借方)'!E36+'BS(借方)'!E37+'BS(借方)'!E38+'BS(借方)'!E48+'BS(借方)'!E49+'BS(借方)'!E50 -> 0 | E20: 純資産合計 | F20: =SUM(F17:F19) -> 326908762
B21: 資産合計 | C21: =C4+C11 -> 796508990 | E21: 負債・純資産合計 | F21: =F15+F20 -> 796508990
B22: （検算）資産合計＝負債・純資産合計 | C22: =EXACT(C21,F21) -> 1
B23: ※短期借入金・長期借入金には役員借入金（ネットキャッシュ!F7）を含む
C24: ='ネットキャッシュ'!F7 -> 359666506

Sheet 取引先
L2: (単位：千円)
B3: № | C3: 得意先 | D3: 取引内容 | E3: 本社所在地 | F3: 業種等 | G3: ='BS(借方)'!C4 -> 令和6年3月期 | I3: ='BS(借方)'!D4 -> 令和7年3月期 | K3: ='BS(借方)'!E4 -> 令和8年3月期 | M3: 備考
G4: 売上高 | H4: 構成比 | I4: 売上高 | J4: 構成比 | K4: 売上高 | L4: 構成比
B5: 1 | C5: 鎌倉山店（本店） | D5: 店頭販売・カフェ | E5: 神奈川県鎌倉市 | F5: 飲食・小売 | G5: 92068073 | H5: =IFERROR(G5/G$16,"") -> 0.24011124 | I5: 90651247 | J5: =IFERROR(I5/I$16,"") -> 0.073650503 | K5: 99971894 | L5: =IFERROR(K5/K$16,"") -> 0.31305944 | M5: 自社所有の物件で営業
B6: 2 | C6: 紀尾井町店 | D6: 店頭販売・カフェ | E6: 東京都千代田区 | F6: 飲食・小売 | G6: 88621416 | H6: =IFERROR(G6/G$16,"") -> 0.23112244 | I6: 99543252 | J6: =IFERROR(I6/I$16,"") -> 0.080874901 | K6: 87917532 | L6: =IFERROR(K6/K$16,"") -> 0.27531152 | M6: 賃借
B7: 3 | C7: 大船店 | D7: 店頭販売・カフェ | E7: 神奈川県鎌倉市 | F7: 飲食・小売 | G7: 85043304 | H7: =IFERROR(G7/G$16,"") -> 0.22179082 | I7: 89094125 | J7: =IFERROR(I7/I$16,"") -> 0.072385404 | K7: 91286307 | L7: =IFERROR(K7/K$16,"") -> 0.28586075 | M7: 賃借（百貨店内。家賃支払先：三越伊勢丹）
B8: 4 | C8: 四谷店 | D8: 店頭販売・カフェ | E8: 東京都新宿区 | F8: 飲食・小売 | G8: 54918195 | H8: =IFERROR(G8/G$16,"") -> 0.14322528 | I8: 0 | J8: =IFERROR(I8/I$16,"") -> 0 | K8: 0 | L8: =IFERROR(K8/K$16,"") -> 0 | M8: 令和7年3月期以降は売上なし（閉店と推察）
B9: 5 | C9: ミリュウショップ | D9: 物販（EC等と推察） | E9: － | F9: 小売 | G9: 25967085 | H9: =IFERROR(G9/G$16,"") -> 0.06772151 | I9: 42088346 | J9: =IFERROR(I9/I$16,"") -> 0.034195094 | K9: 7427382 | L9: =IFERROR(K9/K$16,"") -> 0.023258658 | M9: 令和8年3月期に急減（要因は要確認）
B10: 6 | C10: リンベル株式会社 | D10: ギフト商品の卸（推察） | E10: 東京都 | F10: 卸売 | G10: 9099750 | H10: =IFERROR(G10/G$16,"") -> 0.023731921 | I10: 11706000 | J10: =IFERROR(I10/I$16,"") -> 0.0095106556 | K10: 6032250 | L10: =IFERROR(K10/K$16,"") -> 0.018889838
B11: 7 | C11: 株式会社ケンコーポレーション | D11: 商品販売（内容要確認） | E11: － | F11: － | G11: 5750360 | H11: =IFERROR(G11/G$16,"") -> 0.014996795 | I11: 5672510 | J11: =IFERROR(I11/I$16,"") -> 0.0046086869 | K11: 2033260 | L11: =IFERROR(K11/K$16,"") -> 0.006367102
B12: 8 | C12: 不動産賃貸収入 | D12: 賃貸収入（松濤フラッツ） | E12: 東京都渋谷区 | F12: 不動産賃貸 | G12: 16633646 | H12: =IFERROR(G12/G$16,"") -> 0.043380134 | I12: 16832410 | J12: =IFERROR(I12/I$16,"") -> 0.013675658 | K12: 1635396 | L12: =IFERROR(K12/K$16,"") -> 0.005121201 | M12: 非継続（令和7年3月末に売却）
B13: 9 | C13: 不動産売却収入 | D13: 土地・建物（松濤フラッツ） | E13: 東京都渋谷区 | F13: 不動産売買 | G13: 0 | H13: =IFERROR(G13/G$16,"") -> 0 | I13: 869200000 | J13: =IFERROR(I13/I$16,"") -> 0.70619015 | K13: 0 | L13: =IFERROR(K13/K$16,"") -> 0 | M13: 非継続（令和7年3月31日売却）
B14: 10 | C14: コンサル収入 | D14: コンサルティング報酬 | E14: － | F14: － | G14: 0 | H14: =IFERROR(G14/G$16,"") -> 0 | I14: 0 | J14: =IFERROR(I14/I$16,"") -> 0 | K14: 14000000 | L14: =IFERROR(K14/K$16,"") -> 0.043840644 | M14: 単発。相手先・契約内容は要確認
C15: その他（決済代行・法人取引等） | G15: 5337422 | H15: =IFERROR(G15/G$16,"") -> 0.013919863 | I15: 6042081 | J15: =IFERROR(I15/I$16,"") -> 0.0049089485 | K15: 9034353 | L15: =IFERROR(K15/K$16,"") -> 0.028290847
C16: 合計 | G16: =SUM(G5:G15) -> 383439251 | H16: =SUM(H5:H15) -> 1 | I16: =SUM(I5:I15) -> 1230829971 | J16: =SUM(J5:J15) -> 1 | K16: =SUM(K5:K15) -> 319338374 | L16: =SUM(L5:L15) -> 1
C17: （検算）PL売上高と一致 | G17: =EXACT(G16,PL!C11) -> 1 | I17: =EXACT(I16,PL!E11) -> 1 | K17: =EXACT(K16,PL!G11) -> 1

Sheet 仕入先
K2: (単位：千円)
B3: № | C3: 仕入先 | D3: 仕入内容 | E3: 本社所在地 | F3: ='BS(借方)'!C4 -> 令和6年3月期 | H3: ='BS(借方)'!D4 -> 令和7年3月期 | J3: ='BS(借方)'!E4 -> 令和8年3月期 | L3: 備考
F4: 仕入高 | G4: 構成比 | H4: 仕入高 | I4: 構成比 | J4: 仕入高 | K4: 構成比
B5: 1 | C5: 株式会社イワセ・エスタ | D5: 食材・製菓材料（推察） | E5: 要確認 | F5: 28050300 | G5: =IFERROR(F5/F$16,"") -> 0.26502144 | H5: 24442344 | I5: =IFERROR(H5/H$16,"") -> 0.24232458 | J5: 21717876 | K5: =IFERROR(J5/J$16,"") -> 0.22621344
B6: 2 | C6: 池伝株式会社 | D6: 輸入食材等（推察） | E6: 要確認 | F6: 18268647 | G6: =IFERROR(F6/F$16,"") -> 0.17260361 | H6: 17378610 | I6: =IFERROR(H6/H$16,"") -> 0.1722938 | J6: 13460004 | K6: =IFERROR(J6/J$16,"") -> 0.14019943
B7: 3 | C7: （取引先名記載なし） | D7: 現金仕入等 | E7: 要確認 | F7: 688192 | G7: =IFERROR(F7/F$16,"") -> 0.0065020922 | H7: 1597573 | I7: =IFERROR(H7/H$16,"") -> 0.015838547 | J7: 10441136 | K7: =IFERROR(J7/J$16,"") -> 0.1087549 | L7: 元帳上、取引先名が空欄
B8: 4 | C8: 株式会社東光 | D8: 食材・原材料（推察） | E8: 要確認 | F8: 6091895 | G8: =IFERROR(F8/F$16,"") -> 0.057556703 | H8: 5500130 | I8: =IFERROR(H8/H$16,"") -> 0.054529005 | J8: 5972479 | K8: =IFERROR(J8/J$16,"") -> 0.062209354
B9: 5 | C9: キーコーヒー株式会社 | D9: コーヒー豆・関連商材 | E9: 要確認 | F9: 5504018 | G9: =IFERROR(F9/F$16,"") -> 0.052002395 | H9: 5611507 | I9: =IFERROR(H9/H$16,"") -> 0.055633211 | J9: 5486964 | K9: =IFERROR(J9/J$16,"") -> 0.057152229
B10: 6 | C10: タカナシ販売株式会社 | D10: 乳製品 | E10: 要確認 | F10: 4106540 | G10: =IFERROR(F10/F$16,"") -> 0.038798913 | H10: 2967216 | I10: =IFERROR(H10/H$16,"") -> 0.029417366 | J10: 5308617 | K10: =IFERROR(J10/J$16,"") -> 0.055294566
B11: 7 | C11: 立替精算 | D11: 立替精算 | E11: 要確認 | F11: 9004353 | G11: =IFERROR(F11/F$16,"") -> 0.085073836 | H11: 7160014 | I11: =IFERROR(H11/H$16,"") -> 0.070985311 | J11: 5172411 | K11: =IFERROR(J11/J$16,"") -> 0.053875844 | L11: 従業員立替等（内訳は要確認）
B12: 8 | C12: 丸叶食品有限会社 | D12: 食材・原材料（推察） | E12: 要確認 | F12: 325567 | G12: =IFERROR(F12/F$16,"") -> 0.0030759826 | H12: 4605130 | I12: =IFERROR(H12/H$16,"") -> 0.045655858 | J12: 4179115 | K12: =IFERROR(J12/J$16,"") -> 0.043529671
B13: 9 | C13: 株式会社ナカリ | D13: 食材・原材料（推察） | E13: 要確認 | F13: 4564800 | G13: =IFERROR(F13/F$16,"") -> 0.04312859 | H13: 2963500 | I13: =IFERROR(H13/H$16,"") -> 0.029380525 | J13: 3629600 | K13: =IFERROR(J13/J$16,"") -> 0.037805922
B14: 10 | C14: 中沢乳業株式会社 | D14: 乳製品 | E14: 要確認 | F14: 3036394 | G14: =IFERROR(F14/F$16,"") -> 0.028688089 | H14: 3191147 | I14: =IFERROR(H14/H$16,"") -> 0.031637447 | J14: 2533914 | K14: =IFERROR(J14/J$16,"") -> 0.026393254
C15: その他（上位10項目以外） | F15: 26200919 | G15: =IFERROR(F15/F$16,"") -> 0.24754834 | H15: 25448965 | I15: =IFERROR(H15/H$16,"") -> 0.25230435 | J15: 18104008 | K15: =IFERROR(J15/J$16,"") -> 0.18857139
C16: 合計 | F16: =SUM(F5:F15) -> 105841625 | G16: =SUM(G5:G15) -> 1 | H16: =SUM(H5:H15) -> 100866136 | I16: =SUM(I5:I15) -> 1 | J16: =SUM(J5:J15) -> 96006124 | K16: =SUM(K5:K15) -> 1
C17: （検算）PL当期商品仕入高と一致（令和7年3月期は不動産売却関連原価を除く） | F17: =EXACT(F16,PL!C13) -> 1 | H17: =EXACT(H16,PL!E13) -> 1 | J17: =EXACT(J16,PL!G13) -> 1

Sheet 外注先
L2: (単位：千円)
B3: № | C3: 外注先 | D3: 外注内容 | E3: 本社所在地 | F3: 業種等 | G3: ='BS(借方)'!C4 -> 令和6年3月期 | I3: ='BS(借方)'!D4 -> 令和7年3月期 | K3: ='BS(借方)'!E4 -> 令和8年3月期 | M3: 備考
G4: 外注費 | H4: 構成比 | I4: 外注費 | J4: 構成比 | K4: 外注費 | L4: 構成比
B5: 1 | C5: 個人外注先A | D5: 外注（内容要確認） | E5: 要確認 | F5: － | G5: 1273723 | H5: =IFERROR(G5/G$16,"") -> 0.2073017 | I5: 1206394 | J5: =IFERROR(I5/I$16,"") -> 0.37612798 | K5: 1335280 | L5: =IFERROR(K5/K$16,"") -> 0.58143601 | M5: 外注費は個人名の取引先が中心（個人事業主等）。氏名は買手向け資料では非開示とする
B6: 2 | C6: （取引先名記載なし） | D6: 外注（内容要確認） | E6: 要確認 | F6: － | G6: 672600 | H6: =IFERROR(G6/G$16,"") -> 0.10946738 | I6: 29988 | J6: =IFERROR(I6/I$16,"") -> 0.0093496202 | K6: 678191 | L6: =IFERROR(K6/K$16,"") -> 0.29531234
B7: 3 | C7: 個人外注先C | D7: 外注（内容要確認） | E7: 要確認 | F7: － | G7: 60180 | H7: =IFERROR(G7/G$16,"") -> 0.00979445 | I7: 13729 | J7: =IFERROR(I7/I$16,"") -> 0.00428041 | K7: 121690 | L7: =IFERROR(K7/K$16,"") -> 0.052988847
B8: 4 | C8: 株式会社アイクス | D8: 外注（内容要確認） | E8: 要確認 | F8: － | G8: 0 | H8: =IFERROR(G8/G$16,"") -> 0 | I8: 0 | J8: =IFERROR(I8/I$16,"") -> 0 | K8: 116000 | L8: =IFERROR(K8/K$16,"") -> 0.050511186
B9: 5 | C9: 個人外注先E | D9: 外注（内容要確認） | E9: 要確認 | F9: － | G9: 0 | H9: =IFERROR(G9/G$16,"") -> 0 | I9: 127006 | J9: =IFERROR(I9/I$16,"") -> 0.039597768 | K9: 45360 | L9: =IFERROR(K9/K$16,"") -> 0.019751616
H10: =IFERROR(G10/G$16,"") -> 0 | J10: =IFERROR(I10/I$16,"") -> 0 | L10: =IFERROR(K10/K$16,"") -> 0
H11: =IFERROR(G11/G$16,"") -> 0 | J11: =IFERROR(I11/I$16,"") -> 0 | L11: =IFERROR(K11/K$16,"") -> 0
H12: =IFERROR(G12/G$16,"") -> 0 | J12: =IFERROR(I12/I$16,"") -> 0 | L12: =IFERROR(K12/K$16,"") -> 0
H13: =IFERROR(G13/G$16,"") -> 0 | J13: =IFERROR(I13/I$16,"") -> 0 | L13: =IFERROR(K13/K$16,"") -> 0
H14: =IFERROR(G14/G$16,"") -> 0 | J14: =IFERROR(I14/I$16,"") -> 0 | L14: =IFERROR(K14/K$16,"") -> 0
C15: その他 | G15: 4137793 | H15: =IFERROR(G15/G$16,"") -> 0.67343647 | I15: 1830286 | J15: =IFERROR(I15/I$16,"") -> 0.57064423 | K15: 0 | L15: =IFERROR(K15/K$16,"") -> 0
C16: 合計 | G16: =SUM(G5:G15) -> 6144296 | H16: =SUM(H5:H15) -> 1 | I16: =SUM(I5:I15) -> 3207403 | J16: =SUM(J5:J15) -> 1 | K16: =SUM(K5:K15) -> 2296521 | L16: =SUM(L5:L15) -> 1
C17: （検算）SGA外注費と一致 | G17: =EXACT(G16,SGA!C28) -> 1 | I17: =EXACT(I16,SGA!E28) -> 1 | K17: =EXACT(K16,SGA!G28) -> 1

Sheet 株主
E2: (単位：千円)
B3: № | C3: 氏名 | D3: 役職 | E3: 役員報酬 （令和8年3月期） | F3: 保有株式数 | G3: 保有割合 | H3: 備考
B5: 1 | C5: 西丸 修 | D5: 代表取締役 | E5: 1920000 | F5: 100 | G5: =F5/$F$15 -> 1 | H5: 法人税申告書 別表二（令和8年3月期）による。株主名簿は未受領（要確認）
G6: =IF(F6="","",F6/$F$15)
G7: =IF(F7="","",F7/$F$15)
G8: =IF(F8="","",F8/$F$15)
G9: =IF(F9="","",F9/$F$15)
G10: =IF(F10="","",F10/$F$15)
G11: =IF(F11="","",F11/$F$15)
G12: =IF(F12="","",F12/$F$15)
G13: =IF(F13="","",F13/$F$15)
G14: =IF(F14="","",F14/$F$15)
C15: 合計 | E15: =SUM(E5:E14) -> 1920000 | F15: =SUM(F5:F14) -> 100 | G15: =F15/$F$15 -> 1

Sheet 取締役
F2: (単位：千円)
B3: № | C3: 氏名 | D3: 役職 | E3: 代表者との関係 | F3: 役員報酬 （令和8年3月期） | G3: 業務範囲 | H3: 備考
B5: 1 | C5: 西丸 修 | D5: 代表取締役 | E5: 本人 | F5: 1920000 | G5: 経営全般（要確認） | H5: 登記簿上の役員構成は未受領。他の役員の有無・譲渡後の関与意向は要確認
C15: 合計 | F15: =SUM(F5:F14) -> 1920000

Sheet 従業員
B4: № | C4: 区分 | D4: イニシャル | E4: 雇用形態 | F4: 性別 | G4: 生年月日 | H4: 年齢 （歳） | I4: 入社年月日 | J4: 勤続年数 （年） | K4: 部署 | L4: 役職 | M4: 2026年2月分給与 （振込支給＋交通費） | N4: 夏季賞与 | O4: 冬季賞与 | P4: 年間総支給額 | Q4: 備考
B5: 1 | C5: 月給者（6名） | E5: 月給制 | K5: 全社 | M5: 要確認 | Q5: 個人別の年齢・勤続・役職は未受領（要確認）
B6: 2 | C6: 時給者（約30名） | E6: 時給制（パート・アルバイト） | K6: 店舗 | M6: 要確認 | Q6: 時給1,225〜1,350円の記載あり。店舗別の配置は要確認
C7: 合計（約36名） | M7: 7854008 | Q7: 役員を除く。賞与の記載なし（要確認）
C9: 2026年2月分給与（給与台帳） | M9: 金額
C10: 振込支給合計（交通費除く） | M10: 7520982
C11: 交通費合計 | M11: 333026
C12: 総支給額（振込支給＋交通費） | M12: =M10+M11 -> 7854008
C13: （参考）法定福利費（会社負担） | M13: 1361985

Sheet 拠点(本社等)
B2: 所在地 | C2: 契約形態 | D2: 延床面積 (㎡) | E2: 月間賃料 (千円) | F2: 敷金 (千円) | G2: アクセス
B3: 神奈川県鎌倉市鎌倉山三丁目2番31号 （本社・鎌倉山店「ル・ミリュウ」） | C3: 自己所有（土地・建物） | D3: 要確認 | E3: － | F3: － | G3: 大船駅からバス（見晴バス停すぐ）※Web情報・要確認
B4: 紀尾井町店（東京都千代田区） ※番地は要確認 | C4: 賃借（契約書未受領） | D4: 要確認 | E4: 981267 | F4: 要確認 | G4: 要確認
B5: 大船店（神奈川県鎌倉市） ※番地は要確認 | C5: 賃借（家賃支払先：三越伊勢丹） | D5: 要確認 | E5: 614722 | F5: 要確認 | G5: 要確認

Sheet 不動産(所有)
I1: 時価は未評価（簿価評価）
B3: 事業所名 | C3: 内容 | D3: 所在地 地番・家屋番号 | E3: 面積 (㎡) | F3: 区分 ・構造 | G3: 所有（建築） 年月・事由 | H3: 前期末簿価 (千円) | I3: 時価 | J3: 固定資産税 評価額 | K3: 備考
B4: 本社・鎌倉山店 | C4: 土地）店舗敷地ほか | D4: 鎌倉市鎌倉山三丁目2番31（地番詳細は要確認） | E4: 要確認 | F4: 宅地（要確認） | G4: 平成22年12月頃 取得（建物は平成22年12月21日取得） | H4: 345029626 | I4: =H4 -> 345029626 | J4: 要確認 | K4: 簿価評価（登記事項証明書・評価証明書等が未受領のため時価評価未実施）。うち約87,420千円は「鎌倉山三丁目計画」の建設仮勘定からの振替（内容要確認）
C5: 建物）店舗（鎌倉店舗） | D5: 同上 | E5: 要確認 | F5: 店舗（構造は要確認） | G5: 平成22年12月21日取得 | H5: 92242941 | I5: =H5 -> 92242941 | J5: － | K5: 簿価評価（償却不足なし）。固定資産台帳より
C6: 建物）螺旋階段ほか | D6: 同上 | E6: 要確認 | F6: － | G6: 平成30年1月取得 | H6: 909149 | I6: =H6 -> 909149 | J6: － | K6: 簿価評価。固定資産台帳より
B7: 大船 | C7: 建物）ブランズタワー大船（専有部分） | D7: 神奈川県鎌倉市大船（住戸・地番は要確認） | E7: 要確認 | F7: 要確認 | G7: 令和3年3月22日取得 | H7: 25569001 | I7: =H7 -> 25569001 | J7: － | K7: 簿価評価。大船店との関係（店舗利用か投資用か）は要確認

Sheet 不動産(賃借) 
B3: 内容 | C3: 内容 | D3: 所在地 地番・家屋番号 | E3: 面積 (㎡) | F3: 契約内容 | G3: 貸主 | H3: 月間賃料 (千円) | I3: 敷金 (千円) | J3: 備考
B4: 紀尾井町店 | C4: 建物）店舗 | D4: 東京都千代田区紀尾井町（番地は要確認） | E4: 要確認 | F4: 賃貸借契約書未受領 | G4: 要確認 | H4: 981267 | I4: 要確認 | J4: 地代家賃（令和8年3月期）年11,775千円の12分の1
B5: 大船店 | C5: 建物）店舗 | D5: 神奈川県鎌倉市大船（番地は要確認） | E5: 要確認 | F5: 賃貸借契約書未受領 | G5: 三越伊勢丹（支払先） | H5: 614722 | I5: 要確認 | J5: 地代家賃年7,377千円の12分の1。百貨店精算を伴う
B6: 社宅等 | C6: 建物）住居 | D6: 第15宮庭マンション（所在地は要確認） | E6: 要確認 | F6: 要確認 | G6: 株式会社トシ建設 | H6: 130000 | I6: 要確認 | J6: 年1,560千円。従業員・役員の住居か要確認
B7: 事務所 | C7: 建物）事務所 | D7: 東京都（所在地は要確認） | E7: 要確認 | F7: 要確認 | G7: シーブス | H7: 53333 | I7: 要確認 | J7: 年640千円
B8: 駐車場 | C8: 土地）駐車場 | D8: 中瀬（所在地は要確認） | E8: 要確認 | F8: 要確認 | G8: 有限会社野村不動産（中瀬） | H8: 28023 | I8: 要確認 | J8: 年336千円

Sheet 設備
B2: № | C2: 科目 | D2: 資産名 | E2: 償却方法 | F2: 取得年 | G2: 取得月 | H2: 耐用年数 | I2: 取得原価 | J2: 期末帳簿価額 | K2: 文字
B3: 1 | C3: 建物 | D3: ブランズタワー大船 | E3: 定額 | F3: 2021 | G3: 3 | H3: 47 | I3: 61053652 | J3: 25569001
B4: 2 | C4: 建物 | D4: 鎌倉店舗 | E4: 定額 | F4: 2010 | G4: 12 | H4: 39 | I4: 198526810 | J4: 92242941
B5: 3 | C5: 建物 | D5: 鎌倉山店 螺旋階段 | E5: 定額 | F5: 2018 | G5: 1 | H5: 39 | I5: 1157408 | J5: 909149
B6: 4 | C6: 建物付属設備 | D6: 鎌倉山店 螺旋階段（新設） | E6: 定額 | F6: 2025 | G6: 10 | H6: 15 | I6: 5345456 | J6: 5166384
B7: 5 | C7: 建物付属設備 | D7: 大船店 B工事 | E7: 定額 | F7: 2022 | G7: 1 | H7: 15 | I7: 6370320 | J7: 4556374
B8: 6 | C8: 建物付属設備 | D8: ルミリュウ大船 内装工事 | E8: 定額 | F8: 2025 | G8: 3 | H8: 15 | I8: 4822473 | J8: 4472443
B9: 7 | C9: 建物付属設備 | D9: 天井照明工事 | E9: 定額 | F9: 2020 | G9: 11 | H9: 15 | I9: 2980706 | J9: 1898960
B10: 8 | C10: 建物付属設備 | D10: 紀尾井町店 空調設備工事 | E10: 定額 | F10: 2016 | G10: 10 | H10: 15 | I10: 4985956 | J10: 1812396
B11: 9 | C11: 建物付属設備 | D11: 鎌倉店 給排水設備 | E11: 定率 | F11: 2010 | G11: 12 | H11: 15 | I11: 23197737 | J11: 617007
B12: 10 | C12: 建物付属設備 | D12: 紀尾井町店 給排水設備工事 | E12: 定額 | F12: 2016 | G12: 10 | H12: 15 | I12: 1650096 | J12: 599814
B13: 11 | C13: 建物付属設備 | D13: 紀尾井町店 電気設備工事 | E13: 定額 | F13: 2016 | G13: 10 | H13: 15 | I13: 1166730 | J13: 424115
B14: 12 | C14: 車両運搬具 | D14: MINI F65S | E14: 定率 | F14: 2025 | G14: 7 | H14: 6 | I14: 4565855 | J14: 3425533
... B18: 16 | C18: 工具器具備品 | D18: 棚什器・冷蔵庫・ワゴン 他 | E18: 定率 | F18: 2025 | G18: 1 | H18: 6 | I18: 462982 | J18: 320833
B19: 17 | D19: その他（償却済・備忘価額1円） | E19: － | F19: － | G19: － | H19: － | I19: － | J19: 15 | K19: 建物付属設備・器具備品の償却済資産

Sheet 財務
B2: IMの財務詳細ページのデータは財務入力のシートから流用してください

Sheet その他
A1: 【要確認事項（案件固有）】
A2: 1. 設立年月・登記事項（商号履歴、役員構成、事業目的、本店移転履歴）：登記事項証明書未受領
A3: 2. 株主構成：法人税申告書 別表二では西丸 修100%。株主名簿・過去の株式異動の確認
A4: 3. 事業内容・屋号・店舗網：Web情報では「ル・ミリュウ鎌倉山」「ラ・プレシューズ（四ツ谷・紀尾井町）」。大船店「ルミリュウ大船」と合わせた現行店舗網の確認。法人税申告書上の事業種目は「不動産賃貸業」
A5: 4. 令和7年3月期の不動産売却（松濤フラッツ・売却額869,200千円・買主㈱日本財託）：取得経緯、売却益、紹介手数料等（計48,960千円）、コンサルティング費用（15,096千円）、㈱アールエイジへの支払29,000千円の内容。令和7年3月末の売掛金841百万円の回収状況
A6: 5. 令和8年3月期のコンサル収入14,000千円（売掛金15,400千円）および前渡金18,508千円（コンサル紹介費用）の相手先・契約内容・回収可能性・返金可否
A7: 6. 過年度法人税等48,375千円（令和3〜4年度分の法人税・地方法人税・事業税、不申告加算税・延滞税を含む）：税務調査の経緯・範囲・未解決事項、令和5年度以降の影響
A8: 7. 役員借入金359,667千円（西丸 修257,667千円、西丸 勇人51,000千円、西丸 翔太51,000千円）：返済条件・譲渡時の取扱い。BS上は短期・長期借入金に含まれる
A9: 8. 銀行借入86,156千円（三井住友銀行31,916千円、三菱UFJ銀行54,240千円）：返済条件・担保・代表者保証の有無
A10: 9. 土地・建物の時価評価：登記事項証明書、固定資産税評価証明書、路線価、不動産鑑定の有無（土地345,030千円は簿価評価）。鎌倉山三丁目計画（約87,420千円を土地へ振替）の内容
A11: 10. 賃貸借契約（紀尾井町店・大船店ほか）の契約書、敷金13,160千円の内訳・返還条件、原状回復義務、契約期間・更新
A12: 11. 従業員：個人別の雇用形態・年齢・勤続・賞与・退職金制度（就業規則・賃金規程・退職金規程）。月給者6名・時給者約30名は給与台帳からの推計
... A37: ・従業員シートのテンプレート記入例（●年夏季賞与、YYYY/MM/DD等）を削除し、2026年2月分の給与支給集計（9〜13行）を追加した。
