Workbook

Sheet ルール
B3: 1 | C3: 文字は「游ゴシック」、数字は「Arial」を基本。備考欄などの細かい文章は「游ゴシック Medium」。
B4: 2 | C4: タイトル、合計欄は太字
B5: 3 | C5: 数字は円単位で入力、表示は千円単位に設定済み
B6: 4 | C6: 基本の背景は以下の通り。紺、水色、グレー、白、青。パレットの上部の色。
C8: 線は紺か白か青。
C10: 資産の部
C11: 科目 | D11: ='BS(借方)'!F10 -> 0 | E11: 調整額 | F11: 調整後
C12: 【流動資産】 | D12: =SUM(D13:D26) -> 5000000 | E12: =SUM(E13:E26) -> -500000 | F12: =SUM(F13:F26) -> 4500000
C13: 現金及び預金 | D13: 5000000 | E13: -500000 | F13: =D13+E13 -> 4500000
F14: =D14+E14 -> 0
B16: ■ 本案件の運用（株式会社鶴岡中央青果）
B17: 1. 本ファイルが唯一の数値ソース。企業概要書・評価書の数字は必ず本ファイルから貼る（パワポに直接打たない）。
B18: 2. 財務入力：D列=24年3月期（第51期）、E列=25年3月期、F列=26年3月期（直近期・評価基準日）、G列=進行期（2026年4〜9月の試算表、6か月累計）。1期目（C列）は未使用のため非表示。
B19: 3. 非表示の行・列は概要書に貼らない（空行・1期目・売上行・氏名等）。貼付スクリプト（im_paste.paste_range）も非表示を自動で除く。
B20: 4. 未確認事項は推測で埋めず「要確認」。推測は「推察」「想定」「（仮説）」と明記し、「その他」シートに集約。社内限の情報は「その他」の「プロセス関連（社内確認事項）」のみに記載。
B21: 5. 更新：2026/10/27 公式フォーマットへ移行（旧マスター261019の内容を転記）。9月試算表・順位表・分類別売上・認定証を反映。SGA 26/3期の行ずれ、テンプレートの数式不具合（年買法G8/H8、ネットキャッシュF15、修正BS(貸方)D50）を修正。
B23: ■ 企業概要書への貼付範囲一覧（各IMシートのA1/A2にも表記）
B24: 会社概要!B2:C15 → 基本情報
B25: PLハイライト!B2:G25 → 財務ハイライト（P/L）
B26: BSハイライト!B2:F21 → 財務ハイライト（B/S）
B27: 取引先!B2:M17 → 主要得意先の3期推移
B28: 仕入先!B2:L17 → 主要仕入先の3期推移
... B47: SGA!B2:L40 → 販売費及び一般管理費

Sheet 財務入力→

Sheet BS(借方)
A1: ■ 貼付範囲 B3:G61 → 企業概要書「貸借対照表（資産の部）」（C列・空行は非表示） | C1: ←基本的にはここをつかう→
C2: 1期目 | D2: 2期目 | E2: 3期目 | F2: （4期目） | G2: 進行期
B3: 資産の部
B4: 科目 | C4: ●●年●月期 | D4: 24年3月期 | E4: 25年3月期 | F4: 26年3月期 | G4: 27年3月期 4〜9月TB
B5: 【流動資産】 | C5: =SUM(C6:C19) -> 0 | D5: =SUM(D6:D19) -> 375589011 | E5: =SUM(E6:E19) -> 303100807 | F5: =SUM(F6:F19) -> 249704912 | G5: =SUM(G6:G19) -> 434733191
B6: 現金及び預金 | D6: 339552632 | E6: 259719301 | F6: 210887077 | G6: 393410846
B7: 売掛金 | D7: 21171056 | E7: 21896538 | F7: 19608899 | G7: 22835432
B8: 資材肥料売掛金 | D8: 1352474 | E8: 1269087 | F8: 1227419 | G8: 1137638
B9: 棚卸資産 | D9: 9859795 | E9: 15443609 | F9: 14596695 | G9: 14405198
B10: 立替金 | D10: 96860 | E10: 6400
B11: 未収入金 | D11: 3684415 | E11: 3905410 | F11: 3011112 | G11: 3045753
B12: 仮払金 | F12: 493135
B13: 前払費用 | D13: 108779 | E13: 96162 | F13: 83575 | G13: 101324
B14: 仮払税金等 | E14: 998300
B15: 貸倒引当金 | D15: -237000 | E15: -234000 | F15: -203000 | G15: -203000
B20: 【固定資産】 | C20: =C21+C35+C46 -> 0 | D20: =D21+D35+D46 -> 276114714 | E20: =E21+E35+E46 -> 264261323 | F20: =F21+F35+F46 -> 235485192 | G20: =G21+G35+G46 -> 230831192
B21: ［有形固定資産］ | C21: =SUM(C22:C34) -> 0 | D21: =SUM(D22:D34) -> 216357447 | E21: =SUM(E22:E34) -> 204260121 | F21: =SUM(F22:F34) -> 196905728 | G21: =SUM(G22:G34) -> 193251728
B22: 建物 | D22: 101161720 | E22: 95851274 | F22: 92065694 | G22: 92065694
B23: 建物付属設備 | D23: 15416918 | E23: 13503020 | F23: 11399836 | G23: 11399836
B24: 構築物 | D24: 382601 | E24: 333498 | F24: 284395 | G24: 284395
B25: 機械装置 | D25: 133566 | E25: 2 | F25: 2 | G25: 2
B26: 車両運搬具 | D26: 5837529 | E26: 1281878 | F26: 15 | G26: 15
B27: 工具器具備品 | D27: 287873 | E27: 153209 | F27: 18546 | G27: 18546
B28: 土地 | D28: 93137240 | E28: 93137240 | F28: 93137240 | G28: 93137240
B29: 減価償却累計額 | G29: -3654000
B35: ［無形固定資産］ | C35: =SUM(C36:C45) -> 0 | D35: =SUM(D36:D45) -> 2870595 | E35: =SUM(E36:E45) -> 2698995 | F35: =SUM(F36:F45) -> 2527395 | G35: =SUM(G36:G45) -> 2527395
B36: 電話加入権 | D36: 2155595 | E36: 2155595 | F36: 2155595 | G36: 2155595
B37: ソフトウェア | D37: 715000 | E37: 543400 | F37: 371800 | G37: 371800
B46: ［投資その他資産］ | C46: =SUM(C47:C55) -> 0 | D46: =SUM(D47:D55) -> 56886672 | E46: =SUM(E47:E55) -> 57302207 | F46: =SUM(F47:F55) -> 36052069 | G46: =SUM(G47:G55) -> 35052069
B47: 投資有価証券 | D47: 3250000 | E47: 3250000 | F47: 2600000 | G47: 1600000
B48: 出資金 | D48: 75000 | E48: 75000 | F48: 75000 | G48: 75000
B49: 長期前払費用 | D49: 397411 | E49: 74500 | F49: 74500 | G49: 74500
B50: 保証金 | D50: 32002569 | E50: 33002569 | F50: 33302569 | G50: 33302569
B51: 事業保険積立金 | D51: 21161692 | E51: 20900138
B56: 【繰延資産】 | C56: =SUM(C57:C60) -> 0 | D56: =SUM(D57:D60) -> 243834 | E56: =SUM(E57:E60) -> 166834 | F56: =SUM(F57:F60) -> 0 | G56: =SUM(G57:G60) -> 0
B57: 繰延資産 | D57: 243834 | E57: 166834
B61: 資産合計 | C61: =C5+C20+C56 -> 0 | D61: =D5+D20+D56 -> 651947559 | E61: =E5+E20+E56 -> 567528964 | F61: =F5+F20+F56 -> 485190104 | G61: =G5+G20+G56 -> 665564383
B63: バランスチェック | C63: =EXACT(C61,'BS (貸方)'!C51) -> 1 | D63: =EXACT(D61,'BS (貸方)'!D51) -> 1 | E63: =EXACT(E61,'BS (貸方)'!E51) -> 1 | F63: =EXACT(F61,'BS (貸方)'!F51) -> 1 | G63: =EXACT(G61,'BS (貸方)'!G51) -> 1
B65: 決算書・試算表の資産合計 | D65: 651947559 | E65: 567528964 | F65: 485190104 | G65: 665564383
B66: チェック | D66: =EXACT(D61,D65) -> 1 | E66: =EXACT(E61,E65) -> 1 | F66: =EXACT(F61,F65) -> 1 | G66: =EXACT(G61,G65) -> 1
B68: ※進行期（G列）は2026年9月末の合計残高試算表（4〜9月の6か月累計）。2026年8〜9月に長期借入金が約1.65億円増加（資金使途は要確認）。

Sheet BS (貸方)
A1: ■ 貼付範囲 B3:G25（負債）／B34:G51（純資産）→ 企業概要書「貸借対照表」
E2: (単位：千円)
B3: 負債の部
B4: 科目 | C4: ='BS(借方)'!C4 -> ●●年●月期 | D4: ='BS(借方)'!D4 -> 24年3月期 | E4: ='BS(借方)'!E4 -> 25年3月期 | F4: ='BS(借方)'!F4 -> 26年3月期 | G4: ='BS(借方)'!G4 -> 27年3月期 4〜9月TB
B5: 【流動負債】 | C5: =SUM(C6:C17) -> 0 | D5: =SUM(D6:D17) -> 34109222 | E5: =SUM(E6:E17) -> 29455728 | F5: =SUM(F6:F17) -> 37279523 | G5: =SUM(G6:G17) -> 31281895
B6: 買掛金 | D6: 18127739 | E6: 19954920 | F6: 26349122 | G6: 18258090
B7: 未払金 | D7: 10198849 | E7: 7302614 | F7: 6630301 | G7: 3564068
B8: 仮受金 | G8: 6109017
B9: 預り金 | D9: 504234 | E9: 557594 | F9: 281300 | G9: 327720
B10: 未払法人税等 | D10: 2308000 | E10: 33900 | F10: 1851300
B11: 未払消費税 | D11: 2970400 | E11: 1606700 | F11: 2167500 | G11: 3023000
B18: 【固定負債】 | C18: =SUM(C19:C24) -> 0 | D18: =SUM(D19:D24) -> 525010000 | E18: =SUM(E19:E24) -> 444316000 | F18: =SUM(F19:F24) -> 370038000 | G18: =SUM(G19:G24) -> 535244000
B19: 長期借入金 | D19: 514690000 | E19: 434046000 | F19: 361058000 | G19: 526264000
B20: 預り保証金 | D20: 10320000 | E20: 10270000 | F20: 8980000 | G20: 8980000
B25: 負債合計 | C25: =C5+C18 -> 0 | D25: =D5+D18 -> 559119222 | E25: =E5+E18 -> 473771728 | F25: =F5+F18 -> 407317523 | G25: =G5+G18 -> 566525895
B34: 純資産の部
B35: 【資本金】 | C35: =SUM(C36:C38) -> 0 | D35: =SUM(D36:D38) -> 40000000 | E35: =SUM(E36:E38) -> 40000000 | F35: =SUM(F36:F38) -> 40000000 | G35: =SUM(G36:G38) -> 40000000
B36: 資本金 | D36: 40000000 | E36: 40000000 | F36: 40000000 | G36: 40000000
B39: 【資本剰余金】 | C39: =SUM(C40:C42) -> 0 | D39: =SUM(D40:D42) -> 0 | E39: =SUM(E40:E42) -> 0 | F39: =SUM(F40:F42) -> 0 | G39: =SUM(G40:G42) -> 0
B43: 【利益剰余金】 | C43: =SUM(C44:C48) -> 0 | D43: =SUM(D44:D48) -> 52828337 | E43: =SUM(E44:E48) -> 53757236 | F43: =SUM(F44:F48) -> 37872581 | G43: =SUM(G44:G48) -> 59038488
B44: 利益準備金 | D44: 1800000 | E44: 2000000 | F44: 2080000 | G44: 2080000
B45: 繰越利益剰余金 | D45: 51028337 | E45: 51757236 | F45: 35792581 | G45: 56958488
B49: 【自己株式】 | C49: 0 | D49: 0 | E49: 0 | F49: 0 | G49: 0
B50: 純資産合計 | C50: =C35+C39+C43+C49 -> 0 | D50: =D35+D39+D43+D49 -> 92828337 | E50: =E35+E39+E43+E49 -> 93757236 | F50: =F35+F39+F43+F49 -> 77872581 | G50: =G35+G39+G43+G49 -> 99038488
B51: 負債・純資産合計 | C51: =C25+C50 -> 0 | D51: =D25+D50 -> 651947559 | E51: =E25+E50 -> 567528964 | F51: =F25+F50 -> 485190104 | G51: =G25+G50 -> 665564383
B53: バランスチェック | C53: =EXACT(C51,'BS(借方)'!C61) -> 1 | D53: =EXACT(D51,'BS(借方)'!D61) -> 1 | E53: =EXACT(E51,'BS(借方)'!E61) -> 1 | F53: =EXACT(F51,'BS(借方)'!F61) -> 1 | G53: =EXACT(G51,'BS(借方)'!G61) -> 1

Sheet PL
A1: ■ 貼付範囲 B2:L56 → 企業概要書「損益計算書」（C:D列・空行は非表示）
L2: (単位：千円)
B3: 科目 | C3: ='BS(借方)'!C4 -> ●●年●月期 | E3: ='BS(借方)'!D4 -> 24年3月期 | G3: ='BS(借方)'!E4 -> 25年3月期 | I3: ='BS(借方)'!F4 -> 26年3月期 | K3: ='BS(借方)'!G4 -> 27年3月期 4〜9月TB
C4: 帳簿価額 | D4: 売上高比 | E4: 帳簿価額 | F4: 売上高比 | G4: 帳簿価額 | H4: 売上高比 | I4: 帳簿価額 | J4: 売上高比 | K4: 帳簿価額 | L4: 売上高比
B5: 商品売上高 | D5: =IF(C5=0,"",C5/C$11) | E5: 1179974308 | F5: =IF(E5=0,"",E5/E$11) -> 1.0012603 | G5: 1183308630 | H5: =IF(G5=0,"",G5/G$11) -> 1.0011517 | I5: 1197530299 | J5: =IF(I5=0,"",I5/I$11) -> 1.0013689 | K5: 568871022 | L5: =IF(K5=0,"",K5/K$11) -> 0.91556776
B6: 資材売上高 | D6: =IF(C6=0,"",C6/C$11) | F6: =IF(E6=0,"",E6/E$11) | H6: =IF(G6=0,"",G6/G$11) | J6: =IF(I6=0,"",I6/I$11) | K6: 5369372 | L6: =IF(K6=0,"",K6/K$11) -> 0.0086417196
B7: 資材売上（自社） | D7: =IF(C7=0,"",C7/C$11) | F7: =IF(E7=0,"",E7/E$11) | H7: =IF(G7=0,"",G7/G$11) | J7: =IF(I7=0,"",I7/I$11) | K7: 9473775 | L7: =IF(K7=0,"",K7/K$11) -> 0.015247539
B8: 主婦センター費 | D8: =IF(C8=0,"",C8/C$11) | F8: =IF(E8=0,"",E8/E$11) | H8: =IF(G8=0,"",G8/G$11) | J8: =IF(I8=0,"",I8/I$11) | K8: 18416492 | L8: =IF(K8=0,"",K8/K$11) -> 0.029640368
B9: 委託手数料収入 | D9: =IF(C9=0,"",C9/C$11) | F9: =IF(E9=0,"",E9/E$11) | H9: =IF(G9=0,"",G9/G$11) | J9: =IF(I9=0,"",I9/I$11) | K9: 19958506 | L9: =IF(K9=0,"",K9/K$11) -> 0.032122158
B10: 売上割戻金 | D10: =IF(C10=0,"",C10/C$11) | E10: -1485210 | F10: =IF(E10=0,"",E10/E$11) -> -0.0012602662 | G10: -1361290 | H10: =IF(G10=0,"",G10/G$11) -> -0.0011517349 | I10: -1637030 | J10: =IF(I10=0,"",I10/I$11) -> -0.0013688763 | K10: -757740 | L10: =IF(K10=0,"",K10/K$11) -> -0.0012195424
B11: 売上高 | C11: =SUM(C5:C10) -> 0 | D11: =IF(C11=0,"",C11/C$11) | E11: =SUM(E5:E10) -> 1178489098 | F11: =IF(E11=0,"",E11/E$11) -> 1 | G11: =SUM(G5:G10) -> 1181947340 | H11: =IF(G11=0,"",G11/G$11) -> 1 | I11: =SUM(I5:I10) -> 1195893269 | J11: =IF(I11=0,"",I11/I$11) -> 1 | K11: =SUM(K5:K10) -> 621331427 | L11: =IF(K11=0,"",K11/K$11) -> 1
B12: 期首棚卸高 | D12: =IF(C12=0,"",C12/C$11) | E12: 15470384 | F12: =IF(E12=0,"",E12/E$11) -> 0.013127303 | G12: 9859795 | H12: =IF(G12=0,"",G12/G$11) -> 0.0083419918 | I12: 15443609 | J12: =IF(I12=0,"",I12/I$11) -> 0.012913869 | K12: 14596695 | L12: =IF(K12=0,"",K12/K$11) -> 0.023492607
B13: 仕入高 | D13: =IF(C13=0,"",C13/C$11) | E13: 953298320 | F13: =IF(E13=0,"",E13/E$11) -> 0.80891569 | G13: 976235640 | H13: =IF(G13=0,"",G13/G$11) -> 0.82595527 | I13: 996035389 | J13: =IF(I13=0,"",I13/I$11) -> 0.83287984 | K13: 514967990 | L13: =IF(K13=0,"",K13/K$11) -> 0.82881369
B14: 期末棚卸高 | D14: =IF(C14=0,"",C14/C$11) | E14: -9859795 | F14: =IF(E14=0,"",E14/E$11) -> -0.0083664711 | G14: -15443609 | H14: =IF(G14=0,"",G14/G$11) -> -0.013066241 | I14: -14596695 | J14: =IF(I14=0,"",I14/I$11) -> -0.012205684 | K14: -14405198 | L14: =IF(K14=0,"",K14/K$11) -> -0.023184403
D15: =IF(C15=0,"",C15/C$11) | F15: =IF(E15=0,"",E15/E$11) | H15: =IF(G15=0,"",G15/G$11) | J15: =IF(I15=0,"",I15/I$11) | L15: =IF(K15=0,"",K15/K$11)
B16: 売上原価 | C16: =SUM(C12:C15) -> 0 | D16: =IF(C16=0,"",C16/C$11) | E16: =SUM(E12:E15) -> 958908909 | F16: =IF(E16=0,"",E16/E$11) -> 0.81367652 | G16: =SUM(G12:G15) -> 970651826 | H16: =IF(G16=0,"",G16/G$11) -> 0.82123103 | I16: =SUM(I12:I15) -> 996882303 | J16: =IF(I16=0,"",I16/I$11) -> 0.83358802 | K16: =SUM(K12:K15) -> 515159487 | L16: =IF(K16=0,"",K16/K$11) -> 0.82912189
B17: 売上総利益 | C17: =C11-C16 -> 0 | D17: =IF(C17=0,"",C17/C$11) | E17: =E11-E16 -> 219580189 | F17: =IF(E17=0,"",E17/E$11) -> 0.18632348 | G17: =G11-G16 -> 211295514 | H17: =IF(G17=0,"",G17/G$11) -> 0.17876897 | I17: =I11-I16 -> 199010966 | J17: =IF(I17=0,"",I17/I$11) -> 0.16641198 | K17: =K11-K16 -> 106171940 | L17: =IF(K17=0,"",K17/K$11) -> 0.17087811
B18: 販売費及び一般管理費 | C18: =SGA!C40 -> 0 | D18: =IF(C18=0,"",C18/C$11) | E18: =SGA!E40 -> 214823441 | F18: =IF(E18=0,"",E18/E$11) -> 0.18228717 | G18: =SGA!G40 -> 215718454 | H18: =IF(G18=0,"",G18/G$11) -> 0.18251105 | I18: =SGA!I40 -> 193151054 | J18: =IF(I18=0,"",I18/I$11) -> 0.16151195 | K18: =SGA!K40 -> 85746239 | L18: =IF(K18=0,"",K18/K$11) -> 0.13800403
B19: 営業利益 | C19: =C17- C18 -> 0 | D19: =IF(C19=0,"",C19/C$11) | E19: =E17- E18 -> 4756748 | F19: =IF(E19=0,"",E19/E$11) -> 0.0040363106 | G19: =G17- G18 -> -4422940 | H19: =IF(G19=0,"",G19/G$11) -> -0.0037420787 | I19: =I17- I18 -> 5859912 | J19: =IF(I19=0,"",I19/I$11) -> 0.0049000293 | K19: =K17- K18 -> 20425701 | L19: =IF(K19=0,"",K19/K$11) -> 0.032874083
B20: 営業外収益 | C20: =SUM(C21:C27) -> 0 | D20: =IF(C20=0,"",C20/C$11) | E20: =SUM(E21:E27) -> 10628095 | F20: =IF(E20=0,"",E20/E$11) -> 0.0090184076 | G20: =SUM(G21:G27) -> 10736890 | H20: =IF(G20=0,"",G20/G$11) -> 0.009084068 | I20: =SUM(I21:I27) -> 6577758 | J20: =IF(I20=0,"",I20/I$11) -> 0.0055002885 | K20: =SUM(K21:K27) -> 2830373 | L20: =IF(K20=0,"",K20/K$11) -> 0.0045553353
B21: 受取利息 | D21: =IF(C21=0,"",C21/C$11) | E21: 1252 | F21: =IF(E21=0,"",E21/E$11) -> 1.0623772e-06 | G21: 84858 | H21: =IF(G21=0,"",G21/G$11) -> 7.1795077e-05 | I21: 267463 | J21: =IF(I21=0,"",I21/I$11) -> 0.00022365123 | K21: 161697 | L21: =IF(K21=0,"",K21/K$11) -> 0.00026024275
B22: 受取配当金 | D22: =IF(C22=0,"",C22/C$11) | E22: 30500 | F22: =IF(E22=0,"",E22/E$11) -> 2.5880596e-05 | G22: 30500 | H22: =IF(G22=0,"",G22/G$11) -> 2.5804872e-05 | I22: 30500 | J22: =IF(I22=0,"",I22/I$11) -> 2.5503948e-05 | K22: 30950 | L22: =IF(K22=0,"",K22/K$11) -> 4.9812385e-05
B23: 受取延滞料 | D23: =IF(C23=0,"",C23/C$11) | E23: 170242 | F23: =IF(E23=0,"",E23/E$11) -> 0.00014445785 | G23: 147416 | H23: =IF(G23=0,"",G23/G$11) -> 0.00012472298 | I23: 96879 | J23: =IF(I23=0,"",I23/I$11) -> 8.1009738e-05 | K23: 58794 | L23: =IF(K23=0,"",K23/K$11) -> 9.4625827e-05
B24: 受取奨励金 | D24: =IF(C24=0,"",C24/C$11) | E24: 2284370 | F24: =IF(E24=0,"",E24/E$11) -> 0.0019383887 | G24: 2406729 | H24: =IF(G24=0,"",G24/G$11) -> 0.0020362405 | I24: 2513377 | J24: =IF(I24=0,"",I24/I$11) -> 0.0021016733 | K24: 1184146 | L24: =IF(K24=0,"",K24/K$11) -> 0.0019058202
B25: 受取運賃・配達収入 | D25: =IF(C25=0,"",C25/C$11) | F25: =IF(E25=0,"",E25/E$11) | H25: =IF(G25=0,"",G25/G$11) | J25: =IF(I25=0,"",I25/I$11) | K25: 163350 | L25: =IF(K25=0,"",K25/K$11) -> 0.00026290317
B26: 雑収入 | D26: =IF(C26=0,"",C26/C$11) | E26: 8141731 | F26: =IF(E26=0,"",E26/E$11) -> 0.006908618 | G26: 8067387 | H26: =IF(G26=0,"",G26/G$11) -> 0.0068255046 | I26: 3669539 | J26: =IF(I26=0,"",I26/I$11) -> 0.0030684502 | K26: 1231436 | L26: =IF(K26=0,"",K26/K$11) -> 0.001981931
D27: =IF(C27=0,"",C27/C$11) | F27: =IF(E27=0,"",E27/E$11) | H27: =IF(G27=0,"",G27/G$11) | J27: =IF(I27=0,"",I27/I$11) | L27: =IF(K27=0,"",K27/K$11)
B28: 営業外費用 | C28: =SUM(C29:C35) -> 0 | D28: =IF(C28=0,"",C28/C$11) | E28: =SUM(E29:E35) -> 4068303 | F28: =IF(E28=0,"",E28/E$11) -> 0.0034521346 | G28: =SUM(G29:G35) -> 4132569 | H28: =IF(G28=0,"",G28/G$11) -> 0.003496407 | I28: =SUM(I29:I35) -> 4369886 | J28: =IF(I28=0,"",I28/I$11) -> 0.0036540769 | K28: =SUM(K29:K35) -> 2090167 | L28: =IF(K28=0,"",K28/K$11) -> 0.003364013
B29: 支払利息 | D29: =IF(C29=0,"",C29/C$11) | E29: 3962441 | F29: =IF(E29=0,"",E29/E$11) -> 0.003362306 | G29: 4040547 | H29: =IF(G29=0,"",G29/G$11) -> 0.0034185508 | I29: 3895556 | J29: =IF(I29=0,"",I29/I$11) -> 0.0032574445 | K29: 2090167 | L29: =IF(K29=0,"",K29/K$11) -> 0.003364013
B30: 出荷奨励金 | D30: =IF(C30=0,"",C30/C$11) | E30: 105862 | F30: =IF(E30=0,"",E30/E$11) -> 8.9828578e-05 | G30: 92022 | H30: =IF(G30=0,"",G30/G$11) -> 7.785626e-05 | I30: 94929 | J30: =IF(I30=0,"",I30/I$11) -> 7.9379157e-05 | L30: =IF(K30=0,"",K30/K$11)
B31: 雑損失 | D31: =IF(C31=0,"",C31/C$11) | F31: =IF(E31=0,"",E31/E$11) | H31: =IF(G31=0,"",G31/G$11) | I31: 379401 | J31: =IF(I31=0,"",I31/I$11) -> 0.00031725323 | L31: =IF(K31=0,"",K31/K$11)
D32: =IF(C32=0,"",C32/C$11) | F32: =IF(E32=0,"",E32/E$11) | H32: =IF(G32=0,"",G32/G$11) | J32: =IF(I32=0,"",I32/I$11) | L32: =IF(K32=0,"",K32/K$11)
D33: =IF(C33=0,"",C33/C$11) | F33: =IF(E33=0,"",E33/E$11) | H33: =IF(G33=0,"",G33/G$11) | J33: =IF(I33=0,"",I33/I$11) | L33: =IF(K33=0,"",K33/K$11)
D34: =IF(C34=0,"",C34/C$11) | F34: =IF(E34=0,"",E34/E$11) | H34: =IF(G34=0,"",G34/G$11) | J34: =IF(I34=0,"",I34/I$11) | L34: =IF(K34=0,"",K34/K$11)
D35: =IF(C35=0,"",C35/C$11) | F35: =IF(E35=0,"",E35/E$11) | H35: =IF(G35=0,"",G35/G$11) | J35: =IF(I35=0,"",I35/I$11) | L35: =IF(K35=0,"",K35/K$11)
B36: 経常利益 | C36: =C19+C20-C28 -> 0 | D36: =IF(C36=0,"",C36/C$11) | E36: =E19+E20-E28 -> 11316540 | F36: =IF(E36=0,"",E36/E$11) -> 0.0096025835 | G36: =G19+G20-G28 -> 2181381 | H36: =IF(G36=0,"",G36/G$11) -> 0.0018455822 | I36: =I19+I20-I28 -> 8067784 | J36: =IF(I36=0,"",I36/I$11) -> 0.0067462408 | K36: =K19+K20-K28 -> 21165907 | L36: =IF(K36=0,"",K36/K$11) -> 0.034065405
B37: 特別利益 | C37: =SUM(C38:C43) -> 0 | D37: =IF(C37=0,"",C37/C$11) | E37: =SUM(E38:E43) -> 1887177 | F37: =IF(E37=0,"",E37/E$11) -> 0.001601353 | G37: =SUM(G38:G43) -> 1845918 | H37: =IF(G37=0,"",G37/G$11) -> 0.0015617599 | I37: =SUM(I38:I43) -> 234000 | J37: =IF(I37=0,"",I37/I$11) -> 0.00019566964 | K37: =SUM(K38:K43) -> 0 | L37: =IF(K37=0,"",K37/K$11)
B38: 固定資産売却益 | D38: =IF(C38=0,"",C38/C$11) | E38: 1711177 | F38: =IF(E38=0,"",E38/E$11) -> 0.0014520092 | G38: 1608918 | H38: =IF(G38=0,"",G38/G$11) -> 0.0013612434 | J38: =IF(I38=0,"",I38/I$11) | L38: =IF(K38=0,"",K38/K$11)
B39: 貸倒引当金戻入 | D39: =IF(C39=0,"",C39/C$11) | E39: 176000 | F39: =IF(E39=0,"",E39/E$11) -> 0.00014934377 | G39: 237000 | H39: =IF(G39=0,"",G39/G$11) -> 0.00020051655 | I39: 234000 | J39: =IF(I39=0,"",I39/I$11) -> 0.00019566964 | L39: =IF(K39=0,"",K39/K$11)
D40: =IF(C40=0,"",C40/C$11) | F40: =IF(E40=0,"",E40/E$11) | H40: =IF(G40=0,"",G40/G$11) | J40: =IF(I40=0,"",I40/I$11) | L40: =IF(K40=0,"",K40/K$11)
D41: =IF(C41=0,"",C41/C$11) | F41: =IF(E41=0,"",E41/E$11) | H41: =IF(G41=0,"",G41/G$11) | J41: =IF(I41=0,"",I41/I$11) | L41: =IF(K41=0,"",K41/K$11)
D42: =IF(C42=0,"",C42/C$11) | F42: =IF(E42=0,"",E42/E$11) | H42: =IF(G42=0,"",G42/G$11) | J42: =IF(I42=0,"",I42/I$11) | L42: =IF(K42=0,"",K42/K$11)
D43: =IF(C43=0,"",C43/C$11) | F43: =IF(E43=0,"",E43/E$11) | H43: =IF(G43=0,"",G43/G$11) | J43: =IF(I43=0,"",I43/I$11) | L43: =IF(K43=0,"",K43/K$11)
B44: 特別損失 | C44: =SUM(C45:C50) -> 0 | D44: =IF(C44=0,"",C44/C$11) | E44: =SUM(E45:E50) -> 438719 | F44: =IF(E44=0,"",E44/E$11) -> 0.00037227243 | G44: =SUM(G45:G50) -> 234000 | H44: =IF(G44=0,"",G44/G$11) -> 0.00019797836 | I44: =SUM(I45:I50) -> 21103139 | J44: =IF(I44=0,"",I44/I$11) -> 0.01764634 | K44: =SUM(K45:K50) -> 0 | L44: =IF(K44=0,"",K44/K$11)
B45: 固定資産売却除却損 | D45: =IF(C45=0,"",C45/C$11) | E45: 201719 | F45: =IF(E45=0,"",E45/E$11) -> 0.00017116747 | H45: =IF(G45=0,"",G45/G$11) | I45: 1 | J45: =IF(I45=0,"",I45/I$11) -> 8.3619502e-10 | L45: =IF(K45=0,"",K45/K$11)
B46: 貸倒引当金繰入 | D46: =IF(C46=0,"",C46/C$11) | E46: 237000 | F46: =IF(E46=0,"",E46/E$11) -> 0.00020110496 | G46: 234000 | H46: =IF(G46=0,"",G46/G$11) -> 0.00019797836 | I46: 203000 | J46: =IF(I46=0,"",I46/I$11) -> 0.00016974759 | L46: =IF(K46=0,"",K46/K$11)
B47: 前期損益修正損 | D47: =IF(C47=0,"",C47/C$11) | F47: =IF(E47=0,"",E47/E$11) | H47: =IF(G47=0,"",G47/G$11) | I47: 20900138 | J47: =IF(I47=0,"",I47/I$11) -> 0.017476591 | L47: =IF(K47=0,"",K47/K$11)
D48: =IF(C48=0,"",C48/C$11) | F48: =IF(E48=0,"",E48/E$11) | H48: =IF(G48=0,"",G48/G$11) | J48: =IF(I48=0,"",I48/I$11) | L48: =IF(K48=0,"",K48/K$11)
D49: =IF(C49=0,"",C49/C$11) | F49: =IF(E49=0,"",E49/E$11) | H49: =IF(G49=0,"",G49/G$11) | J49: =IF(I49=0,"",I49/I$11) | L49: =IF(K49=0,"",K49/K$11)
D50: =IF(C50=0,"",C50/C$11) | F50: =IF(E50=0,"",E50/E$11) | H50: =IF(G50=0,"",G50/G$11) | J50: =IF(I50=0,"",I50/I$11) | L50: =IF(K50=0,"",K50/K$11)
B51: 税引前当期純利益 | C51: =C36+C37-C44 -> 0 | D51: =IF(C51=0,"",C51/C$11) | E51: =E36+E37-E44 -> 12764998 | F51: =IF(E51=0,"",E51/E$11) -> 0.010831664 | G51: =G36+G37-G44 -> 3793299 | H51: =IF(G51=0,"",G51/G$11) -> 0.0032093638 | I51: =I36+I37-I44 -> -12801355 | J51: =IF(I51=0,"",I51/I$11) -> -0.010704429 | K51: =K36+K37-K44 -> 21165907 | L51: =IF(K51=0,"",K51/K$11) -> 0.034065405
B52: 法人税等 | C52: =SUM(C53:C55) -> 0 | D52: =IF(C52=0,"",C52/C$11) | E52: =SUM(E53:E55) -> 3658100 | F52: =IF(E52=0,"",E52/E$11) -> 0.0031040593 | G52: =SUM(G53:G55) -> 864400 | H52: =IF(G52=0,"",G52/G$11) -> 0.00073133546 | I52: =SUM(I53:I55) -> 2283300 | J52: =IF(I52=0,"",I52/I$11) -> 0.0019092841 | K52: =SUM(K53:K55) -> 0 | L52: =IF(K52=0,"",K52/K$11)
B53: 法人税等 | D53: =IF(C53=0,"",C53/C$11) | E53: 3658100 | F53: =IF(E53=0,"",E53/E$11) -> 0.0031040593 | G53: 864400 | H53: =IF(G53=0,"",G53/G$11) -> 0.00073133546 | I53: 2283300 | J53: =IF(I53=0,"",I53/I$11) -> 0.0019092841 | L53: =IF(K53=0,"",K53/K$11)
D55: =IF(C55=0,"",C55/C$11) | F55: =IF(E55=0,"",E55/E$11) | H55: =IF(G55=0,"",G55/G$11) | J55: =IF(I55=0,"",I55/I$11) | L55: =IF(K55=0,"",K55/K$11)
B56: 税引後当期純利益 | C56: =C51-C52 -> 0 | D56: =IF(C56=0,"",C56/C$11) | E56: =E51-E52 -> 9106898 | F56: =IF(E56=0,"",E56/E$11) -> 0.0077276048 | G56: =G51-G52 -> 2928899 | H56: =IF(G56=0,"",G56/G$11) -> 0.0024780283 | I56: =I51-I52 -> -15084655 | J56: =IF(I56=0,"",I56/I$11) -> -0.012613713 | K56: =K51-K52 -> 21165907 | L56: =IF(K56=0,"",K56/K$11) -> 0.034065405
E58: 9106898 | G58: 2928899 | I58: -15084655 | K58: 21165907
C59: =C58=C56 -> 1 | E59: =E58=E56 -> 1 | G59: =G58=G56 -> 1 | I59: =I58=I56 -> 1 | K59: =K58=K56 -> 1
B61: ※進行期（K列）は2026年4〜9月の試算表（6か月累計）。前年同期（2025年4〜9月）はPLハイライトの参考欄。決算書では売上高を「商品売上高」1本で表示（内訳は試算表のみ）。
B62: ※受託販売は2019年10月以降、受託手数料のみの純額表示（個別注記表）。2026/3期の前期損益修正損20,900千円は過年度保険解約訂正額（非経常）。

Sheet CR
H4: (単位：千円)
B5: 科目 | C5: ='BS(借方)'!C4 -> ●●年●月期 | E5: ='BS(借方)'!D4 -> 24年3月期 | G5: ='BS(借方)'!E4 -> 25年3月期 | I5: ='BS(借方)'!F4 -> 26年3月期 | K5: ='BS(借方)'!G4 -> 27年3月期 4〜9月TB
C6: 帳簿価額 | D6: 売上高比 | E6: 帳簿価額 | F6: 売上高比 | G6: 帳簿価額 | H6: 売上高比 | I6: 帳簿価額 | J6: 売上高比 | K6: 帳簿価額 | L6: 売上高比
A7: IMに貼るときは非表示→ | B7: 売上 | C7: =PL!C11 -> 0 | D7: - | E7: =PL!E11 -> 1178489098 | F7: - | G7: =PL!G11 -> 1181947340 | H7: - | I7: =PL!I11 -> 1195893269 | J7: - | K7: =PL!K11 -> 621331427 | L7: -
B8: 期首原材料棚卸高 | D8: =IF(C8=0,"",C8/C$7) | F8: =IF(E8=0,"",E8/E$7) | H8: =IF(G8=0,"",G8/G$7) | J8: =IF(I8=0,"",I8/I$7) | L8: =IF(K8=0,"",K8/K$7)
B9: 原材料仕入高 | D9: =IF(C9=0,"",C9/C$7) | F9: =IF(E9=0,"",E9/E$7) | H9: =IF(G9=0,"",G9/G$7) | J9: =IF(I9=0,"",I9/I$7) | L9: =IF(K9=0,"",K9/K$7)
B10: 小計 | D10: =IF(C10=0,"",C10/C$7) | F10: =IF(E10=0,"",E10/E$7) | H10: =IF(G10=0,"",G10/G$7) | J10: =IF(I10=0,"",I10/I$7) | L10: =IF(K10=0,"",K10/K$7)
B11: 期末原材料棚卸高 | D11: =IF(C11=0,"",C11/C$7) | F11: =IF(E11=0,"",E11/E$7) | H11: =IF(G11=0,"",G11/G$7) | J11: =IF(I11=0,"",I11/I$7) | L11: =IF(K11=0,"",K11/K$7)
D12: =IF(C12=0,"",C12/C$7) | F12: =IF(E12=0,"",E12/E$7) | H12: =IF(G12=0,"",G12/G$7) | J12: =IF(I12=0,"",I12/I$7) | L12: =IF(K12=0,"",K12/K$7)
D13: =IF(C13=0,"",C13/C$7) | F13: =IF(E13=0,"",E13/E$7) | H13: =IF(G13=0,"",G13/G$7) | J13: =IF(I13=0,"",I13/I$7) | L13: =IF(K13=0,"",K13/K$7)
B14: 材料費 | C14: =SUM(C8:C13) -> 0 | D14: =IF(C14=0,"",C14/C$7) | E14: =SUM(E8:E13) -> 0 | F14: =IF(E14=0,"",E14/E$7) | G14: =SUM(G8:G13) -> 0 | H14: =IF(G14=0,"",G14/G$7) | I14: =SUM(I8:I13) -> 0 | J14: =IF(I14=0,"",I14/I$7) | K14: =SUM(K8:K13) -> 0 | L14: =IF(K14=0,"",K14/K$7)
D15: =IF(C15=0,"",C15/C$7) | F15: =IF(E15=0,"",E15/E$7) | H15: =IF(G15=0,"",G15/G$7) | J15: =IF(I15=0,"",I15/I$7) | L15: =IF(K15=0,"",K15/K$7)
D18: =IF(C18=0,"",C18/C$7) | F18: =IF(E18=0,"",E18/E$7) | H18: =IF(G18=0,"",G18/G$7) | J18: =IF(I18=0,"",I18/I$7) | L18: =IF(K18=0,"",K18/K$7)
D19: =IF(C19=0,"",C19/C$7) | F19: =IF(E19=0,"",E19/E$7) | H19: =IF(G19=0,"",G19/G$7) | J19: =IF(I19=0,"",I19/I$7) | L19: =IF(K19=0,"",K19/K$7)
D20: =IF(C20=0,"",C20/C$7) | F20: =IF(E20=0,"",E20/E$7) | H20: =IF(G20=0,"",G20/G$7) | J20: =IF(I20=0,"",I20/I$7) | L20: =IF(K20=0,"",K20/K$7)
D21: =IF(C21=0,"",C21/C$7) | F21: =IF(E21=0,"",E21/E$7) | H21: =IF(G21=0,"",G21/G$7) | J21: =IF(I21=0,"",I21/I$7) | L21: =IF(K21=0,"",K21/K$7)
D22: =IF(C22=0,"",C22/C$7) | F22: =IF(E22=0,"",E22/E$7) | H22: =IF(G22=0,"",G22/G$7) | J22: =IF(I22=0,"",I22/I$7) | L22: =IF(K22=0,"",K22/K$7)
B23: 労務費 | C23: =SUM(C15:C22) -> 0 | D23: =IF(C23=0,"",C23/C$7) | E23: =SUM(E15:E22) -> 0 | F23: =IF(E23=0,"",E23/E$7) | G23: =SUM(G15:G22) -> 0 | H23: =IF(G23=0,"",G23/G$7) | I23: =SUM(I15:I22) -> 0 | J23: =IF(I23=0,"",I23/I$7) | K23: =SUM(K15:K22) -> 0 | L23: =IF(K23=0,"",K23/K$7)
D24: =IF(C24=0,"",C24/C$7) | F24: =IF(E24=0,"",E24/E$7) | H24: =IF(G24=0,"",G24/G$7) | J24: =IF(I24=0,"",I24/I$7) | L24: =IF(K24=0,"",K24/K$7)
D28: =IF(C28=0,"",C28/C$7) | F28: =IF(E28=0,"",E28/E$7) | H28: =IF(G28=0,"",G28/G$7) | J28: =IF(I28=0,"",I28/I$7) | L28: =IF(K28=0,"",K28/K$7)
D29: =IF(C29=0,"",C29/C$7) | F29: =IF(E29=0,"",E29/E$7) | H29: =IF(G29=0,"",G29/G$7) | J29: =IF(I29=0,"",I29/I$7) | L29: =IF(K29=0,"",K29/K$7)
D30: =IF(C30=0,"",C30/C$7) | F30: =IF(E30=0,"",E30/E$7) | H30: =IF(G30=0,"",G30/G$7) | J30: =IF(I30=0,"",I30/I$7) | L30: =IF(K30=0,"",K30/K$7)
D31: =IF(C31=0,"",C31/C$7) | F31: =IF(E31=0,"",E31/E$7) | H31: =IF(G31=0,"",G31/G$7) | J31: =IF(I31=0,"",I31/I$7) | L31: =IF(K31=0,"",K31/K$7)
D32: =IF(C32=0,"",C32/C$7) | F32: =IF(E32=0,"",E32/E$7) | H32: =IF(G32=0,"",G32/G$7) | J32: =IF(I32=0,"",I32/I$7) | L32: =IF(K32=0,"",K32/K$7)
B33: 外注加工費 | C33: =SUM(C24:C32) -> 0 | D33: =IF(C33=0,"",C33/C$7) | E33: =SUM(E24:E32) -> 0 | F33: =IF(E33=0,"",E33/E$7) | G33: =SUM(G24:G32) -> 0 | H33: =IF(G33=0,"",G33/G$7) | I33: =SUM(I24:I32) -> 0 | J33: =IF(I33=0,"",I33/I$7) | K33: =SUM(K24:K32) -> 0 | L33: =IF(K33=0,"",K33/K$7)
D34: =IF(C34=0,"",C34/C$7) | F34: =IF(E34=0,"",E34/E$7) | H34: =IF(G34=0,"",G34/G$7) | J34: =IF(I34=0,"",I34/I$7) | L34: =IF(K34=0,"",K34/K$7)
D35: =IF(C35=0,"",C35/C$7) | F35: =IF(E35=0,"",E35/E$7) | H35: =IF(G35=0,"",G35/G$7) | J35: =IF(I35=0,"",I35/I$7) | L35: =IF(K35=0,"",K35/K$7)
D36: =IF(C36=0,"",C36/C$7) | F36: =IF(E36=0,"",E36/E$7) | H36: =IF(G36=0,"",G36/G$7) | J36: =IF(I36=0,"",I36/I$7) | L36: =IF(K36=0,"",K36/K$7)
D39: =IF(C39=0,"",C39/C$7) | F39: =IF(E39=0,"",E39/E$7) | H39: =IF(G39=0,"",G39/G$7) | J39: =IF(I39=0,"",I39/I$7) | L39: =IF(K39=0,"",K39/K$7)
D40: =IF(C40=0,"",C40/C$7) | F40: =IF(E40=0,"",E40/E$7) | H40: =IF(G40=0,"",G40/G$7) | J40: =IF(I40=0,"",I40/I$7) | L40: =IF(K40=0,"",K40/K$7)
D41: =IF(C41=0,"",C41/C$7) | F41: =IF(E41=0,"",E41/E$7) | H41: =IF(G41=0,"",G41/G$7) | J41: =IF(I41=0,"",I41/I$7) | L41: =IF(K41=0,"",K41/K$7)
D42: =IF(C42=0,"",C42/C$7) | F42: =IF(E42=0,"",E42/E$7) | H42: =IF(G42=0,"",G42/G$7) | J42: =IF(I42=0,"",I42/I$7) | L42: =IF(K42=0,"",K42/K$7)
D43: =IF(C43=0,"",C43/C$7) | F43: =IF(E43=0,"",E43/E$7) | H43: =IF(G43=0,"",G43/G$7) | J43: =IF(I43=0,"",I43/I$7) | L43: =IF(K43=0,"",K43/K$7)
D44: =IF(C44=0,"",C44/C$7) | F44: =IF(E44=0,"",E44/E$7) | H44: =IF(G44=0,"",G44/G$7) | J44: =IF(I44=0,"",I44/I$7) | L44: =IF(K44=0,"",K44/K$7)
D45: =IF(C45=0,"",C45/C$7) | F45: =IF(E45=0,"",E45/E$7) | H45: =IF(G45=0,"",G45/G$7) | J45: =IF(I45=0,"",I45/I$7) | L45: =IF(K45=0,"",K45/K$7)
B46: 経費 | C46: =SUM(C34:C45) -> 0 | D46: =IF(C46=0,"",C46/C$7) | E46: =SUM(E34:E45) -> 0 | F46: =IF(E46=0,"",E46/E$7) | G46: =SUM(G34:G45) -> 0 | H46: =IF(G46=0,"",G46/G$7) | I46: =SUM(I34:I45) -> 0 | J46: =IF(I46=0,"",I46/I$7) | K46: =SUM(K34:K45) -> 0 | L46: =IF(K46=0,"",K46/K$7)
B47: 当期製造費用 | C47: =C14+C23+C33+C46 -> 0 | D47: =IF(C47=0,"",C47/C$7) | E47: =E14+E23+E33+E46 -> 0 | F47: =IF(E47=0,"",E47/E$7) | G47: =G14+G23+G33+G46 -> 0 | H47: =IF(G47=0,"",G47/G$7) | I47: =I14+I23+I33+I46 -> 0 | J47: =IF(I47=0,"",I47/I$7) | K47: =K14+K23+K33+K46 -> 0 | L47: =IF(K47=0,"",K47/K$7)
B48: 期首仕掛品棚卸高 | D48: =IF(C48=0,"",C48/C$7) | E48: =SUM(E36:E47) -> 0 | F48: =IF(E48=0,"",E48/E$7) | G48: =SUM(G36:G47) -> 0 | H48: =IF(G48=0,"",G48/G$7) | I48: =SUM(I36:I47) -> 0 | J48: =IF(I48=0,"",I48/I$7) | K48: =SUM(K36:K47) -> 0 | L48: =IF(K48=0,"",K48/K$7)
B49: 合計 | C49: =SUM(C47:C48) -> 0 | D49: =IF(C49=0,"",C49/C$7) | E49: =SUM(E47:E48) -> 0 | F49: =IF(E49=0,"",E49/E$7) | G49: =SUM(G47:G48) -> 0 | H49: =IF(G49=0,"",G49/G$7) | I49: =SUM(I47:I48) -> 0 | J49: =IF(I49=0,"",I49/I$7) | K49: =SUM(K47:K48) -> 0 | L49: =IF(K49=0,"",K49/K$7)
B50: 期末仕掛品棚卸高 | D50: =IF(C50=0,"",C50/C$7) | E50: =SUM(E40:E49) -> 0 | F50: =IF(E50=0,"",E50/E$7) | G50: =SUM(G40:G49) -> 0 | H50: =IF(G50=0,"",G50/G$7) | I50: =SUM(I40:I49) -> 0 | J50: =IF(I50=0,"",I50/I$7) | K50: =SUM(K40:K49) -> 0 | L50: =IF(K50=0,"",K50/K$7)
B51: 当期製造原価 | C51: =C49-C50 -> 0 | D51: =IF(C51=0,"",C51/C$7) | E51: =E49-E50 -> 0 | F51: =IF(E51=0,"",E51/E$7) | G51: =G49-G50 -> 0 | H51: =IF(G51=0,"",G51/G$7) | I51: =I49-I50 -> 0 | J51: =IF(I51=0,"",I51/I$7) | K51: =K49-K50 -> 0 | L51: =IF(K51=0,"",K51/K$7)

Sheet SGA
A1: ■ 貼付範囲 B2:L40 → 企業概要書「販売費及び一般管理費」（売上行・C:D列・空行は非表示）
L2: (単位：千円)
B3: 科目 | C3: ='BS(借方)'!C4 -> ●●年●月期 | E3: ='BS(借方)'!D4 -> 24年3月期 | G3: ='BS(借方)'!E4 -> 25年3月期 | I3: ='BS(借方)'!F4 -> 26年3月期 | K3: ='BS(借方)'!G4 -> 27年3月期 4〜9月TB
C4: 帳簿価額 | D4: 売上高比 | E4: 帳簿価額 | F4: 売上高比 | G4: 帳簿価額 | H4: 売上高比 | I4: 帳簿価額 | J4: 売上高比 | K4: 帳簿価額 | L4: 売上高比
B5: 売上 | C5: =PL!C11 -> 0 | E5: =PL!E11 -> 1178489098 | F5: - | G5: =PL!G11 -> 1181947340 | H5: - | I5: =PL!I11 -> 1195893269 | J5: - | K5: =PL!K11 -> 621331427 | L5: - | M5: ←IMに貼るときは非表示
B6: 役員報酬 | E6: 22200000 | F6: =E6/$E$5 -> 0.01883768 | G6: 22200000 | H6: =G6/$G$5 -> 0.018782563 | I6: 15360000 | J6: =I6/$I$5 -> 0.012843956 | K6: 6150000 | L6: =K6/$K$5 -> 0.009898099
B7: 給料手当 | E7: 73148460 | F7: =E7/$E$5 -> 0.062069696 | G7: 74179162 | H7: =G7/$G$5 -> 0.062760124 | I7: 71673365 | J7: =I7/$I$5 -> 0.059932911 | K7: 30948228 | L7: =K7/$K$5 -> 0.049809533
B8: 賞与 | E8: 6002150 | F8: =E8/$E$5 -> 0.0050930891 | G8: 5692500 | H8: =G8/$G$5 -> 0.0048162044 | J8: =I8/$I$5 -> 0 | L8: =K8/$K$5 -> 0
B9: 退職金共済掛金 | E9: 3175000 | F9: =E9/$E$5 -> 0.0026941276 | G9: 3166000 | H9: =G9/$G$5 -> 0.0026786303 | I9: 3026000 | J9: =I9/$I$5 -> 0.0025303261 | K9: 1139000 | L9: =K9/$K$5 -> 0.0018331601
B10: 退職金 | F10: =E10/$E$5 -> 0 | G10: 356400 | H10: =G10/$G$5 -> 0.00030153628 | I10: 746960 | J10: =I10/$I$5 -> 0.00062460423 | L10: =K10/$K$5 -> 0
B11: 法定福利費 | E11: 15154087 | F11: =E11/$E$5 -> 0.012858911 | G11: 14913183 | H11: =G11/$G$5 -> 0.012617468 | I11: 13295870 | J11: =I11/$I$5 -> 0.01111794 | K11: 5327882 | L11: =K11/$K$5 -> 0.0085749437
B12: 福利厚生費 | E12: 594849 | F12: =E12/$E$5 -> 0.00050475562 | G12: 899852 | H12: =G12/$G$5 -> 0.00076133003 | I12: 460243 | J12: =I12/$I$5 -> 0.00038485291 | K12: 124395 | L12: =K12/$K$5 -> 0.00020020716
B13: 広告宣伝費 | E13: 203020 | F13: =E13/$E$5 -> 0.00017227143 | G13: 114444 | H13: =G13/$G$5 -> 9.6826649e-05 | I13: 89300 | J13: =I13/$I$5 -> 7.4672216e-05 | K13: 10000 | L13: =K13/$K$5 -> 1.609447e-05
B14: 旅費交通費 | E14: 44957 | F14: =E14/$E$5 -> 3.8147998e-05 | G14: 212048 | H14: =G14/$G$5 -> 0.00017940562 | I14: 78650 | J14: =I14/$I$5 -> 6.5766739e-05 | K14: 9490 | L14: =K14/$K$5 -> 1.5273652e-05
B15: 通信費 | E15: 1434812 | F15: =E15/$E$5 -> 0.0012175013 | G15: 1143086 | H15: =G15/$G$5 -> 0.00096712092 | I15: 1191701 | J15: =I15/$I$5 -> 0.00099649445 | K15: 502790 | L15: =K15/$K$5 -> 0.00080921386
B16: 車両関連費 | E16: 8475295 | F16: =E16/$E$5 -> 0.0071916618 | G16: 10126052 | H16: =G16/$G$5 -> 0.0085672615 | I16: 9861597 | J16: =I16/$I$5 -> 0.0082462183 | K16: 4665234 | L16: =K16/$K$5 -> 0.0075084469
B17: 運賃 | E17: 27546757 | F17: =E17/$E$5 -> 0.023374639 | G17: 29493733 | H17: =G17/$G$5 -> 0.024953509 | I17: 28996599 | J17: =I17/$I$5 -> 0.024246812 | K17: 12047802 | L17: =K17/$K$5 -> 0.019390299
B18: 振込手数料負担金 | E18: 122652 | F18: =E18/$E$5 -> 0.00010407563 | G18: 207322 | H18: =G18/$G$5 -> 0.00017540714 | I18: 215198 | J18: =I18/$I$5 -> 0.0001799475 | K18: 96382 | L18: =K18/$K$5 -> 0.00015512172
B19: 委託手数料 | E19: 3709319 | F19: =E19/$E$5 -> 0.0031475208 | G19: 3538995 | H19: =G19/$G$5 -> 0.002994207 | I19: 4075300 | J19: =I19/$I$5 -> 0.0034077456 | K19: 2223299 | L19: =K19/$K$5 -> 0.0035782819
B20: 接待交際費 | E20: 3474959 | F20: =E20/$E$5 -> 0.002948656 | G20: 2485921 | H20: =G20/$G$5 -> 0.0021032418 | I20: 1580405 | J20: =I20/$I$5 -> 0.0013215268 | K20: 1059003 | L20: =K20/$K$5 -> 0.0017044092
B21: 水道光熱費 | E21: 4423538 | F21: =E21/$E$5 -> 0.0037535672 | G21: 4700697 | H21: =G21/$G$5 -> 0.0039770782 | I21: 4684668 | J21: =I21/$I$5 -> 0.0039172961 | K21: 2318547 | L21: =K21/$K$5 -> 0.0037315785
B22: 消耗品費 | E22: 35750 | F22: =E22/$E$5 -> 3.0335452e-05 | H22: =G22/$G$5 -> 0 | I22: 95055 | J22: =I22/$I$5 -> 7.9484518e-05 | L22: =K22/$K$5 -> 0
B23: 租税公課 | E23: 14464767 | F23: =E23/$E$5 -> 0.012273993 | G23: 12813800 | H23: =G23/$G$5 -> 0.010841261 | I23: 12176834 | J23: =I23/$I$5 -> 0.010182208 | K23: 3616634 | L23: =K23/$K$5 -> 0.0058207807
B24: 支払手数料 | E24: 1546474 | F24: =E24/$E$5 -> 0.0013122514 | G24: 1527460 | H24: =G24/$G$5 -> 0.0012923249 | I24: 1596627 | J24: =I24/$I$5 -> 0.0013350916 | K24: 1290018 | L24: =K24/$K$5 -> 0.0020762156
B25: 諸会費 | E25: 181000 | F25: =E25/$E$5 -> 0.00015358649 | G25: 141000 | H25: =G25/$G$5 -> 0.00011929465 | I25: 138400 | J25: =I25/$I$5 -> 0.00011572939 | K25: 116000 | L25: =K25/$K$5 -> 0.00018669585
B26: 寄付金 | E26: 13000 | F26: =E26/$E$5 -> 1.1031074e-05 | G26: 71000 | H26: =G26/$G$5 -> 6.0070358e-05 | I26: 11000 | J26: =I26/$I$5 -> 9.1981453e-06 | K26: 7000 | L26: =K26/$K$5 -> 1.1266129e-05
B27: リース料 | E27: 4711966 | F27: =E27/$E$5 -> 0.0039983111 | G27: 6710821 | H27: =G27/$G$5 -> 0.0056777665 | I27: 6227194 | J27: =I27/$I$5 -> 0.0052071486 | K27: 3082216 | L27: =K27/$K$5 -> 0.0049606633
B28: 支払保険料 | E28: 2772322 | F28: =E28/$E$5 -> 0.0023524375 | G28: 1431329 | H28: =G28/$G$5 -> 0.0012109922 | I28: 1541660 | J28: =I28/$I$5 -> 0.0012891284 | K28: 325790 | L28: =K28/$K$5 -> 0.00052434174
B29: 修繕費 | E29: 1169740 | F29: =E29/$E$5 -> 0.000992576 | G29: 707846 | H29: =G29/$G$5 -> 0.00059888117 | I29: 123750 | J29: =I29/$I$5 -> 0.00010347913 | K29: 702130 | L29: =K29/$K$5 -> 0.001130041
B30: 事務用消耗品費 | E30: 2033078 | F30: =E30/$E$5 -> 0.0017251564 | G30: 1934919 | H30: =G30/$G$5 -> 0.0016370602 | I30: 2335738 | J30: =I30/$I$5 -> 0.0019531325 | K30: 1408266 | L30: =K30/$K$5 -> 0.0022665295
B31: 減価償却費 | E31: 13663684 | F31: =E31/$E$5 -> 0.011594239 | G31: 12557564 | H31: =G31/$G$5 -> 0.01062447 | I31: 8878970 | J31: =I31/$I$5 -> 0.0074245505 | K31: 3654000 | L31: =K31/$K$5 -> 0.0058809193
B32: 雑費 | E32: 4521805 | F32: =E32/$E$5 -> 0.0038369511 | G32: 4393320 | H32: =G32/$G$5 -> 0.0037170184 | I32: 4689970 | J32: =I32/$I$5 -> 0.0039217296 | K32: 1899133 | L32: =K32/$K$5 -> 0.0030565539
F33: =E33/$E$5 -> 0 | H33: =G33/$G$5 -> 0 | J33: =I33/$I$5 -> 0 | L33: =K33/$K$5 -> 0
B34: 消費税引当金 | F34: =E34/$E$5 -> 0 | H34: =G34/$G$5 -> 0 | J34: =I34/$I$5 -> 0 | K34: 3023000 | L34: =K34/$K$5 -> 0.0048653583
F35: =E35/$E$5 -> 0 | H35: =G35/$G$5 -> 0 | J35: =I35/$I$5 -> 0 | L35: =K35/$K$5 -> 0
F36: =E36/$E$5 -> 0 | H36: =G36/$G$5 -> 0 | J36: =I36/$I$5 -> 0 | L36: =K36/$K$5 -> 0
F37: =E37/$E$5 -> 0 | H37: =G37/$G$5 -> 0 | J37: =I37/$I$5 -> 0 | L37: =K37/$K$5 -> 0
F38: =E38/$E$5 -> 0 | H38: =G38/$G$5 -> 0 | J38: =I38/$I$5 -> 0 | L38: =K38/$K$5 -> 0
F39: =E39/$E$5 -> 0 | H39: =G39/$G$5 -> 0 | J39: =I39/$I$5 -> 0 | L39: =K39/$K$5 -> 0
B40: 販売費および一般管理費合計 | C40: =SUM(C6:C39) -> 0 | E40: =SUM(E6:E39) -> 214823441 | F40: =E40/E5 -> 0.18228717 | G40: =SUM(G6:G39) -> 215718454 | H40: =G40/G5 -> 0.18251105 | I40: =SUM(I6:I39) -> 193151054 | J40: =I40/I5 -> 0.16151195 | K40: =SUM(K6:K39) -> 85746239 | L40: =K40/K5 -> 0.13800403
B42: 決算書・試算表の販管費計 | E42: 214823441 | G42: 215718454 | I42: 193151054 | K42: 85746239
B43: チェック | E43: =EXACT(E40,E42) -> 1 | G43: =EXACT(G40,G42) -> 1 | I43: =EXACT(I40,I42) -> 1 | K43: =EXACT(K40,K42) -> 1
B45: ※2026/3期（I列）の賞与〜広告宣伝費は記入時に1行ずれていたため決算書の内訳に合わせて修正（賞与0、退職金共済掛金3,026千円、退職金747千円、法定福利費13,296千円、福利厚生費460千円、広告宣伝費89千円）。
B46: ※消費税は税込経理。決算では納付額を租税公課、試算表では消費税引当金に計上。進行期（K列）は2026年4〜9月の6か月累計。

Sheet VR→ 

Sheet 株式価値 
A1: 作業不要（自動作成）
F2: (単位：千円)
C3: min | D3: 差（グラフ作成用） | E3: max
B4: インカム | C4: 0 | D4: 0 | E4: 0 | F4: 100 | I4: ｚ
B5: マーケット | C5: ='EV EBITDAマルチプル'!K7 -> -87379098 | D5: =E5-C5 -> 37467417 | E5: ='EV EBITDAマルチプル'!M7 -> -49911682 | F5: 0
B6: コスト | C6: =年買法!K6 -> 65761604 | D6: =E6-C6 -> 20886293 | E6: =年買法!M6 -> 86647897 | F6: 0

Sheet 修正BS(借方)
E2: (単位：千円)
B3: 資産の部
B4: 科目 | C4: ='BS(借方)'!F4 -> 26年3月期 | D4: 修正額 | E4: 修正後
B5: 【流動資産】 | C5: =SUM(C6:C19) -> 249704912 | D5: =SUM(D6:D19) -> 203000 | E5: =C5+D5 -> 249907912
B6: ='BS(借方)'!B6 -> 現金及び預金 | C6: ='BS(借方)'!F6 -> 210887077 | E6: =C6+D6 -> 210887077
B7: ='BS(借方)'!B7 -> 売掛金 | C7: ='BS(借方)'!F7 -> 19608899 | E7: =C7+D7 -> 19608899
B8: ='BS(借方)'!B8 -> 資材肥料売掛金 | C8: ='BS(借方)'!F8 -> 1227419 | E8: =C8+D8 -> 1227419
B9: ='BS(借方)'!B9 -> 棚卸資産 | C9: ='BS(借方)'!F9 -> 14596695 | E9: =C9+D9 -> 14596695
B10: ='BS(借方)'!B10 -> 立替金 | C10: ='BS(借方)'!F10 -> 0 | E10: =C10+D10 -> 0
B11: ='BS(借方)'!B11 -> 未収入金 | C11: ='BS(借方)'!F11 -> 3011112 | E11: =C11+D11 -> 3011112
B12: ='BS(借方)'!B12 -> 仮払金 | C12: ='BS(借方)'!F12 -> 493135 | E12: =C12+D12 -> 493135
B13: ='BS(借方)'!B13 -> 前払費用 | C13: ='BS(借方)'!F13 -> 83575 | E13: =C13+D13 -> 83575
B14: ='BS(借方)'!B14 -> 仮払税金等 | C14: ='BS(借方)'!F14 -> 0 | E14: =C14+D14 -> 0
B15: ='BS(借方)'!B15 -> 貸倒引当金 | C15: ='BS(借方)'!F15 -> -203000 | D15: 203000 | E15: =C15+D15 -> 0 | F15: 個別に回収可能性を判断するため全額戻入（貸倒実績は要確認）
B16: ='BS(借方)'!B16 -> 0 | C16: ='BS(借方)'!F16 -> 0 | E16: =C16+D16 -> 0
B17: ='BS(借方)'!B17 -> 0 | C17: ='BS(借方)'!F17 -> 0 | E17: =C17+D17 -> 0
B18: ='BS(借方)'!B18 -> 0 | C18: ='BS(借方)'!F18 -> 0 | E18: =C18+D18 -> 0
E19: =C19+D19 -> 0
B20: 【固定資産】 | C20: =C21+C35+C46 -> 235485192 | D20: =D21+D35+D46 -> -20225824 | E20: =C20+D20 -> 2.1525937e+08
B21: ［有形固定資産］ | C21: =SUM(C22:C34) -> 196905728 | D21: =SUM(D22:D34) -> -25312229 | E21: =C21+D21 -> 1.715935e+08
B22: ='BS(借方)'!B22 -> 建物 | C22: ='BS(借方)'!F22 -> 92065694 | E22: =C22+D22 -> 92065694
B23: ='BS(借方)'!B23 -> 建物付属設備 | C23: ='BS(借方)'!F23 -> 11399836 | E23: =C23+D23 -> 11399836
B24: ='BS(借方)'!B24 -> 構築物 | C24: ='BS(借方)'!F24 -> 284395 | E24: =C24+D24 -> 284395
B25: ='BS(借方)'!B25 -> 機械装置 | C25: ='BS(借方)'!F25 -> 2 | E25: =C25+D25 -> 2
B26: ='BS(借方)'!B26 -> 車両運搬具 | C26: ='BS(借方)'!F26 -> 15 | E26: =C26+D26 -> 15
B27: ='BS(借方)'!B27 -> 工具器具備品 | C27: ='BS(借方)'!F27 -> 18546 | E27: =C27+D27 -> 18546
B28: ='BS(借方)'!B28 -> 土地 | C28: ='BS(借方)'!F28 -> 93137240 | D28: =土地!E8 -> -25312229 | E28: =C28+D28 -> 67825011 | F28: 固定資産税評価額（R8年度）÷0.7で時価を推計（「土地」シート）
B29: ='BS(借方)'!B29 -> 減価償却累計額 | C29: ='BS(借方)'!F29 -> 0 | E29: =C29+D29 -> 0
B30: ='BS(借方)'!B30 -> 0 | C30: ='BS(借方)'!F30 -> 0 | E30: =C30+D30 -> 0
B31: ='BS(借方)'!B31 -> 0 | C31: ='BS(借方)'!F31 -> 0 | E31: =C31+D31 -> 0
B32: ='BS(借方)'!B32 -> 0 | C32: ='BS(借方)'!F32 -> 0 | E32: =C32+D32 -> 0
B33: ='BS(借方)'!B33 -> 0 | C33: ='BS(借方)'!F33 -> 0 | E33: =C33+D33 -> 0
E34: =C34+D34 -> 0
B35: ［無形固定資産］ | C35: =SUM(C36:C45) -> 2527395 | D35: =SUM(D36:D45) -> -2155595 | E35: =C35+D35 -> 371800
B36: ='BS(借方)'!B36 -> 電話加入権 | C36: ='BS(借方)'!F36 -> 2155595 | D36: -2155595 | E36: =C36+D36 -> 0 | F36: 換金価値なしとしてゼロ評価
B37: ='BS(借方)'!B37 -> ソフトウェア | C37: ='BS(借方)'!F37 -> 371800 | E37: =C37+D37 -> 371800
B38: ='BS(借方)'!B38 -> 0 | C38: ='BS(借方)'!F38 -> 0 | E38: =C38+D38 -> 0
B39: ='BS(借方)'!B39 -> 0 | C39: ='BS(借方)'!F39 -> 0 | E39: =C39+D39 -> 0
B40: ='BS(借方)'!B40 -> 0 | C40: ='BS(借方)'!F40 -> 0 | E40: =C40+D40 -> 0
E41: =C41+D41 -> 0
E42: =C42+D42 -> 0
E43: =C43+D43 -> 0
E44: =C44+D44 -> 0
E45: =C45+D45 -> 0
B46: ［投資その他資産］ | C46: =SUM(C47:C54) -> 36052069 | D46: =SUM(D47:D54) -> 7242000 | E46: =C46+D46 -> 43294069
B47: ='BS(借方)'!B47 -> 投資有価証券 | C47: ='BS(借方)'!F47 -> 2600000 | D47: =有価証券!E9 -> 7242000 | E47: =C47+D47 -> 9842000 | F47: フィデアHD株式を時価評価（「有価証券」シート）
B48: ='BS(借方)'!B48 -> 出資金 | C48: ='BS(借方)'!F48 -> 75000 | E48: =C48+D48 -> 75000
B49: ='BS(借方)'!B49 -> 長期前払費用 | C49: ='BS(借方)'!F49 -> 74500 | E49: =C49+D49 -> 74500
B50: ='BS(借方)'!B50 -> 保証金 | C50: ='BS(借方)'!F50 -> 33302569 | E50: =C50+D50 -> 33302569
B51: ='BS(借方)'!B51 -> 事業保険積立金 | C51: ='BS(借方)'!F51 -> 0 | E51: =C51+D51 -> 0
B52: ='BS(借方)'!B52 -> 0 | C52: ='BS(借方)'!F52 -> 0 | E52: =C52+D52 -> 0
B53: ='BS(借方)'!B53 -> 0 | C53: ='BS(借方)'!F53 -> 0 | E53: =C53+D53 -> 0
B54: ='BS(借方)'!B54 -> 0 | C54: ='BS(借方)'!F54 -> 0 | E54: =C54+D54 -> 0
E55: =C55+D55 -> 0
B56: 【繰延資産】 | C56: =SUM(C57:C59) -> 0 | D56: =SUM(D57:D59) -> 0 | E56: =C56+D56 -> 0
B57: ='BS(借方)'!B57 -> 繰延資産 | C57: ='BS(借方)'!F57 -> 0 | E57: =C57+D57 -> 0
E58: =C58+D58 -> 0
E59: =C59+D59 -> 0
B60: 【繰延税金資産】 | C60: 0 | D60: 0 | E60: =C60+D60 -> 0
B61: 資産合計 | C61: =C5+C20+C56+C60 -> 485190104 | D61: =D5+D20+D56+D60 -> -20022824 | E61: =C61+D61 -> 4.6516728e+08

Sheet 売掛・棚卸
E2: (単位：千円)
A3: 売掛金 | B3: 相手先 | C3: 帳簿価額 | D3: 評価差額 | E3: 評価額 | F3: 調整事由
B4: 売掛金（青果物） | C4: ='BS(借方)'!F7 -> 19608899 | D4: 0 | E4: =SUM(C4,D4) -> 19608899 | F4: 年齢表未受領のため簿価評価（長期滞留の有無は要確認）
B5: 資材肥料売掛金 | C5: ='BS(借方)'!F8 -> 1227419 | D5: 0 | E5: =SUM(C5,D5) -> 1227419 | F5: 同上
B8: 合計 | C8: =SUM(C4:C7) -> 20836318 | D8: =SUM(D4:D7) -> 0 | E8: =C8+D8 -> 20836318
E12: (単位：千円)
A13: 商品在庫 | B13: 相手先 | C13: 帳簿価額 | D13: 評価差額 | E13: 評価額 | F13: 調整事由
B14: 棚卸資産（青果物・資材） | C14: ='BS(借方)'!F9 -> 14596695 | D14: 0 | E14: =C14+D14 -> 14596695 | F14: 青果物は短期回転。廃棄を要する滞留在庫はなく帳簿は概ね実態どおり（第2回面談）。資材の滞留有無は要確認
B18: 合計 | C18: =SUM(C14:C17) -> 14596695 | D18: =SUM(D14:D17) -> 0 | E18: =C18+D18 -> 14596695

Sheet 減価償却
E2: (単位：千円)
B3: 資産 | C3: 帳簿価額 | D3: 評価差額 | E3: 評価額 | F3: 調整事由
B4: 建物 | C4: ='BS(借方)'!F22 -> 92065694 | D4: 0 | E4: =SUM(C4,D4) -> 92065694 | F4: 固定資産台帳未受領。別表十六で償却不足なしを確認し簿価評価
B5: 建物付属設備 | C5: ='BS(借方)'!F23 -> 11399836 | D5: 0 | E5: =SUM(C5,D5) -> 11399836 | F5: 簿価評価
B6: 構築物 | C6: ='BS(借方)'!F24 -> 284395 | D6: 0 | E6: =SUM(C6,D6) -> 284395 | F6: 簿価評価
B7: 車両運搬具・工具器具備品等 | C7: ='BS(借方)'!F25+'BS(借方)'!F26+'BS(借方)'!F27 -> 18563 | D7: 0 | E7: =SUM(C7,D7) -> 18563 | F7: 簿価評価
B8: 合計 | C8: =SUM(C4:C7) -> 103768488 | D8: =SUM(D4:D7) -> 0 | E8: =C8+D8 -> 103768488

Sheet 土地
F2: (単位：千円)
B3: 内容・所在地 | C3: 地積(㎡) | D3: 帳簿価額 | E3: 評価差額 | F3: 時価評価額 | G3: 調整事由
B4: 本社・市場／鶴岡市宝田一丁目4-2 | C4: 3100.22 | D4: 70757240 | E4: =F4-D4 -> -19526947 | F4: ='不動産(所有)'!I4 -> 51230293 | G4: 固定資産税評価額（R8年度）÷0.7にて時価を推計（鑑定・路線価で要確認）
B5: パッケージ場／鶴岡市宝田一丁目5-1 | C5: 900.5 | D5: 21380000 | E5: =F5-D5 -> -6293860 | F5: ='不動産(所有)'!I10 -> 15086140 | G5: 固定資産税評価額（R8年度）÷0.7にて時価を推計（鑑定・路線価で要確認）
B6: 旧倉庫敷地（駐車場）／東田川郡庄内町長沼字宮前304-7 | C6: 261.81 | D6: 1000000 | E6: =F6-D6 -> 508578.57 | F6: ='不動産(所有)'!I13 -> 1508578.6 | G6: 固定資産税評価額（R8年度）÷0.7にて時価を推計（鑑定・路線価で要確認）
B8: 合計 | C8: =SUM(C4:C7) -> 4262.53 | D8: =SUM(D4:D7) -> 93137240 | E8: =SUM(E4:E7) -> -25312229 | F8: =SUM(F4:F7) -> 67825011

Sheet 保険
E2: (単位：千円)
B3: 保険商品 | C3: 帳簿価額 | D3: 評価差額 | E3: 評価額 | F3: 調整事由
B4: 事業保険積立金 | C4: 0 | D4: =E4-C4 -> 0 | E4: 0 | F4: 2026/3期に全額取崩し済（前期損益修正損20,900千円）。簿外の解約返戻金の有無は要確認
B8: 合計 | C8: =SUM(C4:C7) -> 0 | D8: =SUM(D4:D7) -> 0 | E8: =C8+D8 -> 0

Sheet 有価証券
F2: (単位：千円)
B3: 銘柄 | C3: 数量 | D3: 帳簿価額 | E3: 評価差額 | F3: 評価額 | G3: 調整事由
B4: 株式）フィデアホールディングス | C4: 3000 | D4: 1200000 | E4: =F4-D4 -> 7242000 | F4: =2814*C4 -> 8442000 | G4: 2026年9月18日終値（2,814円）を元に時価を算出（算定日終値で要更新）
B5: 株式）(株)庄果・出資金）鶴岡信用金庫ほか | C5: - | D5: 1400000 | E5: =F5-D5 -> 0 | F5: =D5 -> 1400000 | G5: 取引関係上の保有。市場価格なし（簿価評価）
B9: 合計 | C9: - | D9: =SUM(D4:D8) -> 2600000 | E9: =SUM(E4:E8) -> 7242000 | F9: =D9+E9 -> 9842000

Sheet 修正BS(貸方) 
E2: (単位：千円)
B3: 負債の部
B4: 科目 | C4: ='修正BS(借方)'!C4 -> 26年3月期 | D4: 修正額 | E4: 修正後
B5: 【流動負債】 | C5: =SUM(C6:C17) -> 37279523 | D5: =SUM(D6:D17) -> 0 | E5: =C5+D5 -> 37279523
B6: ='BS (貸方)'!B6 -> 買掛金 | C6: ='BS (貸方)'!F6 -> 26349122 | E6: =C6+D6 -> 26349122
B7: ='BS (貸方)'!B7 -> 未払金 | C7: ='BS (貸方)'!F7 -> 6630301 | E7: =C7+D7 -> 6630301
B8: ='BS (貸方)'!B8 -> 仮受金 | C8: ='BS (貸方)'!F8 -> 0 | E8: =C8+D8 -> 0
B9: ='BS (貸方)'!B9 -> 預り金 | C9: ='BS (貸方)'!F9 -> 281300 | E9: =C9+D9 -> 281300
B10: ='BS (貸方)'!B10 -> 未払法人税等 | C10: ='BS (貸方)'!F10 -> 1851300 | E10: =C10+D10 -> 1851300
B11: ='BS (貸方)'!B11 -> 未払消費税 | C11: ='BS (貸方)'!F11 -> 2167500 | E11: =C11+D11 -> 2167500
B12: ='BS (貸方)'!B12 -> 0 | C12: ='BS (貸方)'!F12 -> 0 | E12: =C12+D12 -> 0
B13: ='BS (貸方)'!B13 -> 0 | C13: ='BS (貸方)'!F13 -> 0 | E13: =C13+D13 -> 0
B14: ='BS (貸方)'!B14 -> 0 | C14: ='BS (貸方)'!F14 -> 0 | E14: =C14+D14 -> 0
B15: ='BS (貸方)'!B15 -> 0 | C15: ='BS (貸方)'!F15 -> 0 | E15: =C15+D15 -> 0
B16: ='BS (貸方)'!B16 -> 0 | C16: ='BS (貸方)'!F16 -> 0 | E16: =C16+D16 -> 0
E17: =C17+D17 -> 0
B18: 【固定負債】 | C18: =SUM(C19:C26) -> 370038000 | D18: =SUM(D19:D26) -> 0 | E18: =C18+D18 -> 370038000
B19: ='BS (貸方)'!B19 -> 長期借入金 | C19: ='BS (貸方)'!F19 -> 361058000 | E19: =C19+D19 -> 361058000
B20: ='BS (貸方)'!B20 -> 預り保証金 | C20: ='BS (貸方)'!F20 -> 8980000 | E20: =C20+D20 -> 8980000
B21: ='BS (貸方)'!B21 -> 0 | C21: ='BS (貸方)'!F21 -> 0 | E21: =C21+D21 -> 0
B22: ='BS (貸方)'!B22 -> 0 | C22: ='BS (貸方)'!F22 -> 0 | E22: =C22+D22 -> 0
B23: ='BS (貸方)'!B23 -> 0 | C23: ='BS (貸方)'!F23 -> 0 | E23: =C23+D23 -> 0
E24: =C24+D24 -> 0
E25: =C25+D25 -> 0
E26: =C26+D26 -> 0
B27: 【繰延税金負債】 | C27: 0 | D27: =税効果!E18 -> 2531300 | E27: =C27+D27 -> 2531300
B28: 負債合計 | C28: =C5+C18+C27 -> 407317523 | D28: =D5+D18+D27 -> 2531300 | E28: =C28+D28 -> 409848823
B34: 純資産の部
B35: 【資本金】 | C35: =SUM(C36:C38) -> 40000000 | D35: =SUM(D36:D38) -> 0 | E35: =C35+D35 -> 40000000
B36: ='BS (貸方)'!B36 -> 資本金 | C36: ='BS (貸方)'!F36 -> 40000000 | E36: =C36+D36 -> 40000000
E37: =C37+D37 -> 0
E38: =C38+D38 -> 0
B39: 【資本剰余金】 | C39: =SUM(C40:C42) -> 0 | D39: =SUM(D40:D42) -> 0 | E39: =C39+D39 -> 0
E40: =C40+D40 -> 0
E41: =C41+D41 -> 0
E42: =C42+D42 -> 0
B43: 【利益剰余金】 | C43: =SUM(C44:C47) -> 37872581 | D43: =SUM(D44:D47) -> 0 | E43: =C43+D43 -> 37872581
B44: ='BS (貸方)'!B44 -> 利益準備金 | C44: ='BS (貸方)'!F44 -> 2080000 | E44: =C44+D44 -> 2080000
B45: ='BS (貸方)'!B45 -> 繰越利益剰余金 | C45: ='BS (貸方)'!F45 -> 35792581 | E45: =C45+D45 -> 35792581
B46: ='BS (貸方)'!B46 -> 0 | C46: ='BS (貸方)'!F46 -> 0 | E46: =C46+D46 -> 0
E47: =C47+D47 -> 0
B48: 【自己株式】 | C48: 0 | D48: 0 | E48: =C48+D48 -> 0
B49: 【評価修正額】 | D49: =SUM(D50:D51) -> -22554124 | E49: =C49+D49 -> -22554124
B50: 修正額 | D50: ='修正BS(借方)'!D61-'修正BS(借方)'!D60-(D28-D27) -> -20022824 | E50: =C50+D50 -> -20022824
B51: 修正税効果 | D51: ='修正BS(借方)'!D60-D27 -> -2531300 | E51: =C51+D51 -> -2531300
B52: 純資産合計 | C52: =C35+C39+C43+C48 -> 77872581 | D52: =D35+D39+D43+D48+D49 -> -22554124 | E52: =C52+D52 -> 55318457
B53: 負債・純資産合計 | C53: =C28+C52 -> 485190104 | D53: =D28+D52 -> -20022824 | E53: =C53+D53 -> 4.6516728e+08
C55: =C53='修正BS(借方)'!C61 -> 1

Sheet 未払人件費・賞与
D2: (単位：千円) | E2: (単位：千円) | F2: (単位：千円)
B3: 2026年4月支払給与（3月後半分） | C3: 未払日数 | D3: 未払給与引当額 | E3: 概算社会保険料 | F3: 未払給与引当額
B4: 2837000 | C4: 3/16〜3/31分 | D4: 0 | E4: 0 | F4: 0 | G4: 未払給与2,837千円は未払金に計上済のため追加計上なし
E7: (単位：千円)
B8: 賞与（規定なし・業績連動） | C8: 支給対象月数 | D8: 経過月数 | E8: 引当額 | F8: 概算社会保険料 | G8: 社保考慮後引当不足
B9: 0 | C9: - | D9: - | E9: 0 | F9: 0 | G9: =E9+F9 -> 0 | H9: 賞与規定なし。2026/3期は支給なし。引当不要と判断（要確認）

Sheet 退職金
J2: (単位：千円)
B3: № | C3: 氏名 | D3: 勤続年数(年) | E3: 基本給 | F3: 支給倍率 | G3: 退職理由率 | H3: 要支給額 | I3: 中退共積立額 | J3: 引当不足
C4: 全従業員 | H4: 0 | I4: 0 | J4: =H4-I4 -> 0
B6: ※中小企業退職金共済（掛金3,026千円/年）・オリックス生命で外部積立。退職時の会社の追加持出しは基本的にないとの認識（退職金規程で要確認）。
C10: 合計 | H10: =SUM(H4:H9) -> 0 | I10: =SUM(I4:I9) -> 0 | J10: =H10-I10 -> 0

Sheet 税効果
E2: (単位：千円)
B3: 修正科目 | C3: 適用判定 | D3: 修正額 | E3: 繰延税金資産/負債 | F3: 備考
B4: 貸倒引当金 | C4: 〇 | D4: ='修正BS(借方)'!D15 -> 203000 | E4: =-D4*-0.34 -> 69020 | F4: 戻入益に課税
B5: 土地 | C5: × | D5: ='修正BS(借方)'!D28 -> -25312229 | E5: 0 | F5: 事業用不動産で売却予定がなく、実現可能性が低いため除外
B6: 電話加入権 | C6: × | D6: ='修正BS(借方)'!D36 -> -2155595 | E6: 0 | F6: 流動性がないため除外
B7: 投資有価証券 | C7: 〇 | D7: ='修正BS(借方)'!D47 -> 7242000 | E7: =-D7*-0.34 -> 2462280 | F7: 評価益に課税
B18: 合計 | C18: - | D18: =SUM(D4:D17) -> -20022824 | E18: =SUM(E4:E17) -> 2531300 | F18: 繰延税金負債（評価益×実効税率34%）

Sheet ネットキャッシュ
F2: (単位：千円)
B3: キャッシュライクアイテム | C3: 金額 | E3: デットライクアイテム | F3: 金額
B4: 現金及び預金 | C4: ='修正BS(借方)'!E6 -> 210887077 | E4: 短期借入金
B5: 役員貸付金 | E5: 長期借入金 | F5: ='修正BS(貸方) '!E19 -> 361058000
B6: 従業員貸付金 | E6: 社債
B7: 立替金 | E7: 役員借入金
B8: 保険積立金 | E8: 未払法人税 | F8: ='修正BS(貸方) '!E10 -> 1851300
B9: 投資有価証券（上場株式・時価） | C9: =有価証券!F4 -> 8442000 | E9: 資産除去債務
B10: 売却予定不動産 | E10: 役員退職慰労金
B11: 売却予定車両 | E11: 営業循環外前受金
E12: ファイナンスリース債務
B13: 合計 | C13: =SUM(C4:C12) -> 219329077 | E13: 合計 | F13: =SUM(F4:F12) -> 362909300
B15: ネットキャッシュ | C15: =C13-F13 -> -143580223 | E15: ネットデット | F15: =F13-C13 -> 143580223
B19: ※預り保証金8,980千円・保証金33,303千円は事業上の預託・預り金としてネットキャッシュに含めていない（取扱いは要確認）。(株)庄果株式・信金出資は取引関係上の保有のため除外。

Sheet 修正PL
K2: (単位：千円)
B3: 科目 | C3: ='BS(借方)'!C4 -> ●●年●月期 | F3: ='BS(借方)'!D4 -> 24年3月期 | I3: ='BS(借方)'!E4 -> 25年3月期 | L3: ='BS(借方)'!F4 -> 26年3月期 | O3: ='BS(借方)'!G4 -> 27年3月期 4〜9月TB
C4: 帳簿価額 | D4: 修正額 | E4: 修正後 | F4: 帳簿価額 | G4: 修正額 | H4: 修正後 | I4: 帳簿価額 | J4: 修正額 | K4: 修正後 | L4: 帳簿価額 | M4: 修正額 | N4: 修正後 | O4: 帳簿価額 | P4: 修正額 | Q4: 修正後
B5: =PL!B5 -> 商品売上高 | C5: =PL!C5 -> 0 | E5: =C5+D5 -> 0 | F5: =PL!E5 -> 1179974308 | H5: =F5+G5 -> 1179974308 | I5: =PL!G5 -> 1183308630 | K5: =I5+J5 -> 1183308630 | L5: =PL!I5 -> 1197530299 | N5: =L5+M5 -> 1197530299 | O5: =PL!K5 -> 568871022 | Q5: =O5+P5 -> 568871022
B6: =PL!B6 -> 資材売上高 | C6: =PL!C6 -> 0 | E6: =C6+D6 -> 0 | F6: =PL!E6 -> 0 | H6: =F6+G6 -> 0 | I6: =PL!G6 -> 0 | K6: =I6+J6 -> 0 | L6: =PL!I6 -> 0 | N6: =L6+M6 -> 0 | O6: =PL!K6 -> 5369372 | Q6: =O6+P6 -> 5369372
B7: =PL!B7 -> 資材売上（自社） | C7: =PL!C7 -> 0 | E7: =C7+D7 -> 0 | F7: =PL!E7 -> 0 | H7: =F7+G7 -> 0 | I7: =PL!G7 -> 0 | K7: =I7+J7 -> 0 | L7: =PL!I7 -> 0 | N7: =L7+M7 -> 0 | O7: =PL!K7 -> 9473775 | Q7: =O7+P7 -> 9473775
B8: =PL!B8 -> 主婦センター費 | C8: =PL!C8 -> 0 | E8: =C8+D8 -> 0 | F8: =PL!E8 -> 0 | H8: =F8+G8 -> 0 | I8: =PL!G8 -> 0 | K8: =I8+J8 -> 0 | L8: =PL!I8 -> 0 | N8: =L8+M8 -> 0 | O8: =PL!K8 -> 18416492 | Q8: =O8+P8 -> 18416492
B9: =PL!B9 -> 委託手数料収入 | C9: =PL!C9 -> 0 | E9: =C9+D9 -> 0 | F9: =PL!E9 -> 0 | H9: =F9+G9 -> 0 | I9: =PL!G9 -> 0 | K9: =I9+J9 -> 0 | L9: =PL!I9 -> 0 | N9: =L9+M9 -> 0 | O9: =PL!K9 -> 19958506 | Q9: =O9+P9 -> 19958506
B10: =PL!B10 -> 売上割戻金 | C10: =PL!C10 -> 0 | E10: =C10+D10 -> 0 | F10: =PL!E10 -> -1485210 | H10: =F10+G10 -> -1485210 | I10: =PL!G10 -> -1361290 | K10: =I10+J10 -> -1361290 | L10: =PL!I10 -> -1637030 | N10: =L10+M10 -> -1637030 | O10: =PL!K10 -> -757740 | Q10: =O10+P10 -> -757740
B11: 売上高 | C11: =SUM(C5:C10) -> 0 | D11: =SUM(D5:D10) -> 0 | E11: =C11+D11 -> 0 | F11: =SUM(F5:F10) -> 1178489098 | G11: =SUM(G5:G10) -> 0 | H11: =F11+G11 -> 1178489098 | I11: =SUM(I5:I10) -> 1181947340 | J11: =SUM(J5:J10) -> 0 | K11: =I11+J11 -> 1181947340 | L11: =SUM(L5:L10) -> 1195893269 | M11: =SUM(M5:M10) -> 0 | N11: =L11+M11 -> 1195893269 | O11: =SUM(O5:O10) -> 621331427 | P11: =SUM(P5:P10) -> 0 | Q11: =O11+P11 -> 621331427
B12: =PL!B12 -> 期首棚卸高 | C12: =PL!C12 -> 0 | E12: =C12+D12 -> 0 | F12: =PL!E12 -> 15470384 | H12: =F12+G12 -> 15470384 | I12: =PL!G12 -> 9859795 | K12: =I12+J12 -> 9859795 | L12: =PL!I12 -> 15443609 | N12: =L12+M12 -> 15443609 | O12: =PL!K12 -> 14596695 | Q12: =O12+P12 -> 14596695
B13: =PL!B13 -> 仕入高 | C13: =PL!C13 -> 0 | E13: =C13+D13 -> 0 | F13: =PL!E13 -> 953298320 | H13: =F13+G13 -> 953298320 | I13: =PL!G13 -> 976235640 | K13: =I13+J13 -> 976235640 | L13: =PL!I13 -> 996035389 | N13: =L13+M13 -> 996035389 | O13: =PL!K13 -> 514967990 | Q13: =O13+P13 -> 514967990
B14: =PL!B14 -> 期末棚卸高 | C14: =PL!C14 -> 0 | E14: =C14+D14 -> 0 | F14: =PL!E14 -> -9859795 | H14: =F14+G14 -> -9859795 | I14: =PL!G14 -> -15443609 | K14: =I14+J14 -> -15443609 | L14: =PL!I14 -> -14596695 | N14: =L14+M14 -> -14596695 | O14: =PL!K14 -> -14405198 | Q14: =O14+P14 -> -14405198
B15: =PL!B15 -> 0 | C15: =PL!C15 -> 0 | E15: =C15+D15 -> 0 | F15: =PL!E15 -> 0 | H15: =F15+G15 -> 0 | I15: =PL!G15 -> 0 | K15: =I15+J15 -> 0 | L15: =PL!I15 -> 0 | N15: =L15+M15 -> 0 | O15: =PL!K15 -> 0 | Q15: =O15+P15 -> 0
B16: 売上原価 | C16: =SUM(C12:C15) -> 0 | D16: =SUM(D12:D15) -> 0 | E16: =C16+D16 -> 0 | F16: =SUM(F12:F15) -> 958908909 | G16: =SUM(G12:G15) -> 0 | H16: =F16+G16 -> 958908909 | I16: =SUM(I12:I15) -> 970651826 | J16: =SUM(J12:J15) -> 0 | K16: =I16+J16 -> 970651826 | L16: =SUM(L12:L15) -> 996882303 | M16: =SUM(M12:M15) -> 0 | N16: =L16+M16 -> 996882303 | O16: =SUM(O12:O15) -> 515159487 | P16: =SUM(P12:P15) -> 0 | Q16: =O16+P16 -> 515159487
B17: 売上総利益 | C17: =C11-C16 -> 0 | D17: =D11-D16 -> 0 | E17: =C17+D17 -> 0 | F17: =F11-F16 -> 219580189 | G17: =G11-G16 -> 0 | H17: =F17+G17 -> 219580189 | I17: =I11-I16 -> 211295514 | J17: =J11-J16 -> 0 | K17: =I17+J17 -> 211295514 | L17: =L11-L16 -> 199010966 | M17: =M11-M16 -> 0 | N17: =L17+M17 -> 199010966 | O17: =O11-O16 -> 106171940 | P17: =P11-P16 -> 0 | Q17: =O17+P17 -> 106171940
B18: 販売費及び一般管理費 | C18: =修正SGA!C39 -> 0 | D18: =修正SGA!D39 -> 0 | E18: =C18+D18 -> 0 | F18: =修正SGA!F39 -> 214823441 | G18: =修正SGA!G39 -> -20041508 | H18: =F18+G18 -> 194781933 | I18: =修正SGA!I39 -> 215718454 | J18: =修正SGA!J39 -> -20235707 | K18: =I18+J18 -> 195482747 | L18: =修正SGA!L39 -> 193151054 | M18: =修正SGA!M39 -> -6379024.2 | N18: =L18+M18 -> 1.8677203e+08 | O18: =修正SGA!O39 -> 85746239 | P18: =修正SGA!P39 -> -1406434.1 | Q18: =O18+P18 -> 84339805
B19: 営業利益 | C19: =C17- C18 -> 0 | D19: =D17- D18 -> 0 | E19: =C19+D19 -> 0 | F19: =F17- F18 -> 4756748 | G19: =G17- G18 -> 20041508 | H19: =F19+G19 -> 24798256 | I19: =I17- I18 -> -4422940 | J19: =J17- J18 -> 20235707 | K19: =I19+J19 -> 15812767 | L19: =L17- L18 -> 5859912 | M19: =M17- M18 -> 6379024.2 | N19: =L19+M19 -> 12238936 | O19: =O17- O18 -> 20425701 | P19: =P17- P18 -> 1406434.1 | Q19: =O19+P19 -> 21832135
B20: 営業外収益 | C20: =SUM(C21:C27) -> 0 | D20: =SUM(D21:D27) -> 0 | E20: =C20+D20 -> 0 | F20: =SUM(F21:F27) -> 10628095 | G20: =SUM(G21:G27) -> -2284370 | H20: =F20+G20 -> 8343725 | I20: =SUM(I21:I27) -> 10736890 | J20: =SUM(J21:J27) -> -2406729 | K20: =I20+J20 -> 8330161 | L20: =SUM(L21:L27) -> 6577758 | M20: =SUM(M21:M27) -> -2513377 | N20: =L20+M20 -> 4064381 | O20: =SUM(O21:O27) -> 2830373 | P20: =SUM(P21:P27) -> -1184146 | Q20: =O20+P20 -> 1646227
B21: =PL!B21 -> 受取利息 | C21: =PL!C21 -> 0 | E21: =C21+D21 -> 0 | F21: =PL!E21 -> 1252 | H21: =F21+G21 -> 1252 | I21: =PL!G21 -> 84858 | K21: =I21+J21 -> 84858 | L21: =PL!I21 -> 267463 | N21: =L21+M21 -> 267463 | O21: =PL!K21 -> 161697 | Q21: =O21+P21 -> 161697
B22: =PL!B22 -> 受取配当金 | C22: =PL!C22 -> 0 | E22: =C22+D22 -> 0 | F22: =PL!E22 -> 30500 | H22: =F22+G22 -> 30500 | I22: =PL!G22 -> 30500 | K22: =I22+J22 -> 30500 | L22: =PL!I22 -> 30500 | N22: =L22+M22 -> 30500 | O22: =PL!K22 -> 30950 | Q22: =O22+P22 -> 30950
B23: =PL!B23 -> 受取延滞料 | C23: =PL!C23 -> 0 | E23: =C23+D23 -> 0 | F23: =PL!E23 -> 170242 | H23: =F23+G23 -> 170242 | I23: =PL!G23 -> 147416 | K23: =I23+J23 -> 147416 | L23: =PL!I23 -> 96879 | N23: =L23+M23 -> 96879 | O23: =PL!K23 -> 58794 | Q23: =O23+P23 -> 58794
B24: =PL!B24 -> 受取奨励金 | C24: =PL!C24 -> 0 | E24: =C24+D24 -> 0 | F24: =PL!E24 -> 2284370 | G24: =-修正PL!F69 -> -2284370 | H24: =F24+G24 -> 0 | I24: =PL!G24 -> 2406729 | J24: =-修正PL!I69 -> -2406729 | K24: =I24+J24 -> 0 | L24: =PL!I24 -> 2513377 | M24: =-修正PL!L69 -> -2513377 | N24: =L24+M24 -> 0 | O24: =PL!K24 -> 1184146 | P24: =-修正PL!O69 -> -1184146 | Q24: =O24+P24 -> 0
B25: =PL!B25 -> 受取運賃・配達収入 | C25: =PL!C25 -> 0 | E25: =C25+D25 -> 0 | F25: =PL!E25 -> 0 | H25: =F25+G25 -> 0 | I25: =PL!G25 -> 0 | K25: =I25+J25 -> 0 | L25: =PL!I25 -> 0 | N25: =L25+M25 -> 0 | O25: =PL!K25 -> 163350 | Q25: =O25+P25 -> 163350
B26: =PL!B26 -> 雑収入 | C26: =PL!C26 -> 0 | E26: =C26+D26 -> 0 | F26: =PL!E26 -> 8141731 | H26: =F26+G26 -> 8141731 | I26: =PL!G26 -> 8067387 | K26: =I26+J26 -> 8067387 | L26: =PL!I26 -> 3669539 | N26: =L26+M26 -> 3669539 | O26: =PL!K26 -> 1231436 | Q26: =O26+P26 -> 1231436
E27: =C27+D27 -> 0 | H27: =F27+G27 -> 0 | K27: =I27+J27 -> 0 | N27: =L27+M27 -> 0 | Q27: =O27+P27 -> 0
B28: 営業外費用 | C28: =SUM(C29:C35) -> 0 | D28: =SUM(D29:D35) -> 0 | E28: =C28+D28 -> 0 | F28: =SUM(F29:F35) -> 4068303 | G28: =SUM(G29:G35) -> -105862 | H28: =F28+G28 -> 3962441 | I28: =SUM(I29:I35) -> 4132569 | J28: =SUM(J29:J35) -> -92022 | K28: =I28+J28 -> 4040547 | L28: =SUM(L29:L35) -> 4369886 | M28: =SUM(M29:M35) -> -94929 | N28: =L28+M28 -> 4274957 | O28: =SUM(O29:O35) -> 2090167 | P28: =SUM(P29:P35) -> 0 | Q28: =O28+P28 -> 2090167
B29: =PL!B29 -> 支払利息 | C29: =PL!C29 -> 0 | E29: =C29+D29 -> 0 | F29: =PL!E29 -> 3962441 | H29: =F29+G29 -> 3962441 | I29: =PL!G29 -> 4040547 | K29: =I29+J29 -> 4040547 | L29: =PL!I29 -> 3895556 | N29: =L29+M29 -> 3895556 | O29: =PL!K29 -> 2090167 | Q29: =O29+P29 -> 2090167
B30: =PL!B30 -> 出荷奨励金 | C30: =PL!C30 -> 0 | E30: =C30+D30 -> 0 | F30: =PL!E30 -> 105862 | G30: =-修正PL!F70 -> -105862 | H30: =F30+G30 -> 0 | I30: =PL!G30 -> 92022 | J30: =-修正PL!I70 -> -92022 | K30: =I30+J30 -> 0 | L30: =PL!I30 -> 94929 | M30: =-修正PL!L70 -> -94929 | N30: =L30+M30 -> 0 | O30: =PL!K30 -> 0 | P30: =-修正PL!O70 -> 0 | Q30: =O30+P30 -> 0
B31: =PL!B31 -> 雑損失 | C31: =PL!C31 -> 0 | E31: =C31+D31 -> 0 | F31: =PL!E31 -> 0 | H31: =F31+G31 -> 0 | I31: =PL!G31 -> 0 | K31: =I31+J31 -> 0 | L31: =PL!I31 -> 379401 | N31: =L31+M31 -> 379401 | O31: =PL!K31 -> 0 | Q31: =O31+P31 -> 0
B32: =PL!B32 -> 0 | C32: =PL!C32 -> 0 | E32: =C32+D32 -> 0 | F32: =PL!E32 -> 0 | H32: =F32+G32 -> 0 | I32: =PL!G32 -> 0 | K32: =I32+J32 -> 0 | L32: =PL!I32 -> 0 | N32: =L32+M32 -> 0 | O32: =PL!K32 -> 0 | Q32: =O32+P32 -> 0
B33: =PL!B33 -> 0 | C33: =PL!C33 -> 0 | E33: =C33+D33 -> 0 | F33: =PL!E33 -> 0 | H33: =F33+G33 -> 0 | I33: =PL!G33 -> 0 | K33: =I33+J33 -> 0 | L33: =PL!I33 -> 0 | N33: =L33+M33 -> 0 | O33: =PL!K33 -> 0 | Q33: =O33+P33 -> 0
B34: =PL!B34 -> 0 | C34: =PL!C34 -> 0 | E34: =C34+D34 -> 0 | F34: =PL!E34 -> 0 | H34: =F34+G34 -> 0 | I34: =PL!G34 -> 0 | K34: =I34+J34 -> 0 | L34: =PL!I34 -> 0 | N34: =L34+M34 -> 0 | O34: =PL!K34 -> 0 | Q34: =O34+P34 -> 0
E35: =C35+D35 -> 0 | H35: =F35+G35 -> 0 | K35: =I35+J35 -> 0 | N35: =L35+M35 -> 0 | Q35: =O35+P35 -> 0
B36: 経常利益 | C36: =C19+C20-C28 -> 0 | D36: =D19+D20-D28 -> 0 | E36: =C36+D36 -> 0 | F36: =F19+F20-F28 -> 11316540 | G36: =G19+G20-G28 -> 17863000 | H36: =F36+G36 -> 29179540 | I36: =I19+I20-I28 -> 2181381 | J36: =J19+J20-J28 -> 17921000 | K36: =I36+J36 -> 20102381 | L36: =L19+L20-L28 -> 8067784 | M36: =M19+M20-M28 -> 3960576.2 | N36: =L36+M36 -> 12028360 | O36: =O19+O20-O28 -> 21165907 | P36: =P19+P20-P28 -> 222288.12 | Q36: =O36+P36 -> 21388195
B37: 特別利益 | C37: =SUM(C38:C43) -> 0 | D37: =SUM(D38:D43) -> 0 | E37: =C37+D37 -> 0 | F37: =SUM(F38:F43) -> 1887177 | G37: =SUM(G38:G43) -> 0 | H37: =F37+G37 -> 1887177 | I37: =SUM(I38:I43) -> 1845918 | J37: =SUM(J38:J43) -> 0 | K37: =I37+J37 -> 1845918 | L37: =SUM(L38:L43) -> 234000 | M37: =SUM(M38:M43) -> 0 | N37: =L37+M37 -> 234000 | O37: =SUM(O38:O43) -> 0 | P37: =SUM(P38:P43) -> 0 | Q37: =O37+P37 -> 0
B38: =PL!B38 -> 固定資産売却益 | C38: =PL!C38 -> 0 | E38: =C38+D38 -> 0 | F38: =PL!E38 -> 1711177 | H38: =F38+G38 -> 1711177 | I38: =PL!G38 -> 1608918 | K38: =I38+J38 -> 1608918 | L38: =PL!I38 -> 0 | N38: =L38+M38 -> 0 | O38: =PL!K38 -> 0 | Q38: =O38+P38 -> 0
B39: =PL!B39 -> 貸倒引当金戻入 | C39: =PL!C39 -> 0 | E39: =C39+D39 -> 0 | F39: =PL!E39 -> 176000 | H39: =F39+G39 -> 176000 | I39: =PL!G39 -> 237000 | K39: =I39+J39 -> 237000 | L39: =PL!I39 -> 234000 | N39: =L39+M39 -> 234000 | O39: =PL!K39 -> 0 | Q39: =O39+P39 -> 0
B40: =PL!B40 -> 0 | C40: =PL!C40 -> 0 | E40: =C40+D40 -> 0 | F40: =PL!E40 -> 0 | H40: =F40+G40 -> 0 | I40: =PL!G40 -> 0 | K40: =I40+J40 -> 0 | L40: =PL!I40 -> 0 | N40: =L40+M40 -> 0 | O40: =PL!K40 -> 0 | Q40: =O40+P40 -> 0
B41: =PL!B41 -> 0 | C41: =PL!C41 -> 0 | E41: =C41+D41 -> 0 | F41: =PL!E41 -> 0 | H41: =F41+G41 -> 0 | I41: =PL!G41 -> 0 | K41: =I41+J41 -> 0 | L41: =PL!I41 -> 0 | N41: =L41+M41 -> 0 | O41: =PL!K41 -> 0 | Q41: =O41+P41 -> 0
B42: =PL!B42 -> 0 | C42: =PL!C42 -> 0 | E42: =C42+D42 -> 0 | F42: =PL!E42 -> 0 | H42: =F42+G42 -> 0 | I42: =PL!G42 -> 0 | K42: =I42+J42 -> 0 | L42: =PL!I42 -> 0 | N42: =L42+M42 -> 0 | O42: =PL!K42 -> 0 | Q42: =O42+P42 -> 0
E43: =C43+D43 -> 0 | H43: =F43+G43 -> 0 | K43: =I43+J43 -> 0 | N43: =L43+M43 -> 0 | Q43: =O43+P43 -> 0
B44: 特別損失 | C44: =SUM(C45:C50) -> 0 | D44: =SUM(D45:D50) -> 0 | E44: =C44+D44 -> 0 | F44: =SUM(F45:F50) -> 438719 | G44: =SUM(G45:G50) -> 0 | H44: =F44+G44 -> 438719 | I44: =SUM(I45:I50) -> 234000 | J44: =SUM(J45:J50) -> 0 | K44: =I44+J44 -> 234000 | L44: =SUM(L45:L50) -> 21103139 | M44: =SUM(M45:M50) -> 0 | N44: =L44+M44 -> 21103139 | O44: =SUM(O45:O50) -> 0 | P44: =SUM(P45:P50) -> 0 | Q44: =O44+P44 -> 0
B45: =PL!B45 -> 固定資産売却除却損 | C45: =PL!C45 -> 0 | E45: =C45+D45 -> 0 | F45: =PL!E45 -> 201719 | H45: =F45+G45 -> 201719 | I45: =PL!G45 -> 0 | K45: =I45+J45 -> 0 | L45: =PL!I45 -> 1 | N45: =L45+M45 -> 1 | O45: =PL!K45 -> 0 | Q45: =O45+P45 -> 0
B46: =PL!B46 -> 貸倒引当金繰入 | C46: =PL!C46 -> 0 | E46: =C46+D46 -> 0 | F46: =PL!E46 -> 237000 | H46: =F46+G46 -> 237000 | I46: =PL!G46 -> 234000 | K46: =I46+J46 -> 234000 | L46: =PL!I46 -> 203000 | N46: =L46+M46 -> 203000 | O46: =PL!K46 -> 0 | Q46: =O46+P46 -> 0
B47: =PL!B47 -> 前期損益修正損 | C47: =PL!C47 -> 0 | E47: =C47+D47 -> 0 | F47: =PL!E47 -> 0 | H47: =F47+G47 -> 0 | I47: =PL!G47 -> 0 | K47: =I47+J47 -> 0 | L47: =PL!I47 -> 20900138 | N47: =L47+M47 -> 20900138 | O47: =PL!K47 -> 0 | Q47: =O47+P47 -> 0
B48: =PL!B48 -> 0 | C48: =PL!C48 -> 0 | E48: =C48+D48 -> 0 | F48: =PL!E48 -> 0 | H48: =F48+G48 -> 0 | I48: =PL!G48 -> 0 | K48: =I48+J48 -> 0 | L48: =PL!I48 -> 0 | N48: =L48+M48 -> 0 | O48: =PL!K48 -> 0 | Q48: =O48+P48 -> 0
B49: =PL!B49 -> 0 | C49: =PL!C49 -> 0 | E49: =C49+D49 -> 0 | F49: =PL!E49 -> 0 | H49: =F49+G49 -> 0 | I49: =PL!G49 -> 0 | K49: =I49+J49 -> 0 | L49: =PL!I49 -> 0 | N49: =L49+M49 -> 0 | O49: =PL!K49 -> 0 | Q49: =O49+P49 -> 0
E50: =C50+D50 -> 0 | H50: =F50+G50 -> 0 | K50: =I50+J50 -> 0 | N50: =L50+M50 -> 0 | Q50: =O50+P50 -> 0
B51: 税引前当期純利益 | C51: =C36+C37-C44 -> 0 | D51: =D36+D37-D44 -> 0 | E51: =C51+D51 -> 0 | F51: =F36+F37-F44 -> 12764998 | G51: =G36+G37-G44 -> 17863000 | H51: =F51+G51 -> 30627998 | I51: =I36+I37-I44 -> 3793299 | J51: =J36+J37-J44 -> 17921000 | K51: =I51+J51 -> 21714299 | L51: =L36+L37-L44 -> -12801355 | M51: =M36+M37-M44 -> 3960576.2 | N51: =L51+M51 -> -8840778.8 | O51: =O36+O37-O44 -> 21165907 | P51: =P36+P37-P44 -> 222288.12 | Q51: =O51+P51 -> 21388195
B52: 法人税等 | C52: =SUM(C53:C55) -> 0 | D52: =SUM(D53:D55) -> 0 | E52: =C52+D52 -> 0 | F52: =SUM(F53:F55) -> 3658100 | G52: =SUM(G53:G55) -> 0 | H52: =F52+G52 -> 3658100 | I52: =SUM(I53:I55) -> 864400 | J52: =SUM(J53:J55) -> 0 | K52: =I52+J52 -> 864400 | L52: =SUM(L53:L55) -> 2283300 | M52: =SUM(M53:M55) -> 0 | N52: =L52+M52 -> 2283300 | O52: =SUM(O53:O55) -> 0 | P52: =SUM(P53:P55) -> 0 | Q52: =O52+P52 -> 0
B53: =PL!B53 -> 法人税等 | C53: =PL!C53 -> 0 | E53: =C53+D53 -> 0 | F53: =PL!E53 -> 3658100 | H53: =F53+G53 -> 3658100 | I53: =PL!G53 -> 864400 | K53: =I53+J53 -> 864400 | L53: =PL!I53 -> 2283300 | N53: =L53+M53 -> 2283300 | O53: =PL!K53 -> 0 | Q53: =O53+P53 -> 0
B54: =PL!B54 -> 0 | C54: =PL!C54 -> 0 | E54: =C54+D54 -> 0 | F54: =PL!E54 -> 0 | H54: =F54+G54 -> 0 | I54: =PL!G54 -> 0 | K54: =I54+J54 -> 0 | L54: =PL!I54 -> 0 | N54: =L54+M54 -> 0 | O54: =PL!K54 -> 0 | Q54: =O54+P54 -> 0
E55: =C55+D55 -> 0 | H55: =F55+G55 -> 0 | K55: =I55+J55 -> 0 | N55: =L55+M55 -> 0 | Q55: =O55+P55 -> 0
B56: 税引後当期純利益 | C56: =C51-C52 -> 0 | D56: =D51-D52 -> 0 | E56: =C56+D56 -> 0 | F56: =F51-F52 -> 9106898 | G56: =G51-G52 -> 17863000 | H56: =F56+G56 -> 26969898 | I56: =I51-I52 -> 2928899 | J56: =J51-J52 -> 17921000 | K56: =I56+J56 -> 20849899 | L56: =L51-L52 -> -15084655 | M56: =M51-M52 -> 3960576.2 | N56: =L56+M56 -> -11124079 | O56: =O51-O52 -> 21165907 | P56: =P51-P52 -> 222288.12 | Q56: =O56+P56 -> 21388195
F58: 9106898 | I58: 2928899 | L58: -15084655 | O58: 21165907
C59: =C58=C56 -> 1 | F59: =F58=F56 -> 1 | I59: =I58=I56 -> 1 | L59: =L58=L56 -> 1 | O59: =O58=O56 -> 1
B62: ■ 正常化調整の前提（修正SGA・修正PLの修正額、PLハイライト【調整項目】はここを参照）
B63: 項目 | F63: ='BS(借方)'!D4 -> 24年3月期 | I63: ='BS(借方)'!E4 -> 25年3月期 | L63: ='BS(借方)'!F4 -> 26年3月期 | O63: ='BS(借方)'!G4 -> 27年3月期 4〜9月TB | R63: 調整事由
B64: 退任役員の役員報酬（実績） | F64: 17400000 | I64: 17400000 | L64: 11160000 | O64: 4050000 | R64: 譲渡時に退任する役員（代表者・配偶者・監査役）と2026/5退任済みの常務取締役の報酬を全額控除。取締役〔代表者の弟〕は残留のため対象外。進行期は4〜9月の実績
B65: 代表者の顧問料（退任後） | F65: 2160000 | I65: 2160000 | L65: 2160000 | O65: 1080000 | R65: 代表者の現行報酬（月36万円）の半額＝月18万円（2026/10/16面談で合意）。顧問料のため社会保険料は連動させない
B66: 社会保険料率（概算） | F66: 0.15 | R66: 退任役員の報酬控除に連動して社会保険料（概算15%）も控除
B67: 賞与の正常化（社保込） | F67: 0 | I67: 0 | L67: =-AVERAGE(SGA!E8,SGA!G8)*(1+$F$66) -> -6724423.8 | O67: =L67*6/12 -> -3362211.9 | R67: 賞与規定はなく業績に応じて支給。2026/3期は支給なし。継続支給を前提に前2期平均（社保込）を費用計上（保守的）。進行期は6/12
B68: 寄付金 | F68: =SGA!E26 -> 13000 | I68: =SGA!G26 -> 71000 | L68: =SGA!I26 -> 11000 | O68: =SGA!K26 -> 7000 | R68: 譲渡後に発生しない費用として加算
B69: 受取奨励金（営業外収益） | F69: =PL!E24 -> 2284370 | I69: =PL!G24 -> 2406729 | L69: =PL!I24 -> 2513377 | O69: =PL!K24 -> 1184146 | R69: 毎期経常的に発生する事業関連収益として営業利益に振替（内容は要確認）
B70: 出荷奨励金（営業外費用） | F70: =PL!E30 -> 105862 | I70: =PL!G30 -> 92022 | L70: =PL!I30 -> 94929 | O70: =PL!K30 -> 0 | R70: 受取奨励金と対になる支出として同様に振替
B72: 修正後営業利益 | F72: =H19 -> 24798256 | I72: =K19 -> 15812767 | L72: =N19 -> 12238936 | O72: =Q19 -> 21832135
B73: 減価償却費 | F73: =SGA!E31 -> 13663684 | I73: =SGA!G31 -> 12557564 | L73: =SGA!I31 -> 8878970 | O73: =SGA!K31 -> 3654000
B74: 修正後EBITDA | F74: =F72+F73 -> 38461940 | I74: =I72+I73 -> 28370331 | L74: =L72+L73 -> 21117906 | O74: =O72+O73 -> 25486135
B76: ※支払利息は営業外費用のため営業利益ベースの正常収益力には含めない。特別損益（前期損益修正損・固定資産売却損益・貸倒引当金繰入/戻入）は非経常のため対象外。
B77: ※雑収入（ゴミ処理料・冷蔵庫保管料等の経常部分を含む）は内訳資料がないため加算していない（要確認）。支払保険料・接待交際費のオーナー帰属分も未確認（要確認）。

Sheet 修正SGA
K2: (単位：千円)
B3: 科目 | C3: ='BS(借方)'!C4 -> ●●年●月期 | F3: ='BS(借方)'!D4 -> 24年3月期 | I3: ='BS(借方)'!E4 -> 25年3月期 | L3: ='BS(借方)'!F4 -> 26年3月期 | O3: ='BS(借方)'!G4 -> 27年3月期 4〜9月TB
C4: 帳簿価額 | D4: 修正額 | E4: 修正後 | F4: 帳簿価額 | G4: 修正額 | H4: 修正後 | I4: 帳簿価額 | J4: 修正額 | K4: 修正後 | L4: 帳簿価額 | M4: 修正額 | N4: 修正後 | O4: 帳簿価額 | P4: 修正額 | Q4: 修正後
B5: =SGA!B6 -> 役員報酬 | C5: =SGA!C6 -> 0 | E5: =C5+D5 -> 0 | F5: =SGA!E6 -> 22200000 | G5: =-修正PL!F64+修正PL!F65 -> -15240000 | H5: =F5+G5 -> 6960000 | I5: =SGA!G6 -> 22200000 | J5: =-修正PL!I64+修正PL!I65 -> -15240000 | K5: =I5+J5 -> 6960000 | L5: =SGA!I6 -> 15360000 | M5: =-修正PL!L64+修正PL!L65 -> -9000000 | N5: =L5+M5 -> 6360000 | O5: =SGA!K6 -> 6150000 | P5: =-修正PL!O64+修正PL!O65 -> -2970000 | Q5: =O5+P5 -> 3180000
B6: =SGA!B7 -> 給料手当 | C6: =SGA!C7 -> 0 | E6: =C6+D6 -> 0 | F6: =SGA!E7 -> 73148460 | H6: =F6+G6 -> 73148460 | I6: =SGA!G7 -> 74179162 | K6: =I6+J6 -> 74179162 | L6: =SGA!I7 -> 71673365 | N6: =L6+M6 -> 71673365 | O6: =SGA!K7 -> 30948228 | Q6: =O6+P6 -> 30948228
B7: =SGA!B8 -> 賞与 | C7: =SGA!C8 -> 0 | E7: =C7+D7 -> 0 | F7: =SGA!E8 -> 6002150 | G7: =-修正PL!F67 -> 0 | H7: =F7+G7 -> 6002150 | I7: =SGA!G8 -> 5692500 | J7: =-修正PL!I67 -> 0 | K7: =I7+J7 -> 5692500 | L7: =SGA!I8 -> 0 | M7: =-修正PL!L67 -> 6724423.8 | N7: =L7+M7 -> 6724423.8 | O7: =SGA!K8 -> 0 | P7: =-修正PL!O67 -> 3362211.9 | Q7: =O7+P7 -> 3362211.9
B8: =SGA!B9 -> 退職金共済掛金 | C8: =SGA!C9 -> 0 | E8: =C8+D8 -> 0 | F8: =SGA!E9 -> 3175000 | H8: =F8+G8 -> 3175000 | I8: =SGA!G9 -> 3166000 | K8: =I8+J8 -> 3166000 | L8: =SGA!I9 -> 3026000 | N8: =L8+M8 -> 3026000 | O8: =SGA!K9 -> 1139000 | Q8: =O8+P8 -> 1139000
B9: =SGA!B10 -> 退職金 | C9: =SGA!C10 -> 0 | E9: =C9+D9 -> 0 | F9: =SGA!E10 -> 0 | H9: =F9+G9 -> 0 | I9: =SGA!G10 -> 356400 | K9: =I9+J9 -> 356400 | L9: =SGA!I10 -> 746960 | N9: =L9+M9 -> 746960 | O9: =SGA!K10 -> 0 | Q9: =O9+P9 -> 0
B10: =SGA!B11 -> 法定福利費 | C10: =SGA!C11 -> 0 | E10: =C10+D10 -> 0 | F10: =SGA!E11 -> 15154087 | G10: =-修正PL!F64*修正PL!$F$66 -> -2610000 | H10: =F10+G10 -> 12544087 | I10: =SGA!G11 -> 14913183 | J10: =-修正PL!I64*修正PL!$F$66 -> -2610000 | K10: =I10+J10 -> 12303183 | L10: =SGA!I11 -> 13295870 | M10: =-修正PL!L64*修正PL!$F$66 -> -1674000 | N10: =L10+M10 -> 11621870 | O10: =SGA!K11 -> 5327882 | P10: =-修正PL!O64*修正PL!$F$66 -> -607500 | Q10: =O10+P10 -> 4720382
B11: =SGA!B12 -> 福利厚生費 | C11: =SGA!C12 -> 0 | E11: =C11+D11 -> 0 | F11: =SGA!E12 -> 594849 | H11: =F11+G11 -> 594849 | I11: =SGA!G12 -> 899852 | K11: =I11+J11 -> 899852 | L11: =SGA!I12 -> 460243 | N11: =L11+M11 -> 460243 | O11: =SGA!K12 -> 124395 | Q11: =O11+P11 -> 124395
B12: =SGA!B13 -> 広告宣伝費 | C12: =SGA!C13 -> 0 | E12: =C12+D12 -> 0 | F12: =SGA!E13 -> 203020 | H12: =F12+G12 -> 203020 | I12: =SGA!G13 -> 114444 | K12: =I12+J12 -> 114444 | L12: =SGA!I13 -> 89300 | N12: =L12+M12 -> 89300 | O12: =SGA!K13 -> 10000 | Q12: =O12+P12 -> 10000
B13: =SGA!B14 -> 旅費交通費 | C13: =SGA!C14 -> 0 | E13: =C13+D13 -> 0 | F13: =SGA!E14 -> 44957 | H13: =F13+G13 -> 44957 | I13: =SGA!G14 -> 212048 | K13: =I13+J13 -> 212048 | L13: =SGA!I14 -> 78650 | N13: =L13+M13 -> 78650 | O13: =SGA!K14 -> 9490 | Q13: =O13+P13 -> 9490
B14: =SGA!B15 -> 通信費 | C14: =SGA!C15 -> 0 | E14: =C14+D14 -> 0 | F14: =SGA!E15 -> 1434812 | H14: =F14+G14 -> 1434812 | I14: =SGA!G15 -> 1143086 | K14: =I14+J14 -> 1143086 | L14: =SGA!I15 -> 1191701 | N14: =L14+M14 -> 1191701 | O14: =SGA!K15 -> 502790 | Q14: =O14+P14 -> 502790
B15: =SGA!B16 -> 車両関連費 | C15: =SGA!C16 -> 0 | E15: =C15+D15 -> 0 | F15: =SGA!E16 -> 8475295 | H15: =F15+G15 -> 8475295 | I15: =SGA!G16 -> 10126052 | K15: =I15+J15 -> 10126052 | L15: =SGA!I16 -> 9861597 | N15: =L15+M15 -> 9861597 | O15: =SGA!K16 -> 4665234 | Q15: =O15+P15 -> 4665234
B16: =SGA!B17 -> 運賃 | C16: =SGA!C17 -> 0 | E16: =C16+D16 -> 0 | F16: =SGA!E17 -> 27546757 | H16: =F16+G16 -> 27546757 | I16: =SGA!G17 -> 29493733 | K16: =I16+J16 -> 29493733 | L16: =SGA!I17 -> 28996599 | N16: =L16+M16 -> 28996599 | O16: =SGA!K17 -> 12047802 | Q16: =O16+P16 -> 12047802
B17: =SGA!B18 -> 振込手数料負担金 | C17: =SGA!C18 -> 0 | E17: =C17+D17 -> 0 | F17: =SGA!E18 -> 122652 | H17: =F17+G17 -> 122652 | I17: =SGA!G18 -> 207322 | K17: =I17+J17 -> 207322 | L17: =SGA!I18 -> 215198 | N17: =L17+M17 -> 215198 | O17: =SGA!K18 -> 96382 | Q17: =O17+P17 -> 96382
B18: =SGA!B19 -> 委託手数料 | C18: =SGA!C19 -> 0 | E18: =C18+D18 -> 0 | F18: =SGA!E19 -> 3709319 | H18: =F18+G18 -> 3709319 | I18: =SGA!G19 -> 3538995 | K18: =I18+J18 -> 3538995 | L18: =SGA!I19 -> 4075300 | N18: =L18+M18 -> 4075300 | O18: =SGA!K19 -> 2223299 | Q18: =O18+P18 -> 2223299
B19: =SGA!B20 -> 接待交際費 | C19: =SGA!C20 -> 0 | E19: =C19+D19 -> 0 | F19: =SGA!E20 -> 3474959 | H19: =F19+G19 -> 3474959 | I19: =SGA!G20 -> 2485921 | K19: =I19+J19 -> 2485921 | L19: =SGA!I20 -> 1580405 | N19: =L19+M19 -> 1580405 | O19: =SGA!K20 -> 1059003 | Q19: =O19+P19 -> 1059003
B20: =SGA!B21 -> 水道光熱費 | C20: =SGA!C21 -> 0 | E20: =C20+D20 -> 0 | F20: =SGA!E21 -> 4423538 | H20: =F20+G20 -> 4423538 | I20: =SGA!G21 -> 4700697 | K20: =I20+J20 -> 4700697 | L20: =SGA!I21 -> 4684668 | N20: =L20+M20 -> 4684668 | O20: =SGA!K21 -> 2318547 | Q20: =O20+P20 -> 2318547
B21: =SGA!B22 -> 消耗品費 | C21: =SGA!C22 -> 0 | E21: =C21+D21 -> 0 | F21: =SGA!E22 -> 35750 | H21: =F21+G21 -> 35750 | I21: =SGA!G22 -> 0 | K21: =I21+J21 -> 0 | L21: =SGA!I22 -> 95055 | N21: =L21+M21 -> 95055 | O21: =SGA!K22 -> 0 | Q21: =O21+P21 -> 0
B22: =SGA!B23 -> 租税公課 | C22: =SGA!C23 -> 0 | E22: =C22+D22 -> 0 | F22: =SGA!E23 -> 14464767 | H22: =F22+G22 -> 14464767 | I22: =SGA!G23 -> 12813800 | K22: =I22+J22 -> 12813800 | L22: =SGA!I23 -> 12176834 | N22: =L22+M22 -> 12176834 | O22: =SGA!K23 -> 3616634 | Q22: =O22+P22 -> 3616634
... B24: =SGA!B25 -> 諸会費 | C24: =SGA!C25 -> 0 | E24: =C24+D24 -> 0 | F24: =SGA!E25 -> 181000 | H24: =F24+G24 -> 181000 | I24: =SGA!G25 -> 141000 | K24: =I24+J24 -> 141000 | L24: =SGA!I25 -> 138400 | N24: =L24+M24 -> 138400 | O24: =SGA!K25 -> 116000 | Q24: =O24+P24 -> 116000
B25: =SGA!B26 -> 寄付金 | C25: =SGA!C26 -> 0 | E25: =C25+D25 -> 0 | F25: =SGA!E26 -> 13000 | G25: =-修正PL!F68 -> -13000 | H25: =F25+G25 -> 0 | I25: =SGA!G26 -> 71000 | J25: =-修正PL!I68 -> -71000 | K25: =I25+J25 -> 0 | L25: =SGA!I26 -> 11000 | M25: =-修正PL!L68 -> -11000 | N25: =L25+M25 -> 0 | O25: =SGA!K26 -> 7000 | P25: =-修正PL!O68 -> -7000 | Q25: =O25+P25 -> 0
B26: =SGA!B27 -> リース料 | C26: =SGA!C27 -> 0 | E26: =C26+D26 -> 0 | F26: =SGA!E27 -> 4711966 | H26: =F26+G26 -> 4711966 | I26: =SGA!G27 -> 6710821 | K26: =I26+J26 -> 6710821 | L26: =SGA!I27 -> 6227194 | N26: =L26+M26 -> 6227194 | O26: =SGA!K27 -> 3082216 | Q26: =O26+P26 -> 3082216
B27: =SGA!B28 -> 支払保険料 | C27: =SGA!C28 -> 0 | E27: =C27+D27 -> 0 | F27: =SGA!E28 -> 2772322 | H27: =F27+G27 -> 2772322 | I27: =SGA!G28 -> 1431329 | K27: =I27+J27 -> 1431329 | L27: =SGA!I28 -> 1541660 | N27: =L27+M27 -> 1541660 | O27: =SGA!K28 -> 325790 | Q27: =O27+P27 -> 325790
B28: =SGA!B29 -> 修繕費 | C28: =SGA!C29 -> 0 | E28: =C28+D28 -> 0 | F28: =SGA!E29 -> 1169740 | H28: =F28+G28 -> 1169740 | I28: =SGA!G29 -> 707846 | K28: =I28+J28 -> 707846 | L28: =SGA!I29 -> 123750 | N28: =L28+M28 -> 123750 | O28: =SGA!K29 -> 702130 | Q28: =O28+P28 -> 702130
B29: =SGA!B30 -> 事務用消耗品費 | C29: =SGA!C30 -> 0 | E29: =C29+D29 -> 0 | F29: =SGA!E30 -> 2033078 | H29: =F29+G29 -> 2033078 | I29: =SGA!G30 -> 1934919 | K29: =I29+J29 -> 1934919 | L29: =SGA!I30 -> 2335738 | N29: =L29+M29 -> 2335738 | O29: =SGA!K30 -> 1408266 | Q29: =O29+P29 -> 1408266
B30: =SGA!B31 -> 減価償却費 | C30: =SGA!C31 -> 0 | E30: =C30+D30 -> 0 | F30: =SGA!E31 -> 13663684 | H30: =F30+G30 -> 13663684 | I30: =SGA!G31 -> 12557564 | K30: =I30+J30 -> 12557564 | L30: =SGA!I31 -> 8878970 | N30: =L30+M30 -> 8878970 | O30: =SGA!K31 -> 3654000 | Q30: =O30+P30 -> 3654000
B31: =SGA!B32 -> 雑費 | C31: =SGA!C32 -> 0 | E31: =C31+D31 -> 0 | F31: =SGA!E32 -> 4521805 | H31: =F31+G31 -> 4521805 | I31: =SGA!G32 -> 4393320 | K31: =I31+J31 -> 4393320 | L31: =SGA!I32 -> 4689970 | N31: =L31+M31 -> 4689970 | O31: =SGA!K32 -> 1899133 | Q31: =O31+P31 -> 1899133
B32: =SGA!B33 -> 0 | C32: =SGA!C33 -> 0 | E32: =C32+D32 -> 0 | F32: =SGA!E33 -> 0 | H32: =F32+G32 -> 0 | I32: =SGA!G33 -> 0 | K32: =I32+J32 -> 0 | L32: =SGA!I33 -> 0 | N32: =L32+M32 -> 0 | O32: =SGA!K33 -> 0 | Q32: =O32+P32 -> 0
B33: =SGA!B34 -> 消費税引当金 | C33: =SGA!C34 -> 0 | E33: =C33+D33 -> 0 | F33: =SGA!E34 -> 0 | H33: =F33+G33 -> 0 | I33: =SGA!G34 -> 0 | K33: =I33+J33 -> 0 | L33: =SGA!I34 -> 0 | N33: =L33+M33 -> 0 | O33: =SGA!K34 -> 3023000 | Q33: =O33+P33 -> 3023000
B34: 受取奨励金（純額）の振替 | C34: =SGA!C35 -> 0 | E34: =C34+D34 -> 0 | F34: =SGA!E35 -> 0 | G34: =-(修正PL!F69-修正PL!F70) -> -2178508 | H34: =F34+G34 -> -2178508 | I34: =SGA!G35 -> 0 | J34: =-(修正PL!I69-修正PL!I70) -> -2314707 | K34: =I34+J34 -> -2314707 | L34: =SGA!I35 -> 0 | M34: =-(修正PL!L69-修正PL!L70) -> -2418448 | N34: =L34+M34 -> -2418448 | O34: =SGA!K35 -> 0 | P34: =-(修正PL!O69-修正PL!O70) -> -1184146 | Q34: =O34+P34 -> -1184146
E35: =C35+D35 -> 0 | H35: =F35+G35 -> 0 | K35: =I35+J35 -> 0 | N35: =L35+M35 -> 0 | Q35: =O35+P35 -> 0
E36: =C36+D36 -> 0 | H36: =F36+G36 -> 0 | K36: =I36+J36 -> 0 | N36: =L36+M36 -> 0 | Q36: =O36+P36 -> 0
E37: =C37+D37 -> 0 | H37: =F37+G37 -> 0 | K37: =I37+J37 -> 0 | N37: =L37+M37 -> 0 | Q37: =O37+P37 -> 0
E38: =C38+D38 -> 0 | H38: =F38+G38 -> 0 | K38: =I38+J38 -> 0 | N38: =L38+M38 -> 0 | Q38: =O38+P38 -> 0
B39: 販売費および一般管理費合計 | C39: =SUM(C5:C38) -> 0 | D39: =SUM(D5:D38) -> 0 | E39: =C39+D39 -> 0 | F39: =SUM(F5:F38) -> 214823441 | G39: =SUM(G5:G38) -> -20041508 | H39: =F39+G39 -> 194781933 | I39: =SUM(I5:I38) -> 215718454 | J39: =SUM(J5:J38) -> -20235707 | K39: =I39+J39 -> 195482747 | L39: =SUM(L5:L38) -> 193151054 | M39: =SUM(M5:M38) -> -6379024.2 | N39: =L39+M39 -> 1.8677203e+08 | O39: =SUM(O5:O38) -> 85746239 | P39: =SUM(P5:P38) -> -1406434.1 | Q39: =O39+P39 -> 84339805

Sheet 修正CR
K2: (単位：千円)
B3: 科目 | C3: ='BS(借方)'!C4 -> ●●年●月期 | F3: ='BS(借方)'!D4 -> 24年3月期 | I3: ='BS(借方)'!E4 -> 25年3月期 | L3: ='BS(借方)'!F4 -> 26年3月期 | O3: ='BS(借方)'!G4 -> 27年3月期 4〜9月TB
C4: 帳簿価額 | D4: 修正額 | E4: 修正後 | F4: 帳簿価額 | G4: 修正額 | H4: 修正後 | I4: 帳簿価額 | J4: 修正額 | K4: 修正後 | L4: 帳簿価額 | M4: 修正額 | N4: 修正後 | O4: 帳簿価額 | P4: 修正額 | Q4: 修正後
B5: 期首原材料棚卸高 | E5: =C5+D5 -> 0 | H5: =F5+G5 -> 0 | K5: =I5+J5 -> 0 | N5: =L5+M5 -> 0 | Q5: =O5+P5 -> 0
B6: 原材料仕入高 | E6: =C6+D6 -> 0 | H6: =F6+G6 -> 0 | K6: =I6+J6 -> 0 | N6: =L6+M6 -> 0 | Q6: =O6+P6 -> 0
B7: 小計 | E7: =C7+D7 -> 0 | H7: =F7+G7 -> 0 | K7: =I7+J7 -> 0 | N7: =L7+M7 -> 0 | Q7: =O7+P7 -> 0
B8: 期末原材料棚卸高 | E8: =C8+D8 -> 0 | H8: =F8+G8 -> 0 | K8: =I8+J8 -> 0 | N8: =L8+M8 -> 0 | Q8: =O8+P8 -> 0
E9: =C9+D9 -> 0 | H9: =F9+G9 -> 0 | K9: =I9+J9 -> 0 | N9: =L9+M9 -> 0 | Q9: =O9+P9 -> 0
E10: =C10+D10 -> 0 | H10: =F10+G10 -> 0 | K10: =I10+J10 -> 0 | N10: =L10+M10 -> 0 | Q10: =O10+P10 -> 0
B11: 材料費 | C11: =SUM(C5:C10) -> 0 | D11: =SUM(D5:D10) -> 0 | E11: =C11+D11 -> 0 | F11: =SUM(F5:F10) -> 0 | G11: =SUM(G5:G10) -> 0 | H11: =F11+G11 -> 0 | I11: =SUM(I5:I10) -> 0 | J11: =SUM(J5:J10) -> 0 | K11: =I11+J11 -> 0 | L11: =SUM(L5:L10) -> 0 | M11: =SUM(M5:M10) -> 0 | N11: =L11+M11 -> 0 | O11: =SUM(O5:O10) -> 0 | P11: =SUM(P5:P10) -> 0 | Q11: =O11+P11 -> 0
E12: =C12+D12 -> 0 | H12: =F12+G12 -> 0 | K12: =I12+J12 -> 0 | N12: =L12+M12 -> 0 | Q12: =O12+P12 -> 0
E13: =C13+D13 -> 0 | H13: =F13+G13 -> 0 | K13: =I13+J13 -> 0 | N13: =L13+M13 -> 0 | Q13: =O13+P13 -> 0
E14: =C14+D14 -> 0 | H14: =F14+G14 -> 0 | K14: =I14+J14 -> 0 | N14: =L14+M14 -> 0 | Q14: =O14+P14 -> 0
E15: =C15+D15 -> 0 | H15: =F15+G15 -> 0 | K15: =I15+J15 -> 0 | N15: =L15+M15 -> 0 | Q15: =O15+P15 -> 0
E16: =C16+D16 -> 0 | H16: =F16+G16 -> 0 | K16: =I16+J16 -> 0 | N16: =L16+M16 -> 0 | Q16: =O16+P16 -> 0
E17: =C17+D17 -> 0 | H17: =F17+G17 -> 0 | K17: =I17+J17 -> 0 | N17: =L17+M17 -> 0 | Q17: =O17+P17 -> 0
B18: 労務費 | C18: =SUM(C12:C17) -> 0 | D18: =SUM(D12:D17) -> 0 | E18: =C18+D18 -> 0 | F18: =SUM(F12:F17) -> 0 | G18: =SUM(G12:G17) -> 0 | H18: =F18+G18 -> 0 | I18: =SUM(I12:I17) -> 0 | J18: =SUM(J12:J17) -> 0 | K18: =I18+J18 -> 0 | L18: =SUM(L12:L17) -> 0 | M18: =SUM(M12:M17) -> 0 | N18: =L18+M18 -> 0 | O18: =SUM(O12:O17) -> 0 | P18: =SUM(P12:P17) -> 0 | Q18: =O18+P18 -> 0
E19: =C19+D19 -> 0 | H19: =F19+G19 -> 0 | K19: =I19+J19 -> 0 | N19: =L19+M19 -> 0 | Q19: =O19+P19 -> 0
E20: =C20+D20 -> 0 | H20: =F20+G20 -> 0 | K20: =I20+J20 -> 0 | N20: =L20+M20 -> 0 | Q20: =O20+P20 -> 0
E21: =C21+D21 -> 0 | H21: =F21+G21 -> 0 | K21: =I21+J21 -> 0 | N21: =L21+M21 -> 0 | Q21: =O21+P21 -> 0
E22: =C22+D22 -> 0 | H22: =F22+G22 -> 0 | K22: =I22+J22 -> 0 | N22: =L22+M22 -> 0 | Q22: =O22+P22 -> 0
E23: =C23+D23 -> 0 | H23: =F23+G23 -> 0 | K23: =I23+J23 -> 0 | N23: =L23+M23 -> 0 | Q23: =O23+P23 -> 0
E24: =C24+D24 -> 0 | H24: =F24+G24 -> 0 | K24: =I24+J24 -> 0 | N24: =L24+M24 -> 0 | Q24: =O24+P24 -> 0
B25: 外注加工費 | C25: =SUM(C19:C24) -> 0 | D25: =SUM(D19:D24) -> 0 | E25: =C25+D25 -> 0 | F25: =SUM(F19:F24) -> 0 | G25: =SUM(G19:G24) -> 0 | H25: =F25+G25 -> 0 | I25: =SUM(I19:I24) -> 0 | J25: =SUM(J19:J24) -> 0 | K25: =I25+J25 -> 0 | L25: =SUM(L19:L24) -> 0 | M25: =SUM(M19:M24) -> 0 | N25: =L25+M25 -> 0 | O25: =SUM(O19:O24) -> 0 | P25: =SUM(P19:P24) -> 0 | Q25: =O25+P25 -> 0
E26: =C26+D26 -> 0 | H26: =F26+G26 -> 0 | K26: =I26+J26 -> 0 | N26: =L26+M26 -> 0 | Q26: =O26+P26 -> 0
E27: =C27+D27 -> 0 | H27: =F27+G27 -> 0 | K27: =I27+J27 -> 0 | N27: =L27+M27 -> 0 | Q27: =O27+P27 -> 0
E28: =C28+D28 -> 0 | H28: =F28+G28 -> 0 | K28: =I28+J28 -> 0 | N28: =L28+M28 -> 0 | Q28: =O28+P28 -> 0
E29: =C29+D29 -> 0 | H29: =F29+G29 -> 0 | K29: =I29+J29 -> 0 | N29: =L29+M29 -> 0 | Q29: =O29+P29 -> 0
E30: =C30+D30 -> 0 | H30: =F30+G30 -> 0 | K30: =I30+J30 -> 0 | N30: =L30+M30 -> 0 | Q30: =O30+P30 -> 0
E31: =C31+D31 -> 0 | H31: =F31+G31 -> 0 | K31: =I31+J31 -> 0 | N31: =L31+M31 -> 0 | Q31: =O31+P31 -> 0
E32: =C32+D32 -> 0 | H32: =F32+G32 -> 0 | K32: =I32+J32 -> 0 | N32: =L32+M32 -> 0 | Q32: =O32+P32 -> 0
E33: =C33+D33 -> 0 | H33: =F33+G33 -> 0 | K33: =I33+J33 -> 0 | N33: =L33+M33 -> 0 | Q33: =O33+P33 -> 0
E34: =C34+D34 -> 0 | H34: =F34+G34 -> 0 | K34: =I34+J34 -> 0 | N34: =L34+M34 -> 0 | Q34: =O34+P34 -> 0
E35: =C35+D35 -> 0 | H35: =F35+G35 -> 0 | K35: =I35+J35 -> 0 | N35: =L35+M35 -> 0 | Q35: =O35+P35 -> 0
B36: 経費 | C36: =SUM(C26:C35) -> 0 | D36: =SUM(D26:D35) -> 0 | E36: =C36+D36 -> 0 | F36: =SUM(F26:F35) -> 0 | G36: =SUM(G26:G35) -> 0 | H36: =F36+G36 -> 0 | I36: =SUM(I26:I35) -> 0 | J36: =SUM(J26:J35) -> 0 | K36: =I36+J36 -> 0 | L36: =SUM(L26:L35) -> 0 | M36: =SUM(M26:M35) -> 0 | N36: =L36+M36 -> 0 | O36: =SUM(O26:O35) -> 0 | P36: =SUM(P26:P35) -> 0 | Q36: =O36+P36 -> 0
B37: 当期製造費用 | C37: =C11+C18+C25+C36 -> 0 | D37: =D11+D18+D25+D36 -> 0 | E37: =C37+D37 -> 0 | F37: =F11+F18+F25+F36 -> 0 | G37: =G11+G18+G25+G36 -> 0 | H37: =F37+G37 -> 0 | I37: =I11+I18+I25+I36 -> 0 | J37: =J11+J18+J25+J36 -> 0 | K37: =I37+J37 -> 0 | L37: =L11+L18+L25+L36 -> 0 | M37: =M11+M18+M25+M36 -> 0 | N37: =L37+M37 -> 0 | O37: =O11+O18+O25+O36 -> 0 | P37: =P11+P18+P25+P36 -> 0 | Q37: =O37+P37 -> 0
B38: 期首仕掛品棚卸高 | E38: =C38+D38 -> 0 | H38: =F38+G38 -> 0 | K38: =I38+J38 -> 0 | N38: =L38+M38 -> 0 | Q38: =O38+P38 -> 0
B39: 合計 | C39: =SUM(C37:C38) -> 0 | D39: =SUM(D37:D38) -> 0 | E39: =C39+D39 -> 0 | F39: =SUM(F37:F38) -> 0 | G39: =SUM(G37:G38) -> 0 | H39: =F39+G39 -> 0 | I39: =SUM(I37:I38) -> 0 | J39: =SUM(J37:J38) -> 0 | K39: =I39+J39 -> 0 | L39: =SUM(L37:L38) -> 0 | M39: =SUM(M37:M38) -> 0 | N39: =L39+M39 -> 0 | O39: =SUM(O37:O38) -> 0 | P39: =SUM(P37:P38) -> 0 | Q39: =O39+P39 -> 0
B40: 期末仕掛品棚卸高 | E40: =C40+D40 -> 0 | H40: =F40+G40 -> 0 | K40: =I40+J40 -> 0 | N40: =L40+M40 -> 0 | Q40: =O40+P40 -> 0
B41: 当期製造原価 | C41: =C39-C40 -> 0 | D41: =D39-D40 -> 0 | E41: =C41+D41 -> 0 | F41: =F39-F40 -> 0 | G41: =G39-G40 -> 0 | H41: =F41+G41 -> 0 | I41: =I39-I40 -> 0 | J41: =J39-J40 -> 0 | K41: =I41+J41 -> 0 | L41: =L39-L40 -> 0 | M41: =M39-M40 -> 0 | N41: =L41+M41 -> 0 | O41: =O39-O40 -> 0 | P41: =P39-P40 -> 0 | Q41: =O41+P41 -> 0

Sheet 年買法
C2: (単位：千円) | H2: (単位：千円) | M2: (単位：千円)
B3: 26年3月期 | C3: 金額 | F3: =修正PL!F3 -> 24年3月期 | G3: =修正PL!I3 -> 25年3月期 | H3: =修正PL!L3 -> 26年3月期 | J3: 営業権倍率 | K3: x1 | L3: x2 | M3: x3
B4: 簿価純資産額 | C4: ='修正BS(貸方) '!C52 -> 77872581 | E4: 簿価営業利益 | F4: =修正PL!F19 -> 4756748 | G4: =修正PL!I19 -> -4422940 | H4: =修正PL!L19 -> 5859912 | J4: 時価純資産 | K4: =C7 -> 55318457
B5: 修正額 | C5: ='修正BS(貸方) '!D50 -> -20022824 | E5: 修正額 | F5: =修正PL!G19 -> 20041508 | G5: =修正PL!J19 -> 20235707 | H5: =修正PL!M19 -> 6379024.2 | J5: 営業権 | K5: =H10*1 -> 10443147 | L5: =H10*2 -> 20886293 | M5: =H10*3 -> 31329440
B6: 税効果 | C6: ='修正BS(貸方) '!D51 -> -2531300 | E6: 修正後営業利益 | F6: =SUM(F4:F5) -> 24798256 | G6: =SUM(G4:G5) -> 15812767 | H6: =SUM(H4:H5) -> 12238936 | J6: 想定株式価値 | K6: =K4+K5 -> 65761604 | L6: =K4+L5 -> 76204751 | M6: =K4+M5 -> 86647897
B7: 時価純資産 | C7: =SUM(C4:C6) -> 55318457 | E7: 税考慮額 | F7: =-F6*0.34 -> -8431407 | G7: =-G6*0.34 -> -5376340.8 | H7: =-H6*0.34 -> -4161238.3
E8: 修正後税考慮後営業利益 | F8: =SUM(F6:F7) -> 16366849 | G8: =SUM(G6:G7) -> 10436426 | H8: =SUM(H6:H7) -> 8077697.9
G10: 基準営業利益 | H10: =(H8*0.5+G8*0.3+F8*0.2) -> 10443147
B12: ※営業権倍率1〜3倍は国内中小企業M&Aのボリュームゾーン。加重は直近期0.5・前期0.3・前々期0.2。

Sheet EV EBITDAマルチプル
C2: (単位：千円) | H2: (単位：千円) | M2: (単位：千円)
B3: 26年3月期 | C3: 金額 | F3: =修正PL!F3 -> 24年3月期 | G3: =修正PL!I3 -> 25年3月期 | H3: =修正PL!L3 -> 26年3月期 | J3: マルチプル倍率 | K3: x3 | L3: x4 | M3: x5
B4: キャッシュライク | C4: =ネットキャッシュ!C13 -> 219329077 | E4: 簿価営業利益 | F4: =修正PL!F19 -> 4756748 | G4: =修正PL!I19 -> -4422940 | H4: =修正PL!L19 -> 5859912 | J4: EV（EBITDA×倍率） | K4: =H10*3 -> 80287321 | L4: =H10*4 -> 1.0704976e+08 | M4: =H10*5 -> 1.338122e+08
B5: デットライク | C5: =ネットキャッシュ!F13 -> 362909300 | E5: 修正額 | F5: =修正PL!G19 -> 20041508 | G5: =修正PL!J19 -> 20235707 | H5: =修正PL!M19 -> 6379024.2 | J5: 非流動性ディスカウント | K5: =-K4*0.3 -> -24086196 | L5: =-L4*0.3 -> -32114929 | M5: =-M4*0.3 -> -40143661
B6: ネットキャッシュ | C6: =C4-C5 -> -143580223 | E6: 修正後営業利益 | F6: =SUM(F4:F5) -> 24798256 | G6: =SUM(G4:G5) -> 15812767 | H6: =SUM(H4:H5) -> 12238936 | J6: =B6 -> ネットキャッシュ | K6: =C6 -> -143580223
E7: 減価償却費 | F7: =SGA!E31 -> 13663684 | G7: =SGA!G31 -> 12557564 | H7: =SGA!I31 -> 8878970 | J7: 想定株式価値 | K7: =SUM(K4:K6) -> -87379098 | L7: =SUM(L4:L5)+K6 -> -68645390 | M7: =SUM(M4:M5)+K6 -> -49911682
E8: 修正後EBITDA | F8: =SUM(F6:F7) -> 38461940 | G8: =SUM(G6:G7) -> 28370331 | H8: =SUM(H6:H7) -> 21117906
G10: 基準EBITDA | H10: =(H8*0.5+G8*0.3+F8*0.2) -> 26762440
B12: ※倍率3〜5倍は国内中小企業M&Aの実務水準。非流動性ディスカウント30%。算定値がマイナスの場合、ネットデットが事業価値を上回ることを示す。

Sheet 参照企業
E2: (単位：千円)
B3: 企業名 | C3: 所在地 | D3: 事業内容 | E3: EV/EVIDA倍率
B4: （未使用）倍率は国内中小企業M&Aの実務水準（3〜5倍）を採用。卸売市場関連の上場会社の倍率は算定日時点の株価で更新が必要（要確認）

Sheet IM→

Sheet 会社概要
A1: ■ 貼付範囲 B2:C15 → 企業概要書「基本情報」（範囲をコピーしてパワポに貼り付け。数字はここを直す）
B2: 項目 | C2: 内容
B3: 会社名 | C3: 株式会社鶴岡中央青果（http://www.turu-chu.co.jp/）
B4: 本社所在地 | C4: 山形県鶴岡市宝田一丁目4番20号
B5: その他拠点 | C5: ① パッケージ場：山形県鶴岡市宝田一丁目5-1 ② 旧倉庫敷地（駐車場）：山形県東田川郡庄内町長沼字宮前304-7
B6: 設立 | C6: 1973年（昭和48年）11月22日（第54期）
B7: 資本金 | C7: =TEXT('BS (貸方)'!F36/1000,"#,##0")&"千円" -> 40,000千円
B8: 代表者 | C8: 岡部 寛
B9: 株主 | C9: 岡部 寛（1,510株／37.8%）ほか7名 代表者一族4名で75.8%を保有
B10: 事業内容 | C10: ・青果物（野菜・果実）の卸売（地方卸売市場の開設・運営、買付販売・受託販売） ・パッケージ（小分け・包装）、配送（量販店の配送受託を含む） ・包装資材の販売
B11: 従業員数 | C11: 24名（正社員17名、嘱託・再雇用・試用3名、パート・アルバイト4名） ※2026年9月1日時点。別途、常勤役員2名
B12: 許認可等 | C12: 地方卸売市場の認定（卸売市場法・山形県知事） 2020年6月認定、2026年2月変更認定
B13: 売上高 | C13: =TEXT(PL!I11/1000,"#,##0")&"千円（2026年3月期）" -> 1,195,893千円（2026年3月期）
B14: 調整後EBITDA | C14: =TEXT(AVERAGE(PLハイライト!D25:F25)/1000,"#,##0")&"千円（過去3期平均）" -> 29,317千円（過去3期平均）
B15: 譲渡理由 | C15: 後継者不在およびさらなる企業の発展

Sheet PLハイライト
A1: ■ 貼付範囲 B2:G25 → 企業概要書「財務ハイライト（P/L）」（範囲をコピーしてパワポに貼り付け。数字はここを直す）
G2: (単位：千円)
C3: ='BS(借方)'!C4 -> ●●年●月期 | D3: ='BS(借方)'!D4 -> 24年3月期 | E3: ='BS(借方)'!E4 -> 25年3月期 | F3: ='BS(借方)'!F4 -> 26年3月期 | G3: ='BS(借方)'!G4 -> 27年3月期 4〜9月TB
B4: 売上高 | D4: =PL!E11 -> 1178489098 | E4: =PL!G11 -> 1181947340 | F4: =PL!I11 -> 1195893269 | G4: =PL!K11 -> 621331427
B5: 前期比 | D5: - | E5: =E4/D4 -> 1.0029345 | F5: =F4/E4 -> 1.0117991 | G5: =IFERROR(G4/G42,"-") -> 0.93063937
B6: 売上総利益 | D6: =PL!E17 -> 219580189 | E6: =PL!G17 -> 211295514 | F6: =PL!I17 -> 199010966 | G6: =PL!K17 -> 106171940
B7: 利益率 | D7: =D6/D4 -> 0.18632348 | E7: =E6/E4 -> 0.17876897 | F7: =F6/F4 -> 0.16641198 | G7: =G6/G4 -> 0.17087811
B8: 営業利益 | D8: =PL!E19 -> 4756748 | E8: =PL!G19 -> -4422940 | F8: =PL!I19 -> 5859912 | G8: =PL!K19 -> 20425701
B9: 利益率 | D9: =D8/D4 -> 0.0040363106 | E9: =E8/E4 -> -0.0037420787 | F9: =F8/F4 -> 0.0049000293 | G9: =G8/G4 -> 0.032874083
B10: 経常利益 | D10: =PL!E36 -> 11316540 | E10: =PL!G36 -> 2181381 | F10: =PL!I36 -> 8067784 | G10: =PL!K36 -> 21165907
B11: 利益率 | D11: =D10/D4 -> 0.0096025835 | E11: =E10/E4 -> 0.0018455822 | F11: =F10/F4 -> 0.0067462408 | G11: =G10/G4 -> 0.034065405
B12: 税引後当期純利益 | D12: =PL!E56 -> 9106898 | E12: =PL!G56 -> 2928899 | F12: =PL!I56 -> -15084655 | G12: =PL!K56 -> 21165907
B13: 利益率 | D13: =D12/D4 -> 0.0077276048 | E13: =E12/E4 -> 0.0024780283 | F13: =F12/F4 -> -0.012613713 | G13: =G12/G4 -> 0.034065405
B15: 減価償却費 | C15: 0 | D15: =SGA!E31 -> 13663684 | E15: =SGA!G31 -> 12557564 | F15: =SGA!I31 -> 8878970 | G15: =SGA!K31 -> 3654000
B17: 調整項目 合計 | D17: =SUM(D18:D23) -> 20041508 | E17: =SUM(E18:E23) -> 20235707 | F17: =SUM(F18:F23) -> 6379024.2 | G17: =SUM(G18:G23) -> 1406434.1
B18: 役員報酬（退任役員） | D18: =修正PL!F64 -> 17400000 | E18: =修正PL!I64 -> 17400000 | F18: =修正PL!L64 -> 11160000 | G18: =修正PL!O64 -> 4050000
B19: 顧問料（代表者） | D19: =-修正PL!F65 -> -2160000 | E19: =-修正PL!I65 -> -2160000 | F19: =-修正PL!L65 -> -2160000 | G19: =-修正PL!O65 -> -1080000
B20: 社会保険料 | D20: =D18*修正PL!$F$66 -> 2610000 | E20: =E18*修正PL!$F$66 -> 2610000 | F20: =F18*修正PL!$F$66 -> 1674000 | G20: =G18*修正PL!$F$66 -> 607500
B21: 賞与の正常化 | D21: =修正PL!F67 -> 0 | E21: =修正PL!I67 -> 0 | F21: =修正PL!L67 -> -6724423.8 | G21: =修正PL!O67 -> -3362211.9
B22: 寄付金 | D22: =修正PL!F68 -> 13000 | E22: =修正PL!I68 -> 71000 | F22: =修正PL!L68 -> 11000 | G22: =修正PL!O68 -> 7000
B23: 受取奨励金（純額） | D23: =修正PL!F69-修正PL!F70 -> 2178508 | E23: =修正PL!I69-修正PL!I70 -> 2314707 | F23: =修正PL!L69-修正PL!L70 -> 2418448 | G23: =修正PL!O69-修正PL!O70 -> 1184146
B25: 調整後EBITDA | D25: =D8+D15+D17 -> 38461940 | E25: =E8+E15+E17 -> 28370331 | F25: =F8+F15+F17 -> 21117906 | G25: =G8+G15+G17 -> 25486135
B28: 参考（リード文・Comment用。貼付範囲外）
B29: 調整後EBITDA 3期平均 | C29: =AVERAGE(D25:F25) -> 29316726
B30: 調整後EBITDA 直近2期平均 | C30: =AVERAGE(E25:F25) -> 24744119
B31: チェック：修正PLの修正後EBITDA（26/3期）と一致 | C31: =ROUND(F25,0)=ROUND(修正PL!L74,0) -> TRUE
B32: EBITDA（営業利益＋減価償却費） | D32: =D8+D15 -> 18420432 | E32: =E8+E15 -> 8134624 | F32: =F8+F15 -> 14738882 | G32: =G8+G15 -> 24079701
B33: 販売費及び一般管理費 | D33: =SGA!E40 -> 214823441 | E33: =SGA!G40 -> 215718454 | F33: =SGA!I40 -> 193151054 | G33: =SGA!K40 -> 85746239
B35: 前年同期（2025年4〜9月 試算表）
B36: 前年同期 売上総利益 | G36: 108315825
B37: 前年同期 販管費 | G37: 98862164
B38: 前年同期 営業利益 | G38: 9453661
B39: 前年同期 経常利益 | G39: 10012691
B40: 前年同期 税引前当期純利益 | G40: 9880669
B41: 前年同期 減価償却費 | G41: 6240000
B42: 前年同期 売上高 | G42: 667639313
B43: 前年同期 人件費（役員報酬・給料・法定福利等） | G43: 50027381
B44: 前年同期 運賃 | G44: 17023172
B45: 当期 人件費（役員報酬・給料・法定福利等） | G45: =SUM(SGA!K6:K12) -> 43689505
B47: ※進行期は2026年4〜9月の試算表（6か月累計。年換算しない）。前期比は前年同期との比較。進行期の調整項目は同じ方針で6か月分を算定（賞与の正常化は年額の6/12）。

Sheet BSハイライト
A1: ■ 貼付範囲 B2:F21 → 企業概要書「財務ハイライト（B/S）」（範囲をコピーしてパワポに貼り付け。数字はここを直す）
F2: (単位：千円)
B3: =PLハイライト!F3&"末" -> 26年3月期末
B4: 流動資産 | C4: =SUM(C5:C10) -> 249704912 | E4: 流動負債 | F4: =SUM(F5:F10) -> 37279523
B5: 現預金 | C5: ='BS(借方)'!F6 -> 210887077 | E5: 買掛金 | F5: ='BS (貸方)'!F6 -> 26349122
B6: 売掛金 | C6: ='BS(借方)'!F7+'BS(借方)'!F8 -> 20836318 | E6: 未払金 | F6: ='BS (貸方)'!F7 -> 6630301
B7: 在庫 | C7: ='BS(借方)'!F9 -> 14596695 | E7: 預り金 | F7: ='BS (貸方)'!F9 -> 281300
B8: 未収入金 | C8: ='BS(借方)'!F11 -> 3011112 | E8: 未払法人税等 | F8: ='BS (貸方)'!F10 -> 1851300
B9: 仮払金 | C9: ='BS(借方)'!F12 -> 493135 | E9: 未払消費税 | F9: ='BS (貸方)'!F11 -> 2167500
B10: その他 | C10: ='BS(借方)'!F10+'BS(借方)'!F13+'BS(借方)'!F14+'BS(借方)'!F15 -> -119425 | E10: その他 | F10: ='BS (貸方)'!F8 -> 0
B11: 固定資産 | C11: =SUM(C12:C20) -> 235485192 | E11: 固定負債 | F11: =SUM(F12:F14) -> 370038000
B12: 建物 | C12: ='BS(借方)'!F22 -> 92065694 | E12: 長期借入金 | F12: ='BS (貸方)'!F19 -> 361058000
B13: 建物付属設備 | C13: ='BS(借方)'!F23 -> 11399836 | E13: 預り保証金 | F13: ='BS (貸方)'!F20 -> 8980000
B14: 構築物 | C14: ='BS(借方)'!F24 -> 284395
B15: 土地 | C15: ='BS(借方)'!F28 -> 93137240 | E15: 負債合計 | F15: =F4+F11 -> 407317523
B16: 電話加入権 | C16: ='BS(借方)'!F36 -> 2155595
B17: ソフトウェア | C17: ='BS(借方)'!F37 -> 371800
B18: 投資有価証券 | C18: ='BS(借方)'!F47 -> 2600000 | E18: 資本金 | F18: ='BS (貸方)'!F36 -> 40000000
B19: 保証金 | C19: ='BS(借方)'!F50 -> 33302569 | E19: 利益剰余金 | F19: ='BS (貸方)'!F43 -> 37872581
B20: その他 | C20: ='BS(借方)'!F25+'BS(借方)'!F26+'BS(借方)'!F27+'BS(借方)'!F29+'BS(借方)'!F48+'BS(借方)'!F49+'BS(借方)'!F51+'BS(借方)'!F56 -> 168063 | E20: 純資産合計 | F20: =SUM(F16:F19) -> 77872581
B21: 資産合計 | C21: =C4+C11 -> 485190104 | E21: 負債・純資産合計 | F21: =F15+F20 -> 485190104
F23: =F21=C21 -> 1
B24: 参考：B/S推移（リード文・Comment用。貼付範囲外）
B25: 項目 | C25: ='BS(借方)'!D4 -> 24年3月期 | D25: ='BS(借方)'!E4 -> 25年3月期 | E25: ='BS(借方)'!F4 -> 26年3月期 | F25: ='BS(借方)'!G4 -> 27年3月期 4〜9月TB
B26: 現金及び預金 | C26: ='BS(借方)'!D6 -> 339552632 | D26: ='BS(借方)'!E6 -> 259719301 | E26: ='BS(借方)'!F6 -> 210887077 | F26: ='BS(借方)'!G6 -> 393410846
B27: 長期借入金 | C27: ='BS (貸方)'!D19 -> 514690000 | D27: ='BS (貸方)'!E19 -> 434046000 | E27: ='BS (貸方)'!F19 -> 361058000 | F27: ='BS (貸方)'!G19 -> 526264000
B28: 純資産 | C28: ='BS (貸方)'!D50 -> 92828337 | D28: ='BS (貸方)'!E50 -> 93757236 | E28: ='BS (貸方)'!F50 -> 77872581 | F28: ='BS (貸方)'!G50 -> 99038488
B29: 資産合計 | C29: ='BS(借方)'!D61 -> 651947559 | D29: ='BS(借方)'!E61 -> 567528964 | E29: ='BS(借方)'!F61 -> 485190104 | F29: ='BS(借方)'!G61 -> 665564383
B30: 自己資本比率 | C30: =C28/C29 -> 0.1423862 | D30: =D28/D29 -> 0.16520256 | E30: =E28/E29 -> 0.16049911 | F30: =F28/F29 -> 0.14880377
B31: ネットデット（借入金−現預金） | C31: =C27-C26 -> 175137368 | D31: =D27-D26 -> 174326699 | E31: =E27-E26 -> 150170923 | F31: =F27-F26 -> 132853154
B33: 借入先別残高（2026/3期末）
B34: 鶴岡信用金庫 本店営業部 | C34: 182840000
B35: 山形銀行 鶴岡支店 | C35: 70250000
B36: 日本政策金融公庫 山形支店（1） | C36: 60730000
B37: 日本政策金融公庫 山形支店（2） | C37: 39380000
B38: 日本政策金融公庫 山形支店（3） | C38: 7858000
B39: 合計 | C39: =SUM(C34:C38) -> 361058000
B40: チェック：BS長期借入金と一致 | C40: =C39='BS (貸方)'!F19 -> TRUE
B42: ※2026年9月末は長期借入金526,264千円（3月末比＋165,206千円）、現預金393,411千円。新規借入の借入先・資金使途・条件は要確認。金利・返済条件・担保・保証も要確認。

Sheet 売上構成
A1: 収益源別売上高（進行期 2026年4〜9月 試算表）
A2: ■ 貼付範囲 B4:E11 → 企業概要書「事業の仕組みと収益源」（範囲をコピーしてパワポに貼り付け。数字はここを直す）
E4: (単位：千円)
B5: 収益区分（2026年4〜9月） | C5: 金額 | D5: 構成比 | E5: 内容
B6: 商品売上高 | C6: =PL!K5 -> 568871022 | D6: =C6/C$11 -> 0.91556776 | E6: 青果物の販売（買付販売は総額、受託販売は2019年10月以降手数料のみの純額で計上）
B7: 委託手数料収入 | C7: =PL!K9 -> 19958506 | D7: =C7/C$11 -> 0.032122158 | E7: 受託販売の手数料。生産者の商品を預かり、販売後に販売額の8.5%を収受
B8: 主婦センター費（配送受託） | C8: =PL!K8 -> 18416492 | D8: =C8/C$11 -> 0.029640368 | E8: (株)主婦の店の仕入商品の配送受託。配送額の約10%を収受
B9: 資材売上高 | C9: =PL!K6+PL!K7 -> 14843147 | D9: =C9/C$11 -> 0.023889258 | E9: 包装資材の販売（自社利用分の振替を含む。肥料の取扱いはほぼなし）
B10: 売上割戻（完納奨励金） | C10: =PL!K10 -> -757740 | D10: =C10/C$11 -> -0.0012195424 | E10: 期限内に代金を支払った八百屋等へ支給（市場の商慣習）
B11: 売上高 計 | C11: =SUM(C6:C10) -> 621331427 | D11: =C11/C$11 -> 1
B13: チェック：PL売上高と一致 | C13: =C11=PL!K11 -> TRUE
B15: 参考（貼付範囲外）
B16: 受託手数料率（第2回面談） | C16: 0.085
B17: 受託販売の取扱高（推計：手数料÷率、6か月） | C17: =C7/C16 -> 2.3480595e+08
B18: うち資材売上（自社利用分の振替） | C18: =PL!K7 -> 9473775
B20: ※決算書では売上高を「商品売上高」1本で表示しているため、収益源別の内訳は試算表（2026年4〜9月）で代替。資材売上（自社）は同額を資材仕入（自社）に計上（振替）。

Sheet 品目別売上
A1: 品目別（大分類）売上高の3期推移（分類別商品売上実績表）
A2: ■ 貼付範囲 B4:J23 → 企業概要書「品目別売上高の3期推移」（範囲をコピーしてパワポに貼り付け。数字はここを直す）
J4: (単位：千円)
B5: 区分 | C5: 品目（大分類） | D5: ='BS(借方)'!D4 -> 24年3月期 | F5: ='BS(借方)'!E4 -> 25年3月期 | H5: ='BS(借方)'!F4 -> 26年3月期 | J5: 主な品目（2026/3期の上位）
D6: 売上高 | E6: 構成比 | F6: 売上高 | G6: 構成比 | H6: 売上高 | I6: 構成比
B7: 野菜 | C7: 葉茎菜類 | D7: =SUMIF($D$41:$D$80,$C7,E$41:E$80) -> 205855717 | E7: =D7/D$23 -> 0.15865551 | F7: =SUMIF($D$41:$D$80,$C7,F$41:F$80) -> 244724364 | G7: =F7/F$23 -> 0.18886984 | H7: =SUMIF($D$41:$D$80,$C7,G$41:G$80) -> 191041215 | I7: =H7/H$23 -> 0.14764467 | J7: ねぎ・ほうれん草・小松菜
C8: 果菜類 | D8: =SUMIF($D$41:$D$80,$C8,E$41:E$80) -> 142773955 | E8: =D8/D$23 -> 0.11003763 | F8: =SUMIF($D$41:$D$80,$C8,F$41:F$80) -> 149190942 | G8: =F8/F$23 -> 0.11514043 | H8: =SUMIF($D$41:$D$80,$C8,G$41:G$80) -> 169568777 | I8: =H8/H$23 -> 0.13104987 | J8: ミニトマト・胡瓜・なす
C9: 土物類 | D9: =SUMIF($D$41:$D$80,$C9,E$41:E$80) -> 123756902 | E9: =D9/D$23 -> 0.095380956 | F9: =SUMIF($D$41:$D$80,$C9,F$41:F$80) -> 98683827 | G9: =F9/F$23 -> 0.07616078 | H9: =SUMIF($D$41:$D$80,$C9,G$41:G$80) -> 107261078 | I9: =H9/H$23 -> 0.082895863 | J9: たまねぎ・馬鈴薯・さつま芋
C10: きのこ・山菜類 | D10: =SUMIF($D$41:$D$80,$C10,E$41:E$80) -> 126642640 | E10: =D10/D$23 -> 0.097605029 | F10: =SUMIF($D$41:$D$80,$C10,F$41:F$80) -> 120957714 | G10: =F10/F$23 -> 0.093350999 | H10: =SUMIF($D$41:$D$80,$C10,G$41:G$80) -> 104553005 | I10: =H10/H$23 -> 0.080802951 | J10: 生しいたけ・なめこ・わらび
C11: 豆類 | D11: =SUMIF($D$41:$D$80,$C11,E$41:E$80) -> 66319879 | E11: =D11/D$23 -> 0.051113541 | F11: =SUMIF($D$41:$D$80,$C11,F$41:F$80) -> 71834020 | G11: =F11/F$23 -> 0.055439024 | H11: =SUMIF($D$41:$D$80,$C11,G$41:G$80) -> 68916868 | I11: =H11/H$23 -> 0.053261848 | J11: だだちゃ豆・枝豆・いんげん
C12: 根菜類 | D12: =SUMIF($D$41:$D$80,$C12,E$41:E$80) -> 69221830 | E12: =D12/D$23 -> 0.05335011 | F12: =SUMIF($D$41:$D$80,$C12,F$41:F$80) -> 64047429 | G12: =F12/F$23 -> 0.049429601 | H12: =SUMIF($D$41:$D$80,$C12,G$41:G$80) -> 61837567 | I12: =H12/H$23 -> 0.047790667 | J12: 人参・たけのこ・ごぼう
C13: その他野菜 | D13: =SUMIF($D$41:$D$80,$C13,E$41:E$80) -> 37249573 | E13: =D13/D$23 -> 0.028708701 | F13: =SUMIF($D$41:$D$80,$C13,F$41:F$80) -> 31133046 | G13: =F13/F$23 -> 0.024027413 | H13: =SUMIF($D$41:$D$80,$C13,G$41:G$80) -> 29731575 | I13: =H13/H$23 -> 0.022977809 | J13: しょうが・みょうが・食用菊
B14: 果実 | C14: メロン類 | D14: =SUMIF($D$41:$D$80,$C14,E$41:E$80) -> 131781474 | E14: =D14/D$23 -> 0.10156559 | F14: =SUMIF($D$41:$D$80,$C14,F$41:F$80) -> 133033396 | G14: =F14/F$23 -> 0.10267059 | H14: =SUMIF($D$41:$D$80,$C14,G$41:G$80) -> 124869563 | I14: =H14/H$23 -> 0.096504439 | J14: アンデスメロン・赤アンデス
C15: かき類 | D15: =SUMIF($D$41:$D$80,$C15,E$41:E$80) -> 66975500 | E15: =D15/D$23 -> 0.051618836 | F15: =SUMIF($D$41:$D$80,$C15,F$41:F$80) -> 75493695 | G15: =F15/F$23 -> 0.058263435 | H15: =SUMIF($D$41:$D$80,$C15,G$41:G$80) -> 70713359 | I15: =H15/H$23 -> 0.054650252 | J15: 庄内柿
C16: なし類 | D16: =SUMIF($D$41:$D$80,$C16,E$41:E$80) -> 39028490 | E16: =D16/D$23 -> 0.030079734 | F16: =SUMIF($D$41:$D$80,$C16,F$41:F$80) -> 47751880 | G16: =F16/F$23 -> 0.036853257 | H16: =SUMIF($D$41:$D$80,$C16,G$41:G$80) -> 46850405 | I16: =H16/H$23 -> 0.036207959 | J16: 幸水・豊水・ラ・フランス
C17: 柑橘類 | D17: =SUMIF($D$41:$D$80,$C17,E$41:E$80) -> 73930160 | E17: =D17/D$23 -> 0.056978877 | F17: =SUMIF($D$41:$D$80,$C17,F$41:F$80) -> 67851628 | G17: =F17/F$23 -> 0.052365551 | H17: =SUMIF($D$41:$D$80,$C17,G$41:G$80) -> 58030974 | I17: =H17/H$23 -> 0.044848772 | J17: みかん・ネーブル・デコポン
C18: キウイ・バナナ等 | D18: =SUMIF($D$41:$D$80,$C18,E$41:E$80) -> 28001904 | E18: =D18/D$23 -> 0.021581409 | F18: =SUMIF($D$41:$D$80,$C18,F$41:F$80) -> 21419619 | G18: =F18/F$23 -> 0.016530925 | H18: =SUMIF($D$41:$D$80,$C18,G$41:G$80) -> 38747104 | I18: =H18/H$23 -> 0.029945388 | J18: キウイ・バナナ・アボカド
C19: りんご類 | D19: =SUMIF($D$41:$D$80,$C19,E$41:E$80) -> 16736308 | E19: =D19/D$23 -> 0.012898877 | F19: =SUMIF($D$41:$D$80,$C19,F$41:F$80) -> 15460842 | G19: =F19/F$23 -> 0.011932146 | H19: =SUMIF($D$41:$D$80,$C19,G$41:G$80) -> 33823571 | I19: =H19/H$23 -> 0.026140275 | J19: ふじ・つがる
C20: その他果実 | D20: =SUMIF($D$41:$D$80,$C20,E$41:E$80) -> 85752205 | E20: =D20/D$23 -> 0.066090272 | F20: =SUMIF($D$41:$D$80,$C20,F$41:F$80) -> 74249505 | G20: =F20/F$23 -> 0.057303212 | H20: =SUMIF($D$41:$D$80,$C20,G$41:G$80) -> 109542486 | I20: =H20/H$23 -> 0.084659031 | J20: いちご・すいか・桃・さくらんぼ
B21: 花き | C21: 花き類 | D21: =SUMIF($D$41:$D$80,$C21,E$41:E$80) -> 33554857 | E21: =D21/D$23 -> 0.025861138 | F21: =SUMIF($D$41:$D$80,$C21,F$41:F$80) -> 31787520 | G21: =F21/F$23 -> 0.024532514 | H21: =SUMIF($D$41:$D$80,$C21,G$41:G$80) -> 31116284 | I21: =H21/H$23 -> 0.02404797 | J21: 生花（花束等）
B22: 加工品 | C22: 加工品・その他 | D22: =SUMIF($D$41:$D$80,$C22,E$41:E$80) -> 49919781 | E22: =D22/D$23 -> 0.038473785 | F22: =SUMIF($D$41:$D$80,$C22,F$41:F$80) -> 48110826 | G22: =F22/F$23 -> 0.037130279 | H22: =SUMIF($D$41:$D$80,$C22,G$41:G$80) -> 47321751 | I22: =H22/H$23 -> 0.036572235 | J22: もやし・干物・漬物等
B23: 合計 | D23: =SUM(D7:D22) -> 1297501175 | E23: =D23/D$23 -> 1 | F23: =SUM(F7:F22) -> 1295730253 | G23: =F23/F$23 -> 1 | H23: =SUM(H7:H22) -> 1293925582 | I23: =H23/H$23 -> 1
B25: 野菜 計 | D25: =SUM(D7:D13) -> 771820496 | F25: =SUM(F7:F13) -> 780571342 | H25: =SUM(H7:H13) -> 732910085
B26: 果実 計 | D26: =SUM(D14:D20) -> 442206041 | F26: =SUM(F14:F20) -> 435260565 | H26: =SUM(H14:H20) -> 482577462
B27: 県内／県外（2026/3期、売上金額） | D27: 829653005 | F27: 464272577
B28: チェック：生データ合計と一致 | D28: =ROUND(D23-SUM(E41:E80),0)=0 -> TRUE
B30: ※出所：分類別商品売上実績表（販売管理システム、各期3月末現在の年間累計）。決算書の商品売上高とは集計範囲が異なる（受託販売分を販売額の総額で集計していると推察：要確認）。
B31: ※「県内／県外」の区分が産地か販売先かは要確認。
B39: 大分類別の生データ（分類別商品売上実績表の「大分類計」当年欄の合計売上金額）
B40: 大分類 | C40: 名称 | D40: 集計区分 | E40: 2024/3期 | F40: 2025/3期 | G40: 2026/3期
B41: 301 | C41: 根菜類 | D41: 根菜類 | E41: 69221830 | F41: 64047429 | G41: 61837567
B42: 311 | C42: 葉茎菜類 | D42: 葉茎菜類 | E42: 205855717 | F42: 244724364 | G42: 191041215
B43: 341 | C43: 果菜類 | D43: 果菜類 | E43: 142773955 | F43: 149190942 | G43: 169568777
B44: 351 | C44: 豆科野菜 | D44: 豆類 | E44: 66319879 | F44: 71834020 | G44: 68916868
B45: 361 | C45: 土物類 | D45: 土物類 | E45: 123756902 | F45: 98683827 | G45: 107261078
B46: 371 | C46: 香辛野菜・つまもの野菜 | D46: その他野菜 | E46: 25680755 | F46: 22726731 | G46: 19822942
B47: 381 | C47: きのこ及び山菜類 | D47: きのこ・山菜類 | E47: 126642640 | F47: 120957714 | G47: 104553005
B48: 391 | C48: その他の野菜 | D48: その他野菜 | E48: 4940502 | F48: 4055762 | G48: 4969934
B49: 398 | C49: 規則で定める取扱品目 | D49: その他野菜 | E49: 2186664 | F49: 2787308 | G49: 2888699
B50: 401 | C50: 温州みかん類 | D50: 柑橘類 | E50: 44364583 | F50: 39596229 | G50: 30751161
B51: 411 | C51: 中晩生柑橘類 | D51: 柑橘類 | E51: 29565577 | F51: 28255399 | G51: 27279813
B52: 420 | C52: りんご類 | D52: りんご類 | E52: 16736308 | F52: 15460842 | G52: 33823571
... B80: 999 | C80: その他 | D80: 加工品・その他 | E80: 155586 | F80: 114935 | G80: 123731

Sheet 取引先
A1: ■ 貼付範囲 B2:M17 → 企業概要書「主要得意先の3期推移」（範囲をコピーしてパワポに貼り付け。数字はここを直す）
L2: (単位：千円)
B3: № | C3: 得意先 | D3: 取引内容 | E3: 本社所在地 | F3: 業種等 | G3: ='BS(借方)'!D4 -> 24年3月期 | I3: ='BS(借方)'!E4 -> 25年3月期 | K3: ='BS(借方)'!F4 -> 26年3月期 | M3: 備考
G4: 売上高 | H4: 構成比 | I4: 売上高 | J4: 構成比 | K4: 売上高 | L4: 構成比
B5: 1 | C5: (株)主婦の店（鶴岡店） | D5: 青果物 | E5: 山形県鶴岡市 | F5: 食品スーパー | G5: 308383428 | H5: =IFERROR(G5/G$17,"－") -> 0.26167695 | I5: 302458433 | J5: =IFERROR(I5/I$17,"－") -> 0.2558984 | K5: 345226753 | L5: =IFERROR(K5/K$17,"－") -> 0.28867689 | M5: 配送受託あり
B6: 2 | C6: 生活協同組合共立社 | D6: 青果物 | E6: 山形県鶴岡市 | F6: 生活協同組合 | G6: 96150823 | H6: =IFERROR(G6/G$17,"－") -> 0.081588216 | I6: 99248896 | J6: =IFERROR(I6/I$17,"－") -> 0.083970658 | K6: 85615684 | L6: =IFERROR(K6/K$17,"－") -> 0.071591409 | M6: 毎日納品
B7: 3 | C7: 長井中央青果(株) | D7: 青果物 | E7: 山形県長井市 | F7: 青果卸売業 | G7: =36988620+51092214 -> 88080834 | H7: =IFERROR(G7/G$17,"－") -> 0.074740474 | I7: 77319990 | J7: =IFERROR(I7/I$17,"－") -> 0.065417458 | K7: 75394815 | L7: =IFERROR(K7/K$17,"－") -> 0.063044769 | M7: 仕入先でもある
B8: 4 | C8: 松浦青果(株) | D8: 青果物 | E8: 要確認 | F8: 要確認 | G8: 13988200 | H8: =IFERROR(G8/G$17,"－") -> 0.011869605 | I8: 20012345 | J8: =IFERROR(I8/I$17,"－") -> 0.016931672 | K8: 32186104 | L8: =IFERROR(K8/K$17,"－") -> 0.02691386
B9: 5 | C9: 生活協同組合連合会アイチョイス | D9: 青果物 | E9: 愛知県名古屋市 | F9: 生協連合会 | G9: 25340515 | H9: =IFERROR(G9/G$17,"－") -> 0.021502545 | I9: 28050058 | J9: =IFERROR(I9/I$17,"－") -> 0.023732071 | K9: 22375855 | L9: =IFERROR(K9/K$17,"－") -> 0.018710579
B10: 6 | C10: (株)新庄丸果青果 | D10: 青果物 | E10: 山形県新庄市 | F10: 青果卸売業 | G10: 25221720 | H10: =IFERROR(G10/G$17,"－") -> 0.021401742 | I10: 23896155 | J10: =IFERROR(I10/I$17,"－") -> 0.020217614 | K10: 20030390 | L10: =IFERROR(K10/K$17,"－") -> 0.016749312
B11: 7 | C11: (株)マルタ | D11: 青果物 | E11: 要確認 | F11: 要確認 | G11: 26352085 | H11: =IFERROR(G11/G$17,"－") -> 0.022360907 | I11: 32060257 | J11: =IFERROR(I11/I$17,"－") -> 0.027124945 | K11: 19175010 | L11: =IFERROR(K11/K$17,"－") -> 0.016034048
B12: 8 | C12: 小野寺食品 やま亀 | D12: 青果物 | E12: 要確認 | F12: 食品加工 | G12: 20114508 | H12: =IFERROR(G12/G$17,"－") -> 0.017068048 | I12: 16807815 | J12: =IFERROR(I12/I$17,"－") -> 0.014220443 | K12: 18891770 | L12: =IFERROR(K12/K$17,"－") -> 0.015797204
B13: 9 | C13: (株)R&Cながの青果 | D13: 青果物 | E13: 長野県 | F13: 青果卸売業 | G13: 27716363 | H13: =IFERROR(G13/G$17,"－") -> 0.023518557 | I13: 25776810 | J13: =IFERROR(I13/I$17,"－") -> 0.021808763 | K13: 18856750 | L13: =IFERROR(K13/K$17,"－") -> 0.015767921
B14: 10 | C14: (株)マルト直治郎商店 | D14: 青果物 | E14: 山形県三川町 | F14: 青果卸売業 | G14: － | H14: =IFERROR(G14/G$17,"－") -> － | I14: 6678890 | J14: =IFERROR(I14/I$17,"－") -> 0.0056507509 | K14: 17633870 | L14: =IFERROR(K14/K$17,"－") -> 0.014745354 | M14: 仕入先でもある
C15: 社内勘定（近郷・パッケージ） | D15: 部門別勘定 | E15: － | F15: － | G15: =SUM(G22:G28) -> 306830191 | H15: =IFERROR(G15/G$17,"－") -> 0.26035896 | I15: =SUM(I22:I28) -> 334003936 | J15: =IFERROR(I15/I$17,"－") -> 0.28258783 | K15: =SUM(K22:K28) -> 333489152 | L15: =IFERROR(K15/K$17,"－") -> 0.27886197 | M15: 性質は要確認（注記参照）
C16: その他 | G16: =G17-SUM(G5:G15) -> 240310431 | H16: =IFERROR(G16/G$17,"－") -> 0.203914 | I16: =I17-SUM(I5:I15) -> 215633755 | J16: =IFERROR(I16/I$17,"－") -> 0.18243939 | K16: =K17-SUM(K5:K15) -> 207017116 | L16: =IFERROR(K16/K$17,"－") -> 0.17310668
C17: 合計（決算書の売上高） | G17: =PL!E11 -> 1178489098 | H17: 100.0% | I17: =PL!G11 -> 1181947340 | J17: 100.0% | K17: =PL!I11 -> 1195893269 | L17: 100.0%
B19: ※出所：買参人別順位表（販売管理システム、上位20位）の年間売上金額。上位20位圏外の年度は「－」。構成比は決算書の売上高に対する比率（集計基準が異なるため参考値）。
B20: 社内勘定（集計）
C22: KK 地物果実 | G22: 6919565 | I22: 110231725 | K22: 99079935
C23: KK マルカ | G23: 31997559 | I23: 67036327 | K23: 67277546
C24: KK 開発 | G24: 64841026 | I24: 33259997 | K24: 39250623
C25: KK 社長車 | G25: 40489545 | I25: 38577365 | K25: 38330905
C26: KK メロン（元常務取扱） | G26: 65506775
C27: パッケージ根菜 | G27: 46495688 | I27: 36837944 | K27: 36540635
C28: パッケージ果実・蔬菜 | G28: =34618043+15961990 -> 50580033 | I28: =26594781+21465797 -> 48060578 | K28: =31116065+21893443 -> 53009508
C30: 上位20位計（順位表） | G30: 863326289 | I30: 1034424284 | K30: 1035467601
C31: ※24/3期の上位20位計は25/3期の順位表の前年欄（25/3期の上位20先の前年実績）。

Sheet 仕入先
A1: ■ 貼付範囲 B2:L17 → 企業概要書「主要仕入先の3期推移」（範囲をコピーしてパワポに貼り付け。数字はここを直す）
K2: (単位：千円)
B3: № | C3: 仕入先 | D3: 仕入内容 | E3: 本社所在地 | F3: ='BS(借方)'!D4 -> 24年3月期 | H3: ='BS(借方)'!E4 -> 25年3月期 | J3: ='BS(借方)'!F4 -> 26年3月期 | L3: 備考
F4: 仕入高 | G4: 構成比 | H4: 仕入高 | I4: 構成比 | J4: 仕入高 | K4: 構成比
B5: 1 | C5: 丸果庄内青果(株) | D5: 青果物 | E5: 山形県三川町 | F5: 237536555 | G5: =IFERROR(F5/F$17,"－") -> 0.24917337 | H5: 246284304 | I5: =IFERROR(H5/H$17,"－") -> 0.25227957 | J5: 315032146 | K5: =IFERROR(J5/J$17,"－") -> 0.3162861 | L5: 公設庄内青果物市場の卸売業者
B6: 2 | C6: (株)庄果 | D6: 青果物 | E6: 山形県三川町 | F6: 113535109 | G6: =IFERROR(F6/F$17,"－") -> 0.11909715 | H6: 114398359 | I6: =IFERROR(H6/H$17,"－") -> 0.11718314 | J6: 98621582 | K6: =IFERROR(J6/J$17,"－") -> 0.099014135 | L6: 同上
B7: 3 | C7: 長井中央青果(株) | D7: 青果物 | E7: 山形県長井市 | F7: 29926325 | G7: =IFERROR(F7/F$17,"－") -> 0.031392403 | H7: 35262749 | I7: =IFERROR(H7/H$17,"－") -> 0.036121145 | J7: 62586074 | K7: =IFERROR(J7/J$17,"－") -> 0.062835191 | L7: 販売先でもある
B8: 4 | C8: (株)マルト直治郎商店 | D8: 青果物 | E8: 山形県三川町 | F8: 30113414 | G8: =IFERROR(F8/F$17,"－") -> 0.031588657 | H8: 56151367 | I8: =IFERROR(H8/H$17,"－") -> 0.057518251 | J8: 21974990 | K8: =IFERROR(J8/J$17,"－") -> 0.022062459 | L8: 販売先でもある
B9: 5 | C9: 成田食品(株) | D9: 青果・加工品 | E9: 福島県相馬市 | F9: 14127795 | G9: =IFERROR(F9/F$17,"－") -> 0.01481991 | H9: 14916067 | I9: =IFERROR(H9/H$17,"－") -> 0.015279167 | J9: 15635130 | K9: =IFERROR(J9/J$17,"－") -> 0.015697364
B10: 6 | C10: 庄内みどり農業協同組合 | D10: 受託品 | E10: 山形県酒田市 | F10: 7118174 | G10: =IFERROR(F10/F$17,"－") -> 0.0074668903 | H10: 7593661 | I10: =IFERROR(H10/H$17,"－") -> 0.0077785124 | J10: 8879410 | K10: =IFERROR(J10/J$17,"－") -> 0.0089147535 | L10: 受託販売の委託者
B11: 7 | C11: マルショウ青果(有) | D11: 青果物 | E11: 要確認 | F11: 14839869 | G11: =IFERROR(F11/F$17,"－") -> 0.015566868 | H11: 3207289 | I11: =IFERROR(H11/H$17,"－") -> 0.0032853636 | J11: 7847408 | K11: =IFERROR(J11/J$17,"－") -> 0.0078786438
B12: 8 | C12: 生産者A（波の会） | D12: 地場産青果物 | E12: 庄内地方 | F12: 5608122 | G12: =IFERROR(F12/F$17,"－") -> 0.0058828615 | H12: 6263216 | I12: =IFERROR(H12/H$17,"－") -> 0.0064156805 | J12: 6934170 | K12: =IFERROR(J12/J$17,"－") -> 0.0069617707 | L12: 個人生産者のため匿名
B13: 9 | C13: 生産者B（波の会） | D13: 地場産青果物 | E13: 庄内地方 | F13: 8173503 | G13: =IFERROR(F13/F$17,"－") -> 0.0085739194 | H13: 7441032 | I13: =IFERROR(H13/H$17,"－") -> 0.0076221679 | J13: 6490104 | K13: =IFERROR(J13/J$17,"－") -> 0.0065159372 | L13: 個人生産者のため匿名
B14: 10 | C14: (株)丸越 | D14: 青果物 | E14: 要確認 | F14: － | G14: =IFERROR(F14/F$17,"－") -> － | H14: 6056888 | I14: =IFERROR(H14/H$17,"－") -> 0.0062043299 | J14: 6406749 | K14: =IFERROR(J14/J$17,"－") -> 0.0064322504
C15: 社内勘定（近郷・パッケージ） | D15: 部門別勘定 | E15: － | F15: =SUM(F22:F30) -> 405811206 | G15: =IFERROR(F15/F$17,"－") -> 0.42569172 | H15: =SUM(H22:H30) -> 377523682 | I15: =IFERROR(H15/H$17,"－") -> 0.38671369 | J15: =SUM(J22:J30) -> 328219929 | K15: =IFERROR(J15/J$17,"－") -> 0.32952637 | L15: 性質は要確認（注記参照）
C16: その他 | F16: =F17-SUM(F5:F15) -> 86508248 | G16: =IFERROR(F16/F$17,"－") -> 0.09074625 | H16: =H17-SUM(H5:H15) -> 101137026 | I16: =IFERROR(H16/H$17,"－") -> 0.10359899 | J16: =J17-SUM(J5:J15) -> 117407697 | K16: =IFERROR(J16/J$17,"－") -> 0.11787503
C17: 合計（決算書の仕入高） | F17: =PL!E13 -> 953298320 | G17: 100.0% | H17: =PL!G13 -> 976235640 | I17: 100.0% | J17: =PL!I13 -> 996035389 | K17: 100.0%
B19: ※出所：荷主別順位表（販売管理システム、上位20位）の年間仕入金額。上位20位圏外の年度は「－」。構成比は決算書の仕入高に対する比率（集計基準が異なるため参考値）。
B20: 社内勘定（集計）
C22: KK 地物果実 | F22: 7439366 | H22: 127941370 | J22: 80678993
C23: KK マルカ | F23: 28693863 | H23: 69250898 | J23: 66961587
C24: KK 開発 | F24: 80299497 | H24: 33616540 | J24: 38502541
C25: KK 社長車 | F25: 43810598 | H25: 38396325 | J25: 38548107
C26: KK メロン・大根・常務（担当者別） | F26: =107800157+11451728+9226201 -> 128478086 | H26: 13058625
C27: パッケージ根菜 | F27: 48689621 | H27: 36903178 | J27: 36570360
C28: パッケージ果実 | F28: 35852672 | H28: 23616079 | J28: 32629978
C29: パッケージ蔬菜 | F29: 16356642 | H29: 21396557 | J29: 21921243
C30: パッケージ生花 | F30: 16190861 | H30: 13344110 | J30: 12407120
C32: 上位20件計（順位表） | F32: 728315067 | H32: 892035615 | J32: 889128701

Sheet 外注先
L2: (単位：千円)
B3: № | C3: 外注先 | D3: 外注内容 | E3: 本社所在地 | F3: 業種等 | G3: ●●●●年●月期 | I3: ●●●●年●月期 | K3: ●●●●年●月期 | M3: 備考
G4: 外注費 | H4: 構成比 | I4: 外注費 | J4: 構成比 | K4: 外注費 | L4: 構成比
B5: 1 | C5: 該当なし（外注加工はなし） | M5: 配送は原則自社。東京向け出荷・一部の地元スーパー向けのみ外部運送会社を利用（運賃の委託先別内訳は要確認）
B6: 2
B7: 3
B8: 4
B9: 5
B10: 6
B11: 7
B12: 8
B13: 9
B14: 10

Sheet 月別売上
A1: 月別売上高・仕入高（2026/3期）
A2: ■ 貼付範囲 B4:O8 → 企業概要書「月別売上高」（範囲をコピーしてパワポに貼り付け。数字はここを直す）
O4: (単位：千円)
C5: 4月 | D5: 5月 | E5: 6月 | F5: 7月 | G5: 8月 | H5: 9月 | I5: 10月 | J5: 11月 | K5: 12月 | L5: 1月 | M5: 2月 | N5: 3月 | O5: 合計
B6: 売上高 | C6: 87736 | D6: 101698 | E6: 83794 | F6: 146060 | G6: 138177 | H6: 110175 | I6: 106499 | J6: 100617 | K6: 98058 | L6: 69520 | M6: 69339 | N6: 84221 | O6: 1195894
B7: 仕入高 | C7: 76904 | D7: 86235 | E7: 74095 | F7: 139243 | G7: 96826 | H7: 85074 | I7: 84386 | J7: 85425 | K7: 82345 | L7: 56698 | M7: 58088 | N7: 70716 | O7: 996035
B8: 月平均比 | C8: 0.88037234 | D8: 1.0204717 | E8: 0.840817 | F8: 1.4656148 | G8: 1.3865142 | H8: 1.1055328 | I8: 1.0686466 | J8: 1.0096246 | K8: 0.98394674 | L8: 0.69758691 | M8: 0.6957707 | N8: 0.84510166
B10: 人件費 | C10: 4204 | D10: 7349 | E10: 7586 | F10: 7363 | G10: 7717 | H10: 7474 | I10: 7291 | J10: 7298 | K10: 7200 | L10: 6903 | M10: 6884 | N10: 9764
B12: ※出所：法人事業概況説明書（2026/3期）。千円単位の記載値をそのまま転記（円単位入力の例外）。合計はPLの売上高と端数・集計範囲の差がある。

Sheet 株主
A1: ■ 貼付範囲 B2:H15 → 企業概要書「株主及び役員（株主）」（範囲をコピーしてパワポに貼り付け。数字はここを直す）
E2: (単位：千円)
B3: № | C3: 氏名 | D3: 役職 | E3: ="役員報酬"&CHAR(10)&"（"&'BS(借方)'!F4&"）" -> 役員報酬 （26年3月期） | F3: 保有株式数 | G3: 保有割合 | H3: 備考
B5: 1 | C5: 岡部 寛 | D5: 代表取締役 | E5: 4320000 | F5: 1510 | G5: =F5/$F$15 -> 0.3775
B6: 2 | C6: 岡部 一 | D6: 取締役（代表者の弟） | E6: 4200000 | F6: 720 | G6: =F6/$F$15 -> 0.18
B7: 3 | C7: 岡部 和子 | D7: 代表者の親族 | E7: 0 | F7: 500 | G7: =F7/$F$15 -> 0.125
B8: 4 | C8: 梅津 恵一 | D8: － | E8: 0 | F8: 360 | G8: =F8/$F$15 -> 0.09
B9: 5 | C9: 小野寺 則和 | D9: 監査役 | E9: 120000 | F9: 350 | G9: =F9/$F$15 -> 0.0875
B10: 6 | C10: 岡部 竹古 | D10: 取締役（代表者の配偶者） | E10: 120000 | F10: 300 | G10: =F10/$F$15 -> 0.075
B11: 7 | C11: 佐藤 令子 | D11: － | E11: 0 | F11: 200 | G11: =F11/$F$15 -> 0.05
B12: 8 | C12: 菅原 圭吾 | D12: 元常務取締役 | E12: 6600000 | F12: 60 | G12: =F12/$F$15 -> 0.015 | H12: 2026年5月29日退任
B13: 9 | G13: =F13/$F$15 -> 0
B14: 10 | G14: =F14/$F$15 -> 0
C15: 合計 | E15: =SUM(E5:E14) -> 15360000 | F15: =SUM(F5:F14) -> 4000 | G15: =F15/$F$15 -> 1
B17: チェック：発行済株式総数4,000株 | F17: =F15=4000 -> TRUE
B18: うち代表者一族（岡部家4名） | F18: =F5+F6+F7+F10 -> 3030 | G18: =F18/F15 -> 0.7575
B19: ※出所：法人税申告書別表二（2026/3期）。株主名簿・名義株の有無・親族外株主の取得経緯は要確認。

Sheet 取締役
A1: ■ 貼付範囲 B2:H15 → 企業概要書「株主及び役員（役員）」（範囲をコピーしてパワポに貼り付け。数字はここを直す）
F2: (単位：千円)
B3: № | C3: 氏名 | D3: 役職 | E3: 代表者との関係 | F3: ="役員報酬"&CHAR(10)&"（"&'BS(借方)'!F4&"）" -> 役員報酬 （26年3月期） | G3: 業務範囲 | H3: 備考
B5: 1 | C5: 岡部 寛 | D5: 代表取締役（常勤） | E5: 本人 | F5: 4320000 | G5: 経営全般・販売 | H5: 譲渡後は顧問（最大1年）
B6: 2 | C6: 岡部 一 | D6: 取締役（常勤） | E6: 弟 | F6: 4200000 | G6: 買付・販売 | H6: 譲渡後も継続勤務予定
B7: 3 | C7: 岡部 竹古 | D7: 取締役（非常勤） | E7: 配偶者 | F7: 120000 | G7: 業務への関与なし | H7: 譲渡時に退任予定
B8: 4 | C8: 小野寺 則和 | D8: 監査役（非常勤） | E8: － | F8: 120000 | G8: 会計監査 | H8: 譲渡時に退任予定
B9: 5 | C9: 菅原 圭吾 | D9: 常務取締役（常勤） | E9: － | F9: 6600000 | G9: － | H9: 2026年5月29日退任
B10: 6
B11: 7
B12: 8
B13: 9
B14: 10
C15: 合計 | F15: =SUM(F5:F14) -> 15360000
B17: チェック：SGA役員報酬（26/3期）と一致 | F17: =F15=SGA!I6 -> TRUE

Sheet 従業員
A1: ■ 貼付範囲 B4:Q28 → 企業概要書「従業員一覧」（範囲をコピーしてパワポに貼り付け。数字はここを直す）
F2: 基準日→適宜変更 | G2: 46266
G3: YYYY/MM/DD | I3: YYYY/MM/DD
B4: № | C4: 氏名 | D4: イニシャル | E4: 雇用形態 | F4: 性別 | G4: 生年月日 | H4: 年齢 （歳） | I4: 入社年月日 | J4: 勤続年数 （年） | K4: 部署 | L4: 役職 | M4: 26年9月分総支給 | N4: ●年夏季賞与 | O4: ●年冬季賞与 | P4: ●年総支給額 | Q4: 備考
B5: 1 | E5: 正社員 | F5: 男 | G5: 23059 | H5: =IF(G5="","",DATEDIF(G5,$G$2,"Y")) -> 63 | I5: 45758 | J5: =IF(I5="","",DATEDIF(I5,$G$2,"Y")) -> 1 | K5: 野菜営業部 | L5: 副部長
B6: 2 | E6: 正社員 | F6: 男 | G6: 29093 | H6: =IF(G6="","",DATEDIF(G6,$G$2,"Y")) -> 47 | I6: 37410 | J6: =IF(I6="","",DATEDIF(I6,$G$2,"Y")) -> 24 | K6: 野菜営業部 | L6: 副部長 | Q6: セリ人資格認定、フォークリフト運転免許
B7: 3 | E7: 正社員 | F7: 男 | G7: 34880 | H7: =IF(G7="","",DATEDIF(G7,$G$2,"Y")) -> 31 | I7: 41730 | J7: =IF(I7="","",DATEDIF(I7,$G$2,"Y")) -> 12 | K7: 近郷部 | L7: 課長 | Q7: セリ人資格認定、フォークリフト運転免許
B8: 4 | E8: 正社員 | F8: 男 | G8: 30875 | H8: =IF(G8="","",DATEDIF(G8,$G$2,"Y")) -> 42 | I8: 43486 | J8: =IF(I8="","",DATEDIF(I8,$G$2,"Y")) -> 7 | K8: 近郷部 | Q8: フォークリフト運転免許
B9: 5 | E9: 正社員 | F9: 男 | G9: 29718 | H9: =IF(G9="","",DATEDIF(G9,$G$2,"Y")) -> 45 | I9: 43514 | J9: =IF(I9="","",DATEDIF(I9,$G$2,"Y")) -> 7 | K9: 近郷部 | Q9: フォークリフト運転免許
B10: 6 | E10: 正社員 | F10: 男 | G10: 23096 | H10: =IF(G10="","",DATEDIF(G10,$G$2,"Y")) -> 63 | I10: 43937 | J10: =IF(I10="","",DATEDIF(I10,$G$2,"Y")) -> 6 | K10: 集配部 | Q10: フォークリフト運転免許
B11: 7 | E11: 正社員 | F11: 男 | G11: 34432 | H11: =IF(G11="","",DATEDIF(G11,$G$2,"Y")) -> 32 | I11: 43972 | J11: =IF(I11="","",DATEDIF(I11,$G$2,"Y")) -> 6 | K11: 野菜営業部 | Q11: フォークリフト運転免許
B12: 8 | E12: 正社員 | F12: 男 | G12: 33046 | H12: =IF(G12="","",DATEDIF(G12,$G$2,"Y")) -> 36 | I12: 44550 | J12: =IF(I12="","",DATEDIF(I12,$G$2,"Y")) -> 4 | K12: 野菜営業部 | Q12: フォークリフト運転免許
B13: 9 | E13: 正社員 | F13: 男 | G13: 30645 | H13: =IF(G13="","",DATEDIF(G13,$G$2,"Y")) -> 42 | I13: 41015 | J13: =IF(I13="","",DATEDIF(I13,$G$2,"Y")) -> 14 | K13: 集配部 | Q13: 令和4年4月16日よりフルタイム勤務、フォークリフト運転免許
B14: 10 | E14: 嘱託社員 | F14: 男 | G14: 20758 | H14: =IF(G14="","",DATEDIF(G14,$G$2,"Y")) -> 69 | I14: 38808 | J14: =IF(I14="","",DATEDIF(I14,$G$2,"Y")) -> 20 | K14: 生花部 | Q14: フォークリフト運転免許
B15: 11 | E15: 再雇用正社員 | F15: 男 | G15: 31390 | H15: =IF(G15="","",DATEDIF(G15,$G$2,"Y")) -> 40 | I15: 44949 | J15: =IF(I15="","",DATEDIF(I15,$G$2,"Y")) -> 3 | K15: 集配部
B16: 12 | E16: 試用期間 | F16: 男 | G16: 21804 | H16: =IF(G16="","",DATEDIF(G16,$G$2,"Y")) -> 66 | I16: 45419 | J16: =IF(I16="","",DATEDIF(I16,$G$2,"Y")) -> 2 | K16: 近郷部 | Q16: セリ人資格認定、
B17: 13 | E17: アルバイト | F17: 男 | G17: 25847 | H17: =IF(G17="","",DATEDIF(G17,$G$2,"Y")) -> 55 | I17: 46113 | J17: =IF(I17="","",DATEDIF(I17,$G$2,"Y")) -> 0 | K17: 集配部
B18: 14 | E18: 正社員 | F18: 女 | G18: 25608 | H18: =IF(G18="","",DATEDIF(G18,$G$2,"Y")) -> 56 | I18: 32223 | J18: =IF(I18="","",DATEDIF(I18,$G$2,"Y")) -> 38 | K18: 総務部 | L18: 部長
B19: 15 | E19: 正社員 | F19: 女 | G19: 22273 | H19: =IF(G19="","",DATEDIF(G19,$G$2,"Y")) -> 65 | I19: 28926 | J19: =IF(I19="","",DATEDIF(I19,$G$2,"Y")) -> 47 | K19: 資材部 | L19: 課長
B20: 16 | E20: 正社員 | F20: 女 | G20: 28120 | H20: =IF(G20="","",DATEDIF(G20,$G$2,"Y")) -> 49 | I20: 39223 | J20: =IF(I20="","",DATEDIF(I20,$G$2,"Y")) -> 19 | K20: 野菜営業部 | L20: 課長
B21: 17 | E21: 正社員 | F21: 女 | G21: 35762 | H21: =IF(G21="","",DATEDIF(G21,$G$2,"Y")) -> 28 | I21: 43619 | J21: =IF(I21="","",DATEDIF(I21,$G$2,"Y")) -> 7 | K21: 事務
B22: 18 | E22: 正社員 | F22: 女 | G22: 27221 | H22: =IF(G22="","",DATEDIF(G22,$G$2,"Y")) -> 52 | I22: 38834 | J22: =IF(I22="","",DATEDIF(I22,$G$2,"Y")) -> 20 | K22: パッケージ部 | L22: 係長 | Q22: 平成24年4月21日よりフルタイム勤務
B23: 19 | E23: 正社員 | F23: 女 | G23: 22228 | H23: =IF(G23="","",DATEDIF(G23,$G$2,"Y")) -> 65 | I23: 38835 | J23: =IF(I23="","",DATEDIF(I23,$G$2,"Y")) -> 20 | K23: パッケージ部 | Q23: 平成24年4月21日よりフルタイム勤務
B24: 20 | E24: 正社員 | F24: 女 | G24: 25734 | H24: =IF(G24="","",DATEDIF(G24,$G$2,"Y")) -> 56 | I24: 44287 | J24: =IF(I24="","",DATEDIF(I24,$G$2,"Y")) -> 5 | K24: パッケージ部
B25: 21 | E25: 正社員 | F25: 女 | G25: 21947 | H25: =IF(G25="","",DATEDIF(G25,$G$2,"Y")) -> 66 | I25: 39934 | J25: =IF(I25="","",DATEDIF(I25,$G$2,"Y")) -> 17 | K25: パッケージ部 | Q25: 平成24年4月21日よりフルタイム勤務
B26: 22 | E26: パート | F26: 女 | G26: 21663 | H26: =IF(G26="","",DATEDIF(G26,$G$2,"Y")) -> 67 | I26: 41120 | J26: =IF(I26="","",DATEDIF(I26,$G$2,"Y")) -> 14 | K26: パッケージ部
B27: 23 | E27: パート | F27: 男 | G27: 35398 | H27: =IF(G27="","",DATEDIF(G27,$G$2,"Y")) -> 29 | I27: 43248 | J27: =IF(I27="","",DATEDIF(I27,$G$2,"Y")) -> 8 | K27: パッケージ部
B28: 24 | E28: パート | F28: 女 | G28: 24663 | H28: =IF(G28="","",DATEDIF(G28,$G$2,"Y")) -> 59 | I28: 45064 | J28: =IF(I28="","",DATEDIF(I28,$G$2,"Y")) -> 3 | K28: パッケージ部
B29: 25 | H29: =ROUNDDOWN(($G$2-G29)/365,0) -> 126 | J29: =ROUNDDOWN(($G$2-I29)/365,0) -> 126
B30: 26 | H30: =ROUNDDOWN(($G$2-G30)/365,0) -> 126 | J30: =ROUNDDOWN(($G$2-I30)/365,0) -> 126
B31: 27 | H31: =ROUNDDOWN(($G$2-G31)/365,0) -> 126 | J31: =ROUNDDOWN(($G$2-I31)/365,0) -> 126
B32: 28 | H32: =ROUNDDOWN(($G$2-G32)/365,0) -> 126 | J32: =ROUNDDOWN(($G$2-I32)/365,0) -> 126
B33: 29 | H33: =ROUNDDOWN(($G$2-G33)/365,0) -> 126 | J33: =ROUNDDOWN(($G$2-I33)/365,0) -> 126
B34: 30 | H34: =ROUNDDOWN(($G$2-G34)/365,0) -> 126 | J34: =ROUNDDOWN(($G$2-I34)/365,0) -> 126
B37: 人数 | E37: =COUNTA(E5:E34) -> 24
B38: 平均年齢 | E38: =AVERAGE(H5:H28) -> 50.958333
B39: 平均勤続年数 | E39: =AVERAGE(J5:J28) -> 12.666667
B40: 60歳以上 | E40: =COUNTIF(H5:H28,">=60") -> 8
B41: 正社員 | E41: =COUNTIF(E5:E28,"正社員") -> 17
B42: セリ人資格者 | E42: =COUNTIF(Q5:Q28,"*セリ人*") -> 3
B44: ※出所：職員名簿（2026年9月1日現在）。氏名・イニシャル・生年月日・入社日は概要書に貼らない（非表示列）。賃金台帳（2026/4〜10）は氏名表記のため名簿№との対応確認後に総支給額を転記（要確認）。

Sheet 拠点(本社等)
A1: ■ 貼付範囲 B2:G6 → 企業概要書「拠点概要（本社・市場）」（範囲をコピーしてパワポに貼り付け。数字はここを直す）
B2: 拠点 | C2: 所在地 | D2: 所有区分 | E2: 土地面積 (㎡) | F2: 主な建物 | G2: 用途
B3: 本社・市場 | C3: 山形県鶴岡市宝田一丁目4番20号 （地番：宝田一丁目4-2） | D3: 法人 | E3: 3100.22 | F3: 事務所（管理棟）・市場・倉庫・容器庫・貯蔵庫 | G3: 事務、セリ・相対取引、保管
B4: パッケージ場 | C4: 山形県鶴岡市宝田一丁目5-1 | D4: 法人 | E4: 900.5 | F4: 事務所兼倉庫（パッケージ場）・倉庫 | G4: 小分け・包装、保管
B5: 旧倉庫敷地 | C5: 山形県東田川郡庄内町長沼字宮前304-7 | D5: 法人 | E5: 261.81 | F5: なし（倉庫は老朽化により解体済み） | G5: 月極駐車場として近隣へ賃貸
B6: 賃借物件 | C6: なし（地代家賃の計上なし） | D6: － | F6: － | G6: －
B8: ※営業時間は早朝5時から（終業時刻は要確認）、定休日は水・日・祝日。車両は自己所有とリースを併用（リース料 年6,227千円）。

Sheet 不動産概況
A1: 不動産概況（不動産(所有)シートから集計）
A2: ■ 貼付範囲 B4:J9 → 企業概要書「不動産概況」（範囲をコピーしてパワポに貼り付け。数字はここを直す）
J4: (単位：千円)
B5: 拠点 | C5: 所在地 | D5: 土地面積 (㎡) | E5: 土地の 所有区分 | F5: 建物の所有区分 | G5: 土地簿価 | H5: 土地時価 （推計） | I5: 建物固定資産税 評価額 | J5: 担保
B6: 本社・市場 | C6: ='不動産(所有)'!D4 -> 鶴岡市宝田一丁目4-2 | D6: ='不動産(所有)'!E4 -> 3100.22 | E6: 法人 | F6: 法人（5棟／延床1,246.20㎡） | G6: ='不動産(所有)'!H4 -> 70757240 | H6: ='不動産(所有)'!I4 -> 51230293 | I6: =SUM('不動産(所有)'!J5:J9) -> 22295345 | J6: 要確認
B7: パッケージ場 | C7: ='不動産(所有)'!D10 -> 鶴岡市宝田一丁目5-1 | D7: ='不動産(所有)'!E10 -> 900.5 | E7: 法人 | F7: 法人（2棟／延床766.48㎡） | G7: ='不動産(所有)'!H10 -> 21380000 | H7: ='不動産(所有)'!I10 -> 15086140 | I7: =SUM('不動産(所有)'!J11:J12) -> 24766655 | J7: 要確認
B8: 旧倉庫敷地 | C8: ='不動産(所有)'!D13 -> 東田川郡庄内町長沼字宮前304-7 | D8: ='不動産(所有)'!E13 -> 261.81 | E8: 法人 | F8: 建物なし（解体済み） | G8: ='不動産(所有)'!H13 -> 1000000 | H8: ='不動産(所有)'!I13 -> 1508578.6 | I8: 0 | J8: 要確認
B9: 合計 | D9: =SUM(D6:D8) -> 4262.53 | F9: 法人 7棟 | G9: =SUM(G6:G8) -> 93137240 | H9: =SUM(H6:H8) -> 67825011 | I9: =SUM(I6:I8) -> 47062000
B11: チェック：土地簿価＝BS土地 | G11: =G9='BS(借方)'!F28 -> TRUE
B12: ※土地時価＝固定資産税評価額÷0.7（公示価格水準への割戻し。推計）。建物評価額は令和8年度固定資産税評価額。担保設定は登記簿謄本（未受領）で確認予定。

Sheet 不動産(所有)
A1: ■ 貼付範囲 B3:K15 → 企業概要書「不動産詳細」（範囲をコピーしてパワポに貼り付け。数字はここを直す） | I1: 土地は0.7割戻し
B3: 事業所名 | C3: 内容 | D3: 所在地 地番・家屋番号 | E3: 面積 (㎡) | F3: 区分 ・構造 | G3: 所有（建築） 年月・事由 | H3: 前期末簿価 (千円) | I3: 時価 (千円) | J3: 固定資産税 評価額(千円) | K3: 備考
B4: 本社・市場 | C4: 土地）市場敷地 | D4: 鶴岡市宝田一丁目4-2 | E4: 3100.22 | F4: 宅地 | G4: 要確認 | H4: 70757240 | I4: =J4/0.7 -> 51230293 | J4: 35861205 | K4: 固定資産税評価額を0.7で割戻し、時価を算出
C5: 建物）事務所 | D5: 宝田一丁目4-2 | E5: 365.63 | F5: 鉄骨造 2階 | G5: 1981年新築 | J5: 11218061
C6: 建物）市場 | D6: 宝田一丁目4-2 | E6: 320.22 | F6: 鉄骨造 1階 | G6: 1981年新築 | J6: 4712536
C7: 建物）倉庫 | D7: 宝田一丁目4-2 | E7: 327.13 | F7: 鉄骨造 1階 | G7: 1981年新築 | J7: 4560792
C8: 建物）容器庫 | D8: 宝田一丁目4-2 | E8: 198.74 | F8: 軽量鉄骨造 2階 | G8: 1981年新築 | J8: 1237049
C9: 建物）貯蔵庫 | D9: 宝田一丁目4-2 | E9: 34.48 | F9: 軽量鉄骨造 1階 | G9: 1981年新築 | J9: 566907
B10: パッケージ場 | C10: 土地）作業場敷地 | D10: 鶴岡市宝田一丁目5-1 | E10: 900.5 | F10: 宅地 | G10: 要確認 | H10: 21380000 | I10: =J10/0.7 -> 15086140 | J10: 10560298 | K10: 固定資産税評価額を0.7で割戻し、時価を算出
C11: 建物）事務所兼倉庫 | D11: 宝田一丁目5-1 | E11: 627.4 | F11: 鉄骨造 2階 | G11: 1982年新築 | J11: 13110977
C12: 建物）倉庫 | D12: 宝田一丁目5-1 | E12: 139.08 | F12: 鉄骨造 1階 | G12: 2012年新築 | J12: 11655678
B13: 旧倉庫敷地 | C13: 土地）駐車場 | D13: 東田川郡庄内町長沼字宮前304-7 | E13: 261.81 | F13: 宅地 | G13: 要確認 | H13: 1000000 | I13: =J13/0.7 -> 1508578.6 | J13: 1056005 | K13: 倉庫は解体済み。月極駐車場として賃貸
B14: 建物計 | C14: 建物・付属設備（7棟） | D14: － | E14: =SUM(E5:E9,E11:E12) -> 2012.68 | F14: － | G14: － | H14: ='BS(借方)'!F22+'BS(借方)'!F23 -> 103465530 | I14: =H14 -> 103465530 | J14: =SUM(J5:J9,J11:J12) -> 47062000 | K14: 減価償却過不足なし（別表十六）、簿価＝時価として評価。棟別簿価は台帳で要確認
B15: 合計 | E15: =E4+E10+E13 -> 4262.53 | H15: =SUM(H4:H14) -> 196602770 | I15: =SUM(I4:I14) -> 1.7129054e+08 | J15: =J4+J10+J13+J14 -> 94539508
B17: チェック：土地簿価＝BS土地 | H17: =H4+H10+H13='BS(借方)'!F28 -> TRUE
B18: ※面積は登記地積・床面積（R8年度固定資産税課税明細書）。主要棟は1981〜82年築であり、新耐震基準への適合・アスベスト・修繕履歴は要確認。担保設定は登記簿謄本で要確認。
B19: ※償却資産の課税標準額9,779千円。R8年度固定資産税・都市計画税の年税額1,488千円。

Sheet 不動産(賃借) 
B3: 内容 | C3: 内容 | D3: 所在地 地番・家屋番号 | E3: 面積 (㎡) | F3: 契約内容 | G3: 貸主 | H3: 月間賃料 (千円) | I3: 敷金 (千円) | J3: 備考
B4: 該当なし | C4: 賃借物件なし（地代家賃の計上なし）

Sheet 設備
A1: ■ 貼付範囲 B2:K29 → 企業概要書「保有設備一覧（建物内訳）」（範囲をコピーしてパワポに貼り付け。数字はここを直す）／D33:K41（科目別）
B2: № | C2: 科目 | D2: 資産名（用途） | E2: 償却方法 | F2: 取得年 | G2: 取得月 | H2: 耐用年数 | I2: 取得原価 | J2: 期末帳簿価額 (千円) | K2: 所在・面積等
B3: 1 | C3: 建物 | D3: 管理棟 | J3: 20192827 | K3: 宝田一丁目4-20（365.0㎡）
B4: 2 | C4: 建物 | D4: 荷捌市場 | J4: 5899377 | K4: 宝田一丁目4-20（330.7㎡）
B5: 3 | C5: 建物 | D5: 倉庫 | J5: 1165921 | K5: 宝田一丁目4-20（320.2㎡）
B6: 4 | C6: 建物 | D6: 容器庫 | J6: 500001 | K6: 宝田一丁目4-20（198.7㎡）
B7: 5 | C7: 建物 | D7: 物置 | J7: 1 | K7: 宝田一丁目4-20（34.4㎡）
B8: 6 | C8: 建物 | D8: 容器倉庫 | J8: 249260 | K8: 宝田一丁目4-20
B9: 7 | C9: 建物 | D9: シャッター | J9: 1 | K9: 宝田一丁目4-20
B10: 8 | C10: 建物 | D10: シャッター取替 | J10: 1739340 | K10: 宝田一丁目4-20
B11: 9 | C11: 建物 | D11: 改修工事 | J11: 2695280 | K11: 宝田一丁目4-20
B12: 10 | C12: 建物 | D12: 改修工事 | J12: 6000156 | K12: 宝田一丁目4-20
B13: 11 | C13: 建物 | D13: パッケージ場 | J13: 11751239 | K13: 宝田一丁目5-20（629.3㎡）
B14: 12 | C14: 建物 | D14: シャッター更新 | J14: 1077501 | K14: 宝田一丁目4-20
... B26: 24 | C26: 建物 | D26: シャッター | J26: 2570350 | K26: 宝田一丁目4-20
B27: 25 | C27: 建物 | D27: 資材倉庫外壁改修（2025年5月） | F27: 2025 | G27: 5 | J27: 917734 | K27: 宝田一丁目4-20
B28: 26 | C28: 建物 | D28: 資材倉庫シャッター（2025年5月） | F28: 2025 | G28: 5 | J28: 401759 | K28: 宝田一丁目4-20
C29: 建物 計 | J29: =SUM(J3:J28) -> 92065694
B30: チェック：BS建物と一致 | J30: =J29='BS(借方)'!F22 -> TRUE
D33: 科目 | J33: 期末帳簿価額 (千円) | K33: 備考
D34: 建物 | J34: ='BS(借方)'!F22 -> 92065694 | K34: 左表の内訳のとおり。改修工事を資産計上
D35: 建物付属設備 | J35: ='BS(借方)'!F23 -> 11399836 | K35: 冷蔵庫ユニット・シャッター等（内訳は台帳で要確認）
D36: 構築物 | J36: ='BS(借方)'!F24 -> 284395
D37: 機械装置 | J37: ='BS(借方)'!F25 -> 2 | K37: 備忘価額のみ（償却済）
D38: 車両運搬具 | J38: ='BS(借方)'!F26 -> 15 | K38: 備忘価額のみ（償却済）。車両は自己所有とリースを併用
D39: 工具器具備品 | J39: ='BS(借方)'!F27 -> 18546
D40: ソフトウェア | J40: ='BS(借方)'!F37 -> 371800 | K40: 販売管理システム等と推察（要確認）
D41: 合計 | J41: =SUM(J34:J40) -> 104140288
B43: ※固定資産内訳書（2026/3期末）。固定資産台帳は未受領のため、償却方法・取得年月・取得原価、冷蔵設備・フォークリフト・車両等の明細は受領後に追加（非表示列）。

Sheet 許認可
A1: 許認可一覧
A2: ■ 貼付範囲 B5:F8 → 企業概要書「許認可一覧」（範囲をコピーしてパワポに貼り付け。数字はここを直す）
B5: 許認可等 | C5: 根拠法令・所管 | D5: 内容 | E5: 認定日・効力発生日 | F5: 備考
B6: 地方卸売市場の認定 | C6: 卸売市場法 （山形県知事） | D6: 卸売市場の名称：株式会社鶴岡中央青果 所在地：山形県鶴岡市宝田一丁目4番20号 | E6: 2020年6月19日認定 （効力発生日 2020年6月21日） | F6: 改正卸売市場法の施行に伴う認定
B7: 地方卸売市場の変更の認定 | C7: 卸売市場法第14条 （山形県知事） | D7: 認定事項の変更（変更内容は要確認） | E7: 2026年2月13日認定 （効力発生日 2026年4月1日） | F7: 認定証の写しを受領
B8: 倉庫業 | C8: 倉庫業法 | D8: 定款の目的に記載 | E8: 要確認 | F8: 登録の有無は要確認
B10: ※出所：地方卸売市場の認定証・変更の認定証（山形県）、履歴事項全部証明書。認定の条件（取扱品目・開場日等）は業務規程で要確認。

Sheet 沿革
A1: 沿革
A2: ■ 貼付範囲 B4:C16 → 企業概要書「沿革」（範囲をコピーしてパワポに貼り付け。数字はここを直す）
B4: 年月 | C4: 主な出来事
B5: 1973年11月 | C5: 株式会社鶴岡中央青果を設立
B6: 1981〜82年 | C6: 現本社地（宝田一丁目）に事務所・市場・倉庫・パッケージ場（事務所兼倉庫）を建築
B7: 1984年11月 | C7: 住居表示の実施により本店所在地の表記が「鶴岡市宝田一丁目4番20号」となる
B8: 2006年 | C8: 会社法施行に伴い取締役会設置会社・監査役設置会社の登記
B9: 2012年 | C9: 定款の目的を変更（現行：青果物の販売及び卸売、倉庫業ほか）。宝田一丁目5-1に倉庫（鉄骨造139㎡）を新築
B10: 2019年10月 | C10: 受託販売の会計表示を総額から純額（受託手数料のみ）へ変更
B11: 2020年6月 | C11: 改正卸売市場法の施行に伴い、山形県知事より地方卸売市場の認定を受ける
B12: 2025年5月 | C12: 資材倉庫の外壁・シャッターを改修
B13: 2026年1月 | C13: 鶴岡市内のもう1社の青果市場が撤退し、市内で唯一の青果市場となる
B14: 2026年2月 | C14: 地方卸売市場の変更の認定（2026年4月1日効力発生。変更内容は要確認）
B15: 2026年5月 | C15: 役員改選（取締役3名重任、常務取締役退任）
B16: 時期要確認 | C16: 庄内町長沼の倉庫を老朽化により解体（跡地は駐車場として賃貸）
B18: ※出所：履歴事項全部証明書、地方卸売市場の認定証、固定資産税課税明細書、個別注記表、固定資産内訳書。創業の経緯・代表者の経歴は売主様へ確認中。

Sheet その他補足
A1: その他補足情報
A2: ■ 貼付範囲 B4:C15 → 企業概要書「その他補足情報」（範囲をコピーしてパワポに貼り付け。数字はここを直す）
B4: 項目 | C4: 内容
B5: 許認可 | C5: ・地方卸売市場（卸売市場法）：2020年6月に山形県知事の認定、2026年2月に変更の認定（「許認可一覧」参照） ・倉庫業：定款目的に記載（登録の有無は要確認）
B6: 競合環境 | C6: ・鶴岡市内の青果市場は当社のみ（2026年1月に2社体制から1社に） ・車で10〜15分の三川町に公設市場があり集荷面で競合。山形市・秋田の市場も集荷に来ており、秋田へ直接出荷する農家もある
B7: 市場関係 | C7: ・保証金33,303千円は仕入代金のデポジット（約10日分）。取引終了時に返金される ・預り保証金8,980千円は販売先（八百屋等）からの預り（1先あたり5〜30万円程度）
B8: 手数料・商慣習 | C8: ・受託販売手数料は8.5%（市場で一般的な水準。県への届出等で変更可能だが据置） ・売上割戻は期限内に代金を支払った八百屋等への完納奨励金（市場業界の商慣習）
B9: 賞与・退職金 | C9: ・賞与規定はなく、業績に応じて支給 ・退職金規程あり。中退共・オリックス生命で外部積立（会社の追加負担は基本的にないとの認識）
B10: 加入団体・出資先 | C10: ・山形県中小商工業協同組合、商工会議所、鶴岡信用金庫（出資金）
B11: 取引金融機関 | C11: ・鶴岡信用金庫、山形銀行、荘内銀行、日本政策金融公庫（借入残高は「財務ハイライト（B/S）」参照）
B12: 仕入先・物流 | C12: ・丸果庄内青果(株)、(株)庄果（公設庄内青果物地方卸売市場）、長井中央青果(株)、(株)マルト直治郎商店 ほか ・配送は自社対応（東京向け出荷・一部の地元スーパー向け配送のみ外部運送会社を利用）
B13: 営業時間・定休日 | C13: ・早朝5時から営業（終業時刻は要確認）／定休日は水・日・祝日
B14: 機関設計・株式 | C14: ・取締役会設置会社／監査役設置会社（監査の範囲を会計に限定） ・株式の譲渡制限あり（取締役会の承認）。発行済株式4,000株（株主8名）
B15: Webサイト | C15: ・http://www.turu-chu.co.jp/（だだちゃ豆・庄内柿等の特産品、安全への取組みを掲載。検索結果の要約であり本文は要確認）

Sheet 財務
B2: IMの財務詳細ページのデータは財務入力のシートから流用してください

Sheet その他
A1: 要確認事項・面談回答・Web調査メモ（ヒアリング項目／資料依頼の原本）
A2: 最終更新：2026年10月27日（追加資料〔9月試算表・買参人別／荷主別順位表・分類別商品売上実績表・認定証・賃金台帳〕を反映）。★＝重要論点
B3: No. | C3: 区分 | D3: 論点 | E3: 優先度 | F3: 状況（第2回面談の回答／残る確認事項）
B4: 1 | C4: 事業 | D4: 売上高の構成（買付販売／受託販売手数料／センター費／資材売上）の年度別内訳。決算書では「商品売上高」1本表示 | E4: 高 | F4: 一部回答：受託手数料は販売額の8.5%、センター費は主婦の店の配送額の約10%（1日約10万円）。年度別内訳は資料依頼
B5: 2 | C5: 事業 | D5: 市場の法的位置づけ（卸売市場法上の地方卸売市場の認定／開設者兼卸売業者）、認定日・条件、仲卸業者数・売買参加者数 | E5: 高 | F5: 回答資料受領：地方卸売市場の認定証（2020/6/19認定）・変更の認定証（2026/2/13認定、2026/4/1効力）。変更内容・仲卸業者数・売買参加者数は要確認
B6: 3 | C6: 事業 | D6: 主要販売先別・仕入先（出荷者）別の年間取引高（内訳書は期末残高のみ）。(株)主婦の店への依存度 | E6: 高 | F6: 回答資料受領（買参人別・荷主別順位表、上位20位×3期）。(株)主婦の店鶴岡店は2026/3期345,227千円（決算書売上高の28.9%）で依存度が高い。社内勘定（KK・パッケージ）の性質は要確認
B7: 4 | C7: 事業 | D7: 「主婦センター費」「センター費」の内容、契約条件 | E7: 高 | F7: 回答済：主婦の店の仕入商品の配送を受託し、配送額の約10%をセンター費として受領（1日約10万円）。契約書の有無は要確認
B8: 5 | C8: 財務 | D8: 2025/3期の営業赤字（△4,423千円）の要因。売上総利益率は18.6%→17.9%→16.6%と低下 | E8: 高 | F8: 要確認。足元は人件費削減により利益体質が改善との回答
B9: 6 | C9: 財務 | D9: 2026/3期に賞与計上がない理由。今後の支給方針 | E9: 高 | F9: 回答済：賞与規定はなく、業績に応じて支給。年度別・人別の支給実績は要確認
B10: 7 | C10: 財務 | D10: 前期損益修正損20,900千円（過年度保険解約訂正額）の経緯。解約返戻金の受領有無 | E10: 高 | F10: 要確認
B11: 8 | C11: 財務 | D11: 役員報酬の減額（代表者10,560千円→4,320千円）の理由、常務取締役退任（2026/5）後の体制 | E11: 高 | F11: 一部回答：常務は考え方の相違により退職（業績への悪影響はないとの認識）。業務範囲は社長＝経営全般・販売、弟（63歳）＝買付・販売、配偶者＝関与なし。譲渡後は弟のみ残留、他役員は退任予定。減額理由は要確認
B12: 9 | C12: 財務 | D12: 借入金の金利・返済予定・担保・代表者保証。有利子負債361,058千円（2026/3末） | E12: 高 | F12: 要確認
B13: 10 | C13: 財務 | D13: 保証金33,303千円（うち庄内青果物卸売精算(有)31,993千円）の性質・返還条件、預り保証金8,980千円の相手先 | E13: 中 | F13: 回答済：仕入代金に対するデポジット（約10日分）で取引終了時に返金。預り保証金は販売先（八百屋等）から1先5〜30万円程度
B14: 11 | C14: 財務 | D14: 投資有価証券の減少（2026/3末2,600千円→2026/7末1,600千円）。(株)庄果株式の処分有無 | E14: 中 | F14: 要確認
B15: 12 | C15: 財務 | D15: 租税公課12,177千円の内訳（税込経理による消費税納付額と推察） | E15: 中 | F15: 要確認
... B46: 46 | C46: 財務 | D46: 投資有価証券が2026/3末2,600千円→9月末1,600千円に減少（(株)庄果株式の処分有無） | E46: 中 | F46: 要確認
C48: Web出所：https://www.turu-chu.co.jp/ ／ https://www.pref.yamagata.jp/140031/sangyo/nourinsuisangyou/nogyo/business/oroshiurisijyou.html ／
C49: https://www.pref.yamagata.jp/documents/26382/r7shijo_gaiyou.pdf ／ https://www.inetshonai.or.jp/~seika/main.html
B51: ■ プロセス関連（社内確認事項）
B52: 本項は社内確認事項であり、企業概要書・ノンネームシート等の買手候補への開示資料には記載しない。
B53: No. | C53: 区分 | D53: 内容 | F53: 対応
B54: 1 | C54: 面談運営 | D54: 社長はオンライン面談不可。今後は電話でのやり取りを基本とし、重要なタイミングで往訪する | F54: 往訪日程は都度調整
B55: 2 | C55: 前回プロセス | D55: 前回クロージング手前まで進んだ候補先はオーランドジャパン。トップ面談は同社とのみ実施 | F55: 既接触先として打診対象から除外
B56: 3 | C56: テール条項 | D56: 各仲介会社とのテール条項は、トップ面談を実施した候補先を対象とする形で統一することで了承 | F56: 契約書面の文言を確認
B57: 4 | C57: ロングリスト | D57: LLの18番までの候補先はNG。山形県本社の企業は原則NG。日東ベストはNC（ネームクリア）OK | F57: LLを修正し、NG先を除外
B58: 5 | C58: ネームクリア方針 | D58: 既存取引先および山形県内企業を除けば、基本的に社名開示可能 | F58: 打診時の社名開示ルールとして運用
B59: 6 | C59: ノンネーム | D59: NNの内容は問題なし（社長確認済み） | F59: 現行版で打診開始可
B60: 7 | C60: マッチング方針 | D60: 既接触先・NG先を除外したうえで、余剰商品（過剰入荷分）の販売チャネルを持つ企業を中心にマッチングを進める | F60: LLの優先順位付けに反映
B61: 8 | C61: 追加資料 | D61: 面談時に追加資料を依頼。丸印を付けた6項目（総勘定元帳Excel、給与台帳、品目別取扱高等）を回収し当社で集計。10月分以降の給与台帳も依頼 | F61: 菅原氏経由で回収
B62: 9 | C62: 面談記録 | D62: 2026/10/16往訪。Gemini議事録・文字起こしあり（話者識別が不正確のため、数値・固有名詞は原資料で要確認） | F62: —
B63: 10 | C63: 希望価格の根拠 | D63: 前回ディール時の金額をベースに進める。ミニマム1.1億円（前回最終は1.15億円との発言）、できる限り上を目指す | F63: 買手向け資料には「1.1億円以上」のみ記載
B64: 11 | C64: 前回DD | D64: 前回プロセスでDDを実施済み（棚卸資産の指摘はなかったとの回答） | F64: 前回DDの指摘事項の有無を確認
B65: 12 | C65: NG先（詳細） | D65: 完全同業他社、取引実績のある企業（オイシックス、ロピア等）、山形県本社企業（LL18社＋36番）をNG | F65: LLから除外
... B68: 15 | C68: 土地評価 | D68: 土地の再評価を当社で実施する（社長も購入時より価値が下がっているとの認識） | F68: 田垣内が実施

Sheet スケジュール(横)
B3: TODO | D3: 2月 | U3: 3月 | AZ3: 4月 | CE3: 5月
D4: 12 | E4: 13 | F4: 14 | G4: 15 | H4: 16 | I4: 17 | J4: 18 | K4: 19 | L4: 20 | M4: 21 | N4: 22 | O4: 23 | P4: 24 | Q4: 25 | R4: 26 | S4: 27 | T4: 28 | U4: 1 | V4: 2 | W4: 3 | X4: 4 | Y4: 5 | Z4: 6 | AA4: 7 | AB4: 8 | AC4: 9 | AD4: 10 | AE4: 11 | AF4: 12 | AG4: 13 | AH4: 14 | AI4: 15 | AJ4: 16 | AK4: 17 | AL4: 18 | AM4: 19 | AN4: 20 | AO4: 21 | AP4: 22 | AQ4: 23 | AR4: 24 | AS4: 25 | AT4: 26 | AU4: 27 | AV4: 28 | AW4: 29 | AX4: 30 | AY4: 31 | AZ4: 1 | BA4: 2 | BB4: 3 | BC4: 4 | BD4: 5 | BE4: 6 | BF4: 7 | BG4: 8 | BH4: 9 | BI4: 10 | BJ4: 11 | BK4: 12 | BL4: 13 | BM4: 14 | BN4: 15 | BO4: 16 | BP4: 17 | BQ4: 18 | BR4: 19 | BS4: 20 | BT4: 21 | BU4: 22 | BV4: 23 | BW4: 24 | BX4: 25 | BY4: 26 | BZ4: 27 | CA4: 28 | CB4: 29 | CC4: 30 | CD4: 31 | CE4: 1 | CF4: 2 | CG4: 3 | CH4: 4 | CI4: 5 | CJ4: 6 | CK4: 7 | CL4: 8 | CM4: 9 | CN4: 10 | CO4: 11 | CP4: 12 | CQ4: 13 | CR4: 14 | CS4: 15 | CT4: 16 | CU4: 17 | CV4: 18 | CW4: 19 | CX4: 20 | CY4: 21 | CZ4: 22 | DA4: 23 | DB4: 24 | DC4: 25 | DD4: 26 | DE4: 27 | DF4: 28 | DG4: 29 | DH4: 30 | DI4: 31
B5: 交渉 | C5: TOP面談
C6: LOIドラフト作成
C7: LOI提出
C8: LOI受領(独占交渉権)
B9: DD | C9: DDスコープ・依頼先選定
C10: IRL提出
C11: QAラリー
C12: マネジメントインタビュー | L12: B | AA12: F | AB12: L
C13: DD結果報告 | AX13: F | AY13: L
B14: 契約 | C14: SPA内容調整
C15: SPA締結
C16: CoC対応等
C17: クロージング
C18: 役員変更登記申請
B19: PMI | C19: 従業員・取引先開示
C20: 連帯保証解除等
C21: PMI・グループ連携 | DK21: ● | DL21: 報酬発生

Sheet スケジュール(縦)
B2: スケジュール表
B3: 日付 | C3: 曜日 | D3: 【売主】 ●●●様 | E3: 【買主】 ●●●様 | F3: M&A承継機構
A4: 2025年 | B4: 45931 | C4: =TEXT(B4,"aaa") -> Wed | D4: 本日 お打ち合わせ
B5: =B4+1 -> 2025-10-02 00:00:00 | C5: =TEXT(B5,"aaa") -> Thu | E5: TOP面談準備
B6: =B5+1 -> 2025-10-03 00:00:00 | C6: =TEXT(B6,"aaa") -> Fri | E6: LOI内容検討 | F6: LOIドラフト提示
B7: =B6+1 -> 2025-10-04 00:00:00 | C7: =TEXT(B7,"aaa") -> Sat
B8: =B7+1 -> 2025-10-05 00:00:00 | C8: =TEXT(B8,"aaa") -> Sun
B9: =B8+1 -> 2025-10-06 00:00:00 | C9: =TEXT(B9,"aaa") -> Mon
B10: =B9+1 -> 2025-10-07 00:00:00 | C10: =TEXT(B10,"aaa") -> Tue
B11: =B10+1 -> 2025-10-08 00:00:00 | C11: =TEXT(B11,"aaa") -> Wed | D11: TOP面談
B12: =B11+1 -> 2025-10-09 00:00:00 | C12: =TEXT(B12,"aaa") -> Thu
B13: =B12+1 -> 2025-10-10 00:00:00 | C13: =TEXT(B13,"aaa") -> Fri
B14: =B13+1 -> 2025-10-11 00:00:00 | C14: =TEXT(B14,"aaa") -> Sat
B15: =B14+1 -> 2025-10-12 00:00:00 | C15: =TEXT(B15,"aaa") -> Sun
B16: =B15+1 -> 2025-10-13 00:00:00 | C16: =TEXT(B16,"aaa") -> Mon
B17: =B16+1 -> 2025-10-14 00:00:00 | C17: =TEXT(B17,"aaa") -> Tue | E17: LOI提出
B18: =B17+1 -> 2025-10-15 00:00:00 | C18: =TEXT(B18,"aaa") -> Wed | E18: DDスコープ・依頼先検討
B19: =B18+1 -> 2025-10-16 00:00:00 | C19: =TEXT(B19,"aaa") -> Thu
B20: =B19+1 -> 2025-10-17 00:00:00 | C20: =TEXT(B20,"aaa") -> Fri | D20: LOI回答(独占交渉権付与) | E20: ※独占交渉権獲得 | F20: LOI内容説明
B21: =B20+1 -> 2025-10-18 00:00:00 | C21: =TEXT(B21,"aaa") -> Sat
B22: =B21+1 -> 2025-10-19 00:00:00 | C22: =TEXT(B22,"aaa") -> Sun
B23: =B22+1 -> 2025-10-20 00:00:00 | C23: =TEXT(B23,"aaa") -> Mon
B24: =B23+1 -> 2025-10-21 00:00:00 | C24: =TEXT(B24,"aaa") -> Tue
B25: =B24+1 -> 2025-10-22 00:00:00 | C25: =TEXT(B25,"aaa") -> Wed | E25: DDスコープ・依頼先確定
B26: =B25+1 -> 2025-10-23 00:00:00 | C26: =TEXT(B26,"aaa") -> Thu
B27: =B26+1 -> 2025-10-24 00:00:00 | C27: =TEXT(B27,"aaa") -> Fri
B28: =B27+1 -> 2025-10-25 00:00:00 | C28: =TEXT(B28,"aaa") -> Sat
B29: =B28+1 -> 2025-10-26 00:00:00 | C29: =TEXT(B29,"aaa") -> Sun
B30: =B29+1 -> 2025-10-27 00:00:00 | C30: =TEXT(B30,"aaa") -> Mon | E30: DDキックオフミーティング
B31: =B30+1 -> 2025-10-28 00:00:00 | C31: =TEXT(B31,"aaa") -> Tue | D31: DD資料提出・QA対応 | E31: IRL提出※DD依頼先 | F31: DD資料提出・QA対応
B32: =B31+1 -> 2025-10-29 00:00:00 | C32: =TEXT(B32,"aaa") -> Wed | E32: DDQA対応※DD依頼先
B33: =B32+1 -> 2025-10-30 00:00:00 | C33: =TEXT(B33,"aaa") -> Thu
B34: =B33+1 -> 2025-10-31 00:00:00 | C34: =TEXT(B34,"aaa") -> Fri
B35: =B34+1 -> 2025-11-01 00:00:00 | C35: =TEXT(B35,"aaa") -> Sat
B36: =B35+1 -> 2025-11-02 00:00:00 | C36: =TEXT(B36,"aaa") -> Sun
B37: =B36+1 -> 2025-11-03 00:00:00 | C37: =TEXT(B37,"aaa") -> Mon
B38: =B37+1 -> 2025-11-04 00:00:00 | C38: =TEXT(B38,"aaa") -> Tue | D38: DD資料提出・QA対応 | E38: DDQA対応※DD依頼先 | F38: DD資料提出・QA対応
B39: =B38+1 -> 2025-11-05 00:00:00 | C39: =TEXT(B39,"aaa") -> Wed
B40: =B39+1 -> 2025-11-06 00:00:00 | C40: =TEXT(B40,"aaa") -> Thu
B41: =B40+1 -> 2025-11-07 00:00:00 | C41: =TEXT(B41,"aaa") -> Fri
B42: =B41+1 -> 2025-11-08 00:00:00 | C42: =TEXT(B42,"aaa") -> Sat
B43: =B42+1 -> 2025-11-09 00:00:00 | C43: =TEXT(B43,"aaa") -> Sun
B44: =B43+1 -> 2025-11-10 00:00:00 | C44: =TEXT(B44,"aaa") -> Mon | D44: DD資料提出・QA対応 | E44: DDQA対応※DD依頼先 | F44: DD資料提出・QA対応
B45: =B44+1 -> 2025-11-11 00:00:00 | C45: =TEXT(B45,"aaa") -> Tue
B46: =B45+1 -> 2025-11-12 00:00:00 | C46: =TEXT(B46,"aaa") -> Wed | D46: DDマネジメントインタビュー
B47: =B46+1 -> 2025-11-13 00:00:00 | C47: =TEXT(B47,"aaa") -> Thu
B48: =B47+1 -> 2025-11-14 00:00:00 | C48: =TEXT(B48,"aaa") -> Fri
B49: =B48+1 -> 2025-11-15 00:00:00 | C49: =TEXT(B49,"aaa") -> Sat
B50: =B49+1 -> 2025-11-16 00:00:00 | C50: =TEXT(B50,"aaa") -> Sun
B51: =B50+1 -> 2025-11-17 00:00:00 | C51: =TEXT(B51,"aaa") -> Mon | E51: SPA内容検討 | F51: SPAドラフト提出
B52: =B51+1 -> 2025-11-18 00:00:00 | C52: =TEXT(B52,"aaa") -> Tue
B53: =B52+1 -> 2025-11-19 00:00:00 | C53: =TEXT(B53,"aaa") -> Wed
B54: =B53+1 -> 2025-11-20 00:00:00 | C54: =TEXT(B54,"aaa") -> Thu
B55: =B54+1 -> 2025-11-21 00:00:00 | C55: =TEXT(B55,"aaa") -> Fri | E55: DD結果確認(DD報告会)
B56: =B55+1 -> 2025-11-22 00:00:00 | C56: =TEXT(B56,"aaa") -> Sat
B57: =B56+1 -> 2025-11-23 00:00:00 | C57: =TEXT(B57,"aaa") -> Sun
B58: =B57+1 -> 2025-11-24 00:00:00 | C58: =TEXT(B58,"aaa") -> Mon
B59: =B58+1 -> 2025-11-25 00:00:00 | C59: =TEXT(B59,"aaa") -> Tue | E59: SPA案ご提出
B60: =B59+1 -> 2025-11-26 00:00:00 | C60: =TEXT(B60,"aaa") -> Wed | D60: SPA調整
B61: =B60+1 -> 2025-11-27 00:00:00 | C61: =TEXT(B61,"aaa") -> Thu
B62: =B61+1 -> 2025-11-28 00:00:00 | C62: =TEXT(B62,"aaa") -> Fri
B63: =B62+1 -> 2025-11-29 00:00:00 | C63: =TEXT(B63,"aaa") -> Sat
B64: =B63+1 -> 2025-11-30 00:00:00 | C64: =TEXT(B64,"aaa") -> Sun
B65: =B64+1 -> 2025-12-01 00:00:00 | C65: =TEXT(B65,"aaa") -> Mon | D65: SPA調整
B66: =B65+1 -> 2025-12-02 00:00:00 | C66: =TEXT(B66,"aaa") -> Tue
B67: =B66+1 -> 2025-12-03 00:00:00 | C67: =TEXT(B67,"aaa") -> Wed
B68: =B67+1 -> 2025-12-04 00:00:00 | C68: =TEXT(B68,"aaa") -> Thu
B69: =B68+1 -> 2025-12-05 00:00:00 | C69: =TEXT(B69,"aaa") -> Fri
B70: =B69+1 -> 2025-12-06 00:00:00 | C70: =TEXT(B70,"aaa") -> Sat
B71: =B70+1 -> 2025-12-07 00:00:00 | C71: =TEXT(B71,"aaa") -> Sun
B72: =B71+1 -> 2025-12-08 00:00:00 | C72: =TEXT(B72,"aaa") -> Mon | D72: SPA調整
B73: =B72+1 -> 2025-12-09 00:00:00 | C73: =TEXT(B73,"aaa") -> Tue
B74: =B73+1 -> 2025-12-10 00:00:00 | C74: =TEXT(B74,"aaa") -> Wed
B75: =B74+1 -> 2025-12-11 00:00:00 | C75: =TEXT(B75,"aaa") -> Thu
B76: =B75+1 -> 2025-12-12 00:00:00 | C76: =TEXT(B76,"aaa") -> Fri | D76: 株式譲渡契約書締結
B77: =B76+1 -> 2025-12-13 00:00:00 | C77: =TEXT(B77,"aaa") -> Sat
B78: =B77+1 -> 2025-12-14 00:00:00 | C78: =TEXT(B78,"aaa") -> Sun
B79: =B78+1 -> 2025-12-15 00:00:00 | C79: =TEXT(B79,"aaa") -> Mon | D79: COC対応等 | F79: COC対応等
B80: =B79+1 -> 2025-12-16 00:00:00 | C80: =TEXT(B80,"aaa") -> Tue
B81: =B80+1 -> 2025-12-17 00:00:00 | C81: =TEXT(B81,"aaa") -> Wed
B82: =B81+1 -> 2025-12-18 00:00:00 | C82: =TEXT(B82,"aaa") -> Thu
B83: =B82+1 -> 2025-12-19 00:00:00 | C83: =TEXT(B83,"aaa") -> Fri | D83: クロージング（資金決済、株主名簿書換、役員変更登記申請)
B84: =B83+1 -> 2025-12-20 00:00:00 | C84: =TEXT(B84,"aaa") -> Sat
B85: =B84+1 -> 2025-12-21 00:00:00 | C85: =TEXT(B85,"aaa") -> Sun
B86: =B85+1 -> 2025-12-22 00:00:00 | C86: =TEXT(B86,"aaa") -> Mon | D86: 従業員・取引先への開示、PMI
B87: =B86+1 -> 2025-12-23 00:00:00 | C87: =TEXT(B87,"aaa") -> Tue
B88: =B87+1 -> 2025-12-24 00:00:00 | C88: =TEXT(B88,"aaa") -> Wed
B89: =B88+1 -> 2025-12-25 00:00:00 | C89: =TEXT(B89,"aaa") -> Thu
B90: =B89+1 -> 2025-12-26 00:00:00 | C90: =TEXT(B90,"aaa") -> Fri
B91: =B90+1 -> 2025-12-27 00:00:00 | C91: =TEXT(B91,"aaa") -> Sat
B92: =B91+1 -> 2025-12-28 00:00:00 | C92: =TEXT(B92,"aaa") -> Sun
B93: =B92+1 -> 2025-12-29 00:00:00 | C93: =TEXT(B93,"aaa") -> Mon
B94: =B93+1 -> 2025-12-30 00:00:00 | C94: =TEXT(B94,"aaa") -> Tue
B95: =B94+1 -> 2025-12-31 00:00:00 | C95: =TEXT(B95,"aaa") -> Wed
A96: 2026年 | B96: =B95+1 -> 2026-01-01 00:00:00 | C96: =TEXT(B96,"aaa") -> Thu
B97: =B96+1 -> 2026-01-02 00:00:00 | C97: =TEXT(B97,"aaa") -> Fri
B98: =B97+1 -> 2026-01-03 00:00:00 | C98: =TEXT(B98,"aaa") -> Sat
B99: =B98+1 -> 2026-01-04 00:00:00 | C99: =TEXT(B99,"aaa") -> Sun
B100: =B99+1 -> 2026-01-05 00:00:00 | C100: =TEXT(B100,"aaa") -> Mon
B101: =B100+1 -> 2026-01-06 00:00:00 | C101: =TEXT(B101,"aaa") -> Tue
...

Sheet グラフ
C2: A | D2: B | E2: C | T2: A
B3: 第1四半期 | C3: 50 | D3: 10 | E3: 20 | S3: 第1四半期 | T3: 50
B4: 第2四半期 | C4: 55 | D4: 25 | E4: 22 | S4: 第2四半期 | T4: 55
B5: 第3四半期 | C5: 52 | D5: 45 | E5: 25 | S5: 第3四半期 | T5: 52
B6: 第4四半期 | C6: 50 | D6: 70 | E6: 25 | S6: 第4四半期 | T6: 80
AF16: ｂ
C18: A | D18: B | E18: C
B19: 1ヶ月目 | C19: 100 | D19: 100 | E19: 100 | T19: A
B20: 2ヶ月目 | C20: 105 | D20: 90 | E20: 110 | S20: 第1四半期 | T20: 50
B21: 3か月目 | C21: 110 | D21: 75 | E21: 90 | S21: 第2四半期 | T21: 55
B22: 4か月目 | C22: 115 | D22: 60 | E22: 80 | S22: 第3四半期 | T22: 52
B23: 5か月目 | C23: 120 | D23: 55 | E23: 45 | S23: 第4四半期 | T23: 80
C33: グラフタイトル
B34: A | C34: 60
B35: B | C35: 20
B36: C | C36: 15
B37: D | C37: 5
C51: X | D51: Y | E51: Z
B52: D | C52: 4.3 | D52: 2.4 | E52: 2
B53: C | C53: 2.5 | D53: 4.4 | E53: 2
B54: B | C54: 3.5 | D54: 1.8 | E54: 3
B55: A | C55: 4.5 | D55: 2.8 | E55: 5

Sheet 表
B2: あああ | C2: あああ | D2: あああ | E2: あああ | F2: あああ
B3: あああああ | C3: XXXXX | D3: XXXXX | E3: XXXXX | F3: ああああああああああああああああああああああああああああああああ
B4: あああああ | C4: XXXXX | D4: XXXXX | E4: XXXXX | F4: ああああああああああああああああああああああああああああああああ
B5: あああああ | C5: XXXXX | D5: XXXXX | E5: XXXXX | F5: ああああああああああああああああああああああああああああああああ
B6: あああああ | C6: XXXXX | D6: XXXXX | E6: XXXXX | F6: ああああああああああああああああああああああああああああああああ
B7: あああああ | C7: XXXXX | D7: XXXXX | E7: XXXXX | F7: ああああああああああああああああああああああああああああああああ
B8: あああああ | C8: XXXXX | D8: XXXXX | E8: XXXXX | F8: ああああああああああああああああああああああああああああああああ
B11: あああ | C11: あああ | D11: あああ | E11: あああ | F11: あああ
B12: あああああ | C12: XXXXX | D12: XXXXX | E12: XXXXX | F12: ああああああああああああああああああああああああああああああああ
C13: XXXXX | D13: XXXXX | E13: XXXXX | F13: ああああああああああああああああああああああああああああああああ
B14: あああああ | C14: XXXXX | D14: XXXXX | E14: XXXXX | F14: ああああああああああああああああああああああああああああああああ
C15: XXXXX | D15: XXXXX | E15: XXXXX | F15: ああああああああああああああああああああああああああああああああ
B16: あああああ | C16: XXXXX | D16: XXXXX | E16: XXXXX | F16: ああああああああああああああああああああああああああああああああ
C17: XXXXX | D17: XXXXX | E17: XXXXX | F17: ああああああああああああああああああああああああああああああああ
B20: あああ | C20: あああ | D20: あああ | E20: あああ
B21: あああああ | C21: XXXXX | D21: XXXXX | E21: XXXXX
C22: XXXXX | D22: XXXXX | E22: XXXXX
B23: あああああ | C23: XXXXX | D23: XXXXX | E23: XXXXX
C24: XXXXX | D24: XXXXX | E24: XXXXX
B25: あああああ | C25: XXXXX | D25: XXXXX | E25: XXXXX
C26: XXXXX | D26: XXXXX | E26: XXXXX
B29: あああ | C29: あああ | D29: あああ | E29: あああ
B30: あああああ | C30: XXXXX | D30: XXXXX | E30: XXXXX
C31: XXXXX | D31: XXXXX | E31: XXXXX
B32: あああああ | C32: XXXXX | D32: XXXXX | E32: XXXXX
C33: XXXXX | D33: XXXXX | E33: XXXXX
B34: あああああ | C34: XXXXX | D34: XXXXX | E34: XXXXX
C35: XXXXX | D35: XXXXX | E35: XXXXX
