Workbook

Sheet ルール
B3: 1 | C3: 文字は「游ゴシック」、数字は「Arial」を基本。備考欄などの細かい文章は「游ゴシック Medium」。
B4: 2 | C4: タイトル、合計欄は太字
B5: 3 | C5: 数字は円単位で入力、表示は千円単位に設定済み
B6: 4 | C6: 基本の背景は以下の通り。紺、水色、グレー、白、青。パレットの上部の色。
C8: 線は紺か白か青。
C10: 資産の部
C11: 科目 | D11: ='BS(借方)'!F10 -> 0 | E11: 調整額 | F11: 調整後
C12: 【流動資産】 | D12: =SUM(D13:D26) -> 5000000 | E12: =SUM(E13:E26) -> -500000 | F12: =SUM(F13:F26) -> 4500000
C13: 現金及び預金 | D13: 5000000 | E13: -500000 | F13: =D13+E13 -> 4500000
F14: =D14+E14 -> 0

Sheet 財務入力→

Sheet BS(借方)
C1: ←基本的にはここをつかう→
C2: 1期目 | D2: 2期目 | E2: 3期目 | F2: （4期目） | G2: 進行期
B3: 資産の部
B4: 科目 | C4: 24年1月期 | D4: 25年1月期 | E4: 26年1月期 | F4: ●●年●月期 | G4: ●●年●月 （●か月TB）
B5: 【流動資産】 | C5: =SUM(C6:C19) -> 353922232 | D5: =SUM(D6:D19) -> 309100318 | E5: =SUM(E6:E19) -> 226144406 | F5: =SUM(F6:F19) -> 0 | G5: =SUM(G6:G19) -> 0
B6: 現金及び預金 | C6: 260204106 | D6: 241196237 | E6: 193226490
B7: 売掛金 | C7: 80309192 | D7: 24606051 | E7: 20153150
B8: 貸倒引当金 | C8: -803000 | D8: -246000 | E8: -201000
B9: 商品 | C9: 1377066 | D9: 23573572 | E9: 204834
B10: 証紙 | C10: 48976 | D10: 9771051 | E10: 24020
B11: 前渡金 | C11: 5809100 | D11: 4571906 | E11: 12055237
B12: 立替金 | D12: 79184
B13: 前払費用 | C13: 621392 | D13: 805869 | E13: 640475
B14: 未収入金 | C14: 3228000 | D14: 4742448 | E14: 41200
B15: 仮払税 | C15: 3127400
B20: 【固定資産】 | C20: =C21+C35+C46 -> 140739380 | D20: =D21+D35+D46 -> 228972793 | E20: =E21+E35+E46 -> 323863136 | F20: =F21+F35+F46 -> 0 | G20: =G21+G35+G46 -> 0
B21: ［有形固定資産］ | C21: =SUM(C22:C34) -> 1931618 | D21: =SUM(D22:D34) -> 1479093 | E21: =SUM(E22:E34) -> 1056920 | F21: =SUM(F22:F34) -> 0 | G21: =SUM(G22:G34) -> 0
B22: 建物附属設備 | C22: 830303 | D22: 765648 | E22: 700993
B23: 車両運搬具 | C23: 797788 | D23: 531328 | E23: 264868
B24: 工具器具備品 | C24: 303527 | D24: 182117 | E24: 91059
B35: ［無形固定資産］ | C35: =SUM(C36:C45) -> 0 | D35: =SUM(D36:D45) -> 2688001 | E35: =SUM(E36:E45) -> 2112001 | F35: =SUM(F36:F45) -> 0 | G35: =SUM(G36:G45) -> 0
B36: ソフトウェア | D36: 2688001 | E36: 2112001
B46: ［投資その他資産］ | C46: =SUM(C47:C55) -> 138807762 | D46: =SUM(D47:D55) -> 224805699 | E46: =SUM(E47:E55) -> 320694215 | F46: =SUM(F47:F55) -> 0 | G46: =SUM(G47:G55) -> 0
B47: 投資有価証券 | C47: 112672352 | D47: 188090341 | E47: 275896334
B48: 出資金 | C48: 30000 | D48: 30000 | E48: 30000
B49: 敷金 | C49: 50000 | D49: 50000 | E49: 50000
B50: 差入保証金 | C50: 1263500 | D50: 1263500 | E50: 1263500
B51: 預託金 | C51: 25040 | D51: 25040 | E51: 25040
B52: 保険積立金 | C52: 24766870 | D52: 35346818 | E52: 43326766
B53: 長期前払費用 | E53: 102575
B56: 【繰延資産】 | C56: =SUM(C57:C60) -> 0 | D56: =SUM(D57:D60) -> 0 | E56: =SUM(E57:E60) -> 0 | F56: =SUM(F57:F60) -> 0 | G56: =SUM(G57:G60) -> 0
B61: 資産合計 | C61: =C5+C20+C56 -> 494661612 | D61: =D5+D20+D56 -> 538073111 | E61: =E5+E20+E56 -> 550007542 | F61: =F5+F20+F56 -> 0 | G61: =G5+G20+G56 -> 0
B63: バランスチェック | C63: =EXACT(C61,'BS (貸方)'!C51) -> TRUE | D63: =EXACT(D61,'BS (貸方)'!D51) -> TRUE | E63: =EXACT(E61,'BS (貸方)'!E51) -> TRUE | F63: =EXACT(F61,'BS (貸方)'!F51) -> TRUE | G63: =EXACT(G61,'BS (貸方)'!G51) -> TRUE

Sheet BS (貸方)
E2: (単位：千円)
B3: 負債の部
B4: 科目 | C4: ='BS(借方)'!C4 -> 24年1月期 | D4: ='BS(借方)'!D4 -> 25年1月期 | E4: ='BS(借方)'!E4 -> 26年1月期 | F4: ='BS(借方)'!F4 -> ●●年●月期 | G4: ='BS(借方)'!G4 -> ●●年●月 （●か月TB）
B5: 【流動負債】 | C5: =SUM(C6:C17) -> 47623635 | D5: =SUM(D6:D17) -> 106163378 | E5: =SUM(E6:E17) -> 70491633 | F5: =SUM(F6:F17) -> 0 | G5: =SUM(G6:G17) -> 0
B6: 買掛金 | C6: 42759404 | D6: 51250714 | E6: 9644516
B7: 未払金 | C7: 3911586 | D7: 5447277 | E7: 3947278
B8: 未払法人税等 | C8: 35000 | D8: 19454800 | E8: 2929500
B9: 未払消費税等 | E9: 12017600
B10: 預り金 | C10: 917645 | D10: 154227 | E10: 124739
B11: 仮受金 | D11: 228360
B12: 一年以内返済長期借入金 | D12: 29628000 | E12: 41828000
B18: 【固定負債】 | C18: =SUM(C19:C24) -> 191690000 | D18: =SUM(D19:D24) -> 136004000 | E18: =SUM(E19:E24) -> 145980000 | F18: =SUM(F19:F24) -> 0 | G18: =SUM(G19:G24) -> 0
B19: 長期借入金 | C19: 191690000 | D19: 136004000 | E19: 145980000
B25: 負債合計 | C25: =C5+C18 -> 239313635 | D25: =D5+D18 -> 242167378 | E25: =E5+E18 -> 216471633 | F25: =F5+F18 -> 0 | G25: =G5+G18 -> 0
B34: 純資産の部
B35: 【資本金】 | C35: =SUM(C36:C38) -> 10000000 | D35: =SUM(D36:D38) -> 10000000 | E35: =SUM(E36:E38) -> 10000000 | F35: =SUM(F36:F38) -> 0 | G35: =SUM(G36:G38) -> 0
B36: 資本金 | C36: 10000000 | D36: 10000000 | E36: 10000000
B39: 【資本剰余金】 | C39: =SUM(C40:C42) -> 0 | D39: =SUM(D40:D42) -> 0 | E39: =SUM(E40:E42) -> 0 | F39: =SUM(F40:F42) -> 0 | G39: =SUM(G40:G42) -> 0
B43: 【利益剰余金】 | C43: =SUM(C44:C48) -> 245347977 | D43: =SUM(D44:D48) -> 285905733 | E43: =SUM(E44:E48) -> 323535909 | F43: =SUM(F44:F48) -> 0 | G43: =SUM(G44:G48) -> 0
B44: 繰越利益剰余金 | C44: 245347977 | D44: 285905733 | E44: 323535909
B49: 【自己株式】 | C49: 0 | D49: 0 | E49: 0 | F49: 0 | G49: 0
B50: 純資産合計 | C50: =C35+C39+C43+C49 -> 255347977 | D50: =D35+D39+D43+D49 -> 295905733 | E50: =E35+E39+E43+E49 -> 333535909 | F50: =F35+F39+F43+F49 -> 0 | G50: =G35+G39+G43+G49 -> 0
B51: 負債・純資産合計 | C51: =C25+C50 -> 494661612 | D51: =D25+D50 -> 538073111 | E51: =E25+E50 -> 550007542 | F51: =F25+F50 -> 0 | G51: =G25+G50 -> 0
B53: バランスチェック | C53: =EXACT(C51,'BS(借方)'!C61) -> TRUE | D53: =EXACT(D51,'BS(借方)'!D61) -> TRUE | E53: =EXACT(E51,'BS(借方)'!E61) -> TRUE | F53: =EXACT(F51,'BS(借方)'!F61) -> TRUE | G53: =EXACT(G51,'BS(借方)'!G61) -> TRUE

Sheet PL
H2: (単位：千円)
B3: 科目 | C3: ='BS(借方)'!C4 -> 24年1月期 | E3: ='BS(借方)'!D4 -> 25年1月期 | G3: ='BS(借方)'!E4 -> 26年1月期 | I3: ='BS(借方)'!F4 -> ●●年●月期 | K3: ●年●月期
C4: 帳簿価額 | D4: 売上高比 | E4: 帳簿価額 | F4: 売上高比 | G4: 帳簿価額 | H4: 売上高比 | I4: 帳簿価額 | J4: 売上高比 | K4: 帳簿価額 | L4: 売上高比
B5: 売上高 | C5: 301575965 | D5: =IF(C5=0,"",C5/C$11) -> 0.9520781 | E5: 285379413 | F5: =IF(E5=0,"",E5/E$11) -> 0.6429375 | G5: 387747182 | H5: =IF(G5=0,"",G5/G$11) -> 0.91780019 | J5: =IF(I5=0,"",I5/I$11) | L5: =IF(K5=0,"",K5/K$11)
B6: 輸出売上 | C6: 15179525 | D6: =IF(C6=0,"",C6/C$11) -> 0.0479219 | E6: 158488638 | F6: =IF(E6=0,"",E6/E$11) -> 0.3570625 | G6: 34727325 | H6: =IF(G6=0,"",G6/G$11) -> 0.082199812 | J6: =IF(I6=0,"",I6/I$11) | L6: =IF(K6=0,"",K6/K$11)
D9: =IF(C9=0,"",C9/C$11) | F9: =IF(E9=0,"",E9/E$11) | H9: =IF(G9=0,"",G9/G$11) | J9: =IF(I9=0,"",I9/I$11) | L9: =IF(K9=0,"",K9/K$11)
D10: =IF(C10=0,"",C10/C$11) | F10: =IF(E10=0,"",E10/E$11) | H10: =IF(G10=0,"",G10/G$11) | J10: =IF(I10=0,"",I10/I$11) | L10: =IF(K10=0,"",K10/K$11)
B11: 売上高 | C11: =SUM(C5:C10) -> 316755490 | D11: =IF(C11=0,"",C11/C$11) -> 1 | E11: =SUM(E5:E10) -> 443868051 | F11: =IF(E11=0,"",E11/E$11) -> 1 | G11: =SUM(G5:G10) -> 422474507 | H11: =IF(G11=0,"",G11/G$11) -> 1 | I11: =SUM(I5:I10) -> 0 | J11: =IF(I11=0,"",I11/I$11) | K11: =SUM(K5:K10) -> 0 | L11: =IF(K11=0,"",K11/K$11)
B12: 期首商品棚卸高 | C12: 3024069 | D12: =IF(C12=0,"",C12/C$11) -> 0.0095470137 | E12: 1426042 | F12: =IF(E12=0,"",E12/E$11) -> 0.0032127611 | G12: 33344623 | H12: =IF(G12=0,"",G12/G$11) -> 0.078926947 | J12: =IF(I12=0,"",I12/I$11) | L12: =IF(K12=0,"",K12/K$11)
B13: 当期商品仕入高 | C13: 172656708 | D13: =IF(C13=0,"",C13/C$11) -> 0.54507882 | E13: 237257918 | F13: =IF(E13=0,"",E13/E$11) -> 0.53452353 | G13: 225575333 | H13: =IF(G13=0,"",G13/G$11) -> 0.53393833
B14: （製）支払手数料 | C14: 26573925 | D14: =IF(C14=0,"",C14/C$11) -> 0.083894126 | E14: 50722738 | F14: =IF(E14=0,"",E14/E$11) -> 0.11427436 | G14: 21094265 | H14: =IF(G14=0,"",G14/G$11) -> 0.049930267
B15: （製）サンプル | C15: 6307077 | D15: =IF(C15=0,"",C15/C$11) -> 0.0199115 | E15: 2327904 | F15: =IF(E15=0,"",E15/E$11) -> 0.0052445856 | G15: 2831360 | H15: =IF(G15=0,"",G15/G$11) -> 0.0067018482
B16: 試作費 | C16: 4487974 | D16: =IF(C16=0,"",C16/C$11) -> 0.014168575 | E16: 13796708 | F16: =IF(E16=0,"",E16/E$11) -> 0.031082904 | G16: 3637077 | H16: =IF(G16=0,"",G16/G$11) -> 0.0086089857 | J16: =IF(I16=0,"",I16/I$11) | L16: =IF(K16=0,"",K16/K$11)
B17: （製）外注費 | C17: 8299304 | D17: =IF(C17=0,"",C17/C$11) -> 0.026200979 | E17: 9972324 | F17: =IF(E17=0,"",E17/E$11) -> 0.022466866 | G17: 5262263 | H17: =IF(G17=0,"",G17/G$11) -> 0.012455812 | J17: =IF(I17=0,"",I17/I$11) | L17: =IF(K17=0,"",K17/K$11)
B18: 仕入値引高 | D18: =IF(C18=0,"",C18/C$11) | F18: =IF(E18=0,"",E18/E$11) | G18: -100 | H18: =IF(G18=0,"",G18/G$11) -> -2.3670067e-07 | J18: =IF(I18=0,"",I18/I$11) | L18: =IF(K18=0,"",K18/K$11)
B19: 他勘定振替高 | C19: -6722798 | D19: =IF(C19=0,"",C19/C$11) -> -0.021223935 | E19: -17217311 | F19: =IF(E19=0,"",E19/E$11) -> -0.038789255 | G19: -19844732 | H19: =IF(G19=0,"",G19/G$11) -> -0.046972614
B20: 期末商品棚卸高 | C20: -1426042 | D20: =IF(C20=0,"",C20/C$11) -> -0.0045020277 | E20: -33344623 | F20: =IF(E20=0,"",E20/E$11) -> -0.075122827 | G20: -228854 | H20: =IF(G20=0,"",G20/G$11) -> -0.00054169896
B21: 売上原価 | C21: =SUM(C12:C20) -> 213200217 | D21: =IF(C21=0,"",C21/C$11) -> 0.67307505 | E21: =SUM(E12:E20) -> 264941700 | F21: =IF(E21=0,"",E21/E$11) -> 0.59689293 | G21: =SUM(G12:G20) -> 271671235 | H21: =IF(G21=0,"",G21/G$11) -> 0.64304764 | I21: =SUM(I12:I18) -> 0 | J21: =IF(I21=0,"",I21/I$11) | K21: =SUM(K12:K18) -> 0 | L21: =IF(K21=0,"",K21/K$11)
B22: 売上総利益 | C22: =C11-C21 -> 103555273 | D22: =IF(C22=0,"",C22/C$11) -> 0.32692495 | E22: =E11-E21 -> 178926351 | F22: =IF(E22=0,"",E22/E$11) -> 0.40310707 | G22: =G11-G21 -> 150803272 | H22: =IF(G22=0,"",G22/G$11) -> 0.35695236 | I22: =I11-I21 -> 0 | J22: =IF(I22=0,"",I22/I$11) | K22: =K11-K21 -> 0 | L22: =IF(K22=0,"",K22/K$11)
B23: 販売費及び一般管理費 | C23: =SGA!C40 -> 97395979 | D23: =IF(C23=0,"",C23/C$11) -> 0.30748 | E23: =SGA!E40 -> 100735586 | F23: =IF(E23=0,"",E23/E$11) -> 0.2269494 | G23: =SGA!G40 -> 92289462 | H23: =IF(G23=0,"",G23/G$11) -> 0.21844978 | I23: =SGA!I40 -> 0 | J23: =IF(I23=0,"",I23/I$11) | K23: =SGA!K40 -> 0 | L23: =IF(K23=0,"",K23/K$11)
B24: 営業利益 | C24: =C22- C23 -> 6159294 | D24: =IF(C24=0,"",C24/C$11) -> 0.019444948 | E24: =E22- E23 -> 78190765 | F24: =IF(E24=0,"",E24/E$11) -> 0.17615768 | G24: =G22- G23 -> 58513810 | H24: =IF(G24=0,"",G24/G$11) -> 0.13850258 | I24: =I22- I23 -> 0 | J24: =IF(I24=0,"",I24/I$11) | K24: =K22- K23 -> 0 | L24: =IF(K24=0,"",K24/K$11)
B25: 営業外収益 | C25: =SUM(C26:C32) -> 1358290 | D25: =IF(C25=0,"",C25/C$11) -> 0.004288134 | E25: =SUM(E26:E32) -> 13984344 | F25: =IF(E25=0,"",E25/E$11) -> 0.031505633 | G25: =SUM(G26:G32) -> 8626001 | H25: =IF(G25=0,"",G25/G$11) -> 0.020417802 | I25: =SUM(I26:I32) -> 0 | J25: =IF(I25=0,"",I25/I$11) | K25: =SUM(K26:K32) -> 0 | L25: =IF(K25=0,"",K25/K$11)
B26: 受取利息 | C26: 101059 | D26: =IF(C26=0,"",C26/C$11) -> 0.00031904419 | E26: 1035013 | F26: =IF(E26=0,"",E26/E$11) -> 0.0023318033 | G26: 326339 | H26: =IF(G26=0,"",G26/G$11) -> 0.00077244661 | J26: =IF(I26=0,"",I26/I$11) | L26: =IF(K26=0,"",K26/K$11)
B27: 受取配当金 | C27: 712050 | D27: =IF(C27=0,"",C27/C$11) -> 0.0022479484 | E27: 7151912 | F27: =IF(E27=0,"",E27/E$11) -> 0.016112698 | G27: 7555640 | H27: =IF(G27=0,"",G27/G$11) -> 0.017884251 | J27: =IF(I27=0,"",I27/I$11) | L27: =IF(K27=0,"",K27/K$11)
B28: 貸倒引当金戻入額 | C28: 534000 | D28: =IF(C28=0,"",C28/C$11) -> 0.0016858429 | E28: 803000 | F28: =IF(E28=0,"",E28/E$11) -> 0.0018090962 | G28: 246000 | H28: =IF(G28=0,"",G28/G$11) -> 0.00058228365 | J28: =IF(I28=0,"",I28/I$11) | L28: =IF(K28=0,"",K28/K$11)
B29: 雑収入 | C29: 2197 | D29: =IF(C29=0,"",C29/C$11) -> 6.9359492e-06 | E29: 2195483 | F29: =IF(E29=0,"",E29/E$11) -> 0.0049462515 | G29: 216735 | H29: =IF(G29=0,"",G29/G$11) -> 0.0005130132 | J29: =IF(I29=0,"",I29/I$11) | L29: =IF(K29=0,"",K29/K$11)
B30: 仕入割引 | D30: =IF(C30=0,"",C30/C$11) | F30: =IF(E30=0,"",E30/E$11) | G30: 10455 | H30: =IF(G30=0,"",G30/G$11) -> 2.4747055e-05 | J30: =IF(I30=0,"",I30/I$11) | L30: =IF(K30=0,"",K30/K$11)
B31: 為替差益 | C31: 8984 | D31: =IF(C31=0,"",C31/C$11) -> 2.8362571e-05 | E31: 2798936 | F31: =IF(E31=0,"",E31/E$11) -> 0.0063057839 | G31: 270832 | H31: =IF(G31=0,"",G31/G$11) -> 0.00064106117 | J31: =IF(I31=0,"",I31/I$11) | L31: =IF(K31=0,"",K31/K$11)
D32: =IF(C32=0,"",C32/C$11) | F32: =IF(E32=0,"",E32/E$11) | H32: =IF(G32=0,"",G32/G$11) | J32: =IF(I32=0,"",I32/I$11) | L32: =IF(K32=0,"",K32/K$11)
B33: 営業外費用 | C33: =SUM(C34:C40) -> 852015 | D33: =IF(C33=0,"",C33/C$11) -> 0.0026898192 | E33: =SUM(E34:E40) -> 2246448 | F33: =IF(E33=0,"",E33/E$11) -> 0.0050610716 | G33: =SUM(G34:G40) -> 2196742 | H33: =IF(G33=0,"",G33/G$11) -> 0.0051997031 | I33: =SUM(I34:I40) -> 0 | J33: =IF(I33=0,"",I33/I$11) | K33: =SUM(K34:K40) -> 0 | L33: =IF(K33=0,"",K33/K$11)
B34: 支払利息 | C34: 852015 | D34: =IF(C34=0,"",C34/C$11) -> 0.0026898192 | E34: 1716559 | F34: =IF(E34=0,"",E34/E$11) -> 0.0038672732 | G34: 2196742 | H34: =IF(G34=0,"",G34/G$11) -> 0.0051997031 | J34: =IF(I34=0,"",I34/I$11) | L34: =IF(K34=0,"",K34/K$11)
B35: 雑損失 | D35: =IF(C35=0,"",C35/C$11) | E35: 529889 | F35: =IF(E35=0,"",E35/E$11) -> 0.0011937985 | H35: =IF(G35=0,"",G35/G$11) | J35: =IF(I35=0,"",I35/I$11) | L35: =IF(K35=0,"",K35/K$11)
D36: =IF(C36=0,"",C36/C$11) | F36: =IF(E36=0,"",E36/E$11) | H36: =IF(G36=0,"",G36/G$11) | J36: =IF(I36=0,"",I36/I$11) | L36: =IF(K36=0,"",K36/K$11)
D37: =IF(C37=0,"",C37/C$11) | F37: =IF(E37=0,"",E37/E$11) | H37: =IF(G37=0,"",G37/G$11) | J37: =IF(I37=0,"",I37/I$11) | L37: =IF(K37=0,"",K37/K$11)
D38: =IF(C38=0,"",C38/C$11) | F38: =IF(E38=0,"",E38/E$11) | H38: =IF(G38=0,"",G38/G$11) | J38: =IF(I38=0,"",I38/I$11) | L38: =IF(K38=0,"",K38/K$11)
D39: =IF(C39=0,"",C39/C$11) | F39: =IF(E39=0,"",E39/E$11) | H39: =IF(G39=0,"",G39/G$11) | J39: =IF(I39=0,"",I39/I$11) | L39: =IF(K39=0,"",K39/K$11)
D40: =IF(C40=0,"",C40/C$11) | F40: =IF(E40=0,"",E40/E$11) | H40: =IF(G40=0,"",G40/G$11) | J40: =IF(I40=0,"",I40/I$11) | L40: =IF(K40=0,"",K40/K$11)
B41: 経常利益 | C41: =C24+C25-C33 -> 6665569 | D41: =IF(C41=0,"",C41/C$11) -> 0.021043263 | E41: =E24+E25-E33 -> 89928661 | F41: =IF(E41=0,"",E41/E$11) -> 0.20260224 | G41: =G24+G25-G33 -> 64943069 | H41: =IF(G41=0,"",G41/G$11) -> 0.15372068 | I41: =I24+I25-I33 -> 0 | J41: =IF(I41=0,"",I41/I$11) | K41: =K24+K25-K33 -> 0 | L41: =IF(K41=0,"",K41/K$11)
B42: 特別利益 | C42: =SUM(C43:C48) -> 0 | D42: =IF(C42=0,"",C42/C$11) | E42: =SUM(E43:E48) -> 21984310 | F42: =IF(E42=0,"",E42/E$11) -> 0.049528931 | G42: =SUM(G43:G48) -> 12486495 | H42: =IF(G42=0,"",G42/G$11) -> 0.029555618 | I42: =SUM(I43:I48) -> 0 | J42: =IF(I42=0,"",I42/I$11) | K42: =SUM(K43:K48) -> 0 | L42: =IF(K42=0,"",K42/K$11)
B43: 投資有価証券売却益 | D43: =IF(C43=0,"",C43/C$11) | E43: 21984310 | F43: =IF(E43=0,"",E43/E$11) -> 0.049528931 | G43: 12486495 | H43: =IF(G43=0,"",G43/G$11) -> 0.029555618 | J43: =IF(I43=0,"",I43/I$11) | L43: =IF(K43=0,"",K43/K$11)
D44: =IF(C44=0,"",C44/C$11) | F44: =IF(E44=0,"",E44/E$11) | H44: =IF(G44=0,"",G44/G$11) | J44: =IF(I44=0,"",I44/I$11) | L44: =IF(K44=0,"",K44/K$11)
D45: =IF(C45=0,"",C45/C$11) | F45: =IF(E45=0,"",E45/E$11) | H45: =IF(G45=0,"",G45/G$11) | J45: =IF(I45=0,"",I45/I$11) | L45: =IF(K45=0,"",K45/K$11)
D46: =IF(C46=0,"",C46/C$11) | F46: =IF(E46=0,"",E46/E$11) | H46: =IF(G46=0,"",G46/G$11) | J46: =IF(I46=0,"",I46/I$11) | L46: =IF(K46=0,"",K46/K$11)
D47: =IF(C47=0,"",C47/C$11) | F47: =IF(E47=0,"",E47/E$11) | H47: =IF(G47=0,"",G47/G$11) | J47: =IF(I47=0,"",I47/I$11) | L47: =IF(K47=0,"",K47/K$11)
D48: =IF(C48=0,"",C48/C$11) | F48: =IF(E48=0,"",E48/E$11) | H48: =IF(G48=0,"",G48/G$11) | J48: =IF(I48=0,"",I48/I$11) | L48: =IF(K48=0,"",K48/K$11)
B49: 特別損失 | C49: =SUM(C50:C55) -> 11676176 | D49: =IF(C49=0,"",C49/C$11) -> 0.036861795 | E49: =SUM(E50:E55) -> 50657768 | F49: =IF(E49=0,"",E49/E$11) -> 0.11412799 | G49: =SUM(G50:G55) -> 25990527 | H49: =IF(G49=0,"",G49/G$11) -> 0.061519752 | I49: =SUM(I50:I55) -> 0 | J49: =IF(I49=0,"",I49/I$11) | K49: =SUM(K50:K55) -> 0 | L49: =IF(K49=0,"",K49/K$11)
B50: 投資有価証券売却損 | D50: =IF(C50=0,"",C50/C$11) | E50: 27860505 | F50: =IF(E50=0,"",E50/E$11) -> 0.062767539 | G50: 565843 | H50: =IF(G50=0,"",G50/G$11) -> 0.0013393542 | J50: =IF(I50=0,"",I50/I$11) | L50: =IF(K50=0,"",K50/K$11)
B51: 固定資産除却損 | C51: 2 | D51: =IF(C51=0,"",C51/C$11) -> 6.3140184e-09 | F51: =IF(E51=0,"",E51/E$11) | H51: =IF(G51=0,"",G51/G$11) | J51: =IF(I51=0,"",I51/I$11) | L51: =IF(K51=0,"",K51/K$11)
B52: 棚卸資産廃棄損 | C52: 6722798 | D52: =IF(C52=0,"",C52/C$11) -> 0.021223935 | E52: 17217311 | F52: =IF(E52=0,"",E52/E$11) -> 0.038789255 | G52: 19844732 | H52: =IF(G52=0,"",G52/G$11) -> 0.046972614 | J52: =IF(I52=0,"",I52/I$11) | L52: =IF(K52=0,"",K52/K$11)
B53: 特別保険料 | C53: 4953376 | D53: =IF(C53=0,"",C53/C$11) -> 0.015637854 | E53: 5579952 | F53: =IF(E53=0,"",E53/E$11) -> 0.012571195 | G53: 5579952 | H53: =IF(G53=0,"",G53/G$11) -> 0.013207784 | J53: =IF(I53=0,"",I53/I$11) | L53: =IF(K53=0,"",K53/K$11)
D54: =IF(C54=0,"",C54/C$11) | F54: =IF(E54=0,"",E54/E$11) | H54: =IF(G54=0,"",G54/G$11) | J54: =IF(I54=0,"",I54/I$11) | L54: =IF(K54=0,"",K54/K$11)
D55: =IF(C55=0,"",C55/C$11) | F55: =IF(E55=0,"",E55/E$11) | H55: =IF(G55=0,"",G55/G$11) | J55: =IF(I55=0,"",I55/I$11) | L55: =IF(K55=0,"",K55/K$11)
B56: 税引前当期純利益 | C56: =C41+C42-C49 -> -5010607 | D56: =IF(C56=0,"",C56/C$11) -> -0.015818532 | E56: =E41+E42-E49 -> 61255203 | F56: =IF(E56=0,"",E56/E$11) -> 0.13800318 | G56: =G41+G42-G49 -> 51439037 | H56: =IF(G56=0,"",G56/G$11) -> 0.12175655 | I56: =I41+I42-I49 -> 0 | J56: =IF(I56=0,"",I56/I$11) | K56: =K41+K42-K49 -> 0 | L56: =IF(K56=0,"",K56/K$11)
B57: 法人税等 | C57: =SUM(C58:C60) -> 159573 | D57: =IF(C57=0,"",C57/C$11) -> 0.00050377343 | E57: =SUM(E58:E60) -> 20697447 | F57: =IF(E57=0,"",E57/E$11) -> 0.046629729 | G57: =SUM(G58:G60) -> 13808861 | H57: =IF(G57=0,"",G57/G$11) -> 0.032685667 | I57: =SUM(I58:I60) -> 0 | J57: =IF(I57=0,"",I57/I$11) | K57: =SUM(K58:K60) -> 0 | L57: =IF(K57=0,"",K57/K$11)
B58: 法人税等 | C58: 159573 | D58: =IF(C58=0,"",C58/C$11) -> 0.00050377343 | E58: 20697447 | F58: =IF(E58=0,"",E58/E$11) -> 0.046629729 | G58: 13808861 | H58: =IF(G58=0,"",G58/G$11) -> 0.032685667 | J58: =IF(I58=0,"",I58/I$11) | L58: =IF(K58=0,"",K58/K$11)
D59: =IF(C59=0,"",C59/C$11) | F59: =IF(E59=0,"",E59/E$11) | H59: =IF(G59=0,"",G59/G$11) | J59: =IF(I59=0,"",I59/I$11) | L59: =IF(K59=0,"",K59/K$11)
D60: =IF(C60=0,"",C60/C$11) | F60: =IF(E60=0,"",E60/E$11) | H60: =IF(G60=0,"",G60/G$11) | J60: =IF(I60=0,"",I60/I$11) | L60: =IF(K60=0,"",K60/K$11)
B61: 税引後当期純利益 | C61: =C56-C57 -> -5170180 | D61: =IF(C61=0,"",C61/C$11) -> -0.016322306 | E61: =E56-E57 -> 40557756 | F61: =IF(E61=0,"",E61/E$11) -> 0.091373452 | G61: =G56-G57 -> 37630176 | H61: =IF(G61=0,"",G61/G$11) -> 0.08907088 | I61: =I56-I57 -> 0 | J61: =IF(I61=0,"",I61/I$11) | K61: =K56-K57 -> 0 | L61: =IF(K61=0,"",K61/K$11)
C63: -5170180 | E63: 40557756 | G63: 37630176
C64: =C63=C61 -> TRUE | E64: =E63=E61 -> TRUE | G64: =G63=G61 -> TRUE

Sheet CR
H4: (単位：千円)
B5: 科目 | C5: ='BS(借方)'!C4 -> 24年1月期 | E5: ='BS(借方)'!D4 -> 25年1月期 | G5: ='BS(借方)'!E4 -> 26年1月期 | I5: ='BS(借方)'!F4 -> ●●年●月期 | K5: ='BS(借方)'!G4 -> ●●年●月 （●か月TB）
C6: 帳簿価額 | D6: 売上高比 | E6: 帳簿価額 | F6: 売上高比 | G6: 帳簿価額 | H6: 売上高比 | I6: 帳簿価額 | J6: 売上高比 | K6: 帳簿価額 | L6: 売上高比
A7: IMに貼るときは非表示→ | B7: 売上 | C7: =PL!C11 -> 316755490 | D7: - | E7: =PL!E11 -> 443868051 | F7: - | G7: =PL!G11 -> 422474507 | H7: - | I7: =PL!I11 -> 0 | J7: - | K7: =PL!K11 -> 0 | L7: -
D8: =IF(C8=0,"",C8/C$7) | F8: =IF(E8=0,"",E8/E$7) | H8: =IF(G8=0,"",G8/G$7) | J8: =IF(I8=0,"",I8/I$7) | L8: =IF(K8=0,"",K8/K$7)
D9: =IF(C9=0,"",C9/C$7) | F9: =IF(E9=0,"",E9/E$7) | H9: =IF(G9=0,"",G9/G$7) | J9: =IF(I9=0,"",I9/I$7) | L9: =IF(K9=0,"",K9/K$7)
D10: =IF(C10=0,"",C10/C$7) | F10: =IF(E10=0,"",E10/E$7) | H10: =IF(G10=0,"",G10/G$7) | J10: =IF(I10=0,"",I10/I$7) | L10: =IF(K10=0,"",K10/K$7)
D11: =IF(C11=0,"",C11/C$7) | F11: =IF(E11=0,"",E11/E$7) | H11: =IF(G11=0,"",G11/G$7) | J11: =IF(I11=0,"",I11/I$7) | L11: =IF(K11=0,"",K11/K$7)
D12: =IF(C12=0,"",C12/C$7) | F12: =IF(E12=0,"",E12/E$7) | H12: =IF(G12=0,"",G12/G$7) | J12: =IF(I12=0,"",I12/I$7) | L12: =IF(K12=0,"",K12/K$7)
D13: =IF(C13=0,"",C13/C$7) | F13: =IF(E13=0,"",E13/E$7) | H13: =IF(G13=0,"",G13/G$7) | J13: =IF(I13=0,"",I13/I$7) | L13: =IF(K13=0,"",K13/K$7)
B14: 材料費 | C14: =SUM(C8:C13) -> 0 | D14: =IF(C14=0,"",C14/C$7) | E14: =SUM(E8:E13) -> 0 | F14: =IF(E14=0,"",E14/E$7) | G14: =SUM(G8:G13) -> 0 | H14: =IF(G14=0,"",G14/G$7) | I14: =SUM(I8:I13) -> 0 | J14: =IF(I14=0,"",I14/I$7) | K14: =SUM(K8:K13) -> 0 | L14: =IF(K14=0,"",K14/K$7)
D15: =IF(C15=0,"",C15/C$7) | F15: =IF(E15=0,"",E15/E$7) | H15: =IF(G15=0,"",G15/G$7) | J15: =IF(I15=0,"",I15/I$7) | L15: =IF(K15=0,"",K15/K$7)
D18: =IF(C18=0,"",C18/C$7) | F18: =IF(E18=0,"",E18/E$7) | H18: =IF(G18=0,"",G18/G$7) | J18: =IF(I18=0,"",I18/I$7) | L18: =IF(K18=0,"",K18/K$7)
D19: =IF(C19=0,"",C19/C$7) | F19: =IF(E19=0,"",E19/E$7) | H19: =IF(G19=0,"",G19/G$7) | J19: =IF(I19=0,"",I19/I$7) | L19: =IF(K19=0,"",K19/K$7)
D20: =IF(C20=0,"",C20/C$7) | F20: =IF(E20=0,"",E20/E$7) | H20: =IF(G20=0,"",G20/G$7) | J20: =IF(I20=0,"",I20/I$7) | L20: =IF(K20=0,"",K20/K$7)
D21: =IF(C21=0,"",C21/C$7) | F21: =IF(E21=0,"",E21/E$7) | H21: =IF(G21=0,"",G21/G$7) | J21: =IF(I21=0,"",I21/I$7) | L21: =IF(K21=0,"",K21/K$7)
D22: =IF(C22=0,"",C22/C$7) | F22: =IF(E22=0,"",E22/E$7) | H22: =IF(G22=0,"",G22/G$7) | J22: =IF(I22=0,"",I22/I$7) | L22: =IF(K22=0,"",K22/K$7)
B23: 労務費 | C23: =SUM(C15:C22) -> 0 | D23: =IF(C23=0,"",C23/C$7) | E23: =SUM(E15:E22) -> 0 | F23: =IF(E23=0,"",E23/E$7) | G23: =SUM(G15:G22) -> 0 | H23: =IF(G23=0,"",G23/G$7) | I23: =SUM(I15:I22) -> 0 | J23: =IF(I23=0,"",I23/I$7) | K23: =SUM(K15:K22) -> 0 | L23: =IF(K23=0,"",K23/K$7)
D24: =IF(C24=0,"",C24/C$7) | F24: =IF(E24=0,"",E24/E$7) | H24: =IF(G24=0,"",G24/G$7) | J24: =IF(I24=0,"",I24/I$7) | L24: =IF(K24=0,"",K24/K$7)
D28: =IF(C28=0,"",C28/C$7) | F28: =IF(E28=0,"",E28/E$7) | H28: =IF(G28=0,"",G28/G$7) | J28: =IF(I28=0,"",I28/I$7) | L28: =IF(K28=0,"",K28/K$7)
D29: =IF(C29=0,"",C29/C$7) | F29: =IF(E29=0,"",E29/E$7) | H29: =IF(G29=0,"",G29/G$7) | J29: =IF(I29=0,"",I29/I$7) | L29: =IF(K29=0,"",K29/K$7)
D30: =IF(C30=0,"",C30/C$7) | F30: =IF(E30=0,"",E30/E$7) | H30: =IF(G30=0,"",G30/G$7) | J30: =IF(I30=0,"",I30/I$7) | L30: =IF(K30=0,"",K30/K$7)
D31: =IF(C31=0,"",C31/C$7) | F31: =IF(E31=0,"",E31/E$7) | H31: =IF(G31=0,"",G31/G$7) | J31: =IF(I31=0,"",I31/I$7) | L31: =IF(K31=0,"",K31/K$7)
D32: =IF(C32=0,"",C32/C$7) | F32: =IF(E32=0,"",E32/E$7) | H32: =IF(G32=0,"",G32/G$7) | J32: =IF(I32=0,"",I32/I$7) | L32: =IF(K32=0,"",K32/K$7)
B33: 外注加工費 | C33: =SUM(C24:C32) -> 0 | D33: =IF(C33=0,"",C33/C$7) | E33: =SUM(E24:E32) -> 0 | F33: =IF(E33=0,"",E33/E$7) | G33: =SUM(G24:G32) -> 0 | H33: =IF(G33=0,"",G33/G$7) | I33: =SUM(I24:I32) -> 0 | J33: =IF(I33=0,"",I33/I$7) | K33: =SUM(K24:K32) -> 0 | L33: =IF(K33=0,"",K33/K$7)
D34: =IF(C34=0,"",C34/C$7) | F34: =IF(E34=0,"",E34/E$7) | H34: =IF(G34=0,"",G34/G$7) | J34: =IF(I34=0,"",I34/I$7) | L34: =IF(K34=0,"",K34/K$7)
D35: =IF(C35=0,"",C35/C$7) | F35: =IF(E35=0,"",E35/E$7) | H35: =IF(G35=0,"",G35/G$7) | J35: =IF(I35=0,"",I35/I$7) | L35: =IF(K35=0,"",K35/K$7)
D36: =IF(C36=0,"",C36/C$7) | F36: =IF(E36=0,"",E36/E$7) | H36: =IF(G36=0,"",G36/G$7) | J36: =IF(I36=0,"",I36/I$7) | L36: =IF(K36=0,"",K36/K$7)
D39: =IF(C39=0,"",C39/C$7) | F39: =IF(E39=0,"",E39/E$7) | H39: =IF(G39=0,"",G39/G$7) | J39: =IF(I39=0,"",I39/I$7) | L39: =IF(K39=0,"",K39/K$7)
D40: =IF(C40=0,"",C40/C$7) | F40: =IF(E40=0,"",E40/E$7) | H40: =IF(G40=0,"",G40/G$7) | J40: =IF(I40=0,"",I40/I$7) | L40: =IF(K40=0,"",K40/K$7)
D41: =IF(C41=0,"",C41/C$7) | F41: =IF(E41=0,"",E41/E$7) | H41: =IF(G41=0,"",G41/G$7) | J41: =IF(I41=0,"",I41/I$7) | L41: =IF(K41=0,"",K41/K$7)
D42: =IF(C42=0,"",C42/C$7) | F42: =IF(E42=0,"",E42/E$7) | H42: =IF(G42=0,"",G42/G$7) | J42: =IF(I42=0,"",I42/I$7) | L42: =IF(K42=0,"",K42/K$7)
D43: =IF(C43=0,"",C43/C$7) | F43: =IF(E43=0,"",E43/E$7) | H43: =IF(G43=0,"",G43/G$7) | J43: =IF(I43=0,"",I43/I$7) | L43: =IF(K43=0,"",K43/K$7)
D44: =IF(C44=0,"",C44/C$7) | F44: =IF(E44=0,"",E44/E$7) | H44: =IF(G44=0,"",G44/G$7) | J44: =IF(I44=0,"",I44/I$7) | L44: =IF(K44=0,"",K44/K$7)
D45: =IF(C45=0,"",C45/C$7) | F45: =IF(E45=0,"",E45/E$7) | H45: =IF(G45=0,"",G45/G$7) | J45: =IF(I45=0,"",I45/I$7) | L45: =IF(K45=0,"",K45/K$7)
B46: 経費 | C46: =SUM(C34:C45) -> 0 | D46: =IF(C46=0,"",C46/C$7) | E46: =SUM(E34:E45) -> 0 | F46: =IF(E46=0,"",E46/E$7) | G46: =SUM(G34:G45) -> 0 | H46: =IF(G46=0,"",G46/G$7) | I46: =SUM(I34:I45) -> 0 | J46: =IF(I46=0,"",I46/I$7) | K46: =SUM(K34:K45) -> 0 | L46: =IF(K46=0,"",K46/K$7)
B47: 当期製造費用 | C47: =C14+C23+C33+C46 -> 0 | D47: =IF(C47=0,"",C47/C$7) | E47: =E14+E23+E33+E46 -> 0 | F47: =IF(E47=0,"",E47/E$7) | G47: =G14+G23+G33+G46 -> 0 | H47: =IF(G47=0,"",G47/G$7) | I47: =I14+I23+I33+I46 -> 0 | J47: =IF(I47=0,"",I47/I$7) | K47: =K14+K23+K33+K46 -> 0 | L47: =IF(K47=0,"",K47/K$7)
B48: 期首仕掛品棚卸高 | D48: =IF(C48=0,"",C48/C$7) | E48: =SUM(E36:E47) -> 0 | F48: =IF(E48=0,"",E48/E$7) | G48: =SUM(G36:G47) -> 0 | H48: =IF(G48=0,"",G48/G$7) | I48: =SUM(I36:I47) -> 0 | J48: =IF(I48=0,"",I48/I$7) | K48: =SUM(K36:K47) -> 0 | L48: =IF(K48=0,"",K48/K$7)
B49: 合計 | C49: =SUM(C47:C48) -> 0 | D49: =IF(C49=0,"",C49/C$7) | E49: =SUM(E47:E48) -> 0 | F49: =IF(E49=0,"",E49/E$7) | G49: =SUM(G47:G48) -> 0 | H49: =IF(G49=0,"",G49/G$7) | I49: =SUM(I47:I48) -> 0 | J49: =IF(I49=0,"",I49/I$7) | K49: =SUM(K47:K48) -> 0 | L49: =IF(K49=0,"",K49/K$7)
B50: 期末仕掛品棚卸高 | D50: =IF(C50=0,"",C50/C$7) | E50: =SUM(E40:E49) -> 0 | F50: =IF(E50=0,"",E50/E$7) | G50: =SUM(G40:G49) -> 0 | H50: =IF(G50=0,"",G50/G$7) | I50: =SUM(I40:I49) -> 0 | J50: =IF(I50=0,"",I50/I$7) | K50: =SUM(K40:K49) -> 0 | L50: =IF(K50=0,"",K50/K$7)
B51: 当期製造原価 | C51: =C49-C50 -> 0 | D51: =IF(C51=0,"",C51/C$7) | E51: =E49-E50 -> 0 | F51: =IF(E51=0,"",E51/E$7) | G51: =G49-G50 -> 0 | H51: =IF(G51=0,"",G51/G$7) | I51: =I49-I50 -> 0 | J51: =IF(I51=0,"",I51/I$7) | K51: =K49-K50 -> 0 | L51: =IF(K51=0,"",K51/K$7)

Sheet SGA
H2: (単位：千円)
B3: 科目 | C3: ='BS(借方)'!C4 -> 24年1月期 | E3: ='BS(借方)'!D4 -> 25年1月期 | G3: ='BS(借方)'!E4 -> 26年1月期 | I3: ='BS(借方)'!F4 -> ●●年●月期 | K3: ='BS(借方)'!G4 -> ●●年●月 （●か月TB）
C4: 帳簿価額 | D4: 売上高比 | E4: 帳簿価額 | F4: 売上高比 | G4: 帳簿価額 | H4: 売上高比 | I4: 帳簿価額 | J4: 売上高比 | K4: 帳簿価額 | L4: 売上高比
B5: 売上 | C5: =PL!C11 -> 316755490 | D5: - | E5: =PL!E11 -> 443868051 | F5: - | G5: =PL!G11 -> 422474507 | H5: - | I5: =PL!I11 -> 0 | J5: - | K5: =PL!K11 -> 0 | L5: - | M5: ←IMに貼るときは非表示
B6: 役員報酬 | C6: 1104000 | D6: =IFERROR(C6/$C$5,"") -> 0.0034853382 | E6: 1104000 | F6: =IFERROR(E6/$E$5,"") -> 0.0024872256 | G6: 4094000 | H6: =IFERROR(G6/$G$5,"") -> 0.0096905255 | J6: =IFERROR(I6/$I$5,"") | L6: =IFERROR(K6/$K$5,"")
B7: 役員賞与 | C7: 18000000 | D7: =IFERROR(C7/$C$5,"") -> 0.056826166 | E7: 20000000 | F7: =IFERROR(E7/$E$5,"") -> 0.045058436 | G7: 20000000 | H7: =IFERROR(G7/$G$5,"") -> 0.047340135 | J7: =IFERROR(I7/$I$5,"") | L7: =IFERROR(K7/$K$5,"")
B8: 給料手当 | C8: 33649484 | D8: =IFERROR(C8/$C$5,"") -> 0.10623173 | E8: 29811105 | F8: =IFERROR(E8/$E$5,"") -> 0.067162088 | G8: 27938525 | H8: =IFERROR(G8/$G$5,"") -> 0.066130677 | J8: =IFERROR(I8/$I$5,"") | L8: =IFERROR(K8/$K$5,"")
B9: 雑給 | C9: 2538750 | D9: =IFERROR(C9/$C$5,"") -> 0.0080148571 | E9: 6544740 | F9: =IFERROR(E9/$E$5,"") -> 0.014744787 | G9: 299000 | H9: =IFERROR(G9/$G$5,"") -> 0.00070773501 | J9: =IFERROR(I9/$I$5,"") | L9: =IFERROR(K9/$K$5,"")
B10: 賞与 | C10: 4064600 | D10: =IFERROR(C10/$C$5,"") -> 0.01283198 | F10: =IFERROR(E10/$E$5,"") -> 0 | G10: 6079177 | H10: =IFERROR(G10/$G$5,"") -> 0.014389453 | J10: =IFERROR(I10/$I$5,"") | L10: =IFERROR(K10/$K$5,"")
B11: 法定福利費 | C11: 6407318 | D11: =IFERROR(C11/$C$5,"") -> 0.020227962 | E11: 6394777 | F11: =IFERROR(E11/$E$5,"") -> 0.014406932 | G11: 6366731 | H11: =IFERROR(G11/$G$5,"") -> 0.015070095 | J11: =IFERROR(I11/$I$5,"") | L11: =IFERROR(K11/$K$5,"")
B12: 福利厚生費 | C12: 1932474 | D12: =IFERROR(C12/$C$5,"") -> 0.0061008382 | E12: 422087 | F12: =IFERROR(E12/$E$5,"") -> 0.000950929 | G12: 705804 | H12: =IFERROR(G12/$G$5,"") -> 0.0016706428 | J12: =IFERROR(I12/$I$5,"") | L12: =IFERROR(K12/$K$5,"")
B13: 採用教育費 | C13: 280000 | D13: =IFERROR(C13/$C$5,"") -> 0.00088396258 | E13: 1480000 | F13: =IFERROR(E13/$E$5,"") -> 0.0033343242 | H13: =IFERROR(G13/$G$5,"") -> 0 | J13: =IFERROR(I13/$I$5,"") | L13: =IFERROR(K13/$K$5,"")
B14: 荷造運賃 | C14: 9235586 | D14: =IFERROR(C14/$C$5,"") -> 0.02915683 | E14: 13487346 | F14: =IFERROR(E14/$E$5,"") -> 0.030385936 | G14: 7104880 | H14: =IFERROR(G14/$G$5,"") -> 0.016817299 | J14: =IFERROR(I14/$I$5,"") | L14: =IFERROR(K14/$K$5,"")
B15: 広告宣伝費 | C15: 152187 | D15: =IFERROR(C15/$C$5,"") -> 0.00048045576 | E15: 142619 | F15: =IFERROR(E15/$E$5,"") -> 0.00032130945 | G15: 841073 | H15: =IFERROR(G15/$G$5,"") -> 0.0019908254 | J15: =IFERROR(I15/$I$5,"") | L15: =IFERROR(K15/$K$5,"")
B16: 接待交際費 | C16: 1440144 | D16: =IFERROR(C16/$C$5,"") -> 0.0045465479 | E16: 1738203 | F16: =IFERROR(E16/$E$5,"") -> 0.0039160354 | G16: 2336230 | H16: =IFERROR(G16/$G$5,"") -> 0.0055298721 | J16: =IFERROR(I16/$I$5,"") | L16: =IFERROR(K16/$K$5,"")
B17: 会議費 | C17: 211518 | D17: =IFERROR(C17/$C$5,"") -> 0.00066776427 | E17: 214892 | F17: =IFERROR(E17/$E$5,"") -> 0.00048413487 | G17: 284369 | H17: =IFERROR(G17/$G$5,"") -> 0.00067310334 | J17: =IFERROR(I17/$I$5,"") | L17: =IFERROR(K17/$K$5,"")
B18: 旅費交通費 | C18: 645511 | D18: =IFERROR(C18/$C$5,"") -> 0.0020378842 | E18: 2129949 | F18: =IFERROR(E18/$E$5,"") -> 0.0047986085 | G18: 1018914 | H18: =IFERROR(G18/$G$5,"") -> 0.0024117763 | J18: =IFERROR(I18/$I$5,"") | L18: =IFERROR(K18/$K$5,"")
B19: 通信費 | C19: 1416425 | D19: =IFERROR(C19/$C$5,"") -> 0.0044716668 | E19: 1506325 | F19: =IFERROR(E19/$E$5,"") -> 0.0033936324 | G19: 1506831 | H19: =IFERROR(G19/$G$5,"") -> 0.0035666791 | J19: =IFERROR(I19/$I$5,"") | L19: =IFERROR(K19/$K$5,"")
B20: 販売促進費 | C20: 65128 | D20: =IFERROR(C20/$C$5,"") -> 0.0002056097 | F20: =IFERROR(E20/$E$5,"") -> 0 | H20: =IFERROR(G20/$G$5,"") -> 0 | J20: =IFERROR(I20/$I$5,"") | L20: =IFERROR(K20/$K$5,"")
B21: 事務用消耗品費 | C21: 1145535 | D21: =IFERROR(C21/$C$5,"") -> 0.0036164645 | E21: 1700793 | F21: =IFERROR(E21/$E$5,"") -> 0.0038317536 | G21: 1195194 | H21: =IFERROR(G21/$G$5,"") -> 0.0028290322 | J21: =IFERROR(I21/$I$5,"") | L21: =IFERROR(K21/$K$5,"")
B22: 修繕費 | C22: 44900 | D22: =IFERROR(C22/$C$5,"") -> 0.00014174971 | E22: 190064 | F22: =IFERROR(E22/$E$5,"") -> 0.00042819933 | H22: =IFERROR(G22/$G$5,"") -> 0 | J22: =IFERROR(I22/$I$5,"") | L22: =IFERROR(K22/$K$5,"")
B23: 水道光熱費 | C23: 394299 | D23: =IFERROR(C23/$C$5,"") -> 0.0012448056 | E23: 403021 | F23: =IFERROR(E23/$E$5,"") -> 0.00090797479 | G23: 412583 | H23: =IFERROR(G23/$G$5,"") -> 0.00097658674 | J23: =IFERROR(I23/$I$5,"") | L23: =IFERROR(K23/$K$5,"")
B24: 諸会費 | C24: 57450 | D24: =IFERROR(C24/$C$5,"") -> 0.00018137018 | E24: 36000 | F24: =IFERROR(E24/$E$5,"") -> 8.1105184e-05 | G24: 48000 | H24: =IFERROR(G24/$G$5,"") -> 0.00011361632 | J24: =IFERROR(I24/$I$5,"") | L24: =IFERROR(K24/$K$5,"")
B25: 支払手数料 | C25: 3167934 | D25: =IFERROR(C25/$C$5,"") -> 0.010001197 | E25: 3674031 | F25: =IFERROR(E25/$E$5,"") -> 0.0082773045 | G25: 1179313 | H25: =IFERROR(G25/$G$5,"") -> 0.0027914418 | J25: =IFERROR(I25/$I$5,"") | L25: =IFERROR(K25/$K$5,"")
B26: 車両費 | C26: 650214 | D26: =IFERROR(C26/$C$5,"") -> 0.0020527316 | E26: 478916 | F26: =IFERROR(E26/$E$5,"") -> 0.0010789603 | G26: 716759 | H26: =IFERROR(G26/$G$5,"") -> 0.0016965734 | J26: =IFERROR(I26/$I$5,"") | L26: =IFERROR(K26/$K$5,"")
B27: 地代家賃 | C27: 5430000 | D27: =IFERROR(C27/$C$5,"") -> 0.01714256 | E27: 5430000 | F27: =IFERROR(E27/$E$5,"") -> 0.012233365 | G27: 5500911 | H27: =IFERROR(G27/$G$5,"") -> 0.013020693 | J27: =IFERROR(I27/$I$5,"") | L27: =IFERROR(K27/$K$5,"")
B28: リース料 | C28: 131200 | D28: =IFERROR(C28/$C$5,"") -> 0.00041419961 | E28: 160920 | F28: =IFERROR(E28/$E$5,"") -> 0.00036254017 | G28: 147510 | H28: =IFERROR(G28/$G$5,"") -> 0.00034915716 | J28: =IFERROR(I28/$I$5,"") | L28: =IFERROR(K28/$K$5,"")
B29: 保険料 | C29: 709690 | D29: =IFERROR(C29/$C$5,"") -> 0.0022404979 | E29: 1090090 | F29: =IFERROR(E29/$E$5,"") -> 0.0024558875 | G29: 735330 | H29: =IFERROR(G29/$G$5,"") -> 0.0017405311 | J29: =IFERROR(I29/$I$5,"") | L29: =IFERROR(K29/$K$5,"")
B30: 租税公課 | C30: 234840 | D30: =IFERROR(C30/$C$5,"") -> 0.00074139204 | E30: 175360 | F30: =IFERROR(E30/$E$5,"") -> 0.00039507236 | G30: 269084 | H30: =IFERROR(G30/$G$5,"") -> 0.00063692364 | J30: =IFERROR(I30/$I$5,"") | L30: =IFERROR(K30/$K$5,"")
B31: 支払報酬料 | C31: 755000 | D31: =IFERROR(C31/$C$5,"") -> 0.002383542 | E31: 755000 | F31: =IFERROR(E31/$E$5,"") -> 0.0017009559 | G31: 762000 | H31: =IFERROR(G31/$G$5,"") -> 0.0018036591 | J31: =IFERROR(I31/$I$5,"") | L31: =IFERROR(K31/$K$5,"")
B32: 寄付金 | C32: 50000 | D32: =IFERROR(C32/$C$5,"") -> 0.00015785046 | E32: 200000 | F32: =IFERROR(E32/$E$5,"") -> 0.00045058436 | G32: 50000 | H32: =IFERROR(G32/$G$5,"") -> 0.00011835034 | J32: =IFERROR(I32/$I$5,"") | L32: =IFERROR(K32/$K$5,"")
B33: 研究開発費 | C33: 174503 | D33: =IFERROR(C33/$C$5,"") -> 0.00055090758 | E33: 574824 | F33: =IFERROR(E33/$E$5,"") -> 0.0012950335 | G33: 170367 | H33: =IFERROR(G33/$G$5,"") -> 0.00040325984 | J33: =IFERROR(I33/$I$5,"") | L33: =IFERROR(K33/$K$5,"")
B34: 減価償却費 | C34: 881300 | D34: =IFERROR(C34/$C$5,"") -> 0.0027822722 | E34: 644524 | F34: =IFERROR(E34/$E$5,"") -> 0.0014520622 | G34: 1182673 | H34: =IFERROR(G34/$G$5,"") -> 0.0027993949 | J34: =IFERROR(I34/$I$5,"") | L34: =IFERROR(K34/$K$5,"")
B35: 貸倒引当金繰入額 | C35: 803000 | D35: =IFERROR(C35/$C$5,"") -> 0.0025350784 | E35: 246000 | F35: =IFERROR(E35/$E$5,"") -> 0.00055421876 | G35: 201000 | H35: =IFERROR(G35/$G$5,"") -> 0.00047576835 | J35: =IFERROR(I35/$I$5,"") | L35: =IFERROR(K35/$K$5,"")
B36: 通勤 | C36: 1622989 | D36: =IFERROR(C36/$C$5,"") -> 0.0051237912 | F36: =IFERROR(E36/$E$5,"") -> 0 | G36: 1143204 | H36: =IFERROR(G36/$G$5,"") -> 0.0027059716 | J36: =IFERROR(I36/$I$5,"") | L36: =IFERROR(K36/$K$5,"")
D37: =IFERROR(C37/$C$5,"") -> 0 | F37: =IFERROR(E37/$E$5,"") -> 0 | H37: =IFERROR(G37/$G$5,"") -> 0 | J37: =IFERROR(I37/$I$5,"") | L37: =IFERROR(K37/$K$5,"")
D38: =IFERROR(C38/$C$5,"") -> 0 | F38: =IFERROR(E38/$E$5,"") -> 0 | H38: =IFERROR(G38/$G$5,"") -> 0 | J38: =IFERROR(I38/$I$5,"") | L38: =IFERROR(K38/$K$5,"")
D39: =IFERROR(C39/$C$5,"") -> 0 | F39: =IFERROR(E39/$E$5,"") -> 0 | H39: =IFERROR(G39/$G$5,"") -> 0 | J39: =IFERROR(I39/$I$5,"") | L39: =IFERROR(K39/$K$5,"")
B40: 販売費および一般管理費合計 | C40: =SUM(C6:C39) -> 97395979 | D40: =IFERROR(C40/C5,"") -> 0.30748 | E40: =SUM(E6:E39) -> 100735586 | F40: =IFERROR(E40/E5,"") -> 0.2269494 | G40: =SUM(G6:G39) -> 92289462 | H40: =IFERROR(G40/G5,"") -> 0.21844978 | I40: =SUM(I6:I39) -> 0 | J40: =IFERROR(I40/I5,"") | K40: =SUM(K6:K39) -> 0 | L40: =IFERROR(K40/K5,"")

Sheet VR→ 

Sheet 株式価値 
A1: 作業不要（自動作成）
F2: (単位：千円)
C3: min | D3: 差（グラフ作成用） | E3: max
B4: インカム | C4: 0 | D4: 0 | E4: 0 | F4: 100 | I4: ｚ
B5: マーケット | C5: ='EV EBITDAマルチプル'!K7 -> 1.1220229e+08 | D5: =E5-C5 -> 71189199 | E5: ='EV EBITDAマルチプル'!M7 -> 1.8339149e+08 | F5: 0
B6: コスト | C6: =年買法!K6 -> 33185615 | D6: =E6-C6 -> 51013674 | E6: =年買法!M6 -> 84199289 | F6: 0

Sheet 売掛・棚卸
E2: (単位：千円)
A3: 売掛金 | B3: 相手先 | C3: 帳簿価額 | D3: 評価差額 | E3: 評価額 | F3: 調整事由
B4: （相手先別内訳 未受領） | C4: 20153150 | D4: 0 | F4: 売掛金年齢表・補助残高一覧表が未受領のため個別の回収可能性判断は未実施。帳簿価額により評価する（要確認）。なお貸倒引当金201千円は全額戻入。
B8: 合計 | C8: =SUM(C4:C7) -> 20153150 | D8: =SUM(D4:D7) -> 0 | E8: =C8+D8 -> 20153150
E12: (単位：千円)
A13: 商品在庫 | B13: 相手先 | C13: 帳簿価額 | D13: 評価差額 | E13: 評価額 | F13: 調整事由
B14: 商品 | C14: 204834 | D14: 0 | F14: 令和8年1月期末残高は205千円と僅少。棚卸資産廃棄損が3期連続で計上されており期末在庫は整理済と判断し、帳簿価額により評価する。
B15: 証紙 | C15: 24020 | D15: 0 | F15: 僅少につき帳簿価額により評価する。
B18: 合計 | C18: =SUM(C14:C17) -> 228854 | D18: =SUM(D14:D17) -> 0 | E18: =C18+D18 -> 228854

Sheet 減価償却
E2: (単位：千円)
B3: 資産 | C3: 帳簿価額 | D3: 評価差額 | E3: 評価額 | F3: 調整事由
B4: 建物附属設備 | C4: 700993 | D4: 0 | E4: =SUM(C4,D4) -> 700993 | F4: 減価償却台帳（令和8年1月期）が画像PDFのため個別資産の償却過不足の検証は未実施。有形固定資産・無形固定資産の残高は合計3,169千円と僅少であり、帳簿価額により評価する（要確認）。
B5: 車両運搬具 | C5: 264868 | D5: 0 | E5: =SUM(C5,D5) -> 264868
B6: 工具器具備品 | C6: 91059 | D6: 0 | E6: =SUM(C6,D6) -> 91059
B7: ソフトウェア | C7: 2112001 | D7: 0 | E7: =SUM(C7,D7) -> 2112001
B8: 合計 | C8: =SUM(C4:C7) -> 3168921 | D8: =SUM(D4:D7) -> 0 | E8: =C8+D8 -> 3168921

Sheet 土地
F2: (単位：千円)
B3: 内容・所在地 | C3: 地積(㎡) | D3: 帳簿価額 | E3: 評価差額 | F3: 時価評価額 | G3: 調整事由
B4: 該当なし | G4: 対象会社は土地・建物等の不動産を保有していない（令和8年1月期BSに計上なし、本社は賃借）。したがって不動産の時価評価は実施していない。
B8: 合計 | C8: =SUM(C4:C7) -> 0 | D8: =SUM(D4:D7) -> 0 | E8: =SUM(E4:E7) -> 0 | F8: =SUM(F4:F7) -> 0

Sheet 保険
E2: (単位：千円)
B3: 保険商品 | C3: 帳簿価額 | D3: 評価差額 | E3: 評価額 | F3: 調整事由
B4: 保険積立金（保険会社・商品名 未確認） | C4: 43326766 | D4: =E4-C4 -> 0 | E4: 43326766 | F4: 解約返戻金額の資料が未受領のため帳簿価額により評価する。解約返戻金額の判明後、時価へ更新予定（要確認）。3期連続で特別保険料を計上しており、簿外の返戻金相当額が存在する可能性がある。
B8: 合計 | C8: =SUM(C4:C7) -> 43326766 | D8: =SUM(D4:D7) -> 0 | E8: =C8+D8 -> 43326766

Sheet 有価証券
F2: (単位：千円)
B3: 銘柄 | C3: 数量 | D3: 帳簿価額 | E3: 評価差額 | F3: 評価額 | G3: 調整事由
B4: 投資有価証券（銘柄別内訳 未受領） | C4: - | D4: 275896334 | E4: =F4-D4 -> 0 | F4: 275896334 | G4: 有価証券内訳明細書・証券会社残高証明書が未受領のため帳簿価額により評価する。評価実施日の時価判明後に更新予定（要確認）。総資産の約50%を占める重要科目。
E7: =F7-D7 -> 0
E8: =F8-D8 -> 0
B9: 合計 | C9: - | D9: =SUM(D4:D8) -> 275896334 | E9: =SUM(E4:E8) -> 0 | F9: =D9+E9 -> 275896334

Sheet 未払人件費・賞与
D2: (単位：千円) | E2: (単位：千円) | F2: (単位：千円)
B3: 給与（令和8年1月期） | C3: 未払日数 | D3: 未払給与引当額 | E3: 概算社会保険料 | F3: 未払給与引当額
C4: － | D4: =B4*11/31 -> 0 | E4: =D4*0.15 -> 0 | F4: =D4+E4 -> 0
B6: 就業規則・賃金規程（給与の締日・支払日）が未受領のため、未払給与の引当不足額は算定不能。要確認事項として整理し、本評価では未計上とする。
E7: (単位：千円)
B8: 賞与（令和8年1月期） | C8: 支給対象月数 | D8: 経過月数 | E8: 引当額 | F8: 概算社会保険料 | G8: 社保考慮後引当不足
C9: － | D9: － | E9: =B9*4/6 -> 0 | F9: =E9*0.15 -> 0 | G9: =E9+F9 -> 0
B11: 決算期末（1月31日）時点で夏季賞与の支給対象期間は経過しておらず、冬季賞与は令和7年12月に支給済（給与台帳により確認）。したがって賞与引当不足は生じないものと判断し、追加引当は行わない。

Sheet 退職金
J2: (単位：千円)
B3: № | C3: 氏名 | D3: 勤続年数(年) | E3: 基本給 | F3: 支給倍率 | G3: 退職理由率 | H3: 要支給額 | I3: 中退共積立額 | J3: 引当不足
C10: 合計 | H10: =SUM(H6:H9) -> 0 | I10: =SUM(I6:I9) -> 0 | J10: =H10+I10 -> 0
C12: 退職金規程が未受領であり、中小企業退職金共済等の外部積立の有無も未確認のため、退職給付引当不足額は算定不能。要確認事項として整理し、本評価では未計上とする（従業員7名・平均勤続年数約5年）。

Sheet 税効果
E2: (単位：千円)
B3: 修正科目 | C3: 適用判定 | D3: 修正額 | E3: 繰延税金資産/負債 | F3: 備考
B4: 貸倒引当金 | C4: 〇 | D4: 201000 | E4: =-D4*0.34 -> -68340
B5: 棚卸資産 | C5: 〇 | E5: =-D5*0.34 -> 0 | F5: 評価差額なし
B6: 減価償却資産 | C6: 〇 | E6: =-D6*0.34 -> 0 | F6: 償却過不足未検証のため未評価（要確認）
B7: 投資有価証券 | C7: 〇 | E7: - | F7: 時価資料未受領のため簿価評価（要確認）
B8: 保険積立金 | C8: 〇 | E8: - | F8: 解約返戻金資料未受領のため簿価評価（要確認）
B9: 差入保証金・敷金 | C9: 〇 | E9: =-D9*0.34 -> 0 | F9: 賃貸借契約書の返還条件未確認のため簿価評価（要確認）
B10: 未払給与 | C10: 〇 | E10: =-D10*0.34 -> 0 | F10: 賃金規程未受領のため未計上（要確認）
B11: 賞与引当金 | C11: 〇 | E11: =-D11*0.34 -> 0 | F11: 期末時点で引当不足なし
B12: 退職給付引当金 | C12: 〇 | E12: =-D12*0.34 -> 0 | F12: 退職金規程未受領のため未計上（要確認）
E13: =-D13*0.34 -> 0
E14: =-D14*0.34 -> 0
E15: =-D15*0.34 -> 0
E16: =-D16*0.34 -> 0
E17: =-D17*0.34 -> 0
B18: 合計 | C18: - | D18: =SUM(D4:D17) -> 201000 | E18: =SUM(E4:E17) -> -68340 | F18: 修正額は貸倒引当金の戻入201千円のみであり重要性が乏しいことから、修正貸借対照表上は繰延税金資産／負債を認識せず、「年買法」シートの時価純資産算定において実効税率34%で一括して考慮している。

Sheet ネットキャッシュ
F2: (単位：千円)
B3: キャッシュライクアイテム | C3: 金額 | E3: デットライクアイテム | F3: 金額
B4: 現金及び預金 | C4: ='修正BS(借方)'!E6 -> 193226490 | E4: 一年以内返済長期借入金 | F4: ='修正BS(貸方) '!E11 -> 41828000
B5: 投資有価証券 | C5: ='修正BS(借方)'!E47 -> 0 | E5: 長期借入金 | F5: ='修正BS(貸方) '!E19 -> 145980000
B6: 保険積立金 | C6: ='修正BS(借方)'!E52 -> 0
B13: 合計 | C13: =SUM(C4:C12) -> 193226490 | E13: 合計 | F13: =SUM(F4:F12) -> 187808000
B15: ネットキャッシュ | C15: =C13-F13 -> 5418490

Sheet 修正BS(借方)
E2: (単位：千円)
B3: 資産の部
B4: 科目 | C4: ='BS(借方)'!E4 -> 26年1月期 | D4: 修正額 | E4: 修正後
B5: 【流動資産】 | C5: =SUM(C6:C19) -> 226144406 | D5: =SUM(D6:D19) -> -6369163 | E5: =C5+D5 -> 219775243
B6: 現金及び預金 | C6: 193226490 | E6: =C6+D6 -> 193226490
B7: 売掛金 | C7: 20153150 | E7: =C7+D7 -> 20153150
B8: 貸倒引当金 | C8: -201000 | D8: 201000 | E8: =C8+D8 -> 0
B9: 商品 | C9: 204834 | E9: =C9+D9 -> 204834
B10: 証紙 | C10: 24020 | E10: =C10+D10 -> 24020
B11: 前渡金 | C11: 12055237 | D11: -6570163 | E11: =C11+D11 -> 5485074
B12: 前払費用 | C12: 640475 | E12: =C12+D12 -> 640475
B13: 未収入金 | C13: 41200 | E13: =C13+D13 -> 41200
E14: =C14+D14 -> 0
E15: =C15+D15 -> 0
E16: =C16+D16 -> 0
E17: =C17+D17 -> 0
E18: =C18+D18 -> 0
E19: =C19+D19 -> 0
B20: 【固定資産】 | C20: =C21+C35+C46 -> 323863136 | D20: =D21+D35+D46 -> -319487968 | E20: =C20+D20 -> 4375168
B21: ［有形固定資産］ | C21: =SUM(C22:C34) -> 1056920 | D21: =SUM(D22:D34) -> -264868 | E21: =C21+D21 -> 792052
B22: 建物附属設備 | C22: 700993 | E22: =C22+D22 -> 700993
B23: 車両運搬具 | C23: 264868 | D23: =-C23 -> -264868 | E23: =C23+D23 -> 0
B24: 工具器具備品 | C24: 91059 | E24: =C24+D24 -> 91059
E25: =C25+D25 -> 0
E26: =C26+D26 -> 0
E27: =C27+D27 -> 0
E28: =C28+D28 -> 0
E29: =C29+D29 -> 0
E30: =C30+D30 -> 0
E31: =C31+D31 -> 0
E32: =C32+D32 -> 0
E33: =C33+D33 -> 0
E34: =C34+D34 -> 0
B35: ［無形固定資産］ | C35: =SUM(C36:C45) -> 2112001 | D35: =SUM(D36:D45) -> 0 | E35: =C35+D35 -> 2112001
B36: ソフトウェア | C36: 2112001 | E36: =C36+D36 -> 2112001
E37: =C37+D37 -> 0
E38: =C38+D38 -> 0
E39: =C39+D39 -> 0
E40: =C40+D40 -> 0
E41: =C41+D41 -> 0
E42: =C42+D42 -> 0
E43: =C43+D43 -> 0
E44: =C44+D44 -> 0
E45: =C45+D45 -> 0
B46: ［投資その他資産］ | C46: =SUM(C47:C54) -> 320694215 | D46: =SUM(D47:D54) -> -319223100 | E46: =C46+D46 -> 1471115
B47: 投資有価証券 | C47: 275896334 | D47: =-C47 -> -275896334 | E47: =C47+D47 -> 0
B48: 出資金 | C48: 30000 | E48: =C48+D48 -> 30000
B49: 敷金 | C49: 50000 | E49: =C49+D49 -> 50000
B50: 差入保証金 | C50: 1263500 | E50: =C50+D50 -> 1263500
B51: 預託金 | C51: 25040 | E51: =C51+D51 -> 25040
B52: 保険積立金 | C52: 43326766 | D52: =-C52 -> -43326766 | E52: =C52+D52 -> 0
B53: 長期前払費用 | C53: 102575 | E53: =C53+D53 -> 102575
E54: =C54+D54 -> 0
B55: 【繰延資産】 | C55: =SUM(C56:C59) -> 0 | D55: =SUM(D56:D59) -> 0 | E55: =C55+D55 -> 0
E56: =C56+D56 -> 0
E57: =C57+D57 -> 0
E58: =C58+D58 -> 0
E59: =C59+D59 -> 0
B60: 【繰延税金資産】 | C60: 0 | D60: 0 | E60: =C60+D60 -> 0
B61: 資産合計 | C61: =C5+C20+C55+C60 -> 550007542 | D61: =D5+D20+D55+D60 -> -325857131 | E61: =C61+D61 -> 224150411

Sheet 修正BS(貸方) 
E2: (単位：千円)
B3: 負債の部
B4: 科目 | C4: ='BS (貸方)'!E4 -> 26年1月期 | D4: 修正額 | E4: 修正後
B5: 【流動負債】 | C5: =SUM(C6:C17) -> 70491633 | D5: =SUM(D6:D17) -> 0 | E5: =C5+D5 -> 70491633
B6: 買掛金 | C6: 9644516 | E6: =C6+D6 -> 9644516
B7: 未払金 | C7: 3947278 | E7: =C7+D7 -> 3947278
B8: 未払法人税等 | C8: 2929500 | E8: =C8+D8 -> 2929500
B9: 未払消費税等 | C9: 12017600 | E9: =C9+D9 -> 12017600
B10: 預り金 | C10: 124739 | E10: =C10+D10 -> 124739
B11: 一年以内返済長期借入金 | C11: 41828000 | E11: =C11+D11 -> 41828000
E12: =C12+D12 -> 0
E13: =C13+D13 -> 0
E14: =C14+D14 -> 0
E15: =C15+D15 -> 0
E16: =C16+D16 -> 0
E17: =C17+D17 -> 0
B18: 【固定負債】 | C18: =SUM(C19:C26) -> 145980000 | D18: =SUM(D19:D26) -> 0 | E18: =C18+D18 -> 145980000
B19: 長期借入金 | C19: 145980000 | E19: =C19+D19 -> 145980000
E20: =C20+D20 -> 0
E21: =C21+D21 -> 0
E22: =C22+D22 -> 0
E23: =C23+D23 -> 0
E24: =C24+D24 -> 0
E25: =C25+D25 -> 0
E26: =C26+D26 -> 0
B27: 【繰延税金負債】 | C27: 0 | D27: 0 | E27: =C27+D27 -> 0
B28: 負債合計 | C28: =C5+C18+C27 -> 216471633 | D28: =D5+D18+D27 -> 0 | E28: =C28+D28 -> 216471633
B34: 純資産の部
B35: 【資本金】 | C35: =SUM(C36:C38) -> 10000000 | D35: =SUM(D36:D38) -> 0 | E35: =C35+D35 -> 10000000
B36: 資本金 | C36: 10000000 | E36: =C36+D36 -> 10000000
E37: =C37+D37 -> 0
E38: =C38+D38 -> 0
B39: 【資本剰余金】 | C39: =SUM(C40:C42) -> 0 | D39: =SUM(D40:D42) -> 0 | E39: =C39+D39 -> 0
E40: =C40+D40 -> 0
E41: =C41+D41 -> 0
E42: =C42+D42 -> 0
B43: 【利益剰余金】 | C43: =SUM(C44:C47) -> 323535909 | D43: =SUM(D44:D47) -> 0 | E43: =C43+D43 -> 323535909
B44: 繰越利益剰余金 | C44: 323535909 | E44: =C44+D44 -> 323535909
E45: =C45+D45 -> 0
E46: =C46+D46 -> 0
E47: =C47+D47 -> 0
B48: 【自己株式】 | C48: 0 | D48: 0 | E48: =C48+D48 -> 0
B49: 【評価修正額】 | D49: =SUM(D50:D51) -> -325857131 | E49: =C49+D49 -> -325857131
B50: 修正額 | D50: ='修正BS(借方)'!D61-D28 -> -325857131 | E50: =C50+D50 -> -325857131
B51: 修正税効果 | D51: ='修正BS(借方)'!D60-D27 -> 0 | E51: =C51+D51 -> 0
B52: 純資産合計 | C52: =C35+C39+C43+C48 -> 333535909 | D52: =D35+D39+D43+D48+D49 -> -325857131 | E52: =C52+D52 -> 7678778 | H52: 14514
B53: 負債・純資産合計 | C53: =C28+C52 -> 550007542 | D53: =D28+D52 -> -325857131 | E53: =C53+D53 -> 224150411
C55: =C53='修正BS(借方)'!C61 -> TRUE

Sheet 修正PL
K2: (単位：千円)
B3: 科目 | C3: ='BS(借方)'!C4 -> 24年1月期 | F3: ='BS(借方)'!D4 -> 25年1月期 | I3: ='BS(借方)'!E4 -> 26年1月期 | L3: ='BS(借方)'!F4 -> ●●年●月期 | O3: ='BS(借方)'!G4 -> ●●年●月 （●か月TB）
C4: 帳簿価額 | D4: 修正額 | E4: 修正後 | F4: 帳簿価額 | G4: 修正額 | H4: 修正後 | I4: 帳簿価額 | J4: 修正額 | K4: 修正後 | L4: 帳簿価額 | M4: 修正額 | N4: 修正後 | O4: 帳簿価額 | P4: 修正額 | Q4: 修正後
B5: 売上高 | C5: 301575965 | E5: =C5+D5 -> 301575965 | F5: 285379413 | H5: =F5+G5 -> 285379413 | I5: 387747182 | K5: =I5+J5 -> 387747182 | N5: =L5+M5 -> 0 | Q5: =O5+P5 -> 0
B6: 輸出売上 | C6: 15179525 | E6: =C6+D6 -> 15179525 | F6: 158488638 | H6: =F6+G6 -> 158488638 | I6: 34727325 | K6: =I6+J6 -> 34727325 | N6: =L6+M6 -> 0 | Q6: =O6+P6 -> 0
E7: =C7+D7 -> 0 | H7: =F7+G7 -> 0 | K7: =I7+J7 -> 0 | N7: =L7+M7 -> 0 | Q7: =O7+P7 -> 0
E8: =C8+D8 -> 0 | H8: =F8+G8 -> 0 | K8: =I8+J8 -> 0 | N8: =L8+M8 -> 0 | Q8: =O8+P8 -> 0
B9: 売上高 | C9: =SUM(C5:C8) -> 316755490 | D9: =SUM(D5:D8) -> 0 | E9: =C9+D9 -> 316755490 | F9: =SUM(F5:F8) -> 443868051 | G9: =SUM(G5:G8) -> 0 | H9: =F9+G9 -> 443868051 | I9: =SUM(I5:I8) -> 422474507 | J9: =SUM(J5:J8) -> 0 | K9: =I9+J9 -> 422474507 | L9: =SUM(L5:L8) -> 0 | M9: =SUM(M5:M8) -> 0 | N9: =L9+M9 -> 0 | O9: =SUM(O5:O8) -> 0 | P9: =SUM(P5:P8) -> 0 | Q9: =O9+P9 -> 0
B10: 期首商品棚卸高 | C10: 3024069 | E10: =C10+D10 -> 3024069 | F10: 1426042 | H10: =F10+G10 -> 1426042 | I10: 33344623 | K10: =I10+J10 -> 33344623 | N10: =L10+M10 -> 0 | Q10: =O10+P10 -> 0
B11: 当期商品仕入高 | C11: 172656708 | E11: =C11+D11 -> 172656708 | F11: 237257918 | H11: =F11+G11 -> 237257918 | I11: 225575333 | K11: =I11+J11 -> 225575333 | N11: =L11+M11 -> 0 | Q11: =O11+P11 -> 0
B12: （製）支払手数料 | C12: 26573925 | E12: =C12+D12 -> 26573925 | F12: 50722738 | H12: =F12+G12 -> 50722738 | I12: 21094265 | K12: =I12+J12 -> 21094265 | N12: =L12+M12 -> 0 | Q12: =O12+P12 -> 0
B13: （製）サンプル | C13: 6307077 | E13: =C13+D13 -> 6307077 | F13: 2327904 | H13: =F13+G13 -> 2327904 | I13: 2831360 | K13: =I13+J13 -> 2831360 | N13: =L13+M13 -> 0 | Q13: =O13+P13 -> 0
B14: 試作費 | C14: 4487974 | E14: =C14+D14 -> 4487974 | F14: 13796708 | H14: =F14+G14 -> 13796708 | I14: 3637077 | K14: =I14+J14 -> 3637077 | N14: =L14+M14 -> 0 | Q14: =O14+P14 -> 0
B15: （製）外注費 | C15: 8299304 | E15: =C15+D15 -> 8299304 | F15: 9972324 | H15: =F15+G15 -> 9972324 | I15: 5262263 | K15: =I15+J15 -> 5262263 | N15: =L15+M15 -> 0 | Q15: =O15+P15 -> 0
B16: 仕入値引高 | E16: =C16+D16 -> 0 | H16: =F16+G16 -> 0 | I16: -100 | K16: =I16+J16 -> -100 | N16: =L16+M16 -> 0 | Q16: =O16+P16 -> 0
B17: 他勘定振替高 | C17: -6722798 | D17: =-C17 -> 6722798 | E17: =C17+D17 -> 0 | F17: -17217311 | G17: =-F17 -> 17217311 | H17: =F17+G17 -> 0 | I17: -19844732 | J17: =-I17 -> 19844732 | K17: =I17+J17 -> 0 | N17: =L17+M17 -> 0 | Q17: =O17+P17 -> 0
B18: 期末商品棚卸高 | C18: -1426042 | E18: =C18+D18 -> -1426042 | F18: -33344623 | H18: =F18+G18 -> -33344623 | I18: -228854 | K18: =I18+J18 -> -228854 | N18: =L18+M18 -> 0 | Q18: =O18+P18 -> 0
B19: 売上原価 | C19: =SUM(C10:C18) -> 213200217 | D19: =SUM(D10:D18) -> 6722798 | E19: =C19+D19 -> 219923015 | F19: =SUM(F10:F18) -> 264941700 | G19: =SUM(G10:G18) -> 17217311 | H19: =F19+G19 -> 282159011 | I19: =SUM(I10:I18) -> 271671235 | J19: =SUM(J10:J18) -> 19844732 | K19: =I19+J19 -> 291515967 | L19: =SUM(L10:L18) -> 0 | M19: =SUM(M10:M18) -> 0 | N19: =L19+M19 -> 0 | O19: =SUM(O10:O18) -> 0 | P19: =SUM(P10:P18) -> 0 | Q19: =O19+P19 -> 0
B20: 売上総利益 | C20: =C9-C19 -> 103555273 | D20: =D9-D19 -> -6722798 | E20: =C20+D20 -> 96832475 | F20: =F9-F19 -> 178926351 | G20: =G9-G19 -> -17217311 | H20: =F20+G20 -> 161709040 | I20: =I9-I19 -> 150803272 | J20: =J9-J19 -> -19844732 | K20: =I20+J20 -> 130958540 | L20: =L9-L19 -> 0 | M20: =M9-M19 -> 0 | N20: =L20+M20 -> 0 | O20: =O9-O19 -> 0 | P20: =P9-P19 -> 0 | Q20: =O20+P20 -> 0
B21: 販売費及び一般管理費 | C21: =修正SGA!C39 -> 97395979 | D21: =修正SGA!D39 -> -5212706.5 | E21: =C21+D21 -> 92183272 | F21: =修正SGA!F39 -> 100735586 | G21: =修正SGA!G39 -> -5622703 | H21: =F21+G21 -> 95112883 | I21: =修正SGA!I39 -> 92289462 | J21: =修正SGA!J39 -> -6025730 | K21: =I21+J21 -> 86263732 | N21: =L21+M21 -> 0 | Q21: =O21+P21 -> 0
B22: 営業利益 | C22: =C20- C21 -> 6159294 | D22: =D20- D21 -> -1510091.5 | E22: =C22+D22 -> 4649202.5 | F22: =F20- F21 -> 78190765 | G22: =G20- G21 -> -11594608 | H22: =F22+G22 -> 66596157 | I22: =I20- I21 -> 58513810 | J22: =J20- J21 -> -13819002 | K22: =I22+J22 -> 44694808 | L22: =L20- L21 -> 0 | M22: =M20- M21 -> 0 | N22: =L22+M22 -> 0 | O22: =O20- O21 -> 0 | P22: =P20- P21 -> 0 | Q22: =O22+P22 -> 0
B23: 営業外収益 | C23: =SUM(C24:C29) -> 1358290 | D23: =SUM(D24:D29) -> -1358290 | E23: =C23+D23 -> 0 | F23: =SUM(F24:F29) -> 13984344 | G23: =SUM(G24:G29) -> -13984344 | H23: =F23+G23 -> 0 | I23: =SUM(I24:I29) -> 8626001 | J23: =SUM(J24:J29) -> -8626001 | K23: =I23+J23 -> 0 | L23: =SUM(L24:L29) -> 0 | M23: =SUM(M24:M29) -> 0 | N23: =L23+M23 -> 0 | O23: =SUM(O24:O29) -> 0 | P23: =SUM(P24:P29) -> 0 | Q23: =O23+P23 -> 0
B24: 受取利息 | C24: 101059 | D24: =-C24 -> -101059 | E24: =C24+D24 -> 0 | F24: 1035013 | G24: =-F24 -> -1035013 | H24: =F24+G24 -> 0 | I24: 326339 | J24: =-I24 -> -326339 | K24: =I24+J24 -> 0 | N24: =L24+M24 -> 0 | Q24: =O24+P24 -> 0
B25: 受取配当金 | C25: 712050 | D25: =-C25 -> -712050 | E25: =C25+D25 -> 0 | F25: 7151912 | G25: =-F25 -> -7151912 | H25: =F25+G25 -> 0 | I25: 7555640 | J25: =-I25 -> -7555640 | K25: =I25+J25 -> 0 | N25: =L25+M25 -> 0 | Q25: =O25+P25 -> 0
B26: 貸倒引当金戻入額 | C26: 534000 | D26: =-C26 -> -534000 | E26: =C26+D26 -> 0 | F26: 803000 | G26: =-F26 -> -803000 | H26: =F26+G26 -> 0 | I26: 246000 | J26: =-I26 -> -246000 | K26: =I26+J26 -> 0 | N26: =L26+M26 -> 0 | Q26: =O26+P26 -> 0
B27: 雑収入 | C27: 2197 | D27: =-C27 -> -2197 | E27: =C27+D27 -> 0 | F27: 2195483 | G27: =-F27 -> -2195483 | H27: =F27+G27 -> 0 | I27: 216735 | J27: =-I27 -> -216735 | K27: =I27+J27 -> 0 | N27: =L27+M27 -> 0 | Q27: =O27+P27 -> 0
B28: 仕入割引 | D28: =-C28 -> 0 | E28: =C28+D28 -> 0 | G28: =-F28 -> 0 | H28: =F28+G28 -> 0 | I28: 10455 | J28: =-I28 -> -10455 | K28: =I28+J28 -> 0 | N28: =L28+M28 -> 0 | Q28: =O28+P28 -> 0
B29: 為替差益 | C29: 8984 | D29: =-C29 -> -8984 | E29: =C29+D29 -> 0 | F29: 2798936 | G29: =-F29 -> -2798936 | H29: =F29+G29 -> 0 | I29: 270832 | J29: =-I29 -> -270832 | K29: =I29+J29 -> 0 | N29: =L29+M29 -> 0 | Q29: =O29+P29 -> 0
B30: 営業外費用 | C30: =SUM(C31:C35) -> 852015 | D30: =SUM(D31:D35) -> -852015 | E30: =C30+D30 -> 0 | F30: =SUM(F31:F35) -> 2246448 | G30: =SUM(G31:G35) -> -2246448 | H30: =F30+G30 -> 0 | I30: =SUM(I31:I35) -> 2196742 | J30: =SUM(J31:J35) -> -2196742 | K30: =I30+J30 -> 0 | L30: =SUM(L31:L35) -> 0 | M30: =SUM(M31:M35) -> 0 | N30: =L30+M30 -> 0 | O30: =SUM(O31:O35) -> 0 | P30: =SUM(P31:P35) -> 0 | Q30: =O30+P30 -> 0
B31: 支払利息 | C31: 852015 | D31: =-C31 -> -852015 | E31: =C31+D31 -> 0 | F31: 1716559 | G31: =-F31 -> -1716559 | H31: =F31+G31 -> 0 | I31: 2196742 | J31: =-I31 -> -2196742 | K31: =I31+J31 -> 0 | N31: =L31+M31 -> 0 | Q31: =O31+P31 -> 0
B32: 雑損失 | D32: =-C32 -> 0 | E32: =C32+D32 -> 0 | F32: 529889 | G32: =-F32 -> -529889 | H32: =F32+G32 -> 0 | J32: =-I32 -> 0 | K32: =I32+J32 -> 0 | N32: =L32+M32 -> 0 | Q32: =O32+P32 -> 0
E33: =C33+D33 -> 0 | H33: =F33+G33 -> 0 | K33: =I33+J33 -> 0 | N33: =L33+M33 -> 0 | Q33: =O33+P33 -> 0
E34: =C34+D34 -> 0 | H34: =F34+G34 -> 0 | K34: =I34+J34 -> 0 | N34: =L34+M34 -> 0 | Q34: =O34+P34 -> 0
E35: =C35+D35 -> 0 | H35: =F35+G35 -> 0 | K35: =I35+J35 -> 0 | N35: =L35+M35 -> 0 | Q35: =O35+P35 -> 0
B36: 経常利益 | C36: =C22+C23-C30 -> 6665569 | D36: =D22+D23-D30 -> -2016366.5 | E36: =C36+D36 -> 4649202.5 | F36: =F22+F23-F30 -> 89928661 | G36: =G22+G23-G30 -> -23332504 | H36: =F36+G36 -> 66596157 | I36: =I22+I23-I30 -> 64943069 | J36: =J22+J23-J30 -> -20248261 | K36: =I36+J36 -> 44694808 | L36: =L22+L23-L30 -> 0 | M36: =M22+M23-M30 -> 0 | N36: =L36+M36 -> 0 | O36: =O22+O23-O30 -> 0 | P36: =P22+P23-P30 -> 0 | Q36: =O36+P36 -> 0
B37: 特別利益 | C37: =SUM(C38:C41) -> 0 | D37: =SUM(D38:D41) -> 0 | E37: =C37+D37 -> 0 | F37: =SUM(F38:F41) -> 21984310 | G37: =SUM(G38:G41) -> -21984310 | H37: =F37+G37 -> 0 | I37: =SUM(I38:I41) -> 12486495 | J37: =SUM(J38:J41) -> -12486495 | K37: =I37+J37 -> 0 | L37: =SUM(L38:L41) -> 0 | M37: =SUM(M38:M41) -> 0 | N37: =L37+M37 -> 0 | O37: =SUM(O38:O41) -> 0 | P37: =SUM(P38:P41) -> 0 | Q37: =O37+P37 -> 0
B38: 投資有価証券売却益 | D38: =-C38 -> 0 | E38: =C38+D38 -> 0 | F38: 21984310 | G38: =-F38 -> -21984310 | H38: =F38+G38 -> 0 | I38: 12486495 | J38: =-I38 -> -12486495 | K38: =I38+J38 -> 0 | N38: =L38+M38 -> 0 | Q38: =O38+P38 -> 0
E39: =C39+D39 -> 0 | H39: =F39+G39 -> 0 | K39: =I39+J39 -> 0 | N39: =L39+M39 -> 0 | Q39: =O39+P39 -> 0
E40: =C40+D40 -> 0 | H40: =F40+G40 -> 0 | K40: =I40+J40 -> 0 | N40: =L40+M40 -> 0 | Q40: =O40+P40 -> 0
E41: =C41+D41 -> 0 | H41: =F41+G41 -> 0 | K41: =I41+J41 -> 0 | N41: =L41+M41 -> 0 | Q41: =O41+P41 -> 0
B42: 特別損失 | C42: =SUM(C43:C46) -> 11676176 | D42: =SUM(D43:D46) -> -11676176 | E42: =C42+D42 -> 0 | F42: =SUM(F43:F46) -> 50657768 | G42: =SUM(G43:G46) -> -50657768 | H42: =F42+G42 -> 0 | I42: =SUM(I43:I46) -> 25990527 | J42: =SUM(J43:J46) -> -25990527 | K42: =I42+J42 -> 0 | L42: =SUM(L43:L46) -> 0 | M42: =SUM(M43:M46) -> 0 | N42: =L42+M42 -> 0 | O42: =SUM(O43:O46) -> 0 | P42: =SUM(P43:P46) -> 0 | Q42: =O42+P42 -> 0
B43: 投資有価証券売却損 | D43: =-C43 -> 0 | E43: =C43+D43 -> 0 | F43: 27860505 | G43: =-F43 -> -27860505 | H43: =F43+G43 -> 0 | I43: 565843 | J43: =-I43 -> -565843 | K43: =I43+J43 -> 0 | N43: =L43+M43 -> 0 | Q43: =O43+P43 -> 0
B44: 固定資産除却損 | C44: 2 | D44: =-C44 -> -2 | E44: =C44+D44 -> 0 | G44: =-F44 -> 0 | H44: =F44+G44 -> 0 | J44: =-I44 -> 0 | K44: =I44+J44 -> 0 | N44: =L44+M44 -> 0 | Q44: =O44+P44 -> 0
B45: 棚卸資産廃棄損 | C45: 6722798 | D45: =-C45 -> -6722798 | E45: =C45+D45 -> 0 | F45: 17217311 | G45: =-F45 -> -17217311 | H45: =F45+G45 -> 0 | I45: 19844732 | J45: =-I45 -> -19844732 | K45: =I45+J45 -> 0 | N45: =L45+M45 -> 0 | Q45: =O45+P45 -> 0
B46: 特別保険料 | C46: 4953376 | D46: =-C46 -> -4953376 | E46: =C46+D46 -> 0 | F46: 5579952 | G46: =-F46 -> -5579952 | H46: =F46+G46 -> 0 | I46: 5579952 | J46: =-I46 -> -5579952 | K46: =I46+J46 -> 0 | N46: =L46+M46 -> 0 | Q46: =O46+P46 -> 0
B47: 税引前当期純利益 | C47: =C36+C37-C42 -> -5010607 | D47: =D36+D37-D42 -> 9659809.5 | E47: =C47+D47 -> 4649202.5 | F47: =F36+F37-F42 -> 61255203 | G47: =G36+G37-G42 -> 5340954 | H47: =F47+G47 -> 66596157 | I47: =I36+I37-I42 -> 51439037 | J47: =J36+J37-J42 -> -6744229 | K47: =I47+J47 -> 44694808 | L47: =L36+L37-L42 -> 0 | M47: =M36+M37-M42 -> 0 | N47: =L47+M47 -> 0 | O47: =O36+O37-O42 -> 0 | P47: =P36+P37-P42 -> 0 | Q47: =O47+P47 -> 0
B48: 法人税等 | C48: =SUM(C49:C50) -> 159573 | D48: =SUM(D49:D50) -> 0 | E48: =C48+D48 -> 159573 | F48: =SUM(F49:F50) -> 20697447 | G48: =SUM(G49:G50) -> 0 | H48: =F48+G48 -> 20697447 | I48: =SUM(I49:I50) -> 13808861 | J48: =SUM(J49:J50) -> 0 | K48: =I48+J48 -> 13808861 | L48: =SUM(L49:L50) -> 0 | M48: =SUM(M49:M50) -> 0 | N48: =L48+M48 -> 0 | O48: =SUM(O49:O50) -> 0 | P48: =SUM(P49:P50) -> 0 | Q48: =O48+P48 -> 0
B49: 法人税等 | C49: 159573 | E49: =C49+D49 -> 159573 | F49: 20697447 | H49: =F49+G49 -> 20697447 | I49: 13808861 | K49: =I49+J49 -> 13808861 | N49: =L49+M49 -> 0 | Q49: =O49+P49 -> 0
E50: =C50+D50 -> 0 | H50: =F50+G50 -> 0 | K50: =I50+J50 -> 0 | N50: =L50+M50 -> 0 | Q50: =O50+P50 -> 0
B51: 税引後当期純利益 | C51: =C47-C48 -> -5170180 | D51: =D47-D48 -> 9659809.5 | E51: =C51+D51 -> 4489629.5 | F51: =F47-F48 -> 40557756 | G51: =G47-G48 -> 5340954 | H51: =F51+G51 -> 45898710 | I51: =I47-I48 -> 37630176 | J51: =J47-J48 -> -6744229 | K51: =I51+J51 -> 30885947 | L51: =L47-L48 -> 0 | M51: =M47-M48 -> 0 | N51: =L51+M51 -> 0 | O51: =O47-O48 -> 0 | P51: =P47-P48 -> 0 | Q51: =O51+P51 -> 0
E52: =C52+D52 -> 0 | H52: =F52+G52 -> 0 | K52: =I52+J52 -> 0 | N52: =L52+M52 -> 0 | Q52: =O52+P52 -> 0
C53: -5170180 | E53: =C53+D53 -> -5170180 | F53: 40557756 | H53: =F53+G53 -> 40557756 | I53: 37630176 | K53: =I53+J53 -> 37630176 | N53: =L53+M53 -> 0 | Q53: =O53+P53 -> 0
C54: =C53=C51 -> TRUE | E54: =C54+D54 -> 1 | F54: =F53=F51 -> TRUE | H54: =F54+G54 -> 1 | I54: =I53=I51 -> TRUE | K54: =I54+J54 -> 1 | N54: =L54+M54 -> 0 | Q54: =O54+P54 -> 0
E55: =C55+D55 -> 0 | H55: =F55+G55 -> 0 | K55: =I55+J55 -> 0 | N55: =L55+M55 -> 0 | Q55: =O55+P55 -> 0
E56: =C56+D56 -> 0 | H56: =F56+G56 -> 0 | K56: =I56+J56 -> 0 | N56: =L56+M56 -> 0 | Q56: =O56+P56 -> 0
E57: =C57+D57 -> 0 | H57: =F57+G57 -> 0 | K57: =I57+J57 -> 0 | N57: =L57+M57 -> 0 | Q57: =O57+P57 -> 0
E58: =C58+D58 -> 0 | H58: =F58+G58 -> 0 | K58: =I58+J58 -> 0 | N58: =L58+M58 -> 0 | Q58: =O58+P58 -> 0
E59: =C59+D59 -> 0 | H59: =F59+G59 -> 0 | K59: =I59+J59 -> 0 | N59: =L59+M59 -> 0 | Q59: =O59+P59 -> 0
E60: =C60+D60 -> 0 | H60: =F60+G60 -> 0 | K60: =I60+J60 -> 0 | N60: =L60+M60 -> 0 | Q60: =O60+P60 -> 0
E61: =C61+D61 -> 0 | H61: =F61+G61 -> 0 | K61: =I61+J61 -> 0 | N61: =L61+M61 -> 0 | Q61: =O61+P61 -> 0
E62: =C62+D62 -> 0 | H62: =F62+G62 -> 0 | K62: =I62+J62 -> 0 | N62: =L62+M62 -> 0 | Q62: =O62+P62 -> 0
E63: =C63+D63 -> 0 | H63: =F63+G63 -> 0 | K63: =I63+J63 -> 0 | N63: =L63+M63 -> 0 | Q63: =O63+P63 -> 0
E64: =C64+D64 -> 0 | H64: =F64+G64 -> 0 | K64: =I64+J64 -> 0 | N64: =L64+M64 -> 0 | Q64: =O64+P64 -> 0
E65: =C65+D65 -> 0 | H65: =F65+G65 -> 0 | K65: =I65+J65 -> 0 | N65: =L65+M65 -> 0 | Q65: =O65+P65 -> 0
E66: =C66+D66 -> 0 | H66: =F66+G66 -> 0 | K66: =I66+J66 -> 0 | N66: =L66+M66 -> 0 | Q66: =O66+P66 -> 0
... E73: =C73+D73 -> 0 | H73: =F73+G73 -> 0 | K73: =I73+J73 -> 0 | N73: =L73+M73 -> 0 | Q73: =O73+P73 -> 0

Sheet 修正SGA
K2: (単位：千円)
B3: 科目 | C3: ='BS(借方)'!C4 -> 24年1月期 | F3: ='BS(借方)'!D4 -> 25年1月期 | I3: ='BS(借方)'!E4 -> 26年1月期 | L3: ='BS(借方)'!F4 -> ●●年●月期 | O3: ='BS(借方)'!F4 -> ●●年●月期
C4: 帳簿価額 | D4: 修正額 | E4: 修正後 | F4: 帳簿価額 | G4: 修正額 | H4: 修正後 | I4: 帳簿価額 | J4: 修正額 | K4: 修正後 | L4: 帳簿価額 | M4: 修正額 | N4: 修正後 | O4: 帳簿価額 | P4: 修正額 | Q4: 修正後
B5: 役員報酬 | C5: 1104000 | E5: =C5+D5 -> 1104000 | F5: 1104000 | H5: =F5+G5 -> 1104000 | I5: 4094000 | J5: =-1500000-1490000 -> -2990000 | K5: =I5+J5 -> 1104000 | N5: =L5+M5 -> 0 | Q5: =O5+P5 -> 0
B6: 役員賞与 | C6: 18000000 | E6: =C6+D6 -> 18000000 | F6: 20000000 | H6: =F6+G6 -> 20000000 | I6: 20000000 | K6: =I6+J6 -> 20000000 | N6: =L6+M6 -> 0 | Q6: =O6+P6 -> 0
B7: 給料手当 | C7: 33649484 | E7: =C7+D7 -> 33649484 | F7: 29811105 | H7: =F7+G7 -> 29811105 | I7: 27938525 | K7: =I7+J7 -> 27938525 | N7: =L7+M7 -> 0 | Q7: =O7+P7 -> 0
B8: 雑給 | C8: 2538750 | D8: =-C8 -> -2538750 | E8: =C8+D8 -> 0 | F8: 6544740 | G8: =-1500000-1490000 -> -2990000 | H8: =F8+G8 -> 3554740 | I8: 299000 | K8: =I8+J8 -> 299000 | N8: =L8+M8 -> 0 | Q8: =O8+P8 -> 0
B9: 賞与 | C9: 4064600 | E9: =C9+D9 -> 4064600 | H9: =F9+G9 -> 0 | I9: 6079177 | K9: =I9+J9 -> 6079177 | N9: =L9+M9 -> 0 | Q9: =O9+P9 -> 0
B10: 法定福利費 | C10: 6407318 | D10: =(D5+D6+D8)*0.15 -> -380812.5 | E10: =C10+D10 -> 6026505.5 | F10: 6394777 | G10: =(G5+G6+G8)*0.15 -> -448500 | H10: =F10+G10 -> 5946277 | I10: 6366731 | J10: =(J5+J6)*0.15 -> -448500 | K10: =I10+J10 -> 5918231 | N10: =L10+M10 -> 0 | Q10: =O10+P10 -> 0
B11: 福利厚生費 | C11: 1932474 | E11: =C11+D11 -> 1932474 | F11: 422087 | H11: =F11+G11 -> 422087 | I11: 705804 | K11: =I11+J11 -> 705804 | N11: =L11+M11 -> 0 | Q11: =O11+P11 -> 0
B12: 採用教育費 | C12: 280000 | E12: =C12+D12 -> 280000 | F12: 1480000 | H12: =F12+G12 -> 1480000 | K12: =I12+J12 -> 0 | N12: =L12+M12 -> 0 | Q12: =O12+P12 -> 0
B13: 荷造運賃 | C13: 9235586 | E13: =C13+D13 -> 9235586 | F13: 13487346 | H13: =F13+G13 -> 13487346 | I13: 7104880 | K13: =I13+J13 -> 7104880 | N13: =L13+M13 -> 0 | Q13: =O13+P13 -> 0
B14: 広告宣伝費 | C14: 152187 | E14: =C14+D14 -> 152187 | F14: 142619 | H14: =F14+G14 -> 142619 | I14: 841073 | K14: =I14+J14 -> 841073 | N14: =L14+M14 -> 0 | Q14: =O14+P14 -> 0
B15: 接待交際費 | C15: 1440144 | D15: =-C15 -> -1440144 | E15: =C15+D15 -> 0 | F15: 1738203 | G15: =-F15 -> -1738203 | H15: =F15+G15 -> 0 | I15: 2336230 | J15: =-I15 -> -2336230 | K15: =I15+J15 -> 0 | N15: =L15+M15 -> 0 | Q15: =O15+P15 -> 0
B16: 会議費 | C16: 211518 | E16: =C16+D16 -> 211518 | F16: 214892 | H16: =F16+G16 -> 214892 | I16: 284369 | K16: =I16+J16 -> 284369 | N16: =L16+M16 -> 0 | Q16: =O16+P16 -> 0
B17: 旅費交通費 | C17: 645511 | E17: =C17+D17 -> 645511 | F17: 2129949 | H17: =F17+G17 -> 2129949 | I17: 1018914 | K17: =I17+J17 -> 1018914 | N17: =L17+M17 -> 0 | Q17: =O17+P17 -> 0
B18: 通信費 | C18: 1416425 | E18: =C18+D18 -> 1416425 | F18: 1506325 | H18: =F18+G18 -> 1506325 | I18: 1506831 | K18: =I18+J18 -> 1506831 | N18: =L18+M18 -> 0 | Q18: =O18+P18 -> 0
B19: 販売促進費 | C19: 65128 | E19: =C19+D19 -> 65128 | H19: =F19+G19 -> 0 | K19: =I19+J19 -> 0 | N19: =L19+M19 -> 0 | Q19: =O19+P19 -> 0
B20: 事務用消耗品費 | C20: 1145535 | E20: =C20+D20 -> 1145535 | F20: 1700793 | H20: =F20+G20 -> 1700793 | I20: 1195194 | K20: =I20+J20 -> 1195194 | N20: =L20+M20 -> 0 | Q20: =O20+P20 -> 0
B21: 修繕費 | C21: 44900 | E21: =C21+D21 -> 44900 | F21: 190064 | H21: =F21+G21 -> 190064 | K21: =I21+J21 -> 0 | N21: =L21+M21 -> 0 | Q21: =O21+P21 -> 0
B22: 水道光熱費 | C22: 394299 | E22: =C22+D22 -> 394299 | F22: 403021 | H22: =F22+G22 -> 403021 | I22: 412583 | K22: =I22+J22 -> 412583 | N22: =L22+M22 -> 0 | Q22: =O22+P22 -> 0
B23: 諸会費 | C23: 57450 | E23: =C23+D23 -> 57450 | F23: 36000 | H23: =F23+G23 -> 36000 | I23: 48000 | K23: =I23+J23 -> 48000 | N23: =L23+M23 -> 0 | Q23: =O23+P23 -> 0
B24: 支払手数料 | C24: 3167934 | E24: =C24+D24 -> 3167934 | F24: 3674031 | H24: =F24+G24 -> 3674031 | I24: 1179313 | K24: =I24+J24 -> 1179313 | N24: =L24+M24 -> 0 | Q24: =O24+P24 -> 0
B25: 車両費 | C25: 650214 | E25: =C25+D25 -> 650214 | F25: 478916 | H25: =F25+G25 -> 478916 | I25: 716759 | K25: =I25+J25 -> 716759 | N25: =L25+M25 -> 0 | Q25: =O25+P25 -> 0
B26: 地代家賃 | C26: 5430000 | E26: =C26+D26 -> 5430000 | F26: 5430000 | H26: =F26+G26 -> 5430000 | I26: 5500911 | K26: =I26+J26 -> 5500911 | N26: =L26+M26 -> 0 | Q26: =O26+P26 -> 0
B27: リース料 | C27: 131200 | E27: =C27+D27 -> 131200 | F27: 160920 | H27: =F27+G27 -> 160920 | I27: 147510 | K27: =I27+J27 -> 147510 | N27: =L27+M27 -> 0 | Q27: =O27+P27 -> 0
B28: 保険料 | C28: 709690 | E28: =C28+D28 -> 709690 | F28: 1090090 | H28: =F28+G28 -> 1090090 | I28: 735330 | K28: =I28+J28 -> 735330 | N28: =L28+M28 -> 0 | Q28: =O28+P28 -> 0
B29: 租税公課 | C29: 234840 | E29: =C29+D29 -> 234840 | F29: 175360 | H29: =F29+G29 -> 175360 | I29: 269084 | K29: =I29+J29 -> 269084 | N29: =L29+M29 -> 0 | Q29: =O29+P29 -> 0
B30: 支払報酬料 | C30: 755000 | E30: =C30+D30 -> 755000 | F30: 755000 | H30: =F30+G30 -> 755000 | I30: 762000 | K30: =I30+J30 -> 762000 | N30: =L30+M30 -> 0 | Q30: =O30+P30 -> 0
B31: 寄付金 | C31: 50000 | D31: =-C31 -> -50000 | E31: =C31+D31 -> 0 | F31: 200000 | G31: =-F31 -> -200000 | H31: =F31+G31 -> 0 | I31: 50000 | J31: =-I31 -> -50000 | K31: =I31+J31 -> 0 | N31: =L31+M31 -> 0 | Q31: =O31+P31 -> 0
B32: 研究開発費 | C32: 174503 | E32: =C32+D32 -> 174503 | F32: 574824 | H32: =F32+G32 -> 574824 | I32: 170367 | K32: =I32+J32 -> 170367 | N32: =L32+M32 -> 0 | Q32: =O32+P32 -> 0
B33: 減価償却費 | C33: 881300 | E33: =C33+D33 -> 881300 | F33: 644524 | H33: =F33+G33 -> 644524 | I33: 1182673 | K33: =I33+J33 -> 1182673 | N33: =L33+M33 -> 0 | Q33: =O33+P33 -> 0
B34: 貸倒引当金繰入額 | C34: 803000 | D34: =-C34 -> -803000 | E34: =C34+D34 -> 0 | F34: 246000 | G34: =-F34 -> -246000 | H34: =F34+G34 -> 0 | I34: 201000 | J34: =-I34 -> -201000 | K34: =I34+J34 -> 0 | N34: =L34+M34 -> 0 | Q34: =O34+P34 -> 0
B35: 通勤 | C35: 1622989 | E35: =C35+D35 -> 1622989 | H35: =F35+G35 -> 0 | I35: 1143204 | K35: =I35+J35 -> 1143204 | N35: =L35+M35 -> 0 | Q35: =O35+P35 -> 0
E36: =C36+D36 -> 0 | H36: =F36+G36 -> 0 | K36: =I36+J36 -> 0 | N36: =L36+M36 -> 0 | Q36: =O36+P36 -> 0
E37: =C37+D37 -> 0 | H37: =F37+G37 -> 0 | K37: =I37+J37 -> 0 | N37: =L37+M37 -> 0 | Q37: =O37+P37 -> 0
E38: =C38+D38 -> 0 | H38: =F38+G38 -> 0 | K38: =I38+J38 -> 0 | N38: =L38+M38 -> 0 | Q38: =O38+P38 -> 0
B39: 販売費および一般管理費合計 | C39: =SUM(C5:C38) -> 97395979 | D39: =SUM(D5:D38) -> -5212706.5 | E39: =C39+D39 -> 92183272 | F39: =SUM(F5:F38) -> 100735586 | G39: =SUM(G5:G38) -> -5622703 | H39: =F39+G39 -> 95112883 | I39: =SUM(I5:I38) -> 92289462 | J39: =SUM(J5:J38) -> -6025730 | K39: =I39+J39 -> 86263732 | L39: =SUM(L5:L38) -> 0 | M39: =SUM(M5:M38) -> 0 | N39: =L39+M39 -> 0 | O39: =SUM(O5:O38) -> 0 | P39: =SUM(P5:P38) -> 0 | Q39: =O39+P39 -> 0

Sheet 修正CR
K2: (単位：千円)
B3: 科目 | C3: ='BS(借方)'!C4 -> 24年1月期 | F3: ='BS(借方)'!D4 -> 25年1月期 | I3: ='BS(借方)'!E4 -> 26年1月期 | L3: ='BS(借方)'!F4 -> ●●年●月期 | O3: ='BS(借方)'!G4 -> ●●年●月 （●か月TB）
C4: 帳簿価額 | D4: 修正額 | E4: 修正後 | F4: 帳簿価額 | G4: 修正額 | H4: 修正後 | I4: 帳簿価額 | J4: 修正額 | K4: 修正後 | L4: 帳簿価額 | M4: 修正額 | N4: 修正後 | O4: 帳簿価額 | P4: 修正額 | Q4: 修正後
B5: 期首原材料棚卸高 | C5: 500000 | D5: -500000 | E5: =C5+D5 -> 0 | F5: 500000 | G5: -500000 | H5: =F5+G5 -> 0 | I5: 500000 | J5: -500000 | K5: =I5+J5 -> 0 | L5: 500000 | M5: -500000 | N5: =L5+M5 -> 0 | O5: 500000 | P5: -500000 | Q5: =O5+P5 -> 0
B6: 原材料仕入高 | E6: =C6+D6 -> 0 | H6: =F6+G6 -> 0 | K6: =I6+J6 -> 0 | N6: =L6+M6 -> 0 | Q6: =O6+P6 -> 0
B7: 小計 | E7: =C7+D7 -> 0 | H7: =F7+G7 -> 0 | K7: =I7+J7 -> 0 | N7: =L7+M7 -> 0 | Q7: =O7+P7 -> 0
B8: 期末原材料棚卸高 | E8: =C8+D8 -> 0 | H8: =F8+G8 -> 0 | K8: =I8+J8 -> 0 | N8: =L8+M8 -> 0 | Q8: =O8+P8 -> 0
E9: =C9+D9 -> 0 | H9: =F9+G9 -> 0 | K9: =I9+J9 -> 0 | N9: =L9+M9 -> 0 | Q9: =O9+P9 -> 0
E10: =C10+D10 -> 0 | H10: =F10+G10 -> 0 | K10: =I10+J10 -> 0 | N10: =L10+M10 -> 0 | Q10: =O10+P10 -> 0
B11: 材料費 | C11: =SUM(C5:C10) -> 500000 | D11: =SUM(D5:D10) -> -500000 | E11: =C11+D11 -> 0 | F11: =SUM(F5:F10) -> 500000 | G11: =SUM(G5:G10) -> -500000 | H11: =F11+G11 -> 0 | I11: =SUM(I5:I10) -> 500000 | J11: =SUM(J5:J10) -> -500000 | K11: =I11+J11 -> 0 | L11: =SUM(L5:L10) -> 500000 | M11: =SUM(M5:M10) -> -500000 | N11: =L11+M11 -> 0 | O11: =SUM(O5:O10) -> 500000 | P11: =SUM(P5:P10) -> -500000 | Q11: =O11+P11 -> 0
E12: =C12+D12 -> 0 | H12: =F12+G12 -> 0 | K12: =I12+J12 -> 0 | N12: =L12+M12 -> 0 | Q12: =O12+P12 -> 0
E13: =C13+D13 -> 0 | H13: =F13+G13 -> 0 | K13: =I13+J13 -> 0 | N13: =L13+M13 -> 0 | Q13: =O13+P13 -> 0
E14: =C14+D14 -> 0 | H14: =F14+G14 -> 0 | K14: =I14+J14 -> 0 | N14: =L14+M14 -> 0 | Q14: =O14+P14 -> 0
E15: =C15+D15 -> 0 | H15: =F15+G15 -> 0 | K15: =I15+J15 -> 0 | N15: =L15+M15 -> 0 | Q15: =O15+P15 -> 0
E16: =C16+D16 -> 0 | H16: =F16+G16 -> 0 | K16: =I16+J16 -> 0 | N16: =L16+M16 -> 0 | Q16: =O16+P16 -> 0
E17: =C17+D17 -> 0 | H17: =F17+G17 -> 0 | K17: =I17+J17 -> 0 | N17: =L17+M17 -> 0 | Q17: =O17+P17 -> 0
B18: 労務費 | C18: =SUM(C12:C17) -> 0 | D18: =SUM(D12:D17) -> 0 | E18: =C18+D18 -> 0 | F18: =SUM(F12:F17) -> 0 | G18: =SUM(G12:G17) -> 0 | H18: =F18+G18 -> 0 | I18: =SUM(I12:I17) -> 0 | J18: =SUM(J12:J17) -> 0 | K18: =I18+J18 -> 0 | L18: =SUM(L12:L17) -> 0 | M18: =SUM(M12:M17) -> 0 | N18: =L18+M18 -> 0 | O18: =SUM(O12:O17) -> 0 | P18: =SUM(P12:P17) -> 0 | Q18: =O18+P18 -> 0
E19: =C19+D19 -> 0 | H19: =F19+G19 -> 0 | K19: =I19+J19 -> 0 | N19: =L19+M19 -> 0 | Q19: =O19+P19 -> 0
E20: =C20+D20 -> 0 | H20: =F20+G20 -> 0 | K20: =I20+J20 -> 0 | N20: =L20+M20 -> 0 | Q20: =O20+P20 -> 0
E21: =C21+D21 -> 0 | H21: =F21+G21 -> 0 | K21: =I21+J21 -> 0 | N21: =L21+M21 -> 0 | Q21: =O21+P21 -> 0
E22: =C22+D22 -> 0 | H22: =F22+G22 -> 0 | K22: =I22+J22 -> 0 | N22: =L22+M22 -> 0 | Q22: =O22+P22 -> 0
E23: =C23+D23 -> 0 | H23: =F23+G23 -> 0 | K23: =I23+J23 -> 0 | N23: =L23+M23 -> 0 | Q23: =O23+P23 -> 0
E24: =C24+D24 -> 0 | H24: =F24+G24 -> 0 | K24: =I24+J24 -> 0 | N24: =L24+M24 -> 0 | Q24: =O24+P24 -> 0
B25: 外注加工費 | C25: =SUM(C19:C24) -> 0 | D25: =SUM(D19:D24) -> 0 | E25: =C25+D25 -> 0 | F25: =SUM(F19:F24) -> 0 | G25: =SUM(G19:G24) -> 0 | H25: =F25+G25 -> 0 | I25: =SUM(I19:I24) -> 0 | J25: =SUM(J19:J24) -> 0 | K25: =I25+J25 -> 0 | L25: =SUM(L19:L24) -> 0 | M25: =SUM(M19:M24) -> 0 | N25: =L25+M25 -> 0 | O25: =SUM(O19:O24) -> 0 | P25: =SUM(P19:P24) -> 0 | Q25: =O25+P25 -> 0
E26: =C26+D26 -> 0 | H26: =F26+G26 -> 0 | K26: =I26+J26 -> 0 | N26: =L26+M26 -> 0 | Q26: =O26+P26 -> 0
E27: =C27+D27 -> 0 | H27: =F27+G27 -> 0 | K27: =I27+J27 -> 0 | N27: =L27+M27 -> 0 | Q27: =O27+P27 -> 0
E28: =C28+D28 -> 0 | H28: =F28+G28 -> 0 | K28: =I28+J28 -> 0 | N28: =L28+M28 -> 0 | Q28: =O28+P28 -> 0
E29: =C29+D29 -> 0 | H29: =F29+G29 -> 0 | K29: =I29+J29 -> 0 | N29: =L29+M29 -> 0 | Q29: =O29+P29 -> 0
E30: =C30+D30 -> 0 | H30: =F30+G30 -> 0 | K30: =I30+J30 -> 0 | N30: =L30+M30 -> 0 | Q30: =O30+P30 -> 0
E31: =C31+D31 -> 0 | H31: =F31+G31 -> 0 | K31: =I31+J31 -> 0 | N31: =L31+M31 -> 0 | Q31: =O31+P31 -> 0
E32: =C32+D32 -> 0 | H32: =F32+G32 -> 0 | K32: =I32+J32 -> 0 | N32: =L32+M32 -> 0 | Q32: =O32+P32 -> 0
E33: =C33+D33 -> 0 | H33: =F33+G33 -> 0 | K33: =I33+J33 -> 0 | N33: =L33+M33 -> 0 | Q33: =O33+P33 -> 0
E34: =C34+D34 -> 0 | H34: =F34+G34 -> 0 | K34: =I34+J34 -> 0 | N34: =L34+M34 -> 0 | Q34: =O34+P34 -> 0
E35: =C35+D35 -> 0 | H35: =F35+G35 -> 0 | K35: =I35+J35 -> 0 | N35: =L35+M35 -> 0 | Q35: =O35+P35 -> 0
B36: 経費 | C36: =SUM(C26:C35) -> 0 | D36: =SUM(D26:D35) -> 0 | E36: =C36+D36 -> 0 | F36: =SUM(F26:F35) -> 0 | G36: =SUM(G26:G35) -> 0 | H36: =F36+G36 -> 0 | I36: =SUM(I26:I35) -> 0 | J36: =SUM(J26:J35) -> 0 | K36: =I36+J36 -> 0 | L36: =SUM(L26:L35) -> 0 | M36: =SUM(M26:M35) -> 0 | N36: =L36+M36 -> 0 | O36: =SUM(O26:O35) -> 0 | P36: =SUM(P26:P35) -> 0 | Q36: =O36+P36 -> 0
B37: 当期製造費用 | C37: =C11+C18+C25+C36 -> 500000 | D37: =D11+D18+D25+D36 -> -500000 | E37: =C37+D37 -> 0 | F37: =F11+F18+F25+F36 -> 500000 | G37: =G11+G18+G25+G36 -> -500000 | H37: =F37+G37 -> 0 | I37: =I11+I18+I25+I36 -> 500000 | J37: =J11+J18+J25+J36 -> -500000 | K37: =I37+J37 -> 0 | L37: =L11+L18+L25+L36 -> 500000 | M37: =M11+M18+M25+M36 -> -500000 | N37: =L37+M37 -> 0 | O37: =O11+O18+O25+O36 -> 500000 | P37: =P11+P18+P25+P36 -> -500000 | Q37: =O37+P37 -> 0
B38: 期首仕掛品棚卸高 | E38: =C38+D38 -> 0 | H38: =F38+G38 -> 0 | K38: =I38+J38 -> 0 | N38: =L38+M38 -> 0 | Q38: =O38+P38 -> 0
B39: 合計 | C39: =SUM(C37:C38) -> 500000 | D39: =SUM(D37:D38) -> -500000 | E39: =C39+D39 -> 0 | F39: =SUM(F37:F38) -> 500000 | G39: =SUM(G37:G38) -> -500000 | H39: =F39+G39 -> 0 | I39: =SUM(I37:I38) -> 500000 | J39: =SUM(J37:J38) -> -500000 | K39: =I39+J39 -> 0 | L39: =SUM(L37:L38) -> 500000 | M39: =SUM(M37:M38) -> -500000 | N39: =L39+M39 -> 0 | O39: =SUM(O37:O38) -> 500000 | P39: =SUM(P37:P38) -> -500000 | Q39: =O39+P39 -> 0
B40: 期末仕掛品棚卸高 | E40: =C40+D40 -> 0 | H40: =F40+G40 -> 0 | K40: =I40+J40 -> 0 | N40: =L40+M40 -> 0 | Q40: =O40+P40 -> 0
B41: 当期製造原価 | C41: =C39-C40 -> 500000 | D41: =D39-D40 -> -500000 | E41: =C41+D41 -> 0 | F41: =F39-F40 -> 500000 | G41: =G39-G40 -> -500000 | H41: =F41+G41 -> 0 | I41: =I39-I40 -> 500000 | J41: =J39-J40 -> -500000 | K41: =I41+J41 -> 0 | L41: =L39-L40 -> 500000 | M41: =M39-M40 -> -500000 | N41: =L41+M41 -> 0 | O41: =O39-O40 -> 500000 | P41: =P39-P40 -> -500000 | Q41: =O41+P41 -> 0

Sheet 年買法
C2: (単位：千円) | H2: (単位：千円) | M2: (単位：千円)
B3: =修正PL!I3 -> 26年1月期 | C3: 金額 | F3: =修正PL!C3 -> 24年1月期 | G3: =修正PL!F3 -> 25年1月期 | H3: =修正PL!I3 -> 26年1月期 | J3: 営業権倍率 | K3: x1 | L3: x2 | M3: x3
B4: 簿価純資産額 | C4: ='BS (貸方)'!E50 -> 333535909 | E4: 簿価営業利益 | F4: =修正PL!C22 -> 6159294 | G4: =修正PL!F22 -> 78190765 | H4: =修正PL!I22 -> 58513810 | J4: 時価純資産 | K4: =C6 -> 7678778
B5: 修正額 | C5: ='修正BS(貸方) '!D52 -> -325857131 | E5: 修正額 | F5: =修正PL!D22 -> -1510091.5 | G5: =修正PL!G22 -> -11594608 | H5: =修正PL!J22 -> -13819002 | J5: 営業権 | K5: =H10*1 -> 25506837 | L5: =H10*2 -> 51013674 | M5: =H10*3 -> 76520511
B6: 時価純資産 | C6: =SUM(C4:C5) -> 7678778 | E6: 修正後営業利益 | F6: =SUM(F4:F5) -> 4649202.5 | G6: =SUM(G4:G5) -> 66596157 | H6: =SUM(H4:H5) -> 44694808 | J6: 想定株式価値 | K6: =K4+K5 -> 33185615 | L6: =K4+L5 -> 58692452 | M6: =K4+M5 -> 84199289
E7: 税考慮額 | F7: =-F6*0.34 -> -1580728.9 | G7: =-G6*0.34 -> -22642693 | H7: =-H6*0.34 -> -15196235
E8: 修正後税考慮後営業利益 | F8: =SUM(F6:F7) -> 3068473.6 | G8: =SUM(G6:G7) -> 43953464 | H8: =SUM(H6:H7) -> 29498573
G10: 基準営業利益 | H10: =AVERAGE(F8:H8) -> 25506837

Sheet EV EBITDAマルチプル
C2: (単位：千円) | H2: (単位：千円) | M2: (単位：千円)
B3: =PL!G3 -> 26年1月期 | C3: 金額 | F3: =修正PL!C3 -> 24年1月期 | G3: =修正PL!F3 -> 25年1月期 | H3: =修正PL!I3 -> 26年1月期 | J3: マルチプル倍率 | K3: x3 | L3: x4 | M3: x5
B4: キャッシュライク | C4: =ネットキャッシュ!C13 -> 193226490 | E4: 簿価営業利益 | F4: =修正PL!C22 -> 6159294 | G4: =修正PL!F22 -> 78190765 | H4: =修正PL!I22 -> 58513810 | J4: EV（EBITDA×倍率） | K4: =H10*3 -> 1.1864866e+08 | L4: =H10*4 -> 1.5819822e+08 | M4: =H10*5 -> 1.9774777e+08
B5: デットライク | C5: =ネットキャッシュ!F13 -> 187808000 | E5: 修正額 | F5: =修正PL!D22 -> -1510091.5 | G5: =修正PL!G22 -> -11594608 | H5: =修正PL!J22 -> -13819002 | J5: 非流動性ディスカウント | K5: =-K4*0.1 -> -11864866 | L5: =-L4*0.1 -> -15819822 | M5: =-M4*0.1 -> -19774777
B6: ネットキャッシュ | C6: =C4-C5 -> 5418490 | E6: 修正後営業利益 | F6: =SUM(F4:F5) -> 4649202.5 | G6: =SUM(G4:G5) -> 66596157 | H6: =SUM(H4:H5) -> 44694808 | J6: =B6 -> ネットキャッシュ | K6: =C6 -> 5418490
E7: 減価償却費 | F7: =修正SGA!E33 -> 881300 | G7: =修正SGA!H33 -> 644524 | H7: =修正SGA!K33 -> 1182673 | J7: 想定株式価値 | K7: =SUM(K4:K6) -> 1.1220229e+08 | L7: =SUM(L4:L5)+K6 -> 1.4779689e+08 | M7: =SUM(M4:M5)+K6 -> 1.8339149e+08
E8: 修正後EBITDA | F8: =SUM(F6:F7) -> 5530502.5 | G8: =SUM(G6:G7) -> 67240681 | H8: =SUM(H6:H7) -> 45877481
G10: 基準EBITDA | H10: =AVERAGE(F8:H8) -> 39549555

Sheet 分割後BS
F2: (単位：千円)
B3: 資産の部
B4: 科目 | C4: 修正後BS（分割前） | D4: 分割承継額 | E4: 分割後BS（分割会社） | F4: 新設会社BS
B5: 【流動資産】 | C5: =SUM(C6:C19) -> 226345406 | D5: =SUM(D6:D19) -> -6570163 | E5: =C5+D5 -> 219775243 | F5: =-D5 -> 6570163
B6: 現金及び預金 | C6: ='[1]修正BS(借方)'!E6 -> 193226490 | E6: =C6+D6 -> 193226490 | F6: =-D6 -> 0
B7: 売掛金 | C7: ='[1]修正BS(借方)'!E7 -> 20153150 | E7: =C7+D7 -> 20153150 | F7: =-D7 -> 0
B8: 貸倒引当金 | C8: ='[1]修正BS(借方)'!E8 -> 0 | E8: =C8+D8 -> 0 | F8: =-D8 -> 0
B9: 商品 | C9: ='[1]修正BS(借方)'!E9 -> 204834 | E9: =C9+D9 -> 204834 | F9: =-D9 -> 0
B10: 証紙 | C10: ='[1]修正BS(借方)'!E10 -> 24020 | E10: =C10+D10 -> 24020 | F10: =-D10 -> 0
B11: 前渡金 | C11: ='[1]修正BS(借方)'!E11 -> 12055237 | D11: -6570163 | E11: =C11+D11 -> 5485074 | F11: =-D11 -> 6570163
B12: 前払費用 | C12: ='[1]修正BS(借方)'!E12 -> 640475 | E12: =C12+D12 -> 640475 | F12: =-D12 -> 0
B13: 未収入金 | C13: ='[1]修正BS(借方)'!E13 -> 41200 | E13: =C13+D13 -> 41200 | F13: =-D13 -> 0
E14: =C14+D14 -> 0 | F14: =-D14 -> 0
E15: =C15+D15 -> 0 | F15: =-D15 -> 0
E16: =C16+D16 -> 0 | F16: =-D16 -> 0
E17: =C17+D17 -> 0 | F17: =-D17 -> 0
E18: =C18+D18 -> 0 | F18: =-D18 -> 0
E19: =C19+D19 -> 0 | F19: =-D19 -> 0
B20: 【固定資産】 | C20: =C21+C35+C46 -> 323863136 | D20: =D21+D35+D46 -> -319487968 | E20: =C20+D20 -> 4375168 | F20: =-D20 -> 319487968
B21: ［有形固定資産］ | C21: =SUM(C22:C34) -> 1056920 | D21: =SUM(D22:D34) -> -264868 | E21: =C21+D21 -> 792052 | F21: =-D21 -> 264868
B22: 建物附属設備 | C22: ='[1]修正BS(借方)'!E22 -> 700993 | E22: =C22+D22 -> 700993 | F22: =-D22 -> 0
B23: 車両運搬具 | C23: ='[1]修正BS(借方)'!E23 -> 264868 | D23: =-C23 -> -264868 | E23: =C23+D23 -> 0 | F23: =-D23 -> 264868
B24: 工具器具備品 | C24: ='[1]修正BS(借方)'!E24 -> 91059 | E24: =C24+D24 -> 91059 | F24: =-D24 -> 0
E25: =C25+D25 -> 0 | F25: =-D25 -> 0
E26: =C26+D26 -> 0 | F26: =-D26 -> 0
E27: =C27+D27 -> 0 | F27: =-D27 -> 0
E28: =C28+D28 -> 0 | F28: =-D28 -> 0
E29: =C29+D29 -> 0 | F29: =-D29 -> 0
E30: =C30+D30 -> 0 | F30: =-D30 -> 0
E31: =C31+D31 -> 0 | F31: =-D31 -> 0
E32: =C32+D32 -> 0 | F32: =-D32 -> 0
E33: =C33+D33 -> 0 | F33: =-D33 -> 0
E34: =C34+D34 -> 0 | F34: =-D34 -> 0
B35: ［無形固定資産］ | C35: =SUM(C36:C45) -> 2112001 | D35: =SUM(D36:D45) -> 0 | E35: =C35+D35 -> 2112001 | F35: =-D35 -> 0
B36: ソフトウェア | C36: ='[1]修正BS(借方)'!E36 -> 2112001 | E36: =C36+D36 -> 2112001 | F36: =-D36 -> 0
E37: =C37+D37 -> 0 | F37: =-D37 -> 0
E38: =C38+D38 -> 0 | F38: =-D38 -> 0
E39: =C39+D39 -> 0 | F39: =-D39 -> 0
E40: =C40+D40 -> 0 | F40: =-D40 -> 0
E41: =C41+D41 -> 0 | F41: =-D41 -> 0
E42: =C42+D42 -> 0 | F42: =-D42 -> 0
E43: =C43+D43 -> 0 | F43: =-D43 -> 0
E44: =C44+D44 -> 0 | F44: =-D44 -> 0
E45: =C45+D45 -> 0 | F45: =-D45 -> 0
B46: ［投資その他資産］ | C46: =SUM(C47:C54) -> 320694215 | D46: =SUM(D47:D54) -> -319223100 | E46: =C46+D46 -> 1471115 | F46: =-D46 -> 319223100
B47: 投資有価証券 | C47: ='[1]修正BS(借方)'!E47 -> 275896334 | D47: =-C47 -> -275896334 | E47: =C47+D47 -> 0 | F47: =-D47 -> 275896334
B48: 出資金 | C48: ='[1]修正BS(借方)'!E48 -> 30000 | E48: =C48+D48 -> 30000 | F48: =-D48 -> 0
B49: 敷金 | C49: ='[1]修正BS(借方)'!E49 -> 50000 | E49: =C49+D49 -> 50000 | F49: =-D49 -> 0
B50: 差入保証金 | C50: ='[1]修正BS(借方)'!E50 -> 1263500 | E50: =C50+D50 -> 1263500 | F50: =-D50 -> 0
B51: 預託金 | C51: ='[1]修正BS(借方)'!E51 -> 25040 | E51: =C51+D51 -> 25040 | F51: =-D51 -> 0
B52: 保険積立金 | C52: ='[1]修正BS(借方)'!E52 -> 43326766 | D52: =-C52 -> -43326766 | E52: =C52+D52 -> 0 | F52: =-D52 -> 43326766
B53: 長期前払費用 | C53: ='[1]修正BS(借方)'!E53 -> 102575 | E53: =C53+D53 -> 102575 | F53: =-D53 -> 0
E54: =C54+D54 -> 0 | F54: =-D54 -> 0
B55: 【繰延資産】 | C55: =SUM(C56:C59) -> 0 | D55: =SUM(D56:D59) -> 0 | E55: =C55+D55 -> 0 | F55: =-D55 -> 0
E56: =C56+D56 -> 0 | F56: =-D56 -> 0
E57: =C57+D57 -> 0 | F57: =-D57 -> 0
E58: =C58+D58 -> 0 | F58: =-D58 -> 0
E59: =C59+D59 -> 0 | F59: =-D59 -> 0
B60: 【繰延税金資産】 | C60: ='[1]修正BS(借方)'!E60 -> 0 | E60: =C60+D60 -> 0 | F60: =-D60 -> 0
B61: 資産合計 | C61: =C5+C20+C55+C60 -> 550208542 | D61: =D5+D20+D55+D60 -> -326058131 | E61: =C61+D61 -> 224150411 | F61: =-D61 -> 326058131
B64: 負債の部
B65: 科目 | C65: 修正後BS（分割前） | D65: 分割承継額 | E65: 分割後BS（分割会社） | F65: 新設会社BS
B66: 【流動負債】 | C66: =SUM(C67:C74) -> 70491633 | D66: =SUM(D67:D74) -> 0 | E66: =C66+D66 -> 70491633 | F66: =-D66 -> 0
B67: 買掛金 | C67: ='[1]修正BS(貸方) '!E6 -> 9644516 | E67: =C67+D67 -> 9644516 | F67: =-D67 -> 0
B68: 未払金 | C68: ='[1]修正BS(貸方) '!E7 -> 3947278 | E68: =C68+D68 -> 3947278 | F68: =-D68 -> 0
B69: 未払法人税等 | C69: ='[1]修正BS(貸方) '!E8 -> 2929500 | E69: =C69+D69 -> 2929500 | F69: =-D69 -> 0
B70: 未払消費税等 | C70: ='[1]修正BS(貸方) '!E9 -> 12017600 | E70: =C70+D70 -> 12017600 | F70: =-D70 -> 0
B71: 預り金 | C71: ='[1]修正BS(貸方) '!E10 -> 124739 | E71: =C71+D71 -> 124739 | F71: =-D71 -> 0
B72: 一年以内返済長期借入金 | C72: ='[1]修正BS(貸方) '!E11 -> 41828000 | E72: =C72+D72 -> 41828000 | F72: =-D72 -> 0
E73: =C73+D73 -> 0 | F73: =-D73 -> 0
E74: =C74+D74 -> 0 | F74: =-D74 -> 0
B75: 【固定負債】 | C75: =SUM(C76:C80) -> 145980000 | D75: =SUM(D76:D80) -> 0 | E75: =C75+D75 -> 145980000 | F75: =-D75 -> 0
B76: 長期借入金 | C76: ='[1]修正BS(貸方) '!E19 -> 145980000 | E76: =C76+D76 -> 145980000 | F76: =-D76 -> 0
E77: =C77+D77 -> 0 | F77: =-D77 -> 0
E78: =C78+D78 -> 0 | F78: =-D78 -> 0
E79: =C79+D79 -> 0 | F79: =-D79 -> 0
E80: =C80+D80 -> 0 | F80: =-D80 -> 0
B81: 【繰延税金負債】 | C81: 0 | D81: 0 | E81: =C81+D81 -> 0 | F81: =-D81 -> 0
B82: 負債合計 | C82: =C66+C75+C81 -> 216471633 | D82: =D66+D75+D81 -> 0 | E82: =C82+D82 -> 216471633 | F82: =-D82 -> 0
B84: 純資産の部
B85: 【資本金】 | C85: =SUM(C86:C87) -> 10000000 | D85: =SUM(D86:D87) -> 0 | E85: =C85+D85 -> 10000000 | F85: =-D85 -> 0
B86: 資本金 | C86: ='[1]修正BS(貸方) '!E36 -> 10000000 | E86: =C86+D86 -> 10000000 | F86: =-D86 -> 0
E87: =C87+D87 -> 0 | F87: =-D87 -> 0
B88: 【資本剰余金】 | C88: 0 | D88: 0 | E88: =C88+D88 -> 0 | F88: =-D88 -> 0
B89: 【利益剰余金】 | C89: =SUM(C90:C91) -> 323535909 | D89: =SUM(D90:D91) -> 0 | E89: =C89+D89 -> 323535909 | F89: =-D89 -> 0
B90: 繰越利益剰余金 | C90: ='[1]修正BS(貸方) '!E44 -> 323535909 | E90: =C90+D90 -> 323535909 | F90: =-D90 -> 0
E91: =C91+D91 -> 0 | F91: =-D91 -> 0
B92: 【自己株式】 | C92: 0 | D92: 0 | E92: =C92+D92 -> 0 | F92: =-D92 -> 0
B93: 【評価修正額】 | C93: ='[1]修正BS(貸方) '!E49 -> 201000 | E93: =C93+D93 -> 201000 | F93: =-D93 -> 0
B94: 【分割承継純資産】 | C94: 0 | D94: =分割後BS!D61-D82 -> -326058131 | E94: =C94+D94 -> -326058131 | F94: =-D94 -> 326058131
B95: 純資産合計 | C95: =C85+C88+C89+C92+C93+C94 -> 333736909 | D95: =D85+D88+D89+D92+D93+D94 -> -326058131 | E95: =C95+D95 -> 7678778 | F95: =-D95 -> 326058131
B96: 負債・純資産合計 | C96: =C82+C95 -> 550208542 | D96: =D82+D95 -> -326058131 | E96: =C96+D96 -> 224150411 | F96: =-D96 -> 326058131
B98: バランスチェック | C98: =ROUND(C96,0)=ROUND(C61,0) -> TRUE | D98: =ROUND(D96,0)=ROUND(D61,0) -> TRUE | E98: =ROUND(E96,0)=ROUND(E61,0) -> TRUE | F98: =ROUND(F96,0)=ROUND(F61,0) -> TRUE
B101: 【前提条件】
B102: 1. 本タブは「修正BS(借方)」「修正BS(貸方) 」の修正後残高（令和8年1月期・評価基準日）を分割前BSとしている。
B103: 2. 新設分割により、非事業用資産である投資有価証券275,896千円及び保険積立金43,327千円（計319,223千円）を新設会社へ承継する。
B104: 3. 分割型（人的）分割を前提とし、承継純資産と同額だけ分割会社の純資産が減少するものとしている。
B105: 分社型（物的）分割による場合は、分割会社に新設会社株式が資産計上され純資産は減少しないため、別途、株式の現物配当等が必要となる。
B106: 4. 適格分割（簿価承継）を前提とし、承継資産の含み損益に対する課税は考慮していない。非適格分割となる場合、投資有価証券の含み損益に対し課税が生じる。
B107: 5. 承継資産に対応する負債（借入金等）の承継は想定していない。投資有価証券等が借入金の担保に供されている場合、金融機関の同意及び担保差替えの要否を要確認。
...

Sheet 参照企業
E2: (単位：千円)
B3: 企業名 | C3: 所在地 | D3: 事業内容 | E3: EV/EVIDA倍率
B4: ㈱エスケイジャパン（7608） | C4: 大阪府大阪市 | D4: アミューズメント景品・キャラクター雑貨の企画・製造・販売
B5: ㈱ハピネット（7552） | C5: 東京都台東区 | D5: 玩具・キャラクターグッズ・映像音楽ソフトの企画卸売
B6: ㈱タカラトミー（7867） | C6: 東京都葛飾区 | D6: 玩具・キャラクター商品の企画・製造・販売
B7: ㈱サンリオ（8136） | C7: 東京都品川区 | D7: キャラクターの企画・ライセンス供与、関連商品の企画販売
B8: ㈱ブシロード（7803） | C8: 東京都中野区 | D8: IPの創出・許諾、カードゲーム・キャラクターグッズの企画販売
B9: ㈱KADOKAWA（9468） | C9: 東京都千代田区 | D9: 出版・映像・ゲーム及びIPを活用したライセンス・物販事業
B10: ㈱東映アニメーション（4816） | C10: 東京都中野区 | D10: アニメーション制作、版権許諾・商品化権事業
B11: ㈱IGポート（3791） | C11: 東京都武蔵野市 | D11: アニメーション制作、版権事業・商品販売
B12: ㈱マーベラス（7844） | C12: 東京都品川区 | D12: ゲーム・音楽映像・ライブ及びキャラクターMD事業
B13: ㈱ドウシシャ（7483） | C13: 大阪府大阪市 | D13: 生活用品・キャラクター雑貨の企画開発・卸売
D14: 平均値 | E14: =IFERROR(AVERAGE(E4:E13),"-") -> -
D15: 中央値 | E15: =IFERROR(MEDIAN(E4:E13),"-") -> -
B17: ※ 上記は事業内容・顧客基盤の観点から選定した類似上場会社。EV/EBITDA倍率は算定日時点の株価等に基づき更新のうえ入力する。
B18: ※ 本評価では、国内中小企業M&Aの実務上のボリュームゾーンである3.0～5.0倍を採用している。

Sheet IM→

Sheet 会社概要
B2: 項目 | C2: 内容
B3: 会社名 | C3: 株式会社カナリア
B4: 本社所在地 | C4: 東京都台東区東上野一丁目20番5号 サスガビル4階
B5: 設立 | C5: 2014年2月12日（第12期）
B6: 資本金 | C6: 10,000千円（発行済株式総数1,000株）
B7: 代表者 | C7: 野口 紘（48歳）
B8: 株主 | C8: 野口 紘（1,000株/100.0%）
B9: 事業内容 | C9: ・キャラクターグッズ企画・製造販売事業 （ライセンス／版権商品） ・OEM受託事業
B10: 従業員数 | C10: 10名（うち役員3名、正社員7名）※2026年6月時点
B11: 売上高 | C11: 422,475千円（2026年1月期実績） 443,868千円（2025年1月期実績）
B12: 調整後EBITDA | C12: 43,541千円 （2026年1月期実績） 62,064千円 （2025年1月期実績）
B13: 譲渡理由 | C13: 後継者不在、更なる事業の発展
C16: アニメ・ゲーム版権(IP)を活用したキャラクターグッズの企画・製造・販売、及びOEM受託。自社オリジナルのキャラクターくじ「スターくじ」「あたりツキ！」シリーズを展開。缶バッジ・アクリル・タペストリー・ブランケット・スマホケース・ストラップ・ラバー小物・メガネケース・マグネットシート等、多品目のグッズを取り扱う。製造は中国等海外メーカー及び国内専門メーカーへ委託するファブレス型のB2Bモデル。自社サイト(canaria-tokyo.co.jp)で制作実績・OEMラインナップを公開。

Sheet PLハイライト
E2: (単位：千円)
C3: 2024年1月期 | D3: 2025年1月期 | E3: 2026年1月期 | F3: (該当データなし) | G3: 進行期(令和9年1月期・実績5ヶ月分TB)
B4: 売上高 | C4: =PL!C11 -> 316755490 | D4: =PL!E11 -> 443868051 | E4: =PL!G11 -> 422474507 | F4: =PL!I11 -> 0 | G4: =PL!K11 -> 0
B5: 前期比 | C5: - | D5: =IFERROR(D4/C4,"") -> 1.4012955 | E5: =IFERROR(E4/D4,"") -> 0.95180202 | F5: =IFERROR(F4/E4,"") -> 0 | G5: -
B6: 売上総利益 | C6: =PL!C22 -> 103555273 | D6: =PL!E22 -> 178926351 | E6: =PL!G22 -> 150803272 | F6: =PL!I22 -> 0 | G6: =PL!K22 -> 0
B7: 利益率 | C7: =IFERROR(C6/C4,"") -> 0.32692495 | D7: =IFERROR(D6/D4,"") -> 0.40310707 | E7: =IFERROR(E6/E4,"") -> 0.35695236 | F7: =IFERROR(F6/F4,"") | G7: =IFERROR(G6/G4,"")
B8: 営業利益 | C8: =PL!C24 -> 6159294 | D8: =PL!E24 -> 78190765 | E8: =PL!G24 -> 58513810 | F8: =PL!I24 -> 0 | G8: =PL!K24 -> 0
B9: 利益率 | C9: =IFERROR(C8/C4,"") -> 0.019444948 | D9: =IFERROR(D8/D4,"") -> 0.17615768 | E9: =IFERROR(E8/E4,"") -> 0.13850258 | F9: =IFERROR(F8/F4,"") | G9: =IFERROR(G8/G4,"")
B10: 経常利益 | C10: =PL!C41 -> 6665569 | D10: =PL!E41 -> 89928661 | E10: =PL!G41 -> 64943069 | F10: =PL!I41 -> 0 | G10: =PL!K41 -> 0
B11: 利益率 | C11: =IFERROR(C10/C4,"") -> 0.021043263 | D11: =IFERROR(D10/D4,"") -> 0.20260224 | E11: =IFERROR(E10/E4,"") -> 0.15372068 | F11: =IFERROR(F10/F4,"") | G11: =IFERROR(G10/G4,"")
B12: 税引後当期純利益 | C12: =PL!C61 -> -5170180 | D12: =PL!E61 -> 40557756 | E12: =PL!G61 -> 37630176 | F12: =PL!I61 -> 0 | G12: =PL!K61 -> 0
B13: 利益率 | C13: =IFERROR(C12/C4,"") -> -0.016322306 | D13: =IFERROR(D12/D4,"") -> 0.091373452 | E13: =IFERROR(E12/E4,"") -> 0.08907088 | F13: =IFERROR(F12/F4,"") | G13: =IFERROR(G12/G4,"")
B15: 減価償却費 | C15: 881300 | D15: 644524 | E15: 1182673 | F15: 0 | G15: 0
B17: 調整項目 合計 | C17: =SUM(C18:C26) -> -1510092 | D17: =SUM(D18:D26) -> -11594608 | E17: =SUM(E18:E26) -> -13819002 | F17: =SUM(F18:F26) -> 0 | G17: =SUM(G18:G26) -> 0
B18: 役員報酬（退任予定） | C18: =-修正SGA!D8 -> 2538750 | D18: =-修正SGA!G8 -> 2990000 | E18: =-修正SGA!J5 -> 2990000
B19: 社会保険料 | C19: =-修正SGA!D10 -> 380812 | D19: =-修正SGA!G10 -> 448500 | E19: =-修正SGA!J10 -> 448500
B20: 貸倒引当金繰入額 | C20: =SGA!C35 -> 803000 | D20: =SGA!E35 -> 246000 | E20: =SGA!G35 -> 201000
B21: 寄付金 | C21: =SGA!C32 -> 50000 | D21: =SGA!E32 -> 200000 | E21: =SGA!G32 -> 50000
B22: 棚卸資産廃棄損 （営業費用化） | C22: =PL!C19 -> -6722798 | D22: =PL!E19 -> -17217311 | E22: =PL!G19 -> -19844732
B23: 接待交際費 | C23: =-修正SGA!D15 -> 1440144 | D23: =-修正SGA!G15 -> 1738203 | E23: =-修正SGA!J15 -> 2336230
B36: 調整後EBITDA | C36: =C8+C15+C17 -> 5530502 | D36: =D8+D15+D17 -> 67240681 | E36: =E8+E15+E17 -> 45877481 | F36: =F8+F15+F17 -> 0 | G36: =G8+G15+G17 -> 0

Sheet BSハイライト
F2: (単位：千円)
B3: 2026年1月期
B4: 流動資産 | C4: 226144406 | E4: 流動負債 | F4: =SUM(F5:F10) -> 70491633
B5: 現金及び預金 | C5: 193226490 | E5: 短期借入金 | F5: 41828000
B6: 売掛金 | C6: 20153150 | E6: 買掛金 | F6: 9644516
B7: 貸倒引当金 | C7: -201000 | E7: 未払金 | F7: 3947278
B8: 商品 | C8: 204834 | E8: 未払法人税等 | F8: 2929500
B9: 前渡金 | C9: 12055237 | E9: 未払消費税等 | F9: 12017600
B10: その他 | C10: =C4-SUM(C5:C9) -> 705695 | E10: 預り金 | F10: 124739
B11: 固定資産 | C11: 323863136 | E11: 固定負債 | F11: =SUM(F12) -> 145980000
B12: 建物附属設備 | C12: 700993 | E12: 長期借入金 | F12: 145980000
B13: 車両運搬具 | C13: 264868
B14: 工具器具備品 | C14: 91059 | E14: 負債合計 | F14: =F4+F11 -> 216471633
B15: ソフトウェア | C15: 2112001 | E15: 資本金 | F15: 10000000
B16: 投資有価証券 | C16: 275896334 | E16: 繰越利益剰余金 | F16: 323535909
B17: 保険積立金 | C17: 43326766
B18: 差入保証金 | C18: 1263500
B19: その他 | C19: =C11-SUM(C12:C18) -> 207615
E20: 純資産合計 | F20: =SUM(F15:F19) -> 333535909
B21: 資産合計 | C21: =C4+C11 -> 550007542 | E21: 負債・純資産合計 | F21: =F14+F20 -> 550007542

Sheet 取引先
L2: (単位：千円)
B3: № | C3: 得意先 | D3: 取引内容 | E3: 本社所在地 | F3: 業種等 | G3: 令和6年1月期 | I3: 令和7年1月期 | K3: 令和8年1月期 | M3: 備考
G4: 売上高 | H4: 構成比 | I4: 売上高 | J4: 構成比 | K4: 売上高 | L4: 構成比
B5: 1 | C5: ㈱セガ | D5: キャラクターグッズ商品化(版権使用) | E5: 不明（要確認） | F5: ゲーム・アニメ関連 | G5: 33801606 | H5: =IFERROR(G5/G$16,"-") -> 0.10671198 | I5: 109941383 | J5: =IFERROR(I5/I$16,"-") -> 0.24768934 | K5: 202068680 | L5: =IFERROR(K5/K$16,"-") -> 0.47829792
B6: 2 | C6: ㈱KADOKAWA Game Linkag | D6: キャラクターグッズ商品化(版権使用) | E6: 不明（要確認） | F6: ゲーム・アニメ関連 | G6: 84036762 | H6: =IFERROR(G6/G$16,"-") -> 0.26530483 | I6: 69227005 | J6: =IFERROR(I6/I$16,"-") -> 0.15596303 | K6: 60264237 | L6: =IFERROR(K6/K$16,"-") -> 0.14264585
B7: 3 | C7: ㈱ムービック | D7: キャラクターグッズ商品化(版権使用) | E7: 不明（要確認） | F7: ゲーム・アニメ関連 | G7: 28015124 | H7: =IFERROR(G7/G$16,"-") -> 0.088444005 | I7: 36032647 | J7: =IFERROR(I7/I$16,"-") -> 0.081178735 | K7: 43807641 | L7: =IFERROR(K7/K$16,"-") -> 0.10369298
B8: 4 | C8: ㈱ｽﾓｰﾙﾌﾟﾗﾈｯﾄ | D8: キャラクターグッズ商品化(版権使用) | E8: 不明（要確認） | F8: ゲーム・アニメ関連 | G8: - | H8: =IFERROR(G8/G$16,"-") -> - | I8: - | J8: =IFERROR(I8/I$16,"-") -> - | K8: 42545792 | L8: =IFERROR(K8/K$16,"-") -> 0.10070618
B9: 5 | C9: 杭州迷萌文化創意 | D9: 海外製造委託パートナー | E9: 不明（要確認） | F9: ゲーム・アニメ関連 | G9: 15179525 | H9: =IFERROR(G9/G$16,"-") -> 0.0479219 | I9: 69086138 | J9: =IFERROR(I9/I$16,"-") -> 0.15564567 | K9: 33677325 | L9: =IFERROR(K9/K$16,"-") -> 0.079714455
B10: 6 | C10: ㈱ｿﾙ･インターナショナル | D10: キャラクターグッズ商品化(版権使用) | E10: 不明（要確認） | F10: ゲーム・アニメ関連 | G10: 34096085 | H10: =IFERROR(G10/G$16,"-") -> 0.10764165 | I10: 24321530 | J10: =IFERROR(I10/I$16,"-") -> 0.054794505 | K10: 19081708 | L10: =IFERROR(K10/K$16,"-") -> 0.045166531
B11: 7 | C11: ㈱ケンメディア | D11: キャラクターグッズ商品化(版権使用) | E11: 不明（要確認） | F11: ゲーム・アニメ関連 | G11: 54354381 | H11: =IFERROR(G11/G$16,"-") -> 0.17159728 | I11: 16120455 | J11: =IFERROR(I11/I$16,"-") -> 0.036318124 | K11: 12358967 | L11: =IFERROR(K11/K$16,"-") -> 0.029253758
B12: 8 | C12: ㈱KADOKAWA | D12: キャラクターグッズ商品化(版権使用) | E12: 不明（要確認） | F12: ゲーム・アニメ関連 | G12: 3877760 | H12: =IFERROR(G12/G$16,"-") -> 0.012242124 | I12: - | J12: =IFERROR(I12/I$16,"-") -> - | K12: 2050323 | L12: =IFERROR(K12/K$16,"-") -> 0.0048531283
B13: 9 | C13: ㈱PHP JAPAN | D13: キャラクターグッズ商品化(版権使用) | E13: 不明（要確認） | F13: ゲーム・アニメ関連 | G13: - | H13: =IFERROR(G13/G$16,"-") -> - | I13: 10179051 | J13: =IFERROR(I13/I$16,"-") -> 0.022932606 | K13: 1636230 | L13: =IFERROR(K13/K$16,"-") -> 0.0038729674
B14: 10 | C14: 花禾㈱ | D14: キャラクターグッズ商品化(版権使用) | E14: 不明（要確認） | F14: ゲーム・アニメ関連 | G14: - | H14: =IFERROR(G14/G$16,"-") -> - | I14: - | J14: =IFERROR(I14/I$16,"-") -> - | K14: 1525462 | L14: =IFERROR(K14/K$16,"-") -> 0.0036107788
C15: その他（上位10社圏外の顧客群） | G15: 63394247 | H15: =IFERROR(G15/G$16,"-") -> 0.20013622 | I15: 108959842 | J15: =IFERROR(I15/I$16,"-") -> 0.245478 | K15: 3458142 | L15: =IFERROR(K15/K$16,"-") -> 0.0081854454 | M15: 各期の全社売上高(税抜)から上位10社実績を控除した差引額。上位社の入替りが激しく、直近期の非上位企業も含む
C16: 合計 | G16: =SUM(G5:G15) -> 316755490 | H16: - | I16: =SUM(I5:I15) -> 443868051 | J16: - | K16: =SUM(K5:K15) -> 422474507 | L16: -

Sheet 仕入先
K2: (単位：千円)
B3: № | C3: 仕入先 | D3: 仕入内容 | E3: 本社所在地 | F3: 令和6年1月期 | H3: 令和7年1月期 | J3: 令和8年1月期 | L3: 備考
F4: 仕入高 | G4: 構成比 | H4: 仕入高 | I4: 構成比 | J4: 仕入高 | K4: 構成比
B5: 1 | C5: 非開示（相手先名称は現時点で未提供） | D5: 貿易商社 主に中国製のものを作成依頼 | F5: 96294830 | G5: =IFERROR(F5/F$16,"-") -> 0.46903722 | H5: 172075524 | I5: =IFERROR(H5/H$16,"-") -> 0.54538264 | J5: 122908613 | K5: =IFERROR(J5/J$16,"-") -> 0.41147403
B6: 2 | C6: 非開示（相手先名称は現時点で未提供） | D6: アパレル商品の日本メーカー | F6: - | G6: =IFERROR(F6/F$16,"-") -> - | H6: - | I6: =IFERROR(H6/H$16,"-") -> - | J6: 33755639 | K6: =IFERROR(J6/J$16,"-") -> 0.11300729
B7: 3 | C7: 非開示（相手先名称は現時点で未提供） | D7: アパレル商品の貿易商社 | F7: - | G7: =IFERROR(F7/F$16,"-") -> - | H7: - | I7: =IFERROR(H7/H$16,"-") -> - | J7: 30943171 | K7: =IFERROR(J7/J$16,"-") -> 0.10359169
B8: 4 | C8: 非開示（相手先名称は現時点で未提供） | D8: アクリルの日本メーカー | F8: 40487005 | G8: =IFERROR(F8/F$16,"-") -> 0.19720594 | H8: 24487628 | I8: =IFERROR(H8/H$16,"-") -> 0.077612009 | J8: 27083161 | K8: =IFERROR(J8/J$16,"-") -> 0.090669133
B9: 5 | C9: 非開示（相手先名称は現時点で未提供） | D9: アクリル、缶バッジ、紙類の日本メーカー | F9: 11236641 | G9: =IFERROR(F9/F$16,"-") -> 0.05473194 | H9: 19689920 | I9: =IFERROR(H9/H$16,"-") -> 0.062405973 | J9: 24773941 | K9: =IFERROR(J9/J$16,"-") -> 0.082938316
B10: 6 | C10: 非開示（相手先名称は現時点で未提供） | D10: 成形品、ぬいぐるみの中国メーカー | F10: - | G10: =IFERROR(F10/F$16,"-") -> - | H10: 17563377 | I10: =IFERROR(H10/H$16,"-") -> 0.055666028 | J10: 10979527 | K10: =IFERROR(J10/J$16,"-") -> 0.036757312
B11: 7 | C11: 非開示（相手先名称は現時点で未提供） | D11: 缶バッジの特殊加工の日本メーカー | F11: - | G11: =IFERROR(F11/F$16,"-") -> - | H11: - | I11: =IFERROR(H11/H$16,"-") -> - | J11: 7582630 | K11: =IFERROR(J11/J$16,"-") -> 0.025385164
B12: 8 | C12: 非開示（相手先名称は現時点で未提供） | D12: デジタル機能付きのグッズの日本メーカー | F12: - | G12: =IFERROR(F12/F$16,"-") -> - | H12: - | I12: =IFERROR(H12/H$16,"-") -> - | J12: 5271200 | K12: =IFERROR(J12/J$16,"-") -> 0.017646948
B13: 9 | C13: 非開示（相手先名称は現時点で未提供） | D13: 紙類の日本商社 | F13: 678755 | G13: =IFERROR(F13/F$16,"-") -> 0.0033061106 | H13: 2689881 | I13: =IFERROR(H13/H$16,"-") -> 0.00852541 | J13: 5225159 | K13: =IFERROR(J13/J$16,"-") -> 0.017492812
B14: 10 | C14: 非開示（相手先名称は現時点で未提供） | D14: ロイヤリティー支払い先 | F14: 14347622 | G14: =IFERROR(F14/F$16,"-") -> 0.069885047 | H14: 23586066 | I14: =IFERROR(H14/H$16,"-") -> 0.074754565 | J14: 4906753 | K14: =IFERROR(J14/J$16,"-") -> 0.016426851
C15: その他（上位10項目以外） | F15: 42258322 | G15: =IFERROR(F15/F$16,"-") -> 0.20583375 | H15: 55420992 | I15: =IFERROR(H15/H$16,"-") -> 0.17565338 | J15: 25273414 | K15: =IFERROR(J15/J$16,"-") -> 0.084610454 | L15: 実績表(01_IP/03_営業)は仕入・外注支払の概ね8割程度を捕捉したデータ。上位10項目以外の合計。金額は税込ベース
C16: 合計 | F16: =SUM(F5:F15) -> 205303175 | G16: - | H16: =SUM(H5:H15) -> 315513388 | I16: - | J16: =SUM(J5:J15) -> 298703208 | K16: -

Sheet 外注先
L2: (単位：千円)
B3: № | C3: 外注先 | D3: 外注内容 | E3: 本社所在地 | F3: 業種等 | G3: 令和6年1月期 | I3: 令和7年1月期 | K3: 令和8年1月期 | M3: 備考
G4: 外注費 | H4: 構成比 | I4: 外注費 | J4: 構成比 | K4: 外注費 | L4: 構成比
C5: 外注先別の内訳は仕入先データと一体で管理されており分離不可（01_IP/03_営業「取引先・外注先 実績.xlsx」は仕入・外注を合算した「仕入等支払実績」として提供されている）。実績は「仕入先」シートを参照。製造委託費・外注費のみの分離把握には総勘定元帳等の追加資料が必要。 | H5: =IFERROR(G5/G$16,"-") -> - | J5: =IFERROR(I5/I$16,"-") -> - | L5: =IFERROR(K5/K$16,"-") -> -
H6: =IFERROR(G6/G$16,"-") -> - | J6: =IFERROR(I6/I$16,"-") -> - | L6: =IFERROR(K6/K$16,"-") -> -
H7: =IFERROR(G7/G$16,"-") -> - | J7: =IFERROR(I7/I$16,"-") -> - | L7: =IFERROR(K7/K$16,"-") -> -
H8: =IFERROR(G8/G$16,"-") -> - | J8: =IFERROR(I8/I$16,"-") -> - | L8: =IFERROR(K8/K$16,"-") -> -
H9: =IFERROR(G9/G$16,"-") -> - | J9: =IFERROR(I9/I$16,"-") -> - | L9: =IFERROR(K9/K$16,"-") -> -
H10: =IFERROR(G10/G$16,"-") -> - | J10: =IFERROR(I10/I$16,"-") -> - | L10: =IFERROR(K10/K$16,"-") -> -
H11: =IFERROR(G11/G$16,"-") -> - | J11: =IFERROR(I11/I$16,"-") -> - | L11: =IFERROR(K11/K$16,"-") -> -
H12: =IFERROR(G12/G$16,"-") -> - | J12: =IFERROR(I12/I$16,"-") -> - | L12: =IFERROR(K12/K$16,"-") -> -
H13: =IFERROR(G13/G$16,"-") -> - | J13: =IFERROR(I13/I$16,"-") -> - | L13: =IFERROR(K13/K$16,"-") -> -
H14: =IFERROR(G14/G$16,"-") -> - | J14: =IFERROR(I14/I$16,"-") -> - | L14: =IFERROR(K14/K$16,"-") -> -
H15: =IFERROR(G15/G$16,"-") -> - | J15: =IFERROR(I15/I$16,"-") -> - | L15: =IFERROR(K15/K$16,"-") -> -
C16: 合計 | H16: - | J16: - | L16: -

Sheet 株主
E2: (単位：千円)
B3: № | C3: 氏名 | D3: 役職 | E3: 役員報酬 （2026年1月期） | F3: 保有株式数 | G3: 保有割合 | H3: 備考
B5: 1 | C5: 野口 紘 | D5: 代表取締役 | E5: 21104000 | F5: 1000 | G5: =IFERROR(F5/$F$15,"-") -> 1 | H5: 継続勤務予定
G6: =IFERROR(F6/$F$15,"-") -> 0
G7: =IFERROR(F7/$F$15,"-") -> 0
G8: =IFERROR(F8/$F$15,"-") -> 0
G9: =IFERROR(F9/$F$15,"-") -> 0
G10: =IFERROR(F10/$F$15,"-") -> 0
G11: =IFERROR(F11/$F$15,"-") -> 0
G12: =IFERROR(F12/$F$15,"-") -> 0
G13: =IFERROR(F13/$F$15,"-") -> 0
G14: =IFERROR(F14/$F$15,"-") -> 0
C15: 合計 | E15: =SUM(E5:E14) -> 21104000 | F15: =SUM(F5:F14) -> 1000 | G15: =IFERROR(F15/$F$15,"-") -> 1

Sheet 取締役
F2: (単位：千円)
B3: № | C3: 氏名 | D3: 役職 | E3: 代表者との関係 | F3: 役員報酬 （2026年1月期） | G3: 業務範囲 | H3: 備考
B5: 1 | C5: 野口 紘 | D5: 代表取締役 | E5: 本人 | F5: 21104000 | G5: 経営管理、OEM事業の管掌
B6: 2 | C6: 野口 文枝 | D6: 取締役 | E6: 配偶者 | F6: 1788000 | G6: 業務関与無し | H6: 2025年4月1日就任
B7: 3 | C7: 野口 聰江 | D7: 取締役 | E7: 母 | F7: 1800000 | G7: 業務関与無し | H7: 2025年4月1日就任
C15: 合計 | F15: =SUM(F5:F14) -> 24692000

Sheet 従業員
F2: 基準日→適宜変更 | G2: =TODAY() -> 46237
G3: YYYY/MM/DD | I3: YYYY/MM/DD | M3: （単位：円）
B4: № | C4: 氏名 | D4: イニシャル | E4: 雇用形態 | F4: 性別 | G4: 生年月日 | H4: 年齢 （歳） | I4: 入社年月日 | J4: 勤続年数 （年） | K4: 部署 | L4: 役職 | M4: 2026年5月分 総支給 | N4: ●年夏季賞与 | O4: ●年冬季賞与 | P4: ●年総支給額 | Q4: 備考
B5: 1 | D5: A | E5: 正社員 | F5: 男 | G5: 30897 | H5: =ROUNDDOWN(($G$2-G5)/365,0) -> 42 | I5: 41730 | J5: =ROUNDDOWN(($G$2-I5)/365,0) -> 12 | K5: 制作部 | L5: 部長 | M5: 464600 | N5: 0 | O5: 1691608 | P5: 6820808 | T5: 平均年齢 | U5: =AVERAGE(H5:H11) -> 30.571429
B6: 2 | D6: B | E6: 正社員 | F6: 女 | G6: 31097 | H6: =ROUNDDOWN(($G$2-G6)/365,0) -> 41 | I6: 42217 | J6: =ROUNDDOWN(($G$2-I6)/365,0) -> 11 | K6: 制作部 | L6: 課長 | M6: 413400 | N6: 0 | O6: 772645 | P6: 5349445 | T6: 平均勤続年数 | U6: =AVERAGE(J5:J11) -> 5.4285714
B7: 3 | D7: C | E7: 正社員 | F7: 女 | G7: 34789 | H7: =ROUNDDOWN(($G$2-G7)/365,0) -> 31 | I7: 42828 | J7: =ROUNDDOWN(($G$2-I7)/365,0) -> 9 | K7: 制作部 | M7: 229500 | N7: 0 | O7: 0 | P7: 316929 | Q7: 2026年5月より育休から復帰。
B8: 4 | D8: D | E8: 正社員 | F8: 女 | G8: 36308 | H8: =ROUNDDOWN(($G$2-G8)/365,0) -> 27 | I8: 44531 | J8: =ROUNDDOWN(($G$2-I8)/365,0) -> 4 | K8: 制作部 | L8: 主任 | M8: 347800 | N8: 0 | O8: 1610718 | P8: 5506318
B9: 5 | D9: E | E9: 正社員 | F9: 女 | G9: 38389 | H9: =ROUNDDOWN(($G$2-G9)/365,0) -> 21 | I9: 45748 | J9: =ROUNDDOWN(($G$2-I9)/365,0) -> 1 | K9: 制作部 | M9: 262480 | N9: 0 | O9: 305343 | P9: 3230303
B10: 6 | D10: F | E10: 正社員 | F10: 女 | G10: 36793 | H10: =ROUNDDOWN(($G$2-G10)/365,0) -> 25 | I10: 45809 | J10: =ROUNDDOWN(($G$2-I10)/365,0) -> 1 | K10: 営業部 | M10: 275600 | N10: 0 | O10: 305343 | P10: 3312345
B11: 7 | D11: G | E11: 正社員 | F11: 女 | G11: 36257 | H11: =ROUNDDOWN(($G$2-G11)/365,0) -> 27 | I11: 46113 | J11: =ROUNDDOWN(($G$2-I11)/365,0) -> 0 | K11: 営業部 | M11: 315000 | N11: 0 | O11: 0 | P11: 630000 | Q11: 2026年4月入社。
H12: =ROUNDDOWN(($G$2-G12)/365,0) -> 126 | J12: =ROUNDDOWN(($G$2-I12)/365,0) -> 126
H13: =ROUNDDOWN(($G$2-G13)/365,0) -> 126 | J13: =ROUNDDOWN(($G$2-I13)/365,0) -> 126
H14: =ROUNDDOWN(($G$2-G14)/365,0) -> 126 | J14: =ROUNDDOWN(($G$2-I14)/365,0) -> 126
H15: =ROUNDDOWN(($G$2-G15)/365,0) -> 126 | J15: =ROUNDDOWN(($G$2-I15)/365,0) -> 126
H16: =ROUNDDOWN(($G$2-G16)/365,0) -> 126 | J16: =ROUNDDOWN(($G$2-I16)/365,0) -> 126
H17: =ROUNDDOWN(($G$2-G17)/365,0) -> 126 | J17: =ROUNDDOWN(($G$2-I17)/365,0) -> 126
H18: =ROUNDDOWN(($G$2-G18)/365,0) -> 126 | J18: =ROUNDDOWN(($G$2-I18)/365,0) -> 126
H19: =ROUNDDOWN(($G$2-G19)/365,0) -> 126 | J19: =ROUNDDOWN(($G$2-I19)/365,0) -> 126
H20: =ROUNDDOWN(($G$2-G20)/365,0) -> 126 | J20: =ROUNDDOWN(($G$2-I20)/365,0) -> 126
H21: =ROUNDDOWN(($G$2-G21)/365,0) -> 126 | J21: =ROUNDDOWN(($G$2-I21)/365,0) -> 126
H22: =ROUNDDOWN(($G$2-G22)/365,0) -> 126 | J22: =ROUNDDOWN(($G$2-I22)/365,0) -> 126
H23: =ROUNDDOWN(($G$2-G23)/365,0) -> 126 | J23: =ROUNDDOWN(($G$2-I23)/365,0) -> 126
... H25: =ROUNDDOWN(($G$2-G25)/365,0) -> 126 | J25: =ROUNDDOWN(($G$2-I25)/365,0) -> 126
B26: 22 | H26: =ROUNDDOWN(($G$2-G26)/365,0) -> 126 | J26: =ROUNDDOWN(($G$2-I26)/365,0) -> 126
B27: 23 | H27: =ROUNDDOWN(($G$2-G27)/365,0) -> 126 | J27: =ROUNDDOWN(($G$2-I27)/365,0) -> 126
B28: 24 | H28: =ROUNDDOWN(($G$2-G28)/365,0) -> 126 | J28: =ROUNDDOWN(($G$2-I28)/365,0) -> 126
B29: 25 | H29: =ROUNDDOWN(($G$2-G29)/365,0) -> 126 | J29: =ROUNDDOWN(($G$2-I29)/365,0) -> 126
B30: 26 | H30: =ROUNDDOWN(($G$2-G30)/365,0) -> 126 | J30: =ROUNDDOWN(($G$2-I30)/365,0) -> 126
B31: 27 | H31: =ROUNDDOWN(($G$2-G31)/365,0) -> 126 | J31: =ROUNDDOWN(($G$2-I31)/365,0) -> 126
B32: 28 | H32: =ROUNDDOWN(($G$2-G32)/365,0) -> 126 | J32: =ROUNDDOWN(($G$2-I32)/365,0) -> 126
B33: 29 | H33: =ROUNDDOWN(($G$2-G33)/365,0) -> 126 | J33: =ROUNDDOWN(($G$2-I33)/365,0) -> 126
B34: 30 | H34: =ROUNDDOWN(($G$2-G34)/365,0) -> 126 | J34: =ROUNDDOWN(($G$2-I34)/365,0) -> 126

Sheet 拠点(本社等)
B2: 所在地 | C2: 契約形態 | D2: 延床面積 (㎡) | E2: 月間賃料 (千円) | F2: 敷金 (千円) | G2: アクセス
B3: 東京都台東区東上野一丁目20番5号 サスガビル4階 | C3: 賃借 | D3: 115.7 | E3: 435750 | F3: 1263500 | G3: 仲御徒町駅徒歩4分、上野御徒町駅徒歩6分、 御徒町駅徒歩6分

Sheet 不動産(所有)
I1: 土地は0.7割戻し
B3: 事業所名 | C3: 内容 | D3: 所在地 地番・家屋番号 | E3: 面積 (㎡) | F3: 区分 ・構造 | G3: 所有（建築） 年月・事由 | H3: 前期末簿価 (千円) | I3: 時価 | J3: 固定資産税 評価額 | K3: 備考
C4: 該当なし。BS明細（月次試算表）上、有形固定資産に土地・建物の勘定科目が計上されておらず、附属設備700,993円・車両運搬具264,868円・工具器具備品91,059円のみ。本社は賃借。

Sheet 不動産(賃借) 
B3: 内容 | C3: 内容 | D3: 所在地 地番・家屋番号 | E3: 面積 (㎡) | F3: 契約内容 | G3: 貸主 | H3: 月間賃料 (千円) | I3: 敷金 (千円) | J3: 備考
B4: 本社 | C4: 事務所（サスガビル4階） | D4: 東京都台東区東上野一丁目20番5号 | E4: 不明（要確認） | F4: 普通賃貸借と推定（契約書原本[画像PDF]の目視確認要） | G4: 不明（要確認。契約書原本は画像PDFのため貸主名は未確認） | H4: 458409 | I4: 1263500 | J4: 月間賃料は令和8年1月期PL地代家賃(年5,500,911円)÷12の推定値。敷金はBS差入保証金より。原契約書の目視確認により正確な金額へ要更新

Sheet 設備
B2: № | C2: 科目 | D2: 資産名 | E2: 償却方法 | F2: 取得年 | G2: 取得月 | H2: 耐用年数 | I2: 取得原価 | J2: 期末帳簿価額 | K2: 備考
B3: 1 | C3: 建物附属設備 | D3: パーテション一式 | E3: 定額法 | F3: 2022 | G3: 1 | H3: 15 | I3: 965000 | J3: 700993
B4: 2 | C4: 車両運搬具 | D4: レクサス RXHV | E4: 定率法 | F4: 2019 | G4: 10 | H4: 2 | I4: 5363637 | J4: 1 | K4: 要確認。（私用車の可能性あり）
B5: 3 | C5: 車両運搬具 | D5: FREED HYBRID FF | E5: 定率法 | F5: 2021 | G5: 1 | H5: 6 | I5: 2765228 | J5: 264867 | K5: 要確認。（私用車の可能性あり）
B6: 4 | C6: 工具器具備品 | D6: サーバー Alrit5 | E6: 定率法 | F6: 2022 | G6: 1 | H6: 5 | I6: 872200 | J6: 91059
B7: 5 | C7: ソフトウェア | D7: CAUL RX販売仕入在庫システム | E7: 定額法 | F7: 2024 | G7: 10 | H7: 5 | I7: 2737000 | J7: 2007134
B8: 6 | C8: ソフトウェア | D8: 弥生会計24プロフェッショナル | E8: 定額法 | F8: 2024 | G8: 10 | H8: 5 | I8: 143000 | J8: 104867

Sheet 財務
B2: IMの財務詳細ページのデータは財務入力のシートから流用してください

Sheet その他
A1: 要確認事項・ネクストステップ（本ファイル転記時点の未解消論点）
A2: 1. 譲渡理由：オーナーへの直接ヒアリングが未実施（面談メモ・資料からは確認不可）
A3: 2. 株主構成・持株比率：株主名簿未受領のため不明（登記簿では役員3名のみ判明）
A4: 3. 定款・許認可の有無：未受領（必要資料一覧 項目1・3参照）
A5: 4. 事業別売上高構成（ライセンス商品とOEMの構成比等）：未受領。面談メモにも同様の論点あり
A6: 5. 賃貸借契約の詳細条件：契約書が画像PDFのため月額賃料・敷金以外の更新条件・貸主名等は未確認。PL地代家賃(年5,500,911円)からの推定値で仮置き
A7: 6. 決算書・勘定科目内訳明細・法人税/消費税申告書・減価償却台帳：いずれも画像PDFでOCR未実施。個別科目の特記事項(含み損益等)は目視確認が必要
A8: 7. 投資有価証券残高275,896,334円が資産合計の約50%を占める。事業性資産か非事業性資産(運用資産)かの確認が必要。EBITDA調整・企業価値評価上の重要論点
A9: 8. PLハイライトシートの調整項目「役員報酬(退任予定)20,000千円」がC列(令和6年1月期)に計上されているが、給与台帳では野口紘への役員賞与20,000,000円は令和8年1月期(2025年12月9日支給)分。列位置の確認・修正が必要
A10: 9. 役員報酬水準が低い(代表取締役 月92,000円等)一方、従業員A(制作部部長・勤続13年・年収682万円)の報酬水準が役員を上回る。実質的な経営リソースがAに集中している可能性があり、キーパーソンリスクとして要ヒアリング
A11: 10. 自社オリジナルIP「スターくじ」「あたりツキ！」の売上構成比・権利関係：未確認。版権依存を補う強みとして訴求できる可能性があり、要ヒアリング（面談メモの論点）
A12: 11. 総勘定元帳・社内規程・取引基本契約書・営業活動での提案資料・制作実績資料・進行中の受注残情報：いずれも未受領（必要資料一覧参照）
... A22: ※ 上記IPの著作権は各権利者に帰属。IMのポートフォリオ掲載はNDA下の検討資料としての参考提示。

Sheet スケジュール(横)
B3: TODO | D3: 2月 | U3: 3月 | AZ3: 4月 | CE3: 5月
D4: 12 | E4: 13 | F4: 14 | G4: 15 | H4: 16 | I4: 17 | J4: 18 | K4: 19 | L4: 20 | M4: 21 | N4: 22 | O4: 23 | P4: 24 | Q4: 25 | R4: 26 | S4: 27 | T4: 28 | U4: 1 | V4: 2 | W4: 3 | X4: 4 | Y4: 5 | Z4: 6 | AA4: 7 | AB4: 8 | AC4: 9 | AD4: 10 | AE4: 11 | AF4: 12 | AG4: 13 | AH4: 14 | AI4: 15 | AJ4: 16 | AK4: 17 | AL4: 18 | AM4: 19 | AN4: 20 | AO4: 21 | AP4: 22 | AQ4: 23 | AR4: 24 | AS4: 25 | AT4: 26 | AU4: 27 | AV4: 28 | AW4: 29 | AX4: 30 | AY4: 31 | AZ4: 1 | BA4: 2 | BB4: 3 | BC4: 4 | BD4: 5 | BE4: 6 | BF4: 7 | BG4: 8 | BH4: 9 | BI4: 10 | BJ4: 11 | BK4: 12 | BL4: 13 | BM4: 14 | BN4: 15 | BO4: 16 | BP4: 17 | BQ4: 18 | BR4: 19 | BS4: 20 | BT4: 21 | BU4: 22 | BV4: 23 | BW4: 24 | BX4: 25 | BY4: 26 | BZ4: 27 | CA4: 28 | CB4: 29 | CC4: 30 | CD4: 31 | CE4: 1 | CF4: 2 | CG4: 3 | CH4: 4 | CI4: 5 | CJ4: 6 | CK4: 7 | CL4: 8 | CM4: 9 | CN4: 10 | CO4: 11 | CP4: 12 | CQ4: 13 | CR4: 14 | CS4: 15 | CT4: 16 | CU4: 17 | CV4: 18 | CW4: 19 | CX4: 20 | CY4: 21 | CZ4: 22 | DA4: 23 | DB4: 24 | DC4: 25 | DD4: 26 | DE4: 27 | DF4: 28 | DG4: 29 | DH4: 30 | DI4: 31
B5: 交渉 | C5: TOP面談
C6: LOIドラフト作成
C7: LOI提出
C8: LOI受領(独占交渉権)
B9: DD | C9: DDスコープ・依頼先選定
C10: IRL提出
C11: QAラリー
C12: マネジメントインタビュー | L12: B | AA12: F | AB12: L
C13: DD結果報告 | AX13: F | AY13: L
B14: 契約 | C14: SPA内容調整
C15: SPA締結
C16: CoC対応等
C17: クロージング
C18: 役員変更登記申請
B19: PMI | C19: 従業員・取引先開示
C20: 連帯保証解除等
C21: PMI・グループ連携 | DK21: ● | DL21: 報酬発生

Sheet スケジュール(縦)
B2: スケジュール表
B3: 日付 | C3: 曜日 | D3: 【売主】 ●●●様 | E3: 【買主】 ●●●様 | F3: M&A承継機構
A4: 2025年 | B4: 45931 | C4: =TEXT(B4,"aaa") -> 水 | D4: 本日 お打ち合わせ
B5: =B4+1 -> 45932 | C5: =TEXT(B5,"aaa") -> 木 | E5: TOP面談準備
B6: =B5+1 -> 45933 | C6: =TEXT(B6,"aaa") -> 金 | E6: LOI内容検討 | F6: LOIドラフト提示
B7: =B6+1 -> 45934 | C7: =TEXT(B7,"aaa") -> 土
B8: =B7+1 -> 45935 | C8: =TEXT(B8,"aaa") -> 日
B9: =B8+1 -> 45936 | C9: =TEXT(B9,"aaa") -> 月
B10: =B9+1 -> 45937 | C10: =TEXT(B10,"aaa") -> 火
B11: =B10+1 -> 45938 | C11: =TEXT(B11,"aaa") -> 水 | D11: TOP面談
B12: =B11+1 -> 45939 | C12: =TEXT(B12,"aaa") -> 木
B13: =B12+1 -> 45940 | C13: =TEXT(B13,"aaa") -> 金
B14: =B13+1 -> 45941 | C14: =TEXT(B14,"aaa") -> 土
B15: =B14+1 -> 45942 | C15: =TEXT(B15,"aaa") -> 日
B16: =B15+1 -> 45943 | C16: =TEXT(B16,"aaa") -> 月
B17: =B16+1 -> 45944 | C17: =TEXT(B17,"aaa") -> 火 | E17: LOI提出
B18: =B17+1 -> 45945 | C18: =TEXT(B18,"aaa") -> 水 | E18: DDスコープ・依頼先検討
B19: =B18+1 -> 45946 | C19: =TEXT(B19,"aaa") -> 木
B20: =B19+1 -> 45947 | C20: =TEXT(B20,"aaa") -> 金 | D20: LOI回答(独占交渉権付与) | E20: ※独占交渉権獲得 | F20: LOI内容説明
B21: =B20+1 -> 45948 | C21: =TEXT(B21,"aaa") -> 土
B22: =B21+1 -> 45949 | C22: =TEXT(B22,"aaa") -> 日
B23: =B22+1 -> 45950 | C23: =TEXT(B23,"aaa") -> 月
B24: =B23+1 -> 45951 | C24: =TEXT(B24,"aaa") -> 火
B25: =B24+1 -> 45952 | C25: =TEXT(B25,"aaa") -> 水 | E25: DDスコープ・依頼先確定
B26: =B25+1 -> 45953 | C26: =TEXT(B26,"aaa") -> 木
B27: =B26+1 -> 45954 | C27: =TEXT(B27,"aaa") -> 金
B28: =B27+1 -> 45955 | C28: =TEXT(B28,"aaa") -> 土
B29: =B28+1 -> 45956 | C29: =TEXT(B29,"aaa") -> 日
B30: =B29+1 -> 45957 | C30: =TEXT(B30,"aaa") -> 月 | E30: DDキックオフミーティング
B31: =B30+1 -> 45958 | C31: =TEXT(B31,"aaa") -> 火 | D31: DD資料提出・QA対応 | E31: IRL提出※DD依頼先 | F31: DD資料提出・QA対応
B32: =B31+1 -> 45959 | C32: =TEXT(B32,"aaa") -> 水 | E32: DDQA対応※DD依頼先
B33: =B32+1 -> 45960 | C33: =TEXT(B33,"aaa") -> 木
B34: =B33+1 -> 45961 | C34: =TEXT(B34,"aaa") -> 金
B35: =B34+1 -> 45962 | C35: =TEXT(B35,"aaa") -> 土
B36: =B35+1 -> 45963 | C36: =TEXT(B36,"aaa") -> 日
B37: =B36+1 -> 45964 | C37: =TEXT(B37,"aaa") -> 月
B38: =B37+1 -> 45965 | C38: =TEXT(B38,"aaa") -> 火 | D38: DD資料提出・QA対応 | E38: DDQA対応※DD依頼先 | F38: DD資料提出・QA対応
B39: =B38+1 -> 45966 | C39: =TEXT(B39,"aaa") -> 水
B40: =B39+1 -> 45967 | C40: =TEXT(B40,"aaa") -> 木
B41: =B40+1 -> 45968 | C41: =TEXT(B41,"aaa") -> 金
B42: =B41+1 -> 45969 | C42: =TEXT(B42,"aaa") -> 土
B43: =B42+1 -> 45970 | C43: =TEXT(B43,"aaa") -> 日
B44: =B43+1 -> 45971 | C44: =TEXT(B44,"aaa") -> 月 | D44: DD資料提出・QA対応 | E44: DDQA対応※DD依頼先 | F44: DD資料提出・QA対応
B45: =B44+1 -> 45972 | C45: =TEXT(B45,"aaa") -> 火
B46: =B45+1 -> 45973 | C46: =TEXT(B46,"aaa") -> 水 | D46: DDマネジメントインタビュー
B47: =B46+1 -> 45974 | C47: =TEXT(B47,"aaa") -> 木
B48: =B47+1 -> 45975 | C48: =TEXT(B48,"aaa") -> 金
B49: =B48+1 -> 45976 | C49: =TEXT(B49,"aaa") -> 土
B50: =B49+1 -> 45977 | C50: =TEXT(B50,"aaa") -> 日
B51: =B50+1 -> 45978 | C51: =TEXT(B51,"aaa") -> 月 | E51: SPA内容検討 | F51: SPAドラフト提出
B52: =B51+1 -> 45979 | C52: =TEXT(B52,"aaa") -> 火
B53: =B52+1 -> 45980 | C53: =TEXT(B53,"aaa") -> 水
B54: =B53+1 -> 45981 | C54: =TEXT(B54,"aaa") -> 木
B55: =B54+1 -> 45982 | C55: =TEXT(B55,"aaa") -> 金 | E55: DD結果確認(DD報告会)
B56: =B55+1 -> 45983 | C56: =TEXT(B56,"aaa") -> 土
B57: =B56+1 -> 45984 | C57: =TEXT(B57,"aaa") -> 日
B58: =B57+1 -> 45985 | C58: =TEXT(B58,"aaa") -> 月
B59: =B58+1 -> 45986 | C59: =TEXT(B59,"aaa") -> 火 | E59: SPA案ご提出
B60: =B59+1 -> 45987 | C60: =TEXT(B60,"aaa") -> 水 | D60: SPA調整
B61: =B60+1 -> 45988 | C61: =TEXT(B61,"aaa") -> 木
B62: =B61+1 -> 45989 | C62: =TEXT(B62,"aaa") -> 金
B63: =B62+1 -> 45990 | C63: =TEXT(B63,"aaa") -> 土
B64: =B63+1 -> 45991 | C64: =TEXT(B64,"aaa") -> 日
B65: =B64+1 -> 45992 | C65: =TEXT(B65,"aaa") -> 月 | D65: SPA調整
B66: =B65+1 -> 45993 | C66: =TEXT(B66,"aaa") -> 火
B67: =B66+1 -> 45994 | C67: =TEXT(B67,"aaa") -> 水
B68: =B67+1 -> 45995 | C68: =TEXT(B68,"aaa") -> 木
B69: =B68+1 -> 45996 | C69: =TEXT(B69,"aaa") -> 金
B70: =B69+1 -> 45997 | C70: =TEXT(B70,"aaa") -> 土
B71: =B70+1 -> 45998 | C71: =TEXT(B71,"aaa") -> 日
B72: =B71+1 -> 45999 | C72: =TEXT(B72,"aaa") -> 月 | D72: SPA調整
B73: =B72+1 -> 46000 | C73: =TEXT(B73,"aaa") -> 火
B74: =B73+1 -> 46001 | C74: =TEXT(B74,"aaa") -> 水
B75: =B74+1 -> 46002 | C75: =TEXT(B75,"aaa") -> 木
B76: =B75+1 -> 46003 | C76: =TEXT(B76,"aaa") -> 金 | D76: 株式譲渡契約書締結
B77: =B76+1 -> 46004 | C77: =TEXT(B77,"aaa") -> 土
B78: =B77+1 -> 46005 | C78: =TEXT(B78,"aaa") -> 日
B79: =B78+1 -> 46006 | C79: =TEXT(B79,"aaa") -> 月 | D79: COC対応等 | F79: COC対応等
B80: =B79+1 -> 46007 | C80: =TEXT(B80,"aaa") -> 火
B81: =B80+1 -> 46008 | C81: =TEXT(B81,"aaa") -> 水
B82: =B81+1 -> 46009 | C82: =TEXT(B82,"aaa") -> 木
B83: =B82+1 -> 46010 | C83: =TEXT(B83,"aaa") -> 金 | D83: クロージング（資金決済、株主名簿書換、役員変更登記申請)
B84: =B83+1 -> 46011 | C84: =TEXT(B84,"aaa") -> 土
B85: =B84+1 -> 46012 | C85: =TEXT(B85,"aaa") -> 日
B86: =B85+1 -> 46013 | C86: =TEXT(B86,"aaa") -> 月 | D86: 従業員・取引先への開示、PMI
B87: =B86+1 -> 46014 | C87: =TEXT(B87,"aaa") -> 火
B88: =B87+1 -> 46015 | C88: =TEXT(B88,"aaa") -> 水
B89: =B88+1 -> 46016 | C89: =TEXT(B89,"aaa") -> 木
B90: =B89+1 -> 46017 | C90: =TEXT(B90,"aaa") -> 金
B91: =B90+1 -> 46018 | C91: =TEXT(B91,"aaa") -> 土
B92: =B91+1 -> 46019 | C92: =TEXT(B92,"aaa") -> 日
B93: =B92+1 -> 46020 | C93: =TEXT(B93,"aaa") -> 月
B94: =B93+1 -> 46021 | C94: =TEXT(B94,"aaa") -> 火
B95: =B94+1 -> 46022 | C95: =TEXT(B95,"aaa") -> 水
A96: 2026年 | B96: =B95+1 -> 46023 | C96: =TEXT(B96,"aaa") -> 木
B97: =B96+1 -> 46024 | C97: =TEXT(B97,"aaa") -> 金
B98: =B97+1 -> 46025 | C98: =TEXT(B98,"aaa") -> 土
B99: =B98+1 -> 46026 | C99: =TEXT(B99,"aaa") -> 日
B100: =B99+1 -> 46027 | C100: =TEXT(B100,"aaa") -> 月
B101: =B100+1 -> 46028 | C101: =TEXT(B101,"aaa") -> 火
...

Sheet グラフ
C2: A | D2: B | E2: C | T2: A
B3: 第1四半期 | C3: 50 | D3: 10 | E3: 20 | S3: 第1四半期 | T3: 50
B4: 第2四半期 | C4: 55 | D4: 25 | E4: 22 | S4: 第2四半期 | T4: 55
B5: 第3四半期 | C5: 52 | D5: 45 | E5: 25 | S5: 第3四半期 | T5: 52
B6: 第4四半期 | C6: 50 | D6: 70 | E6: 25 | S6: 第4四半期 | T6: 80
AF16: ｂ
C18: A | D18: B | E18: C
B19: 1ヶ月目 | C19: 100 | D19: 100 | E19: 100 | T19: A
B20: 2ヶ月目 | C20: 105 | D20: 90 | E20: 110 | S20: 第1四半期 | T20: 50
B21: 3か月目 | C21: 110 | D21: 75 | E21: 90 | S21: 第2四半期 | T21: 55
B22: 4か月目 | C22: 115 | D22: 60 | E22: 80 | S22: 第3四半期 | T22: 52
B23: 5か月目 | C23: 120 | D23: 55 | E23: 45 | S23: 第4四半期 | T23: 80
C33: グラフタイトル
B34: A | C34: 60
B35: B | C35: 20
B36: C | C36: 15
B37: D | C37: 5
C51: X | D51: Y | E51: Z
B52: D | C52: 4.3 | D52: 2.4 | E52: 2
B53: C | C53: 2.5 | D53: 4.4 | E53: 2
B54: B | C54: 3.5 | D54: 1.8 | E54: 3
B55: A | C55: 4.5 | D55: 2.8 | E55: 5

Sheet 表
B2: あああ | C2: あああ | D2: あああ | E2: あああ | F2: あああ
B3: あああああ | C3: XXXXX | D3: XXXXX | E3: XXXXX | F3: ああああああああああああああああああああああああああああああああ
B4: あああああ | C4: XXXXX | D4: XXXXX | E4: XXXXX | F4: ああああああああああああああああああああああああああああああああ
B5: あああああ | C5: XXXXX | D5: XXXXX | E5: XXXXX | F5: ああああああああああああああああああああああああああああああああ
B6: あああああ | C6: XXXXX | D6: XXXXX | E6: XXXXX | F6: ああああああああああああああああああああああああああああああああ
B7: あああああ | C7: XXXXX | D7: XXXXX | E7: XXXXX | F7: ああああああああああああああああああああああああああああああああ
B8: あああああ | C8: XXXXX | D8: XXXXX | E8: XXXXX | F8: ああああああああああああああああああああああああああああああああ
B11: あああ | C11: あああ | D11: あああ | E11: あああ | F11: あああ
B12: あああああ | C12: XXXXX | D12: XXXXX | E12: XXXXX | F12: ああああああああああああああああああああああああああああああああ
C13: XXXXX | D13: XXXXX | E13: XXXXX | F13: ああああああああああああああああああああああああああああああああ
B14: あああああ | C14: XXXXX | D14: XXXXX | E14: XXXXX | F14: ああああああああああああああああああああああああああああああああ
C15: XXXXX | D15: XXXXX | E15: XXXXX | F15: ああああああああああああああああああああああああああああああああ
B16: あああああ | C16: XXXXX | D16: XXXXX | E16: XXXXX | F16: ああああああああああああああああああああああああああああああああ
C17: XXXXX | D17: XXXXX | E17: XXXXX | F17: ああああああああああああああああああああああああああああああああ
B20: あああ | C20: あああ | D20: あああ | E20: あああ
B21: あああああ | C21: XXXXX | D21: XXXXX | E21: XXXXX
C22: XXXXX | D22: XXXXX | E22: XXXXX
B23: あああああ | C23: XXXXX | D23: XXXXX | E23: XXXXX
C24: XXXXX | D24: XXXXX | E24: XXXXX
B25: あああああ | C25: XXXXX | D25: XXXXX | E25: XXXXX
C26: XXXXX | D26: XXXXX | E26: XXXXX
B29: あああ | C29: あああ | D29: あああ | E29: あああ
B30: あああああ | C30: XXXXX | D30: XXXXX | E30: XXXXX
C31: XXXXX | D31: XXXXX | E31: XXXXX
B32: あああああ | C32: XXXXX | D32: XXXXX | E32: XXXXX
C33: XXXXX | D33: XXXXX | E33: XXXXX
B34: あああああ | C34: XXXXX | D34: XXXXX | E34: XXXXX
C35: XXXXX | D35: XXXXX | E35: XXXXX
