Workbook

Sheet ルール
B3: 1 | C3: 文字は「游ゴシック」、数字は「Arial」を基本。備考欄などの細かい文章は「游ゴシック Medium」。
B4: 2 | C4: タイトル、合計欄は太字
B5: 3 | C5: 数字は円単位で入力、表示は千円単位に設定済み
B6: 4 | C6: 基本の背景は以下の通り。紺、水色、グレー、白、青。パレットの上部の色。
C8: 線は紺か白か青。
C10: 資産の部
C11: 科目 | D11: ='BS(借方)'!F10 -> 0 | E11: 調整額 | F11: 調整後
C12: 【流動資産】 | D12: =SUM(D13:D26) -> 5000000 | E12: =SUM(E13:E26) -> -500000 | F12: =SUM(F13:F26) -> 4500000
C13: 現金及び預金 | D13: 5000000 | E13: -500000 | F13: =D13+E13 -> 4500000
F14: =D14+E14 -> 0

Sheet 財務入力→

Sheet BS(借方)
C1: ←基本的にはここをつかう→
C2: 1期目 | D2: 2期目 | E2: 3期目 | F2: （4期目） | G2: 進行期
B3: 資産の部
B4: 科目 | C4: 23年12月期 | D4: 24年12月期 | E4: 25年12月期 | F4: ●●年●月期 | G4: ●●年●月 （●か月TB）
B5: 【流動資産】 | C5: =SUM(C6:C19) -> 119157017 | D5: =SUM(D6:D19) -> 130777358 | E5: =SUM(E6:E19) -> 141385419 | F5: =SUM(F6:F19) -> 0 | G5: =SUM(G6:G19) -> 0
B6: 現金及び預金 | C6: 40642580 | D6: 48852895 | E6: 61842402
B7: 商品 | C7: 32079836 | D7: 30240016 | E7: 26584168
B8: 貯蔵品 | C8: 652076 | D8: 580343 | E8: 619688
B9: 前払費用 | C9: 161700 | D9: 161700 | E9: 161700
B10: 未収入金 | C10: 45757825 | D10: 49800104 | E10: 52401281
B11: 貸倒引当金 | C11: -457000 | D11: -498000 | E11: -524000
B12: 仮払金 | E12: 180
B13: 前払金 | C13: 320000 | D13: 330000 | E13: 300000
B14: 未収還付法人税等 | D14: 1310300
B20: 【固定資産】 | C20: =C21+C35+C46 -> 22989981 | D20: =D21+D35+D46 -> 23828405 | E20: =E21+E35+E46 -> 19843083 | F20: =F21+F35+F46 -> 0 | G20: =G21+G35+G46 -> 0
B21: ［有形固定資産］ | C21: =SUM(C22:C34) -> 12240330 | D21: =SUM(D22:D34) -> 9518592 | E21: =SUM(E22:E34) -> 7402395 | F21: =SUM(F22:F34) -> 0 | G21: =SUM(G22:G34) -> 0
B22: 建物附属設備 | C22: 7282837 | D22: 6298675 | E22: 5361688
B23: 工具器具備品 | C23: 4957493 | D23: 3219917 | E23: 2040707
B35: ［無形固定資産］ | C35: =SUM(C36:C45) -> 3084273 | D35: =SUM(D36:D45) -> 7222851 | E35: =SUM(E36:E45) -> 4816004 | F35: =SUM(F36:F45) -> 0 | G35: =SUM(G36:G45) -> 0
B36: ソフトウェア | C36: 3084273 | D36: 7222851 | E36: 4816004
B46: ［投資その他資産］ | C46: =SUM(C47:C55) -> 7665378 | D46: =SUM(D47:D55) -> 7086962 | E46: =SUM(E47:E55) -> 7624684 | F46: =SUM(F47:F55) -> 0 | G46: =SUM(G47:G55) -> 0
B47: 差入保証金 | C47: 6513280 | D47: 6513280 | E47: 6639280
B48: 長期前払費用 | C48: 1152098 | D48: 573682 | E48: 985404
B56: 【繰延資産】 | C56: =SUM(C57:C60) -> 0 | D56: =SUM(D57:D60) -> 0 | E56: =SUM(E57:E60) -> 0 | F56: =SUM(F57:F60) -> 0 | G56: =SUM(G57:G60) -> 0
B61: 資産合計 | C61: =C5+C20+C56 -> 142146998 | D61: =D5+D20+D56 -> 154605763 | E61: =E5+E20+E56 -> 161228502 | F61: =F5+F20+F56 -> 0 | G61: =G5+G20+G56 -> 0
B63: バランスチェック | C63: =EXACT(C61,'BS (貸方)'!C51) -> TRUE | D63: =EXACT(D61,'BS (貸方)'!D51) -> TRUE | E63: =EXACT(E61,'BS (貸方)'!E51) -> TRUE | F63: =EXACT(F61,'BS (貸方)'!F51) -> TRUE | G63: =EXACT(G61,'BS (貸方)'!G51) -> TRUE

Sheet BS (貸方)
E2: (単位：千円)
B3: 負債の部
B4: 科目 | C4: ='BS(借方)'!C4 -> 23年12月期 | D4: ='BS(借方)'!D4 -> 24年12月期 | E4: ='BS(借方)'!E4 -> 25年12月期 | F4: ='BS(借方)'!F4 -> ●●年●月期 | G4: ='BS(借方)'!G4 -> ●●年●月 （●か月TB）
B5: 【流動負債】 | C5: =SUM(C6:C17) -> 40847644 | D5: =SUM(D6:D17) -> 44626188 | E5: =SUM(E6:E17) -> 41577715 | F5: =SUM(F6:F17) -> 0 | G5: =SUM(G6:G17) -> 0
B6: 買掛金 | C6: 23388161 | D6: 32912766 | E6: 26935462
B7: 短期借入金 | C7: 8000000 | D7: 8000000 | E7: 8000000
B8: 未払金 | C8: 3614783 | D8: 3648822 | E8: 3541353
B9: 未払法人税等 | C9: 5844700 | D9: 64600 | E9: 3100900
B18: 【固定負債】 | C18: =SUM(C19:C24) -> 47200000 | D18: =SUM(D19:D24) -> 47200000 | E18: =SUM(E19:E24) -> 47200000 | F18: =SUM(F19:F24) -> 0 | G18: =SUM(G19:G24) -> 0
B19: 長期借入金 | C19: 47200000 | D19: 47200000 | E19: 47200000
B25: 負債合計 | C25: =C5+C18 -> 88047644 | D25: =D5+D18 -> 91826188 | E25: =E5+E18 -> 88777715 | F25: =F5+F18 -> 0 | G25: =G5+G18 -> 0
B34: 純資産の部
B35: 【資本金】 | C35: =SUM(C36:C38) -> 9000000 | D35: =SUM(D36:D38) -> 9000000 | E35: =SUM(E36:E38) -> 9000000 | F35: =SUM(F36:F38) -> 0 | G35: =SUM(G36:G38) -> 0
B36: 資本金 | C36: 9000000 | D36: 9000000 | E36: 9000000
B39: 【資本剰余金】 | C39: =SUM(C40:C42) -> 1000000 | D39: =SUM(D40:D42) -> 1000000 | E39: =SUM(E40:E42) -> 1000000 | F39: =SUM(F40:F42) -> 0 | G39: =SUM(G40:G42) -> 0
B40: 資本準備金 | C40: 1000000 | D40: 1000000 | E40: 1000000
B43: 【利益剰余金】 | C43: =SUM(C44:C48) -> 44099354 | D43: =SUM(D44:D48) -> 52779575 | E43: =SUM(E44:E48) -> 62450787 | F43: =SUM(F44:F48) -> 0 | G43: =SUM(G44:G48) -> 0
B44: 繰越利益剰余金 | C44: 44099354 | D44: 52779575 | E44: 62450787
B49: 【自己株式】 | C49: 0 | D49: 0 | E49: 0 | F49: 0 | G49: 0
B50: 純資産合計 | C50: =C35+C39+C43+C49 -> 54099354 | D50: =D35+D39+D43+D49 -> 62779575 | E50: =E35+E39+E43+E49 -> 72450787 | F50: =F35+F39+F43+F49 -> 0 | G50: =G35+G39+G43+G49 -> 0
B51: 負債・純資産合計 | C51: =C25+C50 -> 142146998 | D51: =D25+D50 -> 154605763 | E51: =E25+E50 -> 161228502 | F51: =F25+F50 -> 0 | G51: =G25+G50 -> 0
B53: バランスチェック | C53: =EXACT(C51,'BS(借方)'!C61) -> TRUE | D53: =EXACT(D51,'BS(借方)'!D61) -> TRUE | E53: =EXACT(E51,'BS(借方)'!E61) -> TRUE | F53: =EXACT(F51,'BS(借方)'!F61) -> TRUE | G53: =EXACT(G51,'BS(借方)'!G61) -> TRUE

Sheet PL
H2: (単位：千円)
B3: 科目 | C3: ='BS(借方)'!C4 -> 23年12月期 | E3: ='BS(借方)'!D4 -> 24年12月期 | G3: ='BS(借方)'!E4 -> 25年12月期 | I3: ='BS(借方)'!F4 -> ●●年●月期 | K3: ='BS(借方)'!G4 -> ●●年●月 （●か月TB）
C4: 帳簿価額 | D4: 売上高比 | E4: 帳簿価額 | F4: 売上高比 | G4: 帳簿価額 | H4: 売上高比 | I4: 帳簿価額 | J4: 売上高比 | K4: 帳簿価額 | L4: 売上高比
B5: 売上高 | C5: 325866987 | D5: =IF(C5=0,"",C5/C$11) -> 1 | E5: 346561600 | F5: =IF(E5=0,"",E5/E$11) -> 1 | G5: 357540639 | H5: =IF(G5=0,"",G5/G$11) -> 1 | J5: =IF(I5=0,"",I5/I$11) | L5: =IF(K5=0,"",K5/K$11)
D6: =IF(C6=0,"",C6/C$11) | F6: =IF(E6=0,"",E6/E$11) | H6: =IF(G6=0,"",G6/G$11) | J6: =IF(I6=0,"",I6/I$11) | L6: =IF(K6=0,"",K6/K$11)
D7: =IF(C7=0,"",C7/C$11) | F7: =IF(E7=0,"",E7/E$11) | H7: =IF(G7=0,"",G7/G$11) | J7: =IF(I7=0,"",I7/I$11) | L7: =IF(K7=0,"",K7/K$11)
D8: =IF(C8=0,"",C8/C$11) | F8: =IF(E8=0,"",E8/E$11) | H8: =IF(G8=0,"",G8/G$11) | J8: =IF(I8=0,"",I8/I$11) | L8: =IF(K8=0,"",K8/K$11)
D9: =IF(C9=0,"",C9/C$11) | F9: =IF(E9=0,"",E9/E$11) | H9: =IF(G9=0,"",G9/G$11) | J9: =IF(I9=0,"",I9/I$11) | L9: =IF(K9=0,"",K9/K$11)
D10: =IF(C10=0,"",C10/C$11) | F10: =IF(E10=0,"",E10/E$11) | H10: =IF(G10=0,"",G10/G$11) | J10: =IF(I10=0,"",I10/I$11) | L10: =IF(K10=0,"",K10/K$11)
B11: 売上高 | C11: =SUM(C5:C10) -> 325866987 | D11: =IF(C11=0,"",C11/C$11) -> 1 | E11: =SUM(E5:E10) -> 346561600 | F11: =IF(E11=0,"",E11/E$11) -> 1 | G11: =SUM(G5:G10) -> 357540639 | H11: =IF(G11=0,"",G11/G$11) -> 1 | I11: =SUM(I5:I10) -> 0 | J11: =IF(I11=0,"",I11/I$11) | K11: =SUM(K5:K10) -> 0 | L11: =IF(K11=0,"",K11/K$11)
B12: 期首商品棚卸高 | C12: 28930577 | D12: =IF(C12=0,"",C12/C$11) -> 0.088780325 | E12: 32079836 | F12: =IF(E12=0,"",E12/E$11) -> 0.092566043 | G12: 30240016 | H12: =IF(G12=0,"",G12/G$11) -> 0.084577843 | J12: =IF(I12=0,"",I12/I$11) | L12: =IF(K12=0,"",K12/K$11)
B13: 当期商品仕入高 | C13: 162685310 | D13: =IF(C13=0,"",C13/C$11) -> 0.49923839 | E13: 179686065 | F13: =IF(E13=0,"",E13/E$11) -> 0.51848233 | G13: 193114742 | H13: =IF(G13=0,"",G13/G$11) -> 0.5401197 | J13: =IF(I13=0,"",I13/I$11) | L13: =IF(K13=0,"",K13/K$11)
B14: 仕入値引戻し高 | C14: -18920 | D14: =IF(C14=0,"",C14/C$11) -> -5.8060499e-05 | F14: =IF(E14=0,"",E14/E$11) | H14: =IF(G14=0,"",G14/G$11) | J14: =IF(I14=0,"",I14/I$11) | L14: =IF(K14=0,"",K14/K$11)
B15: 期末商品棚卸高 | C15: -32079836 | D15: =IF(C15=0,"",C15/C$11) -> -0.098444572 | E15: -30240016 | F15: =IF(E15=0,"",E15/E$11) -> -0.087257261 | G15: -26584168 | H15: =IF(G15=0,"",G15/G$11) -> -0.074352857 | J15: =IF(I15=0,"",I15/I$11) | L15: =IF(K15=0,"",K15/K$11)
B16: 売上原価 | C16: =SUM(C12:C15) -> 159517131 | D16: =IF(C16=0,"",C16/C$11) -> 0.48951608 | E16: =SUM(E12:E15) -> 181525885 | F16: =IF(E16=0,"",E16/E$11) -> 0.52379111 | G16: =SUM(G12:G15) -> 196770590 | H16: =IF(G16=0,"",G16/G$11) -> 0.55034468 | I16: =SUM(I12:I15) -> 0 | J16: =IF(I16=0,"",I16/I$11) | K16: =SUM(K12:K15) -> 0 | L16: =IF(K16=0,"",K16/K$11)
B17: 売上総利益 | C17: =C11-C16 -> 166349856 | D17: =IF(C17=0,"",C17/C$11) -> 0.51048392 | E17: =E11-E16 -> 165035715 | F17: =IF(E17=0,"",E17/E$11) -> 0.47620889 | G17: =G11-G16 -> 160770049 | H17: =IF(G17=0,"",G17/G$11) -> 0.44965532 | I17: =I11-I16 -> 0 | J17: =IF(I17=0,"",I17/I$11) | K17: =K11-K16 -> 0 | L17: =IF(K17=0,"",K17/K$11)
B18: 販売費及び一般管理費 | C18: =SGA!C40 -> 145464229 | D18: =IF(C18=0,"",C18/C$11) -> 0.44639143 | E18: =SGA!E40 -> 154261272 | F18: =IF(E18=0,"",E18/E$11) -> 0.44511934 | G18: =SGA!G40 -> 147845764 | H18: =IF(G18=0,"",G18/G$11) -> 0.41350758 | I18: =SGA!I40 -> 0 | J18: =IF(I18=0,"",I18/I$11) | K18: =SGA!K40 -> 0 | L18: =IF(K18=0,"",K18/K$11)
B19: 営業利益 | C19: =C17- C18 -> 20885627 | D19: =IF(C19=0,"",C19/C$11) -> 0.064092491 | E19: =E17- E18 -> 10774443 | F19: =IF(E19=0,"",E19/E$11) -> 0.031089547 | G19: =G17- G18 -> 12924285 | H19: =IF(G19=0,"",G19/G$11) -> 0.036147737 | I19: =I17- I18 -> 0 | J19: =IF(I19=0,"",I19/I$11) | K19: =K17- K18 -> 0 | L19: =IF(K19=0,"",K19/K$11)
B20: 営業外収益 | C20: =SUM(C21:C27) -> 1273342 | D20: =IF(C20=0,"",C20/C$11) -> 0.0039075514 | E20: =SUM(E21:E27) -> 2398375 | F20: =IF(E20=0,"",E20/E$11) -> 0.0069204869 | G20: =SUM(G21:G27) -> 1051276 | H20: =IF(G20=0,"",G20/G$11) -> 0.0029402979 | I20: =SUM(I21:I27) -> 0 | J20: =IF(I20=0,"",I20/I$11) | K20: =SUM(K21:K27) -> 0 | L20: =IF(K20=0,"",K20/K$11)
B21: 受取利息 | C21: 292 | D21: =IF(C21=0,"",C21/C$11) -> 8.9607113e-07 | E21: 3285 | F21: =IF(E21=0,"",E21/E$11) -> 9.4788344e-06 | G21: 76490 | H21: =IF(G21=0,"",G21/G$11) -> 0.00021393372 | J21: =IF(I21=0,"",I21/I$11) | L21: =IF(K21=0,"",K21/K$11)
B22: 仕入割引 | C22: 211750 | D22: =IF(C22=0,"",C22/C$11) -> 0.00064980501 | E22: 52250 | F22: =IF(E22=0,"",E22/E$11) -> 0.00015076685 | H22: =IF(G22=0,"",G22/G$11) | J22: =IF(I22=0,"",I22/I$11) | L22: =IF(K22=0,"",K22/K$11)
B23: 貸倒引当金戻入額 | C23: 448000 | D23: =IF(C23=0,"",C23/C$11) -> 0.0013747941 | E23: 457000 | F23: =IF(E23=0,"",E23/E$11) -> 0.0013186689 | G23: 498000 | H23: =IF(G23=0,"",G23/G$11) -> 0.0013928487 | J23: =IF(I23=0,"",I23/I$11) | L23: =IF(K23=0,"",K23/K$11)
B24: 雑収入 | C24: 613300 | D24: =IF(C24=0,"",C24/C$11) -> 0.0018820563 | E24: 1885840 | F24: =IF(E24=0,"",E24/E$11) -> 0.0054415723 | G24: 476786 | H24: =IF(G24=0,"",G24/G$11) -> 0.0013335155 | J24: =IF(I24=0,"",I24/I$11) | L24: =IF(K24=0,"",K24/K$11)
D25: =IF(C25=0,"",C25/C$11) | F25: =IF(E25=0,"",E25/E$11) | H25: =IF(G25=0,"",G25/G$11) | J25: =IF(I25=0,"",I25/I$11) | L25: =IF(K25=0,"",K25/K$11)
D26: =IF(C26=0,"",C26/C$11) | F26: =IF(E26=0,"",E26/E$11) | H26: =IF(G26=0,"",G26/G$11) | J26: =IF(I26=0,"",I26/I$11) | L26: =IF(K26=0,"",K26/K$11)
D27: =IF(C27=0,"",C27/C$11) | F27: =IF(E27=0,"",E27/E$11) | H27: =IF(G27=0,"",G27/G$11) | J27: =IF(I27=0,"",I27/I$11) | L27: =IF(K27=0,"",K27/K$11)
B28: 営業外費用 | C28: =SUM(C29:C35) -> 230000 | D28: =IF(C28=0,"",C28/C$11) -> 0.00070580945 | E28: =SUM(E29:E35) -> 2287900 | F28: =IF(E28=0,"",E28/E$11) -> 0.0066017124 | G28: =SUM(G29:G35) -> 90040 | H28: =IF(G28=0,"",G28/G$11) -> 0.00025183151 | I28: =SUM(I29:I35) -> 0 | J28: =IF(I28=0,"",I28/I$11) | K28: =SUM(K29:K35) -> 0 | L28: =IF(K28=0,"",K28/K$11)
B29: 支払利息 | C29: 80000 | D29: =IF(C29=0,"",C29/C$11) -> 0.00024549894 | E29: 80000 | F29: =IF(E29=0,"",E29/E$11) -> 0.00023083919 | G29: 80000 | H29: =IF(G29=0,"",G29/G$11) -> 0.00022375079 | J29: =IF(I29=0,"",I29/I$11) | L29: =IF(K29=0,"",K29/K$11)
B30: 雑損失 | C30: 150000 | D30: =IF(C30=0,"",C30/C$11) -> 0.00046031051 | E30: 1649900 | F30: =IF(E30=0,"",E30/E$11) -> 0.0047607698 | G30: 10040 | H30: =IF(G30=0,"",G30/G$11) -> 2.8080724e-05 | J30: =IF(I30=0,"",I30/I$11) | L30: =IF(K30=0,"",K30/K$11)
B31: 固定資産圧縮損 | D31: =IF(C31=0,"",C31/C$11) | E31: 558000 | F31: =IF(E31=0,"",E31/E$11) -> 0.0016101034 | H31: =IF(G31=0,"",G31/G$11) | J31: =IF(I31=0,"",I31/I$11) | L31: =IF(K31=0,"",K31/K$11)
D32: =IF(C32=0,"",C32/C$11) | F32: =IF(E32=0,"",E32/E$11) | H32: =IF(G32=0,"",G32/G$11) | J32: =IF(I32=0,"",I32/I$11) | L32: =IF(K32=0,"",K32/K$11)
D33: =IF(C33=0,"",C33/C$11) | F33: =IF(E33=0,"",E33/E$11) | H33: =IF(G33=0,"",G33/G$11) | J33: =IF(I33=0,"",I33/I$11) | L33: =IF(K33=0,"",K33/K$11)
D34: =IF(C34=0,"",C34/C$11) | F34: =IF(E34=0,"",E34/E$11) | H34: =IF(G34=0,"",G34/G$11) | J34: =IF(I34=0,"",I34/I$11) | L34: =IF(K34=0,"",K34/K$11)
D35: =IF(C35=0,"",C35/C$11) | F35: =IF(E35=0,"",E35/E$11) | H35: =IF(G35=0,"",G35/G$11) | J35: =IF(I35=0,"",I35/I$11) | L35: =IF(K35=0,"",K35/K$11)
B36: 経常利益 | C36: =C19+C20-C28 -> 21928969 | D36: =IF(C36=0,"",C36/C$11) -> 0.067294233 | E36: =E19+E20-E28 -> 10884918 | F36: =IF(E36=0,"",E36/E$11) -> 0.031408321 | G36: =G19+G20-G28 -> 13885521 | H36: =IF(G36=0,"",G36/G$11) -> 0.038836203 | I36: =I19+I20-I28 -> 0 | J36: =IF(I36=0,"",I36/I$11) | K36: =K19+K20-K28 -> 0 | L36: =IF(K36=0,"",K36/K$11)
B37: 特別利益 | C37: =SUM(C38:C43) -> 0 | D37: =IF(C37=0,"",C37/C$11) | E37: =SUM(E38:E43) -> 0 | F37: =IF(E37=0,"",E37/E$11) | G37: =SUM(G38:G43) -> 0 | H37: =IF(G37=0,"",G37/G$11) | I37: =SUM(I38:I43) -> 0 | J37: =IF(I37=0,"",I37/I$11) | K37: =SUM(K38:K43) -> 0 | L37: =IF(K37=0,"",K37/K$11)
D38: =IF(C38=0,"",C38/C$11) | F38: =IF(E38=0,"",E38/E$11) | H38: =IF(G38=0,"",G38/G$11) | J38: =IF(I38=0,"",I38/I$11) | L38: =IF(K38=0,"",K38/K$11)
D39: =IF(C39=0,"",C39/C$11) | F39: =IF(E39=0,"",E39/E$11) | H39: =IF(G39=0,"",G39/G$11) | J39: =IF(I39=0,"",I39/I$11) | L39: =IF(K39=0,"",K39/K$11)
D40: =IF(C40=0,"",C40/C$11) | F40: =IF(E40=0,"",E40/E$11) | H40: =IF(G40=0,"",G40/G$11) | J40: =IF(I40=0,"",I40/I$11) | L40: =IF(K40=0,"",K40/K$11)
D41: =IF(C41=0,"",C41/C$11) | F41: =IF(E41=0,"",E41/E$11) | H41: =IF(G41=0,"",G41/G$11) | J41: =IF(I41=0,"",I41/I$11) | L41: =IF(K41=0,"",K41/K$11)
D42: =IF(C42=0,"",C42/C$11) | F42: =IF(E42=0,"",E42/E$11) | H42: =IF(G42=0,"",G42/G$11) | J42: =IF(I42=0,"",I42/I$11) | L42: =IF(K42=0,"",K42/K$11)
D43: =IF(C43=0,"",C43/C$11) | F43: =IF(E43=0,"",E43/E$11) | H43: =IF(G43=0,"",G43/G$11) | J43: =IF(I43=0,"",I43/I$11) | L43: =IF(K43=0,"",K43/K$11)
B44: 特別損失 | C44: =SUM(C45:C50) -> 44117 | D44: =IF(C44=0,"",C44/C$11) -> 0.00013538346 | E44: =SUM(E45:E50) -> 0 | F44: =IF(E44=0,"",E44/E$11) | G44: =SUM(G45:G50) -> 0 | H44: =IF(G44=0,"",G44/G$11) | I44: =SUM(I45:I50) -> 0 | J44: =IF(I44=0,"",I44/I$11) | K44: =SUM(K45:K50) -> 0 | L44: =IF(K44=0,"",K44/K$11)
B45: 固定資産除却損 | C45: 44117 | D45: =IF(C45=0,"",C45/C$11) -> 0.00013538346 | F45: =IF(E45=0,"",E45/E$11) | H45: =IF(G45=0,"",G45/G$11) | J45: =IF(I45=0,"",I45/I$11) | L45: =IF(K45=0,"",K45/K$11)
D46: =IF(C46=0,"",C46/C$11) | F46: =IF(E46=0,"",E46/E$11) | H46: =IF(G46=0,"",G46/G$11) | J46: =IF(I46=0,"",I46/I$11) | L46: =IF(K46=0,"",K46/K$11)
D47: =IF(C47=0,"",C47/C$11) | F47: =IF(E47=0,"",E47/E$11) | H47: =IF(G47=0,"",G47/G$11) | J47: =IF(I47=0,"",I47/I$11) | L47: =IF(K47=0,"",K47/K$11)
D48: =IF(C48=0,"",C48/C$11) | F48: =IF(E48=0,"",E48/E$11) | H48: =IF(G48=0,"",G48/G$11) | J48: =IF(I48=0,"",I48/I$11) | L48: =IF(K48=0,"",K48/K$11)
D49: =IF(C49=0,"",C49/C$11) | F49: =IF(E49=0,"",E49/E$11) | H49: =IF(G49=0,"",G49/G$11) | J49: =IF(I49=0,"",I49/I$11) | L49: =IF(K49=0,"",K49/K$11)
D50: =IF(C50=0,"",C50/C$11) | F50: =IF(E50=0,"",E50/E$11) | H50: =IF(G50=0,"",G50/G$11) | J50: =IF(I50=0,"",I50/I$11) | L50: =IF(K50=0,"",K50/K$11)
B51: 税引前当期純利益 | C51: =C36+C37-C44 -> 21884852 | D51: =IF(C51=0,"",C51/C$11) -> 0.06715885 | E51: =E36+E37-E44 -> 10884918 | F51: =IF(E51=0,"",E51/E$11) -> 0.031408321 | G51: =G36+G37-G44 -> 13885521 | H51: =IF(G51=0,"",G51/G$11) -> 0.038836203 | I51: =I36+I37-I44 -> 0 | J51: =IF(I51=0,"",I51/I$11) | K51: =K36+K37-K44 -> 0 | L51: =IF(K51=0,"",K51/K$11)
B52: 法人税等 | C52: =SUM(C53:C55) -> 6900842 | D52: =IF(C52=0,"",C52/C$11) -> 0.021176867 | E52: =SUM(E53:E55) -> 2204697 | F52: =IF(E52=0,"",E52/E$11) -> 0.0063616309 | G52: =SUM(G53:G55) -> 4214309 | H52: =IF(G52=0,"",G52/G$11) -> 0.011786937 | I52: =SUM(I53:I55) -> 0 | J52: =IF(I52=0,"",I52/I$11) | K52: =SUM(K53:K55) -> 0 | L52: =IF(K52=0,"",K52/K$11)
B53: 法人税等 | C53: 6900842 | D53: =IF(C53=0,"",C53/C$11) -> 0.021176867 | E53: 2204697 | F53: =IF(E53=0,"",E53/E$11) -> 0.0063616309 | G53: 4214309 | H53: =IF(G53=0,"",G53/G$11) -> 0.011786937 | J53: =IF(I53=0,"",I53/I$11) | L53: =IF(K53=0,"",K53/K$11)
D55: =IF(C55=0,"",C55/C$11) | F55: =IF(E55=0,"",E55/E$11) | H55: =IF(G55=0,"",G55/G$11) | J55: =IF(I55=0,"",I55/I$11) | L55: =IF(K55=0,"",K55/K$11)
B56: 税引後当期純利益 | C56: =C51-C52 -> 14984010 | D56: =IF(C56=0,"",C56/C$11) -> 0.045981982 | E56: =E51-E52 -> 8680221 | F56: =IF(E56=0,"",E56/E$11) -> 0.02504669 | G56: =G51-G52 -> 9671212 | H56: =IF(G56=0,"",G56/G$11) -> 0.027049266 | I56: =I51-I52 -> 0 | J56: =IF(I56=0,"",I56/I$11) | K56: =K51-K52 -> 0 | L56: =IF(K56=0,"",K56/K$11)
C58: 14984010 | E58: 8680221 | G58: 9671212
C59: =C58=C56 -> TRUE | E59: =E58=E56 -> TRUE | G59: =G58=G56 -> TRUE | I59: =I58=I56 -> TRUE | K59: =K58=K56 -> TRUE

Sheet CR
H4: (単位：千円)
B5: 科目 | C5: ='BS(借方)'!C4 -> 23年12月期 | E5: ='BS(借方)'!D4 -> 24年12月期 | G5: ='BS(借方)'!E4 -> 25年12月期 | I5: ='BS(借方)'!F4 -> ●●年●月期 | K5: ='BS(借方)'!G4 -> ●●年●月 （●か月TB）
C6: 帳簿価額 | D6: 売上高比 | E6: 帳簿価額 | F6: 売上高比 | G6: 帳簿価額 | H6: 売上高比 | I6: 帳簿価額 | J6: 売上高比 | K6: 帳簿価額 | L6: 売上高比
A7: IMに貼るときは非表示→ | B7: 売上 | C7: =PL!C11 -> 325866987 | D7: - | E7: =PL!E11 -> 346561600 | F7: - | G7: =PL!G11 -> 357540639 | H7: - | I7: =PL!I11 -> 0 | J7: - | K7: =PL!K11 -> 0 | L7: -
B8: 期首原材料棚卸高 | D8: =IF(C8=0,"",C8/C$7) | F8: =IF(E8=0,"",E8/E$7) | H8: =IF(G8=0,"",G8/G$7) | J8: =IF(I8=0,"",I8/I$7) | L8: =IF(K8=0,"",K8/K$7)
B9: 原材料仕入高 | D9: =IF(C9=0,"",C9/C$7) | F9: =IF(E9=0,"",E9/E$7) | H9: =IF(G9=0,"",G9/G$7) | J9: =IF(I9=0,"",I9/I$7) | L9: =IF(K9=0,"",K9/K$7)
B10: 小計 | D10: =IF(C10=0,"",C10/C$7) | F10: =IF(E10=0,"",E10/E$7) | H10: =IF(G10=0,"",G10/G$7) | J10: =IF(I10=0,"",I10/I$7) | L10: =IF(K10=0,"",K10/K$7)
B11: 期末原材料棚卸高 | D11: =IF(C11=0,"",C11/C$7) | F11: =IF(E11=0,"",E11/E$7) | H11: =IF(G11=0,"",G11/G$7) | J11: =IF(I11=0,"",I11/I$7) | L11: =IF(K11=0,"",K11/K$7)
D12: =IF(C12=0,"",C12/C$7) | F12: =IF(E12=0,"",E12/E$7) | H12: =IF(G12=0,"",G12/G$7) | J12: =IF(I12=0,"",I12/I$7) | L12: =IF(K12=0,"",K12/K$7)
D13: =IF(C13=0,"",C13/C$7) | F13: =IF(E13=0,"",E13/E$7) | H13: =IF(G13=0,"",G13/G$7) | J13: =IF(I13=0,"",I13/I$7) | L13: =IF(K13=0,"",K13/K$7)
B14: 材料費 | C14: =SUM(C8:C13) -> 0 | D14: =IF(C14=0,"",C14/C$7) | E14: =SUM(E8:E13) -> 0 | F14: =IF(E14=0,"",E14/E$7) | G14: =SUM(G8:G13) -> 0 | H14: =IF(G14=0,"",G14/G$7) | I14: =SUM(I8:I13) -> 0 | J14: =IF(I14=0,"",I14/I$7) | K14: =SUM(K8:K13) -> 0 | L14: =IF(K14=0,"",K14/K$7)
D15: =IF(C15=0,"",C15/C$7) | F15: =IF(E15=0,"",E15/E$7) | H15: =IF(G15=0,"",G15/G$7) | J15: =IF(I15=0,"",I15/I$7) | L15: =IF(K15=0,"",K15/K$7)
D18: =IF(C18=0,"",C18/C$7) | F18: =IF(E18=0,"",E18/E$7) | H18: =IF(G18=0,"",G18/G$7) | J18: =IF(I18=0,"",I18/I$7) | L18: =IF(K18=0,"",K18/K$7)
D19: =IF(C19=0,"",C19/C$7) | F19: =IF(E19=0,"",E19/E$7) | H19: =IF(G19=0,"",G19/G$7) | J19: =IF(I19=0,"",I19/I$7) | L19: =IF(K19=0,"",K19/K$7)
D20: =IF(C20=0,"",C20/C$7) | F20: =IF(E20=0,"",E20/E$7) | H20: =IF(G20=0,"",G20/G$7) | J20: =IF(I20=0,"",I20/I$7) | L20: =IF(K20=0,"",K20/K$7)
D21: =IF(C21=0,"",C21/C$7) | F21: =IF(E21=0,"",E21/E$7) | H21: =IF(G21=0,"",G21/G$7) | J21: =IF(I21=0,"",I21/I$7) | L21: =IF(K21=0,"",K21/K$7)
D22: =IF(C22=0,"",C22/C$7) | F22: =IF(E22=0,"",E22/E$7) | H22: =IF(G22=0,"",G22/G$7) | J22: =IF(I22=0,"",I22/I$7) | L22: =IF(K22=0,"",K22/K$7)
B23: 労務費 | C23: =SUM(C15:C22) -> 0 | D23: =IF(C23=0,"",C23/C$7) | E23: =SUM(E15:E22) -> 0 | F23: =IF(E23=0,"",E23/E$7) | G23: =SUM(G15:G22) -> 0 | H23: =IF(G23=0,"",G23/G$7) | I23: =SUM(I15:I22) -> 0 | J23: =IF(I23=0,"",I23/I$7) | K23: =SUM(K15:K22) -> 0 | L23: =IF(K23=0,"",K23/K$7)
D24: =IF(C24=0,"",C24/C$7) | F24: =IF(E24=0,"",E24/E$7) | H24: =IF(G24=0,"",G24/G$7) | J24: =IF(I24=0,"",I24/I$7) | L24: =IF(K24=0,"",K24/K$7)
D28: =IF(C28=0,"",C28/C$7) | F28: =IF(E28=0,"",E28/E$7) | H28: =IF(G28=0,"",G28/G$7) | J28: =IF(I28=0,"",I28/I$7) | L28: =IF(K28=0,"",K28/K$7)
D29: =IF(C29=0,"",C29/C$7) | F29: =IF(E29=0,"",E29/E$7) | H29: =IF(G29=0,"",G29/G$7) | J29: =IF(I29=0,"",I29/I$7) | L29: =IF(K29=0,"",K29/K$7)
D30: =IF(C30=0,"",C30/C$7) | F30: =IF(E30=0,"",E30/E$7) | H30: =IF(G30=0,"",G30/G$7) | J30: =IF(I30=0,"",I30/I$7) | L30: =IF(K30=0,"",K30/K$7)
D31: =IF(C31=0,"",C31/C$7) | F31: =IF(E31=0,"",E31/E$7) | H31: =IF(G31=0,"",G31/G$7) | J31: =IF(I31=0,"",I31/I$7) | L31: =IF(K31=0,"",K31/K$7)
D32: =IF(C32=0,"",C32/C$7) | F32: =IF(E32=0,"",E32/E$7) | H32: =IF(G32=0,"",G32/G$7) | J32: =IF(I32=0,"",I32/I$7) | L32: =IF(K32=0,"",K32/K$7)
B33: 外注加工費 | C33: =SUM(C24:C32) -> 0 | D33: =IF(C33=0,"",C33/C$7) | E33: =SUM(E24:E32) -> 0 | F33: =IF(E33=0,"",E33/E$7) | G33: =SUM(G24:G32) -> 0 | H33: =IF(G33=0,"",G33/G$7) | I33: =SUM(I24:I32) -> 0 | J33: =IF(I33=0,"",I33/I$7) | K33: =SUM(K24:K32) -> 0 | L33: =IF(K33=0,"",K33/K$7)
D34: =IF(C34=0,"",C34/C$7) | F34: =IF(E34=0,"",E34/E$7) | H34: =IF(G34=0,"",G34/G$7) | J34: =IF(I34=0,"",I34/I$7) | L34: =IF(K34=0,"",K34/K$7)
D35: =IF(C35=0,"",C35/C$7) | F35: =IF(E35=0,"",E35/E$7) | H35: =IF(G35=0,"",G35/G$7) | J35: =IF(I35=0,"",I35/I$7) | L35: =IF(K35=0,"",K35/K$7)
D36: =IF(C36=0,"",C36/C$7) | F36: =IF(E36=0,"",E36/E$7) | H36: =IF(G36=0,"",G36/G$7) | J36: =IF(I36=0,"",I36/I$7) | L36: =IF(K36=0,"",K36/K$7)
D39: =IF(C39=0,"",C39/C$7) | F39: =IF(E39=0,"",E39/E$7) | H39: =IF(G39=0,"",G39/G$7) | J39: =IF(I39=0,"",I39/I$7) | L39: =IF(K39=0,"",K39/K$7)
D40: =IF(C40=0,"",C40/C$7) | F40: =IF(E40=0,"",E40/E$7) | H40: =IF(G40=0,"",G40/G$7) | J40: =IF(I40=0,"",I40/I$7) | L40: =IF(K40=0,"",K40/K$7)
D41: =IF(C41=0,"",C41/C$7) | F41: =IF(E41=0,"",E41/E$7) | H41: =IF(G41=0,"",G41/G$7) | J41: =IF(I41=0,"",I41/I$7) | L41: =IF(K41=0,"",K41/K$7)
D42: =IF(C42=0,"",C42/C$7) | F42: =IF(E42=0,"",E42/E$7) | H42: =IF(G42=0,"",G42/G$7) | J42: =IF(I42=0,"",I42/I$7) | L42: =IF(K42=0,"",K42/K$7)
D43: =IF(C43=0,"",C43/C$7) | F43: =IF(E43=0,"",E43/E$7) | H43: =IF(G43=0,"",G43/G$7) | J43: =IF(I43=0,"",I43/I$7) | L43: =IF(K43=0,"",K43/K$7)
D44: =IF(C44=0,"",C44/C$7) | F44: =IF(E44=0,"",E44/E$7) | H44: =IF(G44=0,"",G44/G$7) | J44: =IF(I44=0,"",I44/I$7) | L44: =IF(K44=0,"",K44/K$7)
D45: =IF(C45=0,"",C45/C$7) | F45: =IF(E45=0,"",E45/E$7) | H45: =IF(G45=0,"",G45/G$7) | J45: =IF(I45=0,"",I45/I$7) | L45: =IF(K45=0,"",K45/K$7)
B46: 経費 | C46: =SUM(C34:C45) -> 0 | D46: =IF(C46=0,"",C46/C$7) | E46: =SUM(E34:E45) -> 0 | F46: =IF(E46=0,"",E46/E$7) | G46: =SUM(G34:G45) -> 0 | H46: =IF(G46=0,"",G46/G$7) | I46: =SUM(I34:I45) -> 0 | J46: =IF(I46=0,"",I46/I$7) | K46: =SUM(K34:K45) -> 0 | L46: =IF(K46=0,"",K46/K$7)
B47: 当期製造費用 | C47: =C14+C23+C33+C46 -> 0 | D47: =IF(C47=0,"",C47/C$7) | E47: =E14+E23+E33+E46 -> 0 | F47: =IF(E47=0,"",E47/E$7) | G47: =G14+G23+G33+G46 -> 0 | H47: =IF(G47=0,"",G47/G$7) | I47: =I14+I23+I33+I46 -> 0 | J47: =IF(I47=0,"",I47/I$7) | K47: =K14+K23+K33+K46 -> 0 | L47: =IF(K47=0,"",K47/K$7)
B48: 期首仕掛品棚卸高 | D48: =IF(C48=0,"",C48/C$7) | E48: =SUM(E36:E47) -> 0 | F48: =IF(E48=0,"",E48/E$7) | G48: =SUM(G36:G47) -> 0 | H48: =IF(G48=0,"",G48/G$7) | I48: =SUM(I36:I47) -> 0 | J48: =IF(I48=0,"",I48/I$7) | K48: =SUM(K36:K47) -> 0 | L48: =IF(K48=0,"",K48/K$7)
B49: 合計 | C49: =SUM(C47:C48) -> 0 | D49: =IF(C49=0,"",C49/C$7) | E49: =SUM(E47:E48) -> 0 | F49: =IF(E49=0,"",E49/E$7) | G49: =SUM(G47:G48) -> 0 | H49: =IF(G49=0,"",G49/G$7) | I49: =SUM(I47:I48) -> 0 | J49: =IF(I49=0,"",I49/I$7) | K49: =SUM(K47:K48) -> 0 | L49: =IF(K49=0,"",K49/K$7)
B50: 期末仕掛品棚卸高 | D50: =IF(C50=0,"",C50/C$7) | E50: =SUM(E40:E49) -> 0 | F50: =IF(E50=0,"",E50/E$7) | G50: =SUM(G40:G49) -> 0 | H50: =IF(G50=0,"",G50/G$7) | I50: =SUM(I40:I49) -> 0 | J50: =IF(I50=0,"",I50/I$7) | K50: =SUM(K40:K49) -> 0 | L50: =IF(K50=0,"",K50/K$7)
B51: 当期製造原価 | C51: =C49-C50 -> 0 | D51: =IF(C51=0,"",C51/C$7) | E51: =E49-E50 -> 0 | F51: =IF(E51=0,"",E51/E$7) | G51: =G49-G50 -> 0 | H51: =IF(G51=0,"",G51/G$7) | I51: =I49-I50 -> 0 | J51: =IF(I51=0,"",I51/I$7) | K51: =K49-K50 -> 0 | L51: =IF(K51=0,"",K51/K$7)

Sheet SGA
H2: (単位：千円)
B3: 科目 | C3: ='BS(借方)'!C4 -> 23年12月期 | E3: ='BS(借方)'!D4 -> 24年12月期 | G3: ='BS(借方)'!E4 -> 25年12月期 | I3: ='BS(借方)'!F4 -> ●●年●月期 | K3: ='BS(借方)'!G4 -> ●●年●月 （●か月TB）
C4: 帳簿価額 | D4: 売上高比 | E4: 帳簿価額 | F4: 売上高比 | G4: 帳簿価額 | H4: 売上高比 | I4: 帳簿価額 | J4: 売上高比 | K4: 帳簿価額 | L4: 売上高比
B5: 売上 | C5: =PL!C11 -> 325866987 | D5: - | E5: =PL!E11 -> 346561600 | F5: - | G5: =PL!G11 -> 357540639 | H5: - | I5: =PL!I11 -> 0 | J5: - | K5: =PL!K11 -> 0 | L5: - | M5: ←IMに貼るときは非表示
B6: 役員報酬 | C6: 10500000 | D6: =C6/$C$5 -> 0.032221736 | E6: 17120000 | F6: =E6/$E$5 -> 0.049399587 | G6: 11870000 | H6: =G6/$G$5 -> 0.033199023 | J6: =IFERROR(I6/$I$5,"") | L6: =IFERROR(K6/$K$5,"")
B7: 給料手当 | C7: 64348988 | D7: =C7/$C$5 -> 0.1974701 | E7: 65194441 | F7: =E7/$E$5 -> 0.1881179 | G7: 64753816 | H7: =G7/$G$5 -> 0.18110897 | J7: =IFERROR(I7/$I$5,"") | L7: =IFERROR(K7/$K$5,"")
B8: 賞与 | C8: 3549000 | D8: =C8/$C$5 -> 0.010890947 | E8: 3405000 | F8: =E8/$E$5 -> 0.0098250931 | G8: 3197000 | H8: =G8/$G$5 -> 0.0089416409 | J8: =IFERROR(I8/$I$5,"") | L8: =IFERROR(K8/$K$5,"")
B9: 退職金 | C9: 370000 | D9: =C9/$C$5 -> 0.0011354326 | F9: =E9/$E$5 -> 0 | H9: =G9/$G$5 -> 0 | J9: =IFERROR(I9/$I$5,"") | L9: =IFERROR(K9/$K$5,"")
B10: 法定福利費 | C10: 11424051 | D10: =C10/$C$5 -> 0.035057405 | E10: 12207732 | F10: =E10/$E$5 -> 0.035225288 | G10: 10842135 | H10: =G10/$G$5 -> 0.030324203 | J10: =IFERROR(I10/$I$5,"") | L10: =IFERROR(K10/$K$5,"")
B11: 福利厚生費 | C11: 1851569 | D11: =C11/$C$5 -> 0.0056819778 | E11: 2218165 | F11: =E11/$E$5 -> 0.0064004927 | G11: 2913601 | H11: =G11/$G$5 -> 0.0081490065 | J11: =IFERROR(I11/$I$5,"") | L11: =IFERROR(K11/$K$5,"")
B12: 採用教育費 | C12: 291360 | D12: =C12/$C$5 -> 0.00089410714 | E12: 184800 | F12: =E12/$E$5 -> 0.00053323854 | G12: 88700 | H12: =G12/$G$5 -> 0.00024808369 | J12: =IFERROR(I12/$I$5,"") | L12: =IFERROR(K12/$K$5,"")
B13: 広告宣伝費 | C13: 1200593 | D13: =C13/$C$5 -> 0.0036843039 | E13: 1208388 | F13: =E13/$E$5 -> 0.0034867914 | G13: 1053123 | H13: =G13/$G$5 -> 0.0029454638 | J13: =IFERROR(I13/$I$5,"") | L13: =IFERROR(K13/$K$5,"")
B14: 接待交際費 | C14: 547960 | D14: =C14/$C$5 -> 0.001681545 | E14: 180010 | F14: =E14/$E$5 -> 0.00051941704 | G14: 86721 | H14: =G14/$G$5 -> 0.00024254865 | J14: =IFERROR(I14/$I$5,"") | L14: =IFERROR(K14/$K$5,"")
B15: 会議費 | C15: 272805 | D15: =C15/$C$5 -> 0.00083716673 | E15: 366979 | F15: =E15/$E$5 -> 0.0010589142 | G15: 459575 | H15: =G15/$G$5 -> 0.0012853784 | J15: =IFERROR(I15/$I$5,"") | L15: =IFERROR(K15/$K$5,"")
B16: 旅費交通費 | C16: 2801560 | D16: =C16/$C$5 -> 0.0085972501 | E16: 2701132 | F16: =E16/$E$5 -> 0.0077940891 | G16: 2770899 | H16: =G16/$G$5 -> 0.0077498855 | J16: =IFERROR(I16/$I$5,"") | L16: =IFERROR(K16/$K$5,"")
B17: 通信費 | C17: 1043002 | D17: =C17/$C$5 -> 0.0032006986 | E17: 1254118 | F17: =E17/$E$5 -> 0.0036187448 | G17: 1367473 | H17: =G17/$G$5 -> 0.0038246645 | J17: =IFERROR(I17/$I$5,"") | L17: =IFERROR(K17/$K$5,"")
B18: 消耗品費 | C18: 2345684 | D18: =C18/$C$5 -> 0.0071982867 | E18: 4467693 | F18: =E18/$E$5 -> 0.012891483 | G18: 3124510 | H18: =G18/$G$5 -> 0.0087388947 | J18: =IFERROR(I18/$I$5,"") | L18: =IFERROR(K18/$K$5,"")
B19: 事務用消耗品費 | C19: 1991419 | D19: =C19/$C$5 -> 0.0061111407 | E19: 1929685 | F19: =E19/$E$5 -> 0.0055680866 | G19: 1771435 | H19: =G19/$G$5 -> 0.0049544997 | J19: =IFERROR(I19/$I$5,"") | L19: =IFERROR(K19/$K$5,"")
B20: 修繕費 | C20: 805390 | D20: =C20/$C$5 -> 0.0024715299 | E20: 926390 | F20: =E20/$E$5 -> 0.002673089 | G20: 532686 | H20: =G20/$G$5 -> 0.0014898614 | J20: =IFERROR(I20/$I$5,"") | L20: =IFERROR(K20/$K$5,"")
B21: 水道光熱費 | C21: 1033592 | D21: =C21/$C$5 -> 0.0031718218 | E21: 1113959 | F21: =E21/$E$5 -> 0.0032143175 | G21: 1037468 | H21: =G21/$G$5 -> 0.0029016785 | J21: =IFERROR(I21/$I$5,"") | L21: =IFERROR(K21/$K$5,"")
... B34: 管理諸費 | C34: 3649888 | D34: =C34/$C$5 -> 0.011200545 | E34: 3432539 | F34: =E34/$E$5 -> 0.0099045567 | G34: 3705328 | H34: =G34/$G$5 -> 0.010363376 | J34: =IFERROR(I34/$I$5,"") | L34: =IFERROR(K34/$K$5,"")
D35: =C35/$C$5 -> 0 | F35: =E35/$E$5 -> 0 | H35: =G35/$G$5 -> 0 | J35: =IFERROR(I35/$I$5,"") | L35: =IFERROR(K35/$K$5,"")
D36: =C36/$C$5 -> 0 | F36: =E36/$E$5 -> 0 | H36: =G36/$G$5 -> 0 | J36: =IFERROR(I36/$I$5,"") | L36: =IFERROR(K36/$K$5,"")
D37: =C37/$C$5 -> 0 | F37: =E37/$E$5 -> 0 | H37: =G37/$G$5 -> 0 | J37: =IFERROR(I37/$I$5,"") | L37: =IFERROR(K37/$K$5,"")
D38: =C38/$C$5 -> 0 | F38: =E38/$E$5 -> 0 | H38: =G38/$G$5 -> 0 | J38: =IFERROR(I38/$I$5,"") | L38: =IFERROR(K38/$K$5,"")
D39: =C39/$C$5 -> 0 | F39: =E39/$E$5 -> 0 | H39: =G39/$G$5 -> 0 | J39: =IFERROR(I39/$I$5,"") | L39: =IFERROR(K39/$K$5,"")
B40: 販売費および一般管理費合計 | C40: =SUM(C6:C39) -> 145464229 | D40: =C40/C5 -> 0.44639143 | E40: =SUM(E6:E39) -> 154261272 | F40: =E40/E5 -> 0.44511934 | G40: =SUM(G6:G39) -> 147845764 | H40: =G40/G5 -> 0.41350758 | I40: =SUM(I6:I39) -> 0 | J40: =IFERROR(I40/I5,"") | K40: =SUM(K6:K39) -> 0 | L40: =IFERROR(K40/K5,"")

Sheet VR→ 

Sheet 株式価値 
A1: 作業不要（自動作成）
F2: (単位：千円)
C3: min | D3: 差（グラフ作成用） | E3: max
B4: インカム | C4: 0 | D4: 0 | E4: 0 | F4: 100 | I4: ｚ
B5: マーケット | C5: ='EV EBITDAマルチプル'!K7 -> 1069000000 | D5: =E5-C5 -> 546000000 | E5: ='EV EBITDAマルチプル'!M7 -> 1615000000 | F5: 0
B6: コスト | C6: =年買法!K6 -> 571000000 | D6: =E6-C6 -> 542000000 | E6: =年買法!M6 -> 1113000000 | F6: 0

Sheet 修正BS(借方)
E2: (単位：千円)
B3: 資産の部
B4: 科目 | C4: ='BS(借方)'!E4 -> 25年12月期 | D4: 修正額 | E4: 修正後
B5: 【流動資産】 | C5: =SUM(C6:C19) -> 141385419 | D5: =SUM(D6:D19) -> 0 | E5: =C5+D5 -> 141385419
B6: ='BS(借方)'!B6 -> 現金及び預金 | C6: ='BS(借方)'!E6 -> 61842402 | E6: =C6+D6 -> 61842402
B7: ='BS(借方)'!B7 -> 商品 | C7: ='BS(借方)'!E7 -> 26584168 | E7: =C7+D7 -> 26584168
B8: ='BS(借方)'!B8 -> 貯蔵品 | C8: ='BS(借方)'!E8 -> 619688 | E8: =C8+D8 -> 619688
B9: ='BS(借方)'!B9 -> 前払費用 | C9: ='BS(借方)'!E9 -> 161700 | E9: =C9+D9 -> 161700
B10: ='BS(借方)'!B10 -> 未収入金 | C10: ='BS(借方)'!E10 -> 52401281 | E10: =C10+D10 -> 52401281
B11: ='BS(借方)'!B11 -> 貸倒引当金 | C11: ='BS(借方)'!E11 -> -524000 | D11: =-C11 | E11: =C11+D11 -> -524000
B12: ='BS(借方)'!B12 -> 仮払金 | C12: ='BS(借方)'!E12 -> 180 | E12: =C12+D12 -> 180
B13: ='BS(借方)'!B13 -> 前払金 | C13: ='BS(借方)'!E13 -> 300000 | E13: =C13+D13 -> 300000
B14: ='BS(借方)'!B14 -> 未収還付法人税等 | C14: ='BS(借方)'!E14 -> 0 | E14: =C14+D14 -> 0
B15: ='BS(借方)'!B15 -> 0 | C15: ='BS(借方)'!E15 -> 0 | E15: =C15+D15 -> 0
B16: ='BS(借方)'!B16 -> 0 | C16: ='BS(借方)'!E16 -> 0 | E16: =C16+D16 -> 0
B17: ='BS(借方)'!B17 -> 0 | C17: ='BS(借方)'!E17 -> 0 | E17: =C17+D17 -> 0
B18: ='BS(借方)'!B18 -> 0 | C18: ='BS(借方)'!E18 -> 0 | E18: =C18+D18 -> 0
E19: =C19+D19 -> 0
B20: 【固定資産】 | C20: =C21+C35+C46 -> 19843083 | D20: =D21+D35+D46 -> 0 | E20: =C20+D20 -> 19843083
B21: ［有形固定資産］ | C21: =SUM(C22:C34) -> 7402395 | D21: =SUM(D22:D34) -> 0 | E21: =C21+D21 -> 7402395
B22: ='BS(借方)'!B22 -> 建物附属設備 | C22: ='BS(借方)'!E22 -> 5361688 | E22: =C22+D22 -> 5361688
B23: ='BS(借方)'!B23 -> 工具器具備品 | C23: ='BS(借方)'!E23 -> 2040707 | E23: =C23+D23 -> 2040707
B24: ='BS(借方)'!B24 -> 0 | C24: ='BS(借方)'!E24 -> 0 | E24: =C24+D24 -> 0
B25: ='BS(借方)'!B25 -> 0 | C25: ='BS(借方)'!E25 -> 0 | E25: =C25+D25 -> 0
B26: ='BS(借方)'!B26 -> 0 | C26: ='BS(借方)'!E26 -> 0 | E26: =C26+D26 -> 0
B27: ='BS(借方)'!B27 -> 0 | C27: ='BS(借方)'!E27 -> 0 | E27: =C27+D27 -> 0
B28: ='BS(借方)'!B28 -> 0 | C28: ='BS(借方)'!E28 -> 0 | E28: =C28+D28 -> 0
B29: ='BS(借方)'!B29 -> 0 | C29: ='BS(借方)'!E29 -> 0 | E29: =C29+D29 -> 0
B30: ='BS(借方)'!B30 -> 0 | C30: ='BS(借方)'!E30 -> 0 | E30: =C30+D30 -> 0
B31: ='BS(借方)'!B31 -> 0 | C31: ='BS(借方)'!E31 -> 0 | E31: =C31+D31 -> 0
B32: ='BS(借方)'!B32 -> 0 | C32: ='BS(借方)'!E32 -> 0 | E32: =C32+D32 -> 0
B33: ='BS(借方)'!B33 -> 0 | C33: ='BS(借方)'!E33 -> 0 | E33: =C33+D33 -> 0
E34: =C34+D34 -> 0
B35: ［無形固定資産］ | C35: =SUM(C36:C45) -> 4816004 | D35: =SUM(D36:D45) -> 0 | E35: =C35+D35 -> 4816004
B36: ='BS(借方)'!B36 -> ソフトウェア | C36: ='BS(借方)'!E36 -> 4816004 | E36: =C36+D36 -> 4816004
B37: ='BS(借方)'!B37 -> 0 | C37: ='BS(借方)'!E37 -> 0 | E37: =C37+D37 -> 0
B38: ='BS(借方)'!B38 -> 0 | C38: ='BS(借方)'!E38 -> 0 | E38: =C38+D38 -> 0
B39: ='BS(借方)'!B39 -> 0 | C39: ='BS(借方)'!E39 -> 0 | E39: =C39+D39 -> 0
B40: ='BS(借方)'!B40 -> 0 | C40: ='BS(借方)'!E40 -> 0 | E40: =C40+D40 -> 0
E41: =C41+D41 -> 0
E42: =C42+D42 -> 0
E43: =C43+D43 -> 0
E44: =C44+D44 -> 0
E45: =C45+D45 -> 0
B46: ［投資その他資産］ | C46: =SUM(C47:C54) -> 7624684 | D46: =SUM(D47:D54) -> 0 | E46: =C46+D46 -> 7624684
B47: ='BS(借方)'!B47 -> 差入保証金 | C47: ='BS(借方)'!E47 -> 6639280 | E47: =C47+D47 -> 6639280
B48: ='BS(借方)'!B48 -> 長期前払費用 | C48: ='BS(借方)'!E48 -> 985404 | D48: =-C48 | E48: =C48+D48 -> 985404
B49: ='BS(借方)'!B49 -> 0 | C49: ='BS(借方)'!E49 -> 0 | E49: =C49+D49 -> 0
B50: ='BS(借方)'!B50 -> 0 | C50: ='BS(借方)'!E50 -> 0 | E50: =C50+D50 -> 0
B51: ='BS(借方)'!B51 -> 0 | C51: ='BS(借方)'!E51 -> 0 | E51: =C51+D51 -> 0
B52: ='BS(借方)'!B52 -> 0 | C52: ='BS(借方)'!E52 -> 0 | E52: =C52+D52 -> 0
B53: ='BS(借方)'!B53 -> 0 | C53: ='BS(借方)'!E53 -> 0 | E53: =C53+D53 -> 0
B54: ='BS(借方)'!B54 -> 0 | C54: ='BS(借方)'!E54 -> 0 | E54: =C54+D54 -> 0
E55: =C55+D55 -> 0
B56: 【繰延資産】 | C56: =SUM(C57:C59) -> 0 | D56: =SUM(D57:D59) -> 0 | E56: =C56+D56 -> 0
B57: ='BS(借方)'!B57 -> 0 | C57: ='BS(借方)'!E57 -> 0 | E57: =C57+D57 -> 0
E58: =C58+D58 -> 0
E59: =C59+D59 -> 0
B60: 【繰延税金資産】 | C60: 0 | D60: =ROUND(MAX(0,-('修正BS(借方)'!D5+'修正BS(借方)'!D20+'修正BS(借方)'!D56-('修正BS(貸方) '!D5+'修正BS(貸方) '!D18))*0.34),0) | E60: =C60+D60 -> 0
B61: 資産合計 | C61: =C5+C20+C56+C60 -> 161228502 | D61: =D5+D20+D56+D60 -> 0 | E61: =C61+D61 -> 161228502

Sheet 売掛・棚卸
E2: (単位：千円)
A3: 未収入金 | B3: 相手先 | C3: 帳簿価額 | D3: 評価差額 | E3: 評価額 | F3: 調整事由
B4: 社会保険診療報酬支払基金（神奈川県） | C4: 35166706 | D4: 0 | E4: =SUM(C4,D4) -> 0 | F4: 診療報酬の請求債権。公的保険者に対する債権であり貸倒リスクは実質的にないため帳簿価額により評価する。
B5: 神奈川県国民健康保険団体連合会 | C5: 16411998 | D5: 0 | E5: =SUM(C5,D5) -> 3087.5 | F5: 診療報酬16,270,584円及び介護給付費141,414円。同上。
B6: その他（㈱パーク24・窓口未収金等） | C6: 822577 | D6: 0 | E6: =SUM(C6,D6) -> 8287 | F6: ㈱パーク24 546千円ほか小口7件。内容は要確認。
E7: =SUM(C7,D7) -> 88980
B8: 合計 | C8: =SUM(C4:C7) -> 125963 | D8: =SUM(D4:D7) -> -25608.5 | E8: =C8+D8 -> 100354.5
E12: (単位：千円)
A13: 商品在庫 | B13: 相手先 | C13: 帳簿価額 | D13: 評価差額 | E13: 評価額 | F13: 調整事由
B14: 商品（薬品等） | C14: 26584168 | D14: 0 | E14: =SUM(C14,D14) | F14: 内訳書上は「薬品等（明細書会社保存）」の一括表示。品目別明細・使用期限別の滞留状況が未確認のため帳簿価額により評価する（要確認）。評価方法は最終仕入原価法。
B15: 貯蔵品（薬袋等） | C15: 619688 | D15: 0 | E15: =SUM(C15,D15) | F15: 長期滞留在庫であり、0円評価とする
E16: =SUM(C16,D16)
E17: =SUM(C17,D17)
B18: 合計 | C18: =SUM(C14:C17) -> 400447 | D18: =SUM(D14:D17) -> -130922 | E18: =C18+D18 -> 269525

Sheet 減価償却
E2: (単位：千円)
B3: 資産 | C3: 帳簿価額 | D3: 評価差額 | E3: 評価額 | F3: 調整事由
B4: 建物附属設備 | C4: 5361688 | D4: 0 | E4: =SUM(C4,D4) -> 0 | F4: 固定資産台帳が未受領のため個別資産の償却過不足の検証は未実施。税法基準（定率法・建物附属設備は定額法、ソフトウェアは定額法）により継続的に償却されており、帳簿価額により評価する（要確認）。店舗はいずれも賃借であり、有形固定資産の大宗は内装造作と推察される。
B5: 工具器具備品 | C5: 2040707 | D5: 0 | E5: =SUM(C5,D5) -> 3087.5 | F5: 消却不足額を減額
B6: ソフトウェア | C6: 4816004 | D6: 0 | E6: =SUM(C6,D6) -> 8287 | F6: 消却不足額を減額
E7: =SUM(C7,D7) -> 88980
B8: 合計 | C8: =SUM(C4:C7) -> 125963 | D8: =SUM(D4:D7) -> -25608.5 | E8: =C8+D8 -> 100354.5

Sheet 土地
F2: (単位：千円)
B3: 内容・所在地 | C3: 地積(㎡) | D3: 帳簿価額 | E3: 評価差額 | F3: 時価評価額 | G3: 調整事由
B4: 該当なし | C4: 500 | D4: 5000000 | E4: =F4-D4 -> -2000000 | F4: 3000000 | G4: 対象会社は土地・建物等の不動産を保有していない。店舗3件・駐車場4件はいずれも賃借（地代家賃等の内訳書により確認）。したがって不動産の時価評価は実施していない。
E5: =F5-D5 -> 2000000
E6: =F6-D6 -> 2000000
E7: =F7-D7 -> 0
B8: 合計 | C8: =SUM(C4:C7) -> 1000 | D8: =SUM(D4:D7) -> 15000000 | E8: =SUM(E4:E7) -> 2000000 | F8: =SUM(F4:F7) -> 17000000

Sheet 保険
E2: (単位：千円)
B3: 保険商品 | C3: 帳簿価額 | D3: 評価差額 | E3: 評価額 | F3: 調整事由
B4: 中小企業倒産防止共済（簿外） | C4: 0 | D4: =E4-C4 -> 5000000 | E4: 0 | F4: 令和7年12月期BSに保険積立金の計上はないが、雑益の内訳書に「倒産防止共済金 前納減額金 9,720円」の計上があり、掛金を全額損金算入している簿外の積立が存在すると認められる。解約手当金額（最大800万円）は時価純資産の加算要素となるため、加入時期・掛金月額・納付済掛金総額を要確認。金額が特定できないため本評価では未計上とする。
B5: 生命保険等 | C5: 0 | E5: 0 | F5: 保険料1,603千円（令和7年12月期）の内訳・保険証券が未受領のため、掛捨て以外の積立性保険の有無は未確認（要確認）。
B8: 合計 | C8: =SUM(C4:C7) -> 10000000 | D8: =SUM(D4:D7) -> 5000000 | E8: =C8+D8 -> 15000000

Sheet 有価証券
F2: (単位：千円)
B3: 銘柄 | C3: 数量 | D3: 帳簿価額 | E3: 評価差額 | F3: 評価額 | G3: 調整事由
B4: 該当なし | C4: 1000 | D4: 0 | E4: =F4-D4 -> 5000000 | F4: 0 | G4: 令和7年12月期BSに有価証券・投資有価証券の計上はない。貸付金及び受取利息の内訳書上、役員貸付金・従業員貸付金の計上もない。
E5: =F5-D5 -> 3000000
E7: =F7-D7 -> 0
E8: =F8-D8 -> 0
B9: 合計 | C9: - | D9: =SUM(D4:D8) -> 20000000 | E9: =SUM(E4:E8) -> 8000000 | F9: =D9+E9 -> 28000000

Sheet 修正BS(貸方) 
E2: (単位：千円)
B3: 負債の部
B4: 科目 | C4: ='修正BS(借方)'!C4 -> 25年12月期 | D4: 修正額 | E4: 修正後
B5: 【流動負債】 | C5: =SUM(C6:C17) -> 41577715 | D5: =SUM(D6:D17) -> 0 | E5: =C5+D5 -> 41577715
B6: ='BS (貸方)'!B6 -> 買掛金 | C6: ='BS (貸方)'!E6 -> 26935462 | E6: =C6+D6 -> 26935462
B7: ='BS (貸方)'!B7 -> 短期借入金 | C7: ='BS (貸方)'!E7 -> 8000000 | E7: =C7+D7 -> 8000000
B8: ='BS (貸方)'!B8 -> 未払金 | C8: ='BS (貸方)'!E8 -> 3541353 | E8: =C8+D8 -> 3541353
B9: ='BS (貸方)'!B9 -> 未払法人税等 | C9: ='BS (貸方)'!E9 -> 3100900 | E9: =C9+D9 -> 3100900
B10: ='BS (貸方)'!B10 -> 0 | C10: ='BS (貸方)'!E10 -> 0 | E10: =C10+D10 -> 0
B11: ='BS (貸方)'!B11 -> 0 | C11: ='BS (貸方)'!E11 -> 0 | E11: =C11+D11 -> 0
B12: ='BS (貸方)'!B12 -> 0 | C12: ='BS (貸方)'!E12 -> 0 | E12: =C12+D12 -> 0
B13: ='BS (貸方)'!B13 -> 0 | C13: ='BS (貸方)'!E13 -> 0 | E13: =C13+D13 -> 0
B14: ='BS (貸方)'!B14 -> 0 | C14: ='BS (貸方)'!E14 -> 0 | E14: =C14+D14 -> 0
B15: ='BS (貸方)'!B15 -> 0 | C15: ='BS (貸方)'!E15 -> 0 | E15: =C15+D15 -> 0
B16: ='BS (貸方)'!B16 -> 0 | C16: ='BS (貸方)'!E16 -> 0 | E16: =C16+D16 -> 0
E17: =C17+D17 -> 0
B18: 【固定負債】 | C18: =SUM(C19:C26) -> 47200000 | D18: =SUM(D19:D26) -> 0 | E18: =C18+D18 -> 47200000
B19: ='BS (貸方)'!B19 -> 長期借入金 | C19: ='BS (貸方)'!E19 -> 47200000 | E19: =C19+D19 -> 47200000
B20: ='BS (貸方)'!B20 -> 0 | C20: ='BS (貸方)'!E20 -> 0 | E20: =C20+D20 -> 0
B21: ='BS (貸方)'!B21 -> 0 | C21: ='BS (貸方)'!E21 -> 0 | E21: =C21+D21 -> 0
B22: ='BS (貸方)'!B22 -> 0 | C22: ='BS (貸方)'!E22 -> 0 | E22: =C22+D22 -> 0
B23: ='BS (貸方)'!B23 -> 0 | C23: ='BS (貸方)'!E23 -> 0 | E23: =C23+D23 -> 0
E24: =C24+D24 -> 0
E25: =C25+D25 -> 0
E26: =C26+D26 -> 0
B27: 【繰延税金負債】 | C27: 0 | D27: =ROUND(MAX(0,('修正BS(借方)'!D5+'修正BS(借方)'!D20+'修正BS(借方)'!D56-('修正BS(貸方) '!D5+'修正BS(貸方) '!D18))*0.34),0) | E27: =C27+D27 -> 0
B28: 負債合計 | C28: =C5+C18+C27 -> 88777715 | D28: =D5+D18+D27 -> 0 | E28: =C28+D28 -> 88777715
B34: 純資産の部
B35: 【資本金】 | C35: =SUM(C36:C38) -> 9000000 | D35: =SUM(D36:D38) -> 0 | E35: =C35+D35 -> 9000000
B36: ='BS (貸方)'!B36 -> 資本金 | C36: ='BS (貸方)'!E36 -> 9000000 | E36: =C36+D36 -> 9000000
E37: =C37+D37 -> 0
E38: =C38+D38 -> 0
B39: 【資本剰余金】 | C39: =SUM(C40:C42) -> 1000000 | D39: =SUM(D40:D42) -> 0 | E39: =C39+D39 -> 1000000
B40: ='BS (貸方)'!B40 -> 資本準備金 | C40: ='BS (貸方)'!E40 -> 1000000 | E40: =C40+D40 -> 1000000
E41: =C41+D41 -> 0
E42: =C42+D42 -> 0
B43: 【利益剰余金】 | C43: =SUM(C44:C47) -> 62450787 | D43: =SUM(D44:D47) -> 0 | E43: =C43+D43 -> 62450787
B44: ='BS (貸方)'!B44 -> 繰越利益剰余金 | C44: ='BS (貸方)'!E44 -> 62450787 | E44: =C44+D44 -> 62450787
B45: ='BS (貸方)'!B45 -> 0 | C45: ='BS (貸方)'!E45 -> 0 | E45: =C45+D45 -> 0
B46: ='BS (貸方)'!B46 -> 0 | C46: ='BS (貸方)'!E46 -> 0 | E46: =C46+D46 -> 0
E47: =C47+D47 -> 0
B48: 【自己株式】 | C48: 0 | D48: 0 | E48: =C48+D48 -> 0
B49: 【評価修正額】 | D49: =SUM(D50:D51) -> 0 | E49: =C49+D49 -> 0
B50: 修正額 | D50: ='修正BS(借方)'!D61-'修正BS(借方)'!D60-(D5+D18) | E50: =C50+D50 -> 0
B51: 修正税効果 | D51: ='修正BS(借方)'!D60-D27 | E51: =C51+D51 -> 0
B52: 純資産合計 | C52: =C35+C39+C43+C48 -> 72450787 | D52: =D35+D39+D43+D48+D49 -> 0 | E52: =C52+D52 -> 72450787
B53: 負債・純資産合計 | C53: =C28+C52 -> 161228502 | D53: =D28+D52 -> 0 | E53: =C53+D53 -> 161228502
C55: =C53='修正BS(借方)'!C61 -> TRUE

Sheet 未払人件費・賞与
D2: (単位：千円) | E2: (単位：千円) | F2: (単位：千円)
B3: ●年●月支払給与 | C3: 未払日数 | D3: 未払給与引当額 | E3: 概算社会保険料 | F3: 未払給与引当額
B4: － | C4: － | D4: － | E4: － | F4: －
B6: 就業規則・賃金規程（給与の締日・支払日）が未受領のため、未払給与の引当不足額は算定不能。要確認事項として整理し、本評価では未計上とする。
E7: (単位：千円)
B8: ●年●月支払予定賞与 | C8: 支給対象月数 | D8: 経過月数 | E8: 引当額 | F8: 概算社会保険料 | G8: 社保考慮後引当不足
B9: － | C9: － | D9: － | E9: － | F9: － | G9: －
B11: 未払金の内訳書に「港北年金事務所 2,349,413円（11月分・賞与分社会保険料）」の計上があり、賞与に係る社会保険料は未払計上されている。賞与支給規程・支給月が未確認のため賞与引当不足額は算定不能。本評価では未計上とする（要確認）。

Sheet 退職金
J2: (単位：千円)
B3: № | C3: 氏名 | D3: 勤続年数(年) | E3: 基本給 | F3: 支給倍率 | G3: 退職理由率 | H3: 要支給額 | I3: 中退共積立額 | J3: 引当不足
B4: 1 | C4: －
B5: 2
B6: 3
B7: 4
B8: 5
C10: 合計 | H10: =SUM(H6:H9) -> 0 | I10: =SUM(I6:I9) -> 0 | J10: =H10+I10 -> 0
B12: 退職金規程・従業員名簿が未受領のため退職給付引当不足額は算定不能。令和5年12月期に退職金370千円の支給実績があり、規程の有無を含め要確認。本評価では未計上とする。

Sheet 税効果
E2: (単位：千円)
B3: 修正科目 | C3: 適用判定 | D3: 修正額 | E3: 繰延税金資産/負債 | F3: 備考
B4: 貸倒引当金 | C4: 〇 | D4: 524000 | E4: =-D4*0.34 | F4: 全額戻入。将来加算一時差異
B5: 長期前払費用 | C5: 〇 | D5: -985404 | E5: =-D5*0.34 | F5: 賃貸借契約の更新料の未償却分を全額控除。将来減算一時差異
B6: 未収入金 | C6: 〇 | E6: =-D6*0.34 | F6: 98.4%が社会保険診療報酬支払基金・国保連に対する債権であり簿価評価
B7: 商品・貯蔵品 | C7: 〇 | E7: =-D7*0.34 | F7: 品目別明細・滞留状況が未確認のため簿価評価（要確認）
B8: 減価償却資産 | C8: 〇 | E8: =-D8*0.34 | F8: 固定資産台帳が未受領のため償却過不足未検証（要確認）
B9: ソフトウェア | C9: 〇 | E9: =-D9*0.34 | F9: 自社利用の業務システムであり、事業継続を前提に簿価評価
B10: 差入保証金 | C10: 〇 | E10: =-D10*0.34 | F10: 店舗・駐車場7件の保証金。返還条件・原状回復義務が未確認のため簿価評価（要確認）
B11: 倒産防止共済（簿外） | C11: 〇 | E11: =-D11*0.34 | F11: 解約手当金額が未確認のため未計上。判明後は加算要素（要確認）
B12: 未払給与（未払残業代） | C12: 〇 | E12: =-D12*0.34 | F12: 就業規則・賃金規程が未受領のため未計上（要確認）
B13: 賞与引当金 | C13: 〇 | E13: =-D13*0.34 | F13: 賞与に係る社会保険料は未払計上済。引当不足額は未確認のため未計上（要確認）
B14: 退職給付引当金 | C14: 〇 | E14: =-D14*0.34 | F14: 退職金規程が未受領のため未計上（要確認）
E15: =-D15*0.34
E16: =-D16*0.34
E17: =-D17*0.34
B18: 合計 | C18: - | D18: =SUM(D4:D17) -> -5000000 | E18: =SUM(E4:E17) -> 1700000 | F18: 修正額の純額は△461千円（貸倒引当金の戻入524千円－長期前払費用の控除985千円）であり、実効税率34%による繰延税金資産157千円を修正貸借対照表上の【繰延税金資産】に計上している。

Sheet ネットキャッシュ
F2: (単位：千円)
B3: キャッシュライクアイテム | C3: 金額 | E3: デットライクアイテム | F3: 金額
B4: 現金及び預金 | C4: ='修正BS(借方)'!E6 | E4: 短期借入金 | F4: ='修正BS(貸方) '!E7
E5: 長期借入金 | F5: ='修正BS(貸方) '!E19
B13: 合計 | C13: =SUM(C4:C12) -> 0 | E13: 合計 | F13: =SUM(F4:F12) -> 0
B15: ネットキャッシュ | C15: =C13-F13 -> 0

Sheet 修正PL
K2: (単位：千円)
B3: 科目 | C3: ='BS(借方)'!C4 -> 23年12月期 | F3: ='BS(借方)'!D4 -> 24年12月期 | I3: ='BS(借方)'!E4 -> 25年12月期 | L3: ='BS(借方)'!F4 -> ●●年●月期 | O3: ='BS(借方)'!G4 -> ●●年●月 （●か月TB）
C4: 帳簿価額 | D4: 修正額 | E4: 修正後 | F4: 帳簿価額 | G4: 修正額 | H4: 修正後 | I4: 帳簿価額 | J4: 修正額 | K4: 修正後 | L4: 帳簿価額 | M4: 修正額 | N4: 修正後 | O4: 帳簿価額 | P4: 修正額 | Q4: 修正後
B5: =PL!B5 -> 売上高 | C5: =PL!C5 -> 325866987 | E5: =C5+D5 -> 325866987 | F5: =PL!E5 -> 346561600 | H5: =F5+G5 -> 346561600 | I5: =PL!G5 -> 357540639 | K5: =I5+J5 -> 357540639 | L5: =PL!I5 -> 0 | N5: =L5+M5 -> 0 | O5: =PL!K5 -> 0 | Q5: =O5+P5 -> 0
B6: =PL!B6 -> 0 | C6: =PL!C6 -> 0 | E6: =C6+D6 -> 0 | F6: =PL!E6 -> 0 | H6: =F6+G6 -> 0 | I6: =PL!G6 -> 0 | K6: =I6+J6 -> 0 | L6: =PL!I6 -> 0 | N6: =L6+M6 -> 0 | O6: =PL!K6 -> 0 | Q6: =O6+P6 -> 0
B7: =PL!B7 -> 0 | C7: =PL!C7 -> 0 | E7: =C7+D7 -> 0 | F7: =PL!E7 -> 0 | H7: =F7+G7 -> 0 | I7: =PL!G7 -> 0 | K7: =I7+J7 -> 0 | L7: =PL!I7 -> 0 | N7: =L7+M7 -> 0 | O7: =PL!K7 -> 0 | Q7: =O7+P7 -> 0
B8: =PL!B8 -> 0 | C8: =PL!C8 -> 0 | E8: =C8+D8 -> 0 | F8: =PL!E8 -> 0 | H8: =F8+G8 -> 0 | I8: =PL!G8 -> 0 | K8: =I8+J8 -> 0 | L8: =PL!I8 -> 0 | N8: =L8+M8 -> 0 | O8: =PL!K8 -> 0 | Q8: =O8+P8 -> 0
B9: =PL!B9 -> 0 | C9: =PL!C9 -> 0 | E9: =C9+D9 -> 0 | F9: =PL!E9 -> 0 | H9: =F9+G9 -> 0 | I9: =PL!G9 -> 0 | K9: =I9+J9 -> 0 | L9: =PL!I9 -> 0 | N9: =L9+M9 -> 0 | O9: =PL!K9 -> 0 | Q9: =O9+P9 -> 0
E10: =C10+D10 -> 0 | H10: =F10+G10 -> 0 | K10: =I10+J10 -> 0 | N10: =L10+M10 -> 0 | Q10: =O10+P10 -> 0
B11: 売上高 | C11: =SUM(C5:C10) -> 325866987 | D11: =SUM(D5:D10) -> 0 | E11: =C11+D11 -> 325866987 | F11: =SUM(F5:F10) -> 346561600 | G11: =SUM(G5:G10) -> 0 | H11: =F11+G11 -> 346561600 | I11: =SUM(I5:I10) -> 357540639 | J11: =SUM(J5:J10) -> 0 | K11: =I11+J11 -> 357540639 | L11: =SUM(L5:L10) -> 0 | M11: =SUM(M5:M10) -> 0 | N11: =L11+M11 -> 0 | O11: =SUM(O5:O10) -> 0 | P11: =SUM(P5:P10) -> 0 | Q11: =O11+P11 -> 0
B12: =PL!B12 -> 期首商品棚卸高 | C12: =PL!C12 -> 28930577 | E12: =C12+D12 -> 28930577 | F12: =PL!E12 -> 32079836 | H12: =F12+G12 -> 32079836 | I12: =PL!G12 -> 30240016 | K12: =I12+J12 -> 30240016 | L12: =PL!I12 -> 0 | N12: =L12+M12 -> 0 | O12: =PL!K12 -> 0 | Q12: =O12+P12 -> 0
B13: =PL!B13 -> 当期商品仕入高 | C13: =PL!C13 -> 162685310 | E13: =C13+D13 -> 162685310 | F13: =PL!E13 -> 179686065 | H13: =F13+G13 -> 179686065 | I13: =PL!G13 -> 193114742 | K13: =I13+J13 -> 193114742 | L13: =PL!I13 -> 0 | N13: =L13+M13 -> 0 | O13: =PL!K13 -> 0 | Q13: =O13+P13 -> 0
B14: =PL!B14 -> 仕入値引戻し高 | C14: =PL!C14 -> -18920 | E14: =C14+D14 -> -18920 | F14: =PL!E14 -> 0 | H14: =F14+G14 -> 0 | I14: =PL!G14 -> 0 | K14: =I14+J14 -> 0 | L14: =PL!I14 -> 0 | N14: =L14+M14 -> 0 | O14: =PL!K14 -> 0 | Q14: =O14+P14 -> 0
B15: =PL!B15 -> 期末商品棚卸高 | C15: =PL!C15 -> -32079836 | E15: =C15+D15 -> -32079836 | F15: =PL!E15 -> -30240016 | H15: =F15+G15 -> -30240016 | I15: =PL!G15 -> -26584168 | K15: =I15+J15 -> -26584168 | L15: =PL!I15 -> 0 | N15: =L15+M15 -> 0 | O15: =PL!K15 -> 0 | Q15: =O15+P15 -> 0
B16: 売上原価 | C16: =SUM(C12:C15) -> 159517131 | D16: =SUM(D12:D15) -> 0 | E16: =C16+D16 -> 159517131 | F16: =SUM(F12:F15) -> 181525885 | G16: =SUM(G12:G15) -> 0 | H16: =F16+G16 -> 181525885 | I16: =SUM(I12:I15) -> 196770590 | J16: =SUM(J12:J15) -> 0 | K16: =I16+J16 -> 196770590 | L16: =SUM(L12:L15) -> 0 | M16: =SUM(M12:M15) -> 0 | N16: =L16+M16 -> 0 | O16: =SUM(O12:O15) -> 0 | P16: =SUM(P12:P15) -> 0 | Q16: =O16+P16 -> 0
B17: 売上総利益 | C17: =C11-C16 -> 166349856 | D17: =D11-D16 -> 0 | E17: =C17+D17 -> 166349856 | F17: =F11-F16 -> 165035715 | G17: =G11-G16 -> 0 | H17: =F17+G17 -> 165035715 | I17: =I11-I16 -> 160770049 | J17: =J11-J16 -> 0 | K17: =I17+J17 -> 160770049 | L17: =L11-L16 -> 0 | M17: =M11-M16 -> 0 | N17: =L17+M17 -> 0 | O17: =O11-O16 -> 0 | P17: =P11-P16 -> 0 | Q17: =O17+P17 -> 0
B18: 販売費及び一般管理費 | C18: =修正SGA!C39 -> 145464229 | D18: =修正SGA!D39 | E18: =C18+D18 -> 145464229 | F18: =修正SGA!F39 -> 154261272 | G18: =修正SGA!G39 | H18: =F18+G18 -> 154261272 | I18: =修正SGA!I39 -> 147845764 | J18: =修正SGA!J39 | K18: =I18+J18 -> 147845764 | L18: =修正SGA!L39 -> 0 | N18: =L18+M18 -> 0 | O18: =修正SGA!O39 -> 0 | Q18: =O18+P18 -> 0
B19: 営業利益 | C19: =C17- C18 -> 20885627 | D19: =D17- D18 -> 0 | E19: =C19+D19 -> 20885627 | F19: =F17- F18 -> 10774443 | G19: =G17- G18 -> 0 | H19: =F19+G19 -> 10774443 | I19: =I17- I18 -> 12924285 | J19: =J17- J18 -> 0 | K19: =I19+J19 -> 12924285 | L19: =L17- L18 -> 0 | M19: =M17- M18 -> 0 | N19: =L19+M19 -> 0 | O19: =O17- O18 -> 0 | P19: =P17- P18 -> 0 | Q19: =O19+P19 -> 0
B20: 営業外収益 | C20: =SUM(C21:C27) -> 1273342 | D20: =SUM(D21:D27) -> 0 | E20: =C20+D20 -> 1273342 | F20: =SUM(F21:F27) -> 2398375 | G20: =SUM(G21:G27) -> 0 | H20: =F20+G20 -> 2398375 | I20: =SUM(I21:I27) -> 1051276 | J20: =SUM(J21:J27) -> 0 | K20: =I20+J20 -> 1051276 | L20: =SUM(L21:L27) -> 0 | M20: =SUM(M21:M27) -> 0 | N20: =L20+M20 -> 0 | O20: =SUM(O21:O27) -> 0 | P20: =SUM(P21:P27) -> 0 | Q20: =O20+P20 -> 0
B21: =PL!B21 -> 受取利息 | C21: =PL!C21 -> 292 | D21: =-C21 | E21: =C21+D21 -> 292 | F21: =PL!E21 -> 3285 | G21: =-F21 | H21: =F21+G21 -> 3285 | I21: =PL!G21 -> 76490 | J21: =-I21 | K21: =I21+J21 -> 76490 | L21: =PL!I21 -> 0 | N21: =L21+M21 -> 0 | O21: =PL!K21 -> 0 | Q21: =O21+P21 -> 0
B22: =PL!B22 -> 仕入割引 | C22: =PL!C22 -> 211750 | D22: =-C22 | E22: =C22+D22 -> 211750 | F22: =PL!E22 -> 52250 | G22: =-F22 | H22: =F22+G22 -> 52250 | I22: =PL!G22 -> 0 | J22: =-I22 | K22: =I22+J22 -> 0 | L22: =PL!I22 -> 0 | N22: =L22+M22 -> 0 | O22: =PL!K22 -> 0 | Q22: =O22+P22 -> 0
B23: =PL!B23 -> 貸倒引当金戻入額 | C23: =PL!C23 -> 448000 | D23: =-C23 | E23: =C23+D23 -> 448000 | F23: =PL!E23 -> 457000 | G23: =-F23 | H23: =F23+G23 -> 457000 | I23: =PL!G23 -> 498000 | J23: =-I23 | K23: =I23+J23 -> 498000 | L23: =PL!I23 -> 0 | N23: =L23+M23 -> 0 | O23: =PL!K23 -> 0 | Q23: =O23+P23 -> 0
B24: =PL!B24 -> 雑収入 | C24: =PL!C24 -> 613300 | D24: =-C24 | E24: =C24+D24 -> 613300 | F24: =PL!E24 -> 1885840 | G24: =-F24 | H24: =F24+G24 -> 1885840 | I24: =PL!G24 -> 476786 | J24: =-I24 | K24: =I24+J24 -> 476786 | L24: =PL!I24 -> 0 | N24: =L24+M24 -> 0 | O24: =PL!K24 -> 0 | Q24: =O24+P24 -> 0
B25: =PL!B25 -> 0 | C25: =PL!C25 -> 0 | E25: =C25+D25 -> 0 | F25: =PL!E25 -> 0 | H25: =F25+G25 -> 0 | I25: =PL!G25 -> 0 | K25: =I25+J25 -> 0 | L25: =PL!I25 -> 0 | N25: =L25+M25 -> 0 | O25: =PL!K25 -> 0 | Q25: =O25+P25 -> 0
B26: =PL!B26 -> 0 | C26: =PL!C26 -> 0 | E26: =C26+D26 -> 0 | F26: =PL!E26 -> 0 | H26: =F26+G26 -> 0 | I26: =PL!G26 -> 0 | K26: =I26+J26 -> 0 | L26: =PL!I26 -> 0 | N26: =L26+M26 -> 0 | O26: =PL!K26 -> 0 | Q26: =O26+P26 -> 0
E27: =C27+D27 -> 0 | H27: =F27+G27 -> 0 | K27: =I27+J27 -> 0 | N27: =L27+M27 -> 0 | Q27: =O27+P27 -> 0
B28: 営業外費用 | C28: =SUM(C29:C35) -> 230000 | D28: =SUM(D29:D35) -> 0 | E28: =C28+D28 -> 230000 | F28: =SUM(F29:F35) -> 2287900 | G28: =SUM(G29:G35) -> 0 | H28: =F28+G28 -> 2287900 | I28: =SUM(I29:I35) -> 90040 | J28: =SUM(J29:J35) -> 0 | K28: =I28+J28 -> 90040 | L28: =SUM(L29:L35) -> 0 | M28: =SUM(M29:M35) -> 0 | N28: =L28+M28 -> 0 | O28: =SUM(O29:O35) -> 0 | P28: =SUM(P29:P35) -> 0 | Q28: =O28+P28 -> 0
B29: =PL!B29 -> 支払利息 | C29: =PL!C29 -> 80000 | D29: =-C29 | E29: =C29+D29 -> 80000 | F29: =PL!E29 -> 80000 | G29: =-F29 | H29: =F29+G29 -> 80000 | I29: =PL!G29 -> 80000 | J29: =-I29 | K29: =I29+J29 -> 80000 | L29: =PL!I29 -> 0 | N29: =L29+M29 -> 0 | O29: =PL!K29 -> 0 | Q29: =O29+P29 -> 0
B30: =PL!B30 -> 雑損失 | C30: =PL!C30 -> 150000 | D30: =-C30 | E30: =C30+D30 -> 150000 | F30: =PL!E30 -> 1649900 | G30: =-F30 | H30: =F30+G30 -> 1649900 | I30: =PL!G30 -> 10040 | J30: =-I30 | K30: =I30+J30 -> 10040 | L30: =PL!I30 -> 0 | N30: =L30+M30 -> 0 | O30: =PL!K30 -> 0 | Q30: =O30+P30 -> 0
B31: =PL!B31 -> 固定資産圧縮損 | C31: =PL!C31 -> 0 | D31: =-C31 | E31: =C31+D31 -> 0 | F31: =PL!E31 -> 558000 | G31: =-F31 | H31: =F31+G31 -> 558000 | I31: =PL!G31 -> 0 | J31: =-I31 | K31: =I31+J31 -> 0 | L31: =PL!I31 -> 0 | N31: =L31+M31 -> 0 | O31: =PL!K31 -> 0 | Q31: =O31+P31 -> 0
B32: =PL!B32 -> 0 | C32: =PL!C32 -> 0 | E32: =C32+D32 -> 0 | F32: =PL!E32 -> 0 | H32: =F32+G32 -> 0 | I32: =PL!G32 -> 0 | K32: =I32+J32 -> 0 | L32: =PL!I32 -> 0 | N32: =L32+M32 -> 0 | O32: =PL!K32 -> 0 | Q32: =O32+P32 -> 0
B33: =PL!B33 -> 0 | C33: =PL!C33 -> 0 | E33: =C33+D33 -> 0 | F33: =PL!E33 -> 0 | H33: =F33+G33 -> 0 | I33: =PL!G33 -> 0 | K33: =I33+J33 -> 0 | L33: =PL!I33 -> 0 | N33: =L33+M33 -> 0 | O33: =PL!K33 -> 0 | Q33: =O33+P33 -> 0
B34: =PL!B34 -> 0 | C34: =PL!C34 -> 0 | E34: =C34+D34 -> 0 | F34: =PL!E34 -> 0 | H34: =F34+G34 -> 0 | I34: =PL!G34 -> 0 | K34: =I34+J34 -> 0 | L34: =PL!I34 -> 0 | N34: =L34+M34 -> 0 | O34: =PL!K34 -> 0 | Q34: =O34+P34 -> 0
E35: =C35+D35 -> 0 | H35: =F35+G35 -> 0 | K35: =I35+J35 -> 0 | N35: =L35+M35 -> 0 | Q35: =O35+P35 -> 0
B36: 経常利益 | C36: =C19+C20-C28 -> 21928969 | D36: =D19+D20-D28 -> 0 | E36: =C36+D36 -> 21928969 | F36: =F19+F20-F28 -> 10884918 | G36: =G19+G20-G28 -> 0 | H36: =F36+G36 -> 10884918 | I36: =I19+I20-I28 -> 13885521 | J36: =J19+J20-J28 -> 0 | K36: =I36+J36 -> 13885521 | L36: =L19+L20-L28 -> 0 | M36: =M19+M20-M28 -> 0 | N36: =L36+M36 -> 0 | O36: =O19+O20-O28 -> 0 | P36: =P19+P20-P28 -> 0 | Q36: =O36+P36 -> 0
B37: 特別利益 | C37: =SUM(C38:C43) -> 0 | D37: =SUM(D38:D43) -> 0 | E37: =C37+D37 -> 0 | F37: =SUM(F38:F43) -> 0 | G37: =SUM(G38:G43) -> 0 | H37: =F37+G37 -> 0 | I37: =SUM(I38:I43) -> 0 | J37: =SUM(J38:J43) -> 0 | K37: =I37+J37 -> 0 | L37: =SUM(L38:L43) -> 0 | M37: =SUM(M38:M43) -> 0 | N37: =L37+M37 -> 0 | O37: =SUM(O38:O43) -> 0 | P37: =SUM(P38:P43) -> 0 | Q37: =O37+P37 -> 0
B38: =PL!B38 -> 0 | C38: =PL!C38 -> 0 | E38: =C38+D38 -> 0 | F38: =PL!E38 -> 0 | H38: =F38+G38 -> 0 | I38: =PL!G38 -> 0 | K38: =I38+J38 -> 0 | L38: =PL!I38 -> 0 | N38: =L38+M38 -> 0 | O38: =PL!K38 -> 0 | Q38: =O38+P38 -> 0
B39: =PL!B39 -> 0 | C39: =PL!C39 -> 0 | E39: =C39+D39 -> 0 | F39: =PL!E39 -> 0 | H39: =F39+G39 -> 0 | I39: =PL!G39 -> 0 | K39: =I39+J39 -> 0 | L39: =PL!I39 -> 0 | N39: =L39+M39 -> 0 | O39: =PL!K39 -> 0 | Q39: =O39+P39 -> 0
B40: =PL!B40 -> 0 | C40: =PL!C40 -> 0 | E40: =C40+D40 -> 0 | F40: =PL!E40 -> 0 | H40: =F40+G40 -> 0 | I40: =PL!G40 -> 0 | K40: =I40+J40 -> 0 | L40: =PL!I40 -> 0 | N40: =L40+M40 -> 0 | O40: =PL!K40 -> 0 | Q40: =O40+P40 -> 0
B41: =PL!B41 -> 0 | C41: =PL!C41 -> 0 | E41: =C41+D41 -> 0 | F41: =PL!E41 -> 0 | H41: =F41+G41 -> 0 | I41: =PL!G41 -> 0 | K41: =I41+J41 -> 0 | L41: =PL!I41 -> 0 | N41: =L41+M41 -> 0 | O41: =PL!K41 -> 0 | Q41: =O41+P41 -> 0
B42: =PL!B42 -> 0 | C42: =PL!C42 -> 0 | E42: =C42+D42 -> 0 | F42: =PL!E42 -> 0 | H42: =F42+G42 -> 0 | I42: =PL!G42 -> 0 | K42: =I42+J42 -> 0 | L42: =PL!I42 -> 0 | N42: =L42+M42 -> 0 | O42: =PL!K42 -> 0 | Q42: =O42+P42 -> 0
E43: =C43+D43 -> 0 | H43: =F43+G43 -> 0 | K43: =I43+J43 -> 0 | N43: =L43+M43 -> 0 | Q43: =O43+P43 -> 0
B44: 特別損失 | C44: =SUM(C45:C50) -> 44117 | D44: =SUM(D45:D50) -> 0 | E44: =C44+D44 -> 44117 | F44: =SUM(F45:F50) -> 0 | G44: =SUM(G45:G50) -> 0 | H44: =F44+G44 -> 0 | I44: =SUM(I45:I50) -> 0 | J44: =SUM(J45:J50) -> 0 | K44: =I44+J44 -> 0 | L44: =SUM(L45:L50) -> 0 | M44: =SUM(M45:M50) -> 0 | N44: =L44+M44 -> 0 | O44: =SUM(O45:O50) -> 0 | P44: =SUM(P45:P50) -> 0 | Q44: =O44+P44 -> 0
B45: =PL!B45 -> 固定資産除却損 | C45: =PL!C45 -> 44117 | D45: =-C45 | E45: =C45+D45 -> 44117 | F45: =PL!E45 -> 0 | G45: =-F45 | H45: =F45+G45 -> 0 | I45: =PL!G45 -> 0 | J45: =-I45 | K45: =I45+J45 -> 0 | L45: =PL!I45 -> 0 | N45: =L45+M45 -> 0 | O45: =PL!K45 -> 0 | Q45: =O45+P45 -> 0
B46: =PL!B46 -> 0 | C46: =PL!C46 -> 0 | E46: =C46+D46 -> 0 | F46: =PL!E46 -> 0 | H46: =F46+G46 -> 0 | I46: =PL!G46 -> 0 | K46: =I46+J46 -> 0 | L46: =PL!I46 -> 0 | N46: =L46+M46 -> 0 | O46: =PL!K46 -> 0 | Q46: =O46+P46 -> 0
B47: =PL!B47 -> 0 | C47: =PL!C47 -> 0 | E47: =C47+D47 -> 0 | F47: =PL!E47 -> 0 | H47: =F47+G47 -> 0 | I47: =PL!G47 -> 0 | K47: =I47+J47 -> 0 | L47: =PL!I47 -> 0 | N47: =L47+M47 -> 0 | O47: =PL!K47 -> 0 | Q47: =O47+P47 -> 0
B48: =PL!B48 -> 0 | C48: =PL!C48 -> 0 | E48: =C48+D48 -> 0 | F48: =PL!E48 -> 0 | H48: =F48+G48 -> 0 | I48: =PL!G48 -> 0 | K48: =I48+J48 -> 0 | L48: =PL!I48 -> 0 | N48: =L48+M48 -> 0 | O48: =PL!K48 -> 0 | Q48: =O48+P48 -> 0
B49: =PL!B49 -> 0 | C49: =PL!C49 -> 0 | E49: =C49+D49 -> 0 | F49: =PL!E49 -> 0 | H49: =F49+G49 -> 0 | I49: =PL!G49 -> 0 | K49: =I49+J49 -> 0 | L49: =PL!I49 -> 0 | N49: =L49+M49 -> 0 | O49: =PL!K49 -> 0 | Q49: =O49+P49 -> 0
E50: =C50+D50 -> 0 | H50: =F50+G50 -> 0 | K50: =I50+J50 -> 0 | N50: =L50+M50 -> 0 | Q50: =O50+P50 -> 0
B51: 税引前当期純利益 | C51: =C36+C37-C44 -> 21884852 | D51: =D36+D37-D44 -> 0 | E51: =C51+D51 -> 21884852 | F51: =F36+F37-F44 -> 10884918 | G51: =G36+G37-G44 -> 0 | H51: =F51+G51 -> 10884918 | I51: =I36+I37-I44 -> 13885521 | J51: =J36+J37-J44 -> 0 | K51: =I51+J51 -> 13885521 | L51: =L36+L37-L44 -> 0 | M51: =M36+M37-M44 -> 0 | N51: =L51+M51 -> 0 | O51: =O36+O37-O44 -> 0 | P51: =P36+P37-P44 -> 0 | Q51: =O51+P51 -> 0
B52: 法人税等 | C52: =SUM(C53:C55) -> 6900842 | D52: =SUM(D53:D55) -> 0 | E52: =C52+D52 -> 6900842 | F52: =SUM(F53:F55) -> 2204697 | G52: =SUM(G53:G55) -> 0 | H52: =F52+G52 -> 2204697 | I52: =SUM(I53:I55) -> 4214309 | J52: =SUM(J53:J55) -> 0 | K52: =I52+J52 -> 4214309 | L52: =SUM(L53:L55) -> 0 | M52: =SUM(M53:M55) -> 0 | N52: =L52+M52 -> 0 | O52: =SUM(O53:O55) -> 0 | P52: =SUM(P53:P55) -> 0 | Q52: =O52+P52 -> 0
B53: =PL!B53 -> 法人税等 | C53: =PL!C53 -> 6900842 | E53: =C53+D53 -> 6900842 | F53: =PL!E53 -> 2204697 | H53: =F53+G53 -> 2204697 | I53: =PL!G53 -> 4214309 | K53: =I53+J53 -> 4214309 | L53: =PL!I53 -> 0 | N53: =L53+M53 -> 0 | O53: =PL!K53 -> 0 | Q53: =O53+P53 -> 0
B54: =PL!B54 -> 0 | C54: =PL!C54 -> 0 | E54: =C54+D54 -> 0 | F54: =PL!E54 -> 0 | H54: =F54+G54 -> 0 | I54: =PL!G54 -> 0 | K54: =I54+J54 -> 0 | L54: =PL!I54 -> 0 | N54: =L54+M54 -> 0 | O54: =PL!K54 -> 0 | Q54: =O54+P54 -> 0
E55: =C55+D55 -> 0 | H55: =F55+G55 -> 0 | K55: =I55+J55 -> 0 | N55: =L55+M55 -> 0 | Q55: =O55+P55 -> 0
B56: 税引後当期純利益 | C56: =C51-C52 -> 14984010 | D56: =D51-D52 -> 0 | E56: =C56+D56 -> 14984010 | F56: =F51-F52 -> 8680221 | G56: =G51-G52 -> 0 | H56: =F56+G56 -> 8680221 | I56: =I51-I52 -> 9671212 | J56: =J51-J52 -> 0 | K56: =I56+J56 -> 9671212 | L56: =L51-L52 -> 0 | M56: =M51-M52 -> 0 | N56: =L56+M56 -> 0 | O56: =O51-O52 -> 0 | P56: =P51-P52 -> 0 | Q56: =O56+P56 -> 0
C58: 14984010 | F58: 8680221 | I58: 9671212
C59: =C58=C56 -> TRUE | F59: =F58=F56 -> TRUE | I59: =I58=I56 -> TRUE | L59: =L58=L56 -> TRUE | O59: =O58=O56 -> TRUE

Sheet 修正SGA
K2: (単位：千円)
B3: 科目 | C3: ='BS(借方)'!C4 -> 23年12月期 | F3: ='BS(借方)'!D4 -> 24年12月期 | I3: ='BS(借方)'!E4 -> 25年12月期 | L3: ='BS(借方)'!F4 -> ●●年●月期 | O3: ='BS(借方)'!G4 -> ●●年●月 （●か月TB）
C4: 帳簿価額 | D4: 修正額 | E4: 修正後 | F4: 帳簿価額 | G4: 修正額 | H4: 修正後 | I4: 帳簿価額 | J4: 修正額 | K4: 修正後 | L4: 帳簿価額 | M4: 修正額 | N4: 修正後 | O4: 帳簿価額 | P4: 修正額 | Q4: 修正後
B5: =SGA!B6 -> 役員報酬 | C5: =SGA!C6 -> 10500000 | E5: =C5+D5 -> 10500000 | F5: =SGA!E6 -> 17120000 | H5: =F5+G5 -> 17120000 | I5: =SGA!G6 -> 11870000 | K5: =I5+J5 -> 11870000 | L5: =SGA!I6 -> 0 | N5: =L5+M5 -> 0 | O5: =SGA!K6 -> 0 | Q5: =O5+P5 -> 0
B6: =SGA!B7 -> 給料手当 | C6: =SGA!C7 -> 64348988 | E6: =C6+D6 -> 64348988 | F6: =SGA!E7 -> 65194441 | H6: =F6+G6 -> 65194441 | I6: =SGA!G7 -> 64753816 | K6: =I6+J6 -> 64753816 | L6: =SGA!I7 -> 0 | N6: =L6+M6 -> 0 | O6: =SGA!K7 -> 0 | Q6: =O6+P6 -> 0
B7: =SGA!B8 -> 賞与 | C7: =SGA!C8 -> 3549000 | E7: =C7+D7 -> 3549000 | F7: =SGA!E8 -> 3405000 | H7: =F7+G7 -> 3405000 | I7: =SGA!G8 -> 3197000 | K7: =I7+J7 -> 3197000 | L7: =SGA!I8 -> 0 | N7: =L7+M7 -> 0 | O7: =SGA!K8 -> 0 | Q7: =O7+P7 -> 0
B8: =SGA!B9 -> 退職金 | C8: =SGA!C9 -> 370000 | D8: =-C8 | E8: =C8+D8 -> 370000 | F8: =SGA!E9 -> 0 | H8: =F8+G8 -> 0 | I8: =SGA!G9 -> 0 | K8: =I8+J8 -> 0 | L8: =SGA!I9 -> 0 | N8: =L8+M8 -> 0 | O8: =SGA!K9 -> 0 | Q8: =O8+P8 -> 0
B9: =SGA!B10 -> 法定福利費 | C9: =SGA!C10 -> 11424051 | E9: =C9+D9 -> 11424051 | F9: =SGA!E10 -> 12207732 | H9: =F9+G9 -> 12207732 | I9: =SGA!G10 -> 10842135 | K9: =I9+J9 -> 10842135 | L9: =SGA!I10 -> 0 | N9: =L9+M9 -> 0 | O9: =SGA!K10 -> 0 | Q9: =O9+P9 -> 0
B10: =SGA!B11 -> 福利厚生費 | C10: =SGA!C11 -> 1851569 | E10: =C10+D10 -> 1851569 | F10: =SGA!E11 -> 2218165 | H10: =F10+G10 -> 2218165 | I10: =SGA!G11 -> 2913601 | K10: =I10+J10 -> 2913601 | L10: =SGA!I11 -> 0 | N10: =L10+M10 -> 0 | O10: =SGA!K11 -> 0 | Q10: =O10+P10 -> 0
B11: =SGA!B12 -> 採用教育費 | C11: =SGA!C12 -> 291360 | E11: =C11+D11 -> 291360 | F11: =SGA!E12 -> 184800 | H11: =F11+G11 -> 184800 | I11: =SGA!G12 -> 88700 | K11: =I11+J11 -> 88700 | L11: =SGA!I12 -> 0 | N11: =L11+M11 -> 0 | O11: =SGA!K12 -> 0 | Q11: =O11+P11 -> 0
B12: =SGA!B13 -> 広告宣伝費 | C12: =SGA!C13 -> 1200593 | E12: =C12+D12 -> 1200593 | F12: =SGA!E13 -> 1208388 | H12: =F12+G12 -> 1208388 | I12: =SGA!G13 -> 1053123 | K12: =I12+J12 -> 1053123 | L12: =SGA!I13 -> 0 | N12: =L12+M12 -> 0 | O12: =SGA!K13 -> 0 | Q12: =O12+P12 -> 0
B13: =SGA!B14 -> 接待交際費 | C13: =SGA!C14 -> 547960 | E13: =C13+D13 -> 547960 | F13: =SGA!E14 -> 180010 | H13: =F13+G13 -> 180010 | I13: =SGA!G14 -> 86721 | K13: =I13+J13 -> 86721 | L13: =SGA!I14 -> 0 | N13: =L13+M13 -> 0 | O13: =SGA!K14 -> 0 | Q13: =O13+P13 -> 0
B14: =SGA!B15 -> 会議費 | C14: =SGA!C15 -> 272805 | E14: =C14+D14 -> 272805 | F14: =SGA!E15 -> 366979 | H14: =F14+G14 -> 366979 | I14: =SGA!G15 -> 459575 | K14: =I14+J14 -> 459575 | L14: =SGA!I15 -> 0 | N14: =L14+M14 -> 0 | O14: =SGA!K15 -> 0 | Q14: =O14+P14 -> 0
B15: =SGA!B16 -> 旅費交通費 | C15: =SGA!C16 -> 2801560 | E15: =C15+D15 -> 2801560 | F15: =SGA!E16 -> 2701132 | H15: =F15+G15 -> 2701132 | I15: =SGA!G16 -> 2770899 | K15: =I15+J15 -> 2770899 | L15: =SGA!I16 -> 0 | N15: =L15+M15 -> 0 | O15: =SGA!K16 -> 0 | Q15: =O15+P15 -> 0
B16: =SGA!B17 -> 通信費 | C16: =SGA!C17 -> 1043002 | E16: =C16+D16 -> 1043002 | F16: =SGA!E17 -> 1254118 | H16: =F16+G16 -> 1254118 | I16: =SGA!G17 -> 1367473 | K16: =I16+J16 -> 1367473 | L16: =SGA!I17 -> 0 | N16: =L16+M16 -> 0 | O16: =SGA!K17 -> 0 | Q16: =O16+P16 -> 0
B17: =SGA!B18 -> 消耗品費 | C17: =SGA!C18 -> 2345684 | E17: =C17+D17 -> 2345684 | F17: =SGA!E18 -> 4467693 | H17: =F17+G17 -> 4467693 | I17: =SGA!G18 -> 3124510 | K17: =I17+J17 -> 3124510 | L17: =SGA!I18 -> 0 | N17: =L17+M17 -> 0 | O17: =SGA!K18 -> 0 | Q17: =O17+P17 -> 0
B18: =SGA!B19 -> 事務用消耗品費 | C18: =SGA!C19 -> 1991419 | E18: =C18+D18 -> 1991419 | F18: =SGA!E19 -> 1929685 | H18: =F18+G18 -> 1929685 | I18: =SGA!G19 -> 1771435 | K18: =I18+J18 -> 1771435 | L18: =SGA!I19 -> 0 | N18: =L18+M18 -> 0 | O18: =SGA!K19 -> 0 | Q18: =O18+P18 -> 0
B19: =SGA!B20 -> 修繕費 | C19: =SGA!C20 -> 805390 | E19: =C19+D19 -> 805390 | F19: =SGA!E20 -> 926390 | H19: =F19+G19 -> 926390 | I19: =SGA!G20 -> 532686 | K19: =I19+J19 -> 532686 | L19: =SGA!I20 -> 0 | N19: =L19+M19 -> 0 | O19: =SGA!K20 -> 0 | Q19: =O19+P19 -> 0
B20: =SGA!B21 -> 水道光熱費 | C20: =SGA!C21 -> 1033592 | E20: =C20+D20 -> 1033592 | F20: =SGA!E21 -> 1113959 | H20: =F20+G20 -> 1113959 | I20: =SGA!G21 -> 1037468 | K20: =I20+J20 -> 1037468 | L20: =SGA!I21 -> 0 | N20: =L20+M20 -> 0 | O20: =SGA!K21 -> 0 | Q20: =O20+P20 -> 0
... B29: =SGA!B30 -> 長期前払費用償却 | C29: =SGA!C30 -> 571543 | E29: =C29+D29 -> 571543 | F29: =SGA!E30 -> 578416 | H29: =F29+G29 -> 578416 | I29: =SGA!G30 -> 579928 | K29: =I29+J29 -> 579928 | L29: =SGA!I30 -> 0 | N29: =L29+M29 -> 0 | O29: =SGA!K30 -> 0 | Q29: =O29+P29 -> 0
B30: =SGA!B31 -> 貸倒引当金繰入額 | C30: =SGA!C31 -> 457000 | D30: =-C30 | E30: =C30+D30 -> 457000 | F30: =SGA!E31 -> 498000 | G30: =-F30 | H30: =F30+G30 -> 498000 | I30: =SGA!G31 -> 524000 | J30: =-I30 | K30: =I30+J30 -> 524000 | L30: =SGA!I31 -> 0 | N30: =L30+M30 -> 0 | O30: =SGA!K31 -> 0 | Q30: =O30+P30 -> 0
B31: =SGA!B32 -> 雑費 | C31: =SGA!C32 -> 227878 | E31: =C31+D31 -> 227878 | F31: =SGA!E32 -> 290290 | H31: =F31+G31 -> 290290 | I31: =SGA!G32 -> 435586 | K31: =I31+J31 -> 435586 | L31: =SGA!I32 -> 0 | N31: =L31+M31 -> 0 | O31: =SGA!K32 -> 0 | Q31: =O31+P31 -> 0
B32: =SGA!B33 -> 派遣料 | C32: =SGA!C33 -> 2346637 | E32: =C32+D32 -> 2346637 | F32: =SGA!E33 -> 1711213 | H32: =F32+G32 -> 1711213 | I32: =SGA!G33 -> 2846031 | K32: =I32+J32 -> 2846031 | L32: =SGA!I33 -> 0 | N32: =L32+M32 -> 0 | O32: =SGA!K33 -> 0 | Q32: =O32+P32 -> 0
B33: =SGA!B34 -> 管理諸費 | C33: =SGA!C34 -> 3649888 | E33: =C33+D33 -> 3649888 | F33: =SGA!E34 -> 3432539 | H33: =F33+G33 -> 3432539 | I33: =SGA!G34 -> 3705328 | K33: =I33+J33 -> 3705328 | L33: =SGA!I34 -> 0 | N33: =L33+M33 -> 0 | O33: =SGA!K34 -> 0 | Q33: =O33+P33 -> 0
B34: =SGA!B35 -> 0 | C34: =SGA!C35 -> 0 | E34: =C34+D34 -> 0 | F34: =SGA!E35 -> 0 | H34: =F34+G34 -> 0 | I34: =SGA!G35 -> 0 | K34: =I34+J34 -> 0 | L34: =SGA!I35 -> 0 | N34: =L34+M34 -> 0 | O34: =SGA!K35 -> 0 | Q34: =O34+P34 -> 0
E35: =C35+D35 -> 0 | H35: =F35+G35 -> 0 | K35: =I35+J35 -> 0 | N35: =L35+M35 -> 0 | Q35: =O35+P35 -> 0
E36: =C36+D36 -> 0 | H36: =F36+G36 -> 0 | K36: =I36+J36 -> 0 | N36: =L36+M36 -> 0 | Q36: =O36+P36 -> 0
E37: =C37+D37 -> 0 | H37: =F37+G37 -> 0 | K37: =I37+J37 -> 0 | N37: =L37+M37 -> 0 | Q37: =O37+P37 -> 0
E38: =C38+D38 -> 0 | H38: =F38+G38 -> 0 | K38: =I38+J38 -> 0 | N38: =L38+M38 -> 0 | Q38: =O38+P38 -> 0
B39: 販売費および一般管理費合計 | C39: =SUM(C5:C38) -> 145464229 | D39: =SUM(D5:D38) -> 0 | E39: =C39+D39 -> 145464229 | F39: =SUM(F5:F38) -> 154261272 | G39: =SUM(G5:G38) -> 0 | H39: =F39+G39 -> 154261272 | I39: =SUM(I5:I38) -> 147845764 | J39: =SUM(J5:J38) -> 0 | K39: =I39+J39 -> 147845764 | L39: =SUM(L5:L38) -> 0 | M39: =SUM(M5:M38) -> 0 | N39: =L39+M39 -> 0 | O39: =SUM(O5:O38) -> 0 | P39: =SUM(P5:P38) -> 0 | Q39: =O39+P39 -> 0

Sheet 修正CR
K2: (単位：千円)
B3: 科目 | C3: ='BS(借方)'!C4 -> 23年12月期 | F3: ='BS(借方)'!D4 -> 24年12月期 | I3: ='BS(借方)'!E4 -> 25年12月期 | L3: ='BS(借方)'!F4 -> ●●年●月期 | O3: ='BS(借方)'!G4 -> ●●年●月 （●か月TB）
C4: 帳簿価額 | D4: 修正額 | E4: 修正後 | F4: 帳簿価額 | G4: 修正額 | H4: 修正後 | I4: 帳簿価額 | J4: 修正額 | K4: 修正後 | L4: 帳簿価額 | M4: 修正額 | N4: 修正後 | O4: 帳簿価額 | P4: 修正額 | Q4: 修正後
B5: 期首原材料棚卸高 | C5: 500000 | D5: -500000 | E5: =C5+D5 -> 0 | F5: 500000 | G5: -500000 | H5: =F5+G5 -> 0 | I5: 500000 | J5: -500000 | K5: =I5+J5 -> 0 | L5: 500000 | M5: -500000 | N5: =L5+M5 -> 0 | O5: 500000 | P5: -500000 | Q5: =O5+P5 -> 0
B6: 原材料仕入高 | E6: =C6+D6 -> 0 | H6: =F6+G6 -> 0 | K6: =I6+J6 -> 0 | N6: =L6+M6 -> 0 | Q6: =O6+P6 -> 0
B7: 小計 | E7: =C7+D7 -> 0 | H7: =F7+G7 -> 0 | K7: =I7+J7 -> 0 | N7: =L7+M7 -> 0 | Q7: =O7+P7 -> 0
B8: 期末原材料棚卸高 | E8: =C8+D8 -> 0 | H8: =F8+G8 -> 0 | K8: =I8+J8 -> 0 | N8: =L8+M8 -> 0 | Q8: =O8+P8 -> 0
E9: =C9+D9 -> 0 | H9: =F9+G9 -> 0 | K9: =I9+J9 -> 0 | N9: =L9+M9 -> 0 | Q9: =O9+P9 -> 0
E10: =C10+D10 -> 0 | H10: =F10+G10 -> 0 | K10: =I10+J10 -> 0 | N10: =L10+M10 -> 0 | Q10: =O10+P10 -> 0
B11: 材料費 | C11: =SUM(C5:C10) -> 500000 | D11: =SUM(D5:D10) -> -500000 | E11: =C11+D11 -> 0 | F11: =SUM(F5:F10) -> 500000 | G11: =SUM(G5:G10) -> -500000 | H11: =F11+G11 -> 0 | I11: =SUM(I5:I10) -> 500000 | J11: =SUM(J5:J10) -> -500000 | K11: =I11+J11 -> 0 | L11: =SUM(L5:L10) -> 500000 | M11: =SUM(M5:M10) -> -500000 | N11: =L11+M11 -> 0 | O11: =SUM(O5:O10) -> 500000 | P11: =SUM(P5:P10) -> -500000 | Q11: =O11+P11 -> 0
E12: =C12+D12 -> 0 | H12: =F12+G12 -> 0 | K12: =I12+J12 -> 0 | N12: =L12+M12 -> 0 | Q12: =O12+P12 -> 0
E13: =C13+D13 -> 0 | H13: =F13+G13 -> 0 | K13: =I13+J13 -> 0 | N13: =L13+M13 -> 0 | Q13: =O13+P13 -> 0
E14: =C14+D14 -> 0 | H14: =F14+G14 -> 0 | K14: =I14+J14 -> 0 | N14: =L14+M14 -> 0 | Q14: =O14+P14 -> 0
E15: =C15+D15 -> 0 | H15: =F15+G15 -> 0 | K15: =I15+J15 -> 0 | N15: =L15+M15 -> 0 | Q15: =O15+P15 -> 0
E16: =C16+D16 -> 0 | H16: =F16+G16 -> 0 | K16: =I16+J16 -> 0 | N16: =L16+M16 -> 0 | Q16: =O16+P16 -> 0
E17: =C17+D17 -> 0 | H17: =F17+G17 -> 0 | K17: =I17+J17 -> 0 | N17: =L17+M17 -> 0 | Q17: =O17+P17 -> 0
B18: 労務費 | C18: =SUM(C12:C17) -> 0 | D18: =SUM(D12:D17) -> 0 | E18: =C18+D18 -> 0 | F18: =SUM(F12:F17) -> 0 | G18: =SUM(G12:G17) -> 0 | H18: =F18+G18 -> 0 | I18: =SUM(I12:I17) -> 0 | J18: =SUM(J12:J17) -> 0 | K18: =I18+J18 -> 0 | L18: =SUM(L12:L17) -> 0 | M18: =SUM(M12:M17) -> 0 | N18: =L18+M18 -> 0 | O18: =SUM(O12:O17) -> 0 | P18: =SUM(P12:P17) -> 0 | Q18: =O18+P18 -> 0
E19: =C19+D19 -> 0 | H19: =F19+G19 -> 0 | K19: =I19+J19 -> 0 | N19: =L19+M19 -> 0 | Q19: =O19+P19 -> 0
E20: =C20+D20 -> 0 | H20: =F20+G20 -> 0 | K20: =I20+J20 -> 0 | N20: =L20+M20 -> 0 | Q20: =O20+P20 -> 0
E21: =C21+D21 -> 0 | H21: =F21+G21 -> 0 | K21: =I21+J21 -> 0 | N21: =L21+M21 -> 0 | Q21: =O21+P21 -> 0
E22: =C22+D22 -> 0 | H22: =F22+G22 -> 0 | K22: =I22+J22 -> 0 | N22: =L22+M22 -> 0 | Q22: =O22+P22 -> 0
E23: =C23+D23 -> 0 | H23: =F23+G23 -> 0 | K23: =I23+J23 -> 0 | N23: =L23+M23 -> 0 | Q23: =O23+P23 -> 0
E24: =C24+D24 -> 0 | H24: =F24+G24 -> 0 | K24: =I24+J24 -> 0 | N24: =L24+M24 -> 0 | Q24: =O24+P24 -> 0
B25: 外注加工費 | C25: =SUM(C19:C24) -> 0 | D25: =SUM(D19:D24) -> 0 | E25: =C25+D25 -> 0 | F25: =SUM(F19:F24) -> 0 | G25: =SUM(G19:G24) -> 0 | H25: =F25+G25 -> 0 | I25: =SUM(I19:I24) -> 0 | J25: =SUM(J19:J24) -> 0 | K25: =I25+J25 -> 0 | L25: =SUM(L19:L24) -> 0 | M25: =SUM(M19:M24) -> 0 | N25: =L25+M25 -> 0 | O25: =SUM(O19:O24) -> 0 | P25: =SUM(P19:P24) -> 0 | Q25: =O25+P25 -> 0
E26: =C26+D26 -> 0 | H26: =F26+G26 -> 0 | K26: =I26+J26 -> 0 | N26: =L26+M26 -> 0 | Q26: =O26+P26 -> 0
E27: =C27+D27 -> 0 | H27: =F27+G27 -> 0 | K27: =I27+J27 -> 0 | N27: =L27+M27 -> 0 | Q27: =O27+P27 -> 0
E28: =C28+D28 -> 0 | H28: =F28+G28 -> 0 | K28: =I28+J28 -> 0 | N28: =L28+M28 -> 0 | Q28: =O28+P28 -> 0
E29: =C29+D29 -> 0 | H29: =F29+G29 -> 0 | K29: =I29+J29 -> 0 | N29: =L29+M29 -> 0 | Q29: =O29+P29 -> 0
E30: =C30+D30 -> 0 | H30: =F30+G30 -> 0 | K30: =I30+J30 -> 0 | N30: =L30+M30 -> 0 | Q30: =O30+P30 -> 0
E31: =C31+D31 -> 0 | H31: =F31+G31 -> 0 | K31: =I31+J31 -> 0 | N31: =L31+M31 -> 0 | Q31: =O31+P31 -> 0
E32: =C32+D32 -> 0 | H32: =F32+G32 -> 0 | K32: =I32+J32 -> 0 | N32: =L32+M32 -> 0 | Q32: =O32+P32 -> 0
E33: =C33+D33 -> 0 | H33: =F33+G33 -> 0 | K33: =I33+J33 -> 0 | N33: =L33+M33 -> 0 | Q33: =O33+P33 -> 0
E34: =C34+D34 -> 0 | H34: =F34+G34 -> 0 | K34: =I34+J34 -> 0 | N34: =L34+M34 -> 0 | Q34: =O34+P34 -> 0
E35: =C35+D35 -> 0 | H35: =F35+G35 -> 0 | K35: =I35+J35 -> 0 | N35: =L35+M35 -> 0 | Q35: =O35+P35 -> 0
B36: 経費 | C36: =SUM(C26:C35) -> 0 | D36: =SUM(D26:D35) -> 0 | E36: =C36+D36 -> 0 | F36: =SUM(F26:F35) -> 0 | G36: =SUM(G26:G35) -> 0 | H36: =F36+G36 -> 0 | I36: =SUM(I26:I35) -> 0 | J36: =SUM(J26:J35) -> 0 | K36: =I36+J36 -> 0 | L36: =SUM(L26:L35) -> 0 | M36: =SUM(M26:M35) -> 0 | N36: =L36+M36 -> 0 | O36: =SUM(O26:O35) -> 0 | P36: =SUM(P26:P35) -> 0 | Q36: =O36+P36 -> 0
B37: 当期製造費用 | C37: =C11+C18+C25+C36 -> 500000 | D37: =D11+D18+D25+D36 -> -500000 | E37: =C37+D37 -> 0 | F37: =F11+F18+F25+F36 -> 500000 | G37: =G11+G18+G25+G36 -> -500000 | H37: =F37+G37 -> 0 | I37: =I11+I18+I25+I36 -> 500000 | J37: =J11+J18+J25+J36 -> -500000 | K37: =I37+J37 -> 0 | L37: =L11+L18+L25+L36 -> 500000 | M37: =M11+M18+M25+M36 -> -500000 | N37: =L37+M37 -> 0 | O37: =O11+O18+O25+O36 -> 500000 | P37: =P11+P18+P25+P36 -> -500000 | Q37: =O37+P37 -> 0
B38: 期首仕掛品棚卸高 | E38: =C38+D38 -> 0 | H38: =F38+G38 -> 0 | K38: =I38+J38 -> 0 | N38: =L38+M38 -> 0 | Q38: =O38+P38 -> 0
B39: 合計 | C39: =SUM(C37:C38) -> 500000 | D39: =SUM(D37:D38) -> -500000 | E39: =C39+D39 -> 0 | F39: =SUM(F37:F38) -> 500000 | G39: =SUM(G37:G38) -> -500000 | H39: =F39+G39 -> 0 | I39: =SUM(I37:I38) -> 500000 | J39: =SUM(J37:J38) -> -500000 | K39: =I39+J39 -> 0 | L39: =SUM(L37:L38) -> 500000 | M39: =SUM(M37:M38) -> -500000 | N39: =L39+M39 -> 0 | O39: =SUM(O37:O38) -> 500000 | P39: =SUM(P37:P38) -> -500000 | Q39: =O39+P39 -> 0
B40: 期末仕掛品棚卸高 | E40: =C40+D40 -> 0 | H40: =F40+G40 -> 0 | K40: =I40+J40 -> 0 | N40: =L40+M40 -> 0 | Q40: =O40+P40 -> 0
B41: 当期製造原価 | C41: =C39-C40 -> 500000 | D41: =D39-D40 -> -500000 | E41: =C41+D41 -> 0 | F41: =F39-F40 -> 500000 | G41: =G39-G40 -> -500000 | H41: =F41+G41 -> 0 | I41: =I39-I40 -> 500000 | J41: =J39-J40 -> -500000 | K41: =I41+J41 -> 0 | L41: =L39-L40 -> 500000 | M41: =M39-M40 -> -500000 | N41: =L41+M41 -> 0 | O41: =O39-O40 -> 500000 | P41: =P39-P40 -> -500000 | Q41: =O41+P41 -> 0

Sheet 年買法
C2: (単位：千円) | H2: (単位：千円) | M2: (単位：千円)
B3: =修正PL!I3 | C3: 金額 | F3: =修正PL!C3 | G3: =修正PL!F3 | H3: =修正PL!I3 | J3: 営業権倍率 | K3: x1 | L3: x2 | M3: x3
B4: 簿価純資産額 | C4: ='BS (貸方)'!E50 | E4: 簿価営業利益 | F4: =修正PL!C19 | G4: =修正PL!F19 | H4: =修正PL!I19 | J4: 時価純資産 | K4: =C7
B5: 修正額 | C5: ='修正BS(貸方) '!D50 | E5: 修正額 | F5: =修正PL!D19 | G5: =修正PL!G19 | H5: =修正PL!J19 | J5: 営業権 | K5: =H10*1 | L5: =H10*2 | M5: =H10*3
B6: 税効果 | C6: ='修正BS(貸方) '!D51 | E6: 修正後営業利益 | F6: =SUM(F4:F5) -> 350000000 | G6: =SUM(G4:G5) -> 350000000 | H6: =SUM(H4:H5) -> 350000000 | J6: 想定株式価値 | K6: =K4+K5 | L6: =K4+L5 | M6: =K4+M5
B7: 時価純資産 | C7: =SUM(C4:C6) -> 333000000 | E7: 税考慮額 | F7: =-F6*0.34 -> -1.19e+08 | G7: =-G6*0.34 -> -1.19e+08 | H7: =-H6*0.34 -> -1.19e+08
E8: 修正後税考慮後営業利益 | F8: =SUM(F6:F7) -> 231000000 | G8: =SUM(G6:G7) | H8: =SUM(H6:H7)
G10: 基準営業利益 | H10: =AVERAGE(F8:H8)

Sheet EV EBITDAマルチプル
C2: (単位：千円) | H2: (単位：千円) | M2: (単位：千円)
B3: =修正PL!I3 | C3: 金額 | F3: =修正PL!C3 | G3: =修正PL!F3 | H3: =修正PL!I3 | J3: マルチプル倍率 | K3: x3 | L3: x4 | M3: x5
B4: キャッシュライク | C4: =ネットキャッシュ!C13 | E4: 簿価営業利益 | F4: =修正PL!C19 | G4: =修正PL!F19 | H4: =修正PL!I19 | J4: EV（EBITDA×倍率） | K4: =H10*3 | L4: =H10*4 | M4: =H10*5
B5: デットライク | C5: =ネットキャッシュ!F13 | E5: 修正額 | F5: =修正PL!D19 | G5: =修正PL!G19 | H5: =修正PL!J19 | J5: 非流動性ディスカウント | K5: =-K4*0.1 | L5: =-L4*0.1 | M5: =-M4*0.1
B6: ネットキャッシュ | C6: =C4-C5 -> 250000000 | E6: 修正後営業利益 | F6: =SUM(F4:F5) -> 350000000 | G6: =SUM(G4:G5) -> 450000000 | H6: =SUM(H4:H5) -> 350000000 | J6: =B6 -> ネットキャッシュ | K6: =C6 -> 250000000
E7: 減価償却費・長期前払費用償却 | F7: =修正SGA!E28+修正SGA!E29 | G7: =修正SGA!H28+修正SGA!H29 | H7: =修正SGA!K28+修正SGA!K29 | J7: 想定株式価値 | K7: =SUM(K4:K6) | L7: =SUM(L4:L5)+K6 | M7: =SUM(M4:M5)+K6
E8: 修正後EBITDA | F8: =SUM(F6:F7) -> 360000000 | G8: =SUM(G6:G7) -> 460000000 | H8: =SUM(H6:H7) -> 360000000
G10: 基準EBITDA | H10: =AVERAGE(F8:H8)

Sheet 参照企業
E2: (単位：千円)
B3: 企業名 | C3: 所在地 | D3: 事業内容 | E3: EV/EVIDA倍率
B4: ㈱アインホールディングス（9627） | C4: 北海道札幌市 | D4: 調剤薬局「アイン薬局」の運営、化粧品小売
B5: 日本調剤㈱（3341） | C5: 東京都千代田区 | D5: 調剤薬局の運営、後発医薬品の製造販売、医療従事者派遣
B6: ㈱クオールホールディングス（3034） | C6: 東京都港区 | D6: 調剤薬局「クオール薬局」の運営、医薬品製造受託
B7: ㈱メディカルシステムネットワーク（4350） | C7: 北海道札幌市 | D7: 調剤薬局の運営、医薬品ネットワーク事業
B8: ㈱ファーマライズホールディングス（2796） | C8: 東京都渋谷区 | D8: 調剤薬局の運営、ヘルスケア関連事業
B9: HYUGA PRIMARY CARE㈱（7133） | C9: 福岡県春日市 | D9: 在宅医療特化型調剤薬局「きらり薬局」の運営
B10: ㈱ミアヘルサ（7129） | C10: 東京都新宿区 | D10: 調剤薬局の運営、介護・保育事業
B11: ㈱メディカル一光グループ（3353） | C11: 三重県四日市市 | D11: 調剤薬局の運営、介護事業
B12: ㈱トーカイ（9729） | C12: 岐阜県岐阜市 | D12: 調剤薬局の運営、福祉用具レンタル、病院関連サービス
B13: ㈱スギホールディングス（7649） | C13: 愛知県大府市 | D13: 調剤併設型ドラッグストアの運営
D14: 平均値 | E14: =IFERROR(AVERAGE(E4:E13),"-")
D15: 中央値 | E15: =IFERROR(MEDIAN(E4:E13),"-")
B17: ※ 勘定科目内訳明細書（棚卸資産＝薬品等、買掛金＝医薬品卸大手、未収入金＝社会保険診療報酬支払基金・国保連）により、対象会社の事業は調剤薬局の運営と認められることから、調剤薬局を主業とする上場会社を選定した。EV/EBITDA倍率は算定日時点の株価等に基づき更新のうえ入力する。
B18: ※ 本評価では、国内中小企業M&Aの実務上のボリュームゾーンである3.0～5.0倍を採用している。なお対象会社は3店舗の小規模事業者であり、上場会社との規模格差は倍率選定上の考慮事項となる。

Sheet IM→

Sheet 会社概要
B2: 項目 | C2: 内容
B3: 会社名 | C3: 株式会社ミドリメディカル
B4: 本社所在地 | C4: 要確認（本社所在地の資料未受領）
B5: その他拠点 | C5: 調剤薬局3店舗（横浜市緑区中山町、横浜市都筑区仲町台2ヶ所）
B6: 設立/創業 | C6: 第9期（令和7年12月期）／12月決算
B7: 資本金 | C7: 9,000千円
B8: 代表者 | C8: 三河 太一
B9: 株主 | C9: 要確認
B10: 事業内容 | C10: 調剤薬局の運営
B11: 従業員数 | C11: 要確認
B12: 許認可等 | C12: 薬局開設許可・保険薬局指定（要確認）
B13: 売上高 | C13: 357,541千円（令和7年12月期）
... B15: 譲渡理由 | C15: 要確認

Sheet PLハイライト
E2: (単位：千円)
C3: 2023年12月期 | D3: 2024年12月期 | E3: 2025年12月期 | F3: ●●●●年●月期 | G3: 進行期(●月TB)
B4: 売上高 | C4: =PL!C11 -> 325866987 | D4: =PL!E11 -> 346561600 | E4: =PL!G11 -> 357540639 | F4: =PL!I11 -> 0 | G4: =PL!K11 -> 0 | I4: 関数組み込みたい
B5: 前期比 | C5: - | D5: =D4/C4 -> 1.0635063 | E5: =E4/D4 -> 1.0316799 | F5: =F4/E4 -> 0 | G5: -
B6: 売上総利益 | C6: =PL!C17 -> 166349856 | D6: =PL!E17 -> 165035715 | E6: =PL!G17 -> 160770049 | F6: =PL!I17 -> 0 | G6: =PL!K17 -> 0
B7: 利益率 | C7: =C6/C4 -> 0.51048392 | D7: =IFERROR(D6/D4,"") | E7: =IFERROR(E6/E4,"") | F7: =IFERROR(F6/F4,"") | G7: =IFERROR(G6/G4,"")
B8: 営業利益 | C8: =PL!C19 -> 20885627 | D8: =PL!E19 -> 10774443 | E8: =PL!G19 -> 12924285 | F8: =PL!I19 -> 0 | G8: =PL!K19 -> 0
B9: 利益率 | C9: =C8/C4 -> 0.064092491 | D9: =D8/D4 -> 0.031089547 | E9: =E8/E4 -> 0.036147737 | F9: =IFERROR(F8/F4,"") | G9: =IFERROR(G8/G4,"")
B10: 経常利益 | C10: =PL!C36 -> 21928969 | D10: =PL!E36 -> 10884918 | E10: =PL!G36 -> 13885521 | F10: =PL!I36 -> 0 | G10: =PL!K36 -> 0
B11: 利益率 | C11: =C10/C4 -> 0.067294233 | D11: =IFERROR(D10/D4,"") | E11: =IFERROR(E10/E4,"") | F11: =IFERROR(F10/F4,"") | G11: =IFERROR(G10/G4,"")
B12: 税引後当期純利益 | C12: =PL!C56 -> 14984010 | D12: =PL!E56 -> 8680221 | E12: =PL!G56 -> 9671212 | F12: =PL!I56 -> 0 | G12: =PL!K56 -> 0
B13: 利益率 | C13: =C12/C4 -> 0.045981982 | D13: =IFERROR(D12/D4,"") | E13: =IFERROR(E12/E4,"") | F13: =IFERROR(F12/F4,"") | G13: =IFERROR(G12/G4,"")
B15: 減価償却費 | C15: =SGA!C29 -> 5076378 | D15: =SGA!E29 -> 5742515 | E15: =SGA!G29 -> 4523044 | F15: 0 | G15: 0
B17: 調整項目 合計 | C17: =SUM(C18:C27) -> 0 | D17: =SUM(D18:D27) -> 0 | E17: =SUM(E18:E27) -> 0 | F17: =SUM(F18:F27) -> 0 | G17: =SUM(G18:G27) -> 0
B18: 役員報酬（退任予定）
B19: 役員報酬（派遣想定）
B20: 社会保険料 | C20: =(C18+C19)*0.15 -> 0 | D20: =(D18+D19)*0.15 -> 0 | E20: =(E18+E19)*0.15 -> 0 | F20: =(F18+F19)*0.15 -> 0 | G20: =(G18+G19)*0.15 -> 0
B21: 支払保険料
B22: 接待交際費
B23: 会議費
B24: 非経常的販管費
B25: 経常的営業外収益
B28: 削減可能な会議費
B29: 削減可能な雑費
B30: 買取予定不動産の賃料
B37: 調整後EBITDA | C37: =C8+C15+C17 -> 25962005 | D37: =D8+D15+D17 -> 16516958 | E37: =E8+E15+E17 -> 17447329 | F37: =F8+F15+F17 -> 0 | G37: =G8+G15+G17 -> 0

Sheet BSハイライト
F2: (単位：千円)
B3: =PLハイライト!E3 -> 2025年12月期
B4: 流動資産 | C4: =SUM(C5:C12) -> 141385419 | E4: 流動負債 | F4: =SUM(F5:F10) -> 41577715
B5: 現預金 | C5: 61842402 | E5: 買掛金 | F5: 26935462
B6: 商品 | C6: 26584168 | E6: 短期借入金 | F6: 8000000
B7: 貯蔵品 | C7: 619688 | E7: 未払金 | F7: 3541353
B8: 前払費用 | C8: 161700 | E8: 未払法人税等 | F8: 3100900
B9: 未収入金 | C9: 52401281
B10: 貸倒引当金 | C10: -524000
B11: 仮払金 | C11: 180 | E11: 固定負債 | F11: =SUM(F12:F14) -> 47200000
B12: 前払金 | C12: 300000 | E12: 長期借入金 | F12: 47200000
B14: 固定資産 | C14: =SUM(C15:C19) -> 19843083
B15: 建物附属設備 | C15: 5361688 | E15: 負債合計 | F15: =F4+F11 -> 88777715
B16: 工具器具備品 | C16: 2040707
B17: ソフトウェア | C17: 4816004 | E17: 資本金 | F17: 9000000
B18: 差入保証金 | C18: 6639280 | E18: 資本準備金 | F18: 1000000
B19: 長期前払費用 | C19: 985404 | E19: 繰越利益剰余金 | F19: 62450787
E20: 純資産合計 | F20: =SUM(F16:F19) -> 72450787
B21: 資産合計 | C21: =C4+C14 -> 161228502 | E21: 負債・純資産合計 | F21: =F15+F20 -> 161228502
F23: =F21=C21 -> TRUE

Sheet 取引先
L2: (単位：千円)
B3: № | C3: 得意先 | D3: 取引内容 | E3: 本社所在地 | F3: 業種等 | G3: ●●●●年●月期 | I3: ●●●●年●月期 | K3: ●●●●年●月期 | M3: 備考
G4: 売上高 | H4: 構成比 | I4: 売上高 | J4: 構成比 | K4: 売上高 | L4: 構成比
B5: 1 | C5: XXXXX株式会社 | E5: XX県XX市 | F5: XXXXX | H5: =IFERROR(G5/G$16,"") | J5: =IFERROR(I5/I$16,"") | L5: =IFERROR(K5/K$16,"") | M5: ああああああああああああああ
B6: 2 | H6: =IFERROR(G6/G$16,"") | J6: =IFERROR(I6/I$16,"") | L6: =IFERROR(K6/K$16,"")
B7: 3 | H7: =IFERROR(G7/G$16,"") | J7: =IFERROR(I7/I$16,"") | L7: =IFERROR(K7/K$16,"")
B8: 4 | H8: =IFERROR(G8/G$16,"") | J8: =IFERROR(I8/I$16,"") | L8: =IFERROR(K8/K$16,"")
B9: 5 | H9: =IFERROR(G9/G$16,"") | J9: =IFERROR(I9/I$16,"") | L9: =IFERROR(K9/K$16,"")
B10: 6 | H10: =IFERROR(G10/G$16,"") | J10: =IFERROR(I10/I$16,"") | L10: =IFERROR(K10/K$16,"")
B11: 7 | H11: =IFERROR(G11/G$16,"") | J11: =IFERROR(I11/I$16,"") | L11: =IFERROR(K11/K$16,"")
B12: 8 | H12: =IFERROR(G12/G$16,"") | J12: =IFERROR(I12/I$16,"") | L12: =IFERROR(K12/K$16,"")
B13: 9 | H13: =IFERROR(G13/G$16,"") | J13: =IFERROR(I13/I$16,"") | L13: =IFERROR(K13/K$16,"")
B14: 10 | H14: =IFERROR(G14/G$16,"") | J14: =IFERROR(I14/I$16,"") | L14: =IFERROR(K14/K$16,"")
C15: その他●社程度 | H15: =IFERROR(G15/G$16,"") | J15: =IFERROR(I15/I$16,"") | L15: =IFERROR(K15/K$16,"")
C16: 合計 | H16: - | J16: - | L16: -

Sheet 仕入先
K2: (単位：千円)
B3: № | C3: 仕入先 | D3: 仕入内容 | E3: 本社所在地 | F3: ●●●●年●月期 | H3: ●●●●年●月期 | J3: ●●●●年●月期 | L3: 備考
F4: 仕入高 | G4: 構成比 | H4: 仕入高 | I4: 構成比 | J4: 仕入高 | K4: 構成比
B5: 1 | C5: ㈱ﾒﾃﾞｨｾｵ | D5: 医薬品 | E5: 東京都中央区 | G5: =IFERROR(F5/F$16,"") | I5: =IFERROR(H5/H$16,"") | K5: =IFERROR(J5/J$16,"") | L5: 買掛金残高 11,139,951円（R7.12末）
B6: 2 | C6: ｱﾙﾌﾚｯｻ㈱ | D6: 医薬品 | E6: 東京都千代田区 | G6: =IFERROR(F6/F$16,"") | I6: =IFERROR(H6/H$16,"") | K6: =IFERROR(J6/J$16,"") | L6: 買掛金残高 8,606,699円（R7.12末）
B7: 3 | C7: ㈱ｽｽﾞｹﾝ | D7: 医薬品 | E7: 横浜市緑区 | G7: =IFERROR(F7/F$16,"") | I7: =IFERROR(H7/H$16,"") | K7: =IFERROR(J7/J$16,"") | L7: 買掛金残高 7,011,326円（R7.12末）
B8: 4 | C8: 神奈川東和薬品㈱ | D8: 医薬品 | E8: 神奈川県高座郡寒川町 | G8: =IFERROR(F8/F$16,"") | I8: =IFERROR(H8/H$16,"") | K8: =IFERROR(J8/J$16,"") | L8: 買掛金残高 68,904円（R7.12末）
B9: 5 | C9: 東邦薬品 | D9: 医薬品 | E9: 東京都世田谷区 | G9: =IFERROR(F9/F$16,"") | I9: =IFERROR(H9/H$16,"") | K9: =IFERROR(J9/J$16,"") | L9: 買掛金残高 59,368円（R7.12末）
B10: 6 | C10: ㈱ｼﾝﾘｮｳ | D10: 医薬品 | E10: 東京都豊島区 | G10: =IFERROR(F10/F$16,"") | I10: =IFERROR(H10/H$16,"") | K10: =IFERROR(J10/J$16,"") | L10: 買掛金残高 49,214円（R7.12末）
B11: 7 | G11: =IFERROR(F11/F$16,"") | I11: =IFERROR(H11/H$16,"") | K11: =IFERROR(J11/J$16,"")
B12: 8 | G12: =IFERROR(F12/F$16,"") | I12: =IFERROR(H12/H$16,"") | K12: =IFERROR(J12/J$16,"")
B13: 9 | G13: =IFERROR(F13/F$16,"") | I13: =IFERROR(H13/H$16,"") | K13: =IFERROR(J13/J$16,"")
B14: 10 | G14: =IFERROR(F14/F$16,"") | I14: =IFERROR(H14/H$16,"") | K14: =IFERROR(J14/J$16,"")
G15: =IFERROR(F15/F$16,"") | I15: =IFERROR(H15/H$16,"") | K15: =IFERROR(J15/J$16,"")
C16: 合計 | G16: - | I16: - | K16: -
C18: ※ 仕入先別の仕入高の内訳は未受領。上記は令和7年12月期の買掛金の内訳書に基づく期末残高であり、仕入高そのものではない。医薬品卸大手3社（㈱ﾒﾃﾞｨｾｵ・ｱﾙﾌﾚｯｻ㈱・㈱ｽｽﾞｹﾝ）で買掛金残高の99.3%を占める。

Sheet 外注先
L2: (単位：千円)
B3: № | C3: 外注先 | D3: 外注内容 | E3: 本社所在地 | F3: 業種等 | G3: ●●●●年●月期 | I3: ●●●●年●月期 | K3: ●●●●年●月期 | M3: 備考
G4: 外注費 | H4: 構成比 | I4: 外注費 | J4: 構成比 | K4: 外注費 | L4: 構成比
B5: 1 | C5: XXXXX株式会社 | E5: XX県XX市 | F5: XXXXX | H5: =IFERROR(G5/G$16,"") | J5: =IFERROR(I5/I$16,"") | L5: =IFERROR(K5/K$16,"") | M5: ああああああああああああああ
B6: 2 | H6: =IFERROR(G6/G$16,"") | J6: =IFERROR(I6/I$16,"") | L6: =IFERROR(K6/K$16,"")
B7: 3 | H7: =IFERROR(G7/G$16,"") | J7: =IFERROR(I7/I$16,"") | L7: =IFERROR(K7/K$16,"")
B8: 4 | H8: =IFERROR(G8/G$16,"") | J8: =IFERROR(I8/I$16,"") | L8: =IFERROR(K8/K$16,"")
B9: 5 | H9: =IFERROR(G9/G$16,"") | J9: =IFERROR(I9/I$16,"") | L9: =IFERROR(K9/K$16,"")
B10: 6 | H10: =IFERROR(G10/G$16,"") | J10: =IFERROR(I10/I$16,"") | L10: =IFERROR(K10/K$16,"")
B11: 7 | H11: =IFERROR(G11/G$16,"") | J11: =IFERROR(I11/I$16,"") | L11: =IFERROR(K11/K$16,"")
B12: 8 | H12: =IFERROR(G12/G$16,"") | J12: =IFERROR(I12/I$16,"") | L12: =IFERROR(K12/K$16,"")
B13: 9 | H13: =IFERROR(G13/G$16,"") | J13: =IFERROR(I13/I$16,"") | L13: =IFERROR(K13/K$16,"")
B14: 10 | H14: =IFERROR(G14/G$16,"") | J14: =IFERROR(I14/I$16,"") | L14: =IFERROR(K14/K$16,"")
C15: その他●社程度 | H15: =IFERROR(G15/G$16,"") | J15: =IFERROR(I15/I$16,"") | L15: =IFERROR(K15/K$16,"")
C16: 合計 | H16: - | J16: - | L16: -

Sheet 株主
E2: (単位：千円)
B3: № | C3: 氏名 | D3: 役職 | E3: 役員報酬 （●年●月期） | F3: 保有株式数 | G3: 保有割合 | H3: 備考
B5: 1 | C5: 要確認 | G5: =IFERROR(F5/$F$15,"") | H5: 株主構成は未受領。短期借入金の相手先が「親会社 一般社団法人スタジオ技術研究会」と記載されており、資本関係の有無を含め要確認。
B6: 2 | G6: =IFERROR(F6/$F$15,"")
B7: 3 | G7: =IFERROR(F7/$F$15,"")
B8: 4 | G8: =IFERROR(F8/$F$15,"")
B9: 5 | G9: =IFERROR(F9/$F$15,"")
B10: 6 | G10: =IFERROR(F10/$F$15,"")
B11: 7 | G11: =IFERROR(F11/$F$15,"")
B12: 8 | G12: =IFERROR(F12/$F$15,"")
B13: 9 | G13: =IFERROR(F13/$F$15,"")
B14: 10 | G14: =IFERROR(F14/$F$15,"")
C15: 合計 | E15: =SUM(E5:E14) -> 22000000 | F15: =SUM(F5:F14) -> 1000 | G15: =IFERROR(F15/$F$15,"")

Sheet 取締役
F2: (単位：千円)
B3: № | C3: 氏名 | D3: 役職 | E3: 代表者との関係 | F3: 役員報酬 （●年●月期） | G3: 業務範囲 | H3: 備考
B5: 1 | C5: 三河 太一 | D5: 代表取締役 | E5: 本人 | F5: 11870000 | G5: 常勤（役員給与等の内訳書による） | H5: M&A後の処遇は要確認
B6: 2
B7: 3
B8: 4
B9: 5
B10: 6
B11: 7
B12: 8
B13: 9
B14: 10
C15: 合計 | F15: =SUM(F5:F14) -> 27000000
C16: ※ 令和7年12月期の役員給与等の内訳書による。上記以外に役員の計上はない。人件費の内訳上、従業員給与手当67,951千円のうち代表者及びその家族分が4,140千円ある（要確認）。

Sheet 従業員
F2: 基準日→適宜変更 | G2: 46053
G3: YYYY/MM/DD | I3: YYYY/MM/DD
B4: № | C4: 氏名 | D4: イニシャル | E4: 雇用形態 | F4: 性別 | G4: 生年月日 | H4: 年齢 （歳） | I4: 入社年月日 | J4: 勤続年数 （年） | K4: 部署 | L4: 役職 | M4: ●年●月分総支給 | N4: ●年夏季賞与 | O4: ●年冬季賞与 | P4: ●年総支給額 | Q4: 備考
B5: 1 | D5: O.S | E5: 正社員 | F5: 男 | G5: 31968 | H5: =ROUNDDOWN(($G$2-G5)/365,0) -> 38 | I5: 45261 | J5: =ROUNDDOWN(($G$2-I5)/365,0) -> 2 | K5: 企業情報部 | L5: 上席課長 | Q5: 中小企業診断士、AFP、日商簿記2級、MOSエキスパート
B6: 2 | H6: =ROUNDDOWN(($G$2-G6)/365,0) -> 126 | J6: =ROUNDDOWN(($G$2-I6)/365,0) -> 126
B7: 3 | H7: =ROUNDDOWN(($G$2-G7)/365,0) -> 126 | J7: =ROUNDDOWN(($G$2-I7)/365,0) -> 126
B8: 4 | H8: =ROUNDDOWN(($G$2-G8)/365,0) -> 126 | J8: =ROUNDDOWN(($G$2-I8)/365,0) -> 126
B9: 5 | H9: =ROUNDDOWN(($G$2-G9)/365,0) -> 126 | J9: =ROUNDDOWN(($G$2-I9)/365,0) -> 126
B10: 6 | H10: =ROUNDDOWN(($G$2-G10)/365,0) -> 126 | J10: =ROUNDDOWN(($G$2-I10)/365,0) -> 126
B11: 7 | H11: =ROUNDDOWN(($G$2-G11)/365,0) -> 126 | J11: =ROUNDDOWN(($G$2-I11)/365,0) -> 126
B12: 8 | H12: =ROUNDDOWN(($G$2-G12)/365,0) -> 126 | J12: =ROUNDDOWN(($G$2-I12)/365,0) -> 126
B13: 9 | H13: =ROUNDDOWN(($G$2-G13)/365,0) -> 126 | J13: =ROUNDDOWN(($G$2-I13)/365,0) -> 126
B14: 10 | H14: =ROUNDDOWN(($G$2-G14)/365,0) -> 126 | J14: =ROUNDDOWN(($G$2-I14)/365,0) -> 126
B15: 11 | H15: =ROUNDDOWN(($G$2-G15)/365,0) -> 126 | J15: =ROUNDDOWN(($G$2-I15)/365,0) -> 126
B16: 12 | H16: =ROUNDDOWN(($G$2-G16)/365,0) -> 126 | J16: =ROUNDDOWN(($G$2-I16)/365,0) -> 126
B17: 13 | H17: =ROUNDDOWN(($G$2-G17)/365,0) -> 126 | J17: =ROUNDDOWN(($G$2-I17)/365,0) -> 126
... B34: 30 | H34: =ROUNDDOWN(($G$2-G34)/365,0) -> 126 | J34: =ROUNDDOWN(($G$2-I34)/365,0) -> 126

Sheet 拠点(本社等)
B2: 所在地 | C2: 契約形態 | D2: 延床面積 (㎡) | E2: 月間賃料 (千円) | F2: 敷金 (千円) | G2: アクセス
B3: 要確認（本社所在地の資料未受領）

Sheet 不動産(所有)
I1: 土地は0.7割戻し
B3: 事業所名 | C3: 内容 | D3: 所在地 地番・家屋番号 | E3: 面積 (㎡) | F3: 区分 ・構造 | G3: 所有（建築） 年月・事由 | H3: 前期末簿価 (千円) | I3: 時価 | J3: 固定資産税 評価額 | K3: 備考
B4: 本店 | C4: 土地）店舗底地 | D4: 西宮市越水町97番1 | E4: 1086.16 | F4: 宅地 | G4: 2000年1月1日相続 | H4: 10000000 | I4: =J4/0.7 -> 17142857 | J4: 12000000 | K4: 固定資産評価額を0.7で割戻し、時価を算出
C5: 土地）駐車場 | D5: 西宮市越水町98番2 | E5: 500.12 | F5: 宅地 | G5: 2000年1月1日相続 | H5: 5000000 | I5: =J5/0.7 -> 10000000 | J5: 7000000 | K5: 固定資産評価額を0.7で割戻し、時価を算出
C6: 建物）店舗 | D6: 97番地1 | E6: 2階：50.12 1階：50.12 合計：100.24 | F6: 店舗 鉄骨造り | G6: 2010年1月1日新築 | H6: 20000000 | I6: 20000000 | J6: - | K6: 減価償却過不足なし、簿価=時価として評価
B7: 工場 | C7: 土地）店舗底地 | D7: 西宮市越水町97番1 | E7: 1086.16 | F7: 宅地 | G7: 2000年1月1日相続 | H7: 10000000 | I7: =J7/0.7 -> 17142857 | J7: 12000000 | K7: 固定資産評価額を0.7で割戻し、時価を算出
C8: 建物）工場 | D8: 97番地1 | E8: 2階：50.12 1階：50.12 合計：100.24 | F8: 工場 鉄骨造り | G8: 2010年1月1日新築 | H8: 20000000 | I8: 20000000 | J8: - | K8: 減価償却過不足なし、簿価=時価として評価
B14: 【●●工場】 | C14: 【●●工場】
B15: 事業所名 | C15: 内容 | D15: 所在地 地番・家屋番号 | E15: 面積 (㎡) | F15: 区分 ・構造 | G15: 所有（建築） 年月・事由 | H15: 前期末簿価 (千円) | I15: 時価 | J15: 固定資産税 評価額 | K15: 備考
B16: 土地）店舗底地 | C16: 土地）店舗底地 | D16: 西宮市越水町97番1 | E16: 1086.16 | F16: 宅地 | G16: 2000年1月1日相続 | H16: 10000000 | I16: =J16/0.7 -> 17142857 | J16: 12000000 | K16: 固定資産評価額を0.7で割戻し、時価を算出
C17: 土地）駐車場 | D17: 西宮市越水町98番2 | E17: 500.12 | F17: 宅地 | G17: 2000年1月1日相続 | H17: 5000000 | I17: =J17/0.7 -> 10000000 | J17: 7000000 | K17: 固定資産評価額を0.7で割戻し、時価を算出
C18: 建物）工場 | D18: 97番地1 | E18: 2階：50.12 1階：50.12 合計：100.24 | F18: 工場 鉄骨造り | G18: 2010年1月1日新築 | H18: 20000000 | I18: 20000000 | J18: - | K18: 減価償却過不足なし、簿価=時価として評価

Sheet 不動産(賃借) 
B3: 内容 | C3: 内容 | D3: 所在地 地番・家屋番号 | E3: 面積 (㎡) | F3: 契約内容 | G3: 貸主 | H3: 月間賃料 (千円) | I3: 敷金 (千円) | J3: 備考
B4: ①店舗 | C4: 建物）店舗 | D4: 横浜市緑区中山町305-20 | F4: 要確認 | G4: ㈱ｲｴﾛｰｽﾀｼﾞｵ | H4: 337500 | I4: 1000000 | J4: 年額 4,050,000円（R7.2〜R8.1）
B5: ②店舗 | C5: 建物）店舗 | D5: 横浜市都筑区仲町台1-33-16 | F5: 要確認 | G5: 片桐 昇 | H5: 296947 | I5: 2000000 | J5: 年額 3,563,364円（R7.2〜R8.1）
B6: ③店舗 | C6: 建物）店舗 | D6: 横浜市都筑区仲町台1-2-28 | F6: 要確認 | G6: ㈱ﾚｰﾍﾞﾝﾄﾗｽﾄ | H6: 718025 | I6: 3480000 | J6: 年額 8,616,300円（R7.2〜R8.1）
B7: 駐車場 | C7: 土地）駐車場 | D7: 横浜市都筑区仲町台2-11-1 | F7: 要確認 | G7: 西川 香代子 | H7: 17600 | I7: 17280 | J7: 年額 211,200円（R7.2〜R8.1）
B8: 駐車場 | C8: 土地）駐車場 | D8: 横浜市都筑区仲町台5-6 | F8: 要確認 | G8: ㈱ﾘﾌﾞｸﾗｯｼｲ | H8: 17600 | I8: 16000 | J8: 年額 211,200円（R7.2〜R8.1）
B9: 駐車場 | C9: 土地）駐車場 | D9: 横浜市都筑区仲町台1-14 | F9: 要確認 | G9: ㈱ﾘﾌﾞｸﾗｯｼｲ | H9: 18700 | J9: 年額 224,400円（R7.2〜R8.1）
B10: 駐車場 | C10: 土地）駐車場 | D10: 横浜市都筑区仲町台 | F10: 要確認 | G10: 神奈川中央住宅㈱ | H10: 19067 | J10: 年額 228,800円（R7.2〜R8.1）
B12: ※ 令和7年12月期の地代家賃等の内訳書及び差入保証金の内訳による。差入保証金にはほかにﾄｰｾｲ･ｺﾐｭﾆﾃｨ㈱126,000円があるが、地代家賃の内訳に対応する記載がなく内容は要確認。賃貸借契約書は未受領のため契約期間・更新条件・原状回復義務は要確認。

Sheet 設備
B2: № | C2: 科目 | D2: 資産名 | E2: 償却方法 | F2: 取得年 | G2: 取得月 | H2: 耐用年数 | I2: 取得原価 | J2: 期末帳簿価額 | K2: 文字
B3: 1 | C3: あああああ | D3: あああああ | E3: あああああ | F3: XXXXX | G3: XXXXX | H3: XXXXX | I3: XXXXX | J3: XXXXX | K3: ああああああああああああああああああああああああああああああああ
B4: 2 | C4: あああああ | D4: あああああ | E4: あああああ | F4: XXXXX | G4: XXXXX | H4: XXXXX | I4: XXXXX | J4: XXXXX | K4: ああああああああああああああああああああああああああああああああ
B5: 3 | C5: あああああ | D5: あああああ | E5: あああああ | F5: XXXXX | G5: XXXXX | H5: XXXXX | I5: XXXXX | J5: XXXXX | K5: ああああああああああああああああああああああああああああああああ
B6: 4 | C6: あああああ | D6: あああああ | E6: あああああ | F6: XXXXX | G6: XXXXX | H6: XXXXX | I6: XXXXX | J6: XXXXX | K6: ああああああああああああああああああああああああああああああああ
B7: 5 | C7: あああああ | D7: あああああ | E7: あああああ | F7: XXXXX | G7: XXXXX | H7: XXXXX | I7: XXXXX | J7: XXXXX | K7: ああああああああああああああああああああああああああああああああ
B8: 6 | C8: あああああ | D8: あああああ | E8: あああああ | F8: XXXXX | G8: XXXXX | H8: XXXXX | I8: XXXXX | J8: XXXXX | K8: ああああああああああああああああああああああああああああああああ
B9: 7 | C9: あああああ | D9: あああああ | E9: あああああ | F9: XXXXX | G9: XXXXX | H9: XXXXX | I9: XXXXX | J9: XXXXX | K9: ああああああああああああああああああああああああああああああああ
B10: 8 | C10: あああああ | D10: あああああ | E10: あああああ | F10: XXXXX | G10: XXXXX | H10: XXXXX | I10: XXXXX | J10: XXXXX | K10: ああああああああああああああああああああああああああああああああ
B11: 9 | C11: あああああ | D11: あああああ | E11: あああああ | F11: XXXXX | G11: XXXXX | H11: XXXXX | I11: XXXXX | J11: XXXXX | K11: ああああああああああああああああああああああああああああああああ
B12: 10 | C12: あああああ | D12: あああああ | E12: あああああ | F12: XXXXX | G12: XXXXX | H12: XXXXX | I12: XXXXX | J12: XXXXX | K12: ああああああああああああああああああああああああああああああああ
C13: 建物合計 | I13: =SUM(I3:I12) -> 0 | J13: =SUM(J3:J12) -> 0
B14: 11 | C14: あああああ | D14: あああああ | E14: あああああ | F14: XXXXX | G14: XXXXX | H14: XXXXX | I14: XXXXX | J14: XXXXX | K14: ああああああああああああああああああああああああああああああああ
B15: 12 | C15: あああああ | D15: あああああ | E15: あああああ | F15: XXXXX | G15: XXXXX | H15: XXXXX | I15: XXXXX | J15: XXXXX | K15: ああああああああああああああああああああああああああああああああ
B16: 13 | C16: あああああ | D16: あああああ | E16: あああああ | F16: XXXXX | G16: XXXXX | H16: XXXXX | I16: XXXXX | J16: XXXXX | K16: ああああああああああああああああああああああああああああああああ
B17: 14 | C17: あああああ | D17: あああああ | E17: あああああ | F17: XXXXX | G17: XXXXX | H17: XXXXX | I17: XXXXX | J17: XXXXX | K17: ああああああああああああああああああああああああああああああああ
B18: 15 | C18: あああああ | D18: あああああ | E18: あああああ | F18: XXXXX | G18: XXXXX | H18: XXXXX | I18: XXXXX | J18: XXXXX | K18: ああああああああああああああああああああああああああああああああ
B19: 16 | C19: あああああ | D19: あああああ | E19: あああああ | F19: XXXXX | G19: XXXXX | H19: XXXXX | I19: XXXXX | J19: XXXXX | K19: ああああああああああああああああああああああああああああああああ
B20: 17 | C20: あああああ | D20: あああああ | E20: あああああ | F20: XXXXX | G20: XXXXX | H20: XXXXX | I20: XXXXX | J20: XXXXX | K20: ああああああああああああああああああああああああああああああああ
B21: 18 | C21: あああああ | D21: あああああ | E21: あああああ | F21: XXXXX | G21: XXXXX | H21: XXXXX | I21: XXXXX | J21: XXXXX | K21: ああああああああああああああああああああああああああああああああ
C22: 車両及び運搬具合計 | I22: =SUM(I14:I21) -> 0 | J22: =SUM(J14:J21) -> 0

Sheet 財務
B2: IMの財務詳細ページのデータは財務入力のシートから流用してください

Sheet その他

Sheet スケジュール(横)
B3: TODO | D3: 2月 | U3: 3月 | AZ3: 4月 | CE3: 5月
D4: 12 | E4: 13 | F4: 14 | G4: 15 | H4: 16 | I4: 17 | J4: 18 | K4: 19 | L4: 20 | M4: 21 | N4: 22 | O4: 23 | P4: 24 | Q4: 25 | R4: 26 | S4: 27 | T4: 28 | U4: 1 | V4: 2 | W4: 3 | X4: 4 | Y4: 5 | Z4: 6 | AA4: 7 | AB4: 8 | AC4: 9 | AD4: 10 | AE4: 11 | AF4: 12 | AG4: 13 | AH4: 14 | AI4: 15 | AJ4: 16 | AK4: 17 | AL4: 18 | AM4: 19 | AN4: 20 | AO4: 21 | AP4: 22 | AQ4: 23 | AR4: 24 | AS4: 25 | AT4: 26 | AU4: 27 | AV4: 28 | AW4: 29 | AX4: 30 | AY4: 31 | AZ4: 1 | BA4: 2 | BB4: 3 | BC4: 4 | BD4: 5 | BE4: 6 | BF4: 7 | BG4: 8 | BH4: 9 | BI4: 10 | BJ4: 11 | BK4: 12 | BL4: 13 | BM4: 14 | BN4: 15 | BO4: 16 | BP4: 17 | BQ4: 18 | BR4: 19 | BS4: 20 | BT4: 21 | BU4: 22 | BV4: 23 | BW4: 24 | BX4: 25 | BY4: 26 | BZ4: 27 | CA4: 28 | CB4: 29 | CC4: 30 | CD4: 31 | CE4: 1 | CF4: 2 | CG4: 3 | CH4: 4 | CI4: 5 | CJ4: 6 | CK4: 7 | CL4: 8 | CM4: 9 | CN4: 10 | CO4: 11 | CP4: 12 | CQ4: 13 | CR4: 14 | CS4: 15 | CT4: 16 | CU4: 17 | CV4: 18 | CW4: 19 | CX4: 20 | CY4: 21 | CZ4: 22 | DA4: 23 | DB4: 24 | DC4: 25 | DD4: 26 | DE4: 27 | DF4: 28 | DG4: 29 | DH4: 30 | DI4: 31
B5: 交渉 | C5: TOP面談
C6: LOIドラフト作成
C7: LOI提出
C8: LOI受領(独占交渉権)
B9: DD | C9: DDスコープ・依頼先選定
C10: IRL提出
C11: QAラリー
C12: マネジメントインタビュー | L12: B | AA12: F | AB12: L
C13: DD結果報告 | AX13: F | AY13: L
B14: 契約 | C14: SPA内容調整
C15: SPA締結
C16: CoC対応等
C17: クロージング
C18: 役員変更登記申請
B19: PMI | C19: 従業員・取引先開示
C20: 連帯保証解除等
C21: PMI・グループ連携 | DK21: ● | DL21: 報酬発生

Sheet スケジュール(縦)
B2: スケジュール表
B3: 日付 | C3: 曜日 | D3: 【売主】 ●●●様 | E3: 【買主】 ●●●様 | F3: M&A承継機構
A4: 2025年 | B4: 45931 | C4: =TEXT(B4,"aaa") -> 水 | D4: 本日 お打ち合わせ
B5: =B4+1 -> 45932 | C5: =TEXT(B5,"aaa") -> 木 | E5: TOP面談準備
B6: =B5+1 -> 45933 | C6: =TEXT(B6,"aaa") -> 金 | E6: LOI内容検討 | F6: LOIドラフト提示
B7: =B6+1 -> 45934 | C7: =TEXT(B7,"aaa") -> 土
B8: =B7+1 -> 45935 | C8: =TEXT(B8,"aaa") -> 日
B9: =B8+1 -> 45936 | C9: =TEXT(B9,"aaa") -> 月
B10: =B9+1 -> 45937 | C10: =TEXT(B10,"aaa") -> 火
B11: =B10+1 -> 45938 | C11: =TEXT(B11,"aaa") -> 水 | D11: TOP面談
B12: =B11+1 -> 45939 | C12: =TEXT(B12,"aaa") -> 木
B13: =B12+1 -> 45940 | C13: =TEXT(B13,"aaa") -> 金
B14: =B13+1 -> 45941 | C14: =TEXT(B14,"aaa") -> 土
B15: =B14+1 -> 45942 | C15: =TEXT(B15,"aaa") -> 日
B16: =B15+1 -> 45943 | C16: =TEXT(B16,"aaa") -> 月
B17: =B16+1 -> 45944 | C17: =TEXT(B17,"aaa") -> 火 | E17: LOI提出
B18: =B17+1 -> 45945 | C18: =TEXT(B18,"aaa") -> 水 | E18: DDスコープ・依頼先検討
B19: =B18+1 -> 45946 | C19: =TEXT(B19,"aaa") -> 木
B20: =B19+1 -> 45947 | C20: =TEXT(B20,"aaa") -> 金 | D20: LOI回答(独占交渉権付与) | E20: ※独占交渉権獲得 | F20: LOI内容説明
B21: =B20+1 -> 45948 | C21: =TEXT(B21,"aaa") -> 土
B22: =B21+1 -> 45949 | C22: =TEXT(B22,"aaa") -> 日
B23: =B22+1 -> 45950 | C23: =TEXT(B23,"aaa") -> 月
B24: =B23+1 -> 45951 | C24: =TEXT(B24,"aaa") -> 火
B25: =B24+1 -> 45952 | C25: =TEXT(B25,"aaa") -> 水 | E25: DDスコープ・依頼先確定
B26: =B25+1 -> 45953 | C26: =TEXT(B26,"aaa") -> 木
B27: =B26+1 -> 45954 | C27: =TEXT(B27,"aaa") -> 金
B28: =B27+1 -> 45955 | C28: =TEXT(B28,"aaa") -> 土
B29: =B28+1 -> 45956 | C29: =TEXT(B29,"aaa") -> 日
B30: =B29+1 -> 45957 | C30: =TEXT(B30,"aaa") -> 月 | E30: DDキックオフミーティング
B31: =B30+1 -> 45958 | C31: =TEXT(B31,"aaa") -> 火 | D31: DD資料提出・QA対応 | E31: IRL提出※DD依頼先 | F31: DD資料提出・QA対応
B32: =B31+1 -> 45959 | C32: =TEXT(B32,"aaa") -> 水 | E32: DDQA対応※DD依頼先
B33: =B32+1 -> 45960 | C33: =TEXT(B33,"aaa") -> 木
B34: =B33+1 -> 45961 | C34: =TEXT(B34,"aaa") -> 金
B35: =B34+1 -> 45962 | C35: =TEXT(B35,"aaa") -> 土
B36: =B35+1 -> 45963 | C36: =TEXT(B36,"aaa") -> 日
B37: =B36+1 -> 45964 | C37: =TEXT(B37,"aaa") -> 月
B38: =B37+1 -> 45965 | C38: =TEXT(B38,"aaa") -> 火 | D38: DD資料提出・QA対応 | E38: DDQA対応※DD依頼先 | F38: DD資料提出・QA対応
B39: =B38+1 -> 45966 | C39: =TEXT(B39,"aaa") -> 水
B40: =B39+1 -> 45967 | C40: =TEXT(B40,"aaa") -> 木
B41: =B40+1 -> 45968 | C41: =TEXT(B41,"aaa") -> 金
B42: =B41+1 -> 45969 | C42: =TEXT(B42,"aaa") -> 土
B43: =B42+1 -> 45970 | C43: =TEXT(B43,"aaa") -> 日
B44: =B43+1 -> 45971 | C44: =TEXT(B44,"aaa") -> 月 | D44: DD資料提出・QA対応 | E44: DDQA対応※DD依頼先 | F44: DD資料提出・QA対応
B45: =B44+1 -> 45972 | C45: =TEXT(B45,"aaa") -> 火
B46: =B45+1 -> 45973 | C46: =TEXT(B46,"aaa") -> 水 | D46: DDマネジメントインタビュー
B47: =B46+1 -> 45974 | C47: =TEXT(B47,"aaa") -> 木
B48: =B47+1 -> 45975 | C48: =TEXT(B48,"aaa") -> 金
B49: =B48+1 -> 45976 | C49: =TEXT(B49,"aaa") -> 土
B50: =B49+1 -> 45977 | C50: =TEXT(B50,"aaa") -> 日
B51: =B50+1 -> 45978 | C51: =TEXT(B51,"aaa") -> 月 | E51: SPA内容検討 | F51: SPAドラフト提出
B52: =B51+1 -> 45979 | C52: =TEXT(B52,"aaa") -> 火
B53: =B52+1 -> 45980 | C53: =TEXT(B53,"aaa") -> 水
B54: =B53+1 -> 45981 | C54: =TEXT(B54,"aaa") -> 木
B55: =B54+1 -> 45982 | C55: =TEXT(B55,"aaa") -> 金 | E55: DD結果確認(DD報告会)
B56: =B55+1 -> 45983 | C56: =TEXT(B56,"aaa") -> 土
B57: =B56+1 -> 45984 | C57: =TEXT(B57,"aaa") -> 日
B58: =B57+1 -> 45985 | C58: =TEXT(B58,"aaa") -> 月
B59: =B58+1 -> 45986 | C59: =TEXT(B59,"aaa") -> 火 | E59: SPA案ご提出
B60: =B59+1 -> 45987 | C60: =TEXT(B60,"aaa") -> 水 | D60: SPA調整
B61: =B60+1 -> 45988 | C61: =TEXT(B61,"aaa") -> 木
B62: =B61+1 -> 45989 | C62: =TEXT(B62,"aaa") -> 金
B63: =B62+1 -> 45990 | C63: =TEXT(B63,"aaa") -> 土
B64: =B63+1 -> 45991 | C64: =TEXT(B64,"aaa") -> 日
B65: =B64+1 -> 45992 | C65: =TEXT(B65,"aaa") -> 月 | D65: SPA調整
B66: =B65+1 -> 45993 | C66: =TEXT(B66,"aaa") -> 火
B67: =B66+1 -> 45994 | C67: =TEXT(B67,"aaa") -> 水
B68: =B67+1 -> 45995 | C68: =TEXT(B68,"aaa") -> 木
B69: =B68+1 -> 45996 | C69: =TEXT(B69,"aaa") -> 金
B70: =B69+1 -> 45997 | C70: =TEXT(B70,"aaa") -> 土
B71: =B70+1 -> 45998 | C71: =TEXT(B71,"aaa") -> 日
B72: =B71+1 -> 45999 | C72: =TEXT(B72,"aaa") -> 月 | D72: SPA調整
B73: =B72+1 -> 46000 | C73: =TEXT(B73,"aaa") -> 火
B74: =B73+1 -> 46001 | C74: =TEXT(B74,"aaa") -> 水
B75: =B74+1 -> 46002 | C75: =TEXT(B75,"aaa") -> 木
B76: =B75+1 -> 46003 | C76: =TEXT(B76,"aaa") -> 金 | D76: 株式譲渡契約書締結
B77: =B76+1 -> 46004 | C77: =TEXT(B77,"aaa") -> 土
B78: =B77+1 -> 46005 | C78: =TEXT(B78,"aaa") -> 日
B79: =B78+1 -> 46006 | C79: =TEXT(B79,"aaa") -> 月 | D79: COC対応等 | F79: COC対応等
B80: =B79+1 -> 46007 | C80: =TEXT(B80,"aaa") -> 火
B81: =B80+1 -> 46008 | C81: =TEXT(B81,"aaa") -> 水
B82: =B81+1 -> 46009 | C82: =TEXT(B82,"aaa") -> 木
B83: =B82+1 -> 46010 | C83: =TEXT(B83,"aaa") -> 金 | D83: クロージング（資金決済、株主名簿書換、役員変更登記申請)
B84: =B83+1 -> 46011 | C84: =TEXT(B84,"aaa") -> 土
B85: =B84+1 -> 46012 | C85: =TEXT(B85,"aaa") -> 日
B86: =B85+1 -> 46013 | C86: =TEXT(B86,"aaa") -> 月 | D86: 従業員・取引先への開示、PMI
B87: =B86+1 -> 46014 | C87: =TEXT(B87,"aaa") -> 火
B88: =B87+1 -> 46015 | C88: =TEXT(B88,"aaa") -> 水
B89: =B88+1 -> 46016 | C89: =TEXT(B89,"aaa") -> 木
B90: =B89+1 -> 46017 | C90: =TEXT(B90,"aaa") -> 金
B91: =B90+1 -> 46018 | C91: =TEXT(B91,"aaa") -> 土
B92: =B91+1 -> 46019 | C92: =TEXT(B92,"aaa") -> 日
B93: =B92+1 -> 46020 | C93: =TEXT(B93,"aaa") -> 月
B94: =B93+1 -> 46021 | C94: =TEXT(B94,"aaa") -> 火
B95: =B94+1 -> 46022 | C95: =TEXT(B95,"aaa") -> 水
A96: 2026年 | B96: =B95+1 -> 46023 | C96: =TEXT(B96,"aaa") -> 木
B97: =B96+1 -> 46024 | C97: =TEXT(B97,"aaa") -> 金
B98: =B97+1 -> 46025 | C98: =TEXT(B98,"aaa") -> 土
B99: =B98+1 -> 46026 | C99: =TEXT(B99,"aaa") -> 日
B100: =B99+1 -> 46027 | C100: =TEXT(B100,"aaa") -> 月
B101: =B100+1 -> 46028 | C101: =TEXT(B101,"aaa") -> 火
...

Sheet グラフ
C2: A | D2: B | E2: C | T2: A
B3: 第1四半期 | C3: 50 | D3: 10 | E3: 20 | S3: 第1四半期 | T3: 50
B4: 第2四半期 | C4: 55 | D4: 25 | E4: 22 | S4: 第2四半期 | T4: 55
B5: 第3四半期 | C5: 52 | D5: 45 | E5: 25 | S5: 第3四半期 | T5: 52
B6: 第4四半期 | C6: 50 | D6: 70 | E6: 25 | S6: 第4四半期 | T6: 80
AF16: ｂ
C18: A | D18: B | E18: C
B19: 1ヶ月目 | C19: 100 | D19: 100 | E19: 100 | T19: A
B20: 2ヶ月目 | C20: 105 | D20: 90 | E20: 110 | S20: 第1四半期 | T20: 50
B21: 3か月目 | C21: 110 | D21: 75 | E21: 90 | S21: 第2四半期 | T21: 55
B22: 4か月目 | C22: 115 | D22: 60 | E22: 80 | S22: 第3四半期 | T22: 52
B23: 5か月目 | C23: 120 | D23: 55 | E23: 45 | S23: 第4四半期 | T23: 80
C33: グラフタイトル
B34: A | C34: 60
B35: B | C35: 20
B36: C | C36: 15
B37: D | C37: 5
C51: X | D51: Y | E51: Z
B52: D | C52: 4.3 | D52: 2.4 | E52: 2
B53: C | C53: 2.5 | D53: 4.4 | E53: 2
B54: B | C54: 3.5 | D54: 1.8 | E54: 3
B55: A | C55: 4.5 | D55: 2.8 | E55: 5

Sheet 表
B2: あああ | C2: あああ | D2: あああ | E2: あああ | F2: あああ
B3: あああああ | C3: XXXXX | D3: XXXXX | E3: XXXXX | F3: ああああああああああああああああああああああああああああああああ
B4: あああああ | C4: XXXXX | D4: XXXXX | E4: XXXXX | F4: ああああああああああああああああああああああああああああああああ
B5: あああああ | C5: XXXXX | D5: XXXXX | E5: XXXXX | F5: ああああああああああああああああああああああああああああああああ
B6: あああああ | C6: XXXXX | D6: XXXXX | E6: XXXXX | F6: ああああああああああああああああああああああああああああああああ
B7: あああああ | C7: XXXXX | D7: XXXXX | E7: XXXXX | F7: ああああああああああああああああああああああああああああああああ
B8: あああああ | C8: XXXXX | D8: XXXXX | E8: XXXXX | F8: ああああああああああああああああああああああああああああああああ
B11: あああ | C11: あああ | D11: あああ | E11: あああ | F11: あああ
B12: あああああ | C12: XXXXX | D12: XXXXX | E12: XXXXX | F12: ああああああああああああああああああああああああああああああああ
C13: XXXXX | D13: XXXXX | E13: XXXXX | F13: ああああああああああああああああああああああああああああああああ
B14: あああああ | C14: XXXXX | D14: XXXXX | E14: XXXXX | F14: ああああああああああああああああああああああああああああああああ
C15: XXXXX | D15: XXXXX | E15: XXXXX | F15: ああああああああああああああああああああああああああああああああ
B16: あああああ | C16: XXXXX | D16: XXXXX | E16: XXXXX | F16: ああああああああああああああああああああああああああああああああ
C17: XXXXX | D17: XXXXX | E17: XXXXX | F17: ああああああああああああああああああああああああああああああああ
B20: あああ | C20: あああ | D20: あああ | E20: あああ
B21: あああああ | C21: XXXXX | D21: XXXXX | E21: XXXXX
C22: XXXXX | D22: XXXXX | E22: XXXXX
B23: あああああ | C23: XXXXX | D23: XXXXX | E23: XXXXX
C24: XXXXX | D24: XXXXX | E24: XXXXX
B25: あああああ | C25: XXXXX | D25: XXXXX | E25: XXXXX
C26: XXXXX | D26: XXXXX | E26: XXXXX
B29: あああ | C29: あああ | D29: あああ | E29: あああ
B30: あああああ | C30: XXXXX | D30: XXXXX | E30: XXXXX
C31: XXXXX | D31: XXXXX | E31: XXXXX
B32: あああああ | C32: XXXXX | D32: XXXXX | E32: XXXXX
C33: XXXXX | D33: XXXXX | E33: XXXXX
B34: あああああ | C34: XXXXX | D34: XXXXX | E34: XXXXX
C35: XXXXX | D35: XXXXX | E35: XXXXX
