Workbook

Sheet 使い方
A1: 店舗データベース 使い方
A4: ■ このファイルが、本事業における唯一の代替不可能な資産です。
A5: 訪問した店の一次情報（予約手段・支払い・注意点）を蓄積します。
A6: 競合が資本で追い抜けないのは、この蓄積だけです。
A8: 【入力タイミング】
A9: 取材当日の夜。AIプロンプト P-02 で音声メモを構造化し、事実確認して転記する。
A10: 後日にすると必ず忘れます。その日のうちに埋めてください。
A12: 【掲載可否のルール】
A13: 「掲載可否」列が『可』になるのは、必須項目（基本情報＋①〜⑨）がすべて埋まっている場合のみです（自動判定）。
A14: 未訪問の店・予約手段が未確認の店は、絶対に商品へ載せないでください。
A15: ここを崩すと、この事業の唯一の差別化が消えます。
A17: 【ステータスの使い方】
... A27: この更新こそが商品の差別化要素です。

Sheet 店舗DB
A1: 店舗データベース
A2: 黄色＝入力必須／橙＝任意／緑＝自動判定。1行＝1店舗。
A3: 5行目は記入例です。実際の入力は6行目から始めてください（記入例は上書きしても構いません）。
A4: ID | B4: ステータス | C4: 訪問日 | D4: 店名(日本語) | E4: Name (EN) | F4: エリア | G4: カテゴリ | H4: 価格帯(¥) | I4: ① Why this one | J4: ② 予約手段 | K4: 何日前から | L4: 海外電話番号 | M4: 海外カード | N4: ③ 支払い | O4: ④ 注意点 | P4: ⑤ 日本語ｽｸﾘﾌﾟﾄ | Q4: ⑥ 最寄駅・出口 | R4: 徒歩分 | S4: ⑦ Best time | T4: ⑧ Pair with | U4: ⑨ 写真 | V4: 掲載可否 | W4: 未充足項目数 | X4: 収録商品 | Y4: 店へ一報 | Z4: 計測コード | AA4: 最終確認日 | AB4: メモ
A5: =IF($D5="","",ROW()-4) | B5: 検証済 | C5: 46277 | D5: 焼鳥 ◯◯ | E5: Yakitori ◯◯ | F5: 新宿三丁目 | G5: 焼鳥 | H5: 12000 | I5: 9 seats, one counter, one man. Same 8-course order for 22 years. No menu, no choice. | J5: 電話のみ | K5: 1ヶ月前の1日 10:00 | L5: 可 | M5: 不可 | N5: 現金のみ / ATM徒歩4分 | O5: タトゥー可 / 12歳未満不可 / 撮影は料理のみ / 90分制 | P5: 済 | Q5: 新宿三丁目 C5出口 | R5: 3 | S5: 火・水 17:30の回 | T5: 徒歩12分の◯◯（2:00まで・カード可） | U5: 済 | V5: =IF($D5="","",IF($W5=0,"可","不可")) | W5: =IF($D5="","",IF($D5="",1,0)+IF($E5="",1,0)+IF($F5="",1,0)+IF($G5="",1,0)+IF($I5="",1,0)+IF($J5="",1,0)+IF($N5="",1,0)+IF($O5="",1,0)+IF($P5="",1,0)+IF($Q5="",1,0)+IF($S5="",1,0)+IF($T5="",1,0)+IF($U5="",1,0)) | X5: Tokyo v1 | Y5: 済 | Z5: OMK-YT01 | AA5: 46277 | AB5: 看板は日本語のみ。コインランドリー隣の紺のれん
A6: =IF($D6="","",ROW()-4) | V6: =IF($D6="","",IF($W6=0,"可","不可")) | W6: =IF($D6="","",IF($D6="",1,0)+IF($E6="",1,0)+IF($F6="",1,0)+IF($G6="",1,0)+IF($I6="",1,0)+IF($J6="",1,0)+IF($N6="",1,0)+IF($O6="",1,0)+IF($P6="",1,0)+IF($Q6="",1,0)+IF($S6="",1,0)+IF($T6="",1,0)+IF($U6="",1,0))
A7: =IF($D7="","",ROW()-4) | V7: =IF($D7="","",IF($W7=0,"可","不可")) | W7: =IF($D7="","",IF($D7="",1,0)+IF($E7="",1,0)+IF($F7="",1,0)+IF($G7="",1,0)+IF($I7="",1,0)+IF($J7="",1,0)+IF($N7="",1,0)+IF($O7="",1,0)+IF($P7="",1,0)+IF($Q7="",1,0)+IF($S7="",1,0)+IF($T7="",1,0)+IF($U7="",1,0))
A8: =IF($D8="","",ROW()-4) | V8: =IF($D8="","",IF($W8=0,"可","不可")) | W8: =IF($D8="","",IF($D8="",1,0)+IF($E8="",1,0)+IF($F8="",1,0)+IF($G8="",1,0)+IF($I8="",1,0)+IF($J8="",1,0)+IF($N8="",1,0)+IF($O8="",1,0)+IF($P8="",1,0)+IF($Q8="",1,0)+IF($S8="",1,0)+IF($T8="",1,0)+IF($U8="",1,0))
A9: =IF($D9="","",ROW()-4) | V9: =IF($D9="","",IF($W9=0,"可","不可")) | W9: =IF($D9="","",IF($D9="",1,0)+IF($E9="",1,0)+IF($F9="",1,0)+IF($G9="",1,0)+IF($I9="",1,0)+IF($J9="",1,0)+IF($N9="",1,0)+IF($O9="",1,0)+IF($P9="",1,0)+IF($Q9="",1,0)+IF($S9="",1,0)+IF($T9="",1,0)+IF($U9="",1,0))
A10: =IF($D10="","",ROW()-4) | V10: =IF($D10="","",IF($W10=0,"可","不可")) | W10: =IF($D10="","",IF($D10="",1,0)+IF($E10="",1,0)+IF($F10="",1,0)+IF($G10="",1,0)+IF($I10="",1,0)+IF($J10="",1,0)+IF($N10="",1,0)+IF($O10="",1,0)+IF($P10="",1,0)+IF($Q10="",1,0)+IF($S10="",1,0)+IF($T10="",1,0)+IF($U10="",1,0))
A11: =IF($D11="","",ROW()-4) | V11: =IF($D11="","",IF($W11=0,"可","不可")) | W11: =IF($D11="","",IF($D11="",1,0)+IF($E11="",1,0)+IF($F11="",1,0)+IF($G11="",1,0)+IF($I11="",1,0)+IF($J11="",1,0)+IF($N11="",1,0)+IF($O11="",1,0)+IF($P11="",1,0)+IF($Q11="",1,0)+IF($S11="",1,0)+IF($T11="",1,0)+IF($U11="",1,0))
A12: =IF($D12="","",ROW()-4) | V12: =IF($D12="","",IF($W12=0,"可","不可")) | W12: =IF($D12="","",IF($D12="",1,0)+IF($E12="",1,0)+IF($F12="",1,0)+IF($G12="",1,0)+IF($I12="",1,0)+IF($J12="",1,0)+IF($N12="",1,0)+IF($O12="",1,0)+IF($P12="",1,0)+IF($Q12="",1,0)+IF($S12="",1,0)+IF($T12="",1,0)+IF($U12="",1,0))
A13: =IF($D13="","",ROW()-4) | V13: =IF($D13="","",IF($W13=0,"可","不可")) | W13: =IF($D13="","",IF($D13="",1,0)+IF($E13="",1,0)+IF($F13="",1,0)+IF($G13="",1,0)+IF($I13="",1,0)+IF($J13="",1,0)+IF($N13="",1,0)+IF($O13="",1,0)+IF($P13="",1,0)+IF($Q13="",1,0)+IF($S13="",1,0)+IF($T13="",1,0)+IF($U13="",1,0))
A14: =IF($D14="","",ROW()-4) | V14: =IF($D14="","",IF($W14=0,"可","不可")) | W14: =IF($D14="","",IF($D14="",1,0)+IF($E14="",1,0)+IF($F14="",1,0)+IF($G14="",1,0)+IF($I14="",1,0)+IF($J14="",1,0)+IF($N14="",1,0)+IF($O14="",1,0)+IF($P14="",1,0)+IF($Q14="",1,0)+IF($S14="",1,0)+IF($T14="",1,0)+IF($U14="",1,0))
A15: =IF($D15="","",ROW()-4) | V15: =IF($D15="","",IF($W15=0,"可","不可")) | W15: =IF($D15="","",IF($D15="",1,0)+IF($E15="",1,0)+IF($F15="",1,0)+IF($G15="",1,0)+IF($I15="",1,0)+IF($J15="",1,0)+IF($N15="",1,0)+IF($O15="",1,0)+IF($P15="",1,0)+IF($Q15="",1,0)+IF($S15="",1,0)+IF($T15="",1,0)+IF($U15="",1,0))
A16: =IF($D16="","",ROW()-4) | V16: =IF($D16="","",IF($W16=0,"可","不可")) | W16: =IF($D16="","",IF($D16="",1,0)+IF($E16="",1,0)+IF($F16="",1,0)+IF($G16="",1,0)+IF($I16="",1,0)+IF($J16="",1,0)+IF($N16="",1,0)+IF($O16="",1,0)+IF($P16="",1,0)+IF($Q16="",1,0)+IF($S16="",1,0)+IF($T16="",1,0)+IF($U16="",1,0))
A17: =IF($D17="","",ROW()-4) | V17: =IF($D17="","",IF($W17=0,"可","不可")) | W17: =IF($D17="","",IF($D17="",1,0)+IF($E17="",1,0)+IF($F17="",1,0)+IF($G17="",1,0)+IF($I17="",1,0)+IF($J17="",1,0)+IF($N17="",1,0)+IF($O17="",1,0)+IF($P17="",1,0)+IF($Q17="",1,0)+IF($S17="",1,0)+IF($T17="",1,0)+IF($U17="",1,0))
... A404: =IF($D404="","",ROW()-4) | V404: =IF($D404="","",IF($W404=0,"可","不可")) | W404: =IF($D404="","",IF($D404="",1,0)+IF($E404="",1,0)+IF($F404="",1,0)+IF($G404="",1,0)+IF($I404="",1,0)+IF($J404="",1,0)+IF($N404="",1,0)+IF($O404="",1,0)+IF($P404="",1,0)+IF($Q404="",1,0)+IF($S404="",1,0)+IF($T404="",1,0)+IF($U404="",1,0))
A406: ※ データはこの範囲（400行）まで。足りなくなったら行を追加し、V列・W列・A列の数式を下方向にコピーしてください。

Sheet 集計
A1: 集計（自動）
A4: 登録店舗数（総数） | B4: =COUNTIF(店舗DB!$D$5:$D$404,"<>")
A5: うち 掲載可（9項目充足） | B5: =COUNTIF(店舗DB!$V$5:$V$404,"可")
A6: うち 掲載不可（項目欠落） | B6: =COUNTIF(店舗DB!$V$5:$V$404,"不可")
A8: ステータス：候補 | B8: =COUNTIF(店舗DB!$B$5:$B$404,"候補")
A9: ステータス：訪問済 | B9: =COUNTIF(店舗DB!$B$5:$B$404,"訪問済")
A10: ステータス：検証済 | B10: =COUNTIF(店舗DB!$B$5:$B$404,"検証済")
A11: ステータス：掲載中 | B11: =COUNTIF(店舗DB!$B$5:$B$404,"掲載中")
A12: ステータス：要再確認 | B12: =COUNTIF(店舗DB!$B$5:$B$404,"要再確認")
A13: ステータス：除外 | B13: =COUNTIF(店舗DB!$B$5:$B$404,"除外")
A15: 店へ一報：済 | B15: =COUNTIF(店舗DB!$Y$5:$Y$404,"済")
A16: 計測コード設定済 | B16: =COUNTIF(店舗DB!$Z$5:$Z$404,"<>")
A19: ■ 商品化の目安
A20: ・Tokyo Access Guide の収録は「掲載可」の店のみ。40〜50店が目標だが、20店でも全店に攻略情報があれば $19 は成立する。
A21: ・「50店」という数字を埋めるために基準を下げないこと。数より密度。
A22: ・「計測コード設定済」の数がタイアップ営業の武器になる。掲載時から仕込むこと。
