Workbook

Sheet ルール
B3: 1 | C3: 文字は「游ゴシック」、数字は「Arial」を基本。備考欄などの細かい文章は「游ゴシック Medium」。
B4: 2 | C4: タイトル、合計欄は太字
B5: 3 | C5: 数字は円単位で入力、表示は千円単位に設定済み
B6: 4 | C6: 基本の背景は以下の通り。紺、水色、グレー、白、青。パレットの上部の色。
C8: 線は紺か白か青。
C10: 資産の部
C11: 科目 | D11: ='BS(借方)'!F10 -> 0 | E11: 調整額 | F11: 調整後
C12: 【流動資産】 | D12: =SUM(D13:D26) -> 5000000 | E12: =SUM(E13:E26) -> -500000 | F12: =SUM(F13:F26) -> 4500000
C13: 現金及び預金 | D13: 5000000 | E13: -500000 | F13: =D13+E13 -> 4500000
F14: =D14+E14 -> 0

Sheet 財務入力→

Sheet BS(借方)
C1: ←基本的にはここをつかう→
C2: 1期目 | D2: 2期目 | E2: 3期目 | F2: （4期目） | G2: 進行期
B3: 資産の部
B4: 科目 | C4: － | D4: 23年11月期 | E4: 24年11月期 | F4: 25年11月期 | G4: 26年11月期 （7か月TB）
B5: 【流動資産】 | C5: =SUM(C6:C19) -> 0 | D5: =SUM(D6:D19) -> 116930952 | E5: =SUM(E6:E19) -> 188786028 | F5: =SUM(F6:F19) -> 150113194 | G5: =SUM(G6:G19) -> 92091317
B6: 現金及び預金 | D6: 13655404 | E6: 17627838 | F6: 10140492 | G6: 14792479
B7: 売掛金 | D7: 28157886 | E7: 39602581 | F7: 27628072 | G7: 16678270
B8: 商品 | D8: 70917819 | E8: 127080914 | F8: 106017284 | G8: 58445785
B9: 貯蔵品 | D9: 150000 | E9: 150000 | F9: 150000 | G9: 150000
B10: 前渡金 | D10: 1200000
B11: 前払費用 | D11: 2837243 | E11: 4237195 | F11: 3991637 | G11: 392743
B12: 未収入金 | E12: 87500 | F12: 30800
B13: 未収還付法人税等 | D13: 12600 | F13: 504909
B14: 仮払金 | F14: 1650000 | G14: 1677040
B15: 立替金 | G15: -45000
B20: 【固定資産】 | C20: =C21+C35+C46 -> 0 | D20: =D21+D35+D46 -> 68592308 | E20: =E21+E35+E46 -> 95384583 | F20: =F21+F35+F46 -> 85271983 | G20: =G21+G35+G46 -> 86018013
B21: ［有形固定資産］ | C21: =SUM(C22:C34) -> 0 | D21: =SUM(D22:D34) -> 42883311 | E21: =SUM(E22:E34) -> 63570009 | F21: =SUM(F22:F34) -> 54658019 | G21: =SUM(G22:G34) -> 57570649
B22: 建物 | D22: 25512741 | E22: 45557783 | F22: 44397084
B23: 建物付属設備 | G23: 44397084
B24: 構築物 | G24: 2475000
B25: 車両運搬具 | D25: 15882874 | E25: 10609341 | F25: 1057574 | G25: 1495204
B26: 工具器具及び備品 | D26: 1246562 | E26: 7402885 | F26: 6044761 | G26: 6044761
B27: 土地 | F27: 2974400 | G27: 2974400
B28: その他の有形固定資産 | D28: 241134 | F28: 184200 | G28: 184200
B35: ［無形固定資産］ | C35: =SUM(C36:C45) -> 0 | D35: =SUM(D36:D45) -> 0 | E35: =SUM(E36:E45) -> 0 | F35: =SUM(F36:F45) -> 0 | G35: =SUM(G36:G45) -> 0
B46: ［投資その他資産］ | C46: =SUM(C47:C55) -> 0 | D46: =SUM(D47:D55) -> 25708997 | E46: =SUM(E47:E55) -> 31814574 | F46: =SUM(F47:F55) -> 30613964 | G46: =SUM(G47:G55) -> 28447364
B47: リサイクル預託金 | D47: 58820 | E47: 58820 | F47: 31500 | G47: 31500
B48: 長期前払費用 | D48: 3335613 | E48: 2513170 | F48: 1711860 | G48: 1711860
B49: 差入保証金 | D49: 20641800 | E49: 27656200 | F49: 27370600 | G49: 25204000
B50: 営業権 | D50: 1672764 | E50: 1586384 | F50: 1500004 | G50: 1500004
B56: 【繰延資産】 | C56: =SUM(C57:C60) -> 0 | D56: =SUM(D57:D60) -> 0 | E56: =SUM(E57:E60) -> 0 | F56: =SUM(F57:F60) -> 0 | G56: =SUM(G57:G60) -> 0
B61: 資産合計 | C61: =C5+C20+C56 -> 0 | D61: =D5+D20+D56 -> 185523260 | E61: =E5+E20+E56 -> 284170611 | F61: =F5+F20+F56 -> 235385177 | G61: =G5+G20+G56 -> 178109330
B63: バランスチェック | C63: =EXACT(C61,'BS (貸方)'!C51) -> 1 | D63: =EXACT(D61,'BS (貸方)'!D51) -> 1 | E63: =EXACT(E61,'BS (貸方)'!E51) -> 1 | F63: =EXACT(F61,'BS (貸方)'!F51) -> 1 | G63: =EXACT(G61,'BS (貸方)'!G51) -> 1

Sheet BS (貸方)
E2: (単位：千円)
B3: 負債の部
B4: 科目 | C4: ='BS(借方)'!C4 -> － | D4: ='BS(借方)'!D4 -> 23年11月期 | E4: ='BS(借方)'!E4 -> 24年11月期 | F4: ='BS(借方)'!F4 -> 25年11月期 | G4: ='BS(借方)'!G4 -> 26年11月期 （7か月TB）
B5: 【流動負債】 | C5: =SUM(C6:C17) -> 0 | D5: =SUM(D6:D17) -> 30379997 | E5: =SUM(E6:E17) -> 47366299 | F5: =SUM(F6:F17) -> 47672202 | G5: =SUM(G6:G17) -> 33413938
B6: 買掛金 | D6: 10175789 | E6: 14254641 | F6: 9202412 | G6: 7003448
B7: 短期借入金 | G7: 3153
B8: 未払金 | F8: 714227
B9: 未払費用 | D9: 12571145 | E9: 24016295 | F9: 20113617 | G9: 9578501
B10: 未払法人税等 | D10: 229900 | E10: 961500 | F10: 242500
B11: 未払消費税等 | D11: 3644800 | E11: 3776100 | F11: 11784100 | G11: 7438091
B12: 預り金 | D12: 614470 | E12: 606685 | F12: 2391530 | G12: 1600194
B13: カード未払金 | D13: 3143893 | E13: 3751078 | F13: 3223816 | G13: 7790551
B18: 【固定負債】 | C18: =SUM(C19:C24) -> 0 | D18: =SUM(D19:D24) -> 149815893 | E18: =SUM(E19:E24) -> 230502580 | F18: =SUM(F19:F24) -> 201769790 | G18: =SUM(G19:G24) -> 196939108
B19: 長期借入金 | D19: 134042000 | E19: 218455000 | F19: 191858000 | G19: 191858000
B20: 役員借入金 | D20: 1121593 | F20: 7565770 | G20: 3402888
B21: 長期未払金 | D21: 14652300 | E21: 12047580 | F21: 2346020 | G21: 1678220
B25: 負債合計 | C25: =C5+C18 -> 0 | D25: =D5+D18 -> 180195890 | E25: =E5+E18 -> 277868879 | F25: =F5+F18 -> 249441992 | G25: =G5+G18 -> 230353046
B34: 純資産の部
B35: 【資本金】 | C35: =SUM(C36:C38) -> 0 | D35: =SUM(D36:D38) -> 1000000 | E35: =SUM(E36:E38) -> 1000000 | F35: =SUM(F36:F38) -> 1000000 | G35: =SUM(G36:G38) -> 1000000
B36: 資本金 | D36: 1000000 | E36: 1000000 | F36: 1000000 | G36: 1000000
B39: 【資本剰余金】 | C39: =SUM(C40:C42) -> 0 | D39: =SUM(D40:D42) -> 0 | E39: =SUM(E40:E42) -> 0 | F39: =SUM(F40:F42) -> 0 | G39: =SUM(G40:G42) -> 0
B43: 【利益剰余金】 | C43: =SUM(C44:C48) -> 0 | D43: =SUM(D44:D48) -> 4327370 | E43: =SUM(E44:E48) -> 5301732 | F43: =SUM(F44:F48) -> -15056815 | G43: =SUM(G44:G48) -> -53243716
B44: 繰越利益剰余金 | D44: 4327370 | E44: 5301732 | F44: -15056815 | G44: -53243716
B49: 【自己株式】 | C49: 0 | D49: 0 | E49: 0 | F49: 0 | G49: 0
B50: 純資産合計 | C50: =C35+C39+C43+C49 -> 0 | D50: =D35+D39+D43+D49 -> 5327370 | E50: =E35+E39+E43+E49 -> 6301732 | F50: =F35+F39+F43+F49 -> -14056815 | G50: =G35+G39+G43+G49 -> -52243716
B51: 負債・純資産合計 | C51: =C25+C50 -> 0 | D51: =D25+D50 -> 185523260 | E51: =E25+E50 -> 284170611 | F51: =F25+F50 -> 235385177 | G51: =G25+G50 -> 178109330
B53: バランスチェック | C53: =EXACT(C51,'BS(借方)'!C61) -> 1 | D53: =EXACT(D51,'BS(借方)'!D61) -> 1 | E53: =EXACT(E51,'BS(借方)'!E61) -> 1 | F53: =EXACT(F51,'BS(借方)'!F61) -> 1 | G53: =EXACT(G51,'BS(借方)'!G61) -> 1

Sheet PL
H2: (単位：千円)
B3: 科目 | C3: ='BS(借方)'!C4 -> － | E3: ='BS(借方)'!D4 -> 23年11月期 | G3: ='BS(借方)'!E4 -> 24年11月期 | I3: ='BS(借方)'!F4 -> 25年11月期 | K3: ='BS(借方)'!G4 -> 26年11月期 （7か月TB）
C4: 帳簿価額 | D4: 売上高比 | E4: 帳簿価額 | F4: 売上高比 | G4: 帳簿価額 | H4: 売上高比 | I4: 帳簿価額 | J4: 売上高比 | K4: 帳簿価額 | L4: 売上高比
B5: 生体売上高 | D5: =IFERROR(IF(C5=0,"",C5/C$11),"") | E5: 293213620 | F5: =IFERROR(IF(E5=0,"",E5/E$11),"") -> 0.61803566 | G5: 333089628 | H5: =IFERROR(IF(G5=0,"",G5/G$11),"") -> 0.6179369 | I5: 338295378 | J5: =IFERROR(IF(I5=0,"",I5/I$11),"") -> 0.60584097 | K5: 165116994 | L5: =IFERROR(IF(K5=0,"",K5/K$11),"") -> 0.59149188
B6: サービス売上高 | D6: =IFERROR(IF(C6=0,"",C6/C$11),"") | E6: 65655525 | F6: =IFERROR(IF(E6=0,"",E6/E$11),"") -> 0.13838871 | G6: 60897406 | H6: =IFERROR(IF(G6=0,"",G6/G$11),"") -> 0.11297486 | I6: 52699187 | J6: =IFERROR(IF(I6=0,"",I6/I$11),"") -> 0.09437707 | K6: 32791687 | L6: =IFERROR(IF(K6=0,"",K6/K$11),"") -> 0.11746832
B7: 物販売上高 | D7: =IFERROR(IF(C7=0,"",C7/C$11),"") | E7: 115559176 | F7: =IFERROR(IF(E7=0,"",E7/E$11),"") -> 0.24357563 | G7: 145047985 | H7: =IFERROR(IF(G7=0,"",G7/G$11),"") -> 0.26908824 | I7: 167395169 | J7: =IFERROR(IF(I7=0,"",I7/I$11),"") -> 0.29978196 | K7: 81244762 | L7: =IFERROR(IF(K7=0,"",K7/K$11),"") -> 0.2910398
D8: =IFERROR(IF(C8=0,"",C8/C$11),"") | F8: =IFERROR(IF(E8=0,"",E8/E$11),"") | H8: =IFERROR(IF(G8=0,"",G8/G$11),"") | J8: =IFERROR(IF(I8=0,"",I8/I$11),"") | L8: =IFERROR(IF(K8=0,"",K8/K$11),"")
D9: =IFERROR(IF(C9=0,"",C9/C$11),"") | F9: =IFERROR(IF(E9=0,"",E9/E$11),"") | H9: =IFERROR(IF(G9=0,"",G9/G$11),"") | J9: =IFERROR(IF(I9=0,"",I9/I$11),"") | L9: =IFERROR(IF(K9=0,"",K9/K$11),"")
D10: =IFERROR(IF(C10=0,"",C10/C$11),"") | F10: =IFERROR(IF(E10=0,"",E10/E$11),"") | H10: =IFERROR(IF(G10=0,"",G10/G$11),"") | J10: =IFERROR(IF(I10=0,"",I10/I$11),"") | L10: =IFERROR(IF(K10=0,"",K10/K$11),"")
B11: 売上高 | C11: =SUM(C5:C10) -> 0 | D11: =IFERROR(IF(C11=0,"",C11/C$11),"") | E11: =SUM(E5:E10) -> 474428321 | F11: =IFERROR(IF(E11=0,"",E11/E$11),"") -> 1 | G11: =SUM(G5:G10) -> 539035019 | H11: =IFERROR(IF(G11=0,"",G11/G$11),"") -> 1 | I11: =SUM(I5:I10) -> 558389734 | J11: =IFERROR(IF(I11=0,"",I11/I$11),"") -> 1 | K11: =SUM(K5:K10) -> 279153443 | L11: =IFERROR(IF(K11=0,"",K11/K$11),"") -> 1
B12: 期首棚卸高 | D12: =IFERROR(IF(C12=0,"",C12/C$11),"") | E12: 39485899 | F12: =IFERROR(IF(E12=0,"",E12/E$11),"") -> 0.083228377 | G12: 70917819 | H12: =IFERROR(IF(G12=0,"",G12/G$11),"") -> 0.1315644 | I12: 127080914 | J12: =IFERROR(IF(I12=0,"",I12/I$11),"") -> 0.22758462 | K12: 106017284 | L12: =IFERROR(IF(K12=0,"",K12/K$11),"") -> 0.37978139
B13: 商品仕入高 | D13: =IFERROR(IF(C13=0,"",C13/C$11),"") | E13: 183853875 | F13: =IFERROR(IF(E13=0,"",E13/E$11),"") -> 0.38752719 | G13: 220800993 | H13: =IFERROR(IF(G13=0,"",G13/G$11),"") -> 0.40962272 | I13: 182243467 | J13: =IFERROR(IF(I13=0,"",I13/I$11),"") -> 0.32637324 | K13: 92273907 | L13: =IFERROR(IF(K13=0,"",K13/K$11),"") -> 0.33054906
B14: 外注費 | D14: =IFERROR(IF(C14=0,"",C14/C$11),"") | E14: 29627732 | F14: =IFERROR(IF(E14=0,"",E14/E$11),"") -> 0.062449333 | G14: 31465971 | H14: =IFERROR(IF(G14=0,"",G14/G$11),"") -> 0.058374632 | I14: 25058151 | J14: =IFERROR(IF(I14=0,"",I14/I$11),"") -> 0.044875737 | K14: 8916840 | L14: =IFERROR(IF(K14=0,"",K14/K$11),"") -> 0.031942432
B15: 他勘定振替高 | D15: =IFERROR(IF(C15=0,"",C15/C$11),"") | F15: =IFERROR(IF(E15=0,"",E15/E$11),"") | H15: =IFERROR(IF(G15=0,"",G15/G$11),"") | J15: =IFERROR(IF(I15=0,"",I15/I$11),"") | K15: -44000000 | L15: =IFERROR(IF(K15=0,"",K15/K$11),"") -> -0.15761941
B16: 期末棚卸高 | D16: =IFERROR(IF(C16=0,"",C16/C$11),"") | E16: -70917819 | F16: =IFERROR(IF(E16=0,"",E16/E$11),"") -> -0.14948058 | G16: -127080914 | H16: =IFERROR(IF(G16=0,"",G16/G$11),"") -> -0.23575632 | I16: -106017284 | J16: =IFERROR(IF(I16=0,"",I16/I$11),"") -> -0.18986252 | K16: -58445785 | L16: =IFERROR(IF(K16=0,"",K16/K$11),"") -> -0.20936795
B17: 売上原価 | C17: =SUM(C12:C16) -> 0 | D17: =IFERROR(IF(C17=0,"",C17/C$11),"") | E17: =SUM(E12:E16) -> 182049687 | F17: =IFERROR(IF(E17=0,"",E17/E$11),"") -> 0.38372432 | G17: =SUM(G12:G16) -> 196103869 | H17: =IFERROR(IF(G17=0,"",G17/G$11),"") -> 0.36380543 | I17: =SUM(I12:I16) -> 228365248 | J17: =IFERROR(IF(I17=0,"",I17/I$11),"") -> 0.40897107 | K17: =SUM(K12:K16) -> 104762246 | L17: =IFERROR(IF(K17=0,"",K17/K$11),"") -> 0.37528552
B18: 売上総利益 | C18: =C11-C17 -> 0 | D18: =IFERROR(IF(C18=0,"",C18/C$11),"") | E18: =E11-E17 -> 292378634 | F18: =IFERROR(IF(E18=0,"",E18/E$11),"") -> 0.61627568 | G18: =G11-G17 -> 342931150 | H18: =IFERROR(IF(G18=0,"",G18/G$11),"") -> 0.63619457 | I18: =I11-I17 -> 330024486 | J18: =IFERROR(IF(I18=0,"",I18/I$11),"") -> 0.59102893 | K18: =K11-K17 -> 174391197 | L18: =IFERROR(IF(K18=0,"",K18/K$11),"") -> 0.62471448
B19: 販売費及び一般管理費 | C19: =SGA!C40 -> 0 | D19: =IFERROR(IF(C19=0,"",C19/C$11),"") | E19: =SGA!E40 -> 290037494 | F19: =IFERROR(IF(E19=0,"",E19/E$11),"") -> 0.61134102 | G19: =SGA!G40 -> 339909050 | H19: =IFERROR(IF(G19=0,"",G19/G$11),"") -> 0.63058807 | I19: =SGA!I40 -> 349576223 | J19: =IFERROR(IF(I19=0,"",I19/I$11),"") -> 0.62604343 | K19: =SGA!K40 -> 167754348 | L19: =IFERROR(IF(K19=0,"",K19/K$11),"") -> 0.60093956
B20: 営業利益 | C20: =C18- C19 -> 0 | D20: =IFERROR(IF(C20=0,"",C20/C$11),"") | E20: =E18- E19 -> 2341140 | F20: =IFERROR(IF(E20=0,"",E20/E$11),"") -> 0.0049346548 | G20: =G18- G19 -> 3022100 | H20: =IFERROR(IF(G20=0,"",G20/G$11),"") -> 0.0056065003 | I20: =I18- I19 -> -19551737 | J20: =IFERROR(IF(I20=0,"",I20/I$11),"") -> -0.035014499 | K20: =K18- K19 -> 6636849 | L20: =IFERROR(IF(K20=0,"",K20/K$11),"") -> 0.023774914
B21: 営業外収益 | C21: =SUM(C22:C28) -> 0 | D21: =IFERROR(IF(C21=0,"",C21/C$11),"") | E21: =SUM(E22:E28) -> 1321452 | F21: =IFERROR(IF(E21=0,"",E21/E$11),"") -> 0.0027853565 | G21: =SUM(G22:G28) -> 2383452 | H21: =IFERROR(IF(G21=0,"",G21/G$11),"") -> 0.0044217016 | I21: =SUM(I22:I28) -> 3631958 | J21: =IFERROR(IF(I21=0,"",I21/I$11),"") -> 0.0065043424 | K21: =SUM(K22:K28) -> 1059276 | L21: =IFERROR(IF(K21=0,"",K21/K$11),"") -> 0.0037946012
B22: 受取利息 | D22: =IFERROR(IF(C22=0,"",C22/C$11),"") | E22: 193 | F22: =IFERROR(IF(E22=0,"",E22/E$11),"") -> 4.0680539e-07 | G22: 4702 | H22: =IFERROR(IF(G22=0,"",G22/G$11),"") -> 8.7229954e-06 | I22: 24608 | J22: =IFERROR(IF(I22=0,"",I22/I$11),"") -> 4.4069578e-05 | K22: 6446 | L22: =IFERROR(IF(K22=0,"",K22/K$11),"") -> 2.3091243e-05
B23: 受取配当金 | D23: =IFERROR(IF(C23=0,"",C23/C$11),"") | E23: 188 | F23: =IFERROR(IF(E23=0,"",E23/E$11),"") -> 3.9626639e-07 | G23: 376 | H23: =IFERROR(IF(G23=0,"",G23/G$11),"") -> 6.9754281e-07 | I23: 282 | J23: =IFERROR(IF(I23=0,"",I23/I$11),"") -> 5.0502361e-07 | K23: 300 | L23: =IFERROR(IF(K23=0,"",K23/K$11),"") -> 1.0746778e-06
B24: 雑収入 | D24: =IFERROR(IF(C24=0,"",C24/C$11),"") | E24: 1321071 | F24: =IFERROR(IF(E24=0,"",E24/E$11),"") -> 0.0027845534 | G24: 2378374 | H24: =IFERROR(IF(G24=0,"",G24/G$11),"") -> 0.0044122811 | I24: 3607068 | J24: =IFERROR(IF(I24=0,"",I24/I$11),"") -> 0.0064597678 | K24: 1052530 | L24: =IFERROR(IF(K24=0,"",K24/K$11),"") -> 0.0037704353
D25: =IFERROR(IF(C25=0,"",C25/C$11),"") | F25: =IFERROR(IF(E25=0,"",E25/E$11),"") | H25: =IFERROR(IF(G25=0,"",G25/G$11),"") | J25: =IFERROR(IF(I25=0,"",I25/I$11),"") | L25: =IFERROR(IF(K25=0,"",K25/K$11),"")
D26: =IFERROR(IF(C26=0,"",C26/C$11),"") | F26: =IFERROR(IF(E26=0,"",E26/E$11),"") | H26: =IFERROR(IF(G26=0,"",G26/G$11),"") | J26: =IFERROR(IF(I26=0,"",I26/I$11),"") | L26: =IFERROR(IF(K26=0,"",K26/K$11),"")
D27: =IFERROR(IF(C27=0,"",C27/C$11),"") | F27: =IFERROR(IF(E27=0,"",E27/E$11),"") | H27: =IFERROR(IF(G27=0,"",G27/G$11),"") | J27: =IFERROR(IF(I27=0,"",I27/I$11),"") | L27: =IFERROR(IF(K27=0,"",K27/K$11),"")
D28: =IFERROR(IF(C28=0,"",C28/C$11),"") | F28: =IFERROR(IF(E28=0,"",E28/E$11),"") | H28: =IFERROR(IF(G28=0,"",G28/G$11),"") | J28: =IFERROR(IF(I28=0,"",I28/I$11),"") | L28: =IFERROR(IF(K28=0,"",K28/K$11),"")
B29: 営業外費用 | C29: =SUM(C30:C36) -> 0 | D29: =IFERROR(IF(C29=0,"",C29/C$11),"") | E29: =SUM(E30:E36) -> 1134221 | F29: =IFERROR(IF(E29=0,"",E29/E$11),"") -> 0.002390711 | G29: =SUM(G30:G36) -> 2295915 | H29: =IFERROR(IF(G29=0,"",G29/G$11),"") -> 0.0042593058 | I29: =SUM(I30:I36) -> 2655577 | J29: =IFERROR(IF(I29=0,"",I29/I$11),"") -> 0.0047557769 | K29: =SUM(K30:K36) -> 1881979 | L29: =IFERROR(IF(K29=0,"",K29/K$11),"") -> 0.0067417367
B30: 支払利息 | D30: =IFERROR(IF(C30=0,"",C30/C$11),"") | E30: 1134221 | F30: =IFERROR(IF(E30=0,"",E30/E$11),"") -> 0.002390711 | G30: 1787923 | H30: =IFERROR(IF(G30=0,"",G30/G$11),"") -> 0.0033168958 | I30: 2590791 | J30: =IFERROR(IF(I30=0,"",I30/I$11),"") -> 0.004639754 | K30: 1881899 | L30: =IFERROR(IF(K30=0,"",K30/K$11),"") -> 0.0067414501
B31: 雑損失 | D31: =IFERROR(IF(C31=0,"",C31/C$11),"") | F31: =IFERROR(IF(E31=0,"",E31/E$11),"") | G31: 507992 | H31: =IFERROR(IF(G31=0,"",G31/G$11),"") -> 0.00094241001 | I31: 64786 | J31: =IFERROR(IF(I31=0,"",I31/I$11),"") -> 0.00011602291 | K31: 80 | L31: =IFERROR(IF(K31=0,"",K31/K$11),"") -> 2.8658074e-07
D32: =IFERROR(IF(C32=0,"",C32/C$11),"") | F32: =IFERROR(IF(E32=0,"",E32/E$11),"") | H32: =IFERROR(IF(G32=0,"",G32/G$11),"") | J32: =IFERROR(IF(I32=0,"",I32/I$11),"") | L32: =IFERROR(IF(K32=0,"",K32/K$11),"")
D33: =IFERROR(IF(C33=0,"",C33/C$11),"") | F33: =IFERROR(IF(E33=0,"",E33/E$11),"") | H33: =IFERROR(IF(G33=0,"",G33/G$11),"") | J33: =IFERROR(IF(I33=0,"",I33/I$11),"") | L33: =IFERROR(IF(K33=0,"",K33/K$11),"")
D34: =IFERROR(IF(C34=0,"",C34/C$11),"") | F34: =IFERROR(IF(E34=0,"",E34/E$11),"") | H34: =IFERROR(IF(G34=0,"",G34/G$11),"") | J34: =IFERROR(IF(I34=0,"",I34/I$11),"") | L34: =IFERROR(IF(K34=0,"",K34/K$11),"")
D35: =IFERROR(IF(C35=0,"",C35/C$11),"") | F35: =IFERROR(IF(E35=0,"",E35/E$11),"") | H35: =IFERROR(IF(G35=0,"",G35/G$11),"") | J35: =IFERROR(IF(I35=0,"",I35/I$11),"") | L35: =IFERROR(IF(K35=0,"",K35/K$11),"")
D36: =IFERROR(IF(C36=0,"",C36/C$11),"") | F36: =IFERROR(IF(E36=0,"",E36/E$11),"") | H36: =IFERROR(IF(G36=0,"",G36/G$11),"") | J36: =IFERROR(IF(I36=0,"",I36/I$11),"") | L36: =IFERROR(IF(K36=0,"",K36/K$11),"")
B37: 経常利益 | C37: =C20+C21-C29 -> 0 | D37: =IFERROR(IF(C37=0,"",C37/C$11),"") | E37: =E20+E21-E29 -> 2528371 | F37: =IFERROR(IF(E37=0,"",E37/E$11),"") -> 0.0053293003 | G37: =G20+G21-G29 -> 3109637 | H37: =IFERROR(IF(G37=0,"",G37/G$11),"") -> 0.0057688961 | I37: =I20+I21-I29 -> -18575356 | J37: =IFERROR(IF(I37=0,"",I37/I$11),"") -> -0.033265934 | K37: =K20+K21-K29 -> 5814146 | L37: =IFERROR(IF(K37=0,"",K37/K$11),"") -> 0.020827778
B38: 特別利益 | C38: =SUM(C39:C44) -> 0 | D38: =IFERROR(IF(C38=0,"",C38/C$11),"") | E38: =SUM(E39:E44) -> 0 | F38: =IFERROR(IF(E38=0,"",E38/E$11),"") | G38: =SUM(G39:G44) -> 0 | H38: =IFERROR(IF(G38=0,"",G38/G$11),"") | I38: =SUM(I39:I44) -> 0 | J38: =IFERROR(IF(I38=0,"",I38/I$11),"") | K38: =SUM(K39:K44) -> 0 | L38: =IFERROR(IF(K38=0,"",K38/K$11),"")
D39: =IFERROR(IF(C39=0,"",C39/C$11),"") | F39: =IFERROR(IF(E39=0,"",E39/E$11),"") | H39: =IFERROR(IF(G39=0,"",G39/G$11),"") | J39: =IFERROR(IF(I39=0,"",I39/I$11),"") | L39: =IFERROR(IF(K39=0,"",K39/K$11),"")
D40: =IFERROR(IF(C40=0,"",C40/C$11),"") | F40: =IFERROR(IF(E40=0,"",E40/E$11),"") | H40: =IFERROR(IF(G40=0,"",G40/G$11),"") | J40: =IFERROR(IF(I40=0,"",I40/I$11),"") | L40: =IFERROR(IF(K40=0,"",K40/K$11),"")
D41: =IFERROR(IF(C41=0,"",C41/C$11),"") | F41: =IFERROR(IF(E41=0,"",E41/E$11),"") | H41: =IFERROR(IF(G41=0,"",G41/G$11),"") | J41: =IFERROR(IF(I41=0,"",I41/I$11),"") | L41: =IFERROR(IF(K41=0,"",K41/K$11),"")
D42: =IFERROR(IF(C42=0,"",C42/C$11),"") | F42: =IFERROR(IF(E42=0,"",E42/E$11),"") | H42: =IFERROR(IF(G42=0,"",G42/G$11),"") | J42: =IFERROR(IF(I42=0,"",I42/I$11),"") | L42: =IFERROR(IF(K42=0,"",K42/K$11),"")
D43: =IFERROR(IF(C43=0,"",C43/C$11),"") | F43: =IFERROR(IF(E43=0,"",E43/E$11),"") | H43: =IFERROR(IF(G43=0,"",G43/G$11),"") | J43: =IFERROR(IF(I43=0,"",I43/I$11),"") | L43: =IFERROR(IF(K43=0,"",K43/K$11),"")
D44: =IFERROR(IF(C44=0,"",C44/C$11),"") | F44: =IFERROR(IF(E44=0,"",E44/E$11),"") | H44: =IFERROR(IF(G44=0,"",G44/G$11),"") | J44: =IFERROR(IF(I44=0,"",I44/I$11),"") | L44: =IFERROR(IF(K44=0,"",K44/K$11),"")
B45: 特別損失 | C45: =SUM(C46:C51) -> 0 | D45: =IFERROR(IF(C45=0,"",C45/C$11),"") | E45: =SUM(E46:E51) -> 0 | F45: =IFERROR(IF(E45=0,"",E45/E$11),"") | G45: =SUM(G46:G51) -> 0 | H45: =IFERROR(IF(G45=0,"",G45/G$11),"") | I45: =SUM(I46:I51) -> 1298191 | J45: =IFERROR(IF(I45=0,"",I45/I$11),"") -> 0.0023248834 | K45: =SUM(K46:K51) -> 44000000 | L45: =IFERROR(IF(K45=0,"",K45/K$11),"") -> 0.15761941
B46: 固定資産売却損 | D46: =IFERROR(IF(C46=0,"",C46/C$11),"") | F46: =IFERROR(IF(E46=0,"",E46/E$11),"") | H46: =IFERROR(IF(G46=0,"",G46/G$11),"") | I46: 968026 | J46: =IFERROR(IF(I46=0,"",I46/I$11),"") -> 0.0017336028 | L46: =IFERROR(IF(K46=0,"",K46/K$11),"")
B47: 固定資産除却損 | D47: =IFERROR(IF(C47=0,"",C47/C$11),"") | F47: =IFERROR(IF(E47=0,"",E47/E$11),"") | H47: =IFERROR(IF(G47=0,"",G47/G$11),"") | I47: 330165 | J47: =IFERROR(IF(I47=0,"",I47/I$11),"") -> 0.00059128057 | L47: =IFERROR(IF(K47=0,"",K47/K$11),"")
B48: 棚卸資産廃棄損 | D48: =IFERROR(IF(C48=0,"",C48/C$11),"") | F48: =IFERROR(IF(E48=0,"",E48/E$11),"") | H48: =IFERROR(IF(G48=0,"",G48/G$11),"") | J48: =IFERROR(IF(I48=0,"",I48/I$11),"") | K48: 44000000 | L48: =IFERROR(IF(K48=0,"",K48/K$11),"") -> 0.15761941
D49: =IFERROR(IF(C49=0,"",C49/C$11),"") | F49: =IFERROR(IF(E49=0,"",E49/E$11),"") | H49: =IFERROR(IF(G49=0,"",G49/G$11),"") | J49: =IFERROR(IF(I49=0,"",I49/I$11),"") | L49: =IFERROR(IF(K49=0,"",K49/K$11),"")
D50: =IFERROR(IF(C50=0,"",C50/C$11),"") | F50: =IFERROR(IF(E50=0,"",E50/E$11),"") | H50: =IFERROR(IF(G50=0,"",G50/G$11),"") | J50: =IFERROR(IF(I50=0,"",I50/I$11),"") | L50: =IFERROR(IF(K50=0,"",K50/K$11),"")
D51: =IFERROR(IF(C51=0,"",C51/C$11),"") | F51: =IFERROR(IF(E51=0,"",E51/E$11),"") | H51: =IFERROR(IF(G51=0,"",G51/G$11),"") | J51: =IFERROR(IF(I51=0,"",I51/I$11),"") | L51: =IFERROR(IF(K51=0,"",K51/K$11),"")
B52: 税引前当期純利益 | C52: =C37+C38-C45 -> 0 | D52: =IFERROR(IF(C52=0,"",C52/C$11),"") | E52: =E37+E38-E45 -> 2528371 | F52: =IFERROR(IF(E52=0,"",E52/E$11),"") -> 0.0053293003 | G52: =G37+G38-G45 -> 3109637 | H52: =IFERROR(IF(G52=0,"",G52/G$11),"") -> 0.0057688961 | I52: =I37+I38-I45 -> -19873547 | J52: =IFERROR(IF(I52=0,"",I52/I$11),"") -> -0.035590817 | K52: =K37+K38-K45 -> -38185854 | L52: =IFERROR(IF(K52=0,"",K52/K$11),"") -> -0.13679163
B53: 法人税等 | C53: =SUM(C54:C56) -> 0 | D53: =IFERROR(IF(C53=0,"",C53/C$11),"") | E53: =SUM(E54:E56) -> 894154 | F53: =IFERROR(IF(E53=0,"",E53/E$11),"") -> 0.0018846978 | G53: =SUM(G54:G56) -> 2135275 | H53: =IFERROR(IF(G53=0,"",G53/G$11),"") -> 0.0039612918 | I53: =SUM(I54:I56) -> 485000 | J53: =IFERROR(IF(I53=0,"",I53/I$11),"") -> 0.00086856898 | K53: 1047 | L53: =IFERROR(IF(K53=0,"",K53/K$11),"") -> 3.7506254e-06
B54: 法人税等 | D54: =IFERROR(IF(C54=0,"",C54/C$11),"") | E54: 894154 | F54: =IFERROR(IF(E54=0,"",E54/E$11),"") -> 0.0018846978 | G54: 2135275 | H54: =IFERROR(IF(G54=0,"",G54/G$11),"") -> 0.0039612918 | I54: 485000 | J54: =IFERROR(IF(I54=0,"",I54/I$11),"") -> 0.00086856898 | K54: 986 | L54: =IFERROR(IF(K54=0,"",K54/K$11),"") -> 3.5321076e-06
D56: =IFERROR(IF(C56=0,"",C56/C$11),"") | F56: =IFERROR(IF(E56=0,"",E56/E$11),"") | H56: =IFERROR(IF(G56=0,"",G56/G$11),"") | J56: =IFERROR(IF(I56=0,"",I56/I$11),"") | L56: =IFERROR(IF(K56=0,"",K56/K$11),"")
B57: 税引後当期純利益 | C57: =C52-C53 -> 0 | D57: =IFERROR(IF(C57=0,"",C57/C$11),"") | E57: =E52-E53 -> 1634217 | F57: =IFERROR(IF(E57=0,"",E57/E$11),"") -> 0.0034446025 | G57: =G52-G53 -> 974362 | H57: =IFERROR(IF(G57=0,"",G57/G$11),"") -> 0.0018076043 | I57: =I52-I53 -> -20358547 | J57: =IFERROR(IF(I57=0,"",I57/I$11),"") -> -0.036459386 | K57: =K52-K53 -> -38186901 | L57: =IFERROR(IF(K57=0,"",K57/K$11),"") -> -0.13679538
E59: 1634217 | G59: 974362 | I59: -20358547 | K59: -38186901
C60: =C59=C57 -> 1 | E60: =E59=E57 -> 1 | G60: =G59=G57 -> 1 | I60: =I59=I57 -> 1 | K60: =K59=K57 -> 1

Sheet CR
B2: ※対象会社は小売業であり製造原価報告書は作成されていないため、本シートは使用しない。
H4: (単位：千円)
B5: 科目 | C5: ='BS(借方)'!C4 -> － | E5: ='BS(借方)'!D4 -> 23年11月期 | G5: ='BS(借方)'!E4 -> 24年11月期 | I5: ='BS(借方)'!F4 -> 25年11月期 | K5: ='BS(借方)'!G4 -> 26年11月期 （7か月TB）
C6: 帳簿価額 | D6: 売上高比 | E6: 帳簿価額 | F6: 売上高比 | G6: 帳簿価額 | H6: 売上高比 | I6: 帳簿価額 | J6: 売上高比 | K6: 帳簿価額 | L6: 売上高比
A7: IMに貼るときは非表示→ | B7: 売上 | C7: =PL!C11 -> 0 | D7: - | E7: =PL!E11 -> 474428321 | F7: - | G7: =PL!G11 -> 539035019 | H7: - | I7: =PL!I11 -> 558389734 | J7: - | K7: =PL!K11 -> 279153443 | L7: -
B8: 期首原材料棚卸高 | D8: =IFERROR(IF(C8=0,"",C8/C$7),"") | F8: =IFERROR(IF(E8=0,"",E8/E$7),"") | H8: =IFERROR(IF(G8=0,"",G8/G$7),"") | J8: =IFERROR(IF(I8=0,"",I8/I$7),"") | L8: =IFERROR(IF(K8=0,"",K8/K$7),"")
B9: 原材料仕入高 | D9: =IFERROR(IF(C9=0,"",C9/C$7),"") | F9: =IFERROR(IF(E9=0,"",E9/E$7),"") | H9: =IFERROR(IF(G9=0,"",G9/G$7),"") | J9: =IFERROR(IF(I9=0,"",I9/I$7),"") | L9: =IFERROR(IF(K9=0,"",K9/K$7),"")
B10: 小計 | D10: =IFERROR(IF(C10=0,"",C10/C$7),"") | F10: =IFERROR(IF(E10=0,"",E10/E$7),"") | H10: =IFERROR(IF(G10=0,"",G10/G$7),"") | J10: =IFERROR(IF(I10=0,"",I10/I$7),"") | L10: =IFERROR(IF(K10=0,"",K10/K$7),"")
B11: 期末原材料棚卸高 | D11: =IFERROR(IF(C11=0,"",C11/C$7),"") | F11: =IFERROR(IF(E11=0,"",E11/E$7),"") | H11: =IFERROR(IF(G11=0,"",G11/G$7),"") | J11: =IFERROR(IF(I11=0,"",I11/I$7),"") | L11: =IFERROR(IF(K11=0,"",K11/K$7),"")
D12: =IFERROR(IF(C12=0,"",C12/C$7),"") | F12: =IFERROR(IF(E12=0,"",E12/E$7),"") | H12: =IFERROR(IF(G12=0,"",G12/G$7),"") | J12: =IFERROR(IF(I12=0,"",I12/I$7),"") | L12: =IFERROR(IF(K12=0,"",K12/K$7),"")
D13: =IFERROR(IF(C13=0,"",C13/C$7),"") | F13: =IFERROR(IF(E13=0,"",E13/E$7),"") | H13: =IFERROR(IF(G13=0,"",G13/G$7),"") | J13: =IFERROR(IF(I13=0,"",I13/I$7),"") | L13: =IFERROR(IF(K13=0,"",K13/K$7),"")
B14: 材料費 | C14: =SUM(C8:C13) -> 0 | D14: =IFERROR(IF(C14=0,"",C14/C$7),"") | E14: =SUM(E8:E13) -> 0 | F14: =IFERROR(IF(E14=0,"",E14/E$7),"") | G14: =SUM(G8:G13) -> 0 | H14: =IFERROR(IF(G14=0,"",G14/G$7),"") | I14: =SUM(I8:I13) -> 0 | J14: =IFERROR(IF(I14=0,"",I14/I$7),"") | K14: =SUM(K8:K13) -> 0 | L14: =IFERROR(IF(K14=0,"",K14/K$7),"")
D15: =IFERROR(IF(C15=0,"",C15/C$7),"") | F15: =IFERROR(IF(E15=0,"",E15/E$7),"") | H15: =IFERROR(IF(G15=0,"",G15/G$7),"") | J15: =IFERROR(IF(I15=0,"",I15/I$7),"") | L15: =IFERROR(IF(K15=0,"",K15/K$7),"")
D18: =IFERROR(IF(C18=0,"",C18/C$7),"") | F18: =IFERROR(IF(E18=0,"",E18/E$7),"") | H18: =IFERROR(IF(G18=0,"",G18/G$7),"") | J18: =IFERROR(IF(I18=0,"",I18/I$7),"") | L18: =IFERROR(IF(K18=0,"",K18/K$7),"")
D19: =IFERROR(IF(C19=0,"",C19/C$7),"") | F19: =IFERROR(IF(E19=0,"",E19/E$7),"") | H19: =IFERROR(IF(G19=0,"",G19/G$7),"") | J19: =IFERROR(IF(I19=0,"",I19/I$7),"") | L19: =IFERROR(IF(K19=0,"",K19/K$7),"")
D20: =IFERROR(IF(C20=0,"",C20/C$7),"") | F20: =IFERROR(IF(E20=0,"",E20/E$7),"") | H20: =IFERROR(IF(G20=0,"",G20/G$7),"") | J20: =IFERROR(IF(I20=0,"",I20/I$7),"") | L20: =IFERROR(IF(K20=0,"",K20/K$7),"")
D21: =IFERROR(IF(C21=0,"",C21/C$7),"") | F21: =IFERROR(IF(E21=0,"",E21/E$7),"") | H21: =IFERROR(IF(G21=0,"",G21/G$7),"") | J21: =IFERROR(IF(I21=0,"",I21/I$7),"") | L21: =IFERROR(IF(K21=0,"",K21/K$7),"")
D22: =IFERROR(IF(C22=0,"",C22/C$7),"") | F22: =IFERROR(IF(E22=0,"",E22/E$7),"") | H22: =IFERROR(IF(G22=0,"",G22/G$7),"") | J22: =IFERROR(IF(I22=0,"",I22/I$7),"") | L22: =IFERROR(IF(K22=0,"",K22/K$7),"")
B23: 労務費 | C23: =SUM(C15:C22) -> 0 | D23: =IFERROR(IF(C23=0,"",C23/C$7),"") | E23: =SUM(E15:E22) -> 0 | F23: =IFERROR(IF(E23=0,"",E23/E$7),"") | G23: =SUM(G15:G22) -> 0 | H23: =IFERROR(IF(G23=0,"",G23/G$7),"") | I23: =SUM(I15:I22) -> 0 | J23: =IFERROR(IF(I23=0,"",I23/I$7),"") | K23: =SUM(K15:K22) -> 0 | L23: =IFERROR(IF(K23=0,"",K23/K$7),"")
D24: =IFERROR(IF(C24=0,"",C24/C$7),"") | F24: =IFERROR(IF(E24=0,"",E24/E$7),"") | H24: =IFERROR(IF(G24=0,"",G24/G$7),"") | J24: =IFERROR(IF(I24=0,"",I24/I$7),"") | L24: =IFERROR(IF(K24=0,"",K24/K$7),"")
D28: =IFERROR(IF(C28=0,"",C28/C$7),"") | F28: =IFERROR(IF(E28=0,"",E28/E$7),"") | H28: =IFERROR(IF(G28=0,"",G28/G$7),"") | J28: =IFERROR(IF(I28=0,"",I28/I$7),"") | L28: =IFERROR(IF(K28=0,"",K28/K$7),"")
D29: =IFERROR(IF(C29=0,"",C29/C$7),"") | F29: =IFERROR(IF(E29=0,"",E29/E$7),"") | H29: =IFERROR(IF(G29=0,"",G29/G$7),"") | J29: =IFERROR(IF(I29=0,"",I29/I$7),"") | L29: =IFERROR(IF(K29=0,"",K29/K$7),"")
D30: =IFERROR(IF(C30=0,"",C30/C$7),"") | F30: =IFERROR(IF(E30=0,"",E30/E$7),"") | H30: =IFERROR(IF(G30=0,"",G30/G$7),"") | J30: =IFERROR(IF(I30=0,"",I30/I$7),"") | L30: =IFERROR(IF(K30=0,"",K30/K$7),"")
D31: =IFERROR(IF(C31=0,"",C31/C$7),"") | F31: =IFERROR(IF(E31=0,"",E31/E$7),"") | H31: =IFERROR(IF(G31=0,"",G31/G$7),"") | J31: =IFERROR(IF(I31=0,"",I31/I$7),"") | L31: =IFERROR(IF(K31=0,"",K31/K$7),"")
D32: =IFERROR(IF(C32=0,"",C32/C$7),"") | F32: =IFERROR(IF(E32=0,"",E32/E$7),"") | H32: =IFERROR(IF(G32=0,"",G32/G$7),"") | J32: =IFERROR(IF(I32=0,"",I32/I$7),"") | L32: =IFERROR(IF(K32=0,"",K32/K$7),"")
B33: 外注加工費 | C33: =SUM(C24:C32) -> 0 | D33: =IFERROR(IF(C33=0,"",C33/C$7),"") | E33: =SUM(E24:E32) -> 0 | F33: =IFERROR(IF(E33=0,"",E33/E$7),"") | G33: =SUM(G24:G32) -> 0 | H33: =IFERROR(IF(G33=0,"",G33/G$7),"") | I33: =SUM(I24:I32) -> 0 | J33: =IFERROR(IF(I33=0,"",I33/I$7),"") | K33: =SUM(K24:K32) -> 0 | L33: =IFERROR(IF(K33=0,"",K33/K$7),"")
D34: =IFERROR(IF(C34=0,"",C34/C$7),"") | F34: =IFERROR(IF(E34=0,"",E34/E$7),"") | H34: =IFERROR(IF(G34=0,"",G34/G$7),"") | J34: =IFERROR(IF(I34=0,"",I34/I$7),"") | L34: =IFERROR(IF(K34=0,"",K34/K$7),"")
D35: =IFERROR(IF(C35=0,"",C35/C$7),"") | F35: =IFERROR(IF(E35=0,"",E35/E$7),"") | H35: =IFERROR(IF(G35=0,"",G35/G$7),"") | J35: =IFERROR(IF(I35=0,"",I35/I$7),"") | L35: =IFERROR(IF(K35=0,"",K35/K$7),"")
D36: =IFERROR(IF(C36=0,"",C36/C$7),"") | F36: =IFERROR(IF(E36=0,"",E36/E$7),"") | H36: =IFERROR(IF(G36=0,"",G36/G$7),"") | J36: =IFERROR(IF(I36=0,"",I36/I$7),"") | L36: =IFERROR(IF(K36=0,"",K36/K$7),"")
D39: =IFERROR(IF(C39=0,"",C39/C$7),"") | F39: =IFERROR(IF(E39=0,"",E39/E$7),"") | H39: =IFERROR(IF(G39=0,"",G39/G$7),"") | J39: =IFERROR(IF(I39=0,"",I39/I$7),"") | L39: =IFERROR(IF(K39=0,"",K39/K$7),"")
D40: =IFERROR(IF(C40=0,"",C40/C$7),"") | F40: =IFERROR(IF(E40=0,"",E40/E$7),"") | H40: =IFERROR(IF(G40=0,"",G40/G$7),"") | J40: =IFERROR(IF(I40=0,"",I40/I$7),"") | L40: =IFERROR(IF(K40=0,"",K40/K$7),"")
D41: =IFERROR(IF(C41=0,"",C41/C$7),"") | F41: =IFERROR(IF(E41=0,"",E41/E$7),"") | H41: =IFERROR(IF(G41=0,"",G41/G$7),"") | J41: =IFERROR(IF(I41=0,"",I41/I$7),"") | L41: =IFERROR(IF(K41=0,"",K41/K$7),"")
D42: =IFERROR(IF(C42=0,"",C42/C$7),"") | F42: =IFERROR(IF(E42=0,"",E42/E$7),"") | H42: =IFERROR(IF(G42=0,"",G42/G$7),"") | J42: =IFERROR(IF(I42=0,"",I42/I$7),"") | L42: =IFERROR(IF(K42=0,"",K42/K$7),"")
D43: =IFERROR(IF(C43=0,"",C43/C$7),"") | F43: =IFERROR(IF(E43=0,"",E43/E$7),"") | H43: =IFERROR(IF(G43=0,"",G43/G$7),"") | J43: =IFERROR(IF(I43=0,"",I43/I$7),"") | L43: =IFERROR(IF(K43=0,"",K43/K$7),"")
D44: =IFERROR(IF(C44=0,"",C44/C$7),"") | F44: =IFERROR(IF(E44=0,"",E44/E$7),"") | H44: =IFERROR(IF(G44=0,"",G44/G$7),"") | J44: =IFERROR(IF(I44=0,"",I44/I$7),"") | L44: =IFERROR(IF(K44=0,"",K44/K$7),"")
D45: =IFERROR(IF(C45=0,"",C45/C$7),"") | F45: =IFERROR(IF(E45=0,"",E45/E$7),"") | H45: =IFERROR(IF(G45=0,"",G45/G$7),"") | J45: =IFERROR(IF(I45=0,"",I45/I$7),"") | L45: =IFERROR(IF(K45=0,"",K45/K$7),"")
B46: 経費 | C46: =SUM(C34:C45) -> 0 | D46: =IFERROR(IF(C46=0,"",C46/C$7),"") | E46: =SUM(E34:E45) -> 0 | F46: =IFERROR(IF(E46=0,"",E46/E$7),"") | G46: =SUM(G34:G45) -> 0 | H46: =IFERROR(IF(G46=0,"",G46/G$7),"") | I46: =SUM(I34:I45) -> 0 | J46: =IFERROR(IF(I46=0,"",I46/I$7),"") | K46: =SUM(K34:K45) -> 0 | L46: =IFERROR(IF(K46=0,"",K46/K$7),"")
B47: 当期製造費用 | C47: =C14+C23+C33+C46 -> 0 | D47: =IFERROR(IF(C47=0,"",C47/C$7),"") | E47: =E14+E23+E33+E46 -> 0 | F47: =IFERROR(IF(E47=0,"",E47/E$7),"") | G47: =G14+G23+G33+G46 -> 0 | H47: =IFERROR(IF(G47=0,"",G47/G$7),"") | I47: =I14+I23+I33+I46 -> 0 | J47: =IFERROR(IF(I47=0,"",I47/I$7),"") | K47: =K14+K23+K33+K46 -> 0 | L47: =IFERROR(IF(K47=0,"",K47/K$7),"")
B48: 期首仕掛品棚卸高 | D48: =IFERROR(IF(C48=0,"",C48/C$7),"") | E48: =SUM(E36:E47) -> 0 | F48: =IFERROR(IF(E48=0,"",E48/E$7),"") | G48: =SUM(G36:G47) -> 0 | H48: =IFERROR(IF(G48=0,"",G48/G$7),"") | I48: =SUM(I36:I47) -> 0 | J48: =IFERROR(IF(I48=0,"",I48/I$7),"") | K48: =SUM(K36:K47) -> 0 | L48: =IFERROR(IF(K48=0,"",K48/K$7),"")
B49: 合計 | C49: =SUM(C47:C48) -> 0 | D49: =IFERROR(IF(C49=0,"",C49/C$7),"") | E49: =SUM(E47:E48) -> 0 | F49: =IFERROR(IF(E49=0,"",E49/E$7),"") | G49: =SUM(G47:G48) -> 0 | H49: =IFERROR(IF(G49=0,"",G49/G$7),"") | I49: =SUM(I47:I48) -> 0 | J49: =IFERROR(IF(I49=0,"",I49/I$7),"") | K49: =SUM(K47:K48) -> 0 | L49: =IFERROR(IF(K49=0,"",K49/K$7),"")
B50: 期末仕掛品棚卸高 | D50: =IFERROR(IF(C50=0,"",C50/C$7),"") | E50: =SUM(E40:E49) -> 0 | F50: =IFERROR(IF(E50=0,"",E50/E$7),"") | G50: =SUM(G40:G49) -> 0 | H50: =IFERROR(IF(G50=0,"",G50/G$7),"") | I50: =SUM(I40:I49) -> 0 | J50: =IFERROR(IF(I50=0,"",I50/I$7),"") | K50: =SUM(K40:K49) -> 0 | L50: =IFERROR(IF(K50=0,"",K50/K$7),"")
B51: 当期製造原価 | C51: =C49-C50 -> 0 | D51: =IFERROR(IF(C51=0,"",C51/C$7),"") | E51: =E49-E50 -> 0 | F51: =IFERROR(IF(E51=0,"",E51/E$7),"") | G51: =G49-G50 -> 0 | H51: =IFERROR(IF(G51=0,"",G51/G$7),"") | I51: =I49-I50 -> 0 | J51: =IFERROR(IF(I51=0,"",I51/I$7),"") | K51: =K49-K50 -> 0 | L51: =IFERROR(IF(K51=0,"",K51/K$7),"")

Sheet SGA
H2: (単位：千円)
B3: 科目 | C3: ='BS(借方)'!C4 -> － | E3: ='BS(借方)'!D4 -> 23年11月期 | G3: ='BS(借方)'!E4 -> 24年11月期 | I3: ='BS(借方)'!F4 -> 25年11月期 | K3: ='BS(借方)'!G4 -> 26年11月期 （7か月TB）
C4: 帳簿価額 | D4: 売上高比 | E4: 帳簿価額 | F4: 売上高比 | G4: 帳簿価額 | H4: 売上高比 | I4: 帳簿価額 | J4: 売上高比 | K4: 帳簿価額 | L4: 売上高比
B5: 売上 | C5: =PL!C11 -> 0 | D5: - | E5: =PL!E11 -> 474428321 | F5: - | G5: =PL!G11 -> 539035019 | H5: - | I5: =PL!I11 -> 558389734 | J5: - | K5: =PL!K11 -> 279153443 | L5: - | M5: ←IMに貼るときは非表示
B6: 従業員給与 | D6: =IFERROR(C6/$C$5,"") | E6: 112323477 | F6: =IFERROR(E6/$E$5,"") -> 0.23675542 | G6: 115961553 | H6: =IFERROR(G6/$G$5,"") -> 0.21512805 | I6: 127016990 | J6: =IFERROR(I6/$I$5,"") -> 0.22747014 | K6: 64179726 | L6: =IFERROR(K6/$K$5,"") -> 0.22990842
B7: 旅費交通費 | D7: =IFERROR(C7/$C$5,"") | E7: 3152359 | F7: =IFERROR(E7/$E$5,"") -> 0.0066445422 | G7: 4978151 | H7: =IFERROR(G7/$G$5,"") -> 0.0092353016 | I7: 5724652 | J7: =IFERROR(I7/$I$5,"") -> 0.010252072 | K7: 3504938 | L7: =IFERROR(K7/$K$5,"") -> 0.012555597
B8: 広告宣伝費 | D8: =IFERROR(C8/$C$5,"") | E8: 24335030 | F8: =IFERROR(E8/$E$5,"") -> 0.051293375 | G8: 34052424 | H8: =IFERROR(G8/$G$5,"") -> 0.063172935 | I8: 26650854 | J8: =IFERROR(I8/$I$5,"") -> 0.047728052 | K8: 15163208 | L8: =IFERROR(K8/$K$5,"") -> 0.054318542
B9: 発送配達費 | D9: =IFERROR(C9/$C$5,"") | E9: 352787 | F9: =IFERROR(E9/$E$5,"") -> 0.00074360443 | G9: 280605 | H9: =IFERROR(G9/$G$5,"") -> 0.00052056915 | I9: 436931 | J9: =IFERROR(I9/$I$5,"") -> 0.00078248394 | K9: 129150 | L9: =IFERROR(K9/$K$5,"") -> 0.00046264878
B10: ロイヤリティ | D10: =IFERROR(C10/$C$5,"") | E10: 45990311 | F10: =IFERROR(E10/$E$5,"") -> 0.096938376 | G10: 39848148 | H10: =IFERROR(G10/$G$5,"") -> 0.073924971 | I10: 29981679 | J10: =IFERROR(I10/$I$5,"") -> 0.053693106 | K10: 14193011 | L10: =IFERROR(K10/$K$5,"") -> 0.050843045
B11: 会議費 | D11: =IFERROR(C11/$C$5,"") | E11: 189625 | F11: =IFERROR(E11/$E$5,"") -> 0.00039969157 | G11: 484171 | H11: =IFERROR(G11/$G$5,"") -> 0.00089821808 | I11: 1489497 | J11: =IFERROR(I11/$I$5,"") -> 0.0026674864 | K11: 887177 | L11: =IFERROR(K11/$K$5,"") -> 0.003178098
B12: 役員報酬 | D12: =IFERROR(C12/$C$5,"") | E12: 9600000 | F12: =IFERROR(E12/$E$5,"") -> 0.02023488 | G12: 9600000 | H12: =IFERROR(G12/$G$5,"") -> 0.017809604 | I12: 14400000 | J12: =IFERROR(I12/$I$5,"") -> 0.02578844 | K12: 6300000 | L12: =IFERROR(K12/$K$5,"") -> 0.022568233
B13: 法定福利費 | D13: =IFERROR(C13/$C$5,"") | E13: 10104201 | F13: =IFERROR(E13/$E$5,"") -> 0.021297635 | G13: 22242217 | H13: =IFERROR(G13/$G$5,"") -> 0.041263028 | I13: 15295210 | J13: =IFERROR(I13/$I$5,"") -> 0.027391639 | K13: 2778916 | L13: =IFERROR(K13/$K$5,"") -> 0.0099547975
B14: 厚生費 | D14: =IFERROR(C14/$C$5,"") | E14: 2936211 | F14: =IFERROR(E14/$E$5,"") -> 0.0061889455 | G14: 3945609 | H14: =IFERROR(G14/$G$5,"") -> 0.0073197638 | I14: 3862961 | J14: =IFERROR(I14/$I$5,"") -> 0.0069180373 | K14: 1748144 | L14: =IFERROR(K14/$K$5,"") -> 0.006262305
B15: 減価償却費 | D15: =IFERROR(C15/$C$5,"") | E15: 3911003 | F15: =IFERROR(E15/$E$5,"") -> 0.008243612 | G15: 9294598 | H15: =IFERROR(G15/$G$5,"") -> 0.017243032 | I15: 6349173 | J15: =IFERROR(I15/$I$5,"") -> 0.011370505 | L15: =IFERROR(K15/$K$5,"") -> 0
B16: リース料 | D16: =IFERROR(C16/$C$5,"") | E16: 4294932 | F16: =IFERROR(E16/$E$5,"") -> 0.0090528575 | G16: 4554982 | H16: =IFERROR(G16/$G$5,"") -> 0.0084502525 | I16: 7249573 | J16: =IFERROR(I16/$I$5,"") -> 0.012982998 | K16: 4352502 | L16: =IFERROR(K16/$K$5,"") -> 0.01559179
B17: 地代家賃 | D17: =IFERROR(C17/$C$5,"") | E17: 8230492 | F17: =IFERROR(E17/$E$5,"") -> 0.017348231 | G17: 19460488 | H17: =IFERROR(G17/$G$5,"") -> 0.036102456 | I17: 33248832 | J17: =IFERROR(I17/$I$5,"") -> 0.059544132 | K17: 19879129 | L17: =IFERROR(K17/$K$5,"") -> 0.071212194
B18: 修繕費 | D18: =IFERROR(C18/$C$5,"") | E18: 468295 | F18: =IFERROR(E18/$E$5,"") -> 0.00098707219 | G18: 1088033 | H18: =IFERROR(G18/$G$5,"") -> 0.002018483 | I18: 275210 | J18: =IFERROR(I18/$I$5,"") -> 0.00049286365 | K18: 243111 | L18: =IFERROR(K18/$K$5,"") -> 0.00087088663
B19: 事務用消耗品費 | D19: =IFERROR(C19/$C$5,"") | E19: 9801863 | F19: =IFERROR(E19/$E$5,"") -> 0.020660367 | G19: 6407354 | H19: =IFERROR(G19/$G$5,"") -> 0.011886712 | I19: 4371794 | J19: =IFERROR(I19/$I$5,"") -> 0.0078292879 | K19: 1558723 | L19: =IFERROR(K19/$K$5,"") -> 0.0055837499
B20: 通信費 | D20: =IFERROR(C20/$C$5,"") | E20: 2455532 | F20: =IFERROR(E20/$E$5,"") -> 0.0051757703 | G20: 2672628 | H20: =IFERROR(G20/$G$5,"") -> 0.0049581714 | I20: 3045340 | J20: =IFERROR(I20/$I$5,"") -> 0.0054537894 | K20: 2149718 | L20: =IFERROR(K20/$K$5,"") -> 0.0077008472
B21: 水道光熱費 | D21: =IFERROR(C21/$C$5,"") | E21: 2958090 | F21: =IFERROR(E21/$E$5,"") -> 0.006235062 | G21: 3148822 | H21: =IFERROR(G21/$G$5,"") -> 0.0058415908 | I21: 3940893 | J21: =IFERROR(I21/$I$5,"") -> 0.0070576029 | K21: 1714053 | L21: =IFERROR(K21/$K$5,"") -> 0.0061401822
B22: 租税公課 | D22: =IFERROR(C22/$C$5,"") | E22: 8881475 | F22: =IFERROR(E22/$E$5,"") -> 0.018720373 | G22: 10506364 | H22: =IFERROR(G22/$G$5,"") -> 0.01949106 | I22: 20061210 | J22: =IFERROR(I22/$I$5,"") -> 0.035926896 | K22: 5281078 | L22: =IFERROR(K22/$K$5,"") -> 0.01891819
B23: 接待交際費 | D23: =IFERROR(C23/$C$5,"") | E23: 8453145 | F23: =IFERROR(E23/$E$5,"") -> 0.017817539 | G23: 10229520 | H23: =IFERROR(G23/$G$5,"") -> 0.018977468 | I23: 8217611 | J23: =IFERROR(I23/$I$5,"") -> 0.014716623 | K23: 4409532 | L23: =IFERROR(K23/$K$5,"") -> 0.015796087
B24: 保険料 | D24: =IFERROR(C24/$C$5,"") | E24: 2411203 | F24: =IFERROR(E24/$E$5,"") -> 0.0050823336 | G24: 4218242 | H24: =IFERROR(G24/$G$5,"") -> 0.0078255435 | I24: 3876512 | J24: =IFERROR(I24/$I$5,"") -> 0.0069423053 | K24: 1726252 | L24: =IFERROR(K24/$K$5,"") -> 0.0061838822
B25: 備品消耗品費 | D25: =IFERROR(C25/$C$5,"") | E25: 12485436 | F25: =IFERROR(E25/$E$5,"") -> 0.026316802 | G25: 14036551 | H25: =IFERROR(G25/$G$5,"") -> 0.026040147 | I25: 8462064 | J25: =IFERROR(I25/$I$5,"") -> 0.015154405 | K25: 4361180 | L25: =IFERROR(K25/$K$5,"") -> 0.015622877
B26: 管理諸費 | D26: =IFERROR(C26/$C$5,"") | E26: 5563800 | F26: =IFERROR(E26/$E$5,"") -> 0.011727377 | G26: 5027000 | H26: =IFERROR(G26/$G$5,"") -> 0.0093259247 | I26: 5797000 | J26: =IFERROR(I26/$I$5,"") -> 0.010381638 | K26: 3197700 | L26: =IFERROR(K26/$K$5,"") -> 0.01145499
B27: 支払手数料 | D27: =IFERROR(C27/$C$5,"") | E27: 7152851 | F27: =IFERROR(E27/$E$5,"") -> 0.015076779 | G27: 11861229 | H27: =IFERROR(G27/$G$5,"") -> 0.022004561 | I27: 14452516 | J27: =IFERROR(I27/$I$5,"") -> 0.025882489 | K27: 6927603 | L27: =IFERROR(K27/$K$5,"") -> 0.02481647
... B29: 車両費 | D29: =IFERROR(C29/$C$5,"") | E29: 626896 | F29: =IFERROR(E29/$E$5,"") -> 0.0013213714 | G29: 446867 | H29: =IFERROR(G29/$G$5,"") -> 0.00082901293 | I29: 512955 | J29: =IFERROR(I29/$I$5,"") -> 0.00091863258 | K29: 258439 | L29: =IFERROR(K29/$K$5,"") -> 0.0009257955
B30: 研修費 | D30: =IFERROR(C30/$C$5,"") | F30: =IFERROR(E30/$E$5,"") -> 0 | G30: 103345 | H30: =IFERROR(G30/$G$5,"") -> 0.00019172224 | I30: 173500 | J30: =IFERROR(I30/$I$5,"") -> 0.00031071488 | K30: 88900 | L30: =IFERROR(K30/$K$5,"") -> 0.00031846285
B31: 雑費 | D31: =IFERROR(C31/$C$5,"") | E31: 3334480 | F31: =IFERROR(E31/$E$5,"") -> 0.0070284168 | G31: 5436149 | H31: =IFERROR(G31/$G$5,"") -> 0.010084964 | I31: 4666766 | J31: =IFERROR(I31/$I$5,"") -> 0.0083575426 | K31: 2718158 | L31: =IFERROR(K31/$K$5,"") -> 0.0097371466
D32: =IFERROR(C32/$C$5,"") | F32: =IFERROR(E32/$E$5,"") -> 0 | H32: =IFERROR(G32/$G$5,"") -> 0 | J32: =IFERROR(I32/$I$5,"") -> 0 | L32: =IFERROR(K32/$K$5,"") -> 0
D33: =IFERROR(C33/$C$5,"") | F33: =IFERROR(E33/$E$5,"") -> 0 | H33: =IFERROR(G33/$G$5,"") -> 0 | J33: =IFERROR(I33/$I$5,"") -> 0 | L33: =IFERROR(K33/$K$5,"") -> 0
D34: =IFERROR(C34/$C$5,"") | F34: =IFERROR(E34/$E$5,"") -> 0 | H34: =IFERROR(G34/$G$5,"") -> 0 | J34: =IFERROR(I34/$I$5,"") -> 0 | L34: =IFERROR(K34/$K$5,"") -> 0
D35: =IFERROR(C35/$C$5,"") | F35: =IFERROR(E35/$E$5,"") -> 0 | H35: =IFERROR(G35/$G$5,"") -> 0 | J35: =IFERROR(I35/$I$5,"") -> 0 | L35: =IFERROR(K35/$K$5,"") -> 0
D36: =IFERROR(C36/$C$5,"") | F36: =IFERROR(E36/$E$5,"") -> 0 | H36: =IFERROR(G36/$G$5,"") -> 0 | J36: =IFERROR(I36/$I$5,"") -> 0 | L36: =IFERROR(K36/$K$5,"") -> 0
D37: =IFERROR(C37/$C$5,"") | F37: =IFERROR(E37/$E$5,"") -> 0 | H37: =IFERROR(G37/$G$5,"") -> 0 | J37: =IFERROR(I37/$I$5,"") -> 0 | L37: =IFERROR(K37/$K$5,"") -> 0
D38: =IFERROR(C38/$C$5,"") | F38: =IFERROR(E38/$E$5,"") -> 0 | H38: =IFERROR(G38/$G$5,"") -> 0 | J38: =IFERROR(I38/$I$5,"") -> 0 | L38: =IFERROR(K38/$K$5,"") -> 0
D39: =IFERROR(C39/$C$5,"") | F39: =IFERROR(E39/$E$5,"") -> 0 | H39: =IFERROR(G39/$G$5,"") -> 0 | J39: =IFERROR(I39/$I$5,"") -> 0 | L39: =IFERROR(K39/$K$5,"") -> 0
B40: 販売費および一般管理費合計 | C40: =SUM(C6:C39) -> 0 | D40: =IFERROR(C40/C5,"") | E40: =SUM(E6:E39) -> 290037494 | F40: =IFERROR(E40/E5,"") -> 0.61134102 | G40: =SUM(G6:G39) -> 339909050 | H40: =IFERROR(G40/G5,"") -> 0.63058807 | I40: =SUM(I6:I39) -> 349576223 | J40: =IFERROR(I40/I5,"") -> 0.62604343 | K40: =SUM(K6:K39) -> 167754348 | L40: =IFERROR(K40/K5,"") -> 0.60093956

Sheet VR→ 

Sheet 評価参考
B2: 参考｜進行期（2026年11月期）7か月実績を年換算した場合の試算
B3: ※不採算2店舗の撤退効果が通期で発現し、進行期7か月の水準が年間を通じて維持されることを前提とした仮説試算であり、評価結果ではない。
C4: (単位：千円)
B5: 進行期7か月 営業利益 | C5: =PLハイライト!G8 -> 6636849 | D5: 月次では減価償却費が未計上のため実質的にEBITDAベース
B6: 正常収益力調整（7か月相当） | C6: =PLハイライト!F17/12*7 -> 11598923 | D6: 第5期の調整項目合計19,884千円を7か月按分
B7: 進行期7か月 修正後EBITDA | C7: =C5+C6 -> 18235772
B8: 年換算 修正後EBITDA | C8: =C7/7*12 -> 31261323 | D8: 7か月実績を12か月へ単純年換算
B9: 減価償却費（通期実績） | C9: =-PLハイライト!F15 -> -6349173 | D9: 第5期の実績額を通期見込みとして控除
B10: 年換算 修正後営業利益 | C10: =C8+C9 -> 24912150
B12: 時価純資産（2026年6月末ベース） | C12: ='BS (貸方)'!G50-'BS(借方)'!G50-'BS(借方)'!G14 -> -55420760 | D12: 進行期末の純資産から営業権・仮払金を控除。棚卸資産の廃棄損は進行期に計上済のため追加の評価減はない
B13: 営業権（年買法・1倍） | C13: =C10*0.66*1 -> 16442019 | D13: 税考慮後営業利益×1倍
B14: 営業権（年買法・3倍） | C14: =C10*0.66*3 -> 49326058 | D14: 税考慮後営業利益×3倍
B15: 想定株式価値（年買法・下限） | C15: =C12+C13 -> -38978741 | D15: 時価純資産＋営業権1倍
B16: 想定株式価値（年買法・上限） | C16: =C12+C14 -> -6094702.2 | D16: 時価純資産＋営業権3倍

Sheet 株式価値 
A1: 作業不要（自動作成）
F2: (単位：千円)
C3: min | D3: 差（グラフ作成用） | E3: max
B4: インカム | C4: 0 | D4: 0 | E4: 0 | F4: 100 | I4: ｚ
B5: マーケット | C5: ='EV EBITDAマルチプル'!K7 -> -140949808 | D5: =E5-C5 -> 32383980 | E5: ='EV EBITDAマルチプル'!M7 -> -108565828 | F5: 0
B6: コスト | C6: =年買法!K6 -> -54971915 | D6: =E6-C6 -> 12469807 | E6: =年買法!M6 -> -42502108 | F6: 0

Sheet 修正BS(借方)
E2: (単位：千円)
B3: 資産の部 | G3: 評価差額の根拠
B4: 科目 | C4: ='BS(借方)'!F4 -> 25年11月期 | D4: 修正額 | E4: 修正後
B5: 【流動資産】 | C5: =SUM(C6:C19) -> 150113194 | D5: =SUM(D6:D19) -> -45650000 | E5: =C5+D5 -> 104463194
B6: ='BS(借方)'!B6 -> 現金及び預金 | C6: ='BS(借方)'!F6 -> 10140492 | E6: =C6+D6 -> 10140492
B7: ='BS(借方)'!B7 -> 売掛金 | C7: ='BS(借方)'!F7 -> 27628072 | E7: =C7+D7 -> 27628072
B8: ='BS(借方)'!B8 -> 商品 | C8: ='BS(借方)'!F8 -> 106017284 | D8: -44000000 | E8: =C8+D8 -> 62017284 | G8: 2026年3月に本社分32,000千円・バックヤード分12,000千円を全額廃棄。基準日時点で既に滞留・陳腐化していたと判断し評価減
B9: ='BS(借方)'!B9 -> 貯蔵品 | C9: ='BS(借方)'!F9 -> 150000 | E9: =C9+D9 -> 150000
B10: ='BS(借方)'!B10 -> 前渡金 | C10: ='BS(借方)'!F10 -> 0 | E10: =C10+D10 -> 0
B11: ='BS(借方)'!B11 -> 前払費用 | C11: ='BS(借方)'!F11 -> 3991637 | E11: =C11+D11 -> 3991637
B12: ='BS(借方)'!B12 -> 未収入金 | C12: ='BS(借方)'!F12 -> 30800 | E12: =C12+D12 -> 30800
B13: ='BS(借方)'!B13 -> 未収還付法人税等 | C13: ='BS(借方)'!F13 -> 504909 | E13: =C13+D13 -> 504909
B14: ='BS(借方)'!B14 -> 仮払金 | C14: ='BS(借方)'!F14 -> 1650000 | D14: -1650000 | E14: =C14+D14 -> 0 | G14: 回収を前提とした支出ではなく資産性が認められないため全額評価減
B15: ='BS(借方)'!B15 -> 立替金 | C15: ='BS(借方)'!F15 -> 0 | E15: =C15+D15 -> 0
B16: ='BS(借方)'!B16 -> 0 | C16: ='BS(借方)'!F16 -> 0 | E16: =C16+D16 -> 0
B17: ='BS(借方)'!B17 -> 0 | C17: ='BS(借方)'!F17 -> 0 | E17: =C17+D17 -> 0
B18: ='BS(借方)'!B18 -> 0 | C18: ='BS(借方)'!F18 -> 0 | E18: =C18+D18 -> 0
E19: =C19+D19 -> 0
B20: 【固定資産】 | C20: =C21+C35+C46 -> 85271983 | D20: =D21+D35+D46 -> -1500004 | E20: =C20+D20 -> 83771979
B21: ［有形固定資産］ | C21: =SUM(C22:C34) -> 54658019 | D21: =SUM(D22:D34) -> 0 | E21: =C21+D21 -> 54658019
B22: ='BS(借方)'!B22 -> 建物 | C22: ='BS(借方)'!F22 -> 44397084 | E22: =C22+D22 -> 44397084
B23: ='BS(借方)'!B23 -> 建物付属設備 | C23: ='BS(借方)'!F23 -> 0 | E23: =C23+D23 -> 0
B24: ='BS(借方)'!B24 -> 構築物 | C24: ='BS(借方)'!F24 -> 0 | E24: =C24+D24 -> 0
B25: ='BS(借方)'!B25 -> 車両運搬具 | C25: ='BS(借方)'!F25 -> 1057574 | E25: =C25+D25 -> 1057574
B26: ='BS(借方)'!B26 -> 工具器具及び備品 | C26: ='BS(借方)'!F26 -> 6044761 | E26: =C26+D26 -> 6044761
B27: ='BS(借方)'!B27 -> 土地 | C27: ='BS(借方)'!F27 -> 2974400 | E27: =C27+D27 -> 2974400
B28: ='BS(借方)'!B28 -> その他の有形固定資産 | C28: ='BS(借方)'!F28 -> 184200 | E28: =C28+D28 -> 184200
B29: ='BS(借方)'!B29 -> 0 | C29: ='BS(借方)'!F29 -> 0 | E29: =C29+D29 -> 0
B30: ='BS(借方)'!B30 -> 0 | C30: ='BS(借方)'!F30 -> 0 | E30: =C30+D30 -> 0
B31: ='BS(借方)'!B31 -> 0 | C31: ='BS(借方)'!F31 -> 0 | E31: =C31+D31 -> 0
B32: ='BS(借方)'!B32 -> 0 | C32: ='BS(借方)'!F32 -> 0 | E32: =C32+D32 -> 0
B33: ='BS(借方)'!B33 -> 0 | C33: ='BS(借方)'!F33 -> 0 | E33: =C33+D33 -> 0
E34: =C34+D34 -> 0
B35: ［無形固定資産］ | C35: =SUM(C36:C45) -> 0 | D35: =SUM(D36:D45) -> 0 | E35: =C35+D35 -> 0
B36: ='BS(借方)'!B36 -> 0 | C36: ='BS(借方)'!F36 -> 0 | E36: =C36+D36 -> 0
B37: ='BS(借方)'!B37 -> 0 | C37: ='BS(借方)'!F37 -> 0 | E37: =C37+D37 -> 0
B38: ='BS(借方)'!B38 -> 0 | C38: ='BS(借方)'!F38 -> 0 | E38: =C38+D38 -> 0
B39: ='BS(借方)'!B39 -> 0 | C39: ='BS(借方)'!F39 -> 0 | E39: =C39+D39 -> 0
B40: ='BS(借方)'!B40 -> 0 | C40: ='BS(借方)'!F40 -> 0 | E40: =C40+D40 -> 0
E41: =C41+D41 -> 0
E42: =C42+D42 -> 0
E43: =C43+D43 -> 0
E44: =C44+D44 -> 0
E45: =C45+D45 -> 0
B46: ［投資その他資産］ | C46: =SUM(C47:C54) -> 30613964 | D46: =SUM(D47:D54) -> -1500004 | E46: =C46+D46 -> 29113960
B47: ='BS(借方)'!B47 -> リサイクル預託金 | C47: ='BS(借方)'!F47 -> 31500 | E47: =C47+D47 -> 31500
B48: ='BS(借方)'!B48 -> 長期前払費用 | C48: ='BS(借方)'!F48 -> 1711860 | E48: =C48+D48 -> 1711860
B49: ='BS(借方)'!B49 -> 差入保証金 | C49: ='BS(借方)'!F49 -> 27370600 | E49: =C49+D49 -> 27370600
B50: ='BS(借方)'!B50 -> 営業権 | C50: ='BS(借方)'!F50 -> 1500004 | D50: -1500004 | E50: =C50+D50 -> 0 | G50: 年買法で営業権を別途算定するため、B/S計上分を残すと二重計上となる。換金価値も認められないため全額評価減
B51: ='BS(借方)'!B51 -> 0 | C51: ='BS(借方)'!F51 -> 0 | E51: =C51+D51 -> 0
B52: ='BS(借方)'!B52 -> 0 | C52: ='BS(借方)'!F52 -> 0 | E52: =C52+D52 -> 0
B53: ='BS(借方)'!B53 -> 0 | C53: ='BS(借方)'!F53 -> 0 | E53: =C53+D53 -> 0
B54: ='BS(借方)'!B54 -> 0 | C54: ='BS(借方)'!F54 -> 0 | E54: =C54+D54 -> 0
E55: =C55+D55 -> 0
B56: 【繰延資産】 | C56: =SUM(C57:C59) -> 0 | D56: =SUM(D57:D59) -> 0 | E56: =C56+D56 -> 0
B57: ='BS(借方)'!B57 -> 0 | C57: ='BS(借方)'!F57 -> 0 | E57: =C57+D57 -> 0
E58: =C58+D58 -> 0
E59: =C59+D59 -> 0
B60: 【繰延税金資産】 | C60: 0 | D60: 0 | E60: =C60+D60 -> 0
B61: 資産合計 | C61: =C5+C20+C56+C60 -> 235385177 | D61: =D5+D20+D56+D60 -> -47150004 | E61: =C61+D61 -> 188235173
B63: ※評価基準日は2025年11月30日（第5期末）。※繰延税金資産は、繰越欠損金を有し課税所得の見込みが立たないため回収可能性を認めず、評価差額に対する税効果は認識していない。

Sheet 売掛・棚卸
E2: (単位：千円)
A3: 売掛金 | B3: 相手先 | C3: 帳簿価額 | D3: 評価差額 | E3: 評価額 | F3: 調整事由
B4: 該当なし | F4: 2025年11月期末の売掛金27,628千円の内訳は㈲ワンラブ（FC本部）17,373千円、カード・PayPay等の決済会社10,255千円。いずれも翌月回収であり滞留債権は認められないため簿価評価とした。
E12: (単位：千円)
A13: 商品在庫 | B13: 相手先 | C13: 帳簿価額 | D13: 評価差額 | E13: 評価額 | F13: 調整事由
B14: 本社（バックヤード含む） | C14: 44000000 | D14: -44000000 | E14: 0 | F14: 2026年3月に本社分32,000千円・バックヤード分12,000千円を全額廃棄。基準日時点で既に滞留・陳腐化していたと判断し全額評価減
B15: 外部保管在庫 | C15: 10000000 | E15: 10000000 | F15: 実在性が未確認のため簿価評価（要確認）。実在しない場合は追加で10,000千円の評価減となる
B16: 店舗在庫（稼働6店舗＋撤退2店舗） | C16: 52017284 | E16: 52017284 | F16: 棚卸表により拠点別残高を確認。滞留・陳腐化は認められないため簿価評価
B17: 合計 | C17: =SUM(C14:C16) -> 106017284 | D17: =SUM(D14:D16) -> -44000000 | E17: =SUM(E14:E16) -> 62017284

Sheet 減価償却
E2: (単位：千円)
B3: 資産 | C3: 帳簿価額 | D3: 評価差額 | E3: 評価額 | F3: 調整事由
B4: 該当なし：減価償却内訳明細書により第5期は適正償却を確認しており、償却不足は認められない。

Sheet 土地
F2: (単位：千円)
B3: 内容・所在地 | C3: 地積(㎡) | D3: 帳簿価額 | E3: 評価差額 | F3: 時価評価額 | G3: 調整事由
B4: 駐車場用地／岐阜県大垣市南若森町字柳原227番3 | C4: 89.4 | D4: 2974400 | F4: 2974400 | G4: 路線価図・固定資産税評価証明が未受領のため簿価評価（要確認）。簿価は33千円/㎡であり大幅な含み損益は生じにくいと推察
B8: 合計 | C8: =C4 -> 89.4 | D8: =D4 -> 2974400 | E8: =SUM(E4:E7) -> 0 | F8: =F4 -> 2974400

Sheet 保険
E2: (単位：千円)
B3: 保険商品 | C3: 帳簿価額 | D3: 評価差額 | E3: 評価額 | F3: 調整事由
B4: 該当なし：保険積立金の計上はない（2025年11月期末残高ゼロ）。

Sheet 有価証券
F2: (単位：千円)
B3: 銘柄 | C3: 数量 | D3: 帳簿価額 | E3: 評価差額 | F3: 評価額 | G3: 調整事由
B4: 該当なし：有価証券・投資有価証券の保有はない（2025年11月期末残高ゼロ）。

Sheet 修正BS(貸方) 
E2: (単位：千円)
B3: 負債の部 | G3: 評価差額の根拠
B4: 科目 | C4: ='修正BS(借方)'!C4 -> 25年11月期 | D4: 修正額 | E4: 修正後
B5: 【流動負債】 | C5: =SUM(C6:C17) -> 47672202 | D5: =SUM(D6:D17) -> 0 | E5: =C5+D5 -> 47672202
B6: ='BS (貸方)'!B6 -> 買掛金 | C6: ='BS (貸方)'!F6 -> 9202412 | E6: =C6+D6 -> 9202412
B7: ='BS (貸方)'!B7 -> 短期借入金 | C7: ='BS (貸方)'!F7 -> 0 | E7: =C7+D7 -> 0
B8: ='BS (貸方)'!B8 -> 未払金 | C8: ='BS (貸方)'!F8 -> 714227 | E8: =C8+D8 -> 714227
B9: ='BS (貸方)'!B9 -> 未払費用 | C9: ='BS (貸方)'!F9 -> 20113617 | E9: =C9+D9 -> 20113617 | G9: 給与の締日から基準日までの経過分が含まれているか要確認。未計上であれば約10,000千円の追加計上余地（賃金台帳では当月締・翌月25日払）
B10: ='BS (貸方)'!B10 -> 未払法人税等 | C10: ='BS (貸方)'!F10 -> 242500 | E10: =C10+D10 -> 242500
B11: ='BS (貸方)'!B11 -> 未払消費税等 | C11: ='BS (貸方)'!F11 -> 11784100 | E11: =C11+D11 -> 11784100
B12: ='BS (貸方)'!B12 -> 預り金 | C12: ='BS (貸方)'!F12 -> 2391530 | E12: =C12+D12 -> 2391530
B13: ='BS (貸方)'!B13 -> カード未払金 | C13: ='BS (貸方)'!F13 -> 3223816 | E13: =C13+D13 -> 3223816
B14: ='BS (貸方)'!B14 -> 0 | C14: ='BS (貸方)'!F14 -> 0 | E14: =C14+D14 -> 0
B15: ='BS (貸方)'!B15 -> 0 | C15: ='BS (貸方)'!F15 -> 0 | E15: =C15+D15 -> 0
B16: ='BS (貸方)'!B16 -> 0 | C16: ='BS (貸方)'!F16 -> 0 | E16: =C16+D16 -> 0
E17: =C17+D17 -> 0
B18: 【固定負債】 | C18: =SUM(C19:C26) -> 201769790 | D18: =SUM(D19:D26) -> 0 | E18: =C18+D18 -> 201769790
B19: ='BS (貸方)'!B19 -> 長期借入金 | C19: ='BS (貸方)'!F19 -> 191858000 | E19: =C19+D19 -> 191858000 | G19: 9本すべて代表者の連帯保証付き。民間6本は信用保証協会の保証付き
B20: ='BS (貸方)'!B20 -> 役員借入金 | C20: ='BS (貸方)'!F20 -> 7565770 | E20: =C20+D20 -> 7565770 | G20: 譲渡時に返済を希望。ネットキャッシュ算定ではデットライクアイテムとして控除
B21: ='BS (貸方)'!B21 -> 長期未払金 | C21: ='BS (貸方)'!F21 -> 2346020 | E21: =C21+D21 -> 2346020
B22: ='BS (貸方)'!B22 -> 0 | C22: ='BS (貸方)'!F22 -> 0 | E22: =C22+D22 -> 0
B23: ='BS (貸方)'!B23 -> 0 | C23: ='BS (貸方)'!F23 -> 0 | E23: =C23+D23 -> 0
E24: =C24+D24 -> 0
E25: =C25+D25 -> 0
E26: =C26+D26 -> 0
B27: 【繰延税金負債】 | C27: 0 | D27: 0 | E27: =C27+D27 -> 0
B28: 負債合計 | C28: =C5+C18+C27 -> 249441992 | D28: =D5+D18+D27 -> 0 | E28: =C28+D28 -> 249441992
B34: 純資産の部
B35: 【資本金】 | C35: =SUM(C36:C38) -> 1000000 | D35: =SUM(D36:D38) -> 0 | E35: =C35+D35 -> 1000000
B36: ='BS (貸方)'!B36 -> 資本金 | C36: ='BS (貸方)'!F36 -> 1000000 | E36: =C36+D36 -> 1000000
E37: =C37+D37 -> 0
E38: =C38+D38 -> 0
B39: 【資本剰余金】 | C39: =SUM(C40:C42) -> 0 | D39: =SUM(D40:D42) -> 0 | E39: =C39+D39 -> 0
E40: =C40+D40 -> 0
E41: =C41+D41 -> 0
E42: =C42+D42 -> 0
B43: 【利益剰余金】 | C43: =SUM(C44:C47) -> -15056815 | D43: =SUM(D44:D47) -> 0 | E43: =C43+D43 -> -15056815
B44: ='BS (貸方)'!B44 -> 繰越利益剰余金 | C44: ='BS (貸方)'!F44 -> -15056815 | E44: =C44+D44 -> -15056815
B45: ='BS (貸方)'!B45 -> 0 | C45: ='BS (貸方)'!F45 -> 0 | E45: =C45+D45 -> 0
B46: ='BS (貸方)'!B46 -> 0 | C46: ='BS (貸方)'!F46 -> 0 | E46: =C46+D46 -> 0
E47: =C47+D47 -> 0
B48: 【自己株式】 | C48: 0 | D48: 0 | E48: =C48+D48 -> 0
B49: 【評価修正額】 | D49: =SUM(D50:D51) -> -47150004 | E49: =C49+D49 -> -47150004
B50: 修正額 | D50: ='修正BS(借方)'!D61-D28 -> -47150004 | E50: =C50+D50 -> -47150004
B51: 修正税効果 | D51: ='修正BS(借方)'!D60-D27 -> 0 | E51: =C51+D51 -> 0
B52: 純資産合計 | C52: =C35+C39+C43+C48 -> -14056815 | D52: =D35+D39+D43+D48+D49 -> -47150004 | E52: =C52+D52 -> -61206819
B53: 負債・純資産合計 | C53: =C28+C52 -> 235385177 | D53: =D28+D52 -> -47150004 | E53: =C53+D53 -> 188235173
B55: ※賞与引当金・退職給付引当金・役員退職慰労引当金・資産除去債務は、規程および撤退店舗の原状回復見積が未受領のため計上していない（追加調整の可能性あり）。 | C55: =C53='修正BS(借方)'!C61 -> 1

Sheet 未払人件費・賞与
D2: (単位：千円) | E2: (単位：千円) | F2: (単位：千円)
B3: 支払給与 | C3: 未払日数 | D3: 未払給与引当額 | E3: 概算社会保険料 | F3: 未払給与引当額
B4: 未評価：賃金台帳では当月締・翌月25日払であり、11月分給与が未払費用20,114千円に含まれているか要確認。未計上であれば社会保険料概算15%を含め約10,000千円超の追加計上が必要。賞与制度の有無も未確認のため引当計上していない。
B8: 支払予定賞与

Sheet 退職金
J2: (単位：千円)
B3: № | C3: 氏名 | D3: 勤続年数(年) | E3: 基本給 | F3: 支給倍率 | G3: 退職理由率 | H3: 要支給額 | I3: 中退共積立額 | J3: 引当不足
C4: 未評価：従業員退職金規程・役員退職慰労金規程がいずれも未受領のため、要支給額を算定できず引当計上していない（要確認）。

Sheet 税効果
E2: (単位：千円)
B3: 修正科目 | C3: 適用判定 | D3: 修正額 | E3: 繰延税金資産/負債 | F3: 備考
B4: 棚卸資産 | C4: × | D4: -44000000 | E4: － | F4: 繰越欠損金を有し課税所得の見込みが立たないため回収可能性を認めず、繰延税金資産を計上しない
B5: 営業権 | C5: × | D5: -1500004 | E5: － | F5: 同上。またB/S計上の営業権は年買法での二重計上を避けるための評価減であり税務上の影響はない
B6: 仮払金 | C6: × | D6: -1650000 | E6: － | F6: 同上
B9: ※実効税率34%。評価差額合計△47,150千円に対する繰延税金資産16,031千円は、回収可能性が認められないため認識していない（保守的な取扱い）。課税所得の見通しが立つ場合は同額だけ時価純資産が上振れする。

Sheet ネットキャッシュ
F2: (単位：千円)
B3: キャッシュライクアイテム | C3: 金額 | E3: デットライクアイテム | F3: 金額
B4: 現金及び預金 | C4: ='BS(借方)'!F6 -> 10140492 | E4: 短期借入金
B5: 役員貸付金 | E5: 長期借入金 | F5: ='BS (貸方)'!F19 -> 191858000
B6: 従業員貸付金 | E6: 社債
B7: 立替金 | E7: 役員借入金 | F7: ='BS (貸方)'!F20 -> 7565770
B8: 保険積立金 | E8: 未払法人税 | F8: ='BS (貸方)'!F10 -> 242500
B9: 投資有価証券 | E9: 資産除去債務
B10: 売却予定不動産 | E10: 役員退職慰労金
B11: 売却予定車両 | E11: 営業循環外前受金
E12: ファイナンスリース債務
B13: 合計 | C13: =SUM(C4:C12) -> 10140492 | E13: 合計 | F13: =SUM(F4:F12) -> 199666270
B15: ※基準日（2025年11月30日）の残高。保険積立金・投資有価証券・役員貸付金の残高はない。※長期未払金2,346千円は分割払いの未払金であり有利子負債ではないためデットライクに含めていない（要確認）。 | C15: =C13-F13 -> -189525778 | E15: ネットデット | F15: =F13-I13 -> 199666270
C17: ↑どっちか消す | F17: ↑どっちか消す

Sheet 修正PL
K2: (単位：千円)
B3: 科目 | C3: ='BS(借方)'!C4 -> － | F3: ='BS(借方)'!D4 -> 23年11月期 | I3: ='BS(借方)'!E4 -> 24年11月期 | L3: ='BS(借方)'!F4 -> 25年11月期 | O3: ='BS(借方)'!G4 -> 26年11月期 （7か月TB） | S3: 調整事由
C4: 帳簿価額 | D4: 修正額 | E4: 修正後 | F4: 帳簿価額 | G4: 修正額 | H4: 修正後 | I4: 帳簿価額 | J4: 修正額 | K4: 修正後 | L4: 帳簿価額 | M4: 修正額 | N4: 修正後 | O4: 帳簿価額 | P4: 修正額 | Q4: 修正後
B5: =PL!B5 -> 生体売上高 | C5: =PL!C5 -> 0 | E5: =C5+D5 -> 0 | F5: =PL!E5 -> 293213620 | H5: =F5+G5 -> 293213620 | I5: =PL!G5 -> 333089628 | K5: =I5+J5 -> 333089628 | L5: =PL!I5 -> 338295378 | N5: =L5+M5 -> 338295378 | O5: =PL!K5 -> 165116994 | Q5: =O5+P5 -> 165116994
B6: =PL!B6 -> サービス売上高 | C6: =PL!C6 -> 0 | E6: =C6+D6 -> 0 | F6: =PL!E6 -> 65655525 | H6: =F6+G6 -> 65655525 | I6: =PL!G6 -> 60897406 | K6: =I6+J6 -> 60897406 | L6: =PL!I6 -> 52699187 | N6: =L6+M6 -> 52699187 | O6: =PL!K6 -> 32791687 | Q6: =O6+P6 -> 32791687
B7: =PL!B7 -> 物販売上高 | C7: =PL!C7 -> 0 | E7: =C7+D7 -> 0 | F7: =PL!E7 -> 115559176 | H7: =F7+G7 -> 115559176 | I7: =PL!G7 -> 145047985 | K7: =I7+J7 -> 145047985 | L7: =PL!I7 -> 167395169 | N7: =L7+M7 -> 167395169 | O7: =PL!K7 -> 81244762 | Q7: =O7+P7 -> 81244762
B8: =PL!B8 -> 0 | C8: =PL!C8 -> 0 | E8: =C8+D8 -> 0 | F8: =PL!E8 -> 0 | H8: =F8+G8 -> 0 | I8: =PL!G8 -> 0 | K8: =I8+J8 -> 0 | L8: =PL!I8 -> 0 | N8: =L8+M8 -> 0 | O8: =PL!K8 -> 0 | Q8: =O8+P8 -> 0
B9: =PL!B9 -> 0 | C9: =PL!C9 -> 0 | E9: =C9+D9 -> 0 | F9: =PL!E9 -> 0 | H9: =F9+G9 -> 0 | I9: =PL!G9 -> 0 | K9: =I9+J9 -> 0 | L9: =PL!I9 -> 0 | N9: =L9+M9 -> 0 | O9: =PL!K9 -> 0 | Q9: =O9+P9 -> 0
E10: =C10+D10 -> 0 | H10: =F10+G10 -> 0 | K10: =I10+J10 -> 0 | N10: =L10+M10 -> 0 | Q10: =O10+P10 -> 0
B11: 売上高 | C11: =SUM(C5:C10) -> 0 | D11: =SUM(D5:D10) -> 0 | E11: =C11+D11 -> 0 | F11: =SUM(F5:F10) -> 474428321 | G11: =SUM(G5:G10) -> 0 | H11: =F11+G11 -> 474428321 | I11: =SUM(I5:I10) -> 539035019 | J11: =SUM(J5:J10) -> 0 | K11: =I11+J11 -> 539035019 | L11: =SUM(L5:L10) -> 558389734 | M11: =SUM(M5:M10) -> 0 | N11: =L11+M11 -> 558389734 | O11: =SUM(O5:O10) -> 279153443 | P11: =SUM(P5:P10) -> 0 | Q11: =O11+P11 -> 279153443
B12: =PL!B12 -> 期首棚卸高 | C12: =PL!C12 -> 0 | E12: =C12+D12 -> 0 | F12: =PL!E12 -> 39485899 | H12: =F12+G12 -> 39485899 | I12: =PL!G12 -> 70917819 | K12: =I12+J12 -> 70917819 | L12: =PL!I12 -> 127080914 | N12: =L12+M12 -> 127080914 | O12: =PL!K12 -> 106017284 | Q12: =O12+P12 -> 106017284
B13: =PL!B13 -> 商品仕入高 | C13: =PL!C13 -> 0 | E13: =C13+D13 -> 0 | F13: =PL!E13 -> 183853875 | H13: =F13+G13 -> 183853875 | I13: =PL!G13 -> 220800993 | K13: =I13+J13 -> 220800993 | L13: =PL!I13 -> 182243467 | N13: =L13+M13 -> 182243467 | O13: =PL!K13 -> 92273907 | Q13: =O13+P13 -> 92273907
B14: =PL!B14 -> 外注費 | C14: =PL!C14 -> 0 | E14: =C14+D14 -> 0 | F14: =PL!E14 -> 29627732 | H14: =F14+G14 -> 29627732 | I14: =PL!G14 -> 31465971 | K14: =I14+J14 -> 31465971 | L14: =PL!I14 -> 25058151 | N14: =L14+M14 -> 25058151 | O14: =PL!K14 -> 8916840 | Q14: =O14+P14 -> 8916840
B15: =PL!B15 -> 他勘定振替高 | C15: =PL!C15 -> 0 | E15: =C15+D15 -> 0 | F15: =PL!E15 -> 0 | H15: =F15+G15 -> 0 | I15: =PL!G15 -> 0 | K15: =I15+J15 -> 0 | L15: =PL!I15 -> 0 | N15: =L15+M15 -> 0 | O15: =PL!K15 -> -44000000 | Q15: =O15+P15 -> -44000000
B16: =PL!B16 -> 期末棚卸高 | C16: =PL!C16 -> 0 | E16: =C16+D16 -> 0 | F16: =PL!E16 -> -70917819 | H16: =F16+G16 -> -70917819 | I16: =PL!G16 -> -127080914 | K16: =I16+J16 -> -127080914 | L16: =PL!I16 -> -106017284 | N16: =L16+M16 -> -106017284 | O16: =PL!K16 -> -58445785 | Q16: =O16+P16 -> -58445785
B17: 売上原価 | C17: =SUM(C12:C16) -> 0 | D17: =SUM(D12:D16) -> 0 | E17: =C17+D17 -> 0 | F17: =SUM(F12:F16) -> 182049687 | G17: =SUM(G12:G16) -> 0 | H17: =F17+G17 -> 182049687 | I17: =SUM(I12:I16) -> 196103869 | J17: =SUM(J12:J16) -> 0 | K17: =I17+J17 -> 196103869 | L17: =SUM(L12:L16) -> 228365248 | M17: =SUM(M12:M16) -> 0 | N17: =L17+M17 -> 228365248 | O17: =SUM(O12:O16) -> 104762246 | P17: =SUM(P12:P16) -> 0 | Q17: =O17+P17 -> 104762246
B18: 売上総利益 | C18: =C11-C17 -> 0 | D18: =D11-D17 -> 0 | E18: =C18+D18 -> 0 | F18: =F11-F17 -> 292378634 | G18: =G11-G17 -> 0 | H18: =F18+G18 -> 292378634 | I18: =I11-I17 -> 342931150 | J18: =J11-J17 -> 0 | K18: =I18+J18 -> 342931150 | L18: =L11-L17 -> 330024486 | M18: =M11-M17 -> 0 | N18: =L18+M18 -> 330024486 | O18: =O11-O17 -> 174391197 | P18: =P11-P17 -> 0 | Q18: =O18+P18 -> 174391197
B19: 販売費及び一般管理費 | C19: =修正SGA!C39 -> 0 | E19: =C19+D19 -> 0 | F19: =修正SGA!F39 -> 290037494 | G19: =修正SGA!G39 -> -7535000 | H19: =F19+G19 -> 282502494 | I19: =修正SGA!I39 -> 339909050 | J19: =修正SGA!J39 -> -19814000 | K19: =I19+J19 -> 320095050 | L19: =修正SGA!L39 -> 349576223 | M19: =修正SGA!M39 -> -19229000 | N19: =L19+M19 -> 330347223 | O19: =修正SGA!O39 -> 167754348 | Q19: =O19+P19 -> 167754348
B20: 営業利益 | C20: =C18- C19 -> 0 | D20: =D18- D19 -> 0 | E20: =C20+D20 -> 0 | F20: =F18- F19 -> 2341140 | G20: =G18- G19 -> 7535000 | H20: =F20+G20 -> 9876140 | I20: =I18- I19 -> 3022100 | J20: =J18- J19 -> 19814000 | K20: =I20+J20 -> 22836100 | L20: =L18- L19 -> -19551737 | M20: =M18- M19 -> 19229000 | N20: =L20+M20 -> -322737 | O20: =O18- O19 -> 6636849 | P20: =P18- P19 -> 0 | Q20: =O20+P20 -> 6636849
B21: 営業外収益 | C21: =SUM(C22:C28) -> 0 | D21: =SUM(D22:D28) -> 0 | E21: =C21+D21 -> 0 | F21: =SUM(F22:F28) -> 1321452 | G21: =SUM(G22:G28) -> 1321000 | H21: =F21+G21 -> 2642452 | I21: =SUM(I22:I28) -> 2383452 | J21: =SUM(J22:J28) -> 635000 | K21: =I21+J21 -> 3018452 | L21: =SUM(L22:L28) -> 3631958 | M21: =SUM(M22:M28) -> 654868 | N21: =L21+M21 -> 4286826 | O21: =SUM(O22:O28) -> 1059276 | P21: =SUM(P22:P28) -> 0 | Q21: =O21+P21 -> 1059276
B22: =PL!B22 -> 受取利息 | C22: =PL!C22 -> 0 | E22: =C22+D22 -> 0 | F22: =PL!E22 -> 193 | H22: =F22+G22 -> 193 | I22: =PL!G22 -> 4702 | K22: =I22+J22 -> 4702 | L22: =PL!I22 -> 24608 | N22: =L22+M22 -> 24608 | O22: =PL!K22 -> 6446 | Q22: =O22+P22 -> 6446
B23: =PL!B23 -> 受取配当金 | C23: =PL!C23 -> 0 | E23: =C23+D23 -> 0 | F23: =PL!E23 -> 188 | H23: =F23+G23 -> 188 | I23: =PL!G23 -> 376 | K23: =I23+J23 -> 376 | L23: =PL!I23 -> 282 | N23: =L23+M23 -> 282 | O23: =PL!K23 -> 300 | Q23: =O23+P23 -> 300
B24: =PL!B24 -> 雑収入 | C24: =PL!C24 -> 0 | E24: =C24+D24 -> 0 | F24: =PL!E24 -> 1321071 | G24: 1321000 | H24: =F24+G24 -> 2642071 | I24: =PL!G24 -> 2378374 | J24: 635000 | K24: =I24+J24 -> 3013374 | L24: =PL!I24 -> 3607068 | M24: 654868 | N24: =L24+M24 -> 4261936 | O24: =PL!K24 -> 1052530 | Q24: =O24+P24 -> 1052530 | S24: 社員割引に伴う経常的な雑収入。事業に付随して継続的に発生するため正常収益力に加算
B25: =PL!B25 -> 0 | C25: =PL!C25 -> 0 | E25: =C25+D25 -> 0 | F25: =PL!E25 -> 0 | H25: =F25+G25 -> 0 | I25: =PL!G25 -> 0 | K25: =I25+J25 -> 0 | L25: =PL!I25 -> 0 | N25: =L25+M25 -> 0 | O25: =PL!K25 -> 0 | Q25: =O25+P25 -> 0
B26: =PL!B26 -> 0 | C26: =PL!C26 -> 0 | E26: =C26+D26 -> 0 | F26: =PL!E26 -> 0 | H26: =F26+G26 -> 0 | I26: =PL!G26 -> 0 | K26: =I26+J26 -> 0 | L26: =PL!I26 -> 0 | N26: =L26+M26 -> 0 | O26: =PL!K26 -> 0 | Q26: =O26+P26 -> 0
B27: =PL!B27 -> 0 | C27: =PL!C27 -> 0 | E27: =C27+D27 -> 0 | F27: =PL!E27 -> 0 | H27: =F27+G27 -> 0 | I27: =PL!G27 -> 0 | K27: =I27+J27 -> 0 | L27: =PL!I27 -> 0 | N27: =L27+M27 -> 0 | O27: =PL!K27 -> 0 | Q27: =O27+P27 -> 0
E28: =C28+D28 -> 0 | H28: =F28+G28 -> 0 | K28: =I28+J28 -> 0 | N28: =L28+M28 -> 0 | Q28: =O28+P28 -> 0
B29: 営業外費用 | C29: =SUM(C30:C36) -> 0 | D29: =SUM(D30:D36) -> 0 | E29: =C29+D29 -> 0 | F29: =SUM(F30:F36) -> 1134221 | G29: =SUM(G30:G36) -> 0 | H29: =F29+G29 -> 1134221 | I29: =SUM(I30:I36) -> 2295915 | J29: =SUM(J30:J36) -> 0 | K29: =I29+J29 -> 2295915 | L29: =SUM(L30:L36) -> 2655577 | M29: =SUM(M30:M36) -> 0 | N29: =L29+M29 -> 2655577 | O29: =SUM(O30:O36) -> 1881979 | P29: =SUM(P30:P36) -> 0 | Q29: =O29+P29 -> 1881979
B30: =PL!B30 -> 支払利息 | C30: =PL!C30 -> 0 | E30: =C30+D30 -> 0 | F30: =PL!E30 -> 1134221 | H30: =F30+G30 -> 1134221 | I30: =PL!G30 -> 1787923 | K30: =I30+J30 -> 1787923 | L30: =PL!I30 -> 2590791 | N30: =L30+M30 -> 2590791 | O30: =PL!K30 -> 1881899 | Q30: =O30+P30 -> 1881899
B31: =PL!B31 -> 雑損失 | C31: =PL!C31 -> 0 | E31: =C31+D31 -> 0 | F31: =PL!E31 -> 0 | H31: =F31+G31 -> 0 | I31: =PL!G31 -> 507992 | K31: =I31+J31 -> 507992 | L31: =PL!I31 -> 64786 | N31: =L31+M31 -> 64786 | O31: =PL!K31 -> 80 | Q31: =O31+P31 -> 80
B32: =PL!B32 -> 0 | C32: =PL!C32 -> 0 | E32: =C32+D32 -> 0 | F32: =PL!E32 -> 0 | H32: =F32+G32 -> 0 | I32: =PL!G32 -> 0 | K32: =I32+J32 -> 0 | L32: =PL!I32 -> 0 | N32: =L32+M32 -> 0 | O32: =PL!K32 -> 0 | Q32: =O32+P32 -> 0
B33: =PL!B33 -> 0 | C33: =PL!C33 -> 0 | E33: =C33+D33 -> 0 | F33: =PL!E33 -> 0 | H33: =F33+G33 -> 0 | I33: =PL!G33 -> 0 | K33: =I33+J33 -> 0 | L33: =PL!I33 -> 0 | N33: =L33+M33 -> 0 | O33: =PL!K33 -> 0 | Q33: =O33+P33 -> 0
B34: =PL!B34 -> 0 | C34: =PL!C34 -> 0 | E34: =C34+D34 -> 0 | F34: =PL!E34 -> 0 | H34: =F34+G34 -> 0 | I34: =PL!G34 -> 0 | K34: =I34+J34 -> 0 | L34: =PL!I34 -> 0 | N34: =L34+M34 -> 0 | O34: =PL!K34 -> 0 | Q34: =O34+P34 -> 0
B35: =PL!B35 -> 0 | C35: =PL!C35 -> 0 | E35: =C35+D35 -> 0 | F35: =PL!E35 -> 0 | H35: =F35+G35 -> 0 | I35: =PL!G35 -> 0 | K35: =I35+J35 -> 0 | L35: =PL!I35 -> 0 | N35: =L35+M35 -> 0 | O35: =PL!K35 -> 0 | Q35: =O35+P35 -> 0
E36: =C36+D36 -> 0 | H36: =F36+G36 -> 0 | K36: =I36+J36 -> 0 | N36: =L36+M36 -> 0 | Q36: =O36+P36 -> 0
B37: 経常利益 | C37: =C20+C21-C29 -> 0 | D37: =D20+D21-D29 -> 0 | E37: =C37+D37 -> 0 | F37: =F20+F21-F29 -> 2528371 | G37: =G20+G21-G29 -> 8856000 | H37: =F37+G37 -> 11384371 | I37: =I20+I21-I29 -> 3109637 | J37: =J20+J21-J29 -> 20449000 | K37: =I37+J37 -> 23558637 | L37: =L20+L21-L29 -> -18575356 | M37: =M20+M21-M29 -> 19883868 | N37: =L37+M37 -> 1308512 | O37: =O20+O21-O29 -> 5814146 | P37: =P20+P21-P29 -> 0 | Q37: =O37+P37 -> 5814146
B38: 特別利益 | C38: =SUM(C39:C44) -> 0 | D38: =SUM(D39:D44) -> 0 | E38: =C38+D38 -> 0 | F38: =SUM(F39:F44) -> 0 | G38: =SUM(G39:G44) -> 0 | H38: =F38+G38 -> 0 | I38: =SUM(I39:I44) -> 0 | J38: =SUM(J39:J44) -> 0 | K38: =I38+J38 -> 0 | L38: =SUM(L39:L44) -> 0 | M38: =SUM(M39:M44) -> 0 | N38: =L38+M38 -> 0 | O38: =SUM(O39:O44) -> 0 | P38: =SUM(P39:P44) -> 0 | Q38: =O38+P38 -> 0
B39: =PL!B39 -> 0 | C39: =PL!C39 -> 0 | E39: =C39+D39 -> 0 | F39: =PL!E39 -> 0 | H39: =F39+G39 -> 0 | I39: =PL!G39 -> 0 | K39: =I39+J39 -> 0 | L39: =PL!I39 -> 0 | N39: =L39+M39 -> 0 | O39: =PL!K39 -> 0 | Q39: =O39+P39 -> 0
B40: =PL!B40 -> 0 | C40: =PL!C40 -> 0 | E40: =C40+D40 -> 0 | F40: =PL!E40 -> 0 | H40: =F40+G40 -> 0 | I40: =PL!G40 -> 0 | K40: =I40+J40 -> 0 | L40: =PL!I40 -> 0 | N40: =L40+M40 -> 0 | O40: =PL!K40 -> 0 | Q40: =O40+P40 -> 0
B41: =PL!B41 -> 0 | C41: =PL!C41 -> 0 | E41: =C41+D41 -> 0 | F41: =PL!E41 -> 0 | H41: =F41+G41 -> 0 | I41: =PL!G41 -> 0 | K41: =I41+J41 -> 0 | L41: =PL!I41 -> 0 | N41: =L41+M41 -> 0 | O41: =PL!K41 -> 0 | Q41: =O41+P41 -> 0
B42: =PL!B42 -> 0 | C42: =PL!C42 -> 0 | E42: =C42+D42 -> 0 | F42: =PL!E42 -> 0 | H42: =F42+G42 -> 0 | I42: =PL!G42 -> 0 | K42: =I42+J42 -> 0 | L42: =PL!I42 -> 0 | N42: =L42+M42 -> 0 | O42: =PL!K42 -> 0 | Q42: =O42+P42 -> 0
B43: =PL!B43 -> 0 | C43: =PL!C43 -> 0 | E43: =C43+D43 -> 0 | F43: =PL!E43 -> 0 | H43: =F43+G43 -> 0 | I43: =PL!G43 -> 0 | K43: =I43+J43 -> 0 | L43: =PL!I43 -> 0 | N43: =L43+M43 -> 0 | O43: =PL!K43 -> 0 | Q43: =O43+P43 -> 0
E44: =C44+D44 -> 0 | H44: =F44+G44 -> 0 | K44: =I44+J44 -> 0 | N44: =L44+M44 -> 0 | Q44: =O44+P44 -> 0
B45: 特別損失 | C45: =SUM(C46:C51) -> 0 | D45: =SUM(D46:D51) -> 0 | E45: =C45+D45 -> 0 | F45: =SUM(F46:F51) -> 0 | G45: =SUM(G46:G51) -> 0 | H45: =F45+G45 -> 0 | I45: =SUM(I46:I51) -> 0 | J45: =SUM(J46:J51) -> 0 | K45: =I45+J45 -> 0 | L45: =SUM(L46:L51) -> 1298191 | M45: =SUM(M46:M51) -> 0 | N45: =L45+M45 -> 1298191 | O45: =SUM(O46:O51) -> 44000000 | P45: =SUM(P46:P51) -> 0 | Q45: =O45+P45 -> 44000000
B46: =PL!B46 -> 固定資産売却損 | C46: =PL!C46 -> 0 | E46: =C46+D46 -> 0 | F46: =PL!E46 -> 0 | H46: =F46+G46 -> 0 | I46: =PL!G46 -> 0 | K46: =I46+J46 -> 0 | L46: =PL!I46 -> 968026 | N46: =L46+M46 -> 968026 | O46: =PL!K46 -> 0 | Q46: =O46+P46 -> 0
B47: =PL!B47 -> 固定資産除却損 | C47: =PL!C47 -> 0 | E47: =C47+D47 -> 0 | F47: =PL!E47 -> 0 | H47: =F47+G47 -> 0 | I47: =PL!G47 -> 0 | K47: =I47+J47 -> 0 | L47: =PL!I47 -> 330165 | N47: =L47+M47 -> 330165 | O47: =PL!K47 -> 0 | Q47: =O47+P47 -> 0
B48: =PL!B48 -> 棚卸資産廃棄損 | C48: =PL!C48 -> 0 | E48: =C48+D48 -> 0 | F48: =PL!E48 -> 0 | H48: =F48+G48 -> 0 | I48: =PL!G48 -> 0 | K48: =I48+J48 -> 0 | L48: =PL!I48 -> 0 | N48: =L48+M48 -> 0 | O48: =PL!K48 -> 44000000 | Q48: =O48+P48 -> 44000000
B49: =PL!B49 -> 0 | C49: =PL!C49 -> 0 | E49: =C49+D49 -> 0 | F49: =PL!E49 -> 0 | H49: =F49+G49 -> 0 | I49: =PL!G49 -> 0 | K49: =I49+J49 -> 0 | L49: =PL!I49 -> 0 | N49: =L49+M49 -> 0 | O49: =PL!K49 -> 0 | Q49: =O49+P49 -> 0
B50: =PL!B50 -> 0 | C50: =PL!C50 -> 0 | E50: =C50+D50 -> 0 | F50: =PL!E50 -> 0 | H50: =F50+G50 -> 0 | I50: =PL!G50 -> 0 | K50: =I50+J50 -> 0 | L50: =PL!I50 -> 0 | N50: =L50+M50 -> 0 | O50: =PL!K50 -> 0 | Q50: =O50+P50 -> 0
E51: =C51+D51 -> 0 | H51: =F51+G51 -> 0 | K51: =I51+J51 -> 0 | N51: =L51+M51 -> 0 | Q51: =O51+P51 -> 0
B52: 税引前当期純利益 | C52: =C37+C38-C45 -> 0 | D52: =D37+D38-D45 -> 0 | E52: =C52+D52 -> 0 | F52: =F37+F38-F45 -> 2528371 | G52: =G37+G38-G45 -> 8856000 | H52: =F52+G52 -> 11384371 | I52: =I37+I38-I45 -> 3109637 | J52: =J37+J38-J45 -> 20449000 | K52: =I52+J52 -> 23558637 | L52: =L37+L38-L45 -> -19873547 | M52: =M37+M38-M45 -> 19883868 | N52: =L52+M52 -> 10321 | O52: =O37+O38-O45 -> -38185854 | P52: =P37+P38-P45 -> 0 | Q52: =O52+P52 -> -38185854
B53: 法人税等 | C53: =SUM(C54:C56) -> 0 | D53: =SUM(D54:D56) -> 0 | E53: =C53+D53 -> 0 | F53: =SUM(F54:F56) -> 894154 | G53: =SUM(G54:G56) -> 0 | H53: =F53+G53 -> 894154 | I53: =SUM(I54:I56) -> 2135275 | J53: =SUM(J54:J56) -> 0 | K53: =I53+J53 -> 2135275 | L53: =SUM(L54:L56) -> 485000 | M53: =SUM(M54:M56) -> 0 | N53: =L53+M53 -> 485000 | O53: =SUM(O54:O56) -> 986 | P53: =SUM(P54:P56) -> 0 | Q53: =O53+P53 -> 986
B54: =PL!B54 -> 法人税等 | C54: =PL!C54 -> 0 | E54: =C54+D54 -> 0 | F54: =PL!E54 -> 894154 | H54: =F54+G54 -> 894154 | I54: =PL!G54 -> 2135275 | K54: =I54+J54 -> 2135275 | L54: =PL!I54 -> 485000 | N54: =L54+M54 -> 485000 | O54: =PL!K54 -> 986 | Q54: =O54+P54 -> 986
B55: =PL!B55 -> 0 | C55: =PL!C55 -> 0 | E55: =C55+D55 -> 0 | F55: =PL!E55 -> 0 | H55: =F55+G55 -> 0 | I55: =PL!G55 -> 0 | K55: =I55+J55 -> 0 | L55: =PL!I55 -> 0 | N55: =L55+M55 -> 0 | O55: =PL!K55 -> 0 | Q55: =O55+P55 -> 0
E56: =C56+D56 -> 0 | H56: =F56+G56 -> 0 | K56: =I56+J56 -> 0 | N56: =L56+M56 -> 0 | Q56: =O56+P56 -> 0
B57: 税引後当期純利益 | C57: =C52-C53 -> 0 | D57: =D52-D53 -> 0 | E57: =C57+D57 -> 0 | F57: =F52-F53 -> 1634217 | G57: =G52-G53 -> 8856000 | H57: =F57+G57 -> 10490217 | I57: =I52-I53 -> 974362 | J57: =J52-J53 -> 20449000 | K57: =I57+J57 -> 21423362 | L57: =L52-L53 -> -20358547 | M57: =M52-M53 -> 19883868 | N57: =L57+M57 -> -474679 | O57: =O52-O53 -> -38186840 | P57: =P52-P53 -> 0 | Q57: =O57+P57 -> -38186840
F59: 1634217 | I59: 974362 | L59: -20358547 | O59: -27305086
B60: ※特別損失に計上された固定資産売却損968千円・除却損330千円は非経常的な損益として調整していない。※2026年3月の棚卸資産廃棄損44,000千円は基準日後の事象であり、修正BSで評価差額として反映している。※支払利息は営業利益に含まれないため、正常収益力の算定上あらためて控除していない。 | C60: =C59=C57 -> 1 | F60: =F59=F57 -> 1 | I60: =I59=I57 -> 1 | L60: =L59=L57 -> 1 | O60: =O59=O57 -> 0
B61: 【正常収益力への橋渡し】
B62: 修正後営業利益（修正PL） | H62: =H20 -> 9876140 | K62: =K20 -> 22836100 | N62: =N20 -> -322737 | S62: ※雑収入は営業外収益であるため修正PL上は営業利益に含まれないが、社員割引に伴い事業へ付随して継続的に発生するため、正常収益力には加算する。この加算後の金額が企業概要書の調整項目合計と一致する。
B63: 経常的雑収入（社員割引）の加算 | H63: =G24 -> 1321000 | K63: =J24 -> 635000 | N63: =M24 -> 654868
B64: 正常収益力（修正後営業利益ベース） | H64: =H62+H63 -> 11197140 | K64: =K62+K63 -> 23471100 | N64: =N62+N63 -> 332131

Sheet 修正SGA
K2: (単位：千円)
B3: 科目 | C3: ='BS(借方)'!C4 -> － | F3: ='BS(借方)'!D4 -> 23年11月期 | I3: ='BS(借方)'!E4 -> 24年11月期 | L3: ='BS(借方)'!F4 -> 25年11月期 | O3: ='BS(借方)'!G4 -> 26年11月期 （7か月TB） | S3: 調整事由
C4: 帳簿価額 | D4: 修正額 | E4: 修正後 | F4: 帳簿価額 | G4: 修正額 | H4: 修正後 | I4: 帳簿価額 | J4: 修正額 | K4: 修正後 | L4: 帳簿価額 | M4: 修正額 | N4: 修正後 | O4: 帳簿価額 | P4: 修正額 | Q4: 修正後
B5: =SGA!B6 -> 従業員給与 | C5: =SGA!C6 -> 0 | E5: =C5+D5 -> 0 | F5: =SGA!E6 -> 112323477 | G5: 0 | H5: =F5+G5 -> 112323477 | I5: =SGA!G6 -> 115961553 | J5: -8831000 | K5: =I5+J5 -> 107130553 | L5: =SGA!I6 -> 127016990 | M5: -8183000 | N5: =L5+M5 -> 118833990 | O5: =SGA!K6 -> 64179726 | Q5: =O5+P5 -> 64179726 | S5: 現場責任者（淺野崇氏）の人件費を役員報酬へ振替
B6: =SGA!B7 -> 旅費交通費 | C6: =SGA!C7 -> 0 | E6: =C6+D6 -> 0 | F6: =SGA!E7 -> 3152359 | H6: =F6+G6 -> 3152359 | I6: =SGA!G7 -> 4978151 | K6: =I6+J6 -> 4978151 | L6: =SGA!I7 -> 5724652 | N6: =L6+M6 -> 5724652 | O6: =SGA!K7 -> 3504938 | Q6: =O6+P6 -> 3504938
B7: =SGA!B8 -> 広告宣伝費 | C7: =SGA!C8 -> 0 | E7: =C7+D7 -> 0 | F7: =SGA!E8 -> 24335030 | H7: =F7+G7 -> 24335030 | I7: =SGA!G8 -> 34052424 | K7: =I7+J7 -> 34052424 | L7: =SGA!I8 -> 26650854 | N7: =L7+M7 -> 26650854 | O7: =SGA!K8 -> 15163208 | Q7: =O7+P7 -> 15163208
B8: =SGA!B9 -> 発送配達費 | C8: =SGA!C9 -> 0 | E8: =C8+D8 -> 0 | F8: =SGA!E9 -> 352787 | H8: =F8+G8 -> 352787 | I8: =SGA!G9 -> 280605 | K8: =I8+J8 -> 280605 | L8: =SGA!I9 -> 436931 | N8: =L8+M8 -> 436931 | O8: =SGA!K9 -> 129150 | Q8: =O8+P8 -> 129150
B9: =SGA!B10 -> ロイヤリティ | C9: =SGA!C10 -> 0 | E9: =C9+D9 -> 0 | F9: =SGA!E10 -> 45990311 | H9: =F9+G9 -> 45990311 | I9: =SGA!G10 -> 39848148 | K9: =I9+J9 -> 39848148 | L9: =SGA!I10 -> 29981679 | N9: =L9+M9 -> 29981679 | O9: =SGA!K10 -> 14193011 | Q9: =O9+P9 -> 14193011
B10: =SGA!B11 -> 会議費 | C10: =SGA!C11 -> 0 | E10: =C10+D10 -> 0 | F10: =SGA!E11 -> 189625 | H10: =F10+G10 -> 189625 | I10: =SGA!G11 -> 484171 | K10: =I10+J10 -> 484171 | L10: =SGA!I11 -> 1489497 | N10: =L10+M10 -> 1489497 | O10: =SGA!K11 -> 887177 | Q10: =O10+P10 -> 887177
B11: =SGA!B12 -> 役員報酬 | C11: =SGA!C12 -> 0 | E11: =C11+D11 -> 0 | F11: =SGA!E12 -> 9600000 | G11: 0 | H11: =F11+G11 -> 9600000 | I11: =SGA!G12 -> 9600000 | J11: 0 | K11: =I11+J11 -> 9600000 | L11: =SGA!I12 -> 14400000 | M11: 0 | N11: =L11+M11 -> 14400000 | O11: =SGA!K12 -> 6300000 | Q11: =O11+P11 -> 6300000 | S11: 代表者の退任分を戻し入れ、後任役員の同水準報酬を控除（差引ゼロ）
B12: =SGA!B13 -> 法定福利費 | C12: =SGA!C13 -> 0 | E12: =C12+D12 -> 0 | F12: =SGA!E13 -> 10104201 | H12: =F12+G12 -> 10104201 | I12: =SGA!G13 -> 22242217 | K12: =I12+J12 -> 22242217 | L12: =SGA!I13 -> 15295210 | N12: =L12+M12 -> 15295210 | O12: =SGA!K13 -> 2778916 | Q12: =O12+P12 -> 2778916
B13: =SGA!B14 -> 厚生費 | C13: =SGA!C14 -> 0 | E13: =C13+D13 -> 0 | F13: =SGA!E14 -> 2936211 | H13: =F13+G13 -> 2936211 | I13: =SGA!G14 -> 3945609 | K13: =I13+J13 -> 3945609 | L13: =SGA!I14 -> 3862961 | N13: =L13+M13 -> 3862961 | O13: =SGA!K14 -> 1748144 | Q13: =O13+P13 -> 1748144
B14: =SGA!B15 -> 減価償却費 | C14: =SGA!C15 -> 0 | E14: =C14+D14 -> 0 | F14: =SGA!E15 -> 3911003 | H14: =F14+G14 -> 3911003 | I14: =SGA!G15 -> 9294598 | K14: =I14+J14 -> 9294598 | L14: =SGA!I15 -> 6349173 | N14: =L14+M14 -> 6349173 | O14: =SGA!K15 -> 0 | Q14: =O14+P14 -> 0
B15: =SGA!B16 -> リース料 | C15: =SGA!C16 -> 0 | E15: =C15+D15 -> 0 | F15: =SGA!E16 -> 4294932 | G15: -2386000 | H15: =F15+G15 -> 1908932 | I15: =SGA!G16 -> 4554982 | J15: -3154000 | K15: =I15+J15 -> 1400982 | L15: =SGA!I16 -> 7249573 | M15: -5604000 | N15: =L15+M15 -> 1645573 | O15: =SGA!K16 -> 4352502 | Q15: =O15+P15 -> 4352502 | S15: 非事業用車両のリース料（本件実行後に発生しない）
B16: =SGA!B17 -> 地代家賃 | C16: =SGA!C17 -> 0 | E16: =C16+D16 -> 0 | F16: =SGA!E17 -> 8230492 | H16: =F16+G16 -> 8230492 | I16: =SGA!G17 -> 19460488 | K16: =I16+J16 -> 19460488 | L16: =SGA!I17 -> 33248832 | N16: =L16+M16 -> 33248832 | O16: =SGA!K17 -> 19879129 | Q16: =O16+P16 -> 19879129
B17: =SGA!B18 -> 修繕費 | C17: =SGA!C18 -> 0 | E17: =C17+D17 -> 0 | F17: =SGA!E18 -> 468295 | H17: =F17+G17 -> 468295 | I17: =SGA!G18 -> 1088033 | K17: =I17+J17 -> 1088033 | L17: =SGA!I18 -> 275210 | N17: =L17+M17 -> 275210 | O17: =SGA!K18 -> 243111 | Q17: =O17+P17 -> 243111
B18: =SGA!B19 -> 事務用消耗品費 | C18: =SGA!C19 -> 0 | E18: =C18+D18 -> 0 | F18: =SGA!E19 -> 9801863 | H18: =F18+G18 -> 9801863 | I18: =SGA!G19 -> 6407354 | K18: =I18+J18 -> 6407354 | L18: =SGA!I19 -> 4371794 | N18: =L18+M18 -> 4371794 | O18: =SGA!K19 -> 1558723 | Q18: =O18+P18 -> 1558723
B19: =SGA!B20 -> 通信費 | C19: =SGA!C20 -> 0 | E19: =C19+D19 -> 0 | F19: =SGA!E20 -> 2455532 | H19: =F19+G19 -> 2455532 | I19: =SGA!G20 -> 2672628 | K19: =I19+J19 -> 2672628 | L19: =SGA!I20 -> 3045340 | N19: =L19+M19 -> 3045340 | O19: =SGA!K20 -> 2149718 | Q19: =O19+P19 -> 2149718
B20: =SGA!B21 -> 水道光熱費 | C20: =SGA!C21 -> 0 | E20: =C20+D20 -> 0 | F20: =SGA!E21 -> 2958090 | H20: =F20+G20 -> 2958090 | I20: =SGA!G21 -> 3148822 | K20: =I20+J20 -> 3148822 | L20: =SGA!I21 -> 3940893 | N20: =L20+M20 -> 3940893 | O20: =SGA!K21 -> 1714053 | Q20: =O20+P20 -> 1714053
B21: =SGA!B22 -> 租税公課 | C21: =SGA!C22 -> 0 | E21: =C21+D21 -> 0 | F21: =SGA!E22 -> 8881475 | H21: =F21+G21 -> 8881475 | I21: =SGA!G22 -> 10506364 | K21: =I21+J21 -> 10506364 | L21: =SGA!I22 -> 20061210 | N21: =L21+M21 -> 20061210 | O21: =SGA!K22 -> 5281078 | Q21: =O21+P21 -> 5281078
B22: =SGA!B23 -> 接待交際費 | C22: =SGA!C23 -> 0 | E22: =C22+D22 -> 0 | F22: =SGA!E23 -> 8453145 | G22: -4453000 | H22: =F22+G22 -> 4000145 | I22: =SGA!G23 -> 10229520 | J22: -6230000 | K22: =I22+J22 -> 3999520 | L22: =SGA!I23 -> 8217611 | M22: -4218000 | N22: =L22+M22 -> 3999611 | O22: =SGA!K23 -> 4409532 | Q22: =O22+P22 -> 4409532 | S22: 接待交際費のうち適正水準4,000千円を超える部分
B23: =SGA!B24 -> 保険料 | C23: =SGA!C24 -> 0 | E23: =C23+D23 -> 0 | F23: =SGA!E24 -> 2411203 | G23: -696000 | H23: =F23+G23 -> 1715203 | I23: =SGA!G24 -> 4218242 | J23: -1599000 | K23: =I23+J23 -> 2619242 | L23: =SGA!I24 -> 3876512 | M23: -1224000 | N23: =L23+M23 -> 2652512 | O23: =SGA!K24 -> 1726252 | Q23: =O23+P23 -> 1726252 | S23: 事業関連性の低い生命保険料
B24: =SGA!B25 -> 備品消耗品費 | C24: =SGA!C25 -> 0 | E24: =C24+D24 -> 0 | F24: =SGA!E25 -> 12485436 | H24: =F24+G24 -> 12485436 | I24: =SGA!G25 -> 14036551 | K24: =I24+J24 -> 14036551 | L24: =SGA!I25 -> 8462064 | N24: =L24+M24 -> 8462064 | O24: =SGA!K25 -> 4361180 | Q24: =O24+P24 -> 4361180
B25: =SGA!B26 -> 管理諸費 | C25: =SGA!C26 -> 0 | E25: =C25+D25 -> 0 | F25: =SGA!E26 -> 5563800 | H25: =F25+G25 -> 5563800 | I25: =SGA!G26 -> 5027000 | K25: =I25+J25 -> 5027000 | L25: =SGA!I26 -> 5797000 | N25: =L25+M25 -> 5797000 | O25: =SGA!K26 -> 3197700 | Q25: =O25+P25 -> 3197700
B26: =SGA!B27 -> 支払手数料 | C26: =SGA!C27 -> 0 | E26: =C26+D26 -> 0 | F26: =SGA!E27 -> 7152851 | H26: =F26+G26 -> 7152851 | I26: =SGA!G27 -> 11861229 | K26: =I26+J26 -> 11861229 | L26: =SGA!I27 -> 14452516 | N26: =L26+M26 -> 14452516 | O26: =SGA!K27 -> 6927603 | Q26: =O26+P26 -> 6927603
B27: =SGA!B28 -> 諸会費 | C27: =SGA!C28 -> 0 | E27: =C27+D27 -> 0 | F27: =SGA!E28 -> 24000 | H27: =F27+G27 -> 24000 | I27: =SGA!G28 -> 24000 | K27: =I27+J27 -> 24000 | L27: =SGA!I28 -> 16500 | N27: =L27+M27 -> 16500 | O27: =SGA!K28 -> 4000 | Q27: =O27+P27 -> 4000
B28: =SGA!B29 -> 車両費 | C28: =SGA!C29 -> 0 | E28: =C28+D28 -> 0 | F28: =SGA!E29 -> 626896 | H28: =F28+G28 -> 626896 | I28: =SGA!G29 -> 446867 | K28: =I28+J28 -> 446867 | L28: =SGA!I29 -> 512955 | N28: =L28+M28 -> 512955 | O28: =SGA!K29 -> 258439 | Q28: =O28+P28 -> 258439
B29: =SGA!B30 -> 研修費 | C29: =SGA!C30 -> 0 | E29: =C29+D29 -> 0 | F29: =SGA!E30 -> 0 | H29: =F29+G29 -> 0 | I29: =SGA!G30 -> 103345 | K29: =I29+J29 -> 103345 | L29: =SGA!I30 -> 173500 | N29: =L29+M29 -> 173500 | O29: =SGA!K30 -> 88900 | Q29: =O29+P29 -> 88900
B30: =SGA!B31 -> 雑費 | C30: =SGA!C31 -> 0 | E30: =C30+D30 -> 0 | F30: =SGA!E31 -> 3334480 | H30: =F30+G30 -> 3334480 | I30: =SGA!G31 -> 5436149 | K30: =I30+J30 -> 5436149 | L30: =SGA!I31 -> 4666766 | N30: =L30+M30 -> 4666766 | O30: =SGA!K31 -> 2718158 | Q30: =O30+P30 -> 2718158
B31: =SGA!B32 -> 0 | C31: =SGA!C32 -> 0 | E31: =C31+D31 -> 0 | F31: =SGA!E32 -> 0 | H31: =F31+G31 -> 0 | I31: =SGA!G32 -> 0 | K31: =I31+J31 -> 0 | L31: =SGA!I32 -> 0 | N31: =L31+M31 -> 0 | O31: =SGA!K32 -> 0 | Q31: =O31+P31 -> 0
B32: =SGA!B33 -> 0 | C32: =SGA!C33 -> 0 | E32: =C32+D32 -> 0 | F32: =SGA!E33 -> 0 | H32: =F32+G32 -> 0 | I32: =SGA!G33 -> 0 | K32: =I32+J32 -> 0 | L32: =SGA!I33 -> 0 | N32: =L32+M32 -> 0 | O32: =SGA!K33 -> 0 | Q32: =O32+P32 -> 0
B33: =SGA!B34 -> 0 | C33: =SGA!C34 -> 0 | E33: =C33+D33 -> 0 | F33: =SGA!E34 -> 0 | H33: =F33+G33 -> 0 | I33: =SGA!G34 -> 0 | K33: =I33+J33 -> 0 | L33: =SGA!I34 -> 0 | N33: =L33+M33 -> 0 | O33: =SGA!K34 -> 0 | Q33: =O33+P33 -> 0
B34: =SGA!B35 -> 0 | C34: =SGA!C35 -> 0 | E34: =C34+D34 -> 0 | F34: =SGA!E35 -> 0 | H34: =F34+G34 -> 0 | I34: =SGA!G35 -> 0 | K34: =I34+J34 -> 0 | L34: =SGA!I35 -> 0 | N34: =L34+M34 -> 0 | O34: =SGA!K35 -> 0 | Q34: =O34+P34 -> 0
E35: =C35+D35 -> 0 | H35: =F35+G35 -> 0 | K35: =I35+J35 -> 0 | N35: =L35+M35 -> 0 | Q35: =O35+P35 -> 0
E36: =C36+D36 -> 0 | H36: =F36+G36 -> 0 | K36: =I36+J36 -> 0 | N36: =L36+M36 -> 0 | Q36: =O36+P36 -> 0
E37: =C37+D37 -> 0 | H37: =F37+G37 -> 0 | K37: =I37+J37 -> 0 | N37: =L37+M37 -> 0 | Q37: =O37+P37 -> 0
E38: =C38+D38 -> 0 | H38: =F38+G38 -> 0 | K38: =I38+J38 -> 0 | N38: =L38+M38 -> 0 | Q38: =O38+P38 -> 0
B39: 販売費および一般管理費合計 | C39: =SUM(C5:C38) -> 0 | D39: =SUM(D5:D38) -> 0 | E39: =C39+D39 -> 0 | F39: =SUM(F5:F38) -> 290037494 | G39: =SUM(G5:G38) -> -7535000 | H39: =F39+G39 -> 282502494 | I39: =SUM(I5:I38) -> 339909050 | J39: =SUM(J5:J38) -> -19814000 | K39: =I39+J39 -> 320095050 | L39: =SUM(L5:L38) -> 349576223 | M39: =SUM(M5:M38) -> -19229000 | N39: =L39+M39 -> 330347223 | O39: =SUM(O5:O38) -> 167754348 | P39: =SUM(P5:P38) -> 0 | Q39: =O39+P39 -> 167754348

Sheet 修正CR
B2: ※対象会社は小売業であり製造原価報告書は作成されていないため、本シートは使用しない。 | K2: (単位：千円)
B3: 科目 | C3: ='BS(借方)'!C4 -> － | F3: ='BS(借方)'!D4 -> 23年11月期 | I3: ='BS(借方)'!E4 -> 24年11月期 | L3: ='BS(借方)'!F4 -> 25年11月期 | O3: ='BS(借方)'!G4 -> 26年11月期 （7か月TB）
C4: 帳簿価額 | D4: 修正額 | E4: 修正後 | F4: 帳簿価額 | G4: 修正額 | H4: 修正後 | I4: 帳簿価額 | J4: 修正額 | K4: 修正後 | L4: 帳簿価額 | M4: 修正額 | N4: 修正後 | O4: 帳簿価額 | P4: 修正額 | Q4: 修正後
B5: 期首原材料棚卸高 | C5: 500000 | D5: -500000 | E5: =C5+D5 -> 0 | F5: 500000 | G5: -500000 | H5: =F5+G5 -> 0 | I5: 500000 | J5: -500000 | K5: =I5+J5 -> 0 | L5: 500000 | M5: -500000 | N5: =L5+M5 -> 0 | O5: 500000 | P5: -500000 | Q5: =O5+P5 -> 0
B6: 原材料仕入高 | E6: =C6+D6 -> 0 | H6: =F6+G6 -> 0 | K6: =I6+J6 -> 0 | N6: =L6+M6 -> 0 | Q6: =O6+P6 -> 0
B7: 小計 | E7: =C7+D7 -> 0 | H7: =F7+G7 -> 0 | K7: =I7+J7 -> 0 | N7: =L7+M7 -> 0 | Q7: =O7+P7 -> 0
B8: 期末原材料棚卸高 | E8: =C8+D8 -> 0 | H8: =F8+G8 -> 0 | K8: =I8+J8 -> 0 | N8: =L8+M8 -> 0 | Q8: =O8+P8 -> 0
E9: =C9+D9 -> 0 | H9: =F9+G9 -> 0 | K9: =I9+J9 -> 0 | N9: =L9+M9 -> 0 | Q9: =O9+P9 -> 0
E10: =C10+D10 -> 0 | H10: =F10+G10 -> 0 | K10: =I10+J10 -> 0 | N10: =L10+M10 -> 0 | Q10: =O10+P10 -> 0
B11: 材料費 | C11: =SUM(C5:C10) -> 500000 | D11: =SUM(D5:D10) -> -500000 | E11: =C11+D11 -> 0 | F11: =SUM(F5:F10) -> 500000 | G11: =SUM(G5:G10) -> -500000 | H11: =F11+G11 -> 0 | I11: =SUM(I5:I10) -> 500000 | J11: =SUM(J5:J10) -> -500000 | K11: =I11+J11 -> 0 | L11: =SUM(L5:L10) -> 500000 | M11: =SUM(M5:M10) -> -500000 | N11: =L11+M11 -> 0 | O11: =SUM(O5:O10) -> 500000 | P11: =SUM(P5:P10) -> -500000 | Q11: =O11+P11 -> 0
E12: =C12+D12 -> 0 | H12: =F12+G12 -> 0 | K12: =I12+J12 -> 0 | N12: =L12+M12 -> 0 | Q12: =O12+P12 -> 0
E13: =C13+D13 -> 0 | H13: =F13+G13 -> 0 | K13: =I13+J13 -> 0 | N13: =L13+M13 -> 0 | Q13: =O13+P13 -> 0
E14: =C14+D14 -> 0 | H14: =F14+G14 -> 0 | K14: =I14+J14 -> 0 | N14: =L14+M14 -> 0 | Q14: =O14+P14 -> 0
E15: =C15+D15 -> 0 | H15: =F15+G15 -> 0 | K15: =I15+J15 -> 0 | N15: =L15+M15 -> 0 | Q15: =O15+P15 -> 0
E16: =C16+D16 -> 0 | H16: =F16+G16 -> 0 | K16: =I16+J16 -> 0 | N16: =L16+M16 -> 0 | Q16: =O16+P16 -> 0
E17: =C17+D17 -> 0 | H17: =F17+G17 -> 0 | K17: =I17+J17 -> 0 | N17: =L17+M17 -> 0 | Q17: =O17+P17 -> 0
B18: 労務費 | C18: =SUM(C12:C17) -> 0 | D18: =SUM(D12:D17) -> 0 | E18: =C18+D18 -> 0 | F18: =SUM(F12:F17) -> 0 | G18: =SUM(G12:G17) -> 0 | H18: =F18+G18 -> 0 | I18: =SUM(I12:I17) -> 0 | J18: =SUM(J12:J17) -> 0 | K18: =I18+J18 -> 0 | L18: =SUM(L12:L17) -> 0 | M18: =SUM(M12:M17) -> 0 | N18: =L18+M18 -> 0 | O18: =SUM(O12:O17) -> 0 | P18: =SUM(P12:P17) -> 0 | Q18: =O18+P18 -> 0
E19: =C19+D19 -> 0 | H19: =F19+G19 -> 0 | K19: =I19+J19 -> 0 | N19: =L19+M19 -> 0 | Q19: =O19+P19 -> 0
E20: =C20+D20 -> 0 | H20: =F20+G20 -> 0 | K20: =I20+J20 -> 0 | N20: =L20+M20 -> 0 | Q20: =O20+P20 -> 0
E21: =C21+D21 -> 0 | H21: =F21+G21 -> 0 | K21: =I21+J21 -> 0 | N21: =L21+M21 -> 0 | Q21: =O21+P21 -> 0
E22: =C22+D22 -> 0 | H22: =F22+G22 -> 0 | K22: =I22+J22 -> 0 | N22: =L22+M22 -> 0 | Q22: =O22+P22 -> 0
E23: =C23+D23 -> 0 | H23: =F23+G23 -> 0 | K23: =I23+J23 -> 0 | N23: =L23+M23 -> 0 | Q23: =O23+P23 -> 0
E24: =C24+D24 -> 0 | H24: =F24+G24 -> 0 | K24: =I24+J24 -> 0 | N24: =L24+M24 -> 0 | Q24: =O24+P24 -> 0
B25: 外注加工費 | C25: =SUM(C19:C24) -> 0 | D25: =SUM(D19:D24) -> 0 | E25: =C25+D25 -> 0 | F25: =SUM(F19:F24) -> 0 | G25: =SUM(G19:G24) -> 0 | H25: =F25+G25 -> 0 | I25: =SUM(I19:I24) -> 0 | J25: =SUM(J19:J24) -> 0 | K25: =I25+J25 -> 0 | L25: =SUM(L19:L24) -> 0 | M25: =SUM(M19:M24) -> 0 | N25: =L25+M25 -> 0 | O25: =SUM(O19:O24) -> 0 | P25: =SUM(P19:P24) -> 0 | Q25: =O25+P25 -> 0
E26: =C26+D26 -> 0 | H26: =F26+G26 -> 0 | K26: =I26+J26 -> 0 | N26: =L26+M26 -> 0 | Q26: =O26+P26 -> 0
E27: =C27+D27 -> 0 | H27: =F27+G27 -> 0 | K27: =I27+J27 -> 0 | N27: =L27+M27 -> 0 | Q27: =O27+P27 -> 0
E28: =C28+D28 -> 0 | H28: =F28+G28 -> 0 | K28: =I28+J28 -> 0 | N28: =L28+M28 -> 0 | Q28: =O28+P28 -> 0
E29: =C29+D29 -> 0 | H29: =F29+G29 -> 0 | K29: =I29+J29 -> 0 | N29: =L29+M29 -> 0 | Q29: =O29+P29 -> 0
E30: =C30+D30 -> 0 | H30: =F30+G30 -> 0 | K30: =I30+J30 -> 0 | N30: =L30+M30 -> 0 | Q30: =O30+P30 -> 0
E31: =C31+D31 -> 0 | H31: =F31+G31 -> 0 | K31: =I31+J31 -> 0 | N31: =L31+M31 -> 0 | Q31: =O31+P31 -> 0
E32: =C32+D32 -> 0 | H32: =F32+G32 -> 0 | K32: =I32+J32 -> 0 | N32: =L32+M32 -> 0 | Q32: =O32+P32 -> 0
E33: =C33+D33 -> 0 | H33: =F33+G33 -> 0 | K33: =I33+J33 -> 0 | N33: =L33+M33 -> 0 | Q33: =O33+P33 -> 0
E34: =C34+D34 -> 0 | H34: =F34+G34 -> 0 | K34: =I34+J34 -> 0 | N34: =L34+M34 -> 0 | Q34: =O34+P34 -> 0
E35: =C35+D35 -> 0 | H35: =F35+G35 -> 0 | K35: =I35+J35 -> 0 | N35: =L35+M35 -> 0 | Q35: =O35+P35 -> 0
B36: 経費 | C36: =SUM(C26:C35) -> 0 | D36: =SUM(D26:D35) -> 0 | E36: =C36+D36 -> 0 | F36: =SUM(F26:F35) -> 0 | G36: =SUM(G26:G35) -> 0 | H36: =F36+G36 -> 0 | I36: =SUM(I26:I35) -> 0 | J36: =SUM(J26:J35) -> 0 | K36: =I36+J36 -> 0 | L36: =SUM(L26:L35) -> 0 | M36: =SUM(M26:M35) -> 0 | N36: =L36+M36 -> 0 | O36: =SUM(O26:O35) -> 0 | P36: =SUM(P26:P35) -> 0 | Q36: =O36+P36 -> 0
B37: 当期製造費用 | C37: =C11+C18+C25+C36 -> 500000 | D37: =D11+D18+D25+D36 -> -500000 | E37: =C37+D37 -> 0 | F37: =F11+F18+F25+F36 -> 500000 | G37: =G11+G18+G25+G36 -> -500000 | H37: =F37+G37 -> 0 | I37: =I11+I18+I25+I36 -> 500000 | J37: =J11+J18+J25+J36 -> -500000 | K37: =I37+J37 -> 0 | L37: =L11+L18+L25+L36 -> 500000 | M37: =M11+M18+M25+M36 -> -500000 | N37: =L37+M37 -> 0 | O37: =O11+O18+O25+O36 -> 500000 | P37: =P11+P18+P25+P36 -> -500000 | Q37: =O37+P37 -> 0
B38: 期首仕掛品棚卸高 | E38: =C38+D38 -> 0 | H38: =F38+G38 -> 0 | K38: =I38+J38 -> 0 | N38: =L38+M38 -> 0 | Q38: =O38+P38 -> 0
B39: 合計 | C39: =SUM(C37:C38) -> 500000 | D39: =SUM(D37:D38) -> -500000 | E39: =C39+D39 -> 0 | F39: =SUM(F37:F38) -> 500000 | G39: =SUM(G37:G38) -> -500000 | H39: =F39+G39 -> 0 | I39: =SUM(I37:I38) -> 500000 | J39: =SUM(J37:J38) -> -500000 | K39: =I39+J39 -> 0 | L39: =SUM(L37:L38) -> 500000 | M39: =SUM(M37:M38) -> -500000 | N39: =L39+M39 -> 0 | O39: =SUM(O37:O38) -> 500000 | P39: =SUM(P37:P38) -> -500000 | Q39: =O39+P39 -> 0
B40: 期末仕掛品棚卸高 | E40: =C40+D40 -> 0 | H40: =F40+G40 -> 0 | K40: =I40+J40 -> 0 | N40: =L40+M40 -> 0 | Q40: =O40+P40 -> 0
B41: 当期製造原価 | C41: =C39-C40 -> 500000 | D41: =D39-D40 -> -500000 | E41: =C41+D41 -> 0 | F41: =F39-F40 -> 500000 | G41: =G39-G40 -> -500000 | H41: =F41+G41 -> 0 | I41: =I39-I40 -> 500000 | J41: =J39-J40 -> -500000 | K41: =I41+J41 -> 0 | L41: =L39-L40 -> 500000 | M41: =M39-M40 -> -500000 | N41: =L41+M41 -> 0 | O41: =O39-O40 -> 500000 | P41: =P39-P40 -> -500000 | Q41: =O41+P41 -> 0

Sheet 評価科目
B2: 評価科目別の検討結果（評価基準日：2025年11月30日） | G2: (単位：千円)
B4: № | C4: 科目 | D4: 帳簿価額 | E4: 評価差額 | F4: 評価額 | G4: 検討結果・調整事由
B5: 1 | C5: 商品（棚卸資産） | D5: ='BS(借方)'!F8 -> 106017284 | E5: -44000000 | F5: =D5+E5 -> 62017284 | G5: 2026年3月に本社分32,000千円・バックヤード分12,000千円を全額廃棄。基準日時点で滞留・陳腐化していたと判断し評価減。残る外部保管在庫10,000千円は実在性が未確認（要確認）
B6: 2 | C6: 営業権 | D6: ='BS(借方)'!F50 -> 1500004 | E6: -1500004 | F6: =D6+E6 -> 0 | G6: 年買法で営業権を別途算定するため二重計上となること、および換金価値が認められないことから全額評価減
B7: 3 | C7: 仮払金 | D7: ='BS(借方)'!F14 -> 1650000 | E7: -1650000 | F7: =D7+E7 -> 0 | G7: 回収を前提とした支出ではなく資産性が認められないため全額評価減
B8: 4 | C8: 売掛金 | D8: ='BS(借方)'!F7 -> 27628072 | E8: 0 | F8: =D8+E8 -> 27628072 | G8: FC本部17,373千円・決済会社10,255千円で構成され、いずれも翌月回収。滞留債権は認められないため簿価評価
B9: 5 | C9: 土地（駐車場用地89.4㎡） | D9: ='BS(借方)'!F27 -> 2974400 | E9: 0 | F9: =D9+E9 -> 2974400 | G9: 路線価図・固定資産税評価証明が未受領のため簿価評価。簿価33千円/㎡であり大幅な含み損益は生じにくいと推察（要確認）
B10: 6 | C10: 建物附属設備・工具器具備品 | D10: ='BS(借方)'!F22+'BS(借方)'!F26 -> 50441845 | E10: 0 | F10: =D10+E10 -> 50441845 | G10: 減価償却内訳明細書により適正償却を確認。単独の換金価値は限定的だが事業継続を前提に簿価評価
B11: 7 | C11: 車両運搬具 | D11: ='BS(借方)'!F25 -> 1057574 | E11: 0 | F11: =D11+E11 -> 1057574 | G11: 事業用3台。中古車市場価値が簿価を上回る可能性があるが査定書が未受領のため簿価評価（要確認）
B12: 8 | C12: 差入保証金 | D12: ='BS(借方)'!F49 -> 27370600 | E12: 0 | F12: =D12+E12 -> 27370600 | G12: 賃貸借契約書が未受領で償却条項・返還条件が不明のため簿価評価。返還額への評価替えの余地がある（要確認）
B13: 9 | C13: 長期前払費用 | D13: ='BS(借方)'!F48 -> 1711860 | E13: 0 | F13: =D13+E13 -> 1711860 | G13: 内訳が未受領のため簿価評価。信用保証料等の前払であれば換金価値は認められず最大1,712千円の減額余地（要確認）
B14: 10 | C14: 未払費用 | D14: ='BS (貸方)'!F9 -> 20113617 | E14: 0 | F14: =D14+E14 -> 20113617 | G14: 賃金台帳では当月締・翌月25日払。11月分給与が未払計上されているか要確認。未計上であれば約10,000千円超の追加計上が必要
B15: 11 | C15: 賞与引当金 | D15: 0 | E15: 0 | F15: =D15+E15 -> 0 | G15: 賞与制度・支給実績が未確認のため未計上（要確認）
B16: 12 | C16: 退職給付引当金 | D16: 0 | E16: 0 | F16: =D16+E16 -> 0 | G16: 退職金規程が未受領のため未計上（要確認）
B17: 13 | C17: 役員退職慰労引当金 | D17: 0 | E17: 0 | F17: =D17+E17 -> 0 | G17: 役員退職慰労金規程が未受領のため未計上（要確認）
B18: 14 | C18: 資産除去債務 | D18: 0 | E18: 0 | F18: =D18+E18 -> 0 | G18: 店舗内装の原状回復義務。撤退2店舗の原状回復費用・違約金が未確認であり未計上（要確認）
B19: 15 | C19: 繰延税金資産 | D19: 0 | E19: 0 | F19: =D19+E19 -> 0 | G19: 繰越欠損金を有し課税所得の見込みが立たないため回収可能性を認めず、税効果は認識していない
C20: 評価差額 合計 | E20: =SUM(E5:E19) -> -47150004

Sheet 年買法
C2: (単位：千円) | H2: (単位：千円) | M2: (単位：千円)
B3: 2025年11月期 | C3: 金額 | F3: 2023年11月期 | G3: 2024年11月期 | H3: 2025年11月期 | J3: 営業権倍率 | K3: x1 | L3: x2 | M3: x3
B4: 簿価純資産額 | C4: ='BS (貸方)'!F50 -> -14056815 | E4: 簿価営業利益 | F4: =PLハイライト!D8 -> 2341140 | G4: =PLハイライト!E8 -> 3022100 | H4: =PLハイライト!F8 -> -19551737 | J4: 時価純資産 | K4: =C7 -> -61206819
B5: 修正額 | C5: ='修正BS(貸方) '!D50 -> -47150004 | E5: 修正額 | F5: =PLハイライト!D17 -> 8856000 | G5: =PLハイライト!E17 -> 20449000 | H5: =PLハイライト!F17 -> 19883868 | J5: 営業権 | K5: =H10*1 -> 6234903.5 | L5: =H10*2 -> 12469807 | M5: =H10*3 -> 18704711
B6: 税効果 | C6: 0 | E6: 修正後営業利益 | F6: =SUM(F4:F5) -> 11197140 | G6: =SUM(G4:G5) -> 23471100 | H6: =SUM(H4:H5) -> 332131 | J6: 想定株式価値 | K6: =K4+K5 -> -54971915 | L6: =K4+L5 -> -48737012 | M6: =K4+M5 -> -42502108
B7: 時価純資産 | C7: =SUM(C4:C6) -> -61206819 | E7: 税考慮額 | F7: =-F6*0.34 -> -3807027.6 | G7: =-G6*0.34 -> -7980174 | H7: =-H6*0.34 -> -112924.54
E8: 修正後税考慮後営業利益 | F8: =SUM(F6:F7) -> 7390112.4 | G8: =SUM(G6:G7) -> 15490926 | H8: =SUM(H6:H7) -> 219206.46
G10: 基準営業利益 | H10: =(H8*0.5+G8*0.3+F8*0.2) -> 6234903.5
B12: ※基準営業利益＝修正後税考慮後営業利益の加重平均（直近期50%・前期30%・前々期20%）。※税考慮額は実効税率34%。※営業権倍率1〜3倍は国内中小企業M&Aのボリュームゾーン。 ※繰越欠損金を有し課税所得の見込みが立たないため、評価差額に対する繰延税金資産は認識していない（税効果ゼロ）。 ※修正額は企業概要書の調整項目合計と同一（販管費の修正＋経常的雑収入）。修正PLでは雑収入を営業外収益に計上しているため、修正PL上の修正後営業利益との差額は当該雑収入である（修正PL 61行目の橋渡しを参照）。

Sheet EV EBITDAマルチプル
C2: (単位：千円) | H2: (単位：千円) | M2: (単位：千円)
B3: 2025年11月期 | C3: 金額 | F3: 2023年11月期 | G3: 2024年11月期 | H3: 2025年11月期 | J3: マルチプル倍率 | K3: x3 | L3: x4 | M3: x5
B4: キャッシュライク | C4: =ネットキャッシュ!C13 -> 10140492 | E4: 簿価営業利益 | F4: =PLハイライト!D8 -> 2341140 | G4: =PLハイライト!E8 -> 3022100 | H4: =PLハイライト!F8 -> -19551737 | J4: EV（EBITDA×倍率） | K4: =H10*3 -> 48575970 | L4: =H10*4 -> 64767960 | M4: =H10*5 -> 80959950
B5: デットライク | C5: =ネットキャッシュ!F13 -> 199666270 | E5: 修正額 | F5: =PLハイライト!D17 -> 8856000 | G5: =PLハイライト!E17 -> 20449000 | H5: =PLハイライト!F17 -> 19883868 | J5: 非流動性ディスカウント（不適用） | K5: 0 | L5: 0 | M5: 0
B6: ネットキャッシュ | C6: =C4-C5 -> -189525778 | E6: 修正後営業利益 | F6: =SUM(F4:F5) -> 11197140 | G6: =SUM(G4:G5) -> 23471100 | H6: =SUM(H4:H5) -> 332131 | J6: =B6 -> ネットキャッシュ | K6: =C6 -> -189525778
E7: 減価償却費 | F7: =PLハイライト!D15 -> 3911003 | G7: =PLハイライト!E15 -> 9294598 | H7: =PLハイライト!F15 -> 6349173 | J7: 想定株式価値 | K7: =SUM(K4:K6) -> -140949808 | L7: =SUM(L4:L5)+K6 -> -124757818 | M7: =SUM(M4:M5)+K6 -> -108565828
E8: 修正後EBITDA | F8: =SUM(F6:F7) -> 15108143 | G8: =SUM(G6:G7) -> 32765698 | H8: =SUM(H6:H7) -> 6681304
G10: 基準EBITDA | H10: =(H8*0.5+G8*0.3+F8*0.2) -> 16191990
B12: ※基準EBITDA＝修正後EBITDAの加重平均（直近期50%・前期30%・前々期20%）。※修正後EBITDA＝修正後営業利益＋減価償却費であり、企業概要書の調整後EBITDAと同一である。 ※当社フォーマットの評価書は非流動性ディスカウントを適用しない（想定株式価値＝EV＋ネットキャッシュ）。過去の評価書と算定方法を揃えるため、EVへの30%控除は行っていない。

Sheet 参照企業
E2: (単位：千円)
B3: 企業名 | C3: 所在地 | D3: 事業内容 | E3: EV/EVIDA倍率
B4: 未選定：ペット関連小売・生体販売を主要事業とする国内上場会社を想定したが、対象会社は債務超過かつ売上規模が大きく異なるため個社の倍率をそのまま適用できない。EV/EBITDA倍率は中小企業M&Aの一般的レンジ3〜5倍を保守的に適用した。

Sheet IM→

Sheet 会社概要
B2: 項目 | C2: 内容
B3: 会社名 | C3: LUXAS株式会社［ラクサス］（法人番号 4200001038172） https://luxas.co.jp/ ※HPの有無・URLは要確認
B4: 本社所在地 | C4: 岐阜県大垣市青柳町3丁目227番地2 ※代表者自宅を法人が賃借（貸主：個人／年額1,000千円）
B5: その他拠点 | C5: 直営店舗8箇所（岐阜県3・三重県3・愛知県1・大阪府1）、 大垣管理センター、松阪管理センター ※2025年11月期「売上高等の事業所別内訳書」ベース
B6: 設立/創業 | C6: 2019年8月 個人事業として創業／2020年12月 法人設立（第5期）
B7: 資本金 | C7: 1,000千円
B8: 代表者 | C8: 代表取締役 淺野 ゆう子（1985年11月生）
B9: 株主 | C9: 淺野 ゆう子（100株／100%） ※株券不発行会社、譲渡制限規定あり（株主総会承認）、設立時から変更なし
B10: 事業内容 | C10: ペットショップ（生体販売・ペット用品販売）、トリミング、ペットホテル、 ペット保険代理店、セキュリティ機器販売
B11: 従業員数 | C11: 73名（役員1名、正社員20名、アルバイト53名）（2026年3月時点）
B12: 許認可等 | C12: 第一種動物取扱業許可（種別：販売／保管） 8事業所で取得
B13: 売上高 | C13: 558,390千円（2025年11月期）
... B15: 譲渡理由 | C15: 成長戦略（資本力・経営基盤のある企業グループ下での多店舗展開の加速）

Sheet 月次推移
B2: 進行期（2026年11月期）の月次推移 ※2025年12月〜2026年6月の7か月 | L2: (単位：千円)
B4: 科目 | C4: 2025年12月 | D4: 2026年1月 | E4: 2026年2月 | F4: 2026年3月 | G4: 2026年4月 | H4: 2026年5月 | I4: 2026年6月 | J4: 7か月累計 | K4: 前年同期比
B5: 生体売上高 | C5: 22574606 | D5: 33442487 | E5: 22793128 | F5: 19019717 | G5: 28992317 | H5: 21084603 | I5: 17210136 | J5: 165116994 | K5: 0.766
B6: サービス売上高 | C6: 4714428 | D6: 3832414 | E6: 4170949 | F6: 6225018 | G6: 4479559 | H6: 4229109 | I6: 5140210 | J6: 32791687 | K6: 1.064
B7: 物販売上高 | C7: 14287821 | D7: 13883151 | E7: 10195384 | F7: 10657750 | G7: 11250432 | H7: 11822698 | I7: 9147526 | J7: 81244762 | K7: 0.823
B8: 売上高 | C8: 41576855 | D8: 51158052 | E8: 37159461 | F8: 35902485 | G8: 44722308 | H8: 37136410 | I8: 31497872 | J8: 279153443 | K8: 0.809
B9: 売上原価 | C9: 17900039 | D9: 14911696 | E9: 11806779 | F9: 12608688 | G9: 18701224 | H9: 13950512 | I9: 14883308 | J9: 104762246 | K9: 0.776
B10: 売上総利益 | C10: 23676816 | D10: 36246356 | E10: 25352682 | F10: 23293797 | G10: 26021084 | H10: 23185898 | I10: 16614564 | J10: 174391197 | K10: 0.83
B11: 販売費及び一般管理費 | C11: 25194150 | D11: 22839389 | E11: 24295519 | F11: 21910128 | G11: 23403974 | H11: 28337808 | I11: 21773380 | J11: 167754348 | K11: 0.854
B12: 従業員給与 | C12: 10067885 | D12: 9790228 | E12: 8675740 | F12: 8542407 | G12: 9024380 | H12: 9411319 | I12: 8667767 | J12: 64179726 | K12: 0.852
B13: 役員報酬 | C13: 900000 | D13: 900000 | E13: 900000 | F13: 900000 | G13: 900000 | H13: 900000 | I13: 900000 | J13: 6300000 | K13: 0.75
B14: 法定福利費 | C14: -2239979 | D14: -1018412 | E14: 1800348 | F14: 898788 | G14: 1564034 | H14: 925093 | I14: 849044 | J14: 2778916 | K14: 0.842
B15: 広告宣伝費 | C15: 5535073 | D15: 1650296 | E15: 1652013 | F15: 1542200 | G15: 1639660 | H15: 1645766 | I15: 1498200 | J15: 15163208 | K15: 0.757
B16: ロイヤリティ | C16: 2404710 | D16: 2515078 | E16: 1953088 | F16: 1561732 | G16: 2085840 | H16: 1964492 | I16: 1708071 | J16: 14193011 | K16: 0.77
... B20: 経常利益 | C20: -1740228 | D20: 13600028 | E20: 844037 | F20: 1090302 | G20: 2408982 | H20: -5309341 | I20: -5079634 | J20: 5814146 | K20: 0.456
B21: 特別損失（棚卸資産廃棄損） | F21: 44000000 | J21: 44000000
B22: 当期純利益 | C22: -1740228 | D22: 13600028 | E22: 843063 | F22: -42909710 | G22: 2408982 | H22: -5309341 | I22: -5079695 | J22: -38186901
B25: 【月末の主要B/S科目】
B26: 科目 | C26: 2025年11月末（決算） | D26: 2025年12月末 | E26: 2026年1月末 | F26: 2026年2月末 | G26: 2026年3月末 | H26: 2026年4月末 | I26: 2026年5月末 | J26: 2026年6月末
B27: 現預金 | C27: 10140492 | D27: 9990901 | E27: 12439434 | F27: 14515681 | G27: 17521538 | H27: 16141151 | I27: 12887032 | J27: 14792479
B28: 売掛金 | C28: 27628072 | D28: 27267195 | E28: 31199518 | F28: 18780393 | G28: 18020457 | H28: 24307518 | I28: 24346668 | J28: 16678270
B29: 棚卸資産 | C29: 106167284 | D29: 106167284 | E29: 106167284 | F29: 106167284 | G29: 61939187 | H29: 61939187 | I29: 61939187 | J29: 58595785
B30: 有形固定資産 | C30: 54658019 | D30: 54658019 | E30: 54658019 | F30: 57133019 | G30: 57133019 | H30: 57133019 | I30: 57133019 | J30: 57570649
B31: 差入保証金 | C31: 27370600 | D31: 27346800 | E31: 27323000 | F31: 27299200 | G31: 25275400 | H31: 25251600 | I31: 25227800 | J31: 25204000
B32: 資産合計 | C32: 235385177 | D32: 231433689 | E32: 237673930 | F32: 229809036 | G32: 185931105 | H32: 190067739 | I32: 186801853 | J32: 178109330
B33: 買掛金 | C33: 9202412 | D33: 12352915 | E33: 9304332 | F33: 6279047 | G33: 7069055 | H33: 9650090 | I33: 8631808 | J33: 7003448
B34: 未払消費税等 | C34: 11784100 | D34: 11784100 | E34: 11447391 | F34: 10438091 | G34: 10438091 | H34: 8438091 | I34: 8438091 | J34: 7438091
B35: 長期借入金 | C35: 191858000 | D35: 191858000 | E35: 191858000 | F35: 191858000 | G35: 191858000 | H35: 191858000 | I35: 191858000 | J35: 191858000
B36: 役員借入金 | C36: 7565770 | D36: 5630657 | E36: 4788319 | F36: 3560039 | G36: 3041783 | H36: 4958985 | I36: 3523411 | J36: 3402888
B37: 負債合計 | C37: 249441992 | D37: 247230732 | E37: 239870945 | F37: 231162988 | G37: 230194767 | H37: 231922419 | I37: 233965874 | J37: 230353046
B38: 純資産合計 | C38: -14056815 | D38: -15797043 | E38: -2197015 | F38: -1353952 | G38: -44263662 | H38: -41854680 | I38: -47164021 | J38: -52243716
B41: ※出所：勘定科目残高推移表 2025年12月〜2026年6月（2026年9月18日出力）。「2025年11月末（決算）」列のみ第5期決算報告書。 ※2026年6月26日出力の旧試算表（2026年4月まで）から、2026年1月〜4月の月次が一部修正されている（販管費・営業外費用・役員借入金等）。本シートは新試算表を正としている。 ※進行期の月次には減価償却費が計上されていない（販管費に「減価償却費」の科目が立っていない）。2025年11月期の通期実績は6,349千円であり、通期ではその分だけ営業利益が減少する見込み（要確認）。 ※法定福利費は2025年12月・2026年1月がマイナス計上となっており、年末調整・社会保険料の精算処理の影響と推察（仮説・要確認）。7か月累計2,779千円は2025年11月期の通期15,295千円に比して低く、期中の未計上分が下期に乗る可能性がある。 ※2026年5月の租税公課4,969千円は、自動車税・固定資産税等の年次課税と推察（仮説）。同月の営業損失の主因。 ※2026年3月に棚卸資産廃棄損44,000千円を計上（他勘定振替高△44,000千円）。棚卸表の「本社32,000千円＋バックヤード12,000千円」に一致する（棚卸明細シート参照）。 ※長期借入金は月次では期首残高のまま据え置かれており、返済額は決算時に一括計上されていると推察（要確認）。

Sheet PLハイライト
G2: (単位：千円)
C3: － | D3: 2023年11月期 | E3: 2024年11月期 | F3: 2025年11月期 | G3: 進行期(7か月TB)
B4: 売上高 | C4: =PL!C11 -> 0 | D4: =PL!E11 -> 474428321 | E4: =PL!G11 -> 539035019 | F4: =PL!I11 -> 558389734 | G4: =PL!K11 -> 279153443
B5: 前期比 | C5: - | D5: =IFERROR(D4/C4,"") | E5: =IFERROR(E4/D4,"") -> 1.136178 | F5: =IFERROR(F4/E4,"") -> 1.0359062 | G5: -
B6: 売上総利益 | C6: =PL!C18 -> 0 | D6: =PL!E18 -> 292378634 | E6: =PL!G18 -> 342931150 | F6: =PL!I18 -> 330024486 | G6: =PL!K18 -> 174391197
B7: 利益率 | C7: =IFERROR(C6/C4,"") | D7: =IFERROR(D6/D4,"") -> 0.61627568 | E7: =IFERROR(E6/E4,"") -> 0.63619457 | F7: =IFERROR(F6/F4,"") -> 0.59102893 | G7: =IFERROR(G6/G4,"") -> 0.62471448
B8: 営業利益 | C8: =PL!C20 -> 0 | D8: =PL!E20 -> 2341140 | E8: =PL!G20 -> 3022100 | F8: =PL!I20 -> -19551737 | G8: =PL!K20 -> 6636849
B9: 利益率 | C9: =IFERROR(C8/C4,"") | D9: =IFERROR(D8/D4,"") -> 0.0049346548 | E9: =IFERROR(E8/E4,"") -> 0.0056065003 | F9: =IFERROR(F8/F4,"") -> -0.035014499 | G9: =IFERROR(G8/G4,"") -> 0.023774914
B10: 経常利益 | C10: =PL!C37 -> 0 | D10: =PL!E37 -> 2528371 | E10: =PL!G37 -> 3109637 | F10: =PL!I37 -> -18575356 | G10: =PL!K37 -> 5814146
B11: 利益率 | C11: =IFERROR(C10/C4,"") | D11: =IFERROR(D10/D4,"") -> 0.0053293003 | E11: =IFERROR(E10/E4,"") -> 0.0057688961 | F11: =IFERROR(F10/F4,"") -> -0.033265934 | G11: =IFERROR(G10/G4,"") -> 0.020827778
B12: 税引後当期純利益 | C12: =PL!C57 -> 0 | D12: =PL!E57 -> 1634217 | E12: =PL!G57 -> 974362 | F12: =PL!I57 -> -20358547 | G12: =PL!K57 -> -38186901
B13: 利益率 | C13: =IFERROR(C12/C4,"") | D13: =IFERROR(D12/D4,"") -> 0.0034446025 | E13: =IFERROR(E12/E4,"") -> 0.0018076043 | F13: =IFERROR(F12/F4,"") -> -0.036459386 | G13: =IFERROR(G12/G4,"") -> -0.13679538
B15: 減価償却費 | C15: 0 | D15: =SGA!E15 -> 3911003 | E15: =SGA!G15 -> 9294598 | F15: =SGA!I15 -> 6349173 | G15: =SGA!K15 -> 0
B17: 調整項目 合計 | C17: =SUM(C18:C27) -> 0 | D17: =SUM(D18:D27) -> 8856000 | E17: =SUM(E18:E27) -> 20449000 | F17: =SUM(F18:F27) -> 19883868 | G17: =SUM(G18:G27) -> 0
B18: 役員報酬（退任予定）＿淺野ゆう子氏 | D18: 9600000 | E18: 9600000 | F18: 14400000
B19: 役員報酬（派遣想定）＿後任代表者（現行と同水準） | D19: -9600000 | E19: -9600000 | F19: -14400000
B20: 社会保険料 | C20: =(C18+C19)*0.15 -> 0 | D20: =(D18+D19)*0.15 -> 0 | E20: =(E18+E19)*0.15 -> 0 | F20: =(F18+F19)*0.15 -> 0 | G20: =(G18+G19)*0.15 -> 0
B21: 支払保険料＿事業関連性の低い生命保険料 | D21: 696000 | E21: 1599000 | F21: 1224000
B22: 接待交際費＿適正水準4,000千円との差額 | D22: 4453000 | E22: 6230000 | F22: 4218000
B23: 会議費
B24: 非経常的販管費＿非事業用車両リース料 | D24: 2386000 | E24: 3154000 | F24: 5604000
B25: 経常的営業外収益＿雑収入のうち社員割引 | D25: 1321000 | E25: 635000 | F25: 654868
B26: 現場責任者人件費の役員報酬への振替 | D26: 0 | E26: 8831000 | F26: 8183000
B28: 削減可能な会議費
B29: 削減可能な雑費
B30: 買取予定不動産の賃料
B37: 調整後EBITDA | C37: =C8+C15+C17 -> 0 | D37: =D8+D15+D17 -> 15108143 | E37: =E8+E15+E17 -> 32765698 | F37: =F8+F15+F17 -> 6681304 | G37: =G8+G15+G17 -> 6636849
B39: 調整後EBITDA（過去3期平均） | D39: =AVERAGE(D37:F37) -> 18185048
B40: 調整後EBITDA（直近2期平均） | D40: =AVERAGE(E37:F37) -> 19723501
B42: 【調整の考え方】M&A実行後に継続的に発生しない費用を戻し入れ、継続的に必要となる費用を控除。代表者（淺野ゆう子氏）は引継完了後に退任、現場責任者（淺野崇氏）が役員に就任し現行と同水準の役員報酬を受ける前提とした。進行期は月次で減価償却費が未計上のため調整後EBITDAは算定していない（要確認）。

Sheet BSハイライト
F2: (単位：千円)
B3: =PLハイライト!F3 -> 2025年11月期 | H3: 進行期（2026年6月末TB） | K3: 進行期（2026年6月末TB）
B4: 流動資産 | C4: =SUM(C5:C11) -> 150113194 | E4: 流動負債 | F4: =SUM(F5:F11) -> 47672202 | H4: 流動資産 | I4: ='BS(借方)'!G5 -> 92091317 | K4: 流動負債 | L4: ='BS (貸方)'!G5 -> 33413938
B5: 現預金 | C5: 10140492 | E5: 買掛金 | F5: 9202412 | H5: 現預金 | I5: ='BS(借方)'!G6 -> 14792479 | K5: 買掛金 | L5: ='BS (貸方)'!G6 -> 7003448
B6: 売掛金 | C6: 27628072 | E6: 未払金 | F6: 714227 | H6: 売掛金 | I6: ='BS(借方)'!G7 -> 16678270 | K6: 短期借入金 | L6: ='BS (貸方)'!G7 -> 3153
B7: 在庫 | C7: 106167284 | E7: 未払費用 | F7: 20113617 | H7: 在庫 | I7: ='BS(借方)'!G8+'BS(借方)'!G9 -> 58595785 | K7: 未払金 | L7: ='BS (貸方)'!G8 -> 0
B8: 前払費用 | C8: 3991637 | E8: 未払法人税等 | F8: 242500 | H8: 前払費用 | I8: ='BS(借方)'!G11 -> 392743 | K8: 未払費用 | L8: ='BS (貸方)'!G9 -> 9578501
B9: 未収入金 | C9: 30800 | E9: 未払消費税等 | F9: 11784100 | H9: 仮払金 | I9: ='BS(借方)'!G14 -> 1677040 | K9: 未払消費税等 | L9: ='BS (貸方)'!G11 -> 7438091
B10: 未収還付法人税等 | C10: 504909 | E10: 預り金 | F10: 2391530 | H10: その他 | I10: ='BS(借方)'!G15 -> -45000 | K10: 預り金 | L10: ='BS (貸方)'!G12 -> 1600194
B11: 仮払金 | C11: 1650000 | E11: カード未払金 | F11: 3223816 | H11: 固定資産 | I11: ='BS(借方)'!G20 -> 86018013 | K11: カード未払金 | L11: ='BS (貸方)'!G13 -> 7790551
B12: 固定資産 | C12: =SUM(C13:C20) -> 85271983 | E12: 固定負債 | F12: =SUM(F13:F15) -> 201769790 | H12: 建物附属設備 | I12: ='BS(借方)'!G23 -> 44397084 | K12: 固定負債 | L12: ='BS (貸方)'!G18 -> 196939108
B13: 建物 | C13: 44397084 | E13: 長期借入金 | F13: 191858000 | H13: 構築物 | I13: ='BS(借方)'!G24 -> 2475000 | K13: 長期借入金 | L13: ='BS (貸方)'!G19 -> 191858000
B14: 車両運搬具 | C14: 1057574 | E14: 役員借入金 | F14: 7565770 | H14: 車両運搬具 | I14: ='BS(借方)'!G25 -> 1495204 | K14: 役員借入金 | L14: ='BS (貸方)'!G20 -> 3402888
B15: 工具器具及び備品 | C15: 6044761 | E15: 長期未払金 | F15: 2346020 | H15: 工具器具及び備品 | I15: ='BS(借方)'!G26 -> 6044761 | K15: 長期未払金 | L15: ='BS (貸方)'!G21 -> 1678220
B16: 土地 | C16: 2974400 | E16: 負債合計 | F16: =F4+F12 -> 249441992 | H16: 土地 | I16: ='BS(借方)'!G27 -> 2974400 | K16: 負債合計 | L16: ='BS (貸方)'!G25 -> 230353046
B17: 長期前払費用 | C17: 1711860 | H17: 長期前払費用 | I17: ='BS(借方)'!G48 -> 1711860
B18: 差入保証金 | C18: 27370600 | E18: 資本金 | F18: 1000000 | H18: 差入保証金 | I18: ='BS(借方)'!G49 -> 25204000 | K18: 資本金 | L18: ='BS (貸方)'!G36 -> 1000000
B19: 営業権 | C19: 1500004 | E19: 利益剰余金 | F19: -15056815 | H19: 営業権 | I19: ='BS(借方)'!G50 -> 1500004 | K19: 利益剰余金 | L19: ='BS (貸方)'!G43 -> -53243716
B20: その他 | C20: 215700 | E20: 純資産合計 | F20: =SUM(F18:F19) -> -14056815 | H20: その他 | I20: ='BS(借方)'!G28+'BS(借方)'!G47 -> 215700 | K20: 純資産合計 | L20: ='BS (貸方)'!G50 -> -52243716
B21: 資産合計 | C21: =C4+C12 -> 235385177 | E21: 負債・純資産合計 | F21: =F16+F20 -> 235385177 | H21: 資産合計 | I21: ='BS(借方)'!G61 -> 178109330 | K21: 負債・純資産合計 | L21: ='BS (貸方)'!G51 -> 178109330
F23: =F21=C21 -> 1 | H23: ※進行期は2026年6月末（7か月）の試算表ベース。決算整理（減価償却・棚卸評価等）は未了。

Sheet 店舗別売上
B2: 店舗別売上高（決算書「売上高等の事業所別内訳書」ベース） | L2: (単位：千円)
B4: № | C4: 事業所名 | D4: 業態 | E4: 所在地 | F4: 2023年11月期 | G4: 構成比 | H4: 2024年11月期 | I4: 構成比 | J4: 2025年11月期 | K4: 構成比 | L4: 進行期7か月 (25/12〜26/6) | M4: 構成比 | N4: 期末棚卸高 (25/11期) | O4: 期末従事 員数(名)
B5: 1 | C5: 本社（セキュリティ事業） | D5: 非店舗 | E5: 岐阜県大垣市 | F5: 12996480 | G5: =IFERROR(F5/F$17,"") -> 0.02739398 | H5: 8908600 | I5: =IFERROR(H5/H$17,"") -> 0.016526941 | J5: 5508219 | K5: =IFERROR(J5/J$17,"") -> 0.0098644704 | L5: 2944810 | M5: =IFERROR(L5/L$17,"") -> 0.010549073 | O5: 3
B6: 2 | C6: 本社（サービス・物販） | D6: 非店舗 | E6: 岐阜県大垣市 | F6: 15610820 | G6: =IFERROR(F6/F$17,"") -> 0.032904486 | H6: 18397207 | I6: =IFERROR(H6/H$17,"") -> 0.034129892 | J6: 22125782 | K6: =IFERROR(J6/J$17,"") -> 0.039624264 | L6: 13650127 | M6: =IFERROR(L6/L$17,"") -> 0.048898294 | N6: 44000000
B7: 3 | C7: ワンラブ カインズホーム明和店 | D7: FC／インショップ | E7: 三重県多気郡明和町 | F7: 65416318 | G7: =IFERROR(F7/F$17,"") -> 0.13788451 | H7: 67267220 | I7: =IFERROR(H7/H$17,"") -> 0.12479193 | J7: 37216460 | K7: =IFERROR(J7/J$17,"") -> 0.066649614 | L7: 25108810 | M7: =IFERROR(L7/L$17,"") -> 0.089946267 | N7: 21818576 | O7: 9
B8: 4 | C8: ワンラブ バローミタス伊勢店 | D8: FC／インショップ | E8: 三重県伊勢市 | F8: 88527370 | G8: =IFERROR(F8/F$17,"") -> 0.18659799 | H8: 75571000 | I8: =IFERROR(H8/H$17,"") -> 0.14019683 | J8: 66609459 | K8: =IFERROR(J8/J$17,"") -> 0.11928847 | L8: 40221277 | M8: =IFERROR(L8/L$17,"") -> 0.14408304 | N8: 2985224 | O8: 8
B9: 5 | C9: ワンラブ ホームセンターバロー久居店 | D9: FC／インショップ | E9: 三重県津市 | F9: 66886986 | G9: =IFERROR(F9/F$17,"") -> 0.14098439 | H9: 62981034 | I9: =IFERROR(H9/H$17,"") -> 0.11684034 | J9: 57326532 | K9: =IFERROR(J9/J$17,"") -> 0.10266401 | L9: 33840444 | M9: =IFERROR(L9/L$17,"") -> 0.12122524 | N9: 2814741 | O9: 7
B10: 6 | C10: ワンラブ アクアウォーク大垣店 ※2026年2月撤退 | D10: FC／インショップ | E10: 岐阜県大垣市 | F10: 50138278 | G10: =IFERROR(F10/F$17,"") -> 0.10568146 | H10: 43305102 | I10: =IFERROR(H10/H$17,"") -> 0.080338198 | J10: 38021413 | K10: =IFERROR(J10/J$17,"") -> 0.068091175 | L10: 6112430 | M10: =IFERROR(L10/L$17,"") -> 0.021896309 | N10: 3045850 | O10: 6
B11: 7 | C11: ワンラブ ペットプラザ岐阜店 ※2026年1月撤退 | D11: FC／インショップ | E11: 岐阜県岐阜市 | F11: 32770375 | G11: =IFERROR(F11/F$17,"") -> 0.069073395 | H11: 20636067 | I11: =IFERROR(H11/H$17,"") -> 0.038283351 | J11: 18944680 | K11: =IFERROR(J11/J$17,"") -> 0.033927343 | L11: 1842692 | M11: =IFERROR(L11/L$17,"") -> 0.0066010004 | N11: 2459389 | O11: 6
B12: 8 | C12: ワンラブ ドン・キホーテ緑店 | D12: FC／インショップ | E12: 愛知県名古屋市緑区 | G12: =IFERROR(F12/F$17,"") -> 0 | H12: 19793315 | I12: =IFERROR(H12/H$17,"") -> 0.036719906 | J12: 51761466 | K12: =IFERROR(J12/J$17,"") -> 0.092697739 | L12: 36963203 | M12: =IFERROR(L12/L$17,"") -> 0.13241178 | N12: 3747447 | O12: 6
B13: 9 | C13: ワンラブ コメリパワー中志段味店 ※2024年6月譲渡 | D13: FC／インショップ | E13: 愛知県名古屋市守山区 | F13: 43554994 | G13: =IFERROR(F13/F$17,"") -> 0.091805215 | H13: 29765016 | I13: =IFERROR(H13/H$17,"") -> 0.055219077 | K13: =IFERROR(J13/J$17,"") -> 0 | M13: =IFERROR(L13/L$17,"") -> 0
B14: 10 | C14: おっきなもふもふ応援隊 岐阜総本店 | D14: 大型犬専門／路面店 | E14: 岐阜県羽島郡岐南町 | F14: 98526700 | G14: =IFERROR(F14/F$17,"") -> 0.20767458 | H14: 157755564 | I14: =IFERROR(H14/H$17,"") -> 0.29266292 | J14: 118491175 | K14: =IFERROR(J14/J$17,"") -> 0.21220156 | L14: 60022946 | M14: =IFERROR(L14/L$17,"") -> 0.21501775 | N14: 6566330 | O14: 11
B15: 11 | C15: おっきなもふもふ応援隊 大阪総本店 | D15: 大型犬専門／路面店 | E15: 大阪府茨木市 | G15: =IFERROR(F15/F$17,"") -> 0 | H15: 34654894 | I15: =IFERROR(H15/H$17,"") -> 0.064290617 | J15: 142384548 | K15: =IFERROR(J15/J$17,"") -> 0.25499134 | L15: 58446704 | M15: =IFERROR(L15/L$17,"") -> 0.20937125 | N15: 8579727 | O15: 10
B16: 12 | C16: デザイナーズワン株式会社（仕入先預け在庫） | D16: － | E16: 愛知県一宮市 | G16: =IFERROR(F16/F$17,"") -> 0 | I16: =IFERROR(H16/H$17,"") -> 0 | K16: =IFERROR(J16/J$17,"") -> 0 | M16: =IFERROR(L16/L$17,"") -> 0 | N16: 10000000
C17: 合計 | F17: =SUM(F5:F16) -> 474428321 | G17: － | H17: =SUM(H5:H16) -> 539035019 | I17: － | J17: =SUM(J5:J16) -> 558389734 | K17: － | L17: =SUM(L5:L16) -> 279153443 | M17: － | N17: =SUM(N5:N16) -> 106017284 | O17: =SUM(O5:O16) -> 66
B19: ※出所：第3期〜第5期 決算報告書「売上高等の事業所別内訳書」、および店舗別（部門別）勘定科目残高推移表 2025年12月〜2026年6月。各期のPL売上高（474,428／539,035／558,390／279,153千円）と一致することを確認済。 ※コメリパワー中志段味店は2024年6月に譲渡。ドン・キホーテ緑店は2024年7月、おっきなもふもふ応援隊 大阪総本店は2024年10月に開店。 ※ペットプラザ岐阜店は2026年1月、アクアウォーク大垣店は2026年2月をもって売上計上が終了しており、両店が撤退した2店舗である（店舗別試算表および従業員名簿の在籍状況により確認）。2026年3月以降の稼働店舗は6店舗。 ※本社（サービス・物販）の進行期13,650千円は月額約195万円で計上されており、ペット保険の代理店手数料と推察される（仮説・要確認）。

Sheet 店舗別損益
B2: 店舗別（部門別）損益 進行期7か月累計（2025年12月〜2026年6月） | K2: (単位：千円)
B4: № | C4: 部門 | D4: 業態 | E4: 状況 | F4: 売上高 | G4: 構成比 | H4: 売上総利益 | I4: 粗利率 | J4: 販管費 | K4: 営業利益 | L4: 営業利益率
B5: 1 | C5: ワンラブ カインズホーム明和店 | D5: FC／インショップ | E5: 稼働中 | F5: 25108810 | G5: =IFERROR(F5/$F$17,"") -> 0.089946267 | H5: 18583119 | I5: =IFERROR(H5/$F5,"") -> 0.74010353 | J5: 18976890 | K5: -393771 | L5: =IFERROR(K5/$F5,"") -> -0.015682583
B6: 2 | C6: ワンラブ バローミタス伊勢店 | D6: FC／インショップ | E6: 稼働中 | F6: 40221277 | G6: =IFERROR(F6/$F$17,"") -> 0.14408304 | H6: 31467687 | I6: =IFERROR(H6/$F6,"") -> 0.78236419 | J6: 14171474 | K6: 17296213 | L6: =IFERROR(K6/$F6,"") -> 0.43002645
B7: 3 | C7: ワンラブ ホームセンターバロー久居店 | D7: FC／インショップ | E7: 稼働中 | F7: 33840444 | G7: =IFERROR(F7/$F$17,"") -> 0.12122524 | H7: 26675472 | I7: =IFERROR(H7/$F7,"") -> 0.78827193 | J7: 13333435 | K7: 13342037 | L7: =IFERROR(K7/$F7,"") -> 0.39426306
B8: 4 | C8: ワンラブ ドン・キホーテ緑店 | D8: FC／インショップ | E8: 稼働中 | F8: 36963203 | G8: =IFERROR(F8/$F$17,"") -> 0.13241178 | H8: 31415730 | I8: =IFERROR(H8/$F8,"") -> 0.84991904 | J8: 13900076 | K8: 17515654 | L8: =IFERROR(K8/$F8,"") -> 0.47386732
B9: 5 | C9: おっきなもふもふ応援隊 岐阜総本店 | D9: 大型犬専門／路面店 | E9: 稼働中 | F9: 60022946 | G9: =IFERROR(F9/$F$17,"") -> 0.21501775 | H9: 48925762 | I9: =IFERROR(H9/$F9,"") -> 0.81511764 | J9: 22723774 | K9: 26201988 | L9: =IFERROR(K9/$F9,"") -> 0.43653286
B10: 6 | C10: おっきなもふもふ応援隊 大阪総本店 | D10: 大型犬専門／路面店 | E10: 稼働中 | F10: 58446704 | G10: =IFERROR(F10/$F$17,"") -> 0.20937125 | H10: 49077529 | I10: =IFERROR(H10/$F10,"") -> 0.83969712 | J10: 22221605 | K10: 26855924 | L10: =IFERROR(K10/$F10,"") -> 0.45949424
C11: 【稼働6店舗 小計】 | D11: － | E11: － | F11: 254603384 | G11: =IFERROR(F11/$F$17,"") -> 0.91205532 | H11: 206145299 | I11: =IFERROR(H11/$F11,"") -> 0.80967227 | J11: 105327254 | K11: 100818045 | L11: =IFERROR(K11/$F11,"") -> 0.39598077
B12: 7 | C12: ワンラブ アクアウォーク大垣店 | D12: FC／インショップ | E12: 2026年2月に撤退 | F12: 6112430 | G12: =IFERROR(F12/$F$17,"") -> 0.021896309 | H12: 859374 | I12: =IFERROR(H12/$F12,"") -> 0.14059449 | J12: 1914906 | K12: -1055532 | L12: =IFERROR(K12/$F12,"") -> -0.17268615
B13: 8 | C13: ワンラブ ペットプラザ岐阜店 | D13: FC／インショップ | E13: 2026年1月に撤退 | F13: 1842692 | G13: =IFERROR(F13/$F$17,"") -> 0.0066010004 | H13: -1274658 | I13: =IFERROR(H13/$F13,"") -> -0.69173687 | J13: 1755945 | K13: -3030603 | L13: =IFERROR(K13/$F13,"") -> -1.6446606
C14: セキュリティ事業 | D14: 非店舗 | E14: － | F14: 2944810 | G14: =IFERROR(F14/$F$17,"") -> 0.010549073 | H14: 1614698 | I14: =IFERROR(H14/$F14,"") -> 0.54831993 | J14: 0 | K14: 1614698 | L14: =IFERROR(K14/$F14,"") -> 0.54831993
C15: 大垣管理センター | D15: 非店舗 | E15: 2026年2月に閉鎖 | F15: 0 | G15: =IFERROR(F15/$F$17,"") -> 0 | H15: 0 | I15: =IFERROR(H15/$F15,"") | J15: 113163 | K15: -113163 | L15: =IFERROR(K15/$F15,"")
C16: 共通部門（本社） | D16: 非店舗 | E16: － | F16: 13650127 | G16: =IFERROR(F16/$F$17,"") -> 0.048898294 | H16: -32953516 | I16: =IFERROR(H16/$F16,"") -> -2.4141545 | J16: 58643080 | K16: -91596596 | L16: =IFERROR(K16/$F16,"") -> -6.7103109
C17: 【合計】 | D17: － | E17: － | F17: 279153443 | G17: =IFERROR(F17/$F$17,"") -> 1 | H17: 174391197 | I17: =IFERROR(H17/$F17,"") -> 0.62471448 | J17: 167754348 | K17: 6636849 | L17: =IFERROR(K17/$F17,"") -> 0.023774914
B19: ※出所：店舗別（部門別）勘定科目残高推移表 2025年12月〜2026年6月（2026年9月18日出力）。部門別の合計は全社の試算表（売上高279,153千円・営業利益6,637千円）と一致することを確認済。 ※店舗別の営業利益は本社費を配賦する前の「店舗貢献利益」であり、本社費等は共通部門に一括計上されている。 ※共通部門の売上13,650千円は、月額約195万円で計上されているサービス売上高であり、ペット保険の代理店手数料と推察される（仮説・要確認）。 ※共通部門の売上原価46,604千円は、本社で仕入れた商品（92,274千円のうち40,994千円）および外注費5,610千円が各店舗へ振り替えられずに共通部門に残っているものと推察される（仮説・要確認）。このため店舗別の粗利・営業利益は実力値より過大に表示されている可能性があり、解釈には留意を要する。 ※明和店の販管費には松阪管理センターの人件費が含まれていると推察される（棚卸表でも松阪管理センターの在庫19,669千円が明和店に含めて計上されている）。 ※大垣管理センターは2026年2月以降、費用のマイナス計上（振替）のみとなっている。

Sheet 店舗別費用
B2: 店舗別（部門別）販管費の内訳 進行期7か月累計（2025年12月〜2026年6月） | P2: (単位：千円)
B4: № | C4: 部門 | D4: 状況 | E4: 売上高 | F4: 従業員給与 | G4: 法定福利費 | H4: 人件費計 | I4: 人件費率 | J4: 役員報酬 | K4: ロイヤリティ | L4: 地代家賃 | M4: 広告宣伝費 | N4: 支払手数料 | O4: その他 | P4: 販管費計 | Q4: 販管費率
B5: 1 | C5: ワンラブ カインズホーム明和店 | D5: 稼働中 | E5: 25108810 | F5: 11070780 | G5: -1054506 | H5: =F5+G5 -> 10016274 | I5: =IFERROR(H5/$E5,"") -> 0.39891472 | J5: 0 | K5: 3467132 | L5: 0 | M5: 2310000 | N5: 655922 | O5: =P5-(F5+G5+J5+K5+L5+M5+N5) -> 2527562 | P5: 18976890 | Q5: =IFERROR(P5/$E5,"") -> 0.75578612
B6: 2 | C6: ワンラブ バローミタス伊勢店 | D6: 稼働中 | E6: 40221277 | F6: 8234159 | G6: -967806 | H6: =F6+G6 -> 7266353 | I6: =IFERROR(H6/$E6,"") -> 0.18065943 | J6: 0 | K6: 4826556 | L6: 0 | M6: 1540000 | N6: 110550 | O6: =P6-(F6+G6+J6+K6+L6+M6+N6) -> 428015 | P6: 14171474 | Q6: =IFERROR(P6/$E6,"") -> 0.35233774
B7: 3 | C7: ワンラブ ホームセンターバロー久居店 | D7: 稼働中 | E7: 33840444 | F7: 7922592 | G7: -1058795 | H7: =F7+G7 -> 6863797 | I7: =IFERROR(H7/$E7,"") -> 0.20282822 | J7: 0 | K7: 4399257 | L7: 0 | M7: 1540000 | N7: 155900 | O7: =P7-(F7+G7+J7+K7+L7+M7+N7) -> 374481 | P7: 13333435 | Q7: =IFERROR(P7/$E7,"") -> 0.39400887
B8: 4 | C8: ワンラブ ドン・キホーテ緑店 | D8: 稼働中 | E8: 36963203 | F8: 6677386 | G8: -709546 | H8: =F8+G8 -> 5967840 | I8: =IFERROR(H8/$E8,"") -> 0.16145354 | J8: 0 | K8: 0 | L8: 5407317 | M8: 770000 | N8: 1043292 | O8: =P8-(F8+G8+J8+K8+L8+M8+N8) -> 711627 | P8: 13900076 | Q8: =IFERROR(P8/$E8,"") -> 0.37605172
B9: 5 | C9: おっきなもふもふ応援隊 岐阜総本店 | D9: 稼働中 | E9: 60022946 | F9: 13862144 | G9: -1525287 | H9: =F9+G9 -> 12336857 | I9: =IFERROR(H9/$E9,"") -> 0.20553568 | J9: 0 | K9: 0 | L9: 5160083 | M9: 2459820 | N9: 2012786 | O9: =P9-(F9+G9+J9+K9+L9+M9+N9) -> 754228 | P9: 22723774 | Q9: =IFERROR(P9/$E9,"") -> 0.37858478
B10: 6 | C10: おっきなもふもふ応援隊 大阪総本店 | D10: 稼働中 | E10: 58446704 | F10: 11461033 | G10: -1133275 | H10: =F10+G10 -> 10327758 | I10: =IFERROR(H10/$E10,"") -> 0.17670386 | J10: 0 | K10: 0 | L10: 6935929 | M10: 2073500 | N10: 2100129 | O10: =P10-(F10+G10+J10+K10+L10+M10+N10) -> 784289 | P10: 22221605 | Q10: =IFERROR(P10/$E10,"") -> 0.38020288
C11: 【稼働6店舗 小計】 | D11: － | E11: =SUM(E5:E10) -> 254603384 | F11: =SUM(F5:F10) -> 59228094 | G11: =SUM(G5:G10) -> -6449215 | H11: =F11+G11 -> 52778879 | I11: =IFERROR(H11/$E11,"") -> 0.20729842 | J11: =SUM(J5:J10) -> 0 | K11: =SUM(K5:K10) -> 12692945 | L11: =SUM(L5:L10) -> 17503329 | M11: =SUM(M5:M10) -> 10693320 | N11: =SUM(N5:N10) -> 6078579 | O11: =P11-(F11+G11+J11+K11+L11+M11+N11) -> 5580202 | P11: =SUM(P5:P10) -> 105327254 | Q11: =IFERROR(P11/$E11,"") -> 0.41369149
B12: 7 | C12: ワンラブ アクアウォーク大垣店 | D12: 2026年2月に撤退 | E12: 6112430 | F12: 1059512 | G12: -175480 | H12: =F12+G12 -> 884032 | I12: =IFERROR(H12/$E12,"") -> 0.14462857 | J12: 0 | K12: 916864 | L12: 30800 | M12: 0 | N12: 203 | O12: =P12-(F12+G12+J12+K12+L12+M12+N12) -> 83007 | P12: 1914906 | Q12: =IFERROR(P12/$E12,"") -> 0.31328064
B13: 8 | C13: ワンラブ ペットプラザ岐阜店 | D13: 2026年1月に撤退 | E13: 1842692 | F13: 1093462 | G13: -97371 | H13: =F13+G13 -> 996091 | I13: =IFERROR(H13/$E13,"") -> 0.54056294 | J13: 0 | K13: 583202 | L13: 0 | M13: 0 | N13: 0 | O13: =P13-(F13+G13+J13+K13+L13+M13+N13) -> 176652 | P13: 1755945 | Q13: =IFERROR(P13/$E13,"") -> 0.95292377
C14: セキュリティ事業 | D14: － | E14: 2944810 | F14: 0 | G14: 0 | H14: =F14+G14 -> 0 | I14: =IFERROR(H14/$E14,"") -> 0 | J14: 0 | K14: 0 | L14: 0 | M14: 0 | N14: 0 | O14: =P14-(F14+G14+J14+K14+L14+M14+N14) -> 0 | P14: 0 | Q14: =IFERROR(P14/$E14,"") -> 0
C15: 大垣管理センター | D15: 2026年2月に閉鎖 | E15: 0 | F15: 348658 | G15: -251815 | H15: =F15+G15 -> 96843 | I15: =IFERROR(H15/$E15,"") | J15: 0 | K15: 0 | L15: 0 | M15: 0 | N15: 0 | O15: =P15-(F15+G15+J15+K15+L15+M15+N15) -> 16320 | P15: 113163 | Q15: =IFERROR(P15/$E15,"")
C16: 共通部門（本社） | D16: － | E16: 13650127 | F16: 2450000 | G16: 9752797 | H16: =F16+G16 -> 12202797 | I16: =IFERROR(H16/$E16,"") -> 0.89396948 | J16: 6300000 | K16: 0 | L16: 2345000 | M16: 4469888 | N16: 848821 | O16: =P16-(F16+G16+J16+K16+L16+M16+N16) -> 32476574 | P16: 58643080 | Q16: =IFERROR(P16/$E16,"") -> 4.2961564
C17: 【合計】 | D17: － | E17: =E5+E6+E7+E8+E9+E10+E12+E13+E14+E15+E16 -> 279153443 | F17: =F5+F6+F7+F8+F9+F10+F12+F13+F14+F15+F16 -> 64179726 | G17: =G5+G6+G7+G8+G9+G10+G12+G13+G14+G15+G16 -> 2778916 | H17: =F17+G17 -> 66958642 | I17: =IFERROR(H17/$E17,"") -> 0.23986321 | J17: =J5+J6+J7+J8+J9+J10+J12+J13+J14+J15+J16 -> 6300000 | K17: =K5+K6+K7+K8+K9+K10+K12+K13+K14+K15+K16 -> 14193011 | L17: =L5+L6+L7+L8+L9+L10+L12+L13+L14+L15+L16 -> 19879129 | M17: =M5+M6+M7+M8+M9+M10+M12+M13+M14+M15+M16 -> 15163208 | N17: =N5+N6+N7+N8+N9+N10+N12+N13+N14+N15+N16 -> 6927603 | O17: =P17-(F17+G17+J17+K17+L17+M17+N17) -> 38332755 | P17: =P5+P6+P7+P8+P9+P10+P12+P13+P14+P15+P16 -> 167754348 | Q17: =IFERROR(P17/$E17,"") -> 0.60093956
B19: ※出所：店舗別（部門別）勘定科目残高推移表 2025年12月〜2026年6月（2026年9月18日出力・11部門）。従業員給与・法定福利費・役員報酬・ロイヤリティ・地代家賃・広告宣伝費・支払手数料の各科目について、11部門の合計が全社PL（64,179,726／2,778,916／6,300,000／14,193,011／19,879,129／15,163,208／6,927,603円）と一致することを確認済。 ※「その他」は販管費計から上記各科目を控除した差額（旅費交通費・厚生費・リース料・通信費・水道光熱費・租税公課・接待交際費・保険料・備品消耗品費・管理諸費・雑費等）。 ※法定福利費は本社（共通部門）に一括計上したうえで各店舗へマイナス計上（振替）する処理がとられており、店舗側は各店ともマイナス残高となる。したがって店舗別の販管費は社会保険料負担分だけ過少に表示されている点に留意を要する（店舗計△6,449千円）。 ※ロイヤリティはワンラブFC加盟店のうち明和・伊勢・久居・大垣・岐阜の5店のみが負担し、ドン・キホーテ緑店は負担がない一方で地代家賃5,407千円（売上高比14.6%）を負担している。緑店のみ契約形態が異なる理由は要確認。 ※広告宣伝費はFC加盟店で月額220千円（緑店は110千円）の定額計上。路面店2店は月額300〜360千円程度で、こちらも概ね定額である。

Sheet 棚卸明細
B2: 棚卸資産の内訳（2025年12月1日時点＝2025年11月期末） | J2: (単位：千円／税抜)
B4: 拠点 | C4: 生体：アクア | D4: 生体：小動物 | E4: 生体：犬猫 | F4: 生体 小計 | G4: 物販 | H4: 合計 | I4: 決算書の計上額 | J4: 備考
B5: ワンラブ カインズホーム明和店 | C5: 140028 | D5: 47670 | E5: 1295000 | F5: 1482698 | G5: 666878 | H5: 2149576 | I5: 21818576 | J5: 決算書上は松阪管理センター分19,669,000円を含めて計上
B6: 松阪管理センター | F6: 19669000 | H6: 19669000 | J6: 明和店に含めて計上
B7: ワンラブ バローミタス伊勢店 | C7: 58416 | D7: 184513 | E7: 1645000 | F7: 1887929 | G7: 1097295 | H7: 2985224 | I7: 2985224
B8: ワンラブ ホームセンターバロー久居店 | E8: 1860000 | F8: 1860000 | G8: 954741 | H8: 2814741 | I8: 2814741
B9: ワンラブ アクアウォーク大垣店 | E9: 1655000 | F9: 1655000 | G9: 1390850 | H9: 3045850 | I9: 3045850 | J9: 2026年2月に撤退
B10: ワンラブ ペットプラザ岐阜店 | E10: 1152000 | F10: 1152000 | G10: 1307389 | H10: 2459389 | I10: 2459389 | J10: 2026年1月に撤退
B11: ワンラブ ドン・キホーテ緑店 | E11: 2125000 | F11: 2125000 | G11: 1514434 | H11: 3639434 | I11: 3747447 | J11: 決算書上は中志段味店分108,013円を含めて計上
B12: ワンラブ コメリパワー中志段味店 | C12: 0 | D12: 0 | E12: 0 | F12: 0 | G12: 108013 | H12: 108013 | J12: 2024年6月に譲渡済
B13: おっきなもふもふ応援隊 岐阜総本店 | E13: 1620000 | F13: 1620000 | G13: 4946330 | H13: 6566330 | I13: 6566330
B14: おっきなもふもふ応援隊 大阪総本店 | E14: 1818000 | F14: 1818000 | G14: 6761727 | H14: 8579727 | I14: 8579727
B15: 【店舗合計】 | F15: 33269627 | G15: 18747657 | H15: 52017284
B16: 本社 | F16: 24000000 | G16: 8000000 | H16: 32000000 | J16: 2026年3月に廃棄損を計上
B17: バックヤード | F17: 0 | G17: 12000000 | H17: 12000000 | J17: 2026年3月に廃棄損を計上
B18: 外部保管分 | F18: 10000000 | G18: 0 | H18: 10000000 | I18: 10000000 | J18: 仕入先デザイナーズワン㈱への預け在庫
B19: 【全社合計】 | F19: 67269627 | G19: 38747657 | H19: 106017284
B22: ※出所：対象会社作成「棚卸表 2025年12月1日時点（最終版）」。全社合計106,017,284円は第5期決算書の商品残高と一致する。 ※本社32,000千円＋バックヤード12,000千円＝44,000千円は、進行期の2026年3月に棚卸資産廃棄損として全額を特別損失に計上している。 ※外部保管分10,000千円は仕入先デザイナーズワン株式会社（代表者の親族が経営）への預け在庫。2026年6月末の商品残高58,446千円のうち同額が含まれているかは要確認。 ※「決算書の計上額」は第5期決算報告書「売上高等の事業所別内訳書」の期末棚卸高。松阪管理センターは明和店に、中志段味店は緑店に含めて計上されている。

Sheet 取引先
L2: (単位：千円)
B3: № | C3: 得意先 | D3: 取引内容 | E3: 本社所在地 | F3: 業種等 | G3: 2023年11月期 | I3: 2024年11月期 | K3: 2025年11月期 | M3: 備考
G4: 売上高 | H4: 構成比 | I4: 売上高 | J4: 構成比 | K4: 売上高 | L4: 構成比
B5: 1 | C5: 一般個人顧客（店舗販売） | D5: 生体・ペット用品・トリミング・ペットホテル・ペット保険 | E5: － | F5: 個人 | G5: 461431841 | H5: =G5/G$16 -> 0.97260602 | I5: 530126419 | J5: =I5/I$16 -> 0.98347306 | K5: 552881515 | L5: =K5/K$16 -> 0.99013553 | M5: 店舗での個人向け販売。得意先別の売上集計は行っていないため、事業所別内訳書の合計から下記セキュリティ事業を控除して算定
B6: 2 | C6: セキュリティ機器販売先 | D6: セキュリティ機器の販売・保守 | E6: － | F6: 法人・個人 | G6: 12996480 | H6: =G6/G$16 -> 0.02739398 | I6: 8908600 | J6: =I6/I$16 -> 0.016526941 | K6: 5508219 | L6: =K6/K$16 -> 0.0098644704 | M6: 代表者配偶者（淺野崇氏）が個人で開始した事業を法人が承継。現在は一部顧客にのみ対応で実質休眠
B7: 3 | H7: =G7/G$16 -> 0 | J7: =I7/I$16 -> 0 | L7: =K7/K$16 -> 0
B8: 4 | H8: =G8/G$16 -> 0 | J8: =I8/I$16 -> 0 | L8: =K8/K$16 -> 0
B9: 5 | H9: =G9/G$16 -> 0 | J9: =I9/I$16 -> 0 | L9: =K9/K$16 -> 0
B10: 6 | H10: =G10/G$16 -> 0 | J10: =I10/I$16 -> 0 | L10: =K10/K$16 -> 0
B11: 7 | H11: =G11/G$16 -> 0 | J11: =I11/I$16 -> 0 | L11: =K11/K$16 -> 0
B12: 8 | H12: =G12/G$16 -> 0 | J12: =I12/I$16 -> 0 | L12: =K12/K$16 -> 0
B13: 9 | H13: =G13/G$16 -> 0 | J13: =I13/I$16 -> 0 | L13: =K13/K$16 -> 0
B14: 10 | H14: =G14/G$16 -> 0 | J14: =I14/I$16 -> 0 | L14: =K14/K$16 -> 0
C15: － | H15: =G15/G$16 -> 0 | J15: =I15/I$16 -> 0 | L15: =K15/K$16 -> 0
C16: 合計 | G16: =SUM(G5:G15) -> 474428321 | H16: - | I16: =SUM(I5:I15) -> 539035019 | J16: - | K16: =SUM(K5:K15) -> 558389734 | L16: -
B18: ※本件は個人向け販売が売上の大宗を占め、得意先別売上高は把握していない（要確認）。2025年11月期末の売上債権先は ㈲ワンラブ 17,373千円／りそなカード㈱ 5,910千円／シティックスカード㈱ 3,109千円／PayPay㈱ 821千円／ポケットカード㈱ 415千円（計27,628千円）。

Sheet 仕入先
K2: (単位：千円)
B3: № | C3: 仕入先 | D3: 仕入内容 | E3: 本社所在地 | F3: 2023年11月期 | H3: 2024年11月期 | J3: 2025年11月期 | L3: 備考
F4: 仕入高 | G4: 構成比 | H4: 仕入高 | I4: 構成比 | J4: 仕入高 | K4: 構成比
B5: 1 | C5: ジャペル株式会社 | D5: 生体・飼育用品等 | E5: 愛知県春日井市 | F5: 91166000 | G5: =F5/F$16 -> 0.49586085 | H5: 109451000 | I5: =H5/H$16 -> 0.49569975 | J5: 107140000 | K5: =J5/J$16 -> 0.58789315 | L5: 肥料・飼料卸売業。仕入高の約6割を占める最大の仕入先
B6: 2 | C6: 有限会社ワンラブ | D6: 生体・飼育用品等 | E6: 愛知県名古屋市 | F6: 44927000 | G6: =F6/F$16 -> 0.24436237 | H6: 50158000 | I6: =H6/H$16 -> 0.22716383 | J6: 29244000 | K6: =J6/J$16 -> 0.16046619 | L6: フランチャイズ本部。仕入に関する取引契約を締結。生体はワンラブがオークション会場で仕入れ、マイクロチップ埋込・ワクチン等の処理後に当社へ供給
B7: 3 | C7: 個人ブリーダー（複数） | D7: 生体 | E7: － | G7: =F7/F$16 -> 0 | H7: 9184000 | I7: =H7/H$16 -> 0.041594015 | J7: 17561000 | K7: =J7/J$16 -> 0.096359825 | L7: 大型犬専門店の展開に伴い直接仕入を拡大
B8: 4 | C8: デザイナーズワン株式会社 | D8: 生体 | E8: 愛知県一宮市 | F8: 10500000 | G8: =F8/F$16 -> 0.057110533 | H8: 12280000 | I8: =H8/H$16 -> 0.05561569 | J8: 9400000 | K8: =J8/J$16 -> 0.051579202 | L8: 代表者の親族が経営する会社。当社が営業権を保有（簿価1,500千円）。大垣・松阪の両管理センターで同社の生体管理を受託
B9: 5 | G9: =F9/F$16 -> 0 | I9: =H9/H$16 -> 0 | K9: =J9/J$16 -> 0
B10: 6 | G10: =F10/F$16 -> 0 | I10: =H10/H$16 -> 0 | K10: =J10/J$16 -> 0
B11: 7 | G11: =F11/F$16 -> 0 | I11: =H11/H$16 -> 0 | K11: =J11/J$16 -> 0
B12: 8 | G12: =F12/F$16 -> 0 | I12: =H12/H$16 -> 0 | K12: =J12/J$16 -> 0
B13: 9 | G13: =F13/F$16 -> 0 | I13: =H13/H$16 -> 0 | K13: =J13/J$16 -> 0
B14: 10 | G14: =F14/F$16 -> 0 | I14: =H14/H$16 -> 0 | K14: =J14/J$16 -> 0
C15: その他約50社（個人含む） | F15: 37261000 | G15: =F15/F$16 -> 0.20266625 | H15: 39728000 | I15: =H15/H$16 -> 0.17992672 | J15: 18899000 | K15: =J15/J$16 -> 0.10370163
C16: 合計 | F16: =SUM(F5:F15) -> 183854000 | G16: - | H16: =SUM(H5:H15) -> 220801000 | I16: - | J16: =SUM(J5:J15) -> 182244000 | K16: -
B18: ※出所：対象会社提供の既存会社説明資料（対象会社提供の総勘定元帳より「商品仕入高」を集計）。PL上の商品仕入高（183,854／220,801／182,243千円）と一致することを確認済。

Sheet 外注先
L2: (単位：千円)
B3: № | C3: 外注先 | D3: 外注内容 | E3: 本社所在地 | F3: 業種等 | G3: 2023年11月期 | I3: 2024年11月期 | K3: 2025年11月期 | M3: 備考
G4: 外注費 | H4: 構成比 | I4: 外注費 | J4: 構成比 | K4: 外注費 | L4: 構成比
B5: 1 | C5: 要確認（内訳未受領） | D5: トリミング・生体管理等の外部委託と推察 | E5: － | F5: － | G5: 29627732 | H5: =G5/G$16 -> 1 | I5: 31465971 | J5: =I5/I$16 -> 1 | K5: 25058151 | L5: =K5/K$16 -> 1 | M5: 売上原価の「外注費」総額。取引先別の内訳は未受領のため要確認
B6: 2 | H6: =G6/G$16 -> 0 | J6: =I6/I$16 -> 0 | L6: =K6/K$16 -> 0
B7: 3 | H7: =G7/G$16 -> 0 | J7: =I7/I$16 -> 0 | L7: =K7/K$16 -> 0
B8: 4 | H8: =G8/G$16 -> 0 | J8: =I8/I$16 -> 0 | L8: =K8/K$16 -> 0
B9: 5 | H9: =G9/G$16 -> 0 | J9: =I9/I$16 -> 0 | L9: =K9/K$16 -> 0
B10: 6 | H10: =G10/G$16 -> 0 | J10: =I10/I$16 -> 0 | L10: =K10/K$16 -> 0
B11: 7 | H11: =G11/G$16 -> 0 | J11: =I11/I$16 -> 0 | L11: =K11/K$16 -> 0
B12: 8 | H12: =G12/G$16 -> 0 | J12: =I12/I$16 -> 0 | L12: =K12/K$16 -> 0
B13: 9 | H13: =G13/G$16 -> 0 | J13: =I13/I$16 -> 0 | L13: =K13/K$16 -> 0
B14: 10 | H14: =G14/G$16 -> 0 | J14: =I14/I$16 -> 0 | L14: =K14/K$16 -> 0
C15: － | H15: =G15/G$16 -> 0 | J15: =I15/I$16 -> 0 | L15: =K15/K$16 -> 0
C16: 合計 | G16: =SUM(G5:G15) -> 29627732 | H16: - | I16: =SUM(I5:I15) -> 31465971 | J16: - | K16: =SUM(K5:K15) -> 25058151 | L16: -

Sheet 株主
E2: (単位：千円)
B3: № | C3: 氏名 | D3: 役職 | E3: 役員報酬 （2025年11月期） | F3: 保有株式数 | G3: 保有割合 | H3: 備考
B5: 1 | C5: 淺野 ゆう子 | D5: 代表取締役 | E5: 14400000 | F5: 100 | G5: =F5/$F$15 -> 1 | H5: 本件依頼者。引継完了後、退任予定
B6: 2 | G6: =F6/$F$15 -> 0
B7: 3 | G7: =F7/$F$15 -> 0
B8: 4 | G8: =F8/$F$15 -> 0
B9: 5 | G9: =F9/$F$15 -> 0
B10: 6 | G10: =F10/$F$15 -> 0
B11: 7 | G11: =F11/$F$15 -> 0
B12: 8 | G12: =F12/$F$15 -> 0
B13: 9 | G13: =F13/$F$15 -> 0
B14: 10 | G14: =F14/$F$15 -> 0
C15: 合計 | E15: =SUM(E5:E14) -> 14400000 | F15: =SUM(F5:F14) -> 100 | G15: =F15/$F$15 -> 1
B17: ※株券不発行会社。譲渡制限規定あり（株主総会承認）。設立（2020年12月）以降、株主の変動なし。

Sheet 取締役
F2: (単位：千円)
B3: № | C3: 氏名 | D3: 役職 | E3: 代表者との関係 | F3: 役員報酬 （2025年11月期） | G3: 業務範囲 | H3: 備考
B5: 1 | C5: 淺野 ゆう子 | D5: 代表取締役 | E5: 本人 | F5: 14400000 | G5: 経理全般、金融機関対応 | H5: 引継完了後、退任予定
B6: 2
B7: 3
B8: 4
B9: 5
B10: 6
B11: 7
B12: 8
B13: 9
B14: 10
C15: 合計 | F15: =SUM(F5:F14) -> 14400000
B17: ※取締役会・監査役はいずれも非設置。役員は代表取締役1名のみ。 ※現場責任者の淺野 崇氏（代表者の配偶者・1980年10月生）は役員ではなく従業員（2025年11月期 給与7,000千円）。経営業務・人材育成・店舗管理を担い、ドン・キホーテ緑店および大垣管理センターの動物取扱責任者を兼務するキーパーソン。本件は既知で、譲渡後の継続関与を前提としている（要確認）。

Sheet 従業員
B4: № | C4: イニシャル | D4: 雇用形態 | E4: 性別 | F4: 年齢 （歳） | G4: 勤続年数 | H4: 部署・店舗 | I4: 役職 | J4: 備考
B5: 1 | C5: 淺野 ゆう子 | D5: 役員 | E5: 女 | F5: 40 | G5: － | H5: 本社 | I5: 代表取締役 | J5: 経理全般・金融機関対応
B6: 2 | C6: 淺野 崇 | D6: 役員 | E6: 男 | F6: 45 | G6: － | H6: 本社 | I6: 現場責任者 | J6: 経営業務・人材育成・店舗管理。緑店・大垣管理センターの動物取扱責任者を兼務
B7: 3 | C7: H.Y | D7: 正社員 | E7: 男 | F7: 26 | G7: 1年0か月 | H7: ワンラブ カインズホーム明和店 | I7: － | J7: －
B8: 4 | C8: T.M | D8: 正社員 | E8: 女 | F8: 23 | G8: 1年0か月 | H8: ワンラブ カインズホーム明和店 | I8: － | J8: －
B9: 5 | C9: A.N | D9: 正社員 | E9: 女 | F9: 21 | G9: 0年6か月 | H9: ワンラブ カインズホーム明和店 | I9: － | J9: －
B10: 6 | C10: W.A | D10: アルバイト | E10: 女 | F10: 29 | G10: 1年7か月 | H10: ワンラブ カインズホーム明和店 | I10: － | J10: －
B11: 7 | C11: K.R | D11: アルバイト | E11: 女 | F11: 25 | G11: 1年4か月 | H11: ワンラブ カインズホーム明和店 | I11: － | J11: －
B12: 8 | C12: M.C | D12: アルバイト | E12: 女 | F12: 41 | G12: 0年7か月 | H12: ワンラブ カインズホーム明和店 | I12: － | J12: －
B13: 9 | C13: N.M | D13: 正社員 | E13: 女 | F13: 31 | G13: 6年5か月 | H13: ワンラブ バローミタス伊勢店 | I13: － | J13: －
B14: 10 | C14: O.T | D14: 正社員 | E14: 女 | F14: 63 | G14: 5年9か月 | H14: ワンラブ バローミタス伊勢店 | I14: － | J14: －
B15: 11 | C15: O.M | D15: アルバイト | E15: 女 | F15: 51 | G15: 6年5か月 | H15: ワンラブ バローミタス伊勢店 | I15: － | J15: －
B16: 12 | C16: T.A | D16: アルバイト | E16: 女 | F16: 32 | G16: 6年5か月 | H16: ワンラブ バローミタス伊勢店 | I16: － | J16: －
... B53: 49 | C53: I.M | D53: アルバイト | E53: 女 | F53: 34 | G53: 1年7か月 | H53: 松阪管理センター | I53: － | J53: －
B54: 合計 | C54: 49名
B56: ※出所：対象会社提供「従業員名簿（全従業員195名）」。退職年月日の入力がない49名を在籍者として集計。 ※イニシャルは役員2名のみ実名、その他は氏名フリガナの頭文字で匿名化している。氏名・生年月日・住所を含む個票を受領済であり、買手候補への開示は本ページの匿名化後の内容による。 ※年齢・勤続年数は2026年9月23日時点。役員2名は入社日の登録がないため勤続年数の集計対象外。 ※事業所単位の動物取扱責任者の配置状況は「部署・店舗別の集計」ブロックおよび概要書P.22に記載している。 ※役職は代表取締役・現場責任者以外に登録がない（要確認）。給与情報は本ページには記載していない。
B63: 【部署・店舗別の集計】
B64: 部署・店舗 | C64: 正社員等（名） | D64: アルバイト（名） | E64: 合計（名） | F64: 平均年齢（歳） | G64: 平均勤続年数（年）
B65: 本社 | C65: 2 | D65: 0 | E65: 2 | F65: 42.5
B66: ワンラブ カインズホーム明和店 | C66: 3 | D66: 3 | E66: 6 | F66: 27.5 | G66: 1
B67: ワンラブ バローミタス伊勢店 | C67: 2 | D67: 7 | E67: 9 | F67: 33.1 | G67: 3.6
B68: ワンラブ ホームセンターバロー久居店 | C68: 2 | D68: 3 | E68: 5 | F68: 32.4 | G68: 3.8
B69: ワンラブ ドン・キホーテ緑店 | C69: 1 | D69: 6 | E69: 7 | F69: 39.3 | G69: 1.8
B70: おっきなもふもふ応援隊 岐阜総本店 | C70: 1 | D70: 9 | E70: 10 | F70: 34 | G70: 1.4
B71: おっきなもふもふ応援隊 大阪総本店 | C71: 4 | D71: 4 | E71: 8 | F71: 28.4 | G71: 1.7
B72: 松阪管理センター | C72: 1 | D72: 1 | E72: 2 | F72: 36.5 | G72: 3.3
B73: 合計 | C73: =SUM(C65:C72) -> 16 | D73: =SUM(D65:D72) -> 33 | E73: =SUM(E65:E72) -> 49

Sheet 拠点(本社等)
B2: 所在地 | C2: 契約形態 | D2: 延床面積 (㎡) | E2: 月間賃料 (千円) | F2: 敷金 (千円) | G2: アクセス
B3: 岐阜県大垣市青柳町3丁目227番地2 （本社／登記上の本店・代表者自宅） | C3: 賃貸借 （貸主：個人） | E3: 83333 | G3: JR東海道本線「大垣駅」より車で約8分（要確認）
B4: 岐阜県大垣市上面4丁目17-1 （ペット出産用施設／大垣管理センターと推察） | C4: 賃貸借 （大東建託パートナーズ㈱） | E4: 47831 | G4: 要確認
B5: 三重県松阪市（松阪管理センター） ※明和店倉庫（貸主：ジェイリース㈱）と同一施設の可能性 | C5: 賃貸借 | E5: 201667 | G5: 要確認
B7: ※月間賃料は2025年11月期の年間支払賃借料（地代家賃等の内訳書）を12で除した参考値。延床面積・敷金・契約期間は未受領（要確認）。 ※本社は代表者の自宅であり、譲渡後の取扱い（賃貸借契約の継続／移転）は要確認。

Sheet 不動産(所有)
I1: 土地は0.7割戻し
B3: 事業所名 | C3: 内容 | D3: 所在地 地番・家屋番号 | E3: 面積 (㎡) | F3: 区分 ・構造 | G3: 所有（建築） 年月・事由 | H3: 前期末簿価 (千円) | I3: 時価 | J3: 固定資産税 評価額 | K3: 備考
B4: 大垣（非店舗） | C4: 土地）駐車場 | D4: 岐阜県大垣市南若森町字柳原227番3 | E4: 89.4 | F4: 宅地 | G4: 2025年11月期中に取得（要確認） | H4: 2974400 | I4: 要確認 | J4: 要確認 | K4: 固定資産税評価額が未受領のため時価は要確認。簿価＝2,974,400円
B7: ※法人所有の不動産は上記土地1筆（89.4㎡）のみ。建物の所有はなく、店舗はすべて賃借（インショップ／路面店）。 ※代表者個人が所有する事業用不動産は無し（対象会社提供の既存会社説明資料「希望条件」欄にて「該当無し」）。

Sheet 不動産(賃借) 
B3: 内容 | C3: 内容 | D3: 所在地 地番・家屋番号 | E3: 面積 (㎡) | F3: 契約内容 | G3: 貸主 | H3: 月間賃料 (千円) | I3: 敷金 (千円) | J3: 備考
B4: ワンラブ カインズホーム明和店 | C4: 建物）店舗（インショップ） | D4: 三重県多気郡明和町中村1236 カインズ明和 ペッツワンコーナー | F4: FC本部（㈲ワンラブ） からの転借 | G4: 有限会社ワンラブ | J4: 月額賃料は売上歩合（約15%）。COC条項あり。ロイヤリティに含めて支払
B5: ワンラブ バローミタス伊勢店 | C5: 建物）店舗（インショップ） | D5: 三重県伊勢市船江1-10-190 バローホームセンター ミタス伊勢店内 | F5: 2020年4月〜2030年4月 ※2年毎の更新 | G5: 有限会社ワンラブ | J5: 月額賃料は売上歩合（売上の11%）。COC条項あり
B6: ワンラブ ホームセンターバロー久居店 | C6: 建物）店舗（インショップ） | D6: 三重県津市戸木町7869-1 バローメガストア久居インター店内 | F6: 2020年12月〜2030年11月 ※2年毎の更新 | G6: 有限会社ワンラブ | J6: 月額賃料は売上歩合（売上の12%）。COC条項あり
B7: ワンラブ アクアウォーク大垣店 | C7: 建物）店舗（インショップ） | D7: 岐阜県大垣市林町6丁目80番21 | F7: 要確認 | G7: 有限会社ワンラブ | J7: 決算書上の事業所名は「ペッツビレッジ大垣店」（要確認）。別途、駐車場地代をユニー㈱へ年184.8千円支払
B8: ワンラブ ペットプラザ岐阜店 | C8: 建物）店舗（インショップ） | D8: 岐阜県岐阜市鶉町3丁目18 | F8: 要確認 | G8: 有限会社ワンラブ | J8: 月額賃料は売上歩合。COC条項の有無は要確認
B9: ワンラブ ドン・キホーテ緑店 | C9: 建物）店舗（インショップ） | D9: 愛知県名古屋市緑区鳥澄1-527 ドン・キホーテ緑店ペット館 | F9: 要確認 | G9: 日本商業施設株式会社 | H9: 749000 | I9: 2700000 | J9: 2025年11月期の年間家賃9,285千円。COC条項は確認中
B10: おっきなもふもふ応援隊 岐阜総本店 | C10: 建物）店舗（路面店） | D10: 岐阜県羽島郡岐南町徳田3-182-1 ザ・ビッグ岐南店1階 区画No.1 | E10: 395.38 | F10: 2023年4月〜2033年1月 定期建物賃貸借（更新なし） | G10: 株式会社カムテイ | H10: 640000 | I10: 2800000 | J10: 2025年11月期の年間家賃8,153千円。COC条項あり。再契約可否は要確認
B11: おっきなもふもふ応援隊 大阪総本店 | C11: 建物）店舗（路面店） | D11: 大阪府茨木市東太田1-4-48 ドン・キホーテ茨木店1階 | E11: 421.1 | F11: 2024年9月〜2027年11月 定期建物賃貸借（更新なし） | G11: 株式会社ドン・キホーテ （サブリース／転貸人：日本商業施設㈱） | H11: 920000 | I11: 3600000 | J11: 駐車場3台分を含む。2025年11月期の年間家賃10,756千円＋駐車場363千円。COC条項あり。再契約は協議のうえ可
B12: 本社 | C12: 建物）事務所（代表者自宅） | D12: 岐阜県大垣市青柳町3丁目227番地2 | F12: 要確認 | G12: 清水 満（個人） | H12: 83333 | J12: 2025年11月期の年間家賃1,000千円
B13: ペット出産用施設 | C13: 建物）その他 | D13: 岐阜県大垣市上面4丁目17-1 | F13: 要確認 | G13: 大東建託パートナーズ株式会社 | H13: 47831 | J13: 2025年11月期の年間家賃574千円
B14: 明和店倉庫 | C14: 建物）倉庫 | D14: 要確認 | F14: 要確認 | G14: ジェイリース株式会社 | H14: 201667 | J14: 2025年11月期の年間家賃2,420千円
B15: 従業員社宅 | C15: 建物）社宅 | D15: 要確認 | F15: 要確認 | G15: 株式会社エポスカード | H15: 42725 | J15: 2025年11月期の年間家賃513千円
B18: ※出所：2025年11月期「地代家賃等の内訳書」、対象会社提供の既存会社説明資料「店舗の状況1・2」。ワンラブFC店（明和・伊勢・久居・大垣・岐阜）の店舗使用料は売上歩合であり、販管費上は「ロイヤリティ」に計上されている。 ※面積・敷金・契約期間の空欄および「要確認」欄は資料未受領。COC条項（会社組織の変更・資本構成の重大な変更時の届出義務、合併時の契約解除可能）が①〜③および岐阜総本店・大阪総本店の契約書に存在するため、本件実行時の対応は要確認。

Sheet 設備
B2: № | C2: 科目 | D2: 資産名 | E2: 償却方法 | F2: 取得年 | G2: 取得月 | H2: 耐用年数 | I2: 取得原価 | J2: 期末帳簿価額 | K2: 文字
B3: 1 | C3: 建物附属設備 | D3: おっきなもふもふ大阪総本店 新装工事 | E3: 定額法 | F3: 2024年 | G3: 10月 | H3: 15年 | I3: 15950000 | J3: 14347025 | K3: 大阪総本店の出店に伴う内装一式
B4: 2 | C4: 建物附属設備 | D4: おっきなもふもふ大阪総本店 内装工事 | E4: 定額法 | F4: 2024年 | G4: 10月 | H4: 15年 | I4: 13000000 | J4: 12927417
B5: 3 | C5: 建物附属設備 | D5: 空調・照明設備 | E5: 定額法 | F5: 2024年 | G5: 7月 | H5: 15年 | I5: 8091127 | J5: 7368321
B6: 4 | C6: 建物附属設備 | D6: ドン・キホーテ緑店 改装工事（給排水・電気配管・照明・エアコン） | E6: 定額法 | F6: 2024年 | G6: 7月 | H6: 15年 | I6: 4319200 | J6: 4270969
B7: 5 | C7: 建物附属設備 | D7: 水回り工事・外装工事 | E7: 定額法 | F7: 2024年 | G7: 9月 | H7: 15年 | I7: 2158650 | J7: 2050179
B8: 6 | C8: 建物附属設備 | D8: 壁面サイン（金属製） | E8: 定額法 | F8: 2023年 | G8: 7月 | H8: 18年 | I8: 1945900 | J8: 1800607
B9: 7 | C9: 建物附属設備 | D9: おっきなもふもふ大阪総本店 サイン改修工事（金属製） | E9: 定額法 | F9: 2024年 | G9: 6月 | H9: 18年 | I9: 1760000 | J9: 1751787
B10: 8 | C10: 建物附属設備 | D10: ドン・キホーテ緑店 改装工事（電気工事） | E10: 定額法 | F10: 2024年 | G10: 8月 | H10: 15年 | I10: 1892000 | J10: 1839182
B11: 9 | C11: 建物附属設備 | D11: 電気設備・その他 | E11: 定額法 | F11: 2024年 | G11: 8月 | H11: 15年 | I11: 1040200 | J11: 1011162
B12: 10 | C12: 建物附属設備 | D12: おっきなもふもふ大阪総本店 外装工事（消防設備） | E12: 定額法 | F12: 2024年 | G12: 8月 | H12: 8年 | I12: 286000 | J12: 241313
B13: 11 | C13: 車両運搬具 | D13: ハイエースバン（トヨタ自動車㈱） | E13: 200%定率法 | F13: 2022年 | G13: 4月 | H13: 6年 | I13: 3168768 | J13: 731557
B14: 12 | C14: 車両運搬具 | D14: ピクシスバン（トヨタ自動車㈱） | E14: 200%定率法 | F14: 2023年 | G14: 7月 | H14: 4年 | I14: 1647234 | J14: 326016
B15: 13 | C15: 車両運搬具 | D15: プリウス（トヨタ自動車㈱） | E15: 200%定率法 | F15: 2020年 | G15: 12月 | H15: 6年 | I15: 1163000 | J15: 1 | K15: 備忘価額1円
B16: 14 | C16: 車両運搬具 | D16: BMW X7 xDrive40d M Sport（BMW AG） | E16: 200%定率法 | F16: 2023年 | G16: 10月 | H16: 6年 | I16: 13540645 | J16: 0 | K16: 2025年11月期中に㈱Luck Autoへ7,562千円で売却（固定資産売却損968千円）。対象会社提供の既存会社説明資料の「進行期に売却」との記載は要確認
B17: 15 | C17: 工具器具備品 | D17: おっきなもふもふ応援隊 展示用什器・陳列用ゲージ | E17: 200%定率法 | F17: 2024年 | G17: 7月 | H17: 8年 | I17: 2400000 | J17: 1612500
B18: 16 | C18: 工具器具備品 | D18: おっきなもふもふ大阪総本店 展示用什器・冷蔵庫 | E18: 200%定率法 | F18: 2024年 | G18: 9月 | H18: 8年 | I18: 3750000 | J18: 2695313
B19: 17 | C19: 工具器具備品 | D19: 複合機・通信機器（bizhub C287ほか）等 | E19: 200%定率法 | F19: 2022〜2024年 | G19: － | H19: 5年 | I19: 11769229 | J19: 1736948 | K19: 複数台。事務機器・通信機器・Airレジ等の合計
C20: 合計 | I20: =SUM(I3:I19) -> 87881953 | J20: =SUM(J3:J19) -> 54710297
B22: ※出所：2025年11月期「旧定率法・定額法による固定資産減価償却内訳明細書」。2025年11月期末の有形固定資産簿価は 建物附属設備44,397千円／車両運搬具1,058千円／工具器具備品6,045千円／土地2,974千円／その他184千円。 ※上記のほかリース車両3台（メルセデス・ベンツ GLE Coupe 月195千円・2024年9月〜60ヶ月、GLS 月212千円・2024年12月〜60ヶ月、日産オーラ 月60千円・2024年9月〜36ヶ月）。ベンツ2台は非事業用であり、本件実行後に解約予定。 ※一括償却資産：ドン・キホーテ緑店 ゲージ改修工事146千円、同 カーテン修繕工事130千円（いずれも2025年6月供用）。

Sheet 財務
B2: IMの財務詳細ページのデータは財務入力のシートから流用してください

Sheet その他
B2: 要確認事項・ネクストステップ
B4: № | C4: 区分 | D4: 論点 | E4: 現時点で確認できている事実／当社の仮説 | F4: 確認方法・依頼先
B5: 1 | C5: 【解決済】店舗 | D5: 2026年1月末に撤退した赤字2店舗の特定 | E5: 店舗別試算表により、ペットプラザ岐阜店が2026年1月、アクアウォーク大垣店が2026年2月をもって売上計上を終了していることを確認。従業員名簿でも両店および大垣管理センターに在籍者がおらず整合する。進行期7か月の両店合計は売上7,955千円・営業損失4,086千円 | F5: 解決（2026年9月受領資料）。撤退に伴う原状回復費用・違約金の有無は引き続き要確認
B6: 2 | C6: 【解決済】資産 | D6: 進行期に計上された棚卸資産廃棄損44,000千円の内容 | E6: 棚卸表（2025年12月1日時点）により、本社32,000千円＋バックヤード12,000千円＝44,000千円と一致することを確認 | F6: 解決（2026年9月受領資料）。廃棄に至った理由・処分方法・証憑は引き続き要確認
B7: 3 | C7: 財務 | D7: 2026年7月以降の月次試算表 | E7: 2025年12月〜2026年6月の7か月分を受領済。進行期7か月の売上279,153千円（前年同期比80.9%）、営業利益6,637千円（同48.2%）。通期の着地見込みを判断するには下期の実績が必要 | F7: 対象会社・顧問税理士へ依頼
B8: 4 | C8: 財務 | D8: 進行期に未計上の減価償却費・法定福利費 | E8: 進行期の月次には減価償却費の科目が立っていない（2025年11月期の通期実績6,349千円）。法定福利費も7か月累計2,778千円と通期実績15,295千円に比して低く、期中の未計上分が下期に乗る可能性がある | F8: 顧問税理士へ確認
B9: 5 | C9: 財務 | D9: 共通部門に残る仕入原価の配賦 | E9: 店舗別試算表では、本社で仕入れた商品40,994千円および外注費5,610千円が各店舗へ振り替えられず共通部門の売上原価に残っている（共通部門の売上原価46,604千円＝本社仕入40,994千円＋外注費5,610千円）。このため店舗別の粗利・営業利益は実力値より過大に表示されている可能性がある（仮説） | F9: 対象会社ヒアリング（本社仕入分の店舗への配分方法）
B10: 6 | C10: 財務 | D10: 2026年5月の租税公課4,969千円の内容 | E10: 5月単月で4,969千円を計上（7か月累計5,281千円の94%）。自動車税・固定資産税等の年次課税と推察（仮説）。同月の営業損失5,152千円の主因 | F10: 対象会社ヒアリング／総勘定元帳
B11: 7 | C11: 店舗収益 | D11: 明和店の販管費が売上に対して突出している要因 | E11: 進行期7か月で売上25,109千円に対し販管費18,977千円（75.6%）。他のFC加盟店（伊勢35.2%・久居39.4%・緑37.6%）と比べて著しく高く、松阪管理センターの人件費が明和店に含まれていると推察（棚卸表でも松阪管理センターの在庫19,669千円が明和店に含めて計上されている）（仮説） | F11: 対象会社ヒアリング（部門設定の考え方）
B12: 8 | C12: 収益モデル | D12: ペット保険の代理店手数料 | E12: 共通部門のサービス売上高が月額約195万円で計上されており、7か月累計13,650千円（年換算23,400千円）。対象会社提供の既存会社説明資料の「年間約19,000千円の保険収入」との聴取と概ね整合し、同手数料と推察（仮説） | F12: 対象会社ヒアリング／アイペット損保との代理店手数料明細
B13: 9 | C13: 【解決済】人事 | D13: 進行期を含む最新の従業員名簿 | E13: 名簿195名（2026年8月27日入社・同年8月31日退職まで収録）を受領。退職日の入力がない49名を在籍者として集計。2025年12月以降の入社44名・退職57名を織り込んでおり、足元の在籍実態を反映している | F13: 2026年9月受領の従業員名簿で確認済
B14: 10 | C14: 人事 | D14: 現場責任者 淺野崇氏の譲渡後の継続関与 | E14: 従業員名簿上、同氏の給与体系は「役員」・区分は「社員」。正常収益力の算定において同氏が役員に就任し現行と同水準の役員報酬を受ける前提を置いている。同氏はドン・キホーテ緑店および大垣管理センターの動物取扱責任者を兼務するキーパーソン | F14: 対象会社ヒアリング（意向確認）
B15: 11 | C15: 契約 | D15: フランチャイズ契約書および店舗賃貸借契約書 | E15: FC本部（㈲ワンラブ）との契約内容、店舗使用料の料率、COC条項の詳細が未確認。定期建物賃貸借（岐阜総本店2033年1月／大阪総本店2027年11月満了）の再契約見通しも要確認 | F15: 対象会社へ依頼（必要資料No.12・13）
B16: 12 | C16: 資産 | D16: 外部保管在庫10,000千円の実在性 | E16: 2025年11月期末の棚卸表に「外部保管分10,000千円（生体）」として計上。仕入先デザイナーズワン株式会社（代表者の親族が経営）への預け在庫と推察。2026年6月末の商品残高58,446千円に同額が含まれているかは未確認 | F16: 対象会社ヒアリング／預け在庫の残高証明
... B22: 18 | C22: プロセス関連（社内確認事項） | D22: 他社仲介の併走状況 | E22: 2025年11月期末の仮払金1,650千円は他社仲介への支払（着手金等）と認められる。本項は社内確認事項であり、買手候補への開示資料には記載しない | F22: 社内
B23: 19 | C23: 契約 | D23: ドン・キホーテ緑店のみロイヤリティの負担がない理由 | E23: 進行期7か月の部門別試算表では、ロイヤリティを負担しているのはワンラブFC加盟店のうち明和・伊勢・久居（および撤退2店）で、売上高比12.0〜13.8%。一方ドン・キホーテ緑店はロイヤリティの計上がなく、代わりに地代家賃5,407千円（同14.6%）を負担しており、同店のみ費用構造が異なる。FC本部からの転借か直接賃借かによって、COC条項や譲渡後の賃料負担が変わる | F23: フランチャイズ契約書／緑店の賃貸借契約書（必要資料No.18・19）

Sheet スケジュール(横)
B3: TODO | D3: 2月 | U3: 3月 | AZ3: 4月 | CE3: 5月
D4: 12 | E4: 13 | F4: 14 | G4: 15 | H4: 16 | I4: 17 | J4: 18 | K4: 19 | L4: 20 | M4: 21 | N4: 22 | O4: 23 | P4: 24 | Q4: 25 | R4: 26 | S4: 27 | T4: 28 | U4: 1 | V4: 2 | W4: 3 | X4: 4 | Y4: 5 | Z4: 6 | AA4: 7 | AB4: 8 | AC4: 9 | AD4: 10 | AE4: 11 | AF4: 12 | AG4: 13 | AH4: 14 | AI4: 15 | AJ4: 16 | AK4: 17 | AL4: 18 | AM4: 19 | AN4: 20 | AO4: 21 | AP4: 22 | AQ4: 23 | AR4: 24 | AS4: 25 | AT4: 26 | AU4: 27 | AV4: 28 | AW4: 29 | AX4: 30 | AY4: 31 | AZ4: 1 | BA4: 2 | BB4: 3 | BC4: 4 | BD4: 5 | BE4: 6 | BF4: 7 | BG4: 8 | BH4: 9 | BI4: 10 | BJ4: 11 | BK4: 12 | BL4: 13 | BM4: 14 | BN4: 15 | BO4: 16 | BP4: 17 | BQ4: 18 | BR4: 19 | BS4: 20 | BT4: 21 | BU4: 22 | BV4: 23 | BW4: 24 | BX4: 25 | BY4: 26 | BZ4: 27 | CA4: 28 | CB4: 29 | CC4: 30 | CD4: 31 | CE4: 1 | CF4: 2 | CG4: 3 | CH4: 4 | CI4: 5 | CJ4: 6 | CK4: 7 | CL4: 8 | CM4: 9 | CN4: 10 | CO4: 11 | CP4: 12 | CQ4: 13 | CR4: 14 | CS4: 15 | CT4: 16 | CU4: 17 | CV4: 18 | CW4: 19 | CX4: 20 | CY4: 21 | CZ4: 22 | DA4: 23 | DB4: 24 | DC4: 25 | DD4: 26 | DE4: 27 | DF4: 28 | DG4: 29 | DH4: 30 | DI4: 31
B5: 交渉 | C5: TOP面談
C6: LOIドラフト作成
C7: LOI提出
C8: LOI受領(独占交渉権)
B9: DD | C9: DDスコープ・依頼先選定
C10: IRL提出
C11: QAラリー
C12: マネジメントインタビュー | L12: B | AA12: F | AB12: L
C13: DD結果報告 | AX13: F | AY13: L
B14: 契約 | C14: SPA内容調整
C15: SPA締結
C16: CoC対応等
C17: クロージング
C18: 役員変更登記申請
B19: PMI | C19: 従業員・取引先開示
C20: 連帯保証解除等
C21: PMI・グループ連携 | DL21: 報酬発生

Sheet スケジュール(縦)
B2: ※本案件ではスケジュール(横)を使用。本シートは未使用。
A4: 2025年
A96: 2026年

Sheet グラフ
A1: ※テンプレートの作図用サンプルデータ。本案件では未使用。
C2: A | D2: B | E2: C | T2: A
B3: 第1四半期 | C3: 50 | D3: 10 | E3: 20 | S3: 第1四半期 | T3: 50
B4: 第2四半期 | C4: 55 | D4: 25 | E4: 22 | S4: 第2四半期 | T4: 55
B5: 第3四半期 | C5: 52 | D5: 45 | E5: 25 | S5: 第3四半期 | T5: 52
B6: 第4四半期 | C6: 50 | D6: 70 | E6: 25 | S6: 第4四半期 | T6: 80
AF16: ｂ
C18: A | D18: B | E18: C
B19: 1ヶ月目 | C19: 100 | D19: 100 | E19: 100 | T19: A
B20: 2ヶ月目 | C20: 105 | D20: 90 | E20: 110 | S20: 第1四半期 | T20: 50
B21: 3か月目 | C21: 110 | D21: 75 | E21: 90 | S21: 第2四半期 | T21: 55
B22: 4か月目 | C22: 115 | D22: 60 | E22: 80 | S22: 第3四半期 | T22: 52
B23: 5か月目 | C23: 120 | D23: 55 | E23: 45 | S23: 第4四半期 | T23: 80
C33: グラフタイトル
B34: A | C34: 60
B35: B | C35: 20
B36: C | C36: 15
B37: D | C37: 5
C51: X | D51: Y | E51: Z
B52: D | C52: 4.3 | D52: 2.4 | E52: 2
B53: C | C53: 2.5 | D53: 4.4 | E53: 2
B54: B | C54: 3.5 | D54: 1.8 | E54: 3
B55: A | C55: 4.5 | D55: 2.8 | E55: 5

Sheet 表
B2: ※作図用の予備シート（本案件では未使用）
